Workbook
Name SCEN: 'Scenario Selector'!$C$5
Name REFRESH_OUT: 'Scenario Selector'!$C$6

Sheet Instructions
B1: RIVR Tech Five-Year Financial Model — Instructions
B2: LREMC Technologies, LLC d/b/a RIVR Tech · FY2027–FY2031 · Prepared 2026-07-21
B4: How to use this model
B5: 1. Go to the 'Scenario Selector' tab and choose Base / Conservative / Aggressive from the drop-down.
B6: 2. Choose the refresh treatment: 'Inside $10M' (base model) or 'Outside $10M' (adjustable model, +$400K/yr).
B7: 3. Every downstream tab recomputes automatically from the Assumptions (CHOOSE-driven).
B8: 4. Edit any BLUE input cell. Do not overwrite black formula cells.
B10: Color legend
B11: BLUE fill = management input / assumption (editable)
B12: ORANGE fill = placeholder pending actual company data (editable)
B13: GREEN fill = key calculated output
B14: WHITE/grey = formula (do not edit directly)
... B38: Source-Data Inventory & Assumption Log accompanying this workbook.

Sheet Executive Dashboard
B1: Executive Dashboard — RIVR Tech Five-Year Plan
B2: Live view of the active scenario. Change scenario on 'Scenario Selector'. Charts refresh on recalculation.
B3: Active scenario: | C3: ='Scenario Selector'!C4
B5: 2031 Revenue | D5: 2031 EBITDA | F5: 2031 EBITDA margin
B6: ='Revenue Model'!G17 | D6: ='Income Statement'!G7 | F6: ='Income Statement'!G7/'Revenue Model'!G17
B8: 2031 Ending subs | D8: 5-Yr capital deployed | F8: Peak cumulative cash need
B9: ='Subscriber Forecast'!G49 | D9: ='Capital Plan'!J21 | F9: =MIN('Cash Flow'!C8:G8)
B11: 2031 Headcount | D11: 2031 Take rate | F11: 5-Yr revenue
B12: =Assumptions!I41 | D12: ='Subscriber Forecast'!G49/((Assumptions!E25+SUM(Assumptions!E27:I27))+(Assumptions!E26+SUM(Assumptions!E28:I28))) | F12: ='Revenue Model'!H17
B16: Chart data (live) | C16: 2027 | D16: 2028 | E16: 2029 | F16: 2030 | G16: 2031
B17: Total revenue | C17: ='Revenue Model'!C17 | D17: ='Revenue Model'!D17 | E17: ='Revenue Model'!E17 | F17: ='Revenue Model'!F17 | G17: ='Revenue Model'!G17
B18: EBITDA | C18: ='Income Statement'!C7 | D18: ='Income Statement'!D7 | E18: ='Income Statement'!E7 | F18: ='Income Statement'!F7 | G18: ='Income Statement'!G7
B19: Ending subscribers | C19: ='Subscriber Forecast'!C49 | D19: ='Subscriber Forecast'!D49 | E19: ='Subscriber Forecast'!E49 | F19: ='Subscriber Forecast'!F49 | G19: ='Subscriber Forecast'!G49
B20: Headcount | C20: =Assumptions!E41 | D20: =Assumptions!F41 | E20: =Assumptions!G41 | F20: =Assumptions!H41 | G20: =Assumptions!I41
B21: Capital deployed | C21: ='Capital Plan'!E24 | D21: ='Capital Plan'!F24 | E21: ='Capital Plan'!G24 | F21: ='Capital Plan'!H24 | G21: ='Capital Plan'!I24
B22: Operating cost / subscriber | C22: ='Operating Expenses'!E31/(('Subscriber Forecast'!C50+'Subscriber Forecast'!C49)/2) | D22: ='Operating Expenses'!F31/(('Subscriber Forecast'!D50+'Subscriber Forecast'!D49)/2) | E22: ='Operating Expenses'!G31/(('Subscriber Forecast'!E50+'Subscriber Forecast'!E49)/2) | F22: ='Operating Expenses'!H31/(('Subscriber Forecast'!F50+'Subscriber Forecast'!F49)/2) | G22: ='Operating Expenses'!I31/(('Subscriber Forecast'!G50+'Subscriber Forecast'!G49)/2)
B23: EBITDA margin | C23: ='Income Statement'!C7/'Revenue Model'!C17 | D23: ='Income Statement'!D7/'Revenue Model'!D17 | E23: ='Income Statement'!E7/'Revenue Model'!E17 | F23: ='Income Statement'!F7/'Revenue Model'!F17 | G23: ='Income Statement'!G7/'Revenue Model'!G17

Sheet Assumptions
B1: Model Assumptions — ACTIVE (selected scenario)
B2: Blue = management input (edit on Scenario Selector). These Active cells feed every downstream tab. Tags: A=Actual, S=Assumption, P=Placeholder, T=Target.
B4: Assumption | C4: Unit | D4: Tag | E4: 2027 | F4: 2028 | G4: 2029 | H4: 2030 | I4: 2031
B5: Residential opening subs (Jan-2027) | C5: subs | D5: S | E5: =CHOOSE(SCEN,'Scenario Selector'!D10,'Scenario Selector'!I10,'Scenario Selector'!N10) | F5: =CHOOSE(SCEN,'Scenario Selector'!D10,'Scenario Selector'!I10,'Scenario Selector'!N10) | G5: =CHOOSE(SCEN,'Scenario Selector'!D10,'Scenario Selector'!I10,'Scenario Selector'!N10) | H5: =CHOOSE(SCEN,'Scenario Selector'!D10,'Scenario Selector'!I10,'Scenario Selector'!N10) | I5: =CHOOSE(SCEN,'Scenario Selector'!D10,'Scenario Selector'!I10,'Scenario Selector'!N10)
B6: Business opening subs | C6: subs | D6: S | E6: =CHOOSE(SCEN,'Scenario Selector'!D11,'Scenario Selector'!I11,'Scenario Selector'!N11) | F6: =CHOOSE(SCEN,'Scenario Selector'!D11,'Scenario Selector'!I11,'Scenario Selector'!N11) | G6: =CHOOSE(SCEN,'Scenario Selector'!D11,'Scenario Selector'!I11,'Scenario Selector'!N11) | H6: =CHOOSE(SCEN,'Scenario Selector'!D11,'Scenario Selector'!I11,'Scenario Selector'!N11) | I6: =CHOOSE(SCEN,'Scenario Selector'!D11,'Scenario Selector'!I11,'Scenario Selector'!N11)
B7: Enterprise/DIA opening subs | C7: subs | D7: S | E7: =CHOOSE(SCEN,'Scenario Selector'!D12,'Scenario Selector'!I12,'Scenario Selector'!N12) | F7: =CHOOSE(SCEN,'Scenario Selector'!D12,'Scenario Selector'!I12,'Scenario Selector'!N12) | G7: =CHOOSE(SCEN,'Scenario Selector'!D12,'Scenario Selector'!I12,'Scenario Selector'!N12) | H7: =CHOOSE(SCEN,'Scenario Selector'!D12,'Scenario Selector'!I12,'Scenario Selector'!N12) | I7: =CHOOSE(SCEN,'Scenario Selector'!D12,'Scenario Selector'!I12,'Scenario Selector'!N12)
B8: Voice opening subs | C8: subs | D8: S | E8: =CHOOSE(SCEN,'Scenario Selector'!D13,'Scenario Selector'!I13,'Scenario Selector'!N13) | F8: =CHOOSE(SCEN,'Scenario Selector'!D13,'Scenario Selector'!I13,'Scenario Selector'!N13) | G8: =CHOOSE(SCEN,'Scenario Selector'!D13,'Scenario Selector'!I13,'Scenario Selector'!N13) | H8: =CHOOSE(SCEN,'Scenario Selector'!D13,'Scenario Selector'!I13,'Scenario Selector'!N13) | I8: =CHOOSE(SCEN,'Scenario Selector'!D13,'Scenario Selector'!I13,'Scenario Selector'!N13)
B9: Residential gross adds | C9: subs/yr | D9: S | E9: =CHOOSE(SCEN,'Scenario Selector'!D14,'Scenario Selector'!I14,'Scenario Selector'!N14) | F9: =CHOOSE(SCEN,'Scenario Selector'!E14,'Scenario Selector'!J14,'Scenario Selector'!O14) | G9: =CHOOSE(SCEN,'Scenario Selector'!F14,'Scenario Selector'!K14,'Scenario Selector'!P14) | H9: =CHOOSE(SCEN,'Scenario Selector'!G14,'Scenario Selector'!L14,'Scenario Selector'!Q14) | I9: =CHOOSE(SCEN,'Scenario Selector'!H14,'Scenario Selector'!M14,'Scenario Selector'!R14)
B10: Business gross adds | C10: subs/yr | D10: S | E10: =CHOOSE(SCEN,'Scenario Selector'!D15,'Scenario Selector'!I15,'Scenario Selector'!N15) | F10: =CHOOSE(SCEN,'Scenario Selector'!E15,'Scenario Selector'!J15,'Scenario Selector'!O15) | G10: =CHOOSE(SCEN,'Scenario Selector'!F15,'Scenario Selector'!K15,'Scenario Selector'!P15) | H10: =CHOOSE(SCEN,'Scenario Selector'!G15,'Scenario Selector'!L15,'Scenario Selector'!Q15) | I10: =CHOOSE(SCEN,'Scenario Selector'!H15,'Scenario Selector'!M15,'Scenario Selector'!R15)
B11: Enterprise gross adds | C11: subs/yr | D11: S | E11: =CHOOSE(SCEN,'Scenario Selector'!D16,'Scenario Selector'!I16,'Scenario Selector'!N16) | F11: =CHOOSE(SCEN,'Scenario Selector'!E16,'Scenario Selector'!J16,'Scenario Selector'!O16) | G11: =CHOOSE(SCEN,'Scenario Selector'!F16,'Scenario Selector'!K16,'Scenario Selector'!P16) | H11: =CHOOSE(SCEN,'Scenario Selector'!G16,'Scenario Selector'!L16,'Scenario Selector'!Q16) | I11: =CHOOSE(SCEN,'Scenario Selector'!H16,'Scenario Selector'!M16,'Scenario Selector'!R16)
B12: Voice gross adds | C12: subs/yr | D12: S | E12: =CHOOSE(SCEN,'Scenario Selector'!D17,'Scenario Selector'!I17,'Scenario Selector'!N17) | F12: =CHOOSE(SCEN,'Scenario Selector'!E17,'Scenario Selector'!J17,'Scenario Selector'!O17) | G12: =CHOOSE(SCEN,'Scenario Selector'!F17,'Scenario Selector'!K17,'Scenario Selector'!P17) | H12: =CHOOSE(SCEN,'Scenario Selector'!G17,'Scenario Selector'!L17,'Scenario Selector'!Q17) | I12: =CHOOSE(SCEN,'Scenario Selector'!H17,'Scenario Selector'!M17,'Scenario Selector'!R17)
B13: Residential churn (annual) | C13: % | D13: S | E13: =CHOOSE(SCEN,'Scenario Selector'!D18,'Scenario Selector'!I18,'Scenario Selector'!N18) | F13: =CHOOSE(SCEN,'Scenario Selector'!D18,'Scenario Selector'!I18,'Scenario Selector'!N18) | G13: =CHOOSE(SCEN,'Scenario Selector'!D18,'Scenario Selector'!I18,'Scenario Selector'!N18) | H13: =CHOOSE(SCEN,'Scenario Selector'!D18,'Scenario Selector'!I18,'Scenario Selector'!N18) | I13: =CHOOSE(SCEN,'Scenario Selector'!D18,'Scenario Selector'!I18,'Scenario Selector'!N18)
B14: Business churn (annual) | C14: % | D14: S | E14: =CHOOSE(SCEN,'Scenario Selector'!D19,'Scenario Selector'!I19,'Scenario Selector'!N19) | F14: =CHOOSE(SCEN,'Scenario Selector'!D19,'Scenario Selector'!I19,'Scenario Selector'!N19) | G14: =CHOOSE(SCEN,'Scenario Selector'!D19,'Scenario Selector'!I19,'Scenario Selector'!N19) | H14: =CHOOSE(SCEN,'Scenario Selector'!D19,'Scenario Selector'!I19,'Scenario Selector'!N19) | I14: =CHOOSE(SCEN,'Scenario Selector'!D19,'Scenario Selector'!I19,'Scenario Selector'!N19)
B15: Enterprise churn (annual) | C15: % | D15: S | E15: =CHOOSE(SCEN,'Scenario Selector'!D20,'Scenario Selector'!I20,'Scenario Selector'!N20) | F15: =CHOOSE(SCEN,'Scenario Selector'!D20,'Scenario Selector'!I20,'Scenario Selector'!N20) | G15: =CHOOSE(SCEN,'Scenario Selector'!D20,'Scenario Selector'!I20,'Scenario Selector'!N20) | H15: =CHOOSE(SCEN,'Scenario Selector'!D20,'Scenario Selector'!I20,'Scenario Selector'!N20) | I15: =CHOOSE(SCEN,'Scenario Selector'!D20,'Scenario Selector'!I20,'Scenario Selector'!N20)
B16: Voice churn (annual) | C16: % | D16: S | E16: =CHOOSE(SCEN,'Scenario Selector'!D21,'Scenario Selector'!I21,'Scenario Selector'!N21) | F16: =CHOOSE(SCEN,'Scenario Selector'!D21,'Scenario Selector'!I21,'Scenario Selector'!N21) | G16: =CHOOSE(SCEN,'Scenario Selector'!D21,'Scenario Selector'!I21,'Scenario Selector'!N21) | H16: =CHOOSE(SCEN,'Scenario Selector'!D21,'Scenario Selector'!I21,'Scenario Selector'!N21) | I16: =CHOOSE(SCEN,'Scenario Selector'!D21,'Scenario Selector'!I21,'Scenario Selector'!N21)
B17: Residential ARPU (start) | C17: $/mo | D17: A | E17: =CHOOSE(SCEN,'Scenario Selector'!D22,'Scenario Selector'!I22,'Scenario Selector'!N22) | F17: =CHOOSE(SCEN,'Scenario Selector'!D22,'Scenario Selector'!I22,'Scenario Selector'!N22) | G17: =CHOOSE(SCEN,'Scenario Selector'!D22,'Scenario Selector'!I22,'Scenario Selector'!N22) | H17: =CHOOSE(SCEN,'Scenario Selector'!D22,'Scenario Selector'!I22,'Scenario Selector'!N22) | I17: =CHOOSE(SCEN,'Scenario Selector'!D22,'Scenario Selector'!I22,'Scenario Selector'!N22)
B18: Residential ARPU growth | C18: % | D18: S | E18: =CHOOSE(SCEN,'Scenario Selector'!D23,'Scenario Selector'!I23,'Scenario Selector'!N23) | F18: =CHOOSE(SCEN,'Scenario Selector'!D23,'Scenario Selector'!I23,'Scenario Selector'!N23) | G18: =CHOOSE(SCEN,'Scenario Selector'!D23,'Scenario Selector'!I23,'Scenario Selector'!N23) | H18: =CHOOSE(SCEN,'Scenario Selector'!D23,'Scenario Selector'!I23,'Scenario Selector'!N23) | I18: =CHOOSE(SCEN,'Scenario Selector'!D23,'Scenario Selector'!I23,'Scenario Selector'!N23)
B19: Business ARPU (start) | C19: $/mo | D19: A | E19: =CHOOSE(SCEN,'Scenario Selector'!D24,'Scenario Selector'!I24,'Scenario Selector'!N24) | F19: =CHOOSE(SCEN,'Scenario Selector'!D24,'Scenario Selector'!I24,'Scenario Selector'!N24) | G19: =CHOOSE(SCEN,'Scenario Selector'!D24,'Scenario Selector'!I24,'Scenario Selector'!N24) | H19: =CHOOSE(SCEN,'Scenario Selector'!D24,'Scenario Selector'!I24,'Scenario Selector'!N24) | I19: =CHOOSE(SCEN,'Scenario Selector'!D24,'Scenario Selector'!I24,'Scenario Selector'!N24)
B20: Business ARPU growth | C20: % | D20: S | E20: =CHOOSE(SCEN,'Scenario Selector'!D25,'Scenario Selector'!I25,'Scenario Selector'!N25) | F20: =CHOOSE(SCEN,'Scenario Selector'!D25,'Scenario Selector'!I25,'Scenario Selector'!N25) | G20: =CHOOSE(SCEN,'Scenario Selector'!D25,'Scenario Selector'!I25,'Scenario Selector'!N25) | H20: =CHOOSE(SCEN,'Scenario Selector'!D25,'Scenario Selector'!I25,'Scenario Selector'!N25) | I20: =CHOOSE(SCEN,'Scenario Selector'!D25,'Scenario Selector'!I25,'Scenario Selector'!N25)
B21: Enterprise ARPU (start) | C21: $/mo | D21: P | E21: =CHOOSE(SCEN,'Scenario Selector'!D26,'Scenario Selector'!I26,'Scenario Selector'!N26) | F21: =CHOOSE(SCEN,'Scenario Selector'!D26,'Scenario Selector'!I26,'Scenario Selector'!N26) | G21: =CHOOSE(SCEN,'Scenario Selector'!D26,'Scenario Selector'!I26,'Scenario Selector'!N26) | H21: =CHOOSE(SCEN,'Scenario Selector'!D26,'Scenario Selector'!I26,'Scenario Selector'!N26) | I21: =CHOOSE(SCEN,'Scenario Selector'!D26,'Scenario Selector'!I26,'Scenario Selector'!N26)
B22: Enterprise ARPU growth | C22: % | D22: S | E22: =CHOOSE(SCEN,'Scenario Selector'!D27,'Scenario Selector'!I27,'Scenario Selector'!N27) | F22: =CHOOSE(SCEN,'Scenario Selector'!D27,'Scenario Selector'!I27,'Scenario Selector'!N27) | G22: =CHOOSE(SCEN,'Scenario Selector'!D27,'Scenario Selector'!I27,'Scenario Selector'!N27) | H22: =CHOOSE(SCEN,'Scenario Selector'!D27,'Scenario Selector'!I27,'Scenario Selector'!N27) | I22: =CHOOSE(SCEN,'Scenario Selector'!D27,'Scenario Selector'!I27,'Scenario Selector'!N27)
B23: Voice ARPU (start) | C23: $/mo | D23: P | E23: =CHOOSE(SCEN,'Scenario Selector'!D28,'Scenario Selector'!I28,'Scenario Selector'!N28) | F23: =CHOOSE(SCEN,'Scenario Selector'!D28,'Scenario Selector'!I28,'Scenario Selector'!N28) | G23: =CHOOSE(SCEN,'Scenario Selector'!D28,'Scenario Selector'!I28,'Scenario Selector'!N28) | H23: =CHOOSE(SCEN,'Scenario Selector'!D28,'Scenario Selector'!I28,'Scenario Selector'!N28) | I23: =CHOOSE(SCEN,'Scenario Selector'!D28,'Scenario Selector'!I28,'Scenario Selector'!N28)
B24: Voice ARPU growth | C24: % | D24: S | E24: =CHOOSE(SCEN,'Scenario Selector'!D29,'Scenario Selector'!I29,'Scenario Selector'!N29) | F24: =CHOOSE(SCEN,'Scenario Selector'!D29,'Scenario Selector'!I29,'Scenario Selector'!N29) | G24: =CHOOSE(SCEN,'Scenario Selector'!D29,'Scenario Selector'!I29,'Scenario Selector'!N29) | H24: =CHOOSE(SCEN,'Scenario Selector'!D29,'Scenario Selector'!I29,'Scenario Selector'!N29) | I24: =CHOOSE(SCEN,'Scenario Selector'!D29,'Scenario Selector'!I29,'Scenario Selector'!N29)
... B26: Business passings (opening) | C26: BP | D26: P | E26: =CHOOSE(SCEN,'Scenario Selector'!D31,'Scenario Selector'!I31,'Scenario Selector'!N31) | F26: =CHOOSE(SCEN,'Scenario Selector'!D31,'Scenario Selector'!I31,'Scenario Selector'!N31) | G26: =CHOOSE(SCEN,'Scenario Selector'!D31,'Scenario Selector'!I31,'Scenario Selector'!N31) | H26: =CHOOSE(SCEN,'Scenario Selector'!D31,'Scenario Selector'!I31,'Scenario Selector'!N31) | I26: =CHOOSE(SCEN,'Scenario Selector'!D31,'Scenario Selector'!I31,'Scenario Selector'!N31)
B27: New residential passings | C27: HP/yr | D27: P | E27: =CHOOSE(SCEN,'Scenario Selector'!D32,'Scenario Selector'!I32,'Scenario Selector'!N32) | F27: =CHOOSE(SCEN,'Scenario Selector'!E32,'Scenario Selector'!J32,'Scenario Selector'!O32) | G27: =CHOOSE(SCEN,'Scenario Selector'!F32,'Scenario Selector'!K32,'Scenario Selector'!P32) | H27: =CHOOSE(SCEN,'Scenario Selector'!G32,'Scenario Selector'!L32,'Scenario Selector'!Q32) | I27: =CHOOSE(SCEN,'Scenario Selector'!H32,'Scenario Selector'!M32,'Scenario Selector'!R32)
B28: New business passings | C28: BP/yr | D28: P | E28: =CHOOSE(SCEN,'Scenario Selector'!D33,'Scenario Selector'!I33,'Scenario Selector'!N33) | F28: =CHOOSE(SCEN,'Scenario Selector'!E33,'Scenario Selector'!J33,'Scenario Selector'!O33) | G28: =CHOOSE(SCEN,'Scenario Selector'!F33,'Scenario Selector'!K33,'Scenario Selector'!P33) | H28: =CHOOSE(SCEN,'Scenario Selector'!G33,'Scenario Selector'!L33,'Scenario Selector'!Q33) | I28: =CHOOSE(SCEN,'Scenario Selector'!H33,'Scenario Selector'!M33,'Scenario Selector'!R33)
B29: Capital deployment fraction | C29: % | D29: S | E29: =CHOOSE(SCEN,'Scenario Selector'!D34,'Scenario Selector'!I34,'Scenario Selector'!N34) | F29: =CHOOSE(SCEN,'Scenario Selector'!E34,'Scenario Selector'!J34,'Scenario Selector'!O34) | G29: =CHOOSE(SCEN,'Scenario Selector'!F34,'Scenario Selector'!K34,'Scenario Selector'!P34) | H29: =CHOOSE(SCEN,'Scenario Selector'!G34,'Scenario Selector'!L34,'Scenario Selector'!Q34) | I29: =CHOOSE(SCEN,'Scenario Selector'!H34,'Scenario Selector'!M34,'Scenario Selector'!R34)
B30: Construction cost / passing | C30: $ | D30: P | E30: =CHOOSE(SCEN,'Scenario Selector'!D35,'Scenario Selector'!I35,'Scenario Selector'!N35) | F30: =CHOOSE(SCEN,'Scenario Selector'!D35,'Scenario Selector'!I35,'Scenario Selector'!N35) | G30: =CHOOSE(SCEN,'Scenario Selector'!D35,'Scenario Selector'!I35,'Scenario Selector'!N35) | H30: =CHOOSE(SCEN,'Scenario Selector'!D35,'Scenario Selector'!I35,'Scenario Selector'!N35) | I30: =CHOOSE(SCEN,'Scenario Selector'!D35,'Scenario Selector'!I35,'Scenario Selector'!N35)
B31: Marketing per gross add | C31: $ | D31: S | E31: =CHOOSE(SCEN,'Scenario Selector'!D36,'Scenario Selector'!I36,'Scenario Selector'!N36) | F31: =CHOOSE(SCEN,'Scenario Selector'!D36,'Scenario Selector'!I36,'Scenario Selector'!N36) | G31: =CHOOSE(SCEN,'Scenario Selector'!D36,'Scenario Selector'!I36,'Scenario Selector'!N36) | H31: =CHOOSE(SCEN,'Scenario Selector'!D36,'Scenario Selector'!I36,'Scenario Selector'!N36) | I31: =CHOOSE(SCEN,'Scenario Selector'!D36,'Scenario Selector'!I36,'Scenario Selector'!N36)
B32: OpEx inflation | C32: % | D32: S | E32: =CHOOSE(SCEN,'Scenario Selector'!D37,'Scenario Selector'!I37,'Scenario Selector'!N37) | F32: =CHOOSE(SCEN,'Scenario Selector'!D37,'Scenario Selector'!I37,'Scenario Selector'!N37) | G32: =CHOOSE(SCEN,'Scenario Selector'!D37,'Scenario Selector'!I37,'Scenario Selector'!N37) | H32: =CHOOSE(SCEN,'Scenario Selector'!D37,'Scenario Selector'!I37,'Scenario Selector'!N37) | I32: =CHOOSE(SCEN,'Scenario Selector'!D37,'Scenario Selector'!I37,'Scenario Selector'!N37)
B33: OpEx efficiency multiplier | C33: x | D33: S | E33: =CHOOSE(SCEN,'Scenario Selector'!D38,'Scenario Selector'!I38,'Scenario Selector'!N38) | F33: =CHOOSE(SCEN,'Scenario Selector'!D38,'Scenario Selector'!I38,'Scenario Selector'!N38) | G33: =CHOOSE(SCEN,'Scenario Selector'!D38,'Scenario Selector'!I38,'Scenario Selector'!N38) | H33: =CHOOSE(SCEN,'Scenario Selector'!D38,'Scenario Selector'!I38,'Scenario Selector'!N38) | I33: =CHOOSE(SCEN,'Scenario Selector'!D38,'Scenario Selector'!I38,'Scenario Selector'!N38)
B34: Managed Wi-Fi attach | C34: % | D34: S | E34: =CHOOSE(SCEN,'Scenario Selector'!D39,'Scenario Selector'!I39,'Scenario Selector'!N39) | F34: =CHOOSE(SCEN,'Scenario Selector'!D39,'Scenario Selector'!I39,'Scenario Selector'!N39) | G34: =CHOOSE(SCEN,'Scenario Selector'!D39,'Scenario Selector'!I39,'Scenario Selector'!N39) | H34: =CHOOSE(SCEN,'Scenario Selector'!D39,'Scenario Selector'!I39,'Scenario Selector'!N39) | I34: =CHOOSE(SCEN,'Scenario Selector'!D39,'Scenario Selector'!I39,'Scenario Selector'!N39)
B35: Managed Wi-Fi price | C35: $/mo | D35: P | E35: =CHOOSE(SCEN,'Scenario Selector'!D40,'Scenario Selector'!I40,'Scenario Selector'!N40) | F35: =CHOOSE(SCEN,'Scenario Selector'!D40,'Scenario Selector'!I40,'Scenario Selector'!N40) | G35: =CHOOSE(SCEN,'Scenario Selector'!D40,'Scenario Selector'!I40,'Scenario Selector'!N40) | H35: =CHOOSE(SCEN,'Scenario Selector'!D40,'Scenario Selector'!I40,'Scenario Selector'!N40) | I35: =CHOOSE(SCEN,'Scenario Selector'!D40,'Scenario Selector'!I40,'Scenario Selector'!N40)
B36: Static IP attach (biz) | C36: % | D36: S | E36: =CHOOSE(SCEN,'Scenario Selector'!D41,'Scenario Selector'!I41,'Scenario Selector'!N41) | F36: =CHOOSE(SCEN,'Scenario Selector'!D41,'Scenario Selector'!I41,'Scenario Selector'!N41) | G36: =CHOOSE(SCEN,'Scenario Selector'!D41,'Scenario Selector'!I41,'Scenario Selector'!N41) | H36: =CHOOSE(SCEN,'Scenario Selector'!D41,'Scenario Selector'!I41,'Scenario Selector'!N41) | I36: =CHOOSE(SCEN,'Scenario Selector'!D41,'Scenario Selector'!I41,'Scenario Selector'!N41)
B37: Static IP price | C37: $/mo | D37: P | E37: =CHOOSE(SCEN,'Scenario Selector'!D42,'Scenario Selector'!I42,'Scenario Selector'!N42) | F37: =CHOOSE(SCEN,'Scenario Selector'!D42,'Scenario Selector'!I42,'Scenario Selector'!N42) | G37: =CHOOSE(SCEN,'Scenario Selector'!D42,'Scenario Selector'!I42,'Scenario Selector'!N42) | H37: =CHOOSE(SCEN,'Scenario Selector'!D42,'Scenario Selector'!I42,'Scenario Selector'!N42) | I37: =CHOOSE(SCEN,'Scenario Selector'!D42,'Scenario Selector'!I42,'Scenario Selector'!N42)
B38: Residential install fee | C38: $ | D38: S | E38: =CHOOSE(SCEN,'Scenario Selector'!D43,'Scenario Selector'!I43,'Scenario Selector'!N43) | F38: =CHOOSE(SCEN,'Scenario Selector'!D43,'Scenario Selector'!I43,'Scenario Selector'!N43) | G38: =CHOOSE(SCEN,'Scenario Selector'!D43,'Scenario Selector'!I43,'Scenario Selector'!N43) | H38: =CHOOSE(SCEN,'Scenario Selector'!D43,'Scenario Selector'!I43,'Scenario Selector'!N43) | I38: =CHOOSE(SCEN,'Scenario Selector'!D43,'Scenario Selector'!I43,'Scenario Selector'!N43)
B39: Business install fee | C39: $ | D39: S | E39: =CHOOSE(SCEN,'Scenario Selector'!D44,'Scenario Selector'!I44,'Scenario Selector'!N44) | F39: =CHOOSE(SCEN,'Scenario Selector'!D44,'Scenario Selector'!I44,'Scenario Selector'!N44) | G39: =CHOOSE(SCEN,'Scenario Selector'!D44,'Scenario Selector'!I44,'Scenario Selector'!N44) | H39: =CHOOSE(SCEN,'Scenario Selector'!D44,'Scenario Selector'!I44,'Scenario Selector'!N44) | I39: =CHOOSE(SCEN,'Scenario Selector'!D44,'Scenario Selector'!I44,'Scenario Selector'!N44)
B40: Enterprise install fee | C40: $ | D40: P | E40: =CHOOSE(SCEN,'Scenario Selector'!D45,'Scenario Selector'!I45,'Scenario Selector'!N45) | F40: =CHOOSE(SCEN,'Scenario Selector'!D45,'Scenario Selector'!I45,'Scenario Selector'!N45) | G40: =CHOOSE(SCEN,'Scenario Selector'!D45,'Scenario Selector'!I45,'Scenario Selector'!N45) | H40: =CHOOSE(SCEN,'Scenario Selector'!D45,'Scenario Selector'!I45,'Scenario Selector'!N45) | I40: =CHOOSE(SCEN,'Scenario Selector'!D45,'Scenario Selector'!I45,'Scenario Selector'!N45)
B41: Total headcount (EOY) | C41: FTE | D41: T | E41: =CHOOSE(SCEN,'Scenario Selector'!D46,'Scenario Selector'!I46,'Scenario Selector'!N46) | F41: =CHOOSE(SCEN,'Scenario Selector'!E46,'Scenario Selector'!J46,'Scenario Selector'!O46) | G41: =CHOOSE(SCEN,'Scenario Selector'!F46,'Scenario Selector'!K46,'Scenario Selector'!P46) | H41: =CHOOSE(SCEN,'Scenario Selector'!G46,'Scenario Selector'!L46,'Scenario Selector'!Q46) | I41: =CHOOSE(SCEN,'Scenario Selector'!H46,'Scenario Selector'!M46,'Scenario Selector'!R46)

Sheet Scenario Selector
B1: Scenario Selector & Driver Library
B2: Pick the active scenario. All model tabs recompute from the Active column via CHOOSE().
B4: ACTIVE SCENARIO → | C4: Base
B5: Scenario index (1=Base 2=Cons 3=Aggr) | C5: =MATCH(C4,{"Base","Conservative","Aggressive"},0)
B6: Refresh treatment | C6: Inside $10M | E6: Base model = Inside. Adjustable model = Outside (+$400K/yr).
B9: Driver | C9: Unit | D9: Base Y1 | E9: Base Y2 | F9: Base Y3 | G9: Base Y4 | H9: Base Y5 | I9: Con Y1 | J9: Con Y2 | K9: Con Y3 | L9: Con Y4 | M9: Con Y5 | N9: Agg Y1 | O9: Agg Y2 | P9: Agg Y3 | Q9: Agg Y4 | R9: Agg Y5
B10: Residential opening subs (Jan-2027) | C10: subs | D10: 4450 | E10: 4450 | F10: 4450 | G10: 4450 | H10: 4450 | I10: 4450 | J10: 4450 | K10: 4450 | L10: 4450 | M10: 4450 | N10: 4450 | O10: 4450 | P10: 4450 | Q10: 4450 | R10: 4450
B11: Business opening subs | C11: subs | D11: 360 | E11: 360 | F11: 360 | G11: 360 | H11: 360 | I11: 360 | J11: 360 | K11: 360 | L11: 360 | M11: 360 | N11: 360 | O11: 360 | P11: 360 | Q11: 360 | R11: 360
B12: Enterprise/DIA opening subs | C12: subs | D12: 13 | E12: 13 | F12: 13 | G12: 13 | H12: 13 | I12: 13 | J12: 13 | K12: 13 | L12: 13 | M12: 13 | N12: 13 | O12: 13 | P12: 13 | Q12: 13 | R12: 13
B13: Voice opening subs | C13: subs | D13: 512 | E13: 512 | F13: 512 | G13: 512 | H13: 512 | I13: 512 | J13: 512 | K13: 512 | L13: 512 | M13: 512 | N13: 512 | O13: 512 | P13: 512 | Q13: 512 | R13: 512
B14: Residential gross adds | C14: subs/yr | D14: 1800 | E14: 2050 | F14: 2150 | G14: 2050 | H14: 1900 | I14: 1350 | J14: 1500 | K14: 1600 | L14: 1550 | M14: 1450 | N14: 2300 | O14: 2700 | P14: 2850 | Q14: 2750 | R14: 2550
B15: Business gross adds | C15: subs/yr | D15: 135 | E15: 160 | F15: 175 | G15: 175 | H15: 165 | I15: 100 | J15: 115 | K15: 125 | L15: 125 | M15: 120 | N15: 175 | O15: 205 | P15: 225 | Q15: 230 | R15: 215
B16: Enterprise gross adds | C16: subs/yr | D16: 6 | E16: 8 | F16: 9 | G16: 9 | H16: 8 | I16: 4 | J16: 5 | K16: 6 | L16: 6 | M16: 6 | N16: 8 | O16: 11 | P16: 12 | Q16: 13 | R16: 12
B17: Voice gross adds | C17: subs/yr | D17: 120 | E17: 130 | F17: 130 | G17: 120 | H17: 110 | I17: 95 | J17: 100 | K17: 100 | L17: 95 | M17: 85 | N17: 140 | O17: 150 | P17: 150 | Q17: 140 | R17: 130
B18: Residential churn (annual) | C18: % | D18: 0.11 | E18: 0.11 | F18: 0.11 | G18: 0.11 | H18: 0.11 | I18: 0.14 | J18: 0.14 | K18: 0.14 | L18: 0.14 | M18: 0.14 | N18: 0.09 | O18: 0.09 | P18: 0.09 | Q18: 0.09 | R18: 0.09
B19: Business churn (annual) | C19: % | D19: 0.08 | E19: 0.08 | F19: 0.08 | G19: 0.08 | H19: 0.08 | I19: 0.1 | J19: 0.1 | K19: 0.1 | L19: 0.1 | M19: 0.1 | N19: 0.065 | O19: 0.065 | P19: 0.065 | Q19: 0.065 | R19: 0.065
B20: Enterprise churn (annual) | C20: % | D20: 0.05 | E20: 0.05 | F20: 0.05 | G20: 0.05 | H20: 0.05 | I20: 0.07 | J20: 0.07 | K20: 0.07 | L20: 0.07 | M20: 0.07 | N20: 0.04 | O20: 0.04 | P20: 0.04 | Q20: 0.04 | R20: 0.04
B21: Voice churn (annual) | C21: % | D21: 0.14 | E21: 0.14 | F21: 0.14 | G21: 0.14 | H21: 0.14 | I21: 0.17 | J21: 0.17 | K21: 0.17 | L21: 0.17 | M21: 0.17 | N21: 0.12 | O21: 0.12 | P21: 0.12 | Q21: 0.12 | R21: 0.12
... B46: Total headcount (EOY) | C46: FTE | D46: 21 | E46: 26 | F46: 31 | G46: 35 | H46: 39 | I46: 20 | J46: 23 | K46: 27 | L46: 30 | M46: 33 | N46: 23 | O46: 29 | P46: 35 | Q46: 40 | R46: 45

Sheet Subscriber Forecast
B1: Subscriber Forecast — Roll-Forward
B2: Beg + Gross Adds − Disconnects = End. Year-1 monthly reconciles to the annual column. Green = ending balances.
B4: YEAR 1 — MONTHLY DETAIL (FY2027)
B5: Metric | D5: Jan | E5: Feb | F5: Mar | G5: Apr | H5: May | I5: Jun | J5: Jul | K5: Aug | L5: Sep | M5: Oct | N5: Nov | O5: Dec | P5: FY2027
B6: Residential
B7: Beginning subs | D7: =Assumptions!E5 | E7: =D10 | F7: =E10 | G7: =F10 | H7: =G10 | I7: =H10 | J7: =I10 | K7: =J10 | L7: =K10 | ... O7: =N10 | P7: =D7
B8: Gross adds | D8: =ROUND(Assumptions!E9*0.07000,0) | E8: =ROUND(Assumptions!E9*0.07200,0) | F8: =ROUND(Assumptions!E9*0.07800,0) | G8: =ROUND(Assumptions!E9*0.08500,0) | H8: =ROUND(Assumptions!E9*0.09000,0) | I8: =ROUND(Assumptions!E9*0.09200,0) | J8: =ROUND(Assumptions!E9*0.09200,0) | K8: =ROUND(Assumptions!E9*0.09000,0) | L8: =ROUND(Assumptions!E9*0.08600,0) | M8: =ROUND(Assumptions!E9*0.08300,0) | N8: =ROUND(Assumptions!E9*0.08200,0) | O8: =Assumptions!E9-(D8+E8+F8+G8+H8+I8+J8+K8+L8+M8+N8) | P8: =SUM(D8:O8)
B9: Disconnects (churn) | D9: =ROUND(D7*Assumptions!E13/12,0) | E9: =ROUND(E7*Assumptions!E13/12,0) | F9: =ROUND(F7*Assumptions!E13/12,0) | G9: =ROUND(G7*Assumptions!E13/12,0) | H9: =ROUND(H7*Assumptions!E13/12,0) | I9: =ROUND(I7*Assumptions!E13/12,0) | J9: =ROUND(J7*Assumptions!E13/12,0) | K9: =ROUND(K7*Assumptions!E13/12,0) | L9: =ROUND(L7*Assumptions!E13/12,0) | M9: =ROUND(M7*Assumptions!E13/12,0) | N9: =ROUND(N7*Assumptions!E13/12,0) | O9: =ROUND(O7*Assumptions!E13/12,0) | P9: =SUM(D9:O9)
B10: Ending subs | D10: =D7+D8-D9 | E10: =E7+E8-E9 | F10: =F7+F8-F9 | G10: =G7+G8-G9 | H10: =H7+H8-H9 | I10: =I7+I8-I9 | J10: =J7+J8-J9 | K10: =K7+K8-K9 | ... O10: =O7+O8-O9 | P10: =O10
B11: Business
B12: Beginning subs | D12: =Assumptions!E6 | E12: =D15 | F12: =E15 | G12: =F15 | H12: =G15 | I12: =H15 | J12: =I15 | K12: =J15 | L12: =K15 | ... O12: =N15 | P12: =D12
B13: Gross adds | D13: =ROUND(Assumptions!E10*0.07000,0) | E13: =ROUND(Assumptions!E10*0.07200,0) | F13: =ROUND(Assumptions!E10*0.07800,0) | G13: =ROUND(Assumptions!E10*0.08500,0) | H13: =ROUND(Assumptions!E10*0.09000,0) | I13: =ROUND(Assumptions!E10*0.09200,0) | J13: =ROUND(Assumptions!E10*0.09200,0) | K13: =ROUND(Assumptions!E10*0.09000,0) | L13: =ROUND(Assumptions!E10*0.08600,0) | M13: =ROUND(Assumptions!E10*0.08300,0) | N13: =ROUND(Assumptions!E10*0.08200,0) | O13: =Assumptions!E10-(D13+E13+F13+G13+H13+I13+J13+K13+L13+M13+N13) | P13: =SUM(D13:O13)
B14: Disconnects (churn) | D14: =ROUND(D12*Assumptions!E14/12,0) | E14: =ROUND(E12*Assumptions!E14/12,0) | F14: =ROUND(F12*Assumptions!E14/12,0) | G14: =ROUND(G12*Assumptions!E14/12,0) | H14: =ROUND(H12*Assumptions!E14/12,0) | I14: =ROUND(I12*Assumptions!E14/12,0) | J14: =ROUND(J12*Assumptions!E14/12,0) | K14: =ROUND(K12*Assumptions!E14/12,0) | L14: =ROUND(L12*Assumptions!E14/12,0) | M14: =ROUND(M12*Assumptions!E14/12,0) | N14: =ROUND(N12*Assumptions!E14/12,0) | O14: =ROUND(O12*Assumptions!E14/12,0) | P14: =SUM(D14:O14)
B15: Ending subs | D15: =D12+D13-D14 | E15: =E12+E13-E14 | F15: =F12+F13-F14 | G15: =G12+G13-G14 | H15: =H12+H13-H14 | I15: =I12+I13-I14 | J15: =J12+J13-J14 | K15: =K12+K13-K14 | ... O15: =O12+O13-O14 | P15: =O15
B16: Enterprise / DIA
B17: Beginning subs | D17: =Assumptions!E7 | E17: =D20 | F17: =E20 | G17: =F20 | H17: =G20 | I17: =H20 | J17: =I20 | K17: =J20 | L17: =K20 | ... O17: =N20 | P17: =D17
B18: Gross adds | D18: =ROUND(Assumptions!E11*0.07000,0) | E18: =ROUND(Assumptions!E11*0.07200,0) | F18: =ROUND(Assumptions!E11*0.07800,0) | G18: =ROUND(Assumptions!E11*0.08500,0) | H18: =ROUND(Assumptions!E11*0.09000,0) | I18: =ROUND(Assumptions!E11*0.09200,0) | J18: =ROUND(Assumptions!E11*0.09200,0) | K18: =ROUND(Assumptions!E11*0.09000,0) | L18: =ROUND(Assumptions!E11*0.08600,0) | M18: =ROUND(Assumptions!E11*0.08300,0) | N18: =ROUND(Assumptions!E11*0.08200,0) | O18: =Assumptions!E11-(D18+E18+F18+G18+H18+I18+J18+K18+L18+M18+N18) | P18: =SUM(D18:O18)
B19: Disconnects (churn) | D19: =ROUND(D17*Assumptions!E15/12,0) | E19: =ROUND(E17*Assumptions!E15/12,0) | F19: =ROUND(F17*Assumptions!E15/12,0) | G19: =ROUND(G17*Assumptions!E15/12,0) | H19: =ROUND(H17*Assumptions!E15/12,0) | I19: =ROUND(I17*Assumptions!E15/12,0) | J19: =ROUND(J17*Assumptions!E15/12,0) | K19: =ROUND(K17*Assumptions!E15/12,0) | L19: =ROUND(L17*Assumptions!E15/12,0) | M19: =ROUND(M17*Assumptions!E15/12,0) | N19: =ROUND(N17*Assumptions!E15/12,0) | O19: =ROUND(O17*Assumptions!E15/12,0) | P19: =SUM(D19:O19)
B20: Ending subs | D20: =D17+D18-D19 | E20: =E17+E18-E19 | F20: =F17+F18-F19 | G20: =G17+G18-G19 | H20: =H17+H18-H19 | I20: =I17+I18-I19 | J20: =J17+J18-J19 | K20: =K17+K18-K19 | ... O20: =O17+O18-O19 | P20: =O20
B21: Voice
B22: Beginning subs | D22: =Assumptions!E8 | E22: =D25 | F22: =E25 | G22: =F25 | H22: =G25 | I22: =H25 | J22: =I25 | K22: =J25 | L22: =K25 | ... O22: =N25 | P22: =D22
B23: Gross adds | D23: =ROUND(Assumptions!E12*0.07000,0) | E23: =ROUND(Assumptions!E12*0.07200,0) | F23: =ROUND(Assumptions!E12*0.07800,0) | G23: =ROUND(Assumptions!E12*0.08500,0) | H23: =ROUND(Assumptions!E12*0.09000,0) | I23: =ROUND(Assumptions!E12*0.09200,0) | J23: =ROUND(Assumptions!E12*0.09200,0) | K23: =ROUND(Assumptions!E12*0.09000,0) | L23: =ROUND(Assumptions!E12*0.08600,0) | M23: =ROUND(Assumptions!E12*0.08300,0) | N23: =ROUND(Assumptions!E12*0.08200,0) | O23: =Assumptions!E12-(D23+E23+F23+G23+H23+I23+J23+K23+L23+M23+N23) | P23: =SUM(D23:O23)
B24: Disconnects (churn) | D24: =ROUND(D22*Assumptions!E16/12,0) | E24: =ROUND(E22*Assumptions!E16/12,0) | F24: =ROUND(F22*Assumptions!E16/12,0) | G24: =ROUND(G22*Assumptions!E16/12,0) | H24: =ROUND(H22*Assumptions!E16/12,0) | I24: =ROUND(I22*Assumptions!E16/12,0) | J24: =ROUND(J22*Assumptions!E16/12,0) | K24: =ROUND(K22*Assumptions!E16/12,0) | L24: =ROUND(L22*Assumptions!E16/12,0) | M24: =ROUND(M22*Assumptions!E16/12,0) | N24: =ROUND(N22*Assumptions!E16/12,0) | O24: =ROUND(O22*Assumptions!E16/12,0) | P24: =SUM(D24:O24)
B25: Ending subs | D25: =D22+D23-D24 | E25: =E22+E23-E24 | F25: =F22+F23-F24 | G25: =G22+G23-G24 | H25: =H22+H23-H24 | I25: =I22+I23-I24 | J25: =J22+J23-J24 | K25: =K22+K23-K24 | ... O25: =O22+O23-O24 | P25: =O25
B27: ANNUAL SUMMARY (2027-2031)
B28: Metric | C28: 2027 | D28: 2028 | E28: 2029 | F28: 2030 | G28: 2031 | H28: 5-Yr / End
B29: Residential
B30: Beginning | C30: =Assumptions!E5 | D30: =C33 | E30: =D33 | F30: =E33 | G30: =F33
B31: Gross adds | C31: =Assumptions!E9 | D31: =Assumptions!F9 | E31: =Assumptions!G9 | F31: =Assumptions!H9 | G31: =Assumptions!I9 | H31: =SUM(C31:G31)
B32: Disconnects | C32: =P9 | D32: =ROUND(D30*Assumptions!E13,0) | E32: =ROUND(E30*Assumptions!E13,0) | F32: =ROUND(F30*Assumptions!E13,0) | G32: =ROUND(G30*Assumptions!E13,0)
B33: Ending | C33: =C30+C31-C32 | D33: =D30+D31-D32 | E33: =E30+E31-E32 | F33: =F30+F31-F32 | G33: =G30+G31-G32 | H33: =G33
B34: Business
B35: Beginning | C35: =Assumptions!E6 | D35: =C38 | E35: =D38 | F35: =E38 | G35: =F38
B36: Gross adds | C36: =Assumptions!E10 | D36: =Assumptions!F10 | E36: =Assumptions!G10 | F36: =Assumptions!H10 | G36: =Assumptions!I10 | H36: =SUM(C36:G36)
B37: Disconnects | C37: =P14 | D37: =ROUND(D35*Assumptions!E14,0) | E37: =ROUND(E35*Assumptions!E14,0) | F37: =ROUND(F35*Assumptions!E14,0) | G37: =ROUND(G35*Assumptions!E14,0)
B38: Ending | C38: =C35+C36-C37 | D38: =D35+D36-D37 | E38: =E35+E36-E37 | F38: =F35+F36-F37 | G38: =G35+G36-G37 | H38: =G38
B39: Enterprise / DIA
B40: Beginning | C40: =Assumptions!E7 | D40: =C43 | E40: =D43 | F40: =E43 | G40: =F43
B41: Gross adds | C41: =Assumptions!E11 | D41: =Assumptions!F11 | E41: =Assumptions!G11 | F41: =Assumptions!H11 | G41: =Assumptions!I11 | H41: =SUM(C41:G41)
B42: Disconnects | C42: =P19 | D42: =ROUND(D40*Assumptions!E15,0) | E42: =ROUND(E40*Assumptions!E15,0) | F42: =ROUND(F40*Assumptions!E15,0) | G42: =ROUND(G40*Assumptions!E15,0)
B43: Ending | C43: =C40+C41-C42 | D43: =D40+D41-D42 | E43: =E40+E41-E42 | F43: =F40+F41-F42 | G43: =G40+G41-G42 | H43: =G43
B44: Voice
B45: Beginning | C45: =Assumptions!E8 | D45: =C48 | E45: =D48 | F45: =E48 | G45: =F48
B46: Gross adds | C46: =Assumptions!E12 | D46: =Assumptions!F12 | E46: =Assumptions!G12 | F46: =Assumptions!H12 | G46: =Assumptions!I12 | H46: =SUM(C46:G46)
B47: Disconnects | C47: =P24 | D47: =ROUND(D45*Assumptions!E16,0) | E47: =ROUND(E45*Assumptions!E16,0) | F47: =ROUND(F45*Assumptions!E16,0) | G47: =ROUND(G45*Assumptions!E16,0)
B48: Ending | C48: =C45+C46-C47 | D48: =D45+D46-D47 | E48: =E45+E46-E47 | F48: =F45+F46-F47 | G48: =G45+G46-G47 | H48: =G48
B49: TOTAL INTERNET (Res+Biz+Ent) | C49: =C33+C38+C43 | D49: =D33+D38+D43 | E49: =E33+E38+E43 | F49: =F33+F38+F43 | G49: =G33+G38+G43
B50: Beginning (internet) | C50: =C30+C35+C40 | D50: =D30+D35+D40 | E50: =E30+E35+E40 | F50: =F30+F35+F40 | G50: =G30+G35+G40
B51: Gross adds (internet) | C51: =C31+C36+C41 | D51: =D31+D36+D41 | E51: =E31+E36+E41 | F51: =F31+F36+F41 | G51: =G31+G36+G41
B52: Disconnects (internet) | C52: =C32+C37+C42 | D52: =D32+D37+D42 | E52: =E32+E37+E42 | F52: =F32+F37+F42 | G52: =G32+G37+G42
B53: Net adds (internet) | C53: =C49-C50 | D53: =D49-D50 | E53: =E49-E50 | F53: =F49-F50 | G53: =G49-G50
B55: CHECK: monthly Dec = annual Y1 (each line, 0=OK) | C55: =ABS(P10-C33)+ABS(P15-C38)+ABS(P20-C43)+ABS(P25-C48)

Sheet Revenue Model
B1: Revenue Model (formula-driven)
B2: Recurring = avg subs × ARPU × 12 + attach services. Nonrecurring = installation/construction. Orange = placeholder input.
B4: Revenue line | C4: 2027 | D4: 2028 | E4: 2029 | F4: 2030 | G4: 2031 | H4: 5-Yr Total
B5: Residential internet | C5: =(('Subscriber Forecast'!C30+'Subscriber Forecast'!C33)/2)*(Assumptions!E17*(1+Assumptions!E18)^0)*12 | D5: =(('Subscriber Forecast'!D30+'Subscriber Forecast'!D33)/2)*(Assumptions!E17*(1+Assumptions!E18)^1)*12 | E5: =(('Subscriber Forecast'!E30+'Subscriber Forecast'!E33)/2)*(Assumptions!E17*(1+Assumptions!E18)^2)*12 | F5: =(('Subscriber Forecast'!F30+'Subscriber Forecast'!F33)/2)*(Assumptions!E17*(1+Assumptions!E18)^3)*12 | G5: =(('Subscriber Forecast'!G30+'Subscriber Forecast'!G33)/2)*(Assumptions!E17*(1+Assumptions!E18)^4)*12 | H5: =SUM(C5:G5)
B6: Business internet | C6: =(('Subscriber Forecast'!C35+'Subscriber Forecast'!C38)/2)*(Assumptions!E19*(1+Assumptions!E20)^0)*12 | D6: =(('Subscriber Forecast'!D35+'Subscriber Forecast'!D38)/2)*(Assumptions!E19*(1+Assumptions!E20)^1)*12 | E6: =(('Subscriber Forecast'!E35+'Subscriber Forecast'!E38)/2)*(Assumptions!E19*(1+Assumptions!E20)^2)*12 | F6: =(('Subscriber Forecast'!F35+'Subscriber Forecast'!F38)/2)*(Assumptions!E19*(1+Assumptions!E20)^3)*12 | G6: =(('Subscriber Forecast'!G35+'Subscriber Forecast'!G38)/2)*(Assumptions!E19*(1+Assumptions!E20)^4)*12 | H6: =SUM(C6:G6)
B7: Enterprise / DIA | C7: =(('Subscriber Forecast'!C40+'Subscriber Forecast'!C43)/2)*(Assumptions!E21*(1+Assumptions!E22)^0)*12 | D7: =(('Subscriber Forecast'!D40+'Subscriber Forecast'!D43)/2)*(Assumptions!E21*(1+Assumptions!E22)^1)*12 | E7: =(('Subscriber Forecast'!E40+'Subscriber Forecast'!E43)/2)*(Assumptions!E21*(1+Assumptions!E22)^2)*12 | F7: =(('Subscriber Forecast'!F40+'Subscriber Forecast'!F43)/2)*(Assumptions!E21*(1+Assumptions!E22)^3)*12 | G7: =(('Subscriber Forecast'!G40+'Subscriber Forecast'!G43)/2)*(Assumptions!E21*(1+Assumptions!E22)^4)*12 | H7: =SUM(C7:G7)
B8: Voice services | C8: =(('Subscriber Forecast'!C45+'Subscriber Forecast'!C48)/2)*(Assumptions!E23*(1+Assumptions!E24)^0)*12 | D8: =(('Subscriber Forecast'!D45+'Subscriber Forecast'!D48)/2)*(Assumptions!E23*(1+Assumptions!E24)^1)*12 | E8: =(('Subscriber Forecast'!E45+'Subscriber Forecast'!E48)/2)*(Assumptions!E23*(1+Assumptions!E24)^2)*12 | F8: =(('Subscriber Forecast'!F45+'Subscriber Forecast'!F48)/2)*(Assumptions!E23*(1+Assumptions!E24)^3)*12 | G8: =(('Subscriber Forecast'!G45+'Subscriber Forecast'!G48)/2)*(Assumptions!E23*(1+Assumptions!E24)^4)*12 | H8: =SUM(C8:G8)
B9: Managed Wi-Fi & premium | C9: =(('Subscriber Forecast'!C30+'Subscriber Forecast'!C33)/2)*Assumptions!E34*Assumptions!E35*12 | D9: =(('Subscriber Forecast'!D30+'Subscriber Forecast'!D33)/2)*Assumptions!E34*Assumptions!E35*12 | E9: =(('Subscriber Forecast'!E30+'Subscriber Forecast'!E33)/2)*Assumptions!E34*Assumptions!E35*12 | F9: =(('Subscriber Forecast'!F30+'Subscriber Forecast'!F33)/2)*Assumptions!E34*Assumptions!E35*12 | G9: =(('Subscriber Forecast'!G30+'Subscriber Forecast'!G33)/2)*Assumptions!E34*Assumptions!E35*12 | H9: =SUM(C9:G9)
B10: Static IP services | C10: =(('Subscriber Forecast'!C35+'Subscriber Forecast'!C38)/2)*Assumptions!E36*Assumptions!E37*12 | D10: =(('Subscriber Forecast'!D35+'Subscriber Forecast'!D38)/2)*Assumptions!E36*Assumptions!E37*12 | E10: =(('Subscriber Forecast'!E35+'Subscriber Forecast'!E38)/2)*Assumptions!E36*Assumptions!E37*12 | F10: =(('Subscriber Forecast'!F35+'Subscriber Forecast'!F38)/2)*Assumptions!E36*Assumptions!E37*12 | G10: =(('Subscriber Forecast'!G35+'Subscriber Forecast'!G38)/2)*Assumptions!E36*Assumptions!E37*12 | H10: =SUM(C10:G10)
B11: Equipment fees (ONT/router) | C11: =((('Subscriber Forecast'!C30+'Subscriber Forecast'!C33)/2)+(('Subscriber Forecast'!C35+'Subscriber Forecast'!C38)/2))*6*12 | D11: =((('Subscriber Forecast'!D30+'Subscriber Forecast'!D33)/2)+(('Subscriber Forecast'!D35+'Subscriber Forecast'!D38)/2))*6*12 | E11: =((('Subscriber Forecast'!E30+'Subscriber Forecast'!E33)/2)+(('Subscriber Forecast'!E35+'Subscriber Forecast'!E38)/2))*6*12 | F11: =((('Subscriber Forecast'!F30+'Subscriber Forecast'!F33)/2)+(('Subscriber Forecast'!F35+'Subscriber Forecast'!F38)/2))*6*12 | G11: =((('Subscriber Forecast'!G30+'Subscriber Forecast'!G33)/2)+(('Subscriber Forecast'!G35+'Subscriber Forecast'!G38)/2))*6*12 | H11: =SUM(C11:G11)
B12: Wholesale / dark fiber / IRU / transport | C12: 180000 | D12: 240000 | E12: 320000 | F12: 410000 | G12: 500000 | H12: =SUM(C12:G12)
B13: Grant operating/admin revenue (if allowable) | C13: 50000 | D13: 60000 | E13: 70000 | F13: 70000 | G13: 60000 | H13: =SUM(C13:G13)
B14: Other telecom services | C14: 40000 | D14: 55000 | E14: 70000 | F14: 85000 | G14: 100000 | H14: =SUM(C14:G14)
B15: RECURRING REVENUE | C15: =C5+C6+C7+C8+C9+C10+C11+C12+C13+C14 | D15: =D5+D6+D7+D8+D9+D10+D11+D12+D13+D14 | E15: =E5+E6+E7+E8+E9+E10+E11+E12+E13+E14 | F15: =F5+F6+F7+F8+F9+F10+F11+F12+F13+F14 | G15: =G5+G6+G7+G8+G9+G10+G11+G12+G13+G14 | H15: =SUM(C15:G15)
B16: Installation & construction (nonrecurring) | C16: ='Subscriber Forecast'!C31*Assumptions!E38+'Subscriber Forecast'!C36*Assumptions!E39+'Subscriber Forecast'!C41*Assumptions!E40 | D16: ='Subscriber Forecast'!D31*Assumptions!E38+'Subscriber Forecast'!D36*Assumptions!E39+'Subscriber Forecast'!D41*Assumptions!E40 | E16: ='Subscriber Forecast'!E31*Assumptions!E38+'Subscriber Forecast'!E36*Assumptions!E39+'Subscriber Forecast'!E41*Assumptions!E40 | F16: ='Subscriber Forecast'!F31*Assumptions!E38+'Subscriber Forecast'!F36*Assumptions!E39+'Subscriber Forecast'!F41*Assumptions!E40 | G16: ='Subscriber Forecast'!G31*Assumptions!E38+'Subscriber Forecast'!G36*Assumptions!E39+'Subscriber Forecast'!G41*Assumptions!E40 | H16: =SUM(C16:G16)
B17: TOTAL REVENUE | C17: =C15+C16 | D17: =D15+D16 | E17: =E15+E16 | F17: =F15+F16 | G17: =G15+G16 | H17: =SUM(C17:G17)
B19: Blended ARPU (recurring/sub/mo) | C19: =C15/(('Subscriber Forecast'!C50+'Subscriber Forecast'!C49)/2+('Subscriber Forecast'!C45+'Subscriber Forecast'!C48)/2)/12 | D19: =D15/(('Subscriber Forecast'!D50+'Subscriber Forecast'!D49)/2+('Subscriber Forecast'!D45+'Subscriber Forecast'!D48)/2)/12 | E19: =E15/(('Subscriber Forecast'!E50+'Subscriber Forecast'!E49)/2+('Subscriber Forecast'!E45+'Subscriber Forecast'!E48)/2)/12 | F19: =F15/(('Subscriber Forecast'!F50+'Subscriber Forecast'!F49)/2+('Subscriber Forecast'!F45+'Subscriber Forecast'!F48)/2)/12 | G19: =G15/(('Subscriber Forecast'!G50+'Subscriber Forecast'!G49)/2+('Subscriber Forecast'!G45+'Subscriber Forecast'!G48)/2)/12

Sheet Operating Expenses
B1: Operating-Expense Model (formula-driven)
B2: Classified Direct / S&M / Network Ops / G&A and Fixed/Variable/Semi-variable. Efficiency multiplier & inflation from Assumptions.
B4: Expense category | C4: Class | D4: Behavior | E4: 2027 | F4: 2028 | G4: 2029 | H4: 2030 | I4: 2031
B5: Internet transit / bandwidth | C5: Direct | D5: Variable | E5: =((('Subscriber Forecast'!C50+'Subscriber Forecast'!C49)/2)*2.5*12*(1+Assumptions!E32)^0)*Assumptions!E33 | F5: =((('Subscriber Forecast'!D50+'Subscriber Forecast'!D49)/2)*2.5*12*(1+Assumptions!E32)^1)*Assumptions!E33 | G5: =((('Subscriber Forecast'!E50+'Subscriber Forecast'!E49)/2)*2.5*12*(1+Assumptions!E32)^2)*Assumptions!E33 | H5: =((('Subscriber Forecast'!F50+'Subscriber Forecast'!F49)/2)*2.5*12*(1+Assumptions!E32)^3)*Assumptions!E33 | I5: =((('Subscriber Forecast'!G50+'Subscriber Forecast'!G49)/2)*2.5*12*(1+Assumptions!E32)^4)*Assumptions!E33
B6: Fiber leases & transport | C6: Direct | D6: Fixed | E6: =((180000+12000*0)*(1+Assumptions!E32)^0)*Assumptions!E33 | F6: =((180000+12000*1)*(1+Assumptions!E32)^1)*Assumptions!E33 | G6: =((180000+12000*2)*(1+Assumptions!E32)^2)*Assumptions!E33 | H6: =((180000+12000*3)*(1+Assumptions!E32)^3)*Assumptions!E33 | I6: =((180000+12000*4)*(1+Assumptions!E32)^4)*Assumptions!E33
B7: Pole attachment expense | C7: Direct | D7: Variable | E7: =(((Assumptions!E25+SUM(Assumptions!E27:E27))+(Assumptions!E26+SUM(Assumptions!E28:E28)))*0.55*(1+Assumptions!E32)^0)*Assumptions!E33 | F7: =(((Assumptions!E25+SUM(Assumptions!E27:F27))+(Assumptions!E26+SUM(Assumptions!E28:F28)))*0.55*(1+Assumptions!E32)^1)*Assumptions!E33 | G7: =(((Assumptions!E25+SUM(Assumptions!E27:G27))+(Assumptions!E26+SUM(Assumptions!E28:G28)))*0.55*(1+Assumptions!E32)^2)*Assumptions!E33 | H7: =(((Assumptions!E25+SUM(Assumptions!E27:H27))+(Assumptions!E26+SUM(Assumptions!E28:H28)))*0.55*(1+Assumptions!E32)^3)*Assumptions!E33 | I7: =(((Assumptions!E25+SUM(Assumptions!E27:I27))+(Assumptions!E26+SUM(Assumptions!E28:I28)))*0.55*(1+Assumptions!E32)^4)*Assumptions!E33
B8: Fiber maintenance | C8: Direct | D8: Fixed | E8: =((95000+15000*0)*(1+Assumptions!E32)^0)*Assumptions!E33 | F8: =((95000+15000*1)*(1+Assumptions!E32)^1)*Assumptions!E33 | G8: =((95000+15000*2)*(1+Assumptions!E32)^2)*Assumptions!E33 | H8: =((95000+15000*3)*(1+Assumptions!E32)^3)*Assumptions!E33 | I8: =((95000+15000*4)*(1+Assumptions!E32)^4)*Assumptions!E33
B9: Network monitoring / NOC | C9: Direct | D9: Fixed | E9: =((140000+10000*0)*(1+Assumptions!E32)^0)*Assumptions!E33 | F9: =((140000+10000*1)*(1+Assumptions!E32)^1)*Assumptions!E33 | G9: =((140000+10000*2)*(1+Assumptions!E32)^2)*Assumptions!E33 | H9: =((140000+10000*3)*(1+Assumptions!E32)^3)*Assumptions!E33 | I9: =((140000+10000*4)*(1+Assumptions!E32)^4)*Assumptions!E33
B10: Voice platform | C10: Direct | D10: Variable | E10: =((('Subscriber Forecast'!C45+'Subscriber Forecast'!C48)/2)*8*12*(1+Assumptions!E32)^0)*Assumptions!E33 | F10: =((('Subscriber Forecast'!D45+'Subscriber Forecast'!D48)/2)*8*12*(1+Assumptions!E32)^1)*Assumptions!E33 | G10: =((('Subscriber Forecast'!E45+'Subscriber Forecast'!E48)/2)*8*12*(1+Assumptions!E32)^2)*Assumptions!E33 | H10: =((('Subscriber Forecast'!F45+'Subscriber Forecast'!F48)/2)*8*12*(1+Assumptions!E32)^3)*Assumptions!E33 | I10: =((('Subscriber Forecast'!G45+'Subscriber Forecast'!G48)/2)*8*12*(1+Assumptions!E32)^4)*Assumptions!E33
B11: Emergency restoration | C11: Direct | D11: Fixed | E11: =(75000*(1+Assumptions!E32)^0)*Assumptions!E33 | F11: =(75000*(1+Assumptions!E32)^1)*Assumptions!E33 | G11: =(75000*(1+Assumptions!E32)^2)*Assumptions!E33 | H11: =(75000*(1+Assumptions!E32)^3)*Assumptions!E33 | I11: =(75000*(1+Assumptions!E32)^4)*Assumptions!E33
B12: Marketing & advertising | C12: S&M | D12: Semi-var | E12: =('Subscriber Forecast'!C51*Assumptions!E31+120000*(1+Assumptions!E32)^0)*Assumptions!E33 | F12: =('Subscriber Forecast'!D51*Assumptions!E31+120000*(1+Assumptions!E32)^1)*Assumptions!E33 | G12: =('Subscriber Forecast'!E51*Assumptions!E31+120000*(1+Assumptions!E32)^2)*Assumptions!E33 | H12: =('Subscriber Forecast'!F51*Assumptions!E31+120000*(1+Assumptions!E32)^3)*Assumptions!E33 | I12: =('Subscriber Forecast'!G51*Assumptions!E31+120000*(1+Assumptions!E32)^4)*Assumptions!E33
B13: Sales commissions | C13: S&M | D13: Variable | E13: =('Revenue Model'!C15*0.015)*Assumptions!E33 | F13: =('Revenue Model'!D15*0.015)*Assumptions!E33 | G13: =('Revenue Model'!E15*0.015)*Assumptions!E33 | H13: =('Revenue Model'!F15*0.015)*Assumptions!E33 | I13: =('Revenue Model'!G15*0.015)*Assumptions!E33
B14: Vehicle fleet (fuel/repairs/ins/lease) | C14: NetOps | D14: Semi-var | E14: =(9500*MAX(8,ROUND(Assumptions!E41*0.55,0))*(1+Assumptions!E32)^0)*Assumptions!E33 | F14: =(9500*MAX(8,ROUND(Assumptions!F41*0.55,0))*(1+Assumptions!E32)^1)*Assumptions!E33 | G14: =(9500*MAX(8,ROUND(Assumptions!G41*0.55,0))*(1+Assumptions!E32)^2)*Assumptions!E33 | H14: =(9500*MAX(8,ROUND(Assumptions!H41*0.55,0))*(1+Assumptions!E32)^3)*Assumptions!E33 | I14: =(9500*MAX(8,ROUND(Assumptions!I41*0.55,0))*(1+Assumptions!E32)^4)*Assumptions!E33
B15: Tools, test & safety equipment | C15: NetOps | D15: Fixed | E15: =((45000+4000*0)*(1+Assumptions!E32)^0)*Assumptions!E33 | F15: =((45000+4000*1)*(1+Assumptions!E32)^1)*Assumptions!E33 | G15: =((45000+4000*2)*(1+Assumptions!E32)^2)*Assumptions!E33 | H15: =((45000+4000*3)*(1+Assumptions!E32)^3)*Assumptions!E33 | I15: =((45000+4000*4)*(1+Assumptions!E32)^4)*Assumptions!E33
B16: Warehouse & inventory | C16: NetOps | D16: Fixed | E16: =((60000+5000*0)*(1+Assumptions!E32)^0)*Assumptions!E33 | F16: =((60000+5000*1)*(1+Assumptions!E32)^1)*Assumptions!E33 | G16: =((60000+5000*2)*(1+Assumptions!E32)^2)*Assumptions!E33 | H16: =((60000+5000*3)*(1+Assumptions!E32)^3)*Assumptions!E33 | I16: =((60000+5000*4)*(1+Assumptions!E32)^4)*Assumptions!E33
B17: Contractor labor | C17: NetOps | D17: Semi-var | E17: =((650000+60000*0)*(1+Assumptions!E32)^0)*Assumptions!E33 | F17: =((650000+60000*1)*(1+Assumptions!E32)^1)*Assumptions!E33 | G17: =((650000+60000*2)*(1+Assumptions!E32)^2)*Assumptions!E33 | H17: =((650000+60000*3)*(1+Assumptions!E32)^3)*Assumptions!E33 | I17: =((650000+60000*4)*(1+Assumptions!E32)^4)*Assumptions!E33
B18: Salaries, OT, benefits (fully loaded) | C18: G&A | D18: Fixed | E18: ='Fully Loaded Labor Cost'!C32 | F18: ='Fully Loaded Labor Cost'!D32 | G18: ='Fully Loaded Labor Cost'!E32 | H18: ='Fully Loaded Labor Cost'!F32 | I18: ='Fully Loaded Labor Cost'!G32
B19: Software / OSS / BSS / CRM / GIS / billing | C19: G&A | D19: Fixed | E19: =((260000+20000*0)*(1+Assumptions!E32)^0)*Assumptions!E33 | F19: =((260000+20000*1)*(1+Assumptions!E32)^1)*Assumptions!E33 | G19: =((260000+20000*2)*(1+Assumptions!E32)^2)*Assumptions!E33 | H19: =((260000+20000*3)*(1+Assumptions!E32)^3)*Assumptions!E33 | I19: =((260000+20000*4)*(1+Assumptions!E32)^4)*Assumptions!E33
B20: Billing & payment processing fees | C20: G&A | D20: Variable | E20: =('Revenue Model'!C15*0.02)*Assumptions!E33 | F20: =('Revenue Model'!D15*0.02)*Assumptions!E33 | G20: =('Revenue Model'!E15*0.02)*Assumptions!E33 | H20: =('Revenue Model'!F15*0.02)*Assumptions!E33 | I20: =('Revenue Model'!G15*0.02)*Assumptions!E33
B21: Customer support | C21: G&A | D21: Semi-var | E21: =((110000+25000*0)*(1+Assumptions!E32)^0)*Assumptions!E33 | F21: =((110000+25000*1)*(1+Assumptions!E32)^1)*Assumptions!E33 | G21: =((110000+25000*2)*(1+Assumptions!E32)^2)*Assumptions!E33 | H21: =((110000+25000*3)*(1+Assumptions!E32)^3)*Assumptions!E33 | I21: =((110000+25000*4)*(1+Assumptions!E32)^4)*Assumptions!E33
B22: Property & casualty insurance | C22: G&A | D22: Fixed | E22: =((185000+10000*0)*(1+Assumptions!E32)^0)*Assumptions!E33 | F22: =((185000+10000*1)*(1+Assumptions!E32)^1)*Assumptions!E33 | G22: =((185000+10000*2)*(1+Assumptions!E32)^2)*Assumptions!E33 | H22: =((185000+10000*3)*(1+Assumptions!E32)^3)*Assumptions!E33 | I22: =((185000+10000*4)*(1+Assumptions!E32)^4)*Assumptions!E33
B23: Professional / legal / consulting / regulatory | C23: G&A | D23: Fixed | E23: =((210000+12000*0)*(1+Assumptions!E32)^0)*Assumptions!E33 | F23: =((210000+12000*1)*(1+Assumptions!E32)^1)*Assumptions!E33 | G23: =((210000+12000*2)*(1+Assumptions!E32)^2)*Assumptions!E33 | H23: =((210000+12000*3)*(1+Assumptions!E32)^3)*Assumptions!E33 | I23: =((210000+12000*4)*(1+Assumptions!E32)^4)*Assumptions!E33
B24: Training & travel | C24: G&A | D24: Semi-var | E24: =((65000+6000*0)*(1+Assumptions!E32)^0)*Assumptions!E33 | F24: =((65000+6000*1)*(1+Assumptions!E32)^1)*Assumptions!E33 | G24: =((65000+6000*2)*(1+Assumptions!E32)^2)*Assumptions!E33 | H24: =((65000+6000*3)*(1+Assumptions!E32)^3)*Assumptions!E33 | I24: =((65000+6000*4)*(1+Assumptions!E32)^4)*Assumptions!E33
B25: Office & administrative | C25: G&A | D25: Fixed | E25: =((140000+12000*0)*(1+Assumptions!E32)^0)*Assumptions!E33 | F25: =((140000+12000*1)*(1+Assumptions!E32)^1)*Assumptions!E33 | G25: =((140000+12000*2)*(1+Assumptions!E32)^2)*Assumptions!E33 | H25: =((140000+12000*3)*(1+Assumptions!E32)^3)*Assumptions!E33 | I25: =((140000+12000*4)*(1+Assumptions!E32)^4)*Assumptions!E33
B26: Utilities | C26: G&A | D26: Fixed | E26: =((70000+6000*0)*(1+Assumptions!E32)^0)*Assumptions!E33 | F26: =((70000+6000*1)*(1+Assumptions!E32)^1)*Assumptions!E33 | G26: =((70000+6000*2)*(1+Assumptions!E32)^2)*Assumptions!E33 | H26: =((70000+6000*3)*(1+Assumptions!E32)^3)*Assumptions!E33 | I26: =((70000+6000*4)*(1+Assumptions!E32)^4)*Assumptions!E33
B27: Bad debt | C27: G&A | D27: Variable | E27: =('Revenue Model'!C17*0.008)*Assumptions!E33 | F27: =('Revenue Model'!D17*0.008)*Assumptions!E33 | G27: =('Revenue Model'!E17*0.008)*Assumptions!E33 | H27: =('Revenue Model'!F17*0.008)*Assumptions!E33 | I27: =('Revenue Model'!G17*0.008)*Assumptions!E33
B28: Taxes & regulatory fees (USF etc.) | C28: G&A | D28: Variable | E28: =('Revenue Model'!C15*0.015)*Assumptions!E33 | F28: =('Revenue Model'!D15*0.015)*Assumptions!E33 | G28: =('Revenue Model'!E15*0.015)*Assumptions!E33 | H28: =('Revenue Model'!F15*0.015)*Assumptions!E33 | I28: =('Revenue Model'!G15*0.015)*Assumptions!E33
B29: Subtotal (pre-contingency) | E29: =SUM(E5:E28) | F29: =SUM(F5:F28) | G29: =SUM(G5:G28) | H29: =SUM(H5:H28) | I29: =SUM(I5:I28)
B30: Contingency | C30: G&A | D30: Semi-var | E30: =E29*0.015 | F30: =F29*0.015 | G30: =G29*0.015 | H30: =H29*0.015 | I30: =I29*0.015
B31: TOTAL OPERATING EXPENSE | E31: =E29+E30 | F31: =F29+F30 | G31: =G29+G30 | H31: =H29+H30 | I31: =I29+I30
B33: By classification:
B34: Direct cost of service | E34: =E5+E6+E7+E8+E9+E10+E11 | F34: =F5+F6+F7+F8+F9+F10+F11 | G34: =G5+G6+G7+G8+G9+G10+G11 | H34: =H5+H6+H7+H8+H9+H10+H11 | I34: =I5+I6+I7+I8+I9+I10+I11
B35: Sales & marketing | E35: =E12+E13 | F35: =F12+F13 | G35: =G12+G13 | H35: =H12+H13 | I35: =I12+I13
B36: Network operations | E36: =E14+E15+E16+E17 | F36: =F14+F15+F16+F17 | G36: =G14+G15+G16+G17 | H36: =H14+H15+H16+H17 | I36: =I14+I15+I16+I17
B37: General & administrative | E37: =E18+E19+E20+E21+E22+E23+E24+E25+E26+E27+E28+E30 | F37: =F18+F19+F20+F21+F22+F23+F24+F25+F26+F27+F28+F30 | G37: =G18+G19+G20+G21+G22+G23+G24+G25+G26+G27+G28+G30 | H37: =H18+H19+H20+H21+H22+H23+H24+H25+H26+H27+H28+H30 | I37: =I18+I19+I20+I21+I22+I23+I24+I25+I26+I27+I28+I30
B39: OpEx per subscriber ($/yr) | E39: ='Operating Expenses'!E31/(('Subscriber Forecast'!C50+'Subscriber Forecast'!C49)/2) | F39: ='Operating Expenses'!F31/(('Subscriber Forecast'!D50+'Subscriber Forecast'!D49)/2) | G39: ='Operating Expenses'!G31/(('Subscriber Forecast'!E50+'Subscriber Forecast'!E49)/2) | H39: ='Operating Expenses'!H31/(('Subscriber Forecast'!F50+'Subscriber Forecast'!F49)/2) | I39: ='Operating Expenses'!I31/(('Subscriber Forecast'!G50+'Subscriber Forecast'!G49)/2)
B40: OpEx per revenue dollar | E40: ='Operating Expenses'!E31/'Revenue Model'!C17 | F40: ='Operating Expenses'!F31/'Revenue Model'!D17 | G40: ='Operating Expenses'!G31/'Revenue Model'!E17 | H40: ='Operating Expenses'!H31/'Revenue Model'!F17 | I40: ='Operating Expenses'!I31/'Revenue Model'!G17

Sheet Current Staffing
B1: Current Staffing Structure (Actual)
B2: 15 filled + 3 open = 18 authorized. Green cells are the reconciliation controls.
B4: Position | C4: Filled | D4: Open | E4: Authorized | F4: Fully-loaded cost each $ | G4: Loaded subtotal $
B5: Chief Operations Officer | C5: 1 | D5: 0 | E5: =C5+D5 | F5: ='Fully Loaded Labor Cost'!G5 | G5: =E5*F5
B6: Director of Outside Plant | C6: 1 | D6: 0 | E6: =C6+D6 | F6: ='Fully Loaded Labor Cost'!G6 | G6: =E6*F6
B7: Supervisors | C7: 2 | D7: 0 | E7: =C7+D7 | F7: ='Fully Loaded Labor Cost'!G7 | G7: =E7*F7
B8: Project Coordinators | C8: 2 | D8: 0 | E8: =C8+D8 | F8: ='Fully Loaded Labor Cost'!G8 | G8: =E8*F8
B9: Sales Coordinator | C9: 1 | D9: 0 | E9: =C9+D9 | F9: ='Fully Loaded Labor Cost'!G9 | G9: =E9*F9
B10: Sales Representatives | C10: 3 | D10: 1 | E10: =C10+D10 | F10: ='Fully Loaded Labor Cost'!G10 | G10: =E10*F10
B11: Fiber Technicians | C11: 5 | D11: 2 | E11: =C11+D11 | F11: ='Fully Loaded Labor Cost'!G11 | G11: =E11*F11
B12: TOTAL | C12: =SUM(C5:C11) | D12: =SUM(D5:D11) | E12: =SUM(E5:E11) | G12: =SUM(G5:G11)
B14: CHECK: Filled = 15 | C14: =C12-15
B15: CHECK: Open = 3 | C15: =D12-3
B16: CHECK: Authorized = 18 | C16: =E12-18

Sheet Five-Year Staffing Plan
B1: Five-Year Staffing Plan — Trigger-Based Hiring
B2: Positions added when measurable business triggers are met, not fixed dates. Blue base salary = editable; loaded cost computed.
B4: Position | C4: Rec. Yr | D4: # | E4: Base $ | F4: Fully-loaded $ | G4: Primary responsibilities | H4: Reason needed | I4: Hiring trigger | J4: Expected benefit | K4: Risk if not added
B5: Network Engineer | C5: 2027 | D5: 1 | E5: 95000 | F5: =E5*'Fully Loaded Labor Cost'!C22*D5 | G5: Design core/access network, capacity planning | H5: Network complexity rising with growth | I5: Subs >6,000 OR 3+ active OLT sites | J5: Prevents outages; scales capacity
B6: NOC Technician | C6: 2027 | D6: 1 | E6: 60000 | F6: =E6*'Fully Loaded Labor Cost'!C22*D6 | G6: 24x7 monitoring, tier-2 triage | H6: Proactive fault management | I6: Trouble tickets >8/tech/day | J6: Faster MTTR; higher availability
B7: Fiber Splicers | C7: 2027 | D7: 2 | E7: 62000 | F7: =E7*'Fully Loaded Labor Cost'!C22*D7 | G7: Backbone/distribution splicing | H7: Construction volume growth | I7: Fiber miles >new-build threshold | J7: In-house splicing lowers cost
B8: Residential Sales Reps | C8: 2028 | D8: 2 | E8: 52000 | F8: =E8*'Fully Loaded Labor Cost'!C22*D8 | G8: Door-to-door & inbound residential sales | H8: Take-rate acceleration | I8: New passings >4,000/yr | J8: Higher take rate on new plant
B9: Customer Support Reps | C9: 2028 | D9: 2 | E9: 44000 | F9: =E9*'Fully Loaded Labor Cost'!C22*D9 | G9: Tier-1 support, billing inquiries | H9: Support volume with subscriber base | I9: Subs >7,500 OR calls/agent high | J9: Protects CSAT & retention
B10: Additional Project Coordinator | C10: 2028 | D10: 1 | E10: 68000 | F10: =E10*'Fully Loaded Labor Cost'!C22*D10 | G10: Coordinate construction projects | H10: Active project count rising | I10: Active projects >6 concurrent | J10: Keeps builds on schedule
B11: Fiber Install/Repair Techs | C11: 2028 | D11: 3 | E11: 58000 | F11: =E11*'Fully Loaded Labor Cost'!C22*D11 | G11: Installs & trouble repair | H11: Install backlog with net adds | I11: Install interval >10 days | J11: Shortens install interval
B12: Enterprise Sales Rep | C12: 2029 | D12: 1 | E12: 72000 | F12: =E12*'Fully Loaded Labor Cost'!C22*D12 | G12: Enterprise/DIA & wholesale sales | H12: B2B revenue expansion | I12: Enterprise pipeline qualified | J12: Higher-ARPU B2B revenue
B13: Construction Inspector | C13: 2029 | D13: 1 | E13: 64000 | F13: =E13*'Fully Loaded Labor Cost'!C22*D13 | G13: QA/QC on construction, grant compliance | H13: Grant documentation & quality | I13: Grant-funded miles active | J13: Grant compliance; fewer defects
B14: GIS / Mapping Specialist | C14: 2029 | D14: 1 | E14: 60000 | F14: =E14*'Fully Loaded Labor Cost'!C22*D14 | G14: Network records, as-builts, GIS | H14: Data quality for ops & grants | I14: Passings >18,000 | J14: Accurate records; faster locates
B15: Additional OSP Supervisor | C15: 2030 | D15: 1 | E15: 90000 | F15: =E15*'Fully Loaded Labor Cost'!C22*D15 | G15: Supervise expanded field crews | H15: Span of control limit | I15: Field FTEs/supervisor >8 | J15: Maintains crew productivity
B16: Marketing Specialist | C16: 2030 | D16: 1 | E16: 58000 | F16: =E16*'Fully Loaded Labor Cost'!C22*D16 | G16: Campaigns, brand, digital | H16: Structured demand generation | I16: Marketing spend >$0.3M/yr | J16: Lower CAC; higher take rate
B17: Customer Experience Manager | C17: 2030 | D17: 1 | E17: 78000 | F17: =E17*'Fully Loaded Labor Cost'!C22*D17 | G17: Own CSAT, retention programs | H17: Retention discipline at scale | I17: Subs >10,000 | J17: Lower churn; higher NRR
B18: Data Analyst | C18: 2031 | D18: 1 | E18: 70000 | F18: =E18*'Fully Loaded Labor Cost'!C22*D18 | G18: KPI reporting, forecasting | H18: Data-driven decisions | I18: Monthly KPI program mature | J18: Better forecasts & decisions
B19: Warehouse & Inventory Specialist | C19: 2031 | D19: 1 | E19: 50000 | F19: =E19*'Fully Loaded Labor Cost'!C22*D19 | G19: Inventory control, staging | H19: Inventory scale & shrink control | I19: Multiple warehouses | J19: Lower shrink; faster installs
B20: TOTAL NEW POSITIONS | D20: =SUM(D5:D19) | F20: =SUM(F5:F19)

Sheet Fully Loaded Labor Cost
B1: Fully-Loaded Labor Cost Build-Up
B2: Blue = editable placeholder wage/benefit inputs. Fully-loaded = base × load factor + tools + recruiting. Orange = placeholder.
B4: Current position | C4: Base salary $ | D4: Filled | E4: Open | F4: Authorized | G4: Loaded/position $
B5: Chief Operations Officer | C5: 165000 | D5: 1 | E5: 0 | F5: =D5+E5 | G5: =C5*C22+C23+C24
B6: Director of Outside Plant | C6: 130000 | D6: 1 | E6: 0 | F6: =D6+E6 | G6: =C6*C22+C23+C24
B7: Supervisors | C7: 92000 | D7: 2 | E7: 0 | F7: =D7+E7 | G7: =C7*C22+C23+C24
B8: Project Coordinators | C8: 68000 | D8: 2 | E8: 0 | F8: =D8+E8 | G8: =C8*C22+C23+C24
B9: Sales Coordinator | C9: 62000 | D9: 1 | E9: 0 | F9: =D9+E9 | G9: =C9*C22+C23+C24
B10: Sales Representatives | C10: 55000 | D10: 3 | E10: 1 | F10: =D10+E10 | G10: =C10*C22+C23+C24
B11: Fiber Technicians | C11: 58000 | D11: 5 | E11: 2 | F11: =D11+E11 | G11: =C11*C22+C23+C24
B12: TOTAL / WEIGHTED | C12: =SUMPRODUCT(C5:C11,F5:F11) | D12: =SUM(D5:D11) | E12: =SUM(E5:E11) | F12: =SUM(F5:F11)
B14: LOAD COMPONENTS (% of base)
B15: Overtime | C15: 0.05
B16: Incentive compensation | C16: 0.06
B17: Payroll taxes | C17: 0.0765
B18: Health & retirement benefits | C18: 0.18
B19: Workers' compensation | C19: 0.035
B20: Training & certifications | C20: 0.015
B21: Uniforms & PPE | C21: 0.01
B22: Load factor (1 + Σ) | C22: =1+SUM(C15:C21)
B23: Per-head tools/laptop/phone/test equip $ | C23: 3500
B24: Per-head recruiting/onboarding $ | C24: 1200
B25: Annual merit increase % | C25: 0.03
B26: Average base salary (authorized) $ | C26: =C12/F12
B27: FULLY-LOADED COST PER POSITION $ | C27: =C26*C22+C23+C24
B29: FIVE-YEAR FULLY-LOADED LABOR COST
B30: Item | C30: 2027 | D30: 2028 | E30: 2029 | F30: 2030 | G30: 2031 | H30: 5-Yr Total
B31: Total headcount (EOY) | C31: =Assumptions!E41 | D31: =Assumptions!F41 | E31: =Assumptions!G41 | F31: =Assumptions!H41 | G31: =Assumptions!I41
B32: Fully-loaded labor cost | C32: =C31*C27*(1+C25)^0 | D32: =D31*C27*(1+C25)^1 | E32: =E31*C27*(1+C25)^2 | F32: =F31*C27*(1+C25)^3 | G32: =G31*C27*(1+C25)^4 | H32: =SUM(C32:G32)

Sheet Capital Plan
B1: Five-Year Capital Plan — $10M/yr · $50M/5yr
B2: Refresh (#15) is fixed $400K/yr & fully committed. Others scale by deployment fraction. Reserve/carryforward allowed — full $10M not forced.
B4: Category | C4: Annual Alloc $ | D4: % Cap | E4: 2027 | F4: 2028 | G4: 2029 | H4: 2030 | I4: 2031 | J4: 5-Yr $ | K4: Depr yrs | L4: Business purpose | M4: Operational benefit | N4: Revenue / cost impact | O4: Timing | P4: Key dependency | Q4: Responsible
B5: 1. Fiber backbone construction | C5: 800000 | D5: =C5/10000000 | E5: =ROUND($C5*Assumptions!E29,0) | F5: =ROUND($C5*Assumptions!F29,0) | G5: =ROUND($C5*Assumptions!G29,0) | H5: =ROUND($C5*Assumptions!H29,0) | I5: =ROUND($C5*Assumptions!I29,0) | J5: =SUM(E5:I5) | K5: 25 | L5: Middle-mile & backbone fiber routes | M5: Adds transport capacity & redundancy | N5: Enables new market revenue; lowers leased-transport cost | O5: Y1-Y3 priority | P5: Permitting, pole make-ready | Q5: VP Engineering / Dir OSP
B6: 2. Distribution fiber construction | C6: 1300000 | D6: =C6/10000000 | E6: =ROUND($C6*Assumptions!E29,0) | F6: =ROUND($C6*Assumptions!F29,0) | G6: =ROUND($C6*Assumptions!G29,0) | H6: =ROUND($C6*Assumptions!H29,0) | I6: =ROUND($C6*Assumptions!I29,0) | J6: =SUM(E6:I6) | K6: 25 | L6: Neighborhood distribution plant | M6: Extends serviceable footprint | N6: Drives new passings → subscriber revenue | O6: Continuous | P6: Backbone in place | Q6: Dir Outside Plant
B7: 3. Fiber-to-the-home expansion | C7: 2350000 | D7: =C7/10000000 | E7: =ROUND($C7*Assumptions!E29,0) | F7: =ROUND($C7*Assumptions!F29,0) | G7: =ROUND($C7*Assumptions!G29,0) | H7: =ROUND($C7*Assumptions!H29,0) | I7: =ROUND($C7*Assumptions!I29,0) | J7: =SUM(E7:I7) | K7: 20 | L7: Drops, ONTs, service laterals | M7: Converts passings to paying subs | N7: Primary residential revenue driver | O7: Continuous, demand-led | P7: Distribution built | Q7: Dir OSP / COO
B8: 4. Business & enterprise expansion | C8: 700000 | D8: =C8/10000000 | E8: =ROUND($C8*Assumptions!E29,0) | F8: =ROUND($C8*Assumptions!F29,0) | G8: =ROUND($C8*Assumptions!G29,0) | H8: =ROUND($C8*Assumptions!H29,0) | I8: =ROUND($C8*Assumptions!I29,0) | J8: =SUM(E8:I8) | K8: 15 | L8: Business fiber & enterprise circuits | M8: Higher-ARPU B2B connectivity | N8: Enterprise/DIA revenue & margin | O8: Y1-Y5, pipeline-led | P8: Sales pipeline | Q8: VP Sales / Eng
B9: 5. Grant matching funds | C9: 1000000 | D9: =C9/10000000 | E9: =ROUND($C9*Assumptions!E29,0) | F9: =ROUND($C9*Assumptions!F29,0) | G9: =ROUND($C9*Assumptions!G29,0) | H9: =ROUND($C9*Assumptions!H29,0) | I9: =ROUND($C9*Assumptions!I29,0) | J9: =SUM(E9:I9) | K9: 20 | L9: Required match for grant builds | M9: Unlocks grant-funded construction | N9: Leverages external capital 2-5x | O9: Per award schedule | P9: Grant awards | Q9: CFO / Grants Mgr
B10: 6. Core network & transport equipment | C10: 500000 | D10: =C10/10000000 | E10: =ROUND($C10*Assumptions!E29,0) | F10: =ROUND($C10*Assumptions!F29,0) | G10: =ROUND($C10*Assumptions!G29,0) | H10: =ROUND($C10*Assumptions!H29,0) | I10: =ROUND($C10*Assumptions!I29,0) | J10: =SUM(E10:I10) | K10: 10 | L10: Routers, switches, DWDM | M10: Core capacity & resiliency | N10: Supports all revenue; avoids congestion | O10: Y1 refresh + growth | P10: Vendor lead times | Q10: Network Engineering
B11: 7. OLT, cabinet & access-network equipment | C11: 650000 | D11: =C11/10000000 | E11: =ROUND($C11*Assumptions!E29,0) | F11: =ROUND($C11*Assumptions!F29,0) | G11: =ROUND($C11*Assumptions!G29,0) | H11: =ROUND($C11*Assumptions!H29,0) | I11: =ROUND($C11*Assumptions!I29,0) | J11: =SUM(E11:I11) | K11: 10 | L11: OLTs, cabinets, splitters | M11: Access-layer subscriber capacity | N11: Enables sub growth per node | O11: With distribution | P11: Cabinet siting/power | Q11: Network Eng / OSP
B12: 8. CPE & ONTs | C12: 600000 | D12: =C12/10000000 | E12: =ROUND($C12*Assumptions!E29,0) | F12: =ROUND($C12*Assumptions!F29,0) | G12: =ROUND($C12*Assumptions!G29,0) | H12: =ROUND($C12*Assumptions!H29,0) | I12: =ROUND($C12*Assumptions!I29,0) | J12: =SUM(E12:I12) | K12: 7 | L12: Customer ONTs, routers, Wi-Fi | M12: In-home service delivery | N12: Per-sub install; equipment fees | O12: Demand-led | P12: Install labor | Q12: Field Operations
B13: 9. Vehicles & fleet | C13: 250000 | D13: =C13/10000000 | E13: =ROUND($C13*Assumptions!E29,0) | F13: =ROUND($C13*Assumptions!F29,0) | G13: =ROUND($C13*Assumptions!G29,0) | H13: =ROUND($C13*Assumptions!H29,0) | I13: =ROUND($C13*Assumptions!I29,0) | J13: =SUM(E13:I13) | K13: 7 | L13: Bucket/service trucks & vans | M13: Field workforce mobility | N13: Install & repair throughput | O13: Y1-Y2 fleet build | P13: Vehicle supply | Q13: Fleet / Facilities
B14: 10. Construction & maintenance equipment | C14: 280000 | D14: =C14/10000000 | E14: =ROUND($C14*Assumptions!E29,0) | F14: =ROUND($C14*Assumptions!F29,0) | G14: =ROUND($C14*Assumptions!G29,0) | H14: =ROUND($C14*Assumptions!H29,0) | I14: =ROUND($C14*Assumptions!I29,0) | J14: =SUM(E14:I14) | K14: 10 | L14: Splicers, locators, plows | M14: Construction & restoration capability | N14: Lowers contractor spend | O14: Y1-Y2 | P14: Procurement | Q14: Dir OSP
B15: 11. IT & cybersecurity | C15: 300000 | D15: =C15/10000000 | E15: =ROUND($C15*Assumptions!E29,0) | F15: =ROUND($C15*Assumptions!F29,0) | G15: =ROUND($C15*Assumptions!G29,0) | H15: =ROUND($C15*Assumptions!H29,0) | I15: =ROUND($C15*Assumptions!I29,0) | J15: =SUM(E15:I15) | K15: 5 | L15: Servers, security, endpoints | M15: IT & security posture | N15: Risk reduction; compliance | O15: Continuous | P15: Vendor roadmap | Q15: IT / CISO
B16: 12. OSS/BSS/CRM/billing/GIS/WFM systems | C16: 340000 | D16: =C16/10000000 | E16: =ROUND($C16*Assumptions!E29,0) | F16: =ROUND($C16*Assumptions!F29,0) | G16: =ROUND($C16*Assumptions!G29,0) | H16: =ROUND($C16*Assumptions!H29,0) | I16: =ROUND($C16*Assumptions!I29,0) | J16: =SUM(E16:I16) | K16: 5 | L16: Operating & billing systems | M16: Automation & data quality | N16: Lowers cost/sub; scales ops | O16: Y1-Y3 phased | P16: Integration effort | Q16: CIO / COO
B17: 13. Buildings, warehouses & facilities | C17: 230000 | D17: =C17/10000000 | E17: =ROUND($C17*Assumptions!E29,0) | F17: =ROUND($C17*Assumptions!F29,0) | G17: =ROUND($C17*Assumptions!G29,0) | H17: =ROUND($C17*Assumptions!H29,0) | I17: =ROUND($C17*Assumptions!I29,0) | J17: =SUM(E17:I17) | K17: 30 | L17: Warehouse & operational facilities | M17: Inventory & crew staging | N17: Operational efficiency | O17: As needed | P17: Site availability | Q17: Facilities
B18: 14. Emergency restoration & resiliency | C18: 200000 | D18: =C18/10000000 | E18: =ROUND($C18*Assumptions!E29,0) | F18: =ROUND($C18*Assumptions!F29,0) | G18: =ROUND($C18*Assumptions!G29,0) | H18: =ROUND($C18*Assumptions!H29,0) | I18: =ROUND($C18*Assumptions!I29,0) | J18: =SUM(E18:I18) | K18: 15 | L18: Spares, generators, redundancy | M18: Storm & outage resilience | N18: Protects revenue & SLA | O18: Ongoing reserve | P18: Risk assessment | Q18: Dir OSP / NOC
B19: 15. Annual equipment refresh program | C19: 400000 | D19: =C19/10000000 | E19: 400000 | F19: 400000 | G19: 400000 | H19: 400000 | I19: 400000 | J19: =SUM(E19:I19) | K19: 7 | L19: Lifecycle equipment refresh | M19: Prevents aging-plant failures | N19: Avoids emergency capex & churn | O19: $400K every year | P19: Lifecycle standards | Q19: COO / Network Eng
B20: 16. Capital contingency reserve | C20: 100000 | D20: =C20/10000000 | E20: =ROUND($C20*Assumptions!E29,0) | F20: =ROUND($C20*Assumptions!F29,0) | G20: =ROUND($C20*Assumptions!G29,0) | H20: =ROUND($C20*Assumptions!H29,0) | I20: =ROUND($C20*Assumptions!I29,0) | J20: =SUM(E20:I20) | K20: — | L20: Unallocated capital reserve | M20: Absorbs cost overruns | N20: Protects plan integrity | O20: Held/deployed as needed | P20: Governance approval | Q20: CFO
B21: TOTAL ALLOCATION | C21: =SUM(C5:C20) | D21: =C21/10000000 | E21: =SUM(E5:E20) | F21: =SUM(F5:F20) | G21: =SUM(G5:G20) | H21: =SUM(H5:H20) | I21: =SUM(I5:I20) | J21: =SUM(J5:J20)
B23: Capital available / year | E23: =IF(REFRESH_OUT="Outside $10M",10400000,10000000) | F23: =IF(REFRESH_OUT="Outside $10M",10400000,10000000) | G23: =IF(REFRESH_OUT="Outside $10M",10400000,10000000) | H23: =IF(REFRESH_OUT="Outside $10M",10400000,10000000) | I23: =IF(REFRESH_OUT="Outside $10M",10400000,10000000)
B24: Capital deployed | E24: =E21 | F24: =F21 | G24: =G21 | H24: =H21 | I24: =I21
B25: Uncommitted (reserve/carryforward) | E25: =E23-E24 | F25: =F23-F24 | G25: =G23-G24 | H25: =H23-H24 | I25: =I23-I24
B26: Cumulative capital deployed | E26: =E24 | F26: =E26+F24 | G26: =F26+G24 | H26: =G26+H24 | I26: =H26+I24
B28: CHECK: allocation = $10.0M (0=OK) | E28: =C21-10000000
B29: CHECK: refresh 5-yr = $2.0M (0=OK) | E29: =J19-2000000

Sheet Equipment Refresh
B1: Annual Equipment-Refresh Program — $400K/yr · $2M/5yr
B2: Committed lifecycle program. Base model: inside the $10M. Adjustable model: outside (+$400K). Never scaled by deployment pace.
B4: Refresh category | C4: Depr yrs | D4: 2027 | E4: 2028 | F4: 2029 | G4: 2030 | H4: 2031 | I4: 5-Yr $
B5: Core/aggregation switch & router refresh | C5: 6 | D5: =ROUND(400000*0.2,0) | E5: =ROUND(400000*0.2,0) | F5: =ROUND(400000*0.2,0) | G5: =ROUND(400000*0.2,0) | H5: =ROUND(400000*0.2,0) | I5: =SUM(D5:H5)
B6: OLT line-card & optics refresh | C6: 7 | D6: =ROUND(400000*0.16,0) | E6: =ROUND(400000*0.16,0) | F6: =ROUND(400000*0.16,0) | G6: =ROUND(400000*0.16,0) | H6: =ROUND(400000*0.16,0) | I6: =SUM(D6:H6)
B7: Field test equipment & OTDR refresh | C7: 5 | D7: =ROUND(400000*0.1,0) | E7: =ROUND(400000*0.1,0) | F7: =ROUND(400000*0.1,0) | G7: =ROUND(400000*0.1,0) | H7: =ROUND(400000*0.1,0) | I7: =SUM(D7:H7)
B8: Splicing & fusion equipment refresh | C8: 6 | D8: =ROUND(400000*0.1,0) | E8: =ROUND(400000*0.1,0) | F8: =ROUND(400000*0.1,0) | G8: =ROUND(400000*0.1,0) | H8: =ROUND(400000*0.1,0) | I8: =SUM(D8:H8)
B9: Fleet telematics & tool refresh | C9: 5 | D9: =ROUND(400000*0.08,0) | E9: =ROUND(400000*0.08,0) | F9: =ROUND(400000*0.08,0) | G9: =ROUND(400000*0.08,0) | H9: =ROUND(400000*0.08,0) | I9: =SUM(D9:H9)
B10: Server / storage / IT refresh | C10: 5 | D10: =ROUND(400000*0.12,0) | E10: =ROUND(400000*0.12,0) | F10: =ROUND(400000*0.12,0) | G10: =ROUND(400000*0.12,0) | H10: =ROUND(400000*0.12,0) | I10: =SUM(D10:H10)
B11: Network security appliance refresh | C11: 5 | D11: =ROUND(400000*0.1,0) | E11: =ROUND(400000*0.1,0) | F11: =ROUND(400000*0.1,0) | G11: =ROUND(400000*0.1,0) | H11: =ROUND(400000*0.1,0) | I11: =SUM(D11:H11)
B12: CPE swap pool (aged ONT/router) | C12: 7 | D12: =400000-(D5+D6+D7+D8+D9+D10+D11) | E12: =400000-(E5+E6+E7+E8+E9+E10+E11) | F12: =400000-(F5+F6+F7+F8+F9+F10+F11) | G12: =400000-(G5+G6+G7+G8+G9+G10+G11) | H12: =400000-(H5+H6+H7+H8+H9+H10+H11) | I12: =SUM(D12:H12)
B13: TOTAL REFRESH | D13: =SUM(D5:D12) | E13: =SUM(E5:E12) | F13: =SUM(F5:F12) | G13: =SUM(G5:G12) | H13: =SUM(H5:H12) | I13: =SUM(I5:I12)
B15: CHECK: each year = $400K (0=OK) | D15: =SUM(D13:H13)-2000000

Sheet Project ROI
B1: Project-Level ROI & Payback (Expansion Templates)
B2: Editable expansion-project calculator. Blue = inputs. Simple payback = capex ÷ annual gross margin. Add rows as needed.
B4: Project | C4: Passings | D4: Cost/passing $ | E4: Capex $ | F4: Take rate | G4: Subs @ maturity | H4: ARPU $/mo | I4: Annual revenue $ | J4: Gross margin % | K4: Annual margin $ | L4: Simple payback yrs
B5: Robeson Co. FTTH Phase 1 | C5: 2200 | D5: 1150 | E5: =C5*D5 | F5: 0.45 | G5: =C5*F5 | H5: 74 | I5: =G5*H5*12 | J5: 0.62 | K5: =I5*J5 | L5: =IF(K5>0,E5/K5,"n/a")
B6: Hoke Co. distribution build | C6: 1500 | D6: 1300 | E6: =C6*D6 | F6: 0.4 | G6: =C6*F6 | H6: 74 | I6: =G6*H6*12 | J6: 0.6 | K6: =I6*J6 | L6: =IF(K6>0,E6/K6,"n/a")
B7: Scotland Co. business corridor | C7: 180 | D7: 3200 | E7: =C7*D7 | F7: 0.55 | G7: =C7*F7 | H7: 149 | I7: =G7*H7*12 | J7: 0.68 | K7: =I7*J7 | L7: =IF(K7>0,E7/K7,"n/a")
B8: Cumberland edge FTTH | C8: 2600 | D8: 1250 | E8: =C8*D8 | F8: 0.42 | G8: =C8*F8 | H8: 74 | I8: =G8*H8*12 | J8: 0.61 | K8: =I8*J8 | L8: =IF(K8>0,E8/K8,"n/a")
B9: Enterprise dark-fiber IRU | C9: 6 | D9: 45000 | E9: =C9*D9 | F9: 1 | G9: =C9*F9 | H9: 2500 | I9: =G9*H9*12 | J9: 0.75 | K9: =I9*J9 | L9: =IF(K9>0,E9/K9,"n/a")

Sheet Income Statement
B1: Income Statement (2027-2031)
B2: EBITDA = Revenue − Operating Expense. Depreciation is a labeled placeholder pending fixed-asset detail.
B4: $ | C4: 2027 | D4: 2028 | E4: 2029 | F4: 2030 | G4: 2031 | H4: 5-Yr Total
B5: Total revenue | C5: ='Revenue Model'!C17 | D5: ='Revenue Model'!D17 | E5: ='Revenue Model'!E17 | F5: ='Revenue Model'!F17 | G5: ='Revenue Model'!G17 | H5: =SUM(C5:G5)
B6: Total operating expense | C6: ='Operating Expenses'!E31 | D6: ='Operating Expenses'!F31 | E6: ='Operating Expenses'!G31 | F6: ='Operating Expenses'!H31 | G6: ='Operating Expenses'!I31 | H6: =SUM(C6:G6)
B7: EBITDA | C7: =C5-C6 | D7: =D5-D6 | E7: =E5-E6 | F7: =F5-F6 | G7: =G5-G6 | H7: =SUM(C7:G7)
B8: EBITDA margin | C8: =C7/C5 | D8: =D7/D5 | E8: =E7/E5 | F8: =F7/F5 | G8: =G7/G5
B9: Depreciation — existing plant (placeholder) | C9: 2400000 | D9: 2400000 | E9: 2400000 | F9: 2400000 | G9: 2400000 | H9: =SUM(C9:G9)
B10: Depreciation — new capex (12-yr composite, ½-yr) | C10: ='Capital Plan'!E24/12*0.5 | D10: ='Capital Plan'!E26/12+'Capital Plan'!F24/12*0.5 | E10: ='Capital Plan'!F26/12+'Capital Plan'!G24/12*0.5 | F10: ='Capital Plan'!G26/12+'Capital Plan'!H24/12*0.5 | G10: ='Capital Plan'!H26/12+'Capital Plan'!I24/12*0.5 | H10: =SUM(C10:G10)
B11: Total depreciation & amortization | C11: =C9+C10 | D11: =D9+D10 | E11: =E9+E10 | F11: =F9+F10 | G11: =G9+G10 | H11: =SUM(C11:G11)
B12: Operating income (EBIT) | C12: =C7-C11 | D12: =D7-D11 | E12: =E7-E11 | F12: =F7-F11 | G12: =G7-G11 | H12: =SUM(C12:G12)
B14: Note: LLC pass-through; no entity income tax modeled (placeholder).

Sheet Cash Flow
B1: Cash-Flow & Capital-Funding Schedule (2027-2031)
B2: FCF before financing = EBITDA − Capex. The $50M capital program funds the build; cumulative cash requirement stays within available funding.
B4: $ | C4: 2027 | D4: 2028 | E4: 2029 | F4: 2030 | G4: 2031 | H4: 5-Yr Total
B5: EBITDA | C5: ='Income Statement'!C7 | D5: ='Income Statement'!D7 | E5: ='Income Statement'!E7 | F5: ='Income Statement'!F7 | G5: ='Income Statement'!G7 | H5: =SUM(C5:G5)
B6: Less: Capital expenditures | C6: =-'Capital Plan'!E24 | D6: =-'Capital Plan'!F24 | E6: =-'Capital Plan'!G24 | F6: =-'Capital Plan'!H24 | G6: =-'Capital Plan'!I24 | H6: =SUM(C6:G6)
B7: Free cash flow before financing | C7: =C5+C6 | D7: =D5+D6 | E7: =E5+E6 | F7: =F5+F6 | G7: =G5+G6 | H7: =SUM(C7:G7)
B8: Cumulative cash requirement | C8: =C7 | D8: =C8+D7 | E8: =D8+E7 | F8: =E8+F7 | G8: =F8+G7
B10: Capital funding available | C10: ='Capital Plan'!E23 | D10: ='Capital Plan'!F23 | E10: ='Capital Plan'!G23 | F10: ='Capital Plan'!H23 | G10: ='Capital Plan'!I23 | H10: =SUM(C10:G10)
B11: Capital funding used | C11: ='Capital Plan'!E24 | D11: ='Capital Plan'!F24 | E11: ='Capital Plan'!G24 | F11: ='Capital Plan'!H24 | G11: ='Capital Plan'!I24 | H11: =SUM(C11:G11)
B12: Capital funding remaining | C12: ='Capital Plan'!E25 | D12: ='Capital Plan'!F25 | E12: ='Capital Plan'!G25 | F12: ='Capital Plan'!H25 | G12: ='Capital Plan'!I25 | H12: =SUM(C12:G12)
B14: BREAK-EVEN ANALYSIS
B15: EBITDA-positive from | C15: 2027 (Year 1)
B16: FCF-positive year (before financing) | C16: Beyond plan horizon — sustained build capex
B17: Approx. EBITDA break-even subs (Yr-1 cost base) | C17: See KPI tab

Sheet KPI Dashboard
B1: Operational & Financial KPI Dashboard
B2: All values computed live from model tabs. Orange = placeholder targets pending actual operating data.
B4: KPI | C4: Unit | D4: 2027 | E4: 2028 | F4: 2029 | G4: 2030 | H4: 2031
B5: Beginning subscribers (internet) | C5: subs | D5: ='Subscriber Forecast'!C50 | E5: ='Subscriber Forecast'!D50 | F5: ='Subscriber Forecast'!E50 | G5: ='Subscriber Forecast'!F50 | H5: ='Subscriber Forecast'!G50
B6: Ending subscribers (internet) | C6: subs | D6: ='Subscriber Forecast'!C49 | E6: ='Subscriber Forecast'!D49 | F6: ='Subscriber Forecast'!E49 | G6: ='Subscriber Forecast'!F49 | H6: ='Subscriber Forecast'!G49
B7: Gross additions | C7: subs | D7: ='Subscriber Forecast'!C51 | E7: ='Subscriber Forecast'!D51 | F7: ='Subscriber Forecast'!E51 | G7: ='Subscriber Forecast'!F51 | H7: ='Subscriber Forecast'!G51
B8: Net additions | C8: subs | D8: ='Subscriber Forecast'!C53 | E8: ='Subscriber Forecast'!D53 | F8: ='Subscriber Forecast'!E53 | G8: ='Subscriber Forecast'!F53 | H8: ='Subscriber Forecast'!G53
B9: Churn (monthly, blended) | C9: % | D9: ='Subscriber Forecast'!C52/(('Subscriber Forecast'!C50+'Subscriber Forecast'!C49)/2)/12 | E9: ='Subscriber Forecast'!D52/(('Subscriber Forecast'!D50+'Subscriber Forecast'!D49)/2)/12 | F9: ='Subscriber Forecast'!E52/(('Subscriber Forecast'!E50+'Subscriber Forecast'!E49)/2)/12 | G9: ='Subscriber Forecast'!F52/(('Subscriber Forecast'!F50+'Subscriber Forecast'!F49)/2)/12 | H9: ='Subscriber Forecast'!G52/(('Subscriber Forecast'!G50+'Subscriber Forecast'!G49)/2)/12
B10: Blended ARPU (recurring) | C10: $/mo | D10: ='Revenue Model'!C15/(('Subscriber Forecast'!C50+'Subscriber Forecast'!C49)/2+('Subscriber Forecast'!C45+'Subscriber Forecast'!C48)/2)/12 | E10: ='Revenue Model'!D15/(('Subscriber Forecast'!D50+'Subscriber Forecast'!D49)/2+('Subscriber Forecast'!D45+'Subscriber Forecast'!D48)/2)/12 | F10: ='Revenue Model'!E15/(('Subscriber Forecast'!E50+'Subscriber Forecast'!E49)/2+('Subscriber Forecast'!E45+'Subscriber Forecast'!E48)/2)/12 | G10: ='Revenue Model'!F15/(('Subscriber Forecast'!F50+'Subscriber Forecast'!F49)/2+('Subscriber Forecast'!F45+'Subscriber Forecast'!F48)/2)/12 | H10: ='Revenue Model'!G15/(('Subscriber Forecast'!G50+'Subscriber Forecast'!G49)/2+('Subscriber Forecast'!G45+'Subscriber Forecast'!G48)/2)/12
B11: Homes & businesses passed | C11: HP+BP | D11: =((Assumptions!E25+SUM(Assumptions!E27:E27))+(Assumptions!E26+SUM(Assumptions!E28:E28))) | E11: =((Assumptions!E25+SUM(Assumptions!E27:F27))+(Assumptions!E26+SUM(Assumptions!E28:F28))) | F11: =((Assumptions!E25+SUM(Assumptions!E27:G27))+(Assumptions!E26+SUM(Assumptions!E28:G28))) | G11: =((Assumptions!E25+SUM(Assumptions!E27:H27))+(Assumptions!E26+SUM(Assumptions!E28:H28))) | H11: =((Assumptions!E25+SUM(Assumptions!E27:I27))+(Assumptions!E26+SUM(Assumptions!E28:I28)))
B12: Take rate | C12: % | D12: ='Subscriber Forecast'!C49/((Assumptions!E25+SUM(Assumptions!E27:E27))+(Assumptions!E26+SUM(Assumptions!E28:E28))) | E12: ='Subscriber Forecast'!D49/((Assumptions!E25+SUM(Assumptions!E27:F27))+(Assumptions!E26+SUM(Assumptions!E28:F28))) | F12: ='Subscriber Forecast'!E49/((Assumptions!E25+SUM(Assumptions!E27:G27))+(Assumptions!E26+SUM(Assumptions!E28:G28))) | G12: ='Subscriber Forecast'!F49/((Assumptions!E25+SUM(Assumptions!E27:H27))+(Assumptions!E26+SUM(Assumptions!E28:H28))) | H12: ='Subscriber Forecast'!G49/((Assumptions!E25+SUM(Assumptions!E27:I27))+(Assumptions!E26+SUM(Assumptions!E28:I28)))
B13: Revenue per passing | C13: $ | D13: ='Revenue Model'!C17/((Assumptions!E25+SUM(Assumptions!E27:E27))+(Assumptions!E26+SUM(Assumptions!E28:E28))) | E13: ='Revenue Model'!D17/((Assumptions!E25+SUM(Assumptions!E27:F27))+(Assumptions!E26+SUM(Assumptions!E28:F28))) | F13: ='Revenue Model'!E17/((Assumptions!E25+SUM(Assumptions!E27:G27))+(Assumptions!E26+SUM(Assumptions!E28:G28))) | G13: ='Revenue Model'!F17/((Assumptions!E25+SUM(Assumptions!E27:H27))+(Assumptions!E26+SUM(Assumptions!E28:H28))) | H13: ='Revenue Model'!G17/((Assumptions!E25+SUM(Assumptions!E27:I27))+(Assumptions!E26+SUM(Assumptions!E28:I28)))
B14: Capital cost per passing | C14: $ | D14: ='Capital Plan'!E24/(Assumptions!E27+Assumptions!E28) | E14: ='Capital Plan'!F24/(Assumptions!F27+Assumptions!F28) | F14: ='Capital Plan'!G24/(Assumptions!G27+Assumptions!G28) | G14: ='Capital Plan'!H24/(Assumptions!H27+Assumptions!H28) | H14: ='Capital Plan'!I24/(Assumptions!I27+Assumptions!I28)
B15: Capital cost per net new customer | C15: $ | D15: ='Capital Plan'!E24/'Subscriber Forecast'!C53 | E15: ='Capital Plan'!F24/'Subscriber Forecast'!D53 | F15: ='Capital Plan'!G24/'Subscriber Forecast'!E53 | G15: ='Capital Plan'!H24/'Subscriber Forecast'!F53 | H15: ='Capital Plan'!I24/'Subscriber Forecast'!G53
B16: Customer acquisition cost (CAC) | C16: $ | D16: =('Operating Expenses'!E12+'Operating Expenses'!E13)/'Subscriber Forecast'!C51 | E16: =('Operating Expenses'!F12+'Operating Expenses'!F13)/'Subscriber Forecast'!D51 | F16: =('Operating Expenses'!G12+'Operating Expenses'!G13)/'Subscriber Forecast'!E51 | G16: =('Operating Expenses'!H12+'Operating Expenses'!H13)/'Subscriber Forecast'!F51 | H16: =('Operating Expenses'!I12+'Operating Expenses'!I13)/'Subscriber Forecast'!G51
B17: Average installation cost | C17: $ | D17: 625 | E17: 610 | F17: 595 | G17: 585 | H17: 575
B18: Average trouble-ticket cost | C18: $ | D18: 78 | E18: 76 | F18: 74 | G18: 72 | H18: 70
B19: Revenue per employee | C19: $ | D19: ='Revenue Model'!C17/Assumptions!E41 | E19: ='Revenue Model'!D17/Assumptions!F41 | F19: ='Revenue Model'!E17/Assumptions!G41 | G19: ='Revenue Model'!F17/Assumptions!H41 | H19: ='Revenue Model'!G17/Assumptions!I41
B20: Subscribers per employee | C20: subs | D20: ='Subscriber Forecast'!C49/Assumptions!E41 | E20: ='Subscriber Forecast'!D49/Assumptions!F41 | F20: ='Subscriber Forecast'!E49/Assumptions!G41 | G20: ='Subscriber Forecast'!F49/Assumptions!H41 | H20: ='Subscriber Forecast'!G49/Assumptions!I41
B21: Subscribers per technician | C21: subs | D21: ='Subscriber Forecast'!C49/MAX(7,ROUND(Assumptions!E41*0.42,0)) | E21: ='Subscriber Forecast'!D49/MAX(7,ROUND(Assumptions!F41*0.42,0)) | F21: ='Subscriber Forecast'!E49/MAX(7,ROUND(Assumptions!G41*0.42,0)) | G21: ='Subscriber Forecast'!F49/MAX(7,ROUND(Assumptions!H41*0.42,0)) | H21: ='Subscriber Forecast'!G49/MAX(7,ROUND(Assumptions!I41*0.42,0))
B22: Overtime % | C22: % | D22: 0.1 | E22: 0.09 | F22: 0.08 | G22: 0.08 | H22: 0.07
B23: Network availability | C23: % | D23: 0.9985 | E23: 0.9985 | F23: 0.9985 | G23: 0.9985 | H23: 0.9985
B24: Average installation interval | C24: days | D24: 9 | E24: 8 | F24: 7 | G24: 7 | H24: 6
B25: Trouble-ticket repeat rate | C25: % | D25: 0.09 | E25: 0.08 | F25: 0.07 | G25: 0.065 | H25: 0.06
B26: EBITDA per subscriber | C26: $/yr | D26: ='Income Statement'!C7/(('Subscriber Forecast'!C50+'Subscriber Forecast'!C49)/2) | E26: ='Income Statement'!D7/(('Subscriber Forecast'!D50+'Subscriber Forecast'!D49)/2) | F26: ='Income Statement'!E7/(('Subscriber Forecast'!E50+'Subscriber Forecast'!E49)/2) | G26: ='Income Statement'!F7/(('Subscriber Forecast'!F50+'Subscriber Forecast'!F49)/2) | H26: ='Income Statement'!G7/(('Subscriber Forecast'!G50+'Subscriber Forecast'!G49)/2)
B27: Operating cost per subscriber | C27: $/yr | D27: ='Operating Expenses'!E31/(('Subscriber Forecast'!C50+'Subscriber Forecast'!C49)/2) | E27: ='Operating Expenses'!F31/(('Subscriber Forecast'!D50+'Subscriber Forecast'!D49)/2) | F27: ='Operating Expenses'!G31/(('Subscriber Forecast'!E50+'Subscriber Forecast'!E49)/2) | G27: ='Operating Expenses'!H31/(('Subscriber Forecast'!F50+'Subscriber Forecast'!F49)/2) | H27: ='Operating Expenses'!I31/(('Subscriber Forecast'!G50+'Subscriber Forecast'!G49)/2)
B28: EBITDA margin | C28: % | D28: ='Income Statement'!C7/'Revenue Model'!C17 | E28: ='Income Statement'!D7/'Revenue Model'!D17 | F28: ='Income Statement'!E7/'Revenue Model'!E17 | G28: ='Income Statement'!F7/'Revenue Model'!F17 | H28: ='Income Statement'!G7/'Revenue Model'!G17
B29: Payback period by expansion project | C29: yrs | D29: See Project ROI tab

Sheet Sensitivity Analysis
B1: Sensitivity Analysis (Year-5 impact, live)
B2: Each table flexes ONE driver, holding others at the active scenario. Exact where linear; contribution-margin approximations are labeled.
B5: Contribution margin on incremental subs (input) | C5: 0.75
B7: 1) ARPU sensitivity → Year-5 EBITDA (exact)
B8: ARPU factor | C8: 0.9 | D8: 0.95 | E8: 1 | F8: 1.05 | G8: 1.1
B9: Year-5 result | C9: ='Income Statement'!G7+(0.9-1)*('Revenue Model'!G5+'Revenue Model'!G6+'Revenue Model'!G7+'Revenue Model'!G8) | D9: ='Income Statement'!G7+(0.95-1)*('Revenue Model'!G5+'Revenue Model'!G6+'Revenue Model'!G7+'Revenue Model'!G8) | E9: ='Income Statement'!G7+(1.0-1)*('Revenue Model'!G5+'Revenue Model'!G6+'Revenue Model'!G7+'Revenue Model'!G8) | F9: ='Income Statement'!G7+(1.05-1)*('Revenue Model'!G5+'Revenue Model'!G6+'Revenue Model'!G7+'Revenue Model'!G8) | G9: ='Income Statement'!G7+(1.1-1)*('Revenue Model'!G5+'Revenue Model'!G6+'Revenue Model'!G7+'Revenue Model'!G8)
B11: 2) Labor cost sensitivity → Year-5 EBITDA (exact)
B12: Labor factor | C12: 0.9 | D12: 0.95 | E12: 1 | F12: 1.05 | G12: 1.1
B13: Year-5 result | C13: ='Income Statement'!G7-(0.9-1)*'Fully Loaded Labor Cost'!G32 | D13: ='Income Statement'!G7-(0.95-1)*'Fully Loaded Labor Cost'!G32 | E13: ='Income Statement'!G7-(1.0-1)*'Fully Loaded Labor Cost'!G32 | F13: ='Income Statement'!G7-(1.05-1)*'Fully Loaded Labor Cost'!G32 | G13: ='Income Statement'!G7-(1.1-1)*'Fully Loaded Labor Cost'!G32
B15: 3) Churn sensitivity → Year-5 EBITDA (approx.)
B16: Churn Δ (pts) | C16: -0.02 | D16: -0.01 | E16: 0 | F16: 0.01 | G16: 0.02
B17: Year-5 result | C17: ='Income Statement'!G7-(-0.02)*'Subscriber Forecast'!G49*(('Revenue Model'!G5+'Revenue Model'!G6+'Revenue Model'!G7+'Revenue Model'!G8)/'Subscriber Forecast'!G49)*$C$5 | D17: ='Income Statement'!G7-(-0.01)*'Subscriber Forecast'!G49*(('Revenue Model'!G5+'Revenue Model'!G6+'Revenue Model'!G7+'Revenue Model'!G8)/'Subscriber Forecast'!G49)*$C$5 | E17: ='Income Statement'!G7-(0.0)*'Subscriber Forecast'!G49*(('Revenue Model'!G5+'Revenue Model'!G6+'Revenue Model'!G7+'Revenue Model'!G8)/'Subscriber Forecast'!G49)*$C$5 | F17: ='Income Statement'!G7-(0.01)*'Subscriber Forecast'!G49*(('Revenue Model'!G5+'Revenue Model'!G6+'Revenue Model'!G7+'Revenue Model'!G8)/'Subscriber Forecast'!G49)*$C$5 | G17: ='Income Statement'!G7-(0.02)*'Subscriber Forecast'!G49*(('Revenue Model'!G5+'Revenue Model'!G6+'Revenue Model'!G7+'Revenue Model'!G8)/'Subscriber Forecast'!G49)*$C$5
B18: Approx: Δchurn × ending subs × blended annual rev × contribution margin.
B20: 4) Take-rate sensitivity → Year-5 EBITDA (approx.)
B21: Take Δ (pts) | C21: -0.05 | D21: -0.025 | E21: 0 | F21: 0.025 | G21: 0.05
B22: Year-5 result | C22: ='Income Statement'!G7+(-0.05)*((Assumptions!E25+SUM(Assumptions!E27:I27))+(Assumptions!E26+SUM(Assumptions!E28:I28)))*(('Revenue Model'!G5+'Revenue Model'!G6+'Revenue Model'!G7+'Revenue Model'!G8)/'Subscriber Forecast'!G49)*$C$5 | D22: ='Income Statement'!G7+(-0.025)*((Assumptions!E25+SUM(Assumptions!E27:I27))+(Assumptions!E26+SUM(Assumptions!E28:I28)))*(('Revenue Model'!G5+'Revenue Model'!G6+'Revenue Model'!G7+'Revenue Model'!G8)/'Subscriber Forecast'!G49)*$C$5 | E22: ='Income Statement'!G7+(0.0)*((Assumptions!E25+SUM(Assumptions!E27:I27))+(Assumptions!E26+SUM(Assumptions!E28:I28)))*(('Revenue Model'!G5+'Revenue Model'!G6+'Revenue Model'!G7+'Revenue Model'!G8)/'Subscriber Forecast'!G49)*$C$5 | F22: ='Income Statement'!G7+(0.025)*((Assumptions!E25+SUM(Assumptions!E27:I27))+(Assumptions!E26+SUM(Assumptions!E28:I28)))*(('Revenue Model'!G5+'Revenue Model'!G6+'Revenue Model'!G7+'Revenue Model'!G8)/'Subscriber Forecast'!G49)*$C$5 | G22: ='Income Statement'!G7+(0.05)*((Assumptions!E25+SUM(Assumptions!E27:I27))+(Assumptions!E26+SUM(Assumptions!E28:I28)))*(('Revenue Model'!G5+'Revenue Model'!G6+'Revenue Model'!G7+'Revenue Model'!G8)/'Subscriber Forecast'!G49)*$C$5
B23: Approx: Δtake × passings × blended annual rev × contribution margin.
B25: 5) New subs/month sensitivity → Year-5 EBITDA (approx.)
B26: Δ subs/month | C26: -50 | D26: -25 | E26: 0 | F26: 25 | G26: 50
B27: Year-5 result | C27: ='Income Statement'!G7+(-50)*12*(('Revenue Model'!G5+'Revenue Model'!G6+'Revenue Model'!G7+'Revenue Model'!G8)/'Subscriber Forecast'!G49)*$C$5 | D27: ='Income Statement'!G7+(-25)*12*(('Revenue Model'!G5+'Revenue Model'!G6+'Revenue Model'!G7+'Revenue Model'!G8)/'Subscriber Forecast'!G49)*$C$5 | E27: ='Income Statement'!G7+(0)*12*(('Revenue Model'!G5+'Revenue Model'!G6+'Revenue Model'!G7+'Revenue Model'!G8)/'Subscriber Forecast'!G49)*$C$5 | F27: ='Income Statement'!G7+(25)*12*(('Revenue Model'!G5+'Revenue Model'!G6+'Revenue Model'!G7+'Revenue Model'!G8)/'Subscriber Forecast'!G49)*$C$5 | G27: ='Income Statement'!G7+(50)*12*(('Revenue Model'!G5+'Revenue Model'!G6+'Revenue Model'!G7+'Revenue Model'!G8)/'Subscriber Forecast'!G49)*$C$5
B28: Approx: Δ monthly adds × 12 × blended annual rev × contribution margin.
B30: 6) Construction cost/passing → passings buildable w/ 5-yr capex
B31: Cost/passing $ | C31: 1000 | D31: 1100 | E31: 1200 | F31: 1300 | G31: 1400
B32: Year-5 result | C32: ='Capital Plan'!J21/1000 | D32: ='Capital Plan'!J21/1100 | E32: ='Capital Plan'!J21/1200 | F32: ='Capital Plan'!J21/1300 | G32: ='Capital Plan'!J21/1400
B33: 5-Yr deployed capital ÷ cost per passing = passings the program can build.
B35: 7) Capital deployment rate → 5-yr capital deployed
B36: Deploy % | C36: 0.85 | D36: 0.9 | E36: 0.95 | F36: 1 | G36: 1
B37: Year-5 result | C37: =MIN(0.85,1)*10000000*5 | D37: =MIN(0.9,1)*10000000*5 | E37: =MIN(0.95,1)*10000000*5 | F37: =MIN(1.0,1)*10000000*5 | G37: =MIN(1.0,1)*10000000*5
B38: Illustrative: uniform deployment fraction × $10M × 5 years.

Sheet Risk Register
B1: Five-Year Risk Register
B2: Probability × Impact = Score (1-5 scale each; score 1-25). Owner and mitigation named for every risk.
B4: # | C4: Risk | D4: Category | E4: Prob (1-5) | F4: Impact (1-5) | G4: Score | H4: Tier | I4: Owner | J4: Mitigation strategy
B5: 1 | C5: Construction-cost inflation | D5: Financial | E5: 4 | F5: 4 | G5: =E5*F5 | H5: =IF(G5>=16,"High",IF(G5>=9,"Medium","Low")) | I5: CFO / Dir OSP | J5: Fixed-price contracts; escalators; value-engineer routes; contingency reserve
B6: 2 | C6: Material availability (fiber/ONT) | D6: Supply | E6: 3 | F6: 4 | G6: =E6*F6 | H6: =IF(G6>=16,"High",IF(G6>=9,"Medium","Low")) | I6: Procurement | J6: Multi-vendor sourcing; safety stock; forward POs; refresh pool
B7: 3 | C7: Contractor performance | D7: Operations | E7: 3 | F7: 4 | G7: =E7*F7 | H7: =IF(G7>=16,"High",IF(G7>=9,"Medium","Low")) | I7: Dir OSP | J7: Qualified vendor list; SLAs; QA inspection; in-house splicing capacity
B8: 4 | C8: Grant compliance / clawback | D8: Regulatory | E8: 3 | F8: 5 | G8: =E8*F8 | H8: =IF(G8>=16,"High",IF(G8>=9,"Medium","Low")) | I8: CFO / Grants Mgr | J8: Compliance calendar; documentation; inspector role; audit readiness
B9: 5 | C9: Workforce shortages | D9: People | E9: 4 | F9: 4 | G9: =E9*F9 | H9: =IF(G9>=16,"High",IF(G9>=9,"Medium","Low")) | I9: COO / HR | J9: Trigger-based hiring; apprenticeships; retention comp; cross-training
B10: 6 | C10: Subscriber growth below forecast | D10: Market | E10: 3 | F10: 5 | G10: =E10*F10 | H10: =IF(G10>=16,"High",IF(G10>=9,"Medium","Low")) | I10: VP Sales | J10: Take-rate campaigns; scenario planning; pace capex to demand
B11: 7 | C11: Elevated churn | D11: Market | E11: 3 | F11: 4 | G11: =E11*F11 | H11: =IF(G11>=16,"High",IF(G11>=9,"Medium","Low")) | I11: CX Manager | J11: Retention programs; service quality; contract terms; win-back
B12: 8 | C12: Competitive pricing / overbuild | D12: Market | E12: 3 | F12: 4 | G12: =E12*F12 | H12: =IF(G12>=16,"High",IF(G12>=9,"Medium","Low")) | I12: CEO / VP Sales | J12: Differentiate on reliability & local service; targeted retention
B13: 9 | C13: Technology obsolescence | D13: Technical | E13: 2 | F13: 3 | G13: =E13*F13 | H13: =IF(G13>=16,"High",IF(G13>=9,"Medium","Low")) | I13: Network Eng | J13: Lifecycle refresh program; standards-based platforms; roadmaps
B14: 10 | C14: Equipment failure | D14: Technical | E14: 3 | F14: 4 | G14: =E14*F14 | H14: =IF(G14>=16,"High",IF(G14>=9,"Medium","Low")) | I14: Network Eng | J14: Redundancy; spares; refresh program; monitoring
B15: 11 | C15: Cybersecurity breach | D15: Security | E15: 3 | F15: 5 | G15: =E15*F15 | H15: =IF(G15>=16,"High",IF(G15>=9,"Medium","Low")) | I15: IT / CISO | J15: Defense-in-depth; MFA; backups; IR plan; security capex
B16: 12 | C16: Network outages | D16: Operations | E16: 3 | F16: 5 | G16: =E16*F16 | H16: =IF(G16>=16,"High",IF(G16>=9,"Medium","Low")) | I16: NOC / Dir OSP | J16: Redundant paths; generators; NOC monitoring; restoration reserve
... B23: 19 | C23: Vendor concentration | D23: Supply | E23: 3 | F23: 3 | G23: =E23*F23 | H23: =IF(G23>=16,"High",IF(G23>=9,"Medium","Low")) | I23: Procurement | J23: Dual-source critical vendors; contractual protections
B24: Risks: 19 | Avg score | G24: =ROUND(AVERAGE(G5:G23),1)
