Workbook

Sheet Executive Dashboard
A1: RIVR Tech — Executive Dashboard
A2: Headline results — Expected scenario (live)
A3: v1.0 (Draft for Executive Review) | 2026-07-20 | LREMC Technologies, LLC d/b/a RIVR Tech | NOT LEGAL ADVICE
A4: LEGEND: | B4: User input | C4: Calculated | D4: Recommended | E4: Review / warning
A6: Cost per dispatch | C6: Annual dispatch expense | E6: Customer-caused dispatch cost
A7: ='Current State'!$B$9 | C7: ='Current State'!$B$10 | E7: ='Current State'!$B$11
A10: Net fee revenue (Yr 1) | C10: Protection margin (Yr 1) | E10: Deflection savings
A11: ='Fee Scenarios'!$B$13 | C11: ='Protection Plan'!$B$9 | E11: ='Three-Year Forecast'!$B$5
A14: Year 1 net effect | C14: Three-year net effect
A15: ='Three-Year Forecast'!$B$13 | C15: ='Three-Year Forecast'!$E$13
A18: Cost recovery of customer-caused dispatch cost: | C18: =('Fee Scenarios'!$B$13+'Protection Plan'!$B$9)/'Current State'!$B$11
A21: Chart Data (Scenario comparison)
A22: Scenario | B22: Net Fees | C22: Plan Margin | D22: Deflection | E22: Year 1 Net | F22: 3-Yr Net
A23: Low | B23: 52963 | C23: 99593 | D23: 86580 | E23: 100847 | F23: 521917
A24: Expected | B24: 97436 | C24: 142276 | D24: 144300 | E24: 245722 | F24: 978275
A25: High | B25: 142864 | C25: 256097 | D25: 259740 | E25: 520412 | F25: 1843546
A46: Protection Plan — Margin by Price Point
A47: Price | B47: Contribution Margin
A48: $7.99 | B48: 104150
A49: $9.99 | B49: 142276
A50: $12.99 | B50: 199466

Sheet Inputs
A1: RIVR Tech — Financial Model — Inputs
A2: Edit yellow cells. Everything else recalculates.
A3: v1.0 (Draft for Executive Review) | 2026-07-20 | LREMC Technologies, LLC d/b/a RIVR Tech | NOT LEGAL ADVICE
A4: LEGEND: | B4: User input | C4: Calculated | D4: Recommended | E4: Review / warning
A6: Input | B6: Value | C6: Unit | D6: Type | E6: Note
A7: Total customers | B7: 18500 | C7: count | D7: Assumption | E7: Assumption — replace with billing-system count.
A8: Residential customers | B8: 16900 | C8: count | D8: Assumption | E8: Assumption.
A9: Business customers | B9: 1600 | C9: count | D9: Assumption | E9: Assumption.
A10: Monthly trouble tickets | B10: 1850 | C10: count | D10: Assumption | E10: Assumption — replace with ticketing export.
A11: Remote-resolution rate | B11: 0.62 | C11: pct | D11: Assumption | E11: Assumption — baseline before program.
A12: Dispatch rate (of tickets) | B12: 0.38 | C12: pct | D12: Assumption | E12: Derived complement of remote resolution.
A13: Customer-caused % of dispatches | B13: 0.3 | C13: pct | D13: Assumption | E13: Assumption — validate from historical dispositions.
A14: Billable % of customer-caused | B14: 0.62 | C14: pct | D14: Assumption | E14: After inconclusive/shared/courtesy removals.
A15: Average billable visit duration (hr) | B15: 0.75 | C15: hours | D15: Assumption | E15: 45 minutes on site.
A16: Loaded technician hourly cost | B16: 68 | C16: usd | D16: Assumption | E16: Wages + benefits + burden.
A17: Avg travel time per dispatch (hr) | B17: 0.5 | C17: hours | D17: Assumption | E17: Windshield time per truck roll.
A18: Vehicle cost per visit | B18: 22 | C18: usd | D18: Assumption | E18: Depreciation + maintenance allocation.
... A38: Billing-system configuration (one-time) | B38: 30000 | C38: usd | D38: Assumption | E38: Codes, disclosures, portal.

Sheet Current State
A1: RIVR Tech — Current State (No Program)
A2: Today's cost of the free-visit model
A3: v1.0 (Draft for Executive Review) | 2026-07-20 | LREMC Technologies, LLC d/b/a RIVR Tech | NOT LEGAL ADVICE
A4: Annual trouble tickets | B4: =Inputs!$B$10*12
A5: Annual dispatches | B5: ='Current State'!B4*Inputs!$B$12
A6: Remote-resolved tickets | B6: ='Current State'!B4*Inputs!$B$11
A7: Customer-caused dispatches | B7: ='Current State'!B5*Inputs!$B$13
A8: Labor per dispatch | B8: =(Inputs!$B$15+Inputs!$B$17)*Inputs!$B$16
A9: Cost per dispatch (loaded) | B9: ='Current State'!B8+Inputs!$B$18+Inputs!$B$19+Inputs!$B$20+Inputs!$B$21
A10: Annual dispatch expense | B10: ='Current State'!B5*'Current State'!B9
A11: Annual customer-caused dispatch cost | B11: ='Current State'!B7*'Current State'!B9
A13: The customer-caused dispatch cost is what the program aims to partly recover.

Sheet Fee Scenarios
A1: RIVR Tech — Fee Scenarios
A2: Gross and net trouble-visit fee revenue
A3: v1.0 (Draft for Executive Review) | 2026-07-20 | LREMC Technologies, LLC d/b/a RIVR Tech | NOT LEGAL ADVICE
A4: Billable visits (customer-caused x billable %) | B4: ='Current State'!$B$7*Inputs!$B$14
A5: Residential billable visits | B5: ='Fee Scenarios'!B4*(Inputs!$B$8/Inputs!$B$7)
A6: Business billable visits | B6: ='Fee Scenarios'!B4*(Inputs!$B$9/Inputs!$B$7)
A7: Gross fee revenue (visits) | B7: ='Fee Scenarios'!B5*Inputs!$B$22+'Fee Scenarios'!B6*Inputs!$B$23
A8: Ancillary fees (gross) | B8: =Inputs!$B$27
A9: Total gross fee revenue | B9: ='Fee Scenarios'!B7+'Fee Scenarios'!B8
A10: Less waivers | B10: =-'Fee Scenarios'!B9*Inputs!$B$25
A11: Less bad debt | B11: =-('Fee Scenarios'!B9+'Fee Scenarios'!B10)*Inputs!$B$26
A12: Net billable (after waivers & bad debt) | B12: ='Fee Scenarios'!B9+'Fee Scenarios'!B10+'Fee Scenarios'!B11
A13: Net fee revenue (x collection rate) | B13: ='Fee Scenarios'!B12*Inputs!$B$24

Sheet Protection Plan
A1: RIVR Tech — Protection Plan
A2: Optional maintenance-protection economics
A3: v1.0 (Draft for Executive Review) | 2026-07-20 | LREMC Technologies, LLC d/b/a RIVR Tech | NOT LEGAL ADVICE
A4: Enrolled members (of residential) | B4: =Inputs!$B$8*Inputs!$B$29
A5: Annual plan revenue | B5: ='Protection Plan'!B4*Inputs!$B$28*12
A6: Covered service events/year | B6: ='Protection Plan'!B4*Inputs!$B$30
A7: Plan service cost | B7: ='Protection Plan'!B6*Inputs!$B$31
A8: Plan admin cost | B8: ='Protection Plan'!B5*Inputs!$B$32
A9: Contribution margin | B9: ='Protection Plan'!B5-'Protection Plan'!B7-'Protection Plan'!B8
A10: Margin per member (annual) | B10: =IF('Protection Plan'!B4=0,0,'Protection Plan'!B9/'Protection Plan'!B4)
A11: Break-even monthly price | B11: =(Inputs!$B$30*Inputs!$B$31)/(12*(1-Inputs!$B$32))
A12: Break-even enrollment (members to cover admin at $0 usage) | B12: =0
A14: Price-Point Comparison
A15: Monthly Price | B15: Annual Revenue | C15: Contribution Margin | D15: Margin/Member
A16: $7.99 | B16: 162037.2 | C16: 104149.97 | D16: 61.6272
A17: $9.99 | B17: 202597.2 | C17: 142276.37 | D17: 84.1872
A18: $12.99 | B18: 263437.2 | C18: 199465.97 | D18: 118.0272
A20: NOTE: Price-comparison values are static snapshots; the live cells above respond to Inputs.
A21: REVIEW: Confirm plan is a service plan, NOT insurance (legal/insurance review).

Sheet Three-Year Forecast
A1: RIVR Tech — Three-Year Forecast
A2: Net financial effect over three years
A3: v1.0 (Draft for Executive Review) | 2026-07-20 | LREMC Technologies, LLC d/b/a RIVR Tech | NOT LEGAL ADVICE
A4: Avoided dispatches (deflection) | B4: ='Current State'!$B$4*Inputs!$B$35
A5: Deflection savings | B5: ='Three-Year Forecast'!B4*'Current State'!$B$9
A6: Churn cost | B6: =Inputs!$B$7*Inputs!$B$33*Inputs!$B$34
A7: Annual recurring net (fees+plan+deflection-churn) | B7: ='Fee Scenarios'!$B$13+'Protection Plan'!$B$9+'Three-Year Forecast'!B5-'Three-Year Forecast'!B6
A8: One-time cost | B8: =Inputs!$B$36+Inputs!$B$37+Inputs!$B$38
B10: Year 1 | C10: Year 2 | D10: Year 3 | E10: 3-Year Total
A11: Recurring net | B11: ='Three-Year Forecast'!B7 | C11: ='Three-Year Forecast'!B7*1.05 | D11: ='Three-Year Forecast'!B7*1.10
A12: Less one-time (Year 1) | B12: =-'Three-Year Forecast'!B8 | C12: 0 | D12: 0
A13: Net effect | B13: =SUM(B11:B12) | C13: =SUM(C11:C12) | D13: =SUM(D11:D12) | E13: =SUM(B13:D13)

Sheet Sensitivity Analysis
A1: RIVR Tech — Sensitivity Analysis
A2: How key drivers move net fee revenue & plan margin
A3: v1.0 (Draft for Executive Review) | 2026-07-20 | LREMC Technologies, LLC d/b/a RIVR Tech | NOT LEGAL ADVICE
A5: 1) Customer-caused % of dispatches -> Net fee revenue
A6: Cust-caused % | B6: 0.1 | C6: 0.15 | D6: 0.2 | E6: 0.25 | F6: 0.3 | G6: 0.35 | H6: 0.4
A7: Result | B7: 41081.213 | C7: 55169.895 | D7: 69258.576 | E7: 83347.258 | F7: 97435.939 | G7: 111524.62 | H7: 125613.3
A10: 2) Residential visit fee ($50-$100) -> Net fee revenue
A11: Res fee $ | B11: 50 | C11: 60 | D11: 70 | E11: 75 | F11: 80 | G11: 90 | H11: 100
A12: Result | B12: 70794.65 | C12: 81451.166 | D12: 92107.681 | E12: 97435.939 | F12: 102764.2 | G12: 113420.71 | H12: 124077.23
A15: 3) Protection-plan enrollment (5%-30%) -> Plan contribution margin
A16: Enrollment % | B16: 0.05 | C16: 0.1 | D16: 0.15 | E16: 0.2 | F16: 0.25 | G16: 0.3
A17: Result | B17: 71138.184 | C17: 142276.37 | D17: 213414.55 | E17: 284552.74 | F17: 355690.92 | G17: 426829.1
A20: 4) Remote-resolution improvement (5%-20%) -> Deflection savings
A21: Improvement pts | B21: 0.05 | C21: 0.08 | D21: 0.1 | E21: 0.12 | F21: 0.15 | G21: 0.2
A22: Result | B22: 144300 | C22: 230880 | D22: 288600 | E22: 346320 | F22: 432900 | G22: 577200
A25: Sensitivity tables are computed snapshots to illustrate driver impact; the Inputs sheet drives the live model.

Sheet KPI Definitions
A1: RIVR Tech — KPI Definitions
A2: How each metric is defined and measured
A3: v1.0 (Draft for Executive Review) | 2026-07-20 | LREMC Technologies, LLC d/b/a RIVR Tech | NOT LEGAL ADVICE
A5: KPI | B5: Definition | C5: Source
A6: Remote-resolution % | B6: Tickets closed without dispatch / total tickets. | C6: Ticketing
A7: Customer-premises issue % | B7: Dispatches classified as customer-premises / dispatches. | C7: Field disposition
A8: Billable visits | B8: Customer-premises visits with documented findings & disclosure. | C8: Billing
A9: Fees assessed / collected / waived | B9: Gross fees, collected fees, and waived fees. | C9: Billing / AR
A10: Waiver % | B10: Waived fees / assessed fees. | C10: Billing
A11: Dispute rate / approved disputes | B11: Disputes / billable visits; approved / disputes. | C11: CX
A12: Repeat visits (7/14/30 days) | B12: Repeat dispatches within window / dispatches. | C12: Ticketing
A13: Cost per dispatch | B13: Loaded labor + vehicle + fuel + materials + admin. | C13: Finance
A14: Avoided truck rolls | B14: Deflected dispatches from improved remote resolution. | C14: Ops
A15: Protection enrollment / revenue / cost | B15: Members, plan revenue, and plan service cost. | C15: Billing
A16: Policy-related churn | B16: Churn attributable to the policy. | C16: CX / Finance
... A18: Support disclosure compliance | B18: Tickets with proper advance disclosure / eligible. | C18: QA

Sheet Data Needed
A1: RIVR Tech — Data Needed
A2: Ten RIVR Tech data points to replace assumptions
A3: v1.0 (Draft for Executive Review) | 2026-07-20 | LREMC Technologies, LLC d/b/a RIVR Tech | NOT LEGAL ADVICE
A5: Data Point | B5: Why It Matters | C5: Source
A6: Total and segment customer counts | B6: Exact residential vs. business active-service counts. | C6: Billing system
A7: 12-month trouble-ticket volume | B7: Monthly tickets, dispatch rate, and remote-resolution rate. | C7: Ticketing / support platform
A8: Historical dispatch dispositions | B8: Share of dispatches that were customer-caused vs. network. | C8: Field/ops records
A9: Actual loaded technician cost | B9: Fully burdened hourly cost per field technician. | C9: Finance / HR
A10: True cost per truck roll | B10: Vehicle, fuel, materials, and admin per dispatch. | C10: Finance / Fleet
A11: Average and travel time per visit | B11: On-site plus windshield time per dispatch. | C11: Field ops
A12: Current collection & bad-debt rates | B12: Collection and write-off experience on customer charges. | C12: Finance / AR
A13: Protection-plan interest / benchmark | B13: Take-rate benchmark or survey for the optional plan. | C13: Marketing / CX
A14: Blended ARPU and churn baseline | B14: Revenue per customer and current churn for impact modeling. | C14: Finance
A15: Implementation and billing-config quotes | B15: Real quotes for billing changes, portal, and training. | C15: IT / Finance / Vendors
