Workbook

Sheet Exec_Dashboard
A1: EXECUTIVE DASHBOARD — COO One-Page View
A2: Regional Fiber Broadband • Weekly Executive Review • Red / Yellow / Green health • All values roll up automatically from the input tabs
B4: REPORTING CONTROLS
B5: Reporting Month ▶ | C5: Jun-2026 | D5: =MATCH(C5,Lists!$A$2:$A$13,0) | E5: (Period index — drives MTD / YTD / Rolling-12)
B7: COMPANY HEALTH — KPI SCORECARD (current reporting month)
B8: TOTAL CUSTOMERS | D8: NEW SALES (MTD) | F8: DISCONNECTS (MTD) | H8: NET ADDS (MTD) | J8: TAKE RATE
B9: =SUMIFS(Customer_Data!$C$4:$C$1003,Customer_Data!$A$4:$A$1003,Exec_Dashboard!$C$5) | D9: =SUMIFS(Customer_Data!$D$4:$D$1003,Customer_Data!$A$4:$A$1003,Exec_Dashboard!$C$5) | F9: =SUMIFS(Customer_Data!$E$4:$E$1003,Customer_Data!$A$4:$A$1003,Exec_Dashboard!$C$5) | H9: =SUMIFS(Customer_Data!$D$4:$D$1003,Customer_Data!$A$4:$A$1003,Exec_Dashboard!$C$5)-SUMIFS(Customer_Data!$E$4:$E$1003,Customer_Data!$A$4:$A$1003,Exec_Dashboard!$C$5) | J9: =IF(SUMIFS(Customer_Data!$F$4:$F$1003,Customer_Data!$A$4:$A$1003,Exec_Dashboard!$C$5)=0,0,SUMIFS(Customer_Data!$C$4:$C$1003,Customer_Data!$A$4:$A$1003,Exec_Dashboard!$C$5)/SUMIFS(Customer_Data!$F$4:$F$1003,Customer_Data!$A$4:$A$1003,Exec_Dashboard!$C$5))
B10: End-of-month subscribers | D10: =IF(D9>=SUMIFS(Sales_Targets!$C$4:$C$1003,Sales_Targets!$A$4:$A$1003,Exec_Dashboard!$C$5),"GREEN",IF(D9>=0.9*SUMIFS(Sales_Targets!$C$4:$C$1003,Sales_Targets!$A$4:$A$1003,Exec_Dashboard!$C$5),"YELLOW","RED")) | F10: =IF(F9<=0.02*SUMIFS(Customer_Data!$C$4:$C$1003,Customer_Data!$A$4:$A$1003,Exec_Dashboard!$C$5),"GREEN",IF(F9<=0.03*SUMIFS(Customer_Data!$C$4:$C$1003,Customer_Data!$A$4:$A$1003,Exec_Dashboard!$C$5),"YELLOW","RED")) | H10: =IF(H9>0,"GREEN",IF(H9=0,"YELLOW","RED")) | J10: =IF(J9>=0.35,"GREEN",IF(J9>=0.25,"YELLOW","RED"))
B13: REVENUE (MTD) | D13: ARPU | F13: MRR | H13: CHURN RATE | J13: HOMES PASSED
B14: =SUMIFS(Financial_Data!$C$4:$C$1003,Financial_Data!$A$4:$A$1003,Exec_Dashboard!$C$5) | D14: =IF(SUMIFS(Customer_Data!$C$4:$C$1003,Customer_Data!$A$4:$A$1003,Exec_Dashboard!$C$5)=0,0,SUMIFS(Financial_Data!$D$4:$D$1003,Financial_Data!$A$4:$A$1003,Exec_Dashboard!$C$5)/SUMIFS(Customer_Data!$C$4:$C$1003,Customer_Data!$A$4:$A$1003,Exec_Dashboard!$C$5)) | F14: =SUMIFS(Financial_Data!$D$4:$D$1003,Financial_Data!$A$4:$A$1003,Exec_Dashboard!$C$5) | H14: =IF(SUMIFS(Customer_Data!$C$4:$C$1003,Customer_Data!$B$4:$B$1003,Exec_Dashboard!$D$5-1)=0,0,SUMIFS(Customer_Data!$E$4:$E$1003,Customer_Data!$A$4:$A$1003,Exec_Dashboard!$C$5)/SUMIFS(Customer_Data!$C$4:$C$1003,Customer_Data!$B$4:$B$1003,Exec_Dashboard!$D$5-1)) | J14: =SUMIFS(Customer_Data!$F$4:$F$1003,Customer_Data!$A$4:$A$1003,Exec_Dashboard!$C$5)
B15: Total billed this month | D15: =IF(D14>=75,"GREEN",IF(D14>=65,"YELLOW","RED")) | F15: Monthly recurring revenue | H15: =IF(H14<=0.015,"GREEN",IF(H14<=0.025,"YELLOW","RED")) | J15: Cumulative passings
B18: ACTIVE PROJECTS | D18: PROJECTS BEHIND | F18: INSTALL BACKLOG | H18: AVG DAYS TO INSTALL | J18: TROUBLE TICKETS (MTD)
B19: =(COUNTIFS(Project_Data!$F$4:$F$1003,"On Track")+COUNTIFS(Project_Data!$F$4:$F$1003,"At Risk")+COUNTIFS(Project_Data!$F$4:$F$1003,"Behind")) | D19: =COUNTIFS(Project_Data!$F$4:$F$1003,"Behind") | F19: =SUMIFS(Operations_Data!$F$4:$F$1003,Operations_Data!$B$4:$B$1003,"<="&Exec_Dashboard!$D$5)-SUMIFS(Operations_Data!$G$4:$G$1003,Operations_Data!$B$4:$B$1003,"<="&Exec_Dashboard!$D$5) | H19: =AVERAGEIFS(Operations_Data!$H$4:$H$1003,Operations_Data!$A$4:$A$1003,Exec_Dashboard!$C$5) | J19: =SUMIFS(Operations_Data!$I$4:$I$1003,Operations_Data!$A$4:$A$1003,Exec_Dashboard!$C$5)
B20: Capital builds in flight | D20: =IF(D19=0,"GREEN",IF(D19<=1,"YELLOW","RED")) | F20: =IF(F19<=200,"GREEN",IF(F19<=400,"YELLOW","RED")) | H20: =IF(H19<=7,"GREEN",IF(H19<=10,"YELLOW","RED")) | J20: =IF(J19<=250,"GREEN",IF(J19<=320,"YELLOW","RED"))
B23: BUDGET vs ACTUAL (REV) | D23: CASH (END OF MONTH) | F23: 90-DAY CASH FORECAST | H23: GRANT REIMB RECEIVED | J23: GRANT OUTSTANDING
B24: =SUMIFS(Financial_Data!$C$4:$C$1003,Financial_Data!$A$4:$A$1003,Exec_Dashboard!$C$5)-SUMIFS(Financial_Data!$J$4:$J$1003,Financial_Data!$A$4:$A$1003,Exec_Dashboard!$C$5) | D24: =SUMIFS(Financial_Data!$N$4:$N$1003,Financial_Data!$A$4:$A$1003,Exec_Dashboard!$C$5) | F24: =SUMIFS(Financial_Data!$N$4:$N$1003,Financial_Data!$A$4:$A$1003,Exec_Dashboard!$C$5)+3*SUMIFS(Financial_Data!$M$4:$M$1003,Financial_Data!$A$4:$A$1003,Exec_Dashboard!$C$5)+SUM(Grant_Data!$E$4:$E$1003)-SUM(Grant_Data!$F$4:$F$1003)-3*(SUMIFS(Financial_Data!$F$4:$F$1003,Financial_Data!$A$4:$A$1003,Exec_Dashboard!$C$5)+SUMIFS(Financial_Data!$E$4:$E$1003,Financial_Data!$A$4:$A$1003,Exec_Dashboard!$C$5)+SUMIFS(Financial_Data!$H$4:$H$1003,Financial_Data!$A$4:$A$1003,Exec_Dashboard!$C$5)) | H24: =SUMIFS(Grant_Data!$F$4:$F$1003,Grant_Data!$F$4:$F$1003,">0") | J24: =SUM(Grant_Data!$E$4:$E$1003)-SUM(Grant_Data!$F$4:$F$1003)
B25: =IF(B24>=0,"GREEN",IF(B24>=-0.05*SUMIFS(Financial_Data!$J$4:$J$1003,Financial_Data!$A$4:$A$1003,Exec_Dashboard!$C$5),"YELLOW","RED")) | D25: =IF(D24>=3000000,"GREEN",IF(D24>=1500000,"YELLOW","RED")) | F25: =IF(F24>=1500000,"GREEN",IF(F24>=500000,"YELLOW","RED")) | H25: Outstanding shown on Financial tab | J25: =IF(J24<=500000,"GREEN",IF(J24<=1200000,"YELLOW","RED"))
F27: AUTO-GENERATED EXECUTIVE SUMMARY
B28: MAJOR RISKS (RED) | D28: KEY DECISIONS NEEDED | F28: ="As of "&C5&": "&SUMIFS(Customer_Data!$C$4:$C$1003,Customer_Data!$A$4:$A$1003,Exec_Dashboard!$C$5)&" customers, net adds "&(SUMIFS(Customer_Data!$D$4:$D$1003,Customer_Data!$A$4:$A$1003,Exec_Dashboard!$C$5)-SUMIFS(Customer_Data!$E$4:$E$1003,Customer_Data!$A$4:$A$1003,Exec_Dashboard!$C$5))&" ("&TEXT(IF(SUMIFS(Customer_Data!$C$4:$C$1003,Customer_Data!$B$4:$B$1003,Exec_Dashboard!$D$5-1)=0,0,SUMIFS(Customer_Data!$E$4:$E$1003,Customer_Data!$A$4:$A$1003,Exec_Dashboard!$C$5)/SUMIFS(Customer_Data!$C$4:$C$1003,Customer_Data!$B$4:$B$1003,Exec_Dashboard!$D$5-1)),"0.0%")&" churn). Revenue "&TEXT(SUMIFS(Financial_Data!$C$4:$C$1003,Financial_Data!$A$4:$A$1003,Exec_Dashboard!$C$5),"$#,##0")&" vs budget "&TEXT(SUMIFS(Financial_Data!$J$4:$J$1003,Financial_Data!$A$4:$A$1003,Exec_Dashboard!$C$5),"$#,##0")&". "&(COUNTIFS(Project_Data!$F$4:$F$1003,"On Track")+COUNTIFS(Project_Data!$F$4:$F$1003,"At Risk")+COUNTIFS(Project_Data!$F$4:$F$1003,"Behind"))&" active projects, "&COUNTIFS(Project_Data!$F$4:$F$1003,"Behind")&" behind. Install backlog "&(SUMIFS(Operations_Data!$F$4:$F$1003,Operations_Data!$B$4:$B$1003,"<="&Exec_Dashboard!$D$5)-SUMIFS(Operations_Data!$G$4:$G$1003,Operations_Data!$B$4:$B$1003,"<="&Exec_Dashboard!$D$5))&", avg "&TEXT(AVERAGEIFS(Operations_Data!$H$4:$H$1003,Operations_Data!$A$4:$A$1003,Exec_Dashboard!$C$5),"0.0")&" days. "&COUNTIFS(Risk_Register!$F$4:$F$1003,">=15")&" red risk(s), "&COUNTIFS(Board_Actions!$I$4:$I$1003,"Yes",Board_Actions!$H$4:$H$1003,"<>Complete")&" decision(s) need executive action."
B29: =COUNTIFS(Risk_Register!$F$4:$F$1003,">=15") | D29: =COUNTIFS(Board_Actions!$I$4:$I$1003,"Yes",Board_Actions!$H$4:$H$1003,"<>Complete")
B30: =IF(B29=0,"GREEN",IF(B29<=1,"YELLOW","RED")) | D30: =IF(D29=0,"GREEN",IF(D29<=3,"YELLOW","RED"))
B33: TIME-SERIES ROLLUPS — This Month / YTD / Rolling-12 / Prior Month / Goal / Variance
B34: Metric | C34: This Month | D34: YTD | E34: Rolling 12 | F34: Prior Month | G34: Goal (MTD) | H34: Variance | I34: Status
B35: New Sales | C35: =SUMIFS(Calc!$C$2:$C$13,Calc!$A$2:$A$13,Exec_Dashboard!$C$5) | D35: =SUMIFS(Calc!$C$2:$C$13,Calc!$B$2:$B$13,"<="&Exec_Dashboard!$D$5) | E35: =SUMIFS(Calc!$C$2:$C$13,Calc!$B$2:$B$13,">"&(Exec_Dashboard!$D$5-12)) | F35: =SUMIFS(Calc!$C$2:$C$13,Calc!$B$2:$B$13,Exec_Dashboard!$D$5-1) | G35: =SUMIFS(Sales_Targets!$C$4:$C$1003,Sales_Targets!$A$4:$A$1003,Exec_Dashboard!$C$5) | H35: =C35-G35 | I35: =IF(C35>=G35,"GREEN",IF(C35>=0.9*G35,"YELLOW","RED"))
B36: Disconnects | C36: =SUMIFS(Calc!$D$2:$D$13,Calc!$A$2:$A$13,Exec_Dashboard!$C$5) | D36: =SUMIFS(Calc!$D$2:$D$13,Calc!$B$2:$B$13,"<="&Exec_Dashboard!$D$5) | E36: =SUMIFS(Calc!$D$2:$D$13,Calc!$B$2:$B$13,">"&(Exec_Dashboard!$D$5-12)) | F36: =SUMIFS(Calc!$D$2:$D$13,Calc!$B$2:$B$13,Exec_Dashboard!$D$5-1) | G36: — | H36: =C36-F36 | I36: =IF(C36<=F36,"GREEN",IF(C36<=1.05*F36,"YELLOW","RED"))
B37: Net Adds | C37: =SUMIFS(Calc!$E$2:$E$13,Calc!$A$2:$A$13,Exec_Dashboard!$C$5) | D37: =SUMIFS(Calc!$E$2:$E$13,Calc!$B$2:$B$13,"<="&Exec_Dashboard!$D$5) | E37: =SUMIFS(Calc!$E$2:$E$13,Calc!$B$2:$B$13,">"&(Exec_Dashboard!$D$5-12)) | F37: =SUMIFS(Calc!$E$2:$E$13,Calc!$B$2:$B$13,Exec_Dashboard!$D$5-1) | G37: — | H37: =C37-F37 | I37: =IF(C37>=F37,"GREEN",IF(C37>=0.95*F37,"YELLOW","RED"))
B38: Revenue | C38: =SUMIFS(Calc!$J$2:$J$13,Calc!$A$2:$A$13,Exec_Dashboard!$C$5) | D38: =SUMIFS(Calc!$J$2:$J$13,Calc!$B$2:$B$13,"<="&Exec_Dashboard!$D$5) | E38: =SUMIFS(Calc!$J$2:$J$13,Calc!$B$2:$B$13,">"&(Exec_Dashboard!$D$5-12)) | F38: =SUMIFS(Calc!$J$2:$J$13,Calc!$B$2:$B$13,Exec_Dashboard!$D$5-1) | G38: =SUMIFS(Financial_Data!$J$4:$J$1003,Financial_Data!$A$4:$A$1003,Exec_Dashboard!$C$5) | H38: =C38-G38 | I38: =IF(C38>=G38,"GREEN",IF(C38>=0.9*G38,"YELLOW","RED"))
B39: MRR | C39: =SUMIFS(Calc!$K$2:$K$13,Calc!$A$2:$A$13,Exec_Dashboard!$C$5) | D39: =SUMIFS(Calc!$K$2:$K$13,Calc!$A$2:$A$13,Exec_Dashboard!$C$5) | E39: =SUMIFS(Calc!$K$2:$K$13,Calc!$A$2:$A$13,Exec_Dashboard!$C$5) | F39: =SUMIFS(Calc!$K$2:$K$13,Calc!$B$2:$B$13,Exec_Dashboard!$D$5-1) | G39: — | H39: =C39-F39 | I39: =IF(C39>=F39,"GREEN",IF(C39>=0.95*F39,"YELLOW","RED"))
B40: CapEx | C40: =SUMIFS(Calc!$M$2:$M$13,Calc!$A$2:$A$13,Exec_Dashboard!$C$5) | D40: =SUMIFS(Calc!$M$2:$M$13,Calc!$B$2:$B$13,"<="&Exec_Dashboard!$D$5) | E40: =SUMIFS(Calc!$M$2:$M$13,Calc!$B$2:$B$13,">"&(Exec_Dashboard!$D$5-12)) | F40: =SUMIFS(Calc!$M$2:$M$13,Calc!$B$2:$B$13,Exec_Dashboard!$D$5-1) | G40: =SUMIFS(Financial_Data!$L$4:$L$1003,Financial_Data!$A$4:$A$1003,Exec_Dashboard!$C$5) | H40: =C40-G40 | I40: =IF(C40<=G40,"GREEN",IF(C40<=1.1*G40,"YELLOW","RED"))
B41: OpEx | C41: =SUMIFS(Calc!$N$2:$N$13,Calc!$A$2:$A$13,Exec_Dashboard!$C$5) | D41: =SUMIFS(Calc!$N$2:$N$13,Calc!$B$2:$B$13,"<="&Exec_Dashboard!$D$5) | E41: =SUMIFS(Calc!$N$2:$N$13,Calc!$B$2:$B$13,">"&(Exec_Dashboard!$D$5-12)) | F41: =SUMIFS(Calc!$N$2:$N$13,Calc!$B$2:$B$13,Exec_Dashboard!$D$5-1) | G41: =SUMIFS(Financial_Data!$K$4:$K$1003,Financial_Data!$A$4:$A$1003,Exec_Dashboard!$C$5) | H41: =C41-G41 | I41: =IF(C41<=G41,"GREEN",IF(C41<=1.1*G41,"YELLOW","RED"))
B42: Installs Completed | C42: =SUMIFS(Calc!$Q$2:$Q$13,Calc!$A$2:$A$13,Exec_Dashboard!$C$5) | D42: =SUMIFS(Calc!$Q$2:$Q$13,Calc!$B$2:$B$13,"<="&Exec_Dashboard!$D$5) | E42: =SUMIFS(Calc!$Q$2:$Q$13,Calc!$B$2:$B$13,">"&(Exec_Dashboard!$D$5-12)) | F42: =SUMIFS(Calc!$Q$2:$Q$13,Calc!$B$2:$B$13,Exec_Dashboard!$D$5-1) | G42: — | H42: =C42-F42 | I42: =IF(C42>=F42,"GREEN",IF(C42>=0.95*F42,"YELLOW","RED"))
B43: Trouble Tickets | C43: =SUMIFS(Calc!$U$2:$U$13,Calc!$A$2:$A$13,Exec_Dashboard!$C$5) | D43: =SUMIFS(Calc!$U$2:$U$13,Calc!$B$2:$B$13,"<="&Exec_Dashboard!$D$5) | E43: =SUMIFS(Calc!$U$2:$U$13,Calc!$B$2:$B$13,">"&(Exec_Dashboard!$D$5-12)) | F43: =SUMIFS(Calc!$U$2:$U$13,Calc!$B$2:$B$13,Exec_Dashboard!$D$5-1) | G43: — | H43: =C43-F43 | I43: =IF(C43<=F43,"GREEN",IF(C43<=1.05*F43,"YELLOW","RED"))
B44: Activations | C44: =SUMIFS(Calc!$W$2:$W$13,Calc!$A$2:$A$13,Exec_Dashboard!$C$5) | D44: =SUMIFS(Calc!$W$2:$W$13,Calc!$B$2:$B$13,"<="&Exec_Dashboard!$D$5) | E44: =SUMIFS(Calc!$W$2:$W$13,Calc!$B$2:$B$13,">"&(Exec_Dashboard!$D$5-12)) | F44: =SUMIFS(Calc!$W$2:$W$13,Calc!$B$2:$B$13,Exec_Dashboard!$D$5-1) | G44: — | H44: =C44-F44 | I44: =IF(C44>=F44,"GREEN",IF(C44>=0.95*F44,"YELLOW","RED"))
B46: TOP OPEN RISKS (highest score) | G46: DECISIONS NEEDED FROM LEADERSHIP / BOARD
B47: Risk | C47: Score | D47: RYG | G47: Decision / Action | J47: Owner | K47: Priority
B48: =IFERROR(INDEX(Risk_Register!$B$4:$B$1003,MATCH(LARGE(Risk_Register!$F$4:$F$1003,1),Risk_Register!$F$4:$F$1003,0)),"") | D48: =LARGE(Risk_Register!$F$4:$F$1003,1) | E48: =IF(D48>=15,"RED",IF(D48>=8,"YELLOW","GREEN")) | G48: =IFERROR(INDEX(Board_Actions!$B$4:$B$1003,AGGREGATE(15,6,(ROW(Board_Actions!$I$4:$I$1003)-3)/((Board_Actions!$I$4:$I$1003="Yes")*(Board_Actions!$H$4:$H$1003<>"Complete")),1)),"") | J48: =IFERROR(INDEX(Board_Actions!$D$4:$D$1003,AGGREGATE(15,6,(ROW(Board_Actions!$I$4:$I$1003)-3)/((Board_Actions!$I$4:$I$1003="Yes")*(Board_Actions!$H$4:$H$1003<>"Complete")),1)),"") | K48: =IFERROR(INDEX(Board_Actions!$G$4:$G$1003,AGGREGATE(15,6,(ROW(Board_Actions!$I$4:$I$1003)-3)/((Board_Actions!$I$4:$I$1003="Yes")*(Board_Actions!$H$4:$H$1003<>"Complete")),1)),"")
B49: =IFERROR(INDEX(Risk_Register!$B$4:$B$1003,MATCH(LARGE(Risk_Register!$F$4:$F$1003,2),Risk_Register!$F$4:$F$1003,0)),"") | D49: =LARGE(Risk_Register!$F$4:$F$1003,2) | E49: =IF(D49>=15,"RED",IF(D49>=8,"YELLOW","GREEN")) | G49: =IFERROR(INDEX(Board_Actions!$B$4:$B$1003,AGGREGATE(15,6,(ROW(Board_Actions!$I$4:$I$1003)-3)/((Board_Actions!$I$4:$I$1003="Yes")*(Board_Actions!$H$4:$H$1003<>"Complete")),2)),"") | J49: =IFERROR(INDEX(Board_Actions!$D$4:$D$1003,AGGREGATE(15,6,(ROW(Board_Actions!$I$4:$I$1003)-3)/((Board_Actions!$I$4:$I$1003="Yes")*(Board_Actions!$H$4:$H$1003<>"Complete")),2)),"") | K49: =IFERROR(INDEX(Board_Actions!$G$4:$G$1003,AGGREGATE(15,6,(ROW(Board_Actions!$I$4:$I$1003)-3)/((Board_Actions!$I$4:$I$1003="Yes")*(Board_Actions!$H$4:$H$1003<>"Complete")),2)),"")
B50: =IFERROR(INDEX(Risk_Register!$B$4:$B$1003,MATCH(LARGE(Risk_Register!$F$4:$F$1003,3),Risk_Register!$F$4:$F$1003,0)),"") | D50: =LARGE(Risk_Register!$F$4:$F$1003,3) | E50: =IF(D50>=15,"RED",IF(D50>=8,"YELLOW","GREEN")) | G50: =IFERROR(INDEX(Board_Actions!$B$4:$B$1003,AGGREGATE(15,6,(ROW(Board_Actions!$I$4:$I$1003)-3)/((Board_Actions!$I$4:$I$1003="Yes")*(Board_Actions!$H$4:$H$1003<>"Complete")),3)),"") | J50: =IFERROR(INDEX(Board_Actions!$D$4:$D$1003,AGGREGATE(15,6,(ROW(Board_Actions!$I$4:$I$1003)-3)/((Board_Actions!$I$4:$I$1003="Yes")*(Board_Actions!$H$4:$H$1003<>"Complete")),3)),"") | K50: =IFERROR(INDEX(Board_Actions!$G$4:$G$1003,AGGREGATE(15,6,(ROW(Board_Actions!$I$4:$I$1003)-3)/((Board_Actions!$I$4:$I$1003="Yes")*(Board_Actions!$H$4:$H$1003<>"Complete")),3)),"")
B51: =IFERROR(INDEX(Risk_Register!$B$4:$B$1003,MATCH(LARGE(Risk_Register!$F$4:$F$1003,4),Risk_Register!$F$4:$F$1003,0)),"") | D51: =LARGE(Risk_Register!$F$4:$F$1003,4) | E51: =IF(D51>=15,"RED",IF(D51>=8,"YELLOW","GREEN")) | G51: =IFERROR(INDEX(Board_Actions!$B$4:$B$1003,AGGREGATE(15,6,(ROW(Board_Actions!$I$4:$I$1003)-3)/((Board_Actions!$I$4:$I$1003="Yes")*(Board_Actions!$H$4:$H$1003<>"Complete")),4)),"") | J51: =IFERROR(INDEX(Board_Actions!$D$4:$D$1003,AGGREGATE(15,6,(ROW(Board_Actions!$I$4:$I$1003)-3)/((Board_Actions!$I$4:$I$1003="Yes")*(Board_Actions!$H$4:$H$1003<>"Complete")),4)),"") | K51: =IFERROR(INDEX(Board_Actions!$G$4:$G$1003,AGGREGATE(15,6,(ROW(Board_Actions!$I$4:$I$1003)-3)/((Board_Actions!$I$4:$I$1003="Yes")*(Board_Actions!$H$4:$H$1003<>"Complete")),4)),"")
B52: =IFERROR(INDEX(Risk_Register!$B$4:$B$1003,MATCH(LARGE(Risk_Register!$F$4:$F$1003,5),Risk_Register!$F$4:$F$1003,0)),"") | D52: =LARGE(Risk_Register!$F$4:$F$1003,5) | E52: =IF(D52>=15,"RED",IF(D52>=8,"YELLOW","GREEN")) | G52: =IFERROR(INDEX(Board_Actions!$B$4:$B$1003,AGGREGATE(15,6,(ROW(Board_Actions!$I$4:$I$1003)-3)/((Board_Actions!$I$4:$I$1003="Yes")*(Board_Actions!$H$4:$H$1003<>"Complete")),5)),"") | J52: =IFERROR(INDEX(Board_Actions!$D$4:$D$1003,AGGREGATE(15,6,(ROW(Board_Actions!$I$4:$I$1003)-3)/((Board_Actions!$I$4:$I$1003="Yes")*(Board_Actions!$H$4:$H$1003<>"Complete")),5)),"") | K52: =IFERROR(INDEX(Board_Actions!$G$4:$G$1003,AGGREGATE(15,6,(ROW(Board_Actions!$I$4:$I$1003)-3)/((Board_Actions!$I$4:$I$1003="Yes")*(Board_Actions!$H$4:$H$1003<>"Complete")),5)),"")
B55: TREND CHARTS

Sheet Sales_Dashboard
A1: SALES MANAGEMENT DASHBOARD
A2: Leads → Qualified → Connects • pipeline, channels, counties, reps, goal vs actual • reporting month set on Exec Dashboard
B4: SALES KPIs (current reporting month)
B5: LEADS (MTD) | D5: QUALIFIED (MTD) | F5: CONVERSION RATE | H5: CONNECTS (MTD) | J5: GOAL (MTD) | L5: VARIANCE TO GOAL
B6: =SUMIFS(Sales_Data!$H$4:$H$1003,Sales_Data!$A$4:$A$1003,Exec_Dashboard!$C$5) | D6: =SUMIFS(Sales_Data!$I$4:$I$1003,Sales_Data!$A$4:$A$1003,Exec_Dashboard!$C$5) | F6: =IF(SUMIFS(Sales_Data!$H$4:$H$1003,Sales_Data!$A$4:$A$1003,Exec_Dashboard!$C$5)=0,0,SUMIFS(Sales_Data!$J$4:$J$1003,Sales_Data!$A$4:$A$1003,Exec_Dashboard!$C$5)/SUMIFS(Sales_Data!$H$4:$H$1003,Sales_Data!$A$4:$A$1003,Exec_Dashboard!$C$5)) | H6: =SUMIFS(Sales_Data!$J$4:$J$1003,Sales_Data!$A$4:$A$1003,Exec_Dashboard!$C$5) | J6: =SUMIFS(Sales_Targets!$C$4:$C$1003,Sales_Targets!$A$4:$A$1003,Exec_Dashboard!$C$5) | L6: =SUMIFS(Sales_Data!$J$4:$J$1003,Sales_Data!$A$4:$A$1003,Exec_Dashboard!$C$5)-SUMIFS(Sales_Targets!$C$4:$C$1003,Sales_Targets!$A$4:$A$1003,Exec_Dashboard!$C$5)
B7: Top of funnel | D7: Sales-qualified | F7: =IF(F6>=0.25,"GREEN",IF(F6>=0.15,"YELLOW","RED")) | H7: Closed-won units | J7: Monthly target | L7: =IF(L6>=0,"GREEN",IF(L6>=-0.1*SUMIFS(Sales_Targets!$C$4:$C$1003,Sales_Targets!$A$4:$A$1003,Exec_Dashboard!$C$5),"YELLOW","RED"))
B10: NEW MRR ADDED | D10: RESIDENTIAL SALES | F10: BUSINESS SALES | H10: PIPELINE VALUE (OPEN) | J10: CLOSED-WON (ARR) | L10: LOST OPPORTUNITIES
B11: =SUMIFS(Sales_Data!$K$4:$K$1003,Sales_Data!$A$4:$A$1003,Exec_Dashboard!$C$5) | D11: =SUMIFS(Sales_Data!$J$4:$J$1003,Sales_Data!$A$4:$A$1003,Exec_Dashboard!$C$5,Sales_Data!$D$4:$D$1003,"Residential") | F11: =SUMIFS(Sales_Data!$J$4:$J$1003,Sales_Data!$A$4:$A$1003,Exec_Dashboard!$C$5,Sales_Data!$D$4:$D$1003,"Business") | H11: =SUMIFS(Pipeline!$G$4:$G$1003,Pipeline!$F$4:$F$1003,"<>Closed-Won",Pipeline!$F$4:$F$1003,"<>Closed-Lost") | J11: =SUMIFS(Pipeline!$G$4:$G$1003,Pipeline!$F$4:$F$1003,"Closed-Won") | L11: =COUNTIFS(Pipeline!$F$4:$F$1003,"Closed-Lost")
B12: Recurring $ added | H12: =IF(H11>=1500000,"GREEN",IF(H11>=800000,"YELLOW","RED"))
B15: ENTERPRISE OPPS (OPEN) | D15: HOA / DEVELOPER OPPS | F15: BULK AGREEMENT OPPS | H15: DOOR KNOCKS (MTD) | J15: QUAL → CLOSE RATE | L15: AVG NEW MRR / CONNECT
B16: =COUNTIFS(Pipeline!$E$4:$E$1003,"Enterprise/DIA",Pipeline!$F$4:$F$1003,"<>Closed-Lost",Pipeline!$F$4:$F$1003,"<>Closed-Won") | D16: =COUNTIFS(Pipeline!$E$4:$E$1003,"HOA/Developer") | F16: =COUNTIFS(Pipeline!$E$4:$E$1003,"Bulk Agreement") | H16: =SUMIFS(Sales_Data!$L$4:$L$1003,Sales_Data!$A$4:$A$1003,Exec_Dashboard!$C$5) | J16: =IF(SUMIFS(Sales_Data!$I$4:$I$1003,Sales_Data!$A$4:$A$1003,Exec_Dashboard!$C$5)=0,0,SUMIFS(Sales_Data!$J$4:$J$1003,Sales_Data!$A$4:$A$1003,Exec_Dashboard!$C$5)/SUMIFS(Sales_Data!$I$4:$I$1003,Sales_Data!$A$4:$A$1003,Exec_Dashboard!$C$5)) | L16: =IF(SUMIFS(Sales_Data!$J$4:$J$1003,Sales_Data!$A$4:$A$1003,Exec_Dashboard!$C$5)=0,0,SUMIFS(Sales_Data!$K$4:$K$1003,Sales_Data!$A$4:$A$1003,Exec_Dashboard!$C$5)/SUMIFS(Sales_Data!$J$4:$J$1003,Sales_Data!$A$4:$A$1003,Exec_Dashboard!$C$5))
B17: DIA pipeline count | H17: D2D activity | J17: =IF(J16>=0.5,"GREEN",IF(J16>=0.3,"YELLOW","RED"))
B20: ANALYTICS
P60: Sales by County | S60: Sales by Channel | V60: Sales by Rep | Y60: Pipeline by Stage | AB60: Lost Reasons
P61: Category | Q61: Value | S61: Category | T61: Value | V61: Category | W61: Value | Y61: Category | Z61: Value | AB61: Category | AC61: Value
P62: Robeson | Q62: =SUMIFS(Sales_Data!$J$4:$J$1003,Sales_Data!$C$4:$C$1003,"Robeson") | S62: Door-to-Door | T62: =SUMIFS(Sales_Data!$J$4:$J$1003,Sales_Data!$E$4:$E$1003,"Door-to-Door") | V62: Maria Lopez | W62: =SUMIFS(Sales_Data!$J$4:$J$1003,Sales_Data!$G$4:$G$1003,"Maria Lopez") | Y62: Prospect | Z62: =SUMIFS(Pipeline!$G$4:$G$1003,Pipeline!$F$4:$F$1003,"Prospect") | AB62: Price | AC62: =COUNTIFS(Pipeline!$J$4:$J$1003,"Price")
P63: Hoke | Q63: =SUMIFS(Sales_Data!$J$4:$J$1003,Sales_Data!$C$4:$C$1003,"Hoke") | S63: Inbound Call | T63: =SUMIFS(Sales_Data!$J$4:$J$1003,Sales_Data!$E$4:$E$1003,"Inbound Call") | V63: James Carter | W63: =SUMIFS(Sales_Data!$J$4:$J$1003,Sales_Data!$G$4:$G$1003,"James Carter") | Y63: Qualified | Z63: =SUMIFS(Pipeline!$G$4:$G$1003,Pipeline!$F$4:$F$1003,"Qualified") | AB63: Competitor Fiber | AC63: =COUNTIFS(Pipeline!$J$4:$J$1003,"Competitor Fiber")
P64: Cumberland | Q64: =SUMIFS(Sales_Data!$J$4:$J$1003,Sales_Data!$C$4:$C$1003,"Cumberland") | S64: Website | T64: =SUMIFS(Sales_Data!$J$4:$J$1003,Sales_Data!$E$4:$E$1003,"Website") | V64: Tanya Hunt | W64: =SUMIFS(Sales_Data!$J$4:$J$1003,Sales_Data!$G$4:$G$1003,"Tanya Hunt") | Y64: Proposal | Z64: =SUMIFS(Pipeline!$G$4:$G$1003,Pipeline!$F$4:$F$1003,"Proposal") | AB64: No Coverage Yet | AC64: =COUNTIFS(Pipeline!$J$4:$J$1003,"No Coverage Yet")
P65: Scotland | Q65: =SUMIFS(Sales_Data!$J$4:$J$1003,Sales_Data!$C$4:$C$1003,"Scotland") | S65: Referral | T65: =SUMIFS(Sales_Data!$J$4:$J$1003,Sales_Data!$E$4:$E$1003,"Referral") | V65: Derek Oxendine | W65: =SUMIFS(Sales_Data!$J$4:$J$1003,Sales_Data!$G$4:$G$1003,"Derek Oxendine") | Y65: Negotiation | Z65: =SUMIFS(Pipeline!$G$4:$G$1003,Pipeline!$F$4:$F$1003,"Negotiation") | AB65: Timing | AC65: =COUNTIFS(Pipeline!$J$4:$J$1003,"Timing")
P66: Bladen | Q66: =SUMIFS(Sales_Data!$J$4:$J$1003,Sales_Data!$C$4:$C$1003,"Bladen") | S66: Event | T66: =SUMIFS(Sales_Data!$J$4:$J$1003,Sales_Data!$E$4:$E$1003,"Event") | V66: Sarah Locklear | W66: =SUMIFS(Sales_Data!$J$4:$J$1003,Sales_Data!$G$4:$G$1003,"Sarah Locklear") | Y66: Closed-Won | Z66: =SUMIFS(Pipeline!$G$4:$G$1003,Pipeline!$F$4:$F$1003,"Closed-Won") | AB66: Credit/Install Fee | AC66: =COUNTIFS(Pipeline!$J$4:$J$1003,"Credit/Install Fee")
P67: Columbus | Q67: =SUMIFS(Sales_Data!$J$4:$J$1003,Sales_Data!$C$4:$C$1003,"Columbus") | S67: HOA/Developer | T67: =SUMIFS(Sales_Data!$J$4:$J$1003,Sales_Data!$E$4:$E$1003,"HOA/Developer") | AB67: Lost Contact | AC67: =COUNTIFS(Pipeline!$J$4:$J$1003,"Lost Contact")
P75: Goal vs Actual (monthly)
P76: Month | Q76: Actual | R76: Goal
P77: =Sales_Targets!A4 | Q77: =SUMIFS(Sales_Data!$J$4:$J$1003,Sales_Data!$B$4:$B$1003,Sales_Targets!B4) | R77: =Sales_Targets!C4
P78: =Sales_Targets!A5 | Q78: =SUMIFS(Sales_Data!$J$4:$J$1003,Sales_Data!$B$4:$B$1003,Sales_Targets!B5) | R78: =Sales_Targets!C5
P79: =Sales_Targets!A6 | Q79: =SUMIFS(Sales_Data!$J$4:$J$1003,Sales_Data!$B$4:$B$1003,Sales_Targets!B6) | R79: =Sales_Targets!C6
P80: =Sales_Targets!A7 | Q80: =SUMIFS(Sales_Data!$J$4:$J$1003,Sales_Data!$B$4:$B$1003,Sales_Targets!B7) | R80: =Sales_Targets!C7
P81: =Sales_Targets!A8 | Q81: =SUMIFS(Sales_Data!$J$4:$J$1003,Sales_Data!$B$4:$B$1003,Sales_Targets!B8) | R81: =Sales_Targets!C8
P82: =Sales_Targets!A9 | Q82: =SUMIFS(Sales_Data!$J$4:$J$1003,Sales_Data!$B$4:$B$1003,Sales_Targets!B9) | R82: =Sales_Targets!C9
P83: =Sales_Targets!A10 | Q83: =SUMIFS(Sales_Data!$J$4:$J$1003,Sales_Data!$B$4:$B$1003,Sales_Targets!B10) | R83: =Sales_Targets!C10
P84: =Sales_Targets!A11 | Q84: =SUMIFS(Sales_Data!$J$4:$J$1003,Sales_Data!$B$4:$B$1003,Sales_Targets!B11) | R84: =Sales_Targets!C11
P85: =Sales_Targets!A12 | Q85: =SUMIFS(Sales_Data!$J$4:$J$1003,Sales_Data!$B$4:$B$1003,Sales_Targets!B12) | R85: =Sales_Targets!C12
P86: =Sales_Targets!A13 | Q86: =SUMIFS(Sales_Data!$J$4:$J$1003,Sales_Data!$B$4:$B$1003,Sales_Targets!B13) | R86: =Sales_Targets!C13
P87: =Sales_Targets!A14 | Q87: =SUMIFS(Sales_Data!$J$4:$J$1003,Sales_Data!$B$4:$B$1003,Sales_Targets!B14) | R87: =Sales_Targets!C14
P88: =Sales_Targets!A15 | Q88: =SUMIFS(Sales_Data!$J$4:$J$1003,Sales_Data!$B$4:$B$1003,Sales_Targets!B15) | R88: =Sales_Targets!C15

Sheet Ops_Dashboard
A1: OPERATIONS MANAGEMENT DASHBOARD
A2: Build → Drop → Install → Activate • trouble tickets, contractors, project health • reporting month set on Exec Dashboard
B4: OPERATIONS KPIs (current reporting month)
B5: HOMES PASSED ADDED | D5: FOOTAGE BUILT | F5: COST / HOME PASSED | H5: DROPS COMPLETED | J5: SPLICES COMPLETED | L5: ACTIVATIONS
B6: =SUMIFS(Operations_Data!$C$4:$C$1003,Operations_Data!$A$4:$A$1003,Exec_Dashboard!$C$5) | D6: =SUMIFS(Operations_Data!$D$4:$D$1003,Operations_Data!$A$4:$A$1003,Exec_Dashboard!$C$5) | F6: =IF(SUMIFS(Operations_Data!$C$4:$C$1003,Operations_Data!$A$4:$A$1003,Exec_Dashboard!$C$5)=0,0,SUMIFS(Financial_Data!$E$4:$E$1003,Financial_Data!$A$4:$A$1003,Exec_Dashboard!$C$5)/SUMIFS(Operations_Data!$C$4:$C$1003,Operations_Data!$A$4:$A$1003,Exec_Dashboard!$C$5)) | H6: =SUMIFS(Operations_Data!$E$4:$E$1003,Operations_Data!$A$4:$A$1003,Exec_Dashboard!$C$5) | J6: =SUMIFS(Operations_Data!$M$4:$M$1003,Operations_Data!$A$4:$A$1003,Exec_Dashboard!$C$5) | L6: =SUMIFS(Operations_Data!$L$4:$L$1003,Operations_Data!$A$4:$A$1003,Exec_Dashboard!$C$5)
B7: This month | D7: Linear feet | F7: =IF(F6<=700,"GREEN",IF(F6<=950,"YELLOW","RED"))
B10: INSTALLS SCHEDULED | D10: INSTALLS COMPLETED | F10: INSTALL BACKLOG | H10: AVG DAYS TO INSTALL | J10: TROUBLE TICKETS | L10: REPEAT TICKET %
B11: =SUMIFS(Operations_Data!$F$4:$F$1003,Operations_Data!$A$4:$A$1003,Exec_Dashboard!$C$5) | D11: =SUMIFS(Operations_Data!$G$4:$G$1003,Operations_Data!$A$4:$A$1003,Exec_Dashboard!$C$5) | F11: =SUMIFS(Operations_Data!$F$4:$F$1003,Operations_Data!$B$4:$B$1003,"<="&Exec_Dashboard!$D$5)-SUMIFS(Operations_Data!$G$4:$G$1003,Operations_Data!$B$4:$B$1003,"<="&Exec_Dashboard!$D$5) | H11: =AVERAGEIFS(Operations_Data!$H$4:$H$1003,Operations_Data!$A$4:$A$1003,Exec_Dashboard!$C$5) | J11: =SUMIFS(Operations_Data!$I$4:$I$1003,Operations_Data!$A$4:$A$1003,Exec_Dashboard!$C$5) | L11: =IF(SUMIFS(Operations_Data!$I$4:$I$1003,Operations_Data!$A$4:$A$1003,Exec_Dashboard!$C$5)=0,0,SUMIFS(Operations_Data!$J$4:$J$1003,Operations_Data!$A$4:$A$1003,Exec_Dashboard!$C$5)/SUMIFS(Operations_Data!$I$4:$I$1003,Operations_Data!$A$4:$A$1003,Exec_Dashboard!$C$5))
D12: =IF(D11>=SUMIFS(Operations_Data!$F$4:$F$1003,Operations_Data!$A$4:$A$1003,Exec_Dashboard!$C$5),"GREEN",IF(D11>=0.85*SUMIFS(Operations_Data!$F$4:$F$1003,Operations_Data!$A$4:$A$1003,Exec_Dashboard!$C$5),"YELLOW","RED")) | F12: =IF(F11<=200,"GREEN",IF(F11<=400,"YELLOW","RED")) | H12: =IF(H11<=7,"GREEN",IF(H11<=10,"YELLOW","RED")) | J12: =IF(J11<=250,"GREEN",IF(J11<=320,"YELLOW","RED")) | L12: =IF(L11<=0.1,"GREEN",IF(L11<=0.15,"YELLOW","RED"))
B15: OUTAGES (MTD) | D15: PROJECTS ON TRACK | F15: PROJECTS AT RISK | H15: PROJECTS BEHIND | J15: AVG PROJECT % COMPLETE | L15: AVG CONTRACTOR SCORE
B16: =SUMIFS(Operations_Data!$K$4:$K$1003,Operations_Data!$A$4:$A$1003,Exec_Dashboard!$C$5) | D16: =COUNTIFS(Project_Data!$F$4:$F$1003,"On Track") | F16: =COUNTIFS(Project_Data!$F$4:$F$1003,"At Risk") | H16: =COUNTIFS(Project_Data!$F$4:$F$1003,"Behind") | J16: =AVERAGE(Project_Data!$E$4:$E$1003) | L16: =AVERAGE(Project_Data!$Q$4:$Q$1003)
B17: =IF(B16<=2,"GREEN",IF(B16<=4,"YELLOW","RED")) | F17: =IF(F16=0,"GREEN",IF(F16<=2,"YELLOW","RED")) | H17: =IF(H16=0,"GREEN",IF(H16<=1,"YELLOW","RED")) | L17: =IF(L16>=8,"GREEN",IF(L16>=6.5,"YELLOW","RED"))
B20: PROJECT HEALTH & ANALYTICS
P60: Build Progress by Project
P61: Project | Q61: % Complete
P62: =Project_Data!A4 | Q62: =Project_Data!E4
P63: =Project_Data!A5 | Q63: =Project_Data!E5
P64: =Project_Data!A6 | Q64: =Project_Data!E6
P65: =Project_Data!A7 | Q65: =Project_Data!E7
P66: =Project_Data!A8 | Q66: =Project_Data!E8
P67: =Project_Data!A9 | Q67: =Project_Data!E9
P68: =Project_Data!A10 | Q68: =Project_Data!E10
P69: =Project_Data!A11 | Q69: =Project_Data!E11
P70: =Project_Data!A12 | Q70: =Project_Data!E12
P71: =Project_Data!A13 | Q71: =Project_Data!E13
P80: Project Status
P81: Status | Q81: Count
P82: On Track | Q82: =COUNTIFS(Project_Data!$F$4:$F$1003,"On Track")
P83: At Risk | Q83: =COUNTIFS(Project_Data!$F$4:$F$1003,"At Risk")
P84: Behind | Q84: =COUNTIFS(Project_Data!$F$4:$F$1003,"Behind")
P85: Complete | Q85: =COUNTIFS(Project_Data!$F$4:$F$1003,"Complete")
P90: Contractor Performance
P91: Contractor | Q91: Avg Score
P92: Cape Fear Underground | Q92: =IFERROR(AVERAGEIFS(Project_Data!$Q$4:$Q$1003,Project_Data!$P$4:$P$1003,"Cape Fear Underground"),0)
P93: FiberBuild Co | Q93: =IFERROR(AVERAGEIFS(Project_Data!$Q$4:$Q$1003,Project_Data!$P$4:$P$1003,"FiberBuild Co"),0)
P94: In-House Crew | Q94: =IFERROR(AVERAGEIFS(Project_Data!$Q$4:$Q$1003,Project_Data!$P$4:$P$1003,"In-House Crew"),0)
P95: Sandhill Construction | Q95: =IFERROR(AVERAGEIFS(Project_Data!$Q$4:$Q$1003,Project_Data!$P$4:$P$1003,"Sandhill Construction"),0)
P100: Trouble Tickets by Category (editable)
P101: Category | Q101: Count
P102: No Signal / Down | Q102: 92
P103: Slow Speed | Q103: 64
P104: Intermittent | Q104: 58
P105: ONT / Equipment | Q105: 41
P106: Outside Plant | Q106: 33
P107: Billing-related | Q107: 22

Sheet Financial_Dashboard
A1: FINANCIAL MANAGEMENT DASHBOARD
A2: Revenue • CapEx/OpEx • budget vs actual • cash forecast • grant reimbursement • margin by service line • reporting month set on Exec Dashboard
B4: FINANCIAL KPIs (current reporting month)
B5: REVENUE (MTD) | D5: MRR | F5: ARPU | H5: CAPITAL SPEND (MTD) | J5: OPERATING EXPENSE | L5: LABOR COST
B6: =SUMIFS(Financial_Data!$C$4:$C$1003,Financial_Data!$A$4:$A$1003,Exec_Dashboard!$C$5) | D6: =SUMIFS(Financial_Data!$D$4:$D$1003,Financial_Data!$A$4:$A$1003,Exec_Dashboard!$C$5) | F6: =IF(SUMIFS(Customer_Data!$C$4:$C$1003,Customer_Data!$A$4:$A$1003,Exec_Dashboard!$C$5)=0,0,SUMIFS(Financial_Data!$D$4:$D$1003,Financial_Data!$A$4:$A$1003,Exec_Dashboard!$C$5)/SUMIFS(Customer_Data!$C$4:$C$1003,Customer_Data!$A$4:$A$1003,Exec_Dashboard!$C$5)) | H6: =SUMIFS(Financial_Data!$E$4:$E$1003,Financial_Data!$A$4:$A$1003,Exec_Dashboard!$C$5) | J6: =SUMIFS(Financial_Data!$F$4:$F$1003,Financial_Data!$A$4:$A$1003,Exec_Dashboard!$C$5) | L6: =SUMIFS(Financial_Data!$G$4:$G$1003,Financial_Data!$A$4:$A$1003,Exec_Dashboard!$C$5)
B7: =IF(B6>=SUMIFS(Financial_Data!$J$4:$J$1003,Financial_Data!$A$4:$A$1003,Exec_Dashboard!$C$5),"GREEN",IF(B6>=0.95*SUMIFS(Financial_Data!$J$4:$J$1003,Financial_Data!$A$4:$A$1003,Exec_Dashboard!$C$5),"YELLOW","RED")) | F7: =IF(F6>=75,"GREEN",IF(F6>=65,"YELLOW","RED")) | H7: =IF(H6<=SUMIFS(Financial_Data!$L$4:$L$1003,Financial_Data!$A$4:$A$1003,Exec_Dashboard!$C$5),"GREEN",IF(H6<=1.1*SUMIFS(Financial_Data!$L$4:$L$1003,Financial_Data!$A$4:$A$1003,Exec_Dashboard!$C$5),"YELLOW","RED")) | J7: =IF(J6<=SUMIFS(Financial_Data!$K$4:$K$1003,Financial_Data!$A$4:$A$1003,Exec_Dashboard!$C$5),"GREEN",IF(J6<=1.05*SUMIFS(Financial_Data!$K$4:$K$1003,Financial_Data!$A$4:$A$1003,Exec_Dashboard!$C$5),"YELLOW","RED"))
B10: CONTRACTOR COST | D10: GRANT REIMB (MTD) | F10: BUDGET VAR (REV) | H10: FORECAST VAR (REV) | J10: CASH (END OF MONTH) | L10: 90-DAY CASH NEED
B11: =SUMIFS(Financial_Data!$H$4:$H$1003,Financial_Data!$A$4:$A$1003,Exec_Dashboard!$C$5) | D11: =SUMIFS(Financial_Data!$I$4:$I$1003,Financial_Data!$A$4:$A$1003,Exec_Dashboard!$C$5) | F11: =SUMIFS(Financial_Data!$C$4:$C$1003,Financial_Data!$A$4:$A$1003,Exec_Dashboard!$C$5)-SUMIFS(Financial_Data!$J$4:$J$1003,Financial_Data!$A$4:$A$1003,Exec_Dashboard!$C$5) | H11: =SUMIFS(Financial_Data!$C$4:$C$1003,Financial_Data!$A$4:$A$1003,Exec_Dashboard!$C$5)-SUMIFS(Financial_Data!$M$4:$M$1003,Financial_Data!$A$4:$A$1003,Exec_Dashboard!$C$5) | J11: =SUMIFS(Financial_Data!$N$4:$N$1003,Financial_Data!$A$4:$A$1003,Exec_Dashboard!$C$5) | L11: =3*(SUMIFS(Financial_Data!$F$4:$F$1003,Financial_Data!$A$4:$A$1003,Exec_Dashboard!$C$5)+SUMIFS(Financial_Data!$E$4:$E$1003,Financial_Data!$A$4:$A$1003,Exec_Dashboard!$C$5)+SUMIFS(Financial_Data!$H$4:$H$1003,Financial_Data!$A$4:$A$1003,Exec_Dashboard!$C$5))-3*SUMIFS(Financial_Data!$M$4:$M$1003,Financial_Data!$A$4:$A$1003,Exec_Dashboard!$C$5)-SUM(Grant_Data!$E$4:$E$1003)-SUM(Grant_Data!$F$4:$F$1003)
F12: =IF(F11>=0,"GREEN",IF(F11>=-0.05*SUMIFS(Financial_Data!$J$4:$J$1003,Financial_Data!$A$4:$A$1003,Exec_Dashboard!$C$5),"YELLOW","RED")) | H12: =IF(H11>=-0.03*SUMIFS(Financial_Data!$M$4:$M$1003,Financial_Data!$A$4:$A$1003,Exec_Dashboard!$C$5),"GREEN",IF(H11>=-0.07*SUMIFS(Financial_Data!$M$4:$M$1003,Financial_Data!$A$4:$A$1003,Exec_Dashboard!$C$5),"YELLOW","RED")) | J12: =IF(J11>=3000000,"GREEN",IF(J11>=1500000,"YELLOW","RED")) | L12: =IF(L11<=SUMIFS(Financial_Data!$N$4:$N$1003,Financial_Data!$A$4:$A$1003,Exec_Dashboard!$C$5),"GREEN",IF(L11<=1.5*SUMIFS(Financial_Data!$N$4:$N$1003,Financial_Data!$A$4:$A$1003,Exec_Dashboard!$C$5),"YELLOW","RED"))
B15: COST / INSTALL | D15: COST / HOME PASSED | F15: GROSS MARGIN % | H15: REVENUE YTD | J15: CAPEX YTD | L15: GRANT REIMB YTD
B16: =IF(SUMIFS(Operations_Data!$G$4:$G$1003,Operations_Data!$A$4:$A$1003,Exec_Dashboard!$C$5)=0,0,SUMIFS(Financial_Data!$H$4:$H$1003,Financial_Data!$A$4:$A$1003,Exec_Dashboard!$C$5)/SUMIFS(Operations_Data!$G$4:$G$1003,Operations_Data!$A$4:$A$1003,Exec_Dashboard!$C$5)) | D16: =IF(SUMIFS(Operations_Data!$C$4:$C$1003,Operations_Data!$A$4:$A$1003,Exec_Dashboard!$C$5)=0,0,SUMIFS(Financial_Data!$E$4:$E$1003,Financial_Data!$A$4:$A$1003,Exec_Dashboard!$C$5)/SUMIFS(Operations_Data!$C$4:$C$1003,Operations_Data!$A$4:$A$1003,Exec_Dashboard!$C$5)) | F16: =IF(SUMIFS(Financial_Data!$C$4:$C$1003,Financial_Data!$A$4:$A$1003,Exec_Dashboard!$C$5)=0,0,(SUMIFS(Financial_Data!$C$4:$C$1003,Financial_Data!$A$4:$A$1003,Exec_Dashboard!$C$5)-(SUMIFS(Financial_Data!$F$4:$F$1003,Financial_Data!$A$4:$A$1003,Exec_Dashboard!$C$5)+SUMIFS(Financial_Data!$H$4:$H$1003,Financial_Data!$A$4:$A$1003,Exec_Dashboard!$C$5)))/SUMIFS(Financial_Data!$C$4:$C$1003,Financial_Data!$A$4:$A$1003,Exec_Dashboard!$C$5)) | H16: =SUMIFS(Financial_Data!$C$4:$C$1003,Financial_Data!$B$4:$B$1003,"<="&Exec_Dashboard!$D$5) | J16: =SUMIFS(Financial_Data!$E$4:$E$1003,Financial_Data!$B$4:$B$1003,"<="&Exec_Dashboard!$D$5) | L16: =SUMIFS(Financial_Data!$I$4:$I$1003,Financial_Data!$B$4:$B$1003,"<="&Exec_Dashboard!$D$5)
B17: =IF(B16<=600,"GREEN",IF(B16<=850,"YELLOW","RED")) | D17: =IF(D16<=700,"GREEN",IF(D16<=950,"YELLOW","RED")) | F17: =IF(F16>=0.4,"GREEN",IF(F16>=0.25,"YELLOW","RED"))
B20: FINANCIAL ANALYTICS
P60: Expense by Category (MTD)
P61: Category | Q61: Amount
P62: Labor | Q62: =SUMIFS(Financial_Data!$G$4:$G$1003,Financial_Data!$A$4:$A$1003,Exec_Dashboard!$C$5)
P63: Contractor | Q63: =SUMIFS(Financial_Data!$H$4:$H$1003,Financial_Data!$A$4:$A$1003,Exec_Dashboard!$C$5)
P64: Other OpEx | Q64: =SUMIFS(Financial_Data!$F$4:$F$1003,Financial_Data!$A$4:$A$1003,Exec_Dashboard!$C$5)-SUMIFS(Financial_Data!$G$4:$G$1003,Financial_Data!$A$4:$A$1003,Exec_Dashboard!$C$5)
P65: CapEx | Q65: =SUMIFS(Financial_Data!$E$4:$E$1003,Financial_Data!$A$4:$A$1003,Exec_Dashboard!$C$5)
P70: Revenue & Margin by Product (MTD)
P71: Product | Q71: Revenue | R71: Margin %
P72: Residential Internet | Q72: =SUMIFS(Revenue_Detail!$E$4:$E$1003,Revenue_Detail!$A$4:$A$1003,Exec_Dashboard!$C$5,Revenue_Detail!$C$4:$C$1003,"Residential Internet") | R72: =IF(SUMIFS(Revenue_Detail!$E$4:$E$1003,Revenue_Detail!$A$4:$A$1003,Exec_Dashboard!$C$5,Revenue_Detail!$C$4:$C$1003,"Residential Internet")=0,0,(SUMIFS(Revenue_Detail!$E$4:$E$1003,Revenue_Detail!$A$4:$A$1003,Exec_Dashboard!$C$5,Revenue_Detail!$C$4:$C$1003,"Residential Internet")-SUMIFS(Revenue_Detail!$F$4:$F$1003,Revenue_Detail!$A$4:$A$1003,Exec_Dashboard!$C$5,Revenue_Detail!$C$4:$C$1003,"Residential Internet"))/SUMIFS(Revenue_Detail!$E$4:$E$1003,Revenue_Detail!$A$4:$A$1003,Exec_Dashboard!$C$5,Revenue_Detail!$C$4:$C$1003,"Residential Internet"))
P73: Business Internet | Q73: =SUMIFS(Revenue_Detail!$E$4:$E$1003,Revenue_Detail!$A$4:$A$1003,Exec_Dashboard!$C$5,Revenue_Detail!$C$4:$C$1003,"Business Internet") | R73: =IF(SUMIFS(Revenue_Detail!$E$4:$E$1003,Revenue_Detail!$A$4:$A$1003,Exec_Dashboard!$C$5,Revenue_Detail!$C$4:$C$1003,"Business Internet")=0,0,(SUMIFS(Revenue_Detail!$E$4:$E$1003,Revenue_Detail!$A$4:$A$1003,Exec_Dashboard!$C$5,Revenue_Detail!$C$4:$C$1003,"Business Internet")-SUMIFS(Revenue_Detail!$F$4:$F$1003,Revenue_Detail!$A$4:$A$1003,Exec_Dashboard!$C$5,Revenue_Detail!$C$4:$C$1003,"Business Internet"))/SUMIFS(Revenue_Detail!$E$4:$E$1003,Revenue_Detail!$A$4:$A$1003,Exec_Dashboard!$C$5,Revenue_Detail!$C$4:$C$1003,"Business Internet"))
P74: Enterprise / DIA | Q74: =SUMIFS(Revenue_Detail!$E$4:$E$1003,Revenue_Detail!$A$4:$A$1003,Exec_Dashboard!$C$5,Revenue_Detail!$C$4:$C$1003,"Enterprise / DIA") | R74: =IF(SUMIFS(Revenue_Detail!$E$4:$E$1003,Revenue_Detail!$A$4:$A$1003,Exec_Dashboard!$C$5,Revenue_Detail!$C$4:$C$1003,"Enterprise / DIA")=0,0,(SUMIFS(Revenue_Detail!$E$4:$E$1003,Revenue_Detail!$A$4:$A$1003,Exec_Dashboard!$C$5,Revenue_Detail!$C$4:$C$1003,"Enterprise / DIA")-SUMIFS(Revenue_Detail!$F$4:$F$1003,Revenue_Detail!$A$4:$A$1003,Exec_Dashboard!$C$5,Revenue_Detail!$C$4:$C$1003,"Enterprise / DIA"))/SUMIFS(Revenue_Detail!$E$4:$E$1003,Revenue_Detail!$A$4:$A$1003,Exec_Dashboard!$C$5,Revenue_Detail!$C$4:$C$1003,"Enterprise / DIA"))
P75: Managed WiFi | Q75: =SUMIFS(Revenue_Detail!$E$4:$E$1003,Revenue_Detail!$A$4:$A$1003,Exec_Dashboard!$C$5,Revenue_Detail!$C$4:$C$1003,"Managed WiFi") | R75: =IF(SUMIFS(Revenue_Detail!$E$4:$E$1003,Revenue_Detail!$A$4:$A$1003,Exec_Dashboard!$C$5,Revenue_Detail!$C$4:$C$1003,"Managed WiFi")=0,0,(SUMIFS(Revenue_Detail!$E$4:$E$1003,Revenue_Detail!$A$4:$A$1003,Exec_Dashboard!$C$5,Revenue_Detail!$C$4:$C$1003,"Managed WiFi")-SUMIFS(Revenue_Detail!$F$4:$F$1003,Revenue_Detail!$A$4:$A$1003,Exec_Dashboard!$C$5,Revenue_Detail!$C$4:$C$1003,"Managed WiFi"))/SUMIFS(Revenue_Detail!$E$4:$E$1003,Revenue_Detail!$A$4:$A$1003,Exec_Dashboard!$C$5,Revenue_Detail!$C$4:$C$1003,"Managed WiFi"))
P76: Voice | Q76: =SUMIFS(Revenue_Detail!$E$4:$E$1003,Revenue_Detail!$A$4:$A$1003,Exec_Dashboard!$C$5,Revenue_Detail!$C$4:$C$1003,"Voice") | R76: =IF(SUMIFS(Revenue_Detail!$E$4:$E$1003,Revenue_Detail!$A$4:$A$1003,Exec_Dashboard!$C$5,Revenue_Detail!$C$4:$C$1003,"Voice")=0,0,(SUMIFS(Revenue_Detail!$E$4:$E$1003,Revenue_Detail!$A$4:$A$1003,Exec_Dashboard!$C$5,Revenue_Detail!$C$4:$C$1003,"Voice")-SUMIFS(Revenue_Detail!$F$4:$F$1003,Revenue_Detail!$A$4:$A$1003,Exec_Dashboard!$C$5,Revenue_Detail!$C$4:$C$1003,"Voice"))/SUMIFS(Revenue_Detail!$E$4:$E$1003,Revenue_Detail!$A$4:$A$1003,Exec_Dashboard!$C$5,Revenue_Detail!$C$4:$C$1003,"Voice"))
P77: Construction / Other | Q77: =SUMIFS(Revenue_Detail!$E$4:$E$1003,Revenue_Detail!$A$4:$A$1003,Exec_Dashboard!$C$5,Revenue_Detail!$C$4:$C$1003,"Construction / Other") | R77: =IF(SUMIFS(Revenue_Detail!$E$4:$E$1003,Revenue_Detail!$A$4:$A$1003,Exec_Dashboard!$C$5,Revenue_Detail!$C$4:$C$1003,"Construction / Other")=0,0,(SUMIFS(Revenue_Detail!$E$4:$E$1003,Revenue_Detail!$A$4:$A$1003,Exec_Dashboard!$C$5,Revenue_Detail!$C$4:$C$1003,"Construction / Other")-SUMIFS(Revenue_Detail!$F$4:$F$1003,Revenue_Detail!$A$4:$A$1003,Exec_Dashboard!$C$5,Revenue_Detail!$C$4:$C$1003,"Construction / Other"))/SUMIFS(Revenue_Detail!$E$4:$E$1003,Revenue_Detail!$A$4:$A$1003,Exec_Dashboard!$C$5,Revenue_Detail!$C$4:$C$1003,"Construction / Other"))
P82: Grant Reimbursement Pipeline
P83: Program | Q83: Received | R83: Outstanding
P84: BEAD | Q84: =SUMIFS(Grant_Data!$F$4:$F$1003,Grant_Data!$B$4:$B$1003,"BEAD") | R84: =SUMIFS(Grant_Data!$E$4:$E$1003,Grant_Data!$B$4:$B$1003,"BEAD")-SUMIFS(Grant_Data!$F$4:$F$1003,Grant_Data!$B$4:$B$1003,"BEAD")
P85: CAB | Q85: =SUMIFS(Grant_Data!$F$4:$F$1003,Grant_Data!$B$4:$B$1003,"CAB") | R85: =SUMIFS(Grant_Data!$E$4:$E$1003,Grant_Data!$B$4:$B$1003,"CAB")-SUMIFS(Grant_Data!$F$4:$F$1003,Grant_Data!$B$4:$B$1003,"CAB")
P86: ARPA | Q86: =SUMIFS(Grant_Data!$F$4:$F$1003,Grant_Data!$B$4:$B$1003,"ARPA") | R86: =SUMIFS(Grant_Data!$E$4:$E$1003,Grant_Data!$B$4:$B$1003,"ARPA")-SUMIFS(Grant_Data!$F$4:$F$1003,Grant_Data!$B$4:$B$1003,"ARPA")
P87: State Grant | Q87: =SUMIFS(Grant_Data!$F$4:$F$1003,Grant_Data!$B$4:$B$1003,"State Grant") | R87: =SUMIFS(Grant_Data!$E$4:$E$1003,Grant_Data!$B$4:$B$1003,"State Grant")-SUMIFS(Grant_Data!$F$4:$F$1003,Grant_Data!$B$4:$B$1003,"State Grant")
P88: RDOF | Q88: =SUMIFS(Grant_Data!$F$4:$F$1003,Grant_Data!$B$4:$B$1003,"RDOF") | R88: =SUMIFS(Grant_Data!$E$4:$E$1003,Grant_Data!$B$4:$B$1003,"RDOF")-SUMIFS(Grant_Data!$F$4:$F$1003,Grant_Data!$B$4:$B$1003,"RDOF")
P92: Capital Spend by Project
P93: Project | Q93: Spent
P94: =Project_Data!A4 | Q94: =Project_Data!L4
P95: =Project_Data!A5 | Q95: =Project_Data!L5
P96: =Project_Data!A6 | Q96: =Project_Data!L6
P97: =Project_Data!A7 | Q97: =Project_Data!L7
P98: =Project_Data!A8 | Q98: =Project_Data!L8
P99: =Project_Data!A9 | Q99: =Project_Data!L9
P100: =Project_Data!A10 | Q100: =Project_Data!L10
P101: =Project_Data!A11 | Q101: =Project_Data!L11
P102: Cash Trend | Q102: =Project_Data!L12
P103: Month | Q103: Cash Balance
P104: =Financial_Data!A4 | Q104: =Financial_Data!N4
P105: =Financial_Data!A5 | Q105: =Financial_Data!N5
P106: =Financial_Data!A6 | Q106: =Financial_Data!N6
P107: =Financial_Data!A7 | Q107: =Financial_Data!N7
P108: =Financial_Data!A8 | Q108: =Financial_Data!N8
P109: =Financial_Data!A9 | Q109: =Financial_Data!N9
P110: =Financial_Data!A10 | Q110: =Financial_Data!N10
P111: =Financial_Data!A11 | Q111: =Financial_Data!N11
P112: =Financial_Data!A12 | Q112: =Financial_Data!N12
P113: =Financial_Data!A13 | Q113: =Financial_Data!N13
P114: =Financial_Data!A14 | Q114: =Financial_Data!N14
P115: =Financial_Data!A15 | Q115: =Financial_Data!N15

Sheet Board_Report
A1: QUARTERLY BOARD REPORT / MONTHLY COO REPORT
A3: ="Reporting Period: "&Exec_Dashboard!C5&" | Regional Fiber Broadband | Prepared by the COO | CONFIDENTIAL — Board of Directors"
A5: 1. EXECUTIVE SUMMARY
A6: ="For the period ending "&Exec_Dashboard!C5&", the company served "&TEXT(SUMIFS(Customer_Data!$C$4:$C$1003,Customer_Data!$A$4:$A$1003,Exec_Dashboard!$C$5),"#,##0")&" customers across the service area, a net change of "&TEXT(SUMIFS(Customer_Data!$D$4:$D$1003,Customer_Data!$A$4:$A$1003,Exec_Dashboard!$C$5)-SUMIFS(Customer_Data!$E$4:$E$1003,Customer_Data!$A$4:$A$1003,Exec_Dashboard!$C$5),"#,##0")&" connections ("&TEXT(SUMIFS(Customer_Data!$D$4:$D$1003,Customer_Data!$A$4:$A$1003,Exec_Dashboard!$C$5),"#,##0")&" new sales less "&TEXT(SUMIFS(Customer_Data!$E$4:$E$1003,Customer_Data!$A$4:$A$1003,Exec_Dashboard!$C$5),"#,##0")&" disconnects, churn "&TEXT(IF(SUMIFS(Customer_Data!$C$4:$C$1003,Customer_Data!$B$4:$B$1003,Exec_Dashboard!$D$5-1)=0,0,SUMIFS(Customer_Data!$E$4:$E$1003,Customer_Data!$A$4:$A$1003,Exec_Dashboard!$C$5)/SUMIFS(Customer_Data!$C$4:$C$1003,Customer_Data!$B$4:$B$1003,Exec_Dashboard!$D$5-1)),"0.0%")&"). Monthly revenue was "&TEXT(SUMIFS(Financial_Data!$C$4:$C$1003,Financial_Data!$A$4:$A$1003,Exec_Dashboard!$C$5),"$#,##0")&" against a budget of "&TEXT(SUMIFS(Financial_Data!$J$4:$J$1003,Financial_Data!$A$4:$A$1003,Exec_Dashboard!$C$5),"$#,##0")&" (variance "&TEXT(SUMIFS(Financial_Data!$C$4:$C$1003,Financial_Data!$A$4:$A$1003,Exec_Dashboard!$C$5)-SUMIFS(Financial_Data!$J$4:$J$1003,Financial_Data!$A$4:$A$1003,Exec_Dashboard!$C$5),"$#,##0")&"). Homes passed reached "&TEXT(SUMIFS(Customer_Data!$F$4:$F$1003,Customer_Data!$A$4:$A$1003,Exec_Dashboard!$C$5),"#,##0")&". Of "&(COUNTIFS(Project_Data!$F$4:$F$1003,"On Track")+COUNTIFS(Project_Data!$F$4:$F$1003,"At Risk")+COUNTIFS(Project_Data!$F$4:$F$1003,"Behind"))&" active capital projects, "&COUNTIFS(Project_Data!$F$4:$F$1003,"Behind")&" are behind schedule and "&COUNTIFS(Project_Data!$F$4:$F$1003,"At Risk")&" at risk. Installation backlog stands at "&TEXT(SUMIFS(Operations_Data!$F$4:$F$1003,Operations_Data!$B$4:$B$1003,"<="&Exec_Dashboard!$D$5)-SUMIFS(Operations_Data!$G$4:$G$1003,Operations_Data!$B$4:$B$1003,"<="&Exec_Dashboard!$D$5),"#,##0")&" orders with an average install time of "&TEXT(AVERAGEIFS(Operations_Data!$H$4:$H$1003,Operations_Data!$A$4:$A$1003,Exec_Dashboard!$C$5),"0.0")&" days. End-of-month cash was "&TEXT(SUMIFS(Financial_Data!$N$4:$N$1003,Financial_Data!$A$4:$A$1003,Exec_Dashboard!$C$5),"$#,##0")&". "&COUNTIFS(Risk_Register!$F$4:$F$1003,">=15")&" risk(s) are red and "&COUNTIFS(Board_Actions!$I$4:$I$1003,"Yes",Board_Actions!$H$4:$H$1003,"<>Complete")&" decision(s) require board attention."
A11: 2. WHAT IS GOING WELL / WHAT IS BEHIND / WHAT NEEDS EXECUTIVE ATTENTION
A12: ✅ Going Well | D12: ⚠️ Behind | F12: 🚩 Needs Executive Attention
A13: • Pembroke Core Ring & Lumberton MDU on/ahead of plan | D13: • Scotland RDOF build behind — grant drawdown at risk | F13: • Approve revolver draw to bridge BEAD reimbursement timing
A14: • ARPU trending up; margin healthy on residential & business | D14: • Columbus BEAD Zone 2 design rework slipping Milestone 1 | F14: • Authorize 2nd construction contractor (Scotland + Columbus)
A15: • BEAD Zone 1 drawdowns paid in full; strong grant execution | D15: • Install backlog rising vs crew capacity in Robeson | F15: • Approve install-crew headcount add to clear backlog
A16: • Avg days-to-install improving month over month | D16: • Make-ready / pole-attachment delays from utility | F16: • Ratify HOA / bulk pricing policy
A18: 3. FINANCIAL PERFORMANCE
A19: Metric | C19: Actual | D19: Budget | E19: Variance
A20: Revenue (MTD) | C20: =SUMIFS(Financial_Data!$C$4:$C$1003,Financial_Data!$A$4:$A$1003,Exec_Dashboard!$C$5) | D20: =SUMIFS(Financial_Data!$J$4:$J$1003,Financial_Data!$A$4:$A$1003,Exec_Dashboard!$C$5) | E20: =SUMIFS(Financial_Data!$C$4:$C$1003,Financial_Data!$A$4:$A$1003,Exec_Dashboard!$C$5)-SUMIFS(Financial_Data!$J$4:$J$1003,Financial_Data!$A$4:$A$1003,Exec_Dashboard!$C$5)
A21: Revenue (YTD) | C21: =SUMIFS(Financial_Data!$C$4:$C$1003,Financial_Data!$B$4:$B$1003,"<="&Exec_Dashboard!$D$5)
A22: MRR | C22: =SUMIFS(Financial_Data!$D$4:$D$1003,Financial_Data!$A$4:$A$1003,Exec_Dashboard!$C$5)
A23: Capital Spend (MTD) | C23: =SUMIFS(Financial_Data!$E$4:$E$1003,Financial_Data!$A$4:$A$1003,Exec_Dashboard!$C$5) | D23: =SUMIFS(Financial_Data!$L$4:$L$1003,Financial_Data!$A$4:$A$1003,Exec_Dashboard!$C$5) | E23: =SUMIFS(Financial_Data!$E$4:$E$1003,Financial_Data!$A$4:$A$1003,Exec_Dashboard!$C$5)-SUMIFS(Financial_Data!$L$4:$L$1003,Financial_Data!$A$4:$A$1003,Exec_Dashboard!$C$5)
A24: Operating Expense (MTD) | C24: =SUMIFS(Financial_Data!$F$4:$F$1003,Financial_Data!$A$4:$A$1003,Exec_Dashboard!$C$5) | D24: =SUMIFS(Financial_Data!$K$4:$K$1003,Financial_Data!$A$4:$A$1003,Exec_Dashboard!$C$5) | E24: =SUMIFS(Financial_Data!$F$4:$F$1003,Financial_Data!$A$4:$A$1003,Exec_Dashboard!$C$5)-SUMIFS(Financial_Data!$K$4:$K$1003,Financial_Data!$A$4:$A$1003,Exec_Dashboard!$C$5)
A25: Grant Reimb (YTD) | C25: =SUMIFS(Financial_Data!$I$4:$I$1003,Financial_Data!$B$4:$B$1003,"<="&Exec_Dashboard!$D$5)
A26: Cash (End of Month) | C26: =SUMIFS(Financial_Data!$N$4:$N$1003,Financial_Data!$A$4:$A$1003,Exec_Dashboard!$C$5)
A28: 4. CUSTOMER GROWTH & OPERATIONAL PERFORMANCE
A29: Customer | C29: Value | E29: Operations | H29: Value
A30: Total Customers | C30: =SUMIFS(Customer_Data!$C$4:$C$1003,Customer_Data!$A$4:$A$1003,Exec_Dashboard!$C$5) | E30: Installs Completed (MTD) | H30: =SUMIFS(Operations_Data!$G$4:$G$1003,Operations_Data!$A$4:$A$1003,Exec_Dashboard!$C$5)
A31: New Sales (MTD) | C31: =SUMIFS(Customer_Data!$D$4:$D$1003,Customer_Data!$A$4:$A$1003,Exec_Dashboard!$C$5) | E31: Install Backlog | H31: =SUMIFS(Operations_Data!$F$4:$F$1003,Operations_Data!$B$4:$B$1003,"<="&Exec_Dashboard!$D$5)-SUMIFS(Operations_Data!$G$4:$G$1003,Operations_Data!$B$4:$B$1003,"<="&Exec_Dashboard!$D$5)
A32: Disconnects (MTD) | C32: =SUMIFS(Customer_Data!$E$4:$E$1003,Customer_Data!$A$4:$A$1003,Exec_Dashboard!$C$5) | E32: Avg Days to Install | H32: =AVERAGEIFS(Operations_Data!$H$4:$H$1003,Operations_Data!$A$4:$A$1003,Exec_Dashboard!$C$5)
A33: Net Adds (MTD) | C33: =SUMIFS(Customer_Data!$D$4:$D$1003,Customer_Data!$A$4:$A$1003,Exec_Dashboard!$C$5)-SUMIFS(Customer_Data!$E$4:$E$1003,Customer_Data!$A$4:$A$1003,Exec_Dashboard!$C$5) | E33: Trouble Tickets (MTD) | H33: =SUMIFS(Operations_Data!$I$4:$I$1003,Operations_Data!$A$4:$A$1003,Exec_Dashboard!$C$5)
A34: Churn Rate | C34: =IF(SUMIFS(Customer_Data!$C$4:$C$1003,Customer_Data!$B$4:$B$1003,Exec_Dashboard!$D$5-1)=0,0,SUMIFS(Customer_Data!$E$4:$E$1003,Customer_Data!$A$4:$A$1003,Exec_Dashboard!$C$5)/SUMIFS(Customer_Data!$C$4:$C$1003,Customer_Data!$B$4:$B$1003,Exec_Dashboard!$D$5-1)) | E34: Outages (MTD) | H34: =SUMIFS(Operations_Data!$K$4:$K$1003,Operations_Data!$A$4:$A$1003,Exec_Dashboard!$C$5)
A35: Homes Passed | C35: =SUMIFS(Customer_Data!$F$4:$F$1003,Customer_Data!$A$4:$A$1003,Exec_Dashboard!$C$5) | E35: Active Projects | H35: =(COUNTIFS(Project_Data!$F$4:$F$1003,"On Track")+COUNTIFS(Project_Data!$F$4:$F$1003,"At Risk")+COUNTIFS(Project_Data!$F$4:$F$1003,"Behind"))
A36: Take Rate | C36: =IF(SUMIFS(Customer_Data!$F$4:$F$1003,Customer_Data!$A$4:$A$1003,Exec_Dashboard!$C$5)=0,0,SUMIFS(Customer_Data!$C$4:$C$1003,Customer_Data!$A$4:$A$1003,Exec_Dashboard!$C$5)/SUMIFS(Customer_Data!$F$4:$F$1003,Customer_Data!$A$4:$A$1003,Exec_Dashboard!$C$5)) | E36: Projects Behind / At Risk | H36: =COUNTIFS(Project_Data!$F$4:$F$1003,"Behind")+COUNTIFS(Project_Data!$F$4:$F$1003,"At Risk")
A38: 5. MAJOR CAPITAL PROJECT UPDATES
A39: Project | C39: County | D39: Status | E39: % Complete | F39: Capital Spent | G39: Blocker / Note
A40: =Project_Data!A4 | C40: =Project_Data!B4 | D40: =Project_Data!F4 | E40: =Project_Data!E4 | F40: =Project_Data!L4 | G40: =Project_Data!R4
A41: =Project_Data!A5 | C41: =Project_Data!B5 | D41: =Project_Data!F5 | E41: =Project_Data!E5 | F41: =Project_Data!L5 | G41: =Project_Data!R5
A42: =Project_Data!A6 | C42: =Project_Data!B6 | D42: =Project_Data!F6 | E42: =Project_Data!E6 | F42: =Project_Data!L6 | G42: =Project_Data!R6
A43: =Project_Data!A7 | C43: =Project_Data!B7 | D43: =Project_Data!F7 | E43: =Project_Data!E7 | F43: =Project_Data!L7 | G43: =Project_Data!R7
A44: =Project_Data!A8 | C44: =Project_Data!B8 | D44: =Project_Data!F8 | E44: =Project_Data!E8 | F44: =Project_Data!L8 | G44: =Project_Data!R8
A45: =Project_Data!A9 | C45: =Project_Data!B9 | D45: =Project_Data!F9 | E45: =Project_Data!E9 | F45: =Project_Data!L9 | G45: =Project_Data!R9
A46: =Project_Data!A10 | C46: =Project_Data!B10 | D46: =Project_Data!F10 | E46: =Project_Data!E10 | F46: =Project_Data!L10 | G46: =Project_Data!R10
A47: =Project_Data!A11 | C47: =Project_Data!B11 | D47: =Project_Data!F11 | E47: =Project_Data!E11 | F47: =Project_Data!L11 | G47: =Project_Data!R11
A48: =Project_Data!A12 | C48: =Project_Data!B12 | D48: =Project_Data!F12 | E48: =Project_Data!E12 | F48: =Project_Data!L12 | G48: =Project_Data!R12
A49: =Project_Data!A13 | C49: =Project_Data!B13 | D49: =Project_Data!F13 | E49: =Project_Data!E13 | F49: =Project_Data!L13 | G49: =Project_Data!R13
A51: 6. GRANT / CAPITAL PROJECT SUMMARY
A52: Total Approved (all programs) | F52: =SUM(Grant_Data!$E$4:$E$1003)
A53: Total Received to Date | F53: =SUM(Grant_Data!$F$4:$F$1003)
A54: Outstanding (Approved − Received) | F54: =SUM(Grant_Data!$E$4:$E$1003)-SUM(Grant_Data!$F$4:$F$1003)
A55: In Review / Submitted (Requested) | F55: =SUMIFS(Grant_Data!$D$4:$D$1003,Grant_Data!$G$4:$G$1003,"Under Review")+SUMIFS(Grant_Data!$D$4:$D$1003,Grant_Data!$G$4:$G$1003,"Submitted")
A56: Total Capital Budget (projects) | F56: =SUM(Project_Data!$K$4:$K$1003)
A57: Total Capital Spent (projects) | F57: =SUM(Project_Data!$L$4:$L$1003)
A59: 7. KEY RISKS (top by score)
A60: Risk | D60: Cat. | E60: Score | F60: Owner | G60: Mitigation
A61: =IFERROR(INDEX(Risk_Register!$B$4:$B$1003,MATCH(LARGE(Risk_Register!$F$4:$F$1003,1),Risk_Register!$F$4:$F$1003,0)),"") | D61: =IFERROR(INDEX(Risk_Register!$C$4:$C$1003,MATCH(LARGE(Risk_Register!$F$4:$F$1003,1),Risk_Register!$F$4:$F$1003,0)),"") | E61: =IFERROR(LARGE(Risk_Register!$F$4:$F$1003,1),"") | F61: =IFERROR(INDEX(Risk_Register!$H$4:$H$1003,MATCH(LARGE(Risk_Register!$F$4:$F$1003,1),Risk_Register!$F$4:$F$1003,0)),"") | G61: =IFERROR(INDEX(Risk_Register!$I$4:$I$1003,MATCH(LARGE(Risk_Register!$F$4:$F$1003,1),Risk_Register!$F$4:$F$1003,0)),"")
A62: =IFERROR(INDEX(Risk_Register!$B$4:$B$1003,MATCH(LARGE(Risk_Register!$F$4:$F$1003,2),Risk_Register!$F$4:$F$1003,0)),"") | D62: =IFERROR(INDEX(Risk_Register!$C$4:$C$1003,MATCH(LARGE(Risk_Register!$F$4:$F$1003,2),Risk_Register!$F$4:$F$1003,0)),"") | E62: =IFERROR(LARGE(Risk_Register!$F$4:$F$1003,2),"") | F62: =IFERROR(INDEX(Risk_Register!$H$4:$H$1003,MATCH(LARGE(Risk_Register!$F$4:$F$1003,2),Risk_Register!$F$4:$F$1003,0)),"") | G62: =IFERROR(INDEX(Risk_Register!$I$4:$I$1003,MATCH(LARGE(Risk_Register!$F$4:$F$1003,2),Risk_Register!$F$4:$F$1003,0)),"")
A63: =IFERROR(INDEX(Risk_Register!$B$4:$B$1003,MATCH(LARGE(Risk_Register!$F$4:$F$1003,3),Risk_Register!$F$4:$F$1003,0)),"") | D63: =IFERROR(INDEX(Risk_Register!$C$4:$C$1003,MATCH(LARGE(Risk_Register!$F$4:$F$1003,3),Risk_Register!$F$4:$F$1003,0)),"") | E63: =IFERROR(LARGE(Risk_Register!$F$4:$F$1003,3),"") | F63: =IFERROR(INDEX(Risk_Register!$H$4:$H$1003,MATCH(LARGE(Risk_Register!$F$4:$F$1003,3),Risk_Register!$F$4:$F$1003,0)),"") | G63: =IFERROR(INDEX(Risk_Register!$I$4:$I$1003,MATCH(LARGE(Risk_Register!$F$4:$F$1003,3),Risk_Register!$F$4:$F$1003,0)),"")
A64: =IFERROR(INDEX(Risk_Register!$B$4:$B$1003,MATCH(LARGE(Risk_Register!$F$4:$F$1003,4),Risk_Register!$F$4:$F$1003,0)),"") | D64: =IFERROR(INDEX(Risk_Register!$C$4:$C$1003,MATCH(LARGE(Risk_Register!$F$4:$F$1003,4),Risk_Register!$F$4:$F$1003,0)),"") | E64: =IFERROR(LARGE(Risk_Register!$F$4:$F$1003,4),"") | F64: =IFERROR(INDEX(Risk_Register!$H$4:$H$1003,MATCH(LARGE(Risk_Register!$F$4:$F$1003,4),Risk_Register!$F$4:$F$1003,0)),"") | G64: =IFERROR(INDEX(Risk_Register!$I$4:$I$1003,MATCH(LARGE(Risk_Register!$F$4:$F$1003,4),Risk_Register!$F$4:$F$1003,0)),"")
A65: =IFERROR(INDEX(Risk_Register!$B$4:$B$1003,MATCH(LARGE(Risk_Register!$F$4:$F$1003,5),Risk_Register!$F$4:$F$1003,0)),"") | D65: =IFERROR(INDEX(Risk_Register!$C$4:$C$1003,MATCH(LARGE(Risk_Register!$F$4:$F$1003,5),Risk_Register!$F$4:$F$1003,0)),"") | E65: =IFERROR(LARGE(Risk_Register!$F$4:$F$1003,5),"") | F65: =IFERROR(INDEX(Risk_Register!$H$4:$H$1003,MATCH(LARGE(Risk_Register!$F$4:$F$1003,5),Risk_Register!$F$4:$F$1003,0)),"") | G65: =IFERROR(INDEX(Risk_Register!$I$4:$I$1003,MATCH(LARGE(Risk_Register!$F$4:$F$1003,5),Risk_Register!$F$4:$F$1003,0)),"")
A67: 8. DECISIONS NEEDED FROM THE BOARD
A68: Decision / Action | E68: Owner | F68: Priority | G68: Due
A69: =IFERROR(INDEX(Board_Actions!$B$4:$B$1003,AGGREGATE(15,6,(ROW(Board_Actions!$I$4:$I$1003)-3)/((Board_Actions!$I$4:$I$1003="Yes")*(Board_Actions!$H$4:$H$1003<>"Complete")),1)),"") | E69: =IFERROR(INDEX(Board_Actions!$D$4:$D$1003,AGGREGATE(15,6,(ROW(Board_Actions!$I$4:$I$1003)-3)/((Board_Actions!$I$4:$I$1003="Yes")*(Board_Actions!$H$4:$H$1003<>"Complete")),1)),"") | F69: =IFERROR(INDEX(Board_Actions!$G$4:$G$1003,AGGREGATE(15,6,(ROW(Board_Actions!$I$4:$I$1003)-3)/((Board_Actions!$I$4:$I$1003="Yes")*(Board_Actions!$H$4:$H$1003<>"Complete")),1)),"") | G69: =IFERROR(INDEX(Board_Actions!$F$4:$F$1003,AGGREGATE(15,6,(ROW(Board_Actions!$I$4:$I$1003)-3)/((Board_Actions!$I$4:$I$1003="Yes")*(Board_Actions!$H$4:$H$1003<>"Complete")),1)),"")
A70: =IFERROR(INDEX(Board_Actions!$B$4:$B$1003,AGGREGATE(15,6,(ROW(Board_Actions!$I$4:$I$1003)-3)/((Board_Actions!$I$4:$I$1003="Yes")*(Board_Actions!$H$4:$H$1003<>"Complete")),2)),"") | E70: =IFERROR(INDEX(Board_Actions!$D$4:$D$1003,AGGREGATE(15,6,(ROW(Board_Actions!$I$4:$I$1003)-3)/((Board_Actions!$I$4:$I$1003="Yes")*(Board_Actions!$H$4:$H$1003<>"Complete")),2)),"") | F70: =IFERROR(INDEX(Board_Actions!$G$4:$G$1003,AGGREGATE(15,6,(ROW(Board_Actions!$I$4:$I$1003)-3)/((Board_Actions!$I$4:$I$1003="Yes")*(Board_Actions!$H$4:$H$1003<>"Complete")),2)),"") | G70: =IFERROR(INDEX(Board_Actions!$F$4:$F$1003,AGGREGATE(15,6,(ROW(Board_Actions!$I$4:$I$1003)-3)/((Board_Actions!$I$4:$I$1003="Yes")*(Board_Actions!$H$4:$H$1003<>"Complete")),2)),"")
A71: =IFERROR(INDEX(Board_Actions!$B$4:$B$1003,AGGREGATE(15,6,(ROW(Board_Actions!$I$4:$I$1003)-3)/((Board_Actions!$I$4:$I$1003="Yes")*(Board_Actions!$H$4:$H$1003<>"Complete")),3)),"") | E71: =IFERROR(INDEX(Board_Actions!$D$4:$D$1003,AGGREGATE(15,6,(ROW(Board_Actions!$I$4:$I$1003)-3)/((Board_Actions!$I$4:$I$1003="Yes")*(Board_Actions!$H$4:$H$1003<>"Complete")),3)),"") | F71: =IFERROR(INDEX(Board_Actions!$G$4:$G$1003,AGGREGATE(15,6,(ROW(Board_Actions!$I$4:$I$1003)-3)/((Board_Actions!$I$4:$I$1003="Yes")*(Board_Actions!$H$4:$H$1003<>"Complete")),3)),"") | G71: =IFERROR(INDEX(Board_Actions!$F$4:$F$1003,AGGREGATE(15,6,(ROW(Board_Actions!$I$4:$I$1003)-3)/((Board_Actions!$I$4:$I$1003="Yes")*(Board_Actions!$H$4:$H$1003<>"Complete")),3)),"")
A72: =IFERROR(INDEX(Board_Actions!$B$4:$B$1003,AGGREGATE(15,6,(ROW(Board_Actions!$I$4:$I$1003)-3)/((Board_Actions!$I$4:$I$1003="Yes")*(Board_Actions!$H$4:$H$1003<>"Complete")),4)),"") | E72: =IFERROR(INDEX(Board_Actions!$D$4:$D$1003,AGGREGATE(15,6,(ROW(Board_Actions!$I$4:$I$1003)-3)/((Board_Actions!$I$4:$I$1003="Yes")*(Board_Actions!$H$4:$H$1003<>"Complete")),4)),"") | F72: =IFERROR(INDEX(Board_Actions!$G$4:$G$1003,AGGREGATE(15,6,(ROW(Board_Actions!$I$4:$I$1003)-3)/((Board_Actions!$I$4:$I$1003="Yes")*(Board_Actions!$H$4:$H$1003<>"Complete")),4)),"") | G72: =IFERROR(INDEX(Board_Actions!$F$4:$F$1003,AGGREGATE(15,6,(ROW(Board_Actions!$I$4:$I$1003)-3)/((Board_Actions!$I$4:$I$1003="Yes")*(Board_Actions!$H$4:$H$1003<>"Complete")),4)),"")
A73: =IFERROR(INDEX(Board_Actions!$B$4:$B$1003,AGGREGATE(15,6,(ROW(Board_Actions!$I$4:$I$1003)-3)/((Board_Actions!$I$4:$I$1003="Yes")*(Board_Actions!$H$4:$H$1003<>"Complete")),5)),"") | E73: =IFERROR(INDEX(Board_Actions!$D$4:$D$1003,AGGREGATE(15,6,(ROW(Board_Actions!$I$4:$I$1003)-3)/((Board_Actions!$I$4:$I$1003="Yes")*(Board_Actions!$H$4:$H$1003<>"Complete")),5)),"") | F73: =IFERROR(INDEX(Board_Actions!$G$4:$G$1003,AGGREGATE(15,6,(ROW(Board_Actions!$I$4:$I$1003)-3)/((Board_Actions!$I$4:$I$1003="Yes")*(Board_Actions!$H$4:$H$1003<>"Complete")),5)),"") | G73: =IFERROR(INDEX(Board_Actions!$F$4:$F$1003,AGGREGATE(15,6,(ROW(Board_Actions!$I$4:$I$1003)-3)/((Board_Actions!$I$4:$I$1003="Yes")*(Board_Actions!$H$4:$H$1003<>"Complete")),5)),"")
A74: =IFERROR(INDEX(Board_Actions!$B$4:$B$1003,AGGREGATE(15,6,(ROW(Board_Actions!$I$4:$I$1003)-3)/((Board_Actions!$I$4:$I$1003="Yes")*(Board_Actions!$H$4:$H$1003<>"Complete")),6)),"") | E74: =IFERROR(INDEX(Board_Actions!$D$4:$D$1003,AGGREGATE(15,6,(ROW(Board_Actions!$I$4:$I$1003)-3)/((Board_Actions!$I$4:$I$1003="Yes")*(Board_Actions!$H$4:$H$1003<>"Complete")),6)),"") | F74: =IFERROR(INDEX(Board_Actions!$G$4:$G$1003,AGGREGATE(15,6,(ROW(Board_Actions!$I$4:$I$1003)-3)/((Board_Actions!$I$4:$I$1003="Yes")*(Board_Actions!$H$4:$H$1003<>"Complete")),6)),"") | G74: =IFERROR(INDEX(Board_Actions!$F$4:$F$1003,AGGREGATE(15,6,(ROW(Board_Actions!$I$4:$I$1003)-3)/((Board_Actions!$I$4:$I$1003="Yes")*(Board_Actions!$H$4:$H$1003<>"Complete")),6)),"")

Sheet Customer_Data
A1: CUSTOMER DATA — Monthly Subscriber Roll-Up
A2: Enter ONE row per month. Total Customers = end-of-month subscriber count. Homes Passed = cumulative. Update weekly/at month close.
A3: Month | B3: Period | C3: Total Customers | D3: New Sales | E3: Disconnects | F3: Homes Passed (cum)
A4: Jul-2025 | B4: 1 | C4: 4619 | D4: 523 | E4: 84 | F4: 18725
A5: Aug-2025 | B5: 2 | C5: 4948 | D5: 430 | E5: 101 | F5: 19853
A6: Sep-2025 | B6: 3 | C6: 5260 | D6: 395 | E6: 83 | F6: 21445
A7: Oct-2025 | B7: 4 | C7: 5678 | D7: 499 | E7: 81 | F7: 22949
A8: Nov-2025 | B8: 5 | C8: 6072 | D8: 468 | E8: 74 | F8: 23879
A9: Dec-2025 | B9: 6 | C9: 6358 | D9: 383 | E9: 97 | F9: 25017
A10: Jan-2026 | B10: 7 | C10: 6774 | D10: 489 | E10: 73 | F10: 26491
A11: Feb-2026 | B11: 8 | C11: 7061 | D11: 410 | E11: 123 | F11: 27616
A12: Mar-2026 | B12: 9 | C12: 7430 | D12: 474 | E12: 105 | F12: 28522
A13: Apr-2026 | B13: 10 | C13: 7706 | D13: 400 | E13: 124 | F13: 29770
A14: May-2026 | B14: 11 | C14: 8048 | D14: 431 | E14: 89 | F14: 30890
A15: Jun-2026 | B15: 12 | C15: 8411 | D15: 446 | E15: 83 | F15: 31884

Sheet Sales_Data
A1: SALES DATA — Connects & Activity (one row per county / segment / month)
A2: Add rows as deals close. Sales = connects. New MRR = added recurring $. Use dropdowns for County / Segment / Channel / Campaign / Rep.
A3: Month | B3: Period | C3: County | D3: Segment | E3: Channel | F3: Campaign | G3: Rep | H3: Leads | I3: Qualified | J3: Sales (units) | K3: New MRR ($) | L3: Door Knocks
A4: Jul-2025 | B4: 1 | C4: Robeson | D4: Residential | E4: Website | F4: Referral Rewards | G4: James Carter | H4: 195 | I4: 135 | J4: 107 | K4: 8453 | L4: 16
A5: Jul-2025 | B5: 1 | C5: Hoke | D5: Residential | E5: HOA/Developer | F5: Referral Rewards | G5: Derek Oxendine | H5: 158 | I5: 119 | J5: 91 | K5: 7189 | L5: 0
A6: Jul-2025 | B6: 1 | C6: Cumberland | D6: Residential | E6: Event | F6: Spring Fiber Push | G6: Maria Lopez | H6: 206 | I6: 112 | J6: 91 | K6: 7189 | L6: 16
A7: Jul-2025 | B7: 1 | C7: Scotland | D7: Residential | E7: Website | F7: Spring Fiber Push | G7: James Carter | H7: 166 | I7: 100 | J7: 69 | K7: 5451 | L7: 10
A8: Jul-2025 | B8: 1 | C8: Bladen | D8: Residential | E8: Event | F8: Referral Rewards | G8: Sarah Locklear | H8: 179 | I8: 79 | J8: 71 | K8: 5609 | L8: 19
A9: Jul-2025 | B9: 1 | C9: Columbus | D9: Business | E9: Door-to-Door | F9: BEAD Awareness | G9: Tanya Hunt | H9: 153 | I9: 110 | J9: 95 | K9: 17100 | L9: 530
A10: Aug-2025 | B10: 2 | C10: Robeson | D10: Residential | E10: Referral | F10: Referral Rewards | G10: Maria Lopez | H10: 171 | I10: 87 | J10: 74 | K10: 5846 | L10: 53
A11: Aug-2025 | B11: 2 | C11: Hoke | D11: Residential | E11: Door-to-Door | F11: Referral Rewards | G11: James Carter | H11: 138 | I11: 88 | J11: 64 | K11: 5056 | L11: 529
A12: Aug-2025 | B12: 2 | C12: Cumberland | D12: Residential | E12: HOA/Developer | F12: Business Connect | G12: Sarah Locklear | H12: 127 | I12: 83 | J12: 75 | K12: 5925 | L12: 4
A13: Aug-2025 | B13: 2 | C13: Scotland | D13: Business | E13: HOA/Developer | F13: BEAD Awareness | G13: Sarah Locklear | H13: 166 | I13: 89 | J13: 79 | K13: 14220 | L13: 37
A14: Aug-2025 | B14: 2 | C14: Bladen | D14: Residential | E14: Referral | F14: BEAD Awareness | G14: Maria Lopez | H14: 165 | I14: 89 | J14: 62 | K14: 4898 | L14: 57
A15: Aug-2025 | B15: 2 | C15: Columbus | D15: Business | E15: Door-to-Door | F15: Referral Rewards | G15: James Carter | H15: 142 | I15: 99 | J15: 76 | K15: 13680 | L15: 331
... A75: Jun-2026 | B75: 12 | C75: Columbus | D75: Residential | E75: HOA/Developer | F75: BEAD Awareness | G75: Tanya Hunt | H75: 141 | I75: 102 | J75: 85 | K75: 6715 | L75: 3

Sheet Pipeline
A1: PIPELINE — Open & Recently-Closed Opportunities
A2: Value = annual recurring $ (ARR). Set Stage via dropdown. Closed-Lost rows require a Lost Reason. Enterprise/DIA, HOA/Developer, Bulk are Opp Types.
A3: Opp ID | B3: Name | C3: County | D3: Segment | E3: Type | F3: Stage | G3: Value (ARR $) | H3: Rep | I3: Close Month | J3: Lost Reason
A4: OPP-1001 | B4: Lumberton Business Park | C4: Robeson | D4: Business | E4: Standard | F4: Closed-Won | G4: 19873 | H4: Sarah Locklear | I4: May-2026
A5: OPP-1002 | B5: Pembroke Town Center Bulk | C5: Robeson | D5: Business | E5: Bulk Agreement | F5: Prospect | G5: 37780 | H5: Tanya Hunt | I5: Jun-2026
A6: OPP-1003 | B6: UNCP Campus DIA | C6: Robeson | D6: Enterprise | E6: Enterprise/DIA | F6: Closed-Lost | G6: 165515 | H6: Sarah Locklear | I6: Jun-2026 | J6: Timing
A7: OPP-1004 | B7: Raeford Logistics DIA | C7: Hoke | D7: Enterprise | E7: Enterprise/DIA | F7: Proposal | G7: 81087 | H7: Derek Oxendine | I7: Jun-2026
A8: OPP-1005 | B8: Maxton Industrial | C8: Robeson | D8: Business | E8: Standard | F8: Proposal | G8: 30123 | H8: Maria Lopez | I8: Jan-2026
A9: OPP-1006 | B9: Highland Trace HOA | C9: Cumberland | D9: Residential | E9: HOA/Developer | F9: Closed-Lost | G9: 30002 | H9: Sarah Locklear | I9: Mar-2026 | J9: Lost Contact
A10: OPP-1007 | B10: Saddlebrook Developer | C10: Hoke | D10: Residential | E10: HOA/Developer | F10: Qualified | G10: 68832 | H10: Maria Lopez | I10: Feb-2026
A11: OPP-1008 | B11: St. Pauls Clinic Group | C11: Robeson | D11: Business | E11: Standard | F11: Proposal | G11: 39834 | H11: Derek Oxendine | I11: Mar-2026
A12: OPP-1009 | B12: Laurinburg Logistics | C12: Scotland | D12: Enterprise | E12: Enterprise/DIA | F12: Closed-Lost | G12: 107576 | H12: Derek Oxendine | I12: Jun-2026 | J12: Price
A13: OPP-1010 | B13: Elizabethtown Retail | C13: Bladen | D13: Business | E13: Standard | F13: Qualified | G13: 39802 | H13: Tanya Hunt | I13: Mar-2026
A14: OPP-1011 | B14: Whiteville School District | C14: Columbus | D14: Enterprise | E14: Enterprise/DIA | F14: Prospect | G14: 235671 | H14: James Carter | I14: Mar-2026
A15: OPP-1012 | B15: Red Springs Apartments Bulk | C15: Robeson | D15: Residential | E15: Bulk Agreement | F15: Negotiation | G15: 41977 | H15: Tanya Hunt | I15: Jun-2026
A16: OPP-1013 | B16: Fayetteville Tech Park | C16: Cumberland | D16: Enterprise | E16: Enterprise/DIA | F16: Closed-Won | G16: 164976 | H16: Sarah Locklear | I16: Mar-2026
A17: OPP-1014 | B17: Shannon Farms Developer | C17: Robeson | D17: Residential | E17: HOA/Developer | F17: Prospect | G17: 44807 | H17: Tanya Hunt | I17: Mar-2026
A18: OPP-1015 | B18: Hope Mills Plaza | C18: Cumberland | D18: Business | E18: Standard | F18: Closed-Lost | G18: 16597 | H18: Derek Oxendine | I18: Mar-2026 | J18: Lost Contact
A19: OPP-1016 | B19: Rowland Manufacturing | C19: Robeson | D19: Business | E19: Standard | F19: Proposal | G19: 44559 | H19: Maria Lopez | I19: Feb-2026
A20: OPP-1017 | B20: Tar Heel Cold Storage | C20: Bladen | D20: Enterprise | E20: Enterprise/DIA | F20: Qualified | G20: 195905 | H20: Derek Oxendine | I20: Jun-2026
A21: OPP-1018 | B21: Parkton HOA Phase 2 | C21: Robeson | D21: Residential | E21: HOA/Developer | F21: Negotiation | G21: 43969 | H21: James Carter | I21: Mar-2026
A22: OPP-1019 | B22: Lumber River Medical | C22: Robeson | D22: Business | E22: Standard | F22: Prospect | G22: 44993 | H22: Tanya Hunt | I22: Apr-2026
A23: OPP-1020 | B23: Scotland Health DIA | C23: Scotland | D23: Enterprise | E23: Enterprise/DIA | F23: Prospect | G23: 187064 | H23: Sarah Locklear | I23: Feb-2026
A24: OPP-1021 | B24: Bladenboro Bulk MDU | C24: Bladen | D24: Residential | E24: Bulk Agreement | F24: Prospect | G24: 61516 | H24: Sarah Locklear | I24: Jan-2026
A25: OPP-1022 | B25: Chadbourn Town Hall | C25: Columbus | D25: Business | E25: Standard | F25: Prospect | G25: 35738 | H25: Maria Lopez | I25: Apr-2026
A26: OPP-1023 | B26: Aberdeen Distribution | C26: Hoke | D26: Enterprise | E26: Enterprise/DIA | F26: Negotiation | G26: 90793 | H26: James Carter | I26: Apr-2026
A27: OPP-1024 | B27: McColl Crossing HOA | C27: Scotland | D27: Residential | E27: HOA/Developer | F27: Negotiation | G27: 76122 | H27: Sarah Locklear | I27: Jun-2026
A28: OPP-1025 | B28: Fairmont Business Row | C28: Robeson | D28: Business | E28: Standard | F28: Proposal | G28: 26919 | H28: Derek Oxendine | I28: Apr-2026

Sheet Operations_Data
A1: OPERATIONS DATA — Monthly Build / Install / Service
A2: One row per month. Homes Passed Added = new this month. Avg Days to Install = order-to-activation. Repeat Tickets = re-opened within 30 days.
A3: Month | B3: Period | C3: Homes Passed Added | D3: Footage Built | E3: Drops Completed | F3: Installs Scheduled | G3: Installs Completed | H3: Avg Days to Install | I3: Trouble Tickets | J3: Repeat Tickets | K3: Outages | L3: Activations | M3: Splices Completed
A4: Jul-2025 | B4: 1 | C4: 1419 | D4: 51035 | E4: 574 | F4: 621 | G4: 534 | H4: 10.3 | I4: 315 | J4: 48 | K4: 5 | L4: 524 | M4: 245
A5: Aug-2025 | B5: 2 | C5: 919 | D5: 45331 | E5: 450 | F5: 477 | G5: 391 | H5: 7.9 | I5: 241 | J5: 36 | K5: 1 | L5: 389 | M5: 244
A6: Sep-2025 | B6: 3 | C6: 970 | D6: 46241 | E6: 487 | F6: 531 | G6: 407 | H6: 12.6 | I6: 222 | J6: 22 | K6: 5 | L6: 394 | M6: 174
A7: Oct-2025 | B7: 4 | C7: 1452 | D7: 51182 | E7: 545 | F7: 553 | G7: 474 | H7: 12.7 | I7: 275 | J7: 31 | K7: 5 | L7: 460 | M7: 150
A8: Nov-2025 | B8: 5 | C8: 1153 | D8: 52725 | E8: 506 | F8: 567 | G8: 484 | H8: 9.6 | I8: 238 | J8: 30 | K8: 1 | L8: 482 | M8: 135
A9: Dec-2025 | B9: 6 | C9: 1134 | D9: 42417 | E9: 408 | F9: 390 | G9: 346 | H9: 5.7 | I9: 240 | J9: 24 | K9: 4 | L9: 340 | M9: 258
A10: Jan-2026 | B10: 7 | C10: 1035 | D10: 68976 | E10: 574 | F10: 634 | G10: 494 | H10: 10.7 | I10: 228 | J10: 19 | K10: 6 | L10: 481 | M10: 210
A11: Feb-2026 | B11: 8 | C11: 1333 | D11: 64941 | E11: 427 | F11: 534 | G11: 401 | H11: 9.5 | I11: 205 | J11: 17 | K11: 6 | L11: 391 | M11: 147
A12: Mar-2026 | B12: 9 | C12: 1154 | D12: 50556 | E12: 559 | F12: 590 | G12: 482 | H12: 5.5 | I12: 226 | J12: 23 | K12: 2 | L12: 480 | M12: 233
A13: Apr-2026 | B13: 10 | C13: 1463 | D13: 44416 | E13: 506 | F13: 540 | G13: 417 | H13: 10.1 | I13: 203 | J13: 31 | K13: 2 | L13: 412 | M13: 224
A14: May-2026 | B14: 11 | C14: 1397 | D14: 69546 | E14: 465 | F14: 529 | G14: 438 | H14: 5.2 | I14: 180 | J14: 28 | K14: 3 | L14: 424 | M14: 193
A15: Jun-2026 | B15: 12 | C15: 1333 | D15: 69894 | E15: 514 | F15: 521 | G15: 457 | H15: 5.3 | I15: 194 | J15: 24 | K15: 5 | L15: 456 | M15: 200

Sheet Project_Data
A1: PROJECT DATA — Capital Build Projects
A2: One row per capital project. % Complete 0-1. Status drives RYG. Permitting / Make-Ready / Splicing use Build Phase dropdown. Contractor Score 0-10.
A3: Project | B3: County | C3: Type | D3: Grant Program | E3: % Complete | F3: Status | G3: Homes Passed Target | H3: Homes Passed Actual | I3: Footage Target | J3: Footage Built | K3: Capital Budget | L3: Capital Spent | M3: Permitting | N3: Make-Ready | O3: Splicing | P3: Contractor | Q3: Contractor Score | R3: Blocker / Note
A4: Robeson BEAD Zone 1 | B4: Robeson | C4: Greenfield | D4: BEAD | E4: 0.78 | F4: On Track | G4: 3200 | H4: 2496 | I4: 165000 | J4: 128700 | K4: 4100000 | L4: 3050000 | M4: Complete | N4: Complete | O4: In Progress | P4: FiberBuild Co | Q4: 8.6
A5: Hoke CAB Expansion | B5: Hoke | C5: Greenfield | D5: CAB | E5: 0.54 | F5: At Risk | G5: 2100 | H5: 1134 | I5: 110000 | J5: 61600 | K5: 2650000 | L5: 1590000 | M5: In Progress | N5: In Progress | O5: Not Started | P5: Sandhill Construction | Q5: 6.9 | R5: Make-ready pole attach delays (utility)
A6: Pembroke Core Ring | B6: Robeson | C6: Backbone | D6: State Grant | E6: 0.92 | F6: On Track | G6: 1400 | H6: 1288 | I6: 48000 | J6: 44200 | K6: 1200000 | L6: 1080000 | M6: Complete | N6: Complete | O6: Complete | P6: FiberBuild Co | Q6: 9.1
A7: Scotland RDOF Area | B7: Scotland | C7: Greenfield | D7: RDOF | E7: 0.41 | F7: Behind | G7: 2600 | H7: 1066 | I7: 138000 | J7: 56600 | K7: 3300000 | L7: 1420000 | M7: In Progress | N7: Not Started | O7: Not Started | P7: Cape Fear Underground | Q7: 5.8 | R7: Permitting backlog + wet-weather standdown
A8: Cumberland Fiber Fill-in | B8: Cumberland | C8: Overbuild | D8: BEAD | E8: 0.66 | F8: On Track | G8: 1900 | H8: 1254 | I8: 92000 | J8: 60700 | K8: 2050000 | L8: 1330000 | M8: Complete | N8: In Progress | O8: In Progress | P8: Sandhill Construction | Q8: 7.4
A9: Bladen ARPA Rural | B9: Bladen | C9: Greenfield | D9: ARPA | E9: 0.33 | F9: At Risk | G9: 1500 | H9: 495 | I9: 102000 | J9: 33700 | K9: 2400000 | L9: 760000 | M9: In Progress | N9: Not Started | O9: Not Started | P9: Cape Fear Underground | Q9: 6.2 | R9: Material lead time on conduit
A10: Columbus BEAD Zone 2 | B10: Columbus | C10: Greenfield | D10: BEAD | E10: 0.18 | F10: Behind | G10: 2800 | H10: 504 | I10: 150000 | J10: 27000 | K10: 3500000 | L10: 590000 | M10: In Progress | N10: Not Started | O10: Not Started | P10: Sandhill Construction | Q10: 6.5 | R10: Design rework after make-ready survey
A11: Lumberton MDU Drops | B11: Robeson | C11: Drop/Activation | D11: State Grant | E11: 0.85 | F11: On Track | G11: 900 | H11: 765 | I11: 18000 | J11: 15300 | K11: 540000 | L11: 451000 | M11: Complete | N11: Complete | O11: Complete | P11: In-House Crew | Q11: 8.9
A12: Raeford Business Loop | B12: Hoke | C12: Backbone | D12: CAB | E12: 0.71 | F12: On Track | G12: 600 | H12: 426 | I12: 26000 | J12: 18900 | K12: 980000 | L12: 690000 | M12: Complete | N12: In Progress | O12: In Progress | P12: FiberBuild Co | Q12: 8.2
A13: Maxton Edge Extension | B13: Robeson | C13: Overbuild | D13: BEAD | E13: 0.49 | F13: At Risk | G13: 1100 | H13: 539 | I13: 64000 | J13: 31400 | K13: 1350000 | L13: 690000 | M13: In Progress | N13: In Progress | O13: Not Started | P13: Sandhill Construction | Q13: 7 | R13: Crew availability shared with Hoke CAB

Sheet Financial_Data
A1: FINANCIAL DATA — Monthly P&L / Capital / Cash
A2: One row per month. Revenue is total billed. OpEx excludes capitalized construction. CapEx = capitalized build. Cash Balance = end-of-month.
A3: Month | B3: Period | C3: Revenue | D3: MRR | E3: CapEx | F3: OpEx | G3: Labor | H3: Contractor | I3: Grant Reimb | J3: Budget Revenue | K3: Budget OpEx | L3: Budget CapEx | M3: Forecast Revenue | N3: Cash Balance
A4: Jul-2025 | B4: 1 | C4: 420561 | D4: 355663 | E4: 570707 | F4: 393091 | G4: 233526 | H4: 270165 | I4: 320000 | J4: 440267 | K4: 406052 | L4: 574015 | M4: 432726 | N4: 4706598
A5: Aug-2025 | B5: 2 | C5: 448772 | D5: 383965 | E5: 561313 | F5: 420533 | G5: 246178 | H5: 256854 | I5: 0 | J5: 459642 | K5: 439949 | L5: 568260 | M5: 456932 | N5: 3916670
A6: Sep-2025 | B6: 3 | C6: 454335 | D6: 411332 | E6: 866692 | F6: 350164 | G6: 224935 | H6: 255861 | I6: 290000 | J6: 444310 | K6: 339694 | L6: 835903 | M6: 461344 | N6: 3188288
A7: Oct-2025 | B7: 4 | C7: 511335 | D7: 447426 | E7: 605277 | F7: 367990 | G7: 234260 | H7: 273132 | I7: 0 | J7: 502150 | K7: 387738 | L7: 619613 | M7: 518680 | N7: 2453224
A8: Nov-2025 | B8: 5 | C8: 533332 | D8: 482117 | E8: 800043 | F8: 376337 | G8: 226043 | H8: 222834 | I8: 410000 | J8: 523942 | K8: 396109 | L8: 824129 | M8: 532684 | N8: 1997342
A9: Dec-2025 | B9: 6 | C9: 569892 | D9: 508640 | E9: 961897 | F9: 387522 | G9: 213665 | H9: 240043 | I9: 0 | J9: 596452 | K9: 387567 | L9: 895132 | M9: 585009 | N9: 977772
A10: Jan-2026 | B10: 7 | C10: 623154 | D10: 545984 | E10: 979469 | F10: 393576 | G10: 230622 | H10: 235738 | I10: 410000 | J10: 621581 | K10: 413827 | L10: 973020 | M10: 623525 | N10: 402143
A11: Feb-2026 | B11: 8 | C11: 629515 | D11: 573353 | E11: 910588 | F11: 384008 | G11: 246789 | H11: 321289 | I11: 0 | J11: 642200 | K11: 403125 | L11: 895931 | M11: 628742 | N11: -584227
A12: Mar-2026 | B12: 9 | C12: 656839 | D12: 607774 | E12: 787138 | F12: 411873 | G12: 242343 | H12: 203831 | I12: 0 | J12: 691870 | K12: 401693 | L12: 744315 | M12: 668149 | N12: -1330230
A13: Apr-2026 | B13: 10 | C13: 714060 | D13: 634974 | E13: 553306 | F13: 394268 | G13: 235216 | H13: 280039 | I13: 410000 | J13: 723695 | K13: 416784 | L13: 585245 | M13: 707247 | N13: -1433783
A14: May-2026 | B14: 11 | C14: 755217 | D14: 667984 | E14: 580058 | F14: 415560 | G14: 245190 | H14: 249946 | I14: 0 | J14: 748285 | K14: 411134 | L14: 548332 | M14: 747763 | N14: -1924130
A15: Jun-2026 | B15: 12 | C15: 790483 | D15: 703160 | E15: 979199 | F15: 397196 | G15: 227261 | H15: 311225 | I15: 0 | J15: 799116 | K15: 385535 | L15: 998830 | M15: 809191 | N15: -2821267

Sheet Revenue_Detail
A1: REVENUE DETAIL — Revenue & COGS by Product / Month
A2: One row per product per month. Used for revenue-by-product and margin-by-service-line. COGS = direct cost of that line.
A3: Month | B3: Period | C3: Product / Service Line | D3: Segment | E3: Revenue | F3: COGS
A4: Jul-2025 | B4: 1 | C4: Residential Internet | D4: Residential | E4: 209725 | F4: 59024
A5: Jul-2025 | B5: 1 | C5: Business Internet | D5: Business | E5: 74291 | F5: 20131
A6: Jul-2025 | B6: 1 | C6: Enterprise / DIA | D6: Enterprise | E6: 54745 | F6: 19319
A7: Jul-2025 | B7: 1 | C7: Managed WiFi | D7: Residential | E7: 22253 | F7: 8702
A8: Jul-2025 | B8: 1 | C8: Voice | D8: Business | E8: 17603 | F8: 7854
A9: Jul-2025 | B9: 1 | C9: Construction / Other | D9: Wholesale/Other | E9: 35983 | F9: 22327
A10: Aug-2025 | B10: 2 | C10: Residential Internet | D10: Residential | E10: 245330 | F10: 67201
A11: Aug-2025 | B11: 2 | C11: Business Internet | D11: Business | E11: 78175 | F11: 20502
A12: Aug-2025 | B12: 2 | C12: Enterprise / DIA | D12: Enterprise | E12: 62997 | F12: 21397
A13: Aug-2025 | B13: 2 | C13: Managed WiFi | D13: Residential | E13: 21177 | F13: 8503
A14: Aug-2025 | B14: 2 | C14: Voice | D14: Business | E14: 17506 | F14: 7919
A15: Aug-2025 | B15: 2 | C15: Construction / Other | D15: Wholesale/Other | E15: 36151 | F15: 22314
... A75: Jun-2026 | B75: 12 | C75: Construction / Other | D75: Wholesale/Other | E75: 59092 | F75: 35886

Sheet Grant_Data
A1: GRANT REIMBURSEMENT DATA — Drawdowns (BEAD / CAB / ARPA / State / RDOF)
A2: One row per drawdown request. Status via dropdown. Outstanding = Approved − Received (computed on Financial dashboard).
A3: Drawdown ID | B3: Program | C3: Project | D3: Amount Requested | E3: Amount Approved | F3: Amount Received | G3: Status | H3: Submission Date | I3: Expected Date | J3: Notes
A4: DRW-2025-014 | B4: BEAD | C4: Robeson BEAD Zone 1 | D4: 980000 | E4: 980000 | F4: 980000 | G4: Paid | H4: 2025-08-12 | I4: 2025-10-01 | J4: Milestone 2 paid in full
A5: DRW-2025-021 | B5: BEAD | C5: Robeson BEAD Zone 1 | D5: 1150000 | E5: 1150000 | F5: 575000 | G5: Partially Paid | H5: 2025-11-03 | I5: 2026-01-15 | J5: 50% advanced; balance on inspection
A6: DRW-2025-009 | B6: CAB | C6: Hoke CAB Expansion | D6: 640000 | E6: 590000 | F6: 590000 | G6: Paid | H6: 2025-09-20 | I6: 2025-11-30 | J6: Approved below request (ineligible poles)
A7: DRW-2026-002 | B7: CAB | C7: Hoke CAB Expansion | D7: 720000 | E7: 0 | F7: 0 | G7: Under Review | H7: 2026-02-10 | I7: 2026-05-01 | J7: Awaiting make-ready documentation
A8: DRW-2025-031 | B8: State Grant | C8: Pembroke Core Ring | D8: 480000 | E8: 480000 | F8: 480000 | G8: Paid | H8: 2025-10-15 | I8: 2025-12-15
A9: DRW-2026-007 | B9: RDOF | C9: Scotland RDOF Area | D9: 560000 | E9: 0 | F9: 0 | G9: Submitted | H9: 2026-03-22 | I9: 2026-06-30 | J9: Behind-schedule project; risk to drawdown
A10: DRW-2026-011 | B10: ARPA | C10: Bladen ARPA Rural | D10: 410000 | E10: 410000 | F10: 0 | G10: Approved | H10: 2026-04-05 | I10: 2026-07-15 | J10: Payment scheduled next quarter
A11: DRW-2026-015 | B11: BEAD | C11: Columbus BEAD Zone 2 | D11: 620000 | E11: 0 | F11: 0 | G11: Not Submitted | I11: 2026-08-01 | J11: Pending Milestone 1 completion

Sheet Sales_Targets
A1: SALES TARGETS — Monthly Goals
A2: One row per month. Sales Goal = net new connects target. Revenue Goal = new MRR target ($).
A3: Month | B3: Period | C3: Sales Goal (units) | D3: Revenue Goal (new MRR $)
A4: Jul-2025 | B4: 1 | C4: 490 | D4: 39200
A5: Aug-2025 | B5: 2 | C5: 400 | D5: 32000
A6: Sep-2025 | B6: 3 | C6: 440 | D6: 35200
A7: Oct-2025 | B7: 4 | C7: 500 | D7: 40000
A8: Nov-2025 | B8: 5 | C8: 440 | D8: 35200
A9: Dec-2025 | B9: 6 | C9: 350 | D9: 28000
A10: Jan-2026 | B10: 7 | C10: 490 | D10: 39200
A11: Feb-2026 | B11: 8 | C11: 380 | D11: 30400
A12: Mar-2026 | B12: 9 | C12: 440 | D12: 35200
A13: Apr-2026 | B13: 10 | C13: 400 | D13: 32000
A14: May-2026 | B14: 11 | C14: 470 | D14: 37600
A15: Jun-2026 | B15: 12 | C15: 420 | D15: 33600

Sheet Risk_Register
A1: RISK REGISTER
A2: Likelihood × Impact (1-5 each). Score & RYG auto-calc. Owner accountable. Review weekly; close when mitigated.
A3: Risk ID | B3: Description | C3: Category | D3: Likelihood | E3: Impact | F3: Score | G3: RYG | H3: Owner | I3: Mitigation | J3: Status | K3: Updated
A4: RSK-01 | B4: Scotland RDOF build behind schedule threatens grant drawdown eligibility | C4: Grant/Compliance | D4: 4 | E4: 5 | F4: =D4*E4 | G4: =IF(F4>=15,"RED",IF(F4>=8,"YELLOW","GREEN")) | H4: VP Construction | I4: Add second crew; weekly state check-in; replan milestones | J4: Mitigating | K4: 2026-06-05
A5: RSK-02 | B5: Make-ready / pole attachment delays from incumbent utility | C5: Regulatory | D5: 4 | E5: 4 | F5: =D5*E5 | G5: =IF(F5>=15,"RED",IF(F5>=8,"YELLOW","GREEN")) | H5: COO | I5: Escalate to NCUC; pre-file remaining attachments | J5: Open | K5: 2026-06-08
A6: RSK-03 | B6: Contractor capacity shared across Hoke + Maxton slowing both | C6: Staffing | D6: 3 | E6: 4 | F6: =D6*E6 | G6: =IF(F6>=15,"RED",IF(F6>=8,"YELLOW","GREEN")) | H6: VP Construction | I6: Negotiate dedicated crew; evaluate 2nd contractor | J6: Mitigating | K6: 2026-06-02
A7: RSK-04 | B7: Conduit / fiber material lead times (Bladen) | C7: Supply Chain | D7: 3 | E7: 3 | F7: =D7*E7 | G7: =IF(F7>=15,"RED",IF(F7>=8,"YELLOW","GREEN")) | H7: Director of Supply | I7: Pre-order long-lead items; buffer stock | J7: Monitoring | K7: 2026-05-28
A8: RSK-05 | B8: Cash timing gap from delayed BEAD reimbursements | C8: Financial | D8: 3 | E8: 5 | F8: =D8*E8 | G8: =IF(F8>=15,"RED",IF(F8>=8,"YELLOW","GREEN")) | H8: CFO | I8: Draw on revolver; accelerate drawdown documentation | J8: Open | K8: 2026-06-10
A9: RSK-06 | B9: Competitor fiber overbuild announced in Cumberland | C9: Market | D9: 3 | E9: 3 | F9: =D9*E9 | G9: =IF(F9>=15,"RED",IF(F9>=8,"YELLOW","GREEN")) | H9: VP Sales | I9: Accelerate take-rate campaign; lock HOA agreements | J9: Monitoring | K9: 2026-06-01
A10: RSK-07 | B10: Repeat trouble tickets indicate splice quality issue in Zone 1 | C10: Construction | D10: 2 | E10: 3 | F10: =D10*E10 | G10: =IF(F10>=15,"RED",IF(F10>=8,"YELLOW","GREEN")) | H10: VP Operations | I10: QA audit on splice crews; rework plan | J10: Mitigating | K10: 2026-06-06
A11: RSK-08 | B11: Install backlog rising vs crew capacity in Robeson | C11: Staffing | D11: 3 | E11: 3 | F11: =D11*E11 | G11: =IF(F11>=15,"RED",IF(F11>=8,"YELLOW","GREEN")) | H11: VP Operations | I11: Add install crew; offer install-fee promo off-peak | J11: Open | K11: 2026-06-09
A12: RSK-09 | B12: Columbus Zone 2 design rework may slip Milestone 1 + grant | C12: Grant/Compliance | D12: 4 | E12: 4 | F12: =D12*E12 | G12: =IF(F12>=15,"RED",IF(F12>=8,"YELLOW","GREEN")) | H12: VP Construction | I12: Expedite redesign; parallel-path permitting | J12: Open | K12: 2026-06-07
A13: RSK-10 | B13: Key enterprise DIA deals concentrated with single rep | C13: Market | D13: 2 | E13: 3 | F13: =D13*E13 | G13: =IF(F13>=15,"RED",IF(F13>=8,"YELLOW","GREEN")) | H13: VP Sales | I13: Cross-staff accounts; document pipeline | J13: Monitoring | K13: 2026-05-20

Sheet Board_Actions
A1: BOARD ACTION ITEMS — Decisions & Follow-ups
A2: Track decisions needed from the executive team / board. Set Decision Needed = Yes for board-level approvals.
A3: Action ID | B3: Description | C3: Category | D3: Owner | E3: Raised | F3: Due | G3: Priority | H3: Status | I3: Decision Needed
A4: ACT-01 | B4: Approve $1.2M revolver draw to bridge BEAD reimbursement timing | C4: Financial | D4: CFO / Board | E4: 2026-06-01 | F4: 2026-06-20 | G4: Critical | H4: In Progress | I4: Yes
A5: ACT-02 | B5: Authorize second construction contractor for Scotland + Columbus | C5: Construction | D5: COO | E5: 2026-05-28 | F5: 2026-06-25 | G5: High | H5: Not Started | I5: Yes
A6: ACT-03 | B6: Approve revised capital plan reforecast (Q3 FY26) | C6: Financial | D6: CFO | E6: 2026-06-05 | F6: 2026-07-01 | G6: High | H6: Not Started | I6: Yes
A7: ACT-04 | B7: Ratify HOA / bulk agreement pricing policy | C7: Commercial | D7: VP Sales | E7: 2026-05-15 | F7: 2026-06-30 | G7: Medium | H7: In Progress | I7: Yes
A8: ACT-05 | B8: Approve install-crew headcount add (2 FTE) to clear backlog | C8: Operations | D8: VP Operations | E8: 2026-06-08 | F8: 2026-06-22 | G8: High | H8: Not Started | I8: Yes
A9: ACT-06 | B9: Review competitive response plan for Cumberland overbuild | C9: Market | D9: VP Sales | E9: 2026-06-02 | F9: 2026-07-10 | G9: Medium | H9: Not Started | I9: No
A10: ACT-07 | B10: Sign off on Q4 board reporting calendar | C10: Governance | D10: Chief of Staff | E10: 2026-05-30 | F10: 2026-06-18 | G10: Low | H10: Complete | I10: No
A11: ACT-08 | B11: Approve splice-QA remediation budget for Zone 1 | C11: Operations | D11: VP Operations | E11: 2026-06-06 | F11: 2026-06-28 | G11: Medium | H11: In Progress | I11: Yes

Sheet Data_Dictionary
B1: DATA DICTIONARY — KPI Definitions & Formulas
B3: KPI / Term | C3: Definition | D3: How it is calculated | E3: Source tab
B4: Total Customers | C4: End-of-month active subscriber count | D4: Latest Customer_Data row for the month | E4: Customer_Data
B5: New Sales | C5: Gross new connections in the month | D5: Sum of New Sales for the month | E5: Customer_Data
B6: Disconnects | C6: Subscribers lost in the month | D6: Sum of Disconnects for the month | E6: Customer_Data
B7: Net Adds | C7: Net subscriber change | D7: New Sales − Disconnects | E7: Customer_Data
B8: Churn Rate | C8: Monthly subscriber churn | D8: Disconnects ÷ prior-month Total Customers | E8: Customer_Data
B9: Homes Passed | C9: Cumulative premises where fiber is available | D9: Latest cumulative value | E9: Customer_Data
B10: Take Rate | C10: Penetration of homes passed | D10: Total Customers ÷ Homes Passed | E10: Customer + Customer
B11: ARPU | C11: Average revenue per user | D11: MRR ÷ Total Customers | E11: Financial + Customer
B12: MRR | C12: Monthly recurring revenue | D12: Entered monthly | E12: Financial_Data
B13: Revenue | C13: Total billed revenue in month | D13: Entered monthly (recurring + non-recurring) | E13: Financial_Data
B14: CapEx | C14: Capitalized construction spend | D14: Entered monthly | E14: Financial_Data
... B41: RYG Health | C41: Red/Yellow/Green status | D41: Threshold rules per KPI (see card formulas) | E41: All dashboards

Sheet User_Guide
B1: USER GUIDE & UPDATE PROCESS
B3: HOW THIS WORKBOOK IS ORGANIZED
B4: • DASHBOARDS (read-only views): Exec_Dashboard, Sales_Dashboard, Ops_Dashboard, Financial_Dashboard, Board_Report.
B5: • INPUT TABS (where staff type): Customer_Data, Sales_Data, Pipeline, Operations_Data, Project_Data,
B6: Financial_Data, Revenue_Detail, Grant_Data, Sales_Targets, Risk_Register, Board_Action Items.
B7: • REFERENCE: Data_Dictionary (every KPI defined), Assumptions, User_Guide. Calc & Lists are hidden engine tabs.
B8: • Everything on the dashboards is a formula that reads the input tabs. Type data in, dashboards update automatically.
B10: THE ONE CONTROL YOU SET — REPORTING MONTH
B11: • On Exec_Dashboard, cell C5 ('Reporting Month') has a dropdown. Pick the month you are reporting on.
B12: • Every dashboard and the Board Report follow that selection for This-Month / MTD / YTD / Rolling-12 math.
B14: WEEKLY UPDATE PROCESS (≈20 minutes)
B15: 1. Customer_Data — confirm/adjust the current month row (Total Customers, New Sales, Disconnects, Homes Passed).
... B48: • When you start a new fiscal year, copy the workbook, clear the input rows, and reset Sales_Targets & budgets.

Sheet Assumptions
B1: ASSUMPTIONS & RECOMMENDATIONS FOR FUTURE AUTOMATION
B3: ASSUMPTIONS USED IN THE BUILD
B4: • Company profile: a regional fiber/FTTH ISP operating across southeastern NC counties (Robeson, Hoke,
B5: Cumberland, Scotland, Bladen, Columbus), part-funded by BEAD / CAB / ARPA / State / RDOF capital programs.
B6: • Fiscal year shown is Jul-2025 → Jun-2026 (12 months). Current reporting month defaults to Jun-2026.
B7: • Sample data is illustrative and seeded for realism; replace with your actuals. All formulas remain valid.
B8: • 'Revenue' = total billed (recurring MRR + non-recurring install/equipment). 'OpEx' excludes capitalized build.
B9: • 'CapEx' = capitalized construction. Contractor cost is shown separately for cost-per-install/home math.
B10: • Cost per Install ≈ Contractor cost ÷ installs completed (a directional unit-economics proxy, not fully-loaded).
B11: • Cost per Home Passed ≈ CapEx ÷ homes passed added that month (directional; not all CapEx is plant).
B12: • Install backlog = YTD installs scheduled − YTD installs completed (a running open-order proxy).
B13: • Churn = monthly disconnects ÷ prior-month customers (simple logo churn, not revenue churn).
... B34: 8. Add data-validation guards / input forms to prevent staff entry errors at scale.

Sheet Calc
A1: Month | B1: Period | C1: New Sales | D1: Disconnects | E1: Net Adds | F1: Total Customers | G1: Homes Passed | H1: Take Rate | I1: Churn | J1: Revenue | K1: MRR | L1: ARPU | M1: CapEx | N1: OpEx | O1: Contractor | P1: Grant Reimb | Q1: Installs Completed | R1: Installs Scheduled | S1: Install Backlog | T1: Avg Days Install | U1: Trouble Tickets | V1: Repeat Tickets | W1: Activations | X1: Footage Built | Y1: Budget Revenue | Z1: Budget OpEx | AA1: Cost / Install | AB1: Cost / Home Passed | AC1: Margin % | AD1: Rev vs Budget | AE1: Homes Passed Added
A2: =Customer_Data!A4 | B2: =Customer_Data!B4 | C2: =Customer_Data!D4 | D2: =Customer_Data!E4 | E2: =C2-D2 | F2: =Customer_Data!C4 | G2: =Customer_Data!F4 | H2: =IF(G2=0,0,F2/G2) | I2: =IF(2=2,0,IF(F1=0,0,D2/F1)) | J2: =Financial_Data!C4 | K2: =Financial_Data!D4 | L2: =IF(F2=0,0,K2/F2) | M2: =Financial_Data!E4 | N2: =Financial_Data!F4 | O2: =Financial_Data!H4 | P2: =Financial_Data!I4 | Q2: =Operations_Data!G4 | R2: =Operations_Data!F4 | S2: =IF(2=2,R2-Q2,S1+R2-Q2) | T2: =Operations_Data!H4 | U2: =Operations_Data!I4 | V2: =Operations_Data!J4 | W2: =Operations_Data!L4 | X2: =Operations_Data!D4 | Y2: =Financial_Data!J4 | Z2: =Financial_Data!K4 | AA2: =IF(Q2=0,0,O2/Q2) | AB2: =IF(AE2=0,0,M2/AE2) | AC2: =IF(J2=0,0,(J2-(N2+O2))/J2) | AD2: =J2-Y2 | AE2: =Operations_Data!C4
A3: =Customer_Data!A5 | B3: =Customer_Data!B5 | C3: =Customer_Data!D5 | D3: =Customer_Data!E5 | E3: =C3-D3 | F3: =Customer_Data!C5 | G3: =Customer_Data!F5 | H3: =IF(G3=0,0,F3/G3) | I3: =IF(3=2,0,IF(F2=0,0,D3/F2)) | J3: =Financial_Data!C5 | K3: =Financial_Data!D5 | L3: =IF(F3=0,0,K3/F3) | M3: =Financial_Data!E5 | N3: =Financial_Data!F5 | O3: =Financial_Data!H5 | P3: =Financial_Data!I5 | Q3: =Operations_Data!G5 | R3: =Operations_Data!F5 | S3: =IF(3=2,R3-Q3,S2+R3-Q3) | T3: =Operations_Data!H5 | U3: =Operations_Data!I5 | V3: =Operations_Data!J5 | W3: =Operations_Data!L5 | X3: =Operations_Data!D5 | Y3: =Financial_Data!J5 | Z3: =Financial_Data!K5 | AA3: =IF(Q3=0,0,O3/Q3) | AB3: =IF(AE3=0,0,M3/AE3) | AC3: =IF(J3=0,0,(J3-(N3+O3))/J3) | AD3: =J3-Y3 | AE3: =Operations_Data!C5
A4: =Customer_Data!A6 | B4: =Customer_Data!B6 | C4: =Customer_Data!D6 | D4: =Customer_Data!E6 | E4: =C4-D4 | F4: =Customer_Data!C6 | G4: =Customer_Data!F6 | H4: =IF(G4=0,0,F4/G4) | I4: =IF(4=2,0,IF(F3=0,0,D4/F3)) | J4: =Financial_Data!C6 | K4: =Financial_Data!D6 | L4: =IF(F4=0,0,K4/F4) | M4: =Financial_Data!E6 | N4: =Financial_Data!F6 | O4: =Financial_Data!H6 | P4: =Financial_Data!I6 | Q4: =Operations_Data!G6 | R4: =Operations_Data!F6 | S4: =IF(4=2,R4-Q4,S3+R4-Q4) | T4: =Operations_Data!H6 | U4: =Operations_Data!I6 | V4: =Operations_Data!J6 | W4: =Operations_Data!L6 | X4: =Operations_Data!D6 | Y4: =Financial_Data!J6 | Z4: =Financial_Data!K6 | AA4: =IF(Q4=0,0,O4/Q4) | AB4: =IF(AE4=0,0,M4/AE4) | AC4: =IF(J4=0,0,(J4-(N4+O4))/J4) | AD4: =J4-Y4 | AE4: =Operations_Data!C6
A5: =Customer_Data!A7 | B5: =Customer_Data!B7 | C5: =Customer_Data!D7 | D5: =Customer_Data!E7 | E5: =C5-D5 | F5: =Customer_Data!C7 | G5: =Customer_Data!F7 | H5: =IF(G5=0,0,F5/G5) | I5: =IF(5=2,0,IF(F4=0,0,D5/F4)) | J5: =Financial_Data!C7 | K5: =Financial_Data!D7 | L5: =IF(F5=0,0,K5/F5) | M5: =Financial_Data!E7 | N5: =Financial_Data!F7 | O5: =Financial_Data!H7 | P5: =Financial_Data!I7 | Q5: =Operations_Data!G7 | R5: =Operations_Data!F7 | S5: =IF(5=2,R5-Q5,S4+R5-Q5) | T5: =Operations_Data!H7 | U5: =Operations_Data!I7 | V5: =Operations_Data!J7 | W5: =Operations_Data!L7 | X5: =Operations_Data!D7 | Y5: =Financial_Data!J7 | Z5: =Financial_Data!K7 | AA5: =IF(Q5=0,0,O5/Q5) | AB5: =IF(AE5=0,0,M5/AE5) | AC5: =IF(J5=0,0,(J5-(N5+O5))/J5) | AD5: =J5-Y5 | AE5: =Operations_Data!C7
A6: =Customer_Data!A8 | B6: =Customer_Data!B8 | C6: =Customer_Data!D8 | D6: =Customer_Data!E8 | E6: =C6-D6 | F6: =Customer_Data!C8 | G6: =Customer_Data!F8 | H6: =IF(G6=0,0,F6/G6) | I6: =IF(6=2,0,IF(F5=0,0,D6/F5)) | J6: =Financial_Data!C8 | K6: =Financial_Data!D8 | L6: =IF(F6=0,0,K6/F6) | M6: =Financial_Data!E8 | N6: =Financial_Data!F8 | O6: =Financial_Data!H8 | P6: =Financial_Data!I8 | Q6: =Operations_Data!G8 | R6: =Operations_Data!F8 | S6: =IF(6=2,R6-Q6,S5+R6-Q6) | T6: =Operations_Data!H8 | U6: =Operations_Data!I8 | V6: =Operations_Data!J8 | W6: =Operations_Data!L8 | X6: =Operations_Data!D8 | Y6: =Financial_Data!J8 | Z6: =Financial_Data!K8 | AA6: =IF(Q6=0,0,O6/Q6) | AB6: =IF(AE6=0,0,M6/AE6) | AC6: =IF(J6=0,0,(J6-(N6+O6))/J6) | AD6: =J6-Y6 | AE6: =Operations_Data!C8
A7: =Customer_Data!A9 | B7: =Customer_Data!B9 | C7: =Customer_Data!D9 | D7: =Customer_Data!E9 | E7: =C7-D7 | F7: =Customer_Data!C9 | G7: =Customer_Data!F9 | H7: =IF(G7=0,0,F7/G7) | I7: =IF(7=2,0,IF(F6=0,0,D7/F6)) | J7: =Financial_Data!C9 | K7: =Financial_Data!D9 | L7: =IF(F7=0,0,K7/F7) | M7: =Financial_Data!E9 | N7: =Financial_Data!F9 | O7: =Financial_Data!H9 | P7: =Financial_Data!I9 | Q7: =Operations_Data!G9 | R7: =Operations_Data!F9 | S7: =IF(7=2,R7-Q7,S6+R7-Q7) | T7: =Operations_Data!H9 | U7: =Operations_Data!I9 | V7: =Operations_Data!J9 | W7: =Operations_Data!L9 | X7: =Operations_Data!D9 | Y7: =Financial_Data!J9 | Z7: =Financial_Data!K9 | AA7: =IF(Q7=0,0,O7/Q7) | AB7: =IF(AE7=0,0,M7/AE7) | AC7: =IF(J7=0,0,(J7-(N7+O7))/J7) | AD7: =J7-Y7 | AE7: =Operations_Data!C9
A8: =Customer_Data!A10 | B8: =Customer_Data!B10 | C8: =Customer_Data!D10 | D8: =Customer_Data!E10 | E8: =C8-D8 | F8: =Customer_Data!C10 | G8: =Customer_Data!F10 | H8: =IF(G8=0,0,F8/G8) | I8: =IF(8=2,0,IF(F7=0,0,D8/F7)) | J8: =Financial_Data!C10 | K8: =Financial_Data!D10 | L8: =IF(F8=0,0,K8/F8) | M8: =Financial_Data!E10 | N8: =Financial_Data!F10 | O8: =Financial_Data!H10 | P8: =Financial_Data!I10 | Q8: =Operations_Data!G10 | R8: =Operations_Data!F10 | S8: =IF(8=2,R8-Q8,S7+R8-Q8) | T8: =Operations_Data!H10 | U8: =Operations_Data!I10 | V8: =Operations_Data!J10 | W8: =Operations_Data!L10 | X8: =Operations_Data!D10 | Y8: =Financial_Data!J10 | Z8: =Financial_Data!K10 | AA8: =IF(Q8=0,0,O8/Q8) | AB8: =IF(AE8=0,0,M8/AE8) | AC8: =IF(J8=0,0,(J8-(N8+O8))/J8) | AD8: =J8-Y8 | AE8: =Operations_Data!C10
A9: =Customer_Data!A11 | B9: =Customer_Data!B11 | C9: =Customer_Data!D11 | D9: =Customer_Data!E11 | E9: =C9-D9 | F9: =Customer_Data!C11 | G9: =Customer_Data!F11 | H9: =IF(G9=0,0,F9/G9) | I9: =IF(9=2,0,IF(F8=0,0,D9/F8)) | J9: =Financial_Data!C11 | K9: =Financial_Data!D11 | L9: =IF(F9=0,0,K9/F9) | M9: =Financial_Data!E11 | N9: =Financial_Data!F11 | O9: =Financial_Data!H11 | P9: =Financial_Data!I11 | Q9: =Operations_Data!G11 | R9: =Operations_Data!F11 | S9: =IF(9=2,R9-Q9,S8+R9-Q9) | T9: =Operations_Data!H11 | U9: =Operations_Data!I11 | V9: =Operations_Data!J11 | W9: =Operations_Data!L11 | X9: =Operations_Data!D11 | Y9: =Financial_Data!J11 | Z9: =Financial_Data!K11 | AA9: =IF(Q9=0,0,O9/Q9) | AB9: =IF(AE9=0,0,M9/AE9) | AC9: =IF(J9=0,0,(J9-(N9+O9))/J9) | AD9: =J9-Y9 | AE9: =Operations_Data!C11
A10: =Customer_Data!A12 | B10: =Customer_Data!B12 | C10: =Customer_Data!D12 | D10: =Customer_Data!E12 | E10: =C10-D10 | F10: =Customer_Data!C12 | G10: =Customer_Data!F12 | H10: =IF(G10=0,0,F10/G10) | I10: =IF(10=2,0,IF(F9=0,0,D10/F9)) | J10: =Financial_Data!C12 | K10: =Financial_Data!D12 | L10: =IF(F10=0,0,K10/F10) | M10: =Financial_Data!E12 | N10: =Financial_Data!F12 | O10: =Financial_Data!H12 | P10: =Financial_Data!I12 | Q10: =Operations_Data!G12 | R10: =Operations_Data!F12 | S10: =IF(10=2,R10-Q10,S9+R10-Q10) | T10: =Operations_Data!H12 | U10: =Operations_Data!I12 | V10: =Operations_Data!J12 | W10: =Operations_Data!L12 | X10: =Operations_Data!D12 | Y10: =Financial_Data!J12 | Z10: =Financial_Data!K12 | AA10: =IF(Q10=0,0,O10/Q10) | AB10: =IF(AE10=0,0,M10/AE10) | AC10: =IF(J10=0,0,(J10-(N10+O10))/J10) | AD10: =J10-Y10 | AE10: =Operations_Data!C12
A11: =Customer_Data!A13 | B11: =Customer_Data!B13 | C11: =Customer_Data!D13 | D11: =Customer_Data!E13 | E11: =C11-D11 | F11: =Customer_Data!C13 | G11: =Customer_Data!F13 | H11: =IF(G11=0,0,F11/G11) | I11: =IF(11=2,0,IF(F10=0,0,D11/F10)) | J11: =Financial_Data!C13 | K11: =Financial_Data!D13 | L11: =IF(F11=0,0,K11/F11) | M11: =Financial_Data!E13 | N11: =Financial_Data!F13 | O11: =Financial_Data!H13 | P11: =Financial_Data!I13 | Q11: =Operations_Data!G13 | R11: =Operations_Data!F13 | S11: =IF(11=2,R11-Q11,S10+R11-Q11) | T11: =Operations_Data!H13 | U11: =Operations_Data!I13 | V11: =Operations_Data!J13 | W11: =Operations_Data!L13 | X11: =Operations_Data!D13 | Y11: =Financial_Data!J13 | Z11: =Financial_Data!K13 | AA11: =IF(Q11=0,0,O11/Q11) | AB11: =IF(AE11=0,0,M11/AE11) | AC11: =IF(J11=0,0,(J11-(N11+O11))/J11) | AD11: =J11-Y11 | AE11: =Operations_Data!C13
A12: =Customer_Data!A14 | B12: =Customer_Data!B14 | C12: =Customer_Data!D14 | D12: =Customer_Data!E14 | E12: =C12-D12 | F12: =Customer_Data!C14 | G12: =Customer_Data!F14 | H12: =IF(G12=0,0,F12/G12) | I12: =IF(12=2,0,IF(F11=0,0,D12/F11)) | J12: =Financial_Data!C14 | K12: =Financial_Data!D14 | L12: =IF(F12=0,0,K12/F12) | M12: =Financial_Data!E14 | N12: =Financial_Data!F14 | O12: =Financial_Data!H14 | P12: =Financial_Data!I14 | Q12: =Operations_Data!G14 | R12: =Operations_Data!F14 | S12: =IF(12=2,R12-Q12,S11+R12-Q12) | T12: =Operations_Data!H14 | U12: =Operations_Data!I14 | V12: =Operations_Data!J14 | W12: =Operations_Data!L14 | X12: =Operations_Data!D14 | Y12: =Financial_Data!J14 | Z12: =Financial_Data!K14 | AA12: =IF(Q12=0,0,O12/Q12) | AB12: =IF(AE12=0,0,M12/AE12) | AC12: =IF(J12=0,0,(J12-(N12+O12))/J12) | AD12: =J12-Y12 | AE12: =Operations_Data!C14
A13: =Customer_Data!A15 | B13: =Customer_Data!B15 | C13: =Customer_Data!D15 | D13: =Customer_Data!E15 | E13: =C13-D13 | F13: =Customer_Data!C15 | G13: =Customer_Data!F15 | H13: =IF(G13=0,0,F13/G13) | I13: =IF(13=2,0,IF(F12=0,0,D13/F12)) | J13: =Financial_Data!C15 | K13: =Financial_Data!D15 | L13: =IF(F13=0,0,K13/F13) | M13: =Financial_Data!E15 | N13: =Financial_Data!F15 | O13: =Financial_Data!H15 | P13: =Financial_Data!I15 | Q13: =Operations_Data!G15 | R13: =Operations_Data!F15 | S13: =IF(13=2,R13-Q13,S12+R13-Q13) | T13: =Operations_Data!H15 | U13: =Operations_Data!I15 | V13: =Operations_Data!J15 | W13: =Operations_Data!L15 | X13: =Operations_Data!D15 | Y13: =Financial_Data!J15 | Z13: =Financial_Data!K15 | AA13: =IF(Q13=0,0,O13/Q13) | AB13: =IF(AE13=0,0,M13/AE13) | AC13: =IF(J13=0,0,(J13-(N13+O13))/J13) | AD13: =J13-Y13 | AE13: =Operations_Data!C15

Sheet Lists
A1: Months | B1: Counties | C1: Segments | D1: Channels | E1: Campaigns | F1: Reps | G1: Products | H1: Pipeline Stage | I1: Opp Type | J1: Lost Reason | K1: Project Status | L1: Build Phase Status | M1: Grant Program | N1: Grant Status | O1: Risk Likelihood | P1: Risk Impact | Q1: Risk Status | R1: Risk Category | S1: Action Status | T1: Priority | U1: Yes/No | V1: RYG
A2: Jul-2025 | B2: Robeson | C2: Residential | D2: Door-to-Door | E2: Spring Fiber Push | F2: Maria Lopez | G2: Residential Internet | H2: Prospect | I2: Standard | J2: Price | K2: On Track | L2: Not Started | M2: BEAD | N2: Not Submitted | O2: 1 | P2: 1 | Q2: Open | R2: Construction | S2: Not Started | T2: Low | U2: Yes | V2: Green
A3: Aug-2025 | B3: Hoke | C3: Business | D3: Inbound Call | E3: BEAD Awareness | F3: James Carter | G3: Business Internet | H3: Qualified | I3: HOA/Developer | J3: Competitor Fiber | K3: At Risk | L3: In Progress | M3: CAB | N3: Submitted | O3: 2 | P3: 2 | Q3: Mitigating | R3: Financial | S3: In Progress | T3: Medium | U3: No | V3: Yellow
A4: Sep-2025 | B4: Cumberland | C4: Enterprise | D4: Website | E4: Referral Rewards | F4: Tanya Hunt | G4: Enterprise / DIA | H4: Proposal | I4: Bulk Agreement | J4: No Coverage Yet | K4: Behind | L4: Complete | M4: ARPA | N4: Under Review | O4: 3 | P4: 3 | Q4: Monitoring | R4: Regulatory | S4: Blocked | T4: High | V4: Red
A5: Oct-2025 | B5: Scotland | D5: Referral | E5: Business Connect | F5: Derek Oxendine | G5: Managed WiFi | H5: Negotiation | I5: Enterprise/DIA | J5: Timing | K5: Complete | M5: State Grant | N5: Approved | O5: 4 | P5: 4 | Q5: Closed | R5: Supply Chain | S5: Complete | T5: Critical
A6: Nov-2025 | B6: Bladen | D6: Event | E6: HOA Direct | F6: Sarah Locklear | G6: Voice | H6: Closed-Won | J6: Credit/Install Fee | M6: RDOF | N6: Partially Paid | O6: 5 | P6: 5 | R6: Staffing
A7: Dec-2025 | B7: Columbus | D7: HOA/Developer | G7: Construction / Other | H7: Closed-Lost | J7: Lost Contact | N7: Paid | R7: Market
A8: Jan-2026 | N8: Denied | R8: Grant/Compliance
A9: Feb-2026
A10: Mar-2026
A11: Apr-2026
A12: May-2026
A13: Jun-2026
