Workbook

Sheet Executive Dashboard
A1: RIVR TECH — 2027 REVENUE FORECAST DASHBOARD
A2: LREMC Technologies, LLC d/b/a RIVR Tech · Rural broadband & fiber · Robeson, Hoke, Scotland, Cumberland & surrounding NC counties
B3: Active scenario: | C3: ='Key Assumptions'!$B$4 -> Base | F3: Hoke County project (2027): | H3: ='Consolidated Revenue'!N26 -> 684000 | J3: (calibrated to H1-2026 actuals)
B5: 2027 TOTAL REVENUE | E5: RESIDENTIAL REVENUE | H5: BUSINESS REVENUE | K5: DARK FIBER REVENUE | N5: DEC MRR
B6: ='Consolidated Revenue'!N33 -> 5162584.3 | E6: ='Consolidated Revenue'!N10 -> 3891845.9 | H6: ='Consolidated Revenue'!N16 -> 567598.38 | K6: ='Consolidated Revenue'!N23 -> 19140 | N6: ='Consolidated Revenue'!M36 -> 434711.56
B8: DEC ARR RUN RATE | E8: ENDING RES SUBS | H8: ENDING BUS CUST | K8: ACTIVE DF CONTRACTS | N8: RES NET ADDS
B9: ='Consolidated Revenue'!M37 -> 5216538.8 | E9: ='Residential Forecast'!M12 -> 4072 | H9: ='Business Forecast'!M13 -> 274 | K9: =COUNTIF('Dark Fiber Forecast'!AE8:AE32,"GREEN")+COUNTIF('Dark Fiber Forecast'!AE8:AE32,"YELLOW*")+COUNTIF('Dark Fiber Forecast'!AE8:AE32,"RED*") -> 1 | N9: ='Residential Forecast'!M12-'Residential Forecast'!B6 -> 24
B11: BUS NET ADDS | E11: AVG RES ARPU | H11: AVG BUS ARPU | K11: RES CHURN % | N11: BUS CHURN %
B12: ='Business Forecast'!M13-'Business Forecast'!B6 -> 25 | E12: ='Residential Forecast'!N28 -> 75.11 | H12: ='Business Forecast'!N39 -> 160.915 | K12: ='Key Assumptions'!$B$18*'Key Assumptions'!$C$12 -> 0.015 | N12: ='Key Assumptions'!$B$38*'Key Assumptions'!$F$12 -> 0.01
A60: Chart data (auto)
A61: Residential | B61: ='Consolidated Revenue'!N10 -> 3891845.9
A62: Business | B62: ='Consolidated Revenue'!N16 -> 567598.38
A63: Dark Fiber | B63: ='Consolidated Revenue'!N23 -> 19140
A64: Project/Other | B64: ='Consolidated Revenue'!N26 -> 684000
A65: Conservative | B65: ='Scenario Analysis'!N19 -> 4901645.2
A66: Base | B66: ='Scenario Analysis'!N35 -> 5162584.3
A67: Aggressive | B67: ='Scenario Analysis'!N51 -> 5425057.9

Sheet Key Assumptions
A1: KEY ASSUMPTIONS — RIVR Tech 2027 Revenue Forecast
A2: All blue cells are editable inputs. Yellow = key assumption / management input required. Do not overwrite grey formula cells.
A3: SCENARIO SELECTION | L3: LEGEND
A4: Active Scenario (select) | B4: Base | L4: Editable input
A5: Scenario index (auto) | B5: =MATCH($B$4,$A$8:$A$10,0) -> 1 | L5: Key assumption / fill-in
L6: Calculated (do not edit)
A7: Scenario | B7: Res Adds | C7: Res Churn | D7: Res ARPU | E7: Bus Adds | F7: Bus Churn | G7: Bus ARPU | H7: DF Recur | I7: DF Timing(mo) | J7: Install/Constr | L7: Cross-sheet link
A8: Base | B8: 1 | C8: 1 | D8: 1 | E8: 1 | F8: 1 | G8: 1 | H8: 1 | I8: 0 | J8: 1
A9: Conservative | B9: 0.85 | C9: 1.2 | D9: 0.97 | E9: 0.85 | F9: 1.2 | G9: 0.97 | H9: 0.9 | I9: 1 | J9: 0.8
A10: Aggressive | B10: 1.15 | C10: 0.85 | D10: 1.03 | E10: 1.15 | F10: 0.85 | G10: 1.03 | H10: 1.1 | I10: -1 | J10: 1.2
A12: ACTIVE MULTIPLIERS (auto) | B12: =INDEX(B8:B10,$B$5) -> 1 | C12: =INDEX(C8:C10,$B$5) -> 1 | D12: =INDEX(D8:D10,$B$5) -> 1 | E12: =INDEX(E8:E10,$B$5) -> 1 | F12: =INDEX(F8:F10,$B$5) -> 1 | G12: =INDEX(G8:G10,$B$5) -> 1 | H12: =INDEX(H8:H10,$B$5) -> 1 | I12: =INDEX(I8:I10,$B$5) -> 0 | J12: =INDEX(J8:J10,$B$5) -> 1
A14: RESIDENTIAL ASSUMPTIONS
A16: Beginning residential subscribers (12/31/2026) | B16: =ROUND('2026 Actuals (H1)'!E6/B21,0) -> 4048 | C16: ← calibrated from actuals
A17: Monthly gross additions | B17: 60
A18: Monthly churn % | B18: 0.015
A19: Monthly other disconnects (non-churn) | B19: 5
A20: Monthly reconnects | B20: 8
A21: Residential ARPU ($/mo) | B21: 74
A22: ARPU increase month (1-12) | B22: 7
A23: ARPU increase % | B23: 0.03
A24: Installation revenue per new customer | B24: 99
A25: Upgrade revenue per customer | B25: 25
A26: % customers purchasing upgrades (monthly) | B26: 0.02
A27: Promotional discount % of recurring | B27: 0.02
A28: Bad-debt / collection adj % of gross | B28: 0.01
A29: Other residential revenue ($/mo, fixed) | B29: ='2026 Actuals (H1)'!E8+'2026 Actuals (H1)'!E9 -> 13305.833
A30: Voice / additional svc revenue ($/cust/mo) | B30: =ROUND('2026 Actuals (H1)'!E7/B16,2) -> 1.96
A31: Revenue recognition convention | B31: Average
A33: BUSINESS ASSUMPTIONS
A35: Beginning business customers (12/31/2026) | B35: =ROUND('2026 Actuals (H1)'!E13/B41,0) -> 249 | C35: ← calibrated from actuals
A36: Monthly gross additions - small business | B36: 4
A37: Monthly gross additions - enterprise | B37: 1
A38: Monthly churn % | B38: 0.01
A39: Monthly other disconnects (non-churn) | B39: 2
A40: Monthly reconnects | B40: 2
A41: Business ARPU ($/mo) | B41: 149
A42: ARPU increase month (1-12) | B42: 7
A43: ARPU increase % | B43: 0.03
A44: Installation & construction rev per new cust | B44: 500
A45: Static IP revenue ($/cust/mo) | B45: 0
A46: Managed Wi-Fi / router rev ($/cust/mo) | B46: 0
A47: Voice revenue ($/cust/mo) | B47: =ROUND('2026 Actuals (H1)'!E14/B35,2) -> 9.68
A48: Enterprise / DIA revenue ($/ent cust/mo) | B48: 0
A49: Other business recurring rev ($/cust/mo) | B49: 0
A50: Aid-to-construction rev per new cust | B50: 250
A51: Activation charge per new cust | B51: 100
A52: Professional services ($/mo, fixed) | B52: 1500
A53: Other nonrecurring ($/mo, fixed) | B53: 500
A54: Promotional discount % of recurring | B54: 0.015
A55: Bad-debt adjustment % of gross | B55: 0.01
A56: Revenue recognition convention | B56: Average
A57: Beginning enterprise customers (subset) | B57: 0 | C57: PLACEHOLDER—UPDATE REQUIRED
A59: DARK FIBER GLOBAL ASSUMPTIONS
A60: Default IRU recognition method | B60: Straight-line
A61: Default O&M revenue % of MRC (if blank) | B61: 0.1
A62: IRU ACCOUNTING — CFO / ACCOUNTANT REVIEW REQUIRED
A64: DARK FIBER CONTRACTS (feeds Dark Fiber Forecast automatically by start/end date) | V64: All contract rows above are PLACEHOLDER—UPDATE REQUIRED. Replace with RIVR Tech's actual dark fiber agreements.
A65: # | B65: Customer / Contract Name | C65: Contract Type | D65: Status | E65: Service Description | F65: County / Route | G65: Strands / Pairs | H65: Start Date | I65: End Date | J65: Monthly Recurring Charge | K65: Annual Escalation % | L65: Escalation Date | M65: One-time Construction | N65: One-time Activation | O65: IRU Upfront Payment | P65: IRU Term (yrs) | Q65: IRU Recognition Method | R65: O&M Revenue ($/mo) | S65: Renewal Prob % | T65: Notes
A66: 1 | B66: PLACEHOLDER — Current dark fiber book (H1 2026 run-rate) | C66: Monthly dark fiber lease | D66: Active | E66: Aggregate of existing DF leases — split into real contracts | F66: Multiple | G66: 0 | H66: 45292 | I66: 47848 | J66: 1595 | K66: 0 | L66: 46388 | M66: 0 | N66: 0 | O66: 0 | P66: 0 | Q66: None | R66: 0 | S66: 0.8 | T66: Set to the H1 2026 actual DF run-rate ($1,595/mo). Replace with individual real contracts; the IRU / escalation / expiration engine below will then activate.
A67: 2
A68: 3
A69: 4
A70: 5
A71: 6
A72: 7
A73: 8
A74: 9
A75: 10
A76: 11
A77: 12
A78: 13
... A90: 25
A92: SPECIAL / PROJECT REVENUE (2027)
A93: Hoke County project revenue ($/mo) | B93: 57000 | C93: NEW PROJECT
A94: Hoke project start month (1-12) | B94: 1

Sheet 2026 Actuals (H1)
A1: 2026 ACTUALS — Income Statement (H1, QTR ending June 30, 2026)
A2: Source data from RIVR Tech income statement. Blue = actuals as reported; grey = derived (YTD, monthly run-rate, annualized). Feeds the 2027 model calibration.
B4: Qtr 1 | C4: Qtr 2 | D4: YTD | E4: Monthly Avg | F4: Annualized
A5: OPERATING REVENUE — RESIDENTIAL
A6: Residential Broadband | B6: 937587 | C6: 859936 | D6: =B6+C6 -> 1797523 | E6: =D6/6 -> 299587.17 | F6: =E6*12 -> 3595046
A7: Residential Voice | B7: 23659 | C7: 24039 | D7: =B7+C7 -> 47698 | E7: =D7/6 -> 7949.6667 | F7: =E7*12 -> 95396
A8: Residential Wifi | B8: 721 | C8: 714 | D8: =B8+C8 -> 1435 | E8: =D8/6 -> 239.16667 | F8: =E8*12 -> 2870
A9: Residential Other | B9: 36481 | C9: 41919 | D9: =B9+C9 -> 78400 | E9: =D9/6 -> 13066.667 | F9: =E9*12 -> 156800
A10: Less ACP Credits | B10: 0 | C10: 0 | D10: =B10+C10 -> 0 | E10: =D10/6 -> 0 | F10: =E10*12 -> 0
A11: Total Residential | B11: =B6+B7+B8+B9-B10 -> 998448 | C11: =C6+C7+C8+C9-C10 -> 926608 | D11: =B11+C11 -> 1925056 | E11: =D11/6 -> 320842.67 | F11: =E11*12 -> 3850112
A12: OPERATING REVENUE — BUSINESS
A13: Business Broadband | B13: 109308 | C13: 113631 | D13: =B13+C13 -> 222939 | E13: =D13/6 -> 37156.5 | F13: =E13*12 -> 445878
A14: Business Voice | B14: 7167 | C14: 7289 | D14: =B14+C14 -> 14456 | E14: =D14/6 -> 2409.3333 | F14: =E14*12 -> 28912
A15: Business Wifi | B15: 0 | C15: 0 | D15: =B15+C15 -> 0 | E15: =D15/6 -> 0 | F15: =E15*12 -> 0
A16: Business Other | B16: -277 | C16: -830 | D16: =B16+C16 -> -1107 | E16: =D16/6 -> -184.5 | F16: =E16*12 -> -2214
A17: Total Business | B17: =B13+B14+B15+B16 -> 116198 | C17: =C13+C14+C15+C16 -> 120090 | D17: =B17+C17 -> 236288 | E17: =D17/6 -> 39381.333 | F17: =E17*12 -> 472576
A18: Dark Fiber | B18: 6960 | C18: 2610 | D18: =B18+C18 -> 9570 | E18: =D18/6 -> 1595 | F18: =E18*12 -> 19140
A19: Total Operating Revenue | B19: =B11+B17+B18 -> 1121606 | C19: =C11+C17+C18 -> 1049308 | D19: =B19+C19 -> 2170914 | E19: =D19/6 -> 361819 | F19: =E19*12 -> 4341828
A21: EXPENSES
A22: Cost of Goods Sold | B22: 198002 | C22: 123244 | D22: =B22+C22 -> 321246 | E22: =D22/6 -> 53541 | F22: =E22*12 -> 642492
A23: LREMC Intercompany Expenses | B23: 10483 | C23: 179793 | D23: =B23+C23 -> 190276 | E23: =D23/6 -> 31712.667 | F23: =E23*12 -> 380552
A24: Engineering & Operations | B24: 193141 | C24: 239129 | D24: =B24+C24 -> 432270 | E24: =D24/6 -> 72045 | F24: =E24*12 -> 864540
A25: Marketing | B25: 75988 | C25: 83218 | D25: =B25+C25 -> 159206 | E25: =D25/6 -> 26534.333 | F25: =E25*12 -> 318412
A26: Sales and Customer Support | B26: 59317 | C26: 57351 | D26: =B26+C26 -> 116668 | E26: =D26/6 -> 19444.667 | F26: =E26*12 -> 233336
A27: General and Admin | B27: 311772 | C27: 436254 | D27: =B27+C27 -> 748026 | E27: =D27/6 -> 124671 | F27: =E27*12 -> 1496052
A28: Accounting | B28: 26972 | C28: 35185 | D28: =B28+C28 -> 62157 | E28: =D28/6 -> 10359.5 | F28: =E28*12 -> 124314
A29: HR Support | B29: 36322 | C29: 42959 | D29: =B29+C29 -> 79281 | E29: =D29/6 -> 13213.5 | F29: =E29*12 -> 158562
A30: IT Support | B30: 9495 | C30: 10026 | D30: =B30+C30 -> 19521 | E30: =D30/6 -> 3253.5 | F30: =E30*12 -> 39042
A31: Depreciation and Amortization | B31: 82166 | C31: 99236 | D31: =B31+C31 -> 181402 | E31: =D31/6 -> 30233.667 | F31: =E31*12 -> 362804
A32: Taxes | B32: 4188 | C32: 2865 | D32: =B32+C32 -> 7053 | E32: =D32/6 -> 1175.5 | F32: =E32*12 -> 14106
A33: Total Expenses | B33: =SUM(B22:B32) -> 1007846 | C33: =SUM(C22:C32) -> 1309260 | D33: =B33+C33 -> 2317106 | E33: =D33/6 -> 386184.33 | F33: =E33*12 -> 4634212
A34: Operating Income (loss) | B34: =B19-B33 -> 113760 | C34: =C19-C33 -> -259952 | D34: =B34+C34 -> -146192 | E34: =D34/6 -> -24365.333 | F34: =E34*12 -> -292384
A36: NONOPERATING REVENUE (EXPENSE)
A37: Grant Income | B37: 196019 | C37: 196019 | D37: =B37+C37 -> 392038
A38: BTAP Revenue | B38: 44566 | C38: 6120 | D38: =B38+C38 -> 50686
A39: CAB Revenue | B39: 0 | C39: 48171 | D39: =B39+C39 -> 48171
A40: Other Income | B40: -1500 | C40: 0 | D40: =B40+C40 -> -1500
A41: CAB Grant Expense | B41: -3622 | C41: -2304 | D41: =B41+C41 -> -5926
A42: BTAP Grant Expense | B42: 0 | C42: 0 | D42: =B42+C42 -> 0
A43: BEAD Grant Expense | B43: 114241 | C43: 3032 | D43: =B43+C43 -> 117273
A44: Interest Income | B44: 0 | C44: 0 | D44: =B44+C44 -> 0
A45: Interest Expense | B45: -116277 | C45: -115833 | D45: =B45+C45 -> -232110
A46: Total Nonoperating Income (Expense) | B46: =SUM(B37:B45) -> 233427 | C46: =SUM(C37:C45) -> 135205 | D46: =B46+C46 -> 368632
A47: Net Income (loss) | B47: =B34+B46 -> 347187 | C47: =C34+C46 -> -124747 | D47: =B47+C47 -> 222440
A49: CALIBRATION TO 2027 MODEL
A50: Residential ARPU (from Key Assumptions) | B50: ='Key Assumptions'!B21 -> 74
A51: Implied residential subscribers (H1 run-rate) | B51: =ROUND(E6/B50,0) -> 4048
A52: Business ARPU (from Key Assumptions) | B52: ='Key Assumptions'!B41 -> 149
A53: Implied business customers (H1 run-rate) | B53: =ROUND(E13/B52,0) -> 249
A54: Dark fiber monthly run-rate (actual) | B54: =E18 -> 1595
A55: Annualized total operating revenue | B55: =F19 -> 4341828
A56: Variable cost ratio (COGS / revenue) | B56: =IFERROR(F22/F19,0) -> 0.1479773
A57: Annualized fixed operating cost (ex-COGS) | B57: =F33-F22 -> 3991720
A59: Note: H1 2026 net income of $222,441 was driven largely by grant/BTAP/CAB nonoperating income; operating result was a $(146,191) loss. The 2027 model forecasts operating revenue only.

Sheet Residential Forecast
A1: RESIDENTIAL BROADBAND FORECAST — 2027
A2: Monthly customer roll-forward and revenue. Grey = formulas (do not edit); edit assumptions on Key Assumptions.
A3: Metric | B3: 46388 | C3: 46419 | D3: 46447 | E3: 46478 | F3: 46508 | G3: 46539 | H3: 46569 | I3: 46600 | J3: 46631 | K3: 46661 | L3: 46692 | M3: 46722 | N3: FY 2027
A4: Month # | B4: 1 | C4: 2 | D4: 3 | E4: 4 | F4: 5 | G4: 6 | H4: 7 | I4: 8 | J4: 9 | K4: 10 | L4: 11 | M4: 12
A5: CUSTOMER MOVEMENT
A6: Beginning subscribers | B6: ='Key Assumptions'!$B$16 -> 4048 | C6: =B12 -> 4050 | D6: =C12 -> 4052 | E6: =D12 -> 4054 | F6: =E12 -> 4056 | G6: =F12 -> 4058 | H6: =G12 -> 4060 | I6: =H12 -> 4062 | J6: =I12 -> 4064 | ... M6: =L12 -> 4070 | N6: =B6 -> 4048
A7: Gross additions | B7: =ROUND('Key Assumptions'!$B$17*'Key Assumptions'!$B$12,0) -> 60 | C7: =ROUND('Key Assumptions'!$B$17*'Key Assumptions'!$B$12,0) -> 60 | D7: =ROUND('Key Assumptions'!$B$17*'Key Assumptions'!$B$12,0) -> 60 | E7: =ROUND('Key Assumptions'!$B$17*'Key Assumptions'!$B$12,0) -> 60 | F7: =ROUND('Key Assumptions'!$B$17*'Key Assumptions'!$B$12,0) -> 60 | G7: =ROUND('Key Assumptions'!$B$17*'Key Assumptions'!$B$12,0) -> 60 | H7: =ROUND('Key Assumptions'!$B$17*'Key Assumptions'!$B$12,0) -> 60 | I7: =ROUND('Key Assumptions'!$B$17*'Key Assumptions'!$B$12,0) -> 60 | ... M7: =ROUND('Key Assumptions'!$B$17*'Key Assumptions'!$B$12,0) -> 60 | N7: =SUM(B7:M7) -> 720
A8: Reconnects | B8: ='Key Assumptions'!$B$20 -> 8 | C8: ='Key Assumptions'!$B$20 -> 8 | D8: ='Key Assumptions'!$B$20 -> 8 | E8: ='Key Assumptions'!$B$20 -> 8 | F8: ='Key Assumptions'!$B$20 -> 8 | G8: ='Key Assumptions'!$B$20 -> 8 | H8: ='Key Assumptions'!$B$20 -> 8 | I8: ='Key Assumptions'!$B$20 -> 8 | ... M8: ='Key Assumptions'!$B$20 -> 8 | N8: =SUM(B8:M8) -> 96
A9: Disconnects from churn | B9: =ROUND(B6*'Key Assumptions'!$B$18*'Key Assumptions'!$C$12,0) -> 61 | C9: =ROUND(C6*'Key Assumptions'!$B$18*'Key Assumptions'!$C$12,0) -> 61 | D9: =ROUND(D6*'Key Assumptions'!$B$18*'Key Assumptions'!$C$12,0) -> 61 | E9: =ROUND(E6*'Key Assumptions'!$B$18*'Key Assumptions'!$C$12,0) -> 61 | F9: =ROUND(F6*'Key Assumptions'!$B$18*'Key Assumptions'!$C$12,0) -> 61 | G9: =ROUND(G6*'Key Assumptions'!$B$18*'Key Assumptions'!$C$12,0) -> 61 | H9: =ROUND(H6*'Key Assumptions'!$B$18*'Key Assumptions'!$C$12,0) -> 61 | I9: =ROUND(I6*'Key Assumptions'!$B$18*'Key Assumptions'!$C$12,0) -> 61 | ... M9: =ROUND(M6*'Key Assumptions'!$B$18*'Key Assumptions'!$C$12,0) -> 61 | N9: =SUM(B9:M9) -> 732
A10: Other disconnects | B10: ='Key Assumptions'!$B$19 -> 5 | C10: ='Key Assumptions'!$B$19 -> 5 | D10: ='Key Assumptions'!$B$19 -> 5 | E10: ='Key Assumptions'!$B$19 -> 5 | F10: ='Key Assumptions'!$B$19 -> 5 | G10: ='Key Assumptions'!$B$19 -> 5 | H10: ='Key Assumptions'!$B$19 -> 5 | I10: ='Key Assumptions'!$B$19 -> 5 | ... M10: ='Key Assumptions'!$B$19 -> 5 | N10: =SUM(B10:M10) -> 60
A11: Net additions | B11: =B7+B8-B9-B10 -> 2 | C11: =C7+C8-C9-C10 -> 2 | D11: =D7+D8-D9-D10 -> 2 | E11: =E7+E8-E9-E10 -> 2 | F11: =F7+F8-F9-F10 -> 2 | G11: =G7+G8-G9-G10 -> 2 | H11: =H7+H8-H9-H10 -> 2 | I11: =I7+I8-I9-I10 -> 2 | ... M11: =M7+M8-M9-M10 -> 2 | N11: =SUM(B11:M11) -> 24
A12: Ending subscribers | B12: =MAX(0,B6+B11) -> 4050 | C12: =MAX(0,C6+C11) -> 4052 | D12: =MAX(0,D6+D11) -> 4054 | E12: =MAX(0,E6+E11) -> 4056 | F12: =MAX(0,F6+F11) -> 4058 | G12: =MAX(0,G6+G11) -> 4060 | H12: =MAX(0,H6+H11) -> 4062 | I12: =MAX(0,I6+I11) -> 4064 | ... M12: =MAX(0,M6+M11) -> 4072 | N12: =M12 -> 4072
A13: Average billable subscribers | B13: =IF('Key Assumptions'!$B$31="Average",(B6+B12)/2,IF('Key Assumptions'!$B$31="Beginning",B6,B12)) -> 4049 | C13: =IF('Key Assumptions'!$B$31="Average",(C6+C12)/2,IF('Key Assumptions'!$B$31="Beginning",C6,C12)) -> 4051 | D13: =IF('Key Assumptions'!$B$31="Average",(D6+D12)/2,IF('Key Assumptions'!$B$31="Beginning",D6,D12)) -> 4053 | E13: =IF('Key Assumptions'!$B$31="Average",(E6+E12)/2,IF('Key Assumptions'!$B$31="Beginning",E6,E12)) -> 4055 | F13: =IF('Key Assumptions'!$B$31="Average",(F6+F12)/2,IF('Key Assumptions'!$B$31="Beginning",F6,F12)) -> 4057 | G13: =IF('Key Assumptions'!$B$31="Average",(G6+G12)/2,IF('Key Assumptions'!$B$31="Beginning",G6,G12)) -> 4059 | H13: =IF('Key Assumptions'!$B$31="Average",(H6+H12)/2,IF('Key Assumptions'!$B$31="Beginning",H6,H12)) -> 4061 | I13: =IF('Key Assumptions'!$B$31="Average",(I6+I12)/2,IF('Key Assumptions'!$B$31="Beginning",I6,I12)) -> 4063 | ... M13: =IF('Key Assumptions'!$B$31="Average",(M6+M12)/2,IF('Key Assumptions'!$B$31="Beginning",M6,M12)) -> 4071 | N13: =AVERAGE(B13:M13) -> 4060
A14: REVENUE
A15: Standard recurring broadband revenue | B15: =B13*('Key Assumptions'!$B$21*IF(B4>='Key Assumptions'!$B$22,1+'Key Assumptions'!$B$23,1)*'Key Assumptions'!$D$12) -> 299626 | C15: =C13*('Key Assumptions'!$B$21*IF(C4>='Key Assumptions'!$B$22,1+'Key Assumptions'!$B$23,1)*'Key Assumptions'!$D$12) -> 299774 | D15: =D13*('Key Assumptions'!$B$21*IF(D4>='Key Assumptions'!$B$22,1+'Key Assumptions'!$B$23,1)*'Key Assumptions'!$D$12) -> 299922 | E15: =E13*('Key Assumptions'!$B$21*IF(E4>='Key Assumptions'!$B$22,1+'Key Assumptions'!$B$23,1)*'Key Assumptions'!$D$12) -> 300070 | F15: =F13*('Key Assumptions'!$B$21*IF(F4>='Key Assumptions'!$B$22,1+'Key Assumptions'!$B$23,1)*'Key Assumptions'!$D$12) -> 300218 | G15: =G13*('Key Assumptions'!$B$21*IF(G4>='Key Assumptions'!$B$22,1+'Key Assumptions'!$B$23,1)*'Key Assumptions'!$D$12) -> 300366 | H15: =H13*('Key Assumptions'!$B$21*IF(H4>='Key Assumptions'!$B$22,1+'Key Assumptions'!$B$23,1)*'Key Assumptions'!$D$12) -> 309529.42 | I15: =I13*('Key Assumptions'!$B$21*IF(I4>='Key Assumptions'!$B$22,1+'Key Assumptions'!$B$23,1)*'Key Assumptions'!$D$12) -> 309681.86 | ... M15: =M13*('Key Assumptions'!$B$21*IF(M4>='Key Assumptions'!$B$22,1+'Key Assumptions'!$B$23,1)*'Key Assumptions'!$D$12) -> 310291.62 | N15: =SUM(B15:M15) -> 3659439.1
A16: Upgrade revenue | B16: =B13*'Key Assumptions'!$B$26*'Key Assumptions'!$B$25 -> 2024.5 | C16: =C13*'Key Assumptions'!$B$26*'Key Assumptions'!$B$25 -> 2025.5 | D16: =D13*'Key Assumptions'!$B$26*'Key Assumptions'!$B$25 -> 2026.5 | E16: =E13*'Key Assumptions'!$B$26*'Key Assumptions'!$B$25 -> 2027.5 | F16: =F13*'Key Assumptions'!$B$26*'Key Assumptions'!$B$25 -> 2028.5 | G16: =G13*'Key Assumptions'!$B$26*'Key Assumptions'!$B$25 -> 2029.5 | H16: =H13*'Key Assumptions'!$B$26*'Key Assumptions'!$B$25 -> 2030.5 | I16: =I13*'Key Assumptions'!$B$26*'Key Assumptions'!$B$25 -> 2031.5 | ... M16: =M13*'Key Assumptions'!$B$26*'Key Assumptions'!$B$25 -> 2035.5 | N16: =SUM(B16:M16) -> 24360
A17: Installation revenue | B17: =B7*'Key Assumptions'!$B$24*'Key Assumptions'!$J$12 -> 5940 | C17: =C7*'Key Assumptions'!$B$24*'Key Assumptions'!$J$12 -> 5940 | D17: =D7*'Key Assumptions'!$B$24*'Key Assumptions'!$J$12 -> 5940 | E17: =E7*'Key Assumptions'!$B$24*'Key Assumptions'!$J$12 -> 5940 | F17: =F7*'Key Assumptions'!$B$24*'Key Assumptions'!$J$12 -> 5940 | G17: =G7*'Key Assumptions'!$B$24*'Key Assumptions'!$J$12 -> 5940 | H17: =H7*'Key Assumptions'!$B$24*'Key Assumptions'!$J$12 -> 5940 | I17: =I7*'Key Assumptions'!$B$24*'Key Assumptions'!$J$12 -> 5940 | ... M17: =M7*'Key Assumptions'!$B$24*'Key Assumptions'!$J$12 -> 5940 | N17: =SUM(B17:M17) -> 71280
A18: Voice / additional service revenue | B18: =B13*'Key Assumptions'!$B$30 -> 7936.04 | C18: =C13*'Key Assumptions'!$B$30 -> 7939.96 | D18: =D13*'Key Assumptions'!$B$30 -> 7943.88 | E18: =E13*'Key Assumptions'!$B$30 -> 7947.8 | F18: =F13*'Key Assumptions'!$B$30 -> 7951.72 | G18: =G13*'Key Assumptions'!$B$30 -> 7955.64 | H18: =H13*'Key Assumptions'!$B$30 -> 7959.56 | I18: =I13*'Key Assumptions'!$B$30 -> 7963.48 | ... M18: =M13*'Key Assumptions'!$B$30 -> 7979.16 | N18: =SUM(B18:M18) -> 95491.2
A19: Other residential revenue | B19: ='Key Assumptions'!$B$29 -> 13305.833 | C19: ='Key Assumptions'!$B$29 -> 13305.833 | D19: ='Key Assumptions'!$B$29 -> 13305.833 | E19: ='Key Assumptions'!$B$29 -> 13305.833 | F19: ='Key Assumptions'!$B$29 -> 13305.833 | G19: ='Key Assumptions'!$B$29 -> 13305.833 | H19: ='Key Assumptions'!$B$29 -> 13305.833 | I19: ='Key Assumptions'!$B$29 -> 13305.833 | ... M19: ='Key Assumptions'!$B$29 -> 13305.833 | N19: =SUM(B19:M19) -> 159670
A20: Residential recurring revenue | B20: =B15+B18+B19 -> 320867.87 | C20: =C15+C18+C19 -> 321019.79 | D20: =D15+D18+D19 -> 321171.71 | E20: =E15+E18+E19 -> 321323.63 | F20: =F15+F18+F19 -> 321475.55 | G20: =G15+G18+G19 -> 321627.47 | H20: =H15+H18+H19 -> 330794.81 | I20: =I15+I18+I19 -> 330951.17 | ... M20: =M15+M18+M19 -> 331576.61 | N20: =SUM(B20:M20) -> 3914600.3
A21: Residential one-time revenue | B21: =B16+B17 -> 7964.5 | C21: =C16+C17 -> 7965.5 | D21: =D16+D17 -> 7966.5 | E21: =E16+E17 -> 7967.5 | F21: =F16+F17 -> 7968.5 | G21: =G16+G17 -> 7969.5 | H21: =H16+H17 -> 7970.5 | I21: =I16+I17 -> 7971.5 | ... M21: =M16+M17 -> 7975.5 | N21: =SUM(B21:M21) -> 95640
A22: Gross residential revenue | B22: =B20+B21 -> 328832.37 | C22: =C20+C21 -> 328985.29 | D22: =D20+D21 -> 329138.21 | E22: =E20+E21 -> 329291.13 | F22: =F20+F21 -> 329444.05 | G22: =G20+G21 -> 329596.97 | H22: =H20+H21 -> 338765.31 | I22: =I20+I21 -> 338922.67 | ... M22: =M20+M21 -> 339552.11 | N22: =SUM(B22:M22) -> 4010240.3
A23: Promotional discounts | B23: =-B20*'Key Assumptions'!$B$27 -> -6417.3575 | C23: =-C20*'Key Assumptions'!$B$27 -> -6420.3959 | D23: =-D20*'Key Assumptions'!$B$27 -> -6423.4343 | E23: =-E20*'Key Assumptions'!$B$27 -> -6426.4727 | F23: =-F20*'Key Assumptions'!$B$27 -> -6429.5111 | G23: =-G20*'Key Assumptions'!$B$27 -> -6432.5495 | H23: =-H20*'Key Assumptions'!$B$27 -> -6615.8963 | I23: =-I20*'Key Assumptions'!$B$27 -> -6619.0235 | ... M23: =-M20*'Key Assumptions'!$B$27 -> -6631.5323 | N23: =SUM(B23:M23) -> -78292.006
A24: Bad-debt adjustment | B24: =-B22*'Key Assumptions'!$B$28 -> -3288.3237 | C24: =-C22*'Key Assumptions'!$B$28 -> -3289.8529 | D24: =-D22*'Key Assumptions'!$B$28 -> -3291.3821 | E24: =-E22*'Key Assumptions'!$B$28 -> -3292.9113 | F24: =-F22*'Key Assumptions'!$B$28 -> -3294.4405 | G24: =-G22*'Key Assumptions'!$B$28 -> -3295.9697 | H24: =-H22*'Key Assumptions'!$B$28 -> -3387.6531 | I24: =-I22*'Key Assumptions'!$B$28 -> -3389.2267 | ... M24: =-M22*'Key Assumptions'!$B$28 -> -3395.5211 | N24: =SUM(B24:M24) -> -40102.403
A25: Net residential revenue | B25: =B22+B23+B24 -> 319126.69 | C25: =C22+C23+C24 -> 319275.04 | D25: =D22+D23+D24 -> 319423.4 | E25: =E22+E23+E24 -> 319571.75 | F25: =F22+F23+F24 -> 319720.1 | G25: =G22+G23+G24 -> 319868.45 | H25: =H22+H23+H24 -> 328761.76 | I25: =I22+I23+I24 -> 328914.42 | ... M25: =M22+M23+M24 -> 329525.06 | N25: =SUM(B25:M25) -> 3891845.9
A26: Residential MRR | B26: =B20+B23 -> 314450.52 | C26: =C20+C23 -> 314599.4 | D26: =D20+D23 -> 314748.28 | E26: =E20+E23 -> 314897.16 | F26: =F20+F23 -> 315046.04 | G26: =G20+G23 -> 315194.92 | H26: =H20+H23 -> 324178.92 | I26: =I20+I23 -> 324332.15 | ... M26: =M20+M23 -> 324945.08 | N26: =M26 -> 324945.08
A27: Residential ARR run rate | B27: =B26*12 -> 3773406.2 | C27: =C26*12 -> 3775192.8 | D27: =D26*12 -> 3776979.3 | E27: =E26*12 -> 3778765.9 | F27: =F26*12 -> 3780552.5 | G27: =G26*12 -> 3782339.1 | H27: =H26*12 -> 3890147 | I27: =I26*12 -> 3891985.8 | ... M27: =M26*12 -> 3899341 | N27: =M27 -> 3899341
A28: Effective residential ARPU | B28: =IFERROR(B15/B13,0) -> 74 | C28: =IFERROR(C15/C13,0) -> 74 | D28: =IFERROR(D15/D13,0) -> 74 | E28: =IFERROR(E15/E13,0) -> 74 | F28: =IFERROR(F15/F13,0) -> 74 | G28: =IFERROR(G15/G13,0) -> 74 | H28: =IFERROR(H15/H13,0) -> 76.22 | I28: =IFERROR(I15/I13,0) -> 76.22 | ... M28: =IFERROR(M15/M13,0) -> 76.22 | N28: =AVERAGE(B28:M28) -> 75.11

Sheet Business Forecast
A1: BUSINESS BROADBAND FORECAST — 2027
A2: Recurring separated from construction/installation one-time revenue. Grey = formulas; edit assumptions on Key Assumptions.
A3: Metric | B3: 46388 | C3: 46419 | D3: 46447 | E3: 46478 | F3: 46508 | G3: 46539 | H3: 46569 | I3: 46600 | J3: 46631 | K3: 46661 | L3: 46692 | M3: 46722 | N3: FY 2027
A4: Month # | B4: 1 | C4: 2 | D4: 3 | E4: 4 | F4: 5 | G4: 6 | H4: 7 | I4: 8 | J4: 9 | K4: 10 | L4: 11 | M4: 12
A5: CUSTOMER MOVEMENT
A6: Beginning business customers | B6: ='Key Assumptions'!$B$35 -> 249 | C6: =B13 -> 252 | D6: =C13 -> 254 | E6: =D13 -> 256 | F6: =E13 -> 258 | G6: =F13 -> 260 | H6: =G13 -> 262 | I6: =H13 -> 264 | J6: =I13 -> 266 | ... M6: =L13 -> 272 | N6: =B6 -> 249
A7: New small-business customers | B7: =ROUND('Key Assumptions'!$B$36*'Key Assumptions'!$E$12,0) -> 4 | C7: =ROUND('Key Assumptions'!$B$36*'Key Assumptions'!$E$12,0) -> 4 | D7: =ROUND('Key Assumptions'!$B$36*'Key Assumptions'!$E$12,0) -> 4 | E7: =ROUND('Key Assumptions'!$B$36*'Key Assumptions'!$E$12,0) -> 4 | F7: =ROUND('Key Assumptions'!$B$36*'Key Assumptions'!$E$12,0) -> 4 | G7: =ROUND('Key Assumptions'!$B$36*'Key Assumptions'!$E$12,0) -> 4 | H7: =ROUND('Key Assumptions'!$B$36*'Key Assumptions'!$E$12,0) -> 4 | I7: =ROUND('Key Assumptions'!$B$36*'Key Assumptions'!$E$12,0) -> 4 | ... M7: =ROUND('Key Assumptions'!$B$36*'Key Assumptions'!$E$12,0) -> 4 | N7: =SUM(B7:M7) -> 48
A8: New enterprise customers | B8: =ROUND('Key Assumptions'!$B$37*'Key Assumptions'!$E$12,0) -> 1 | C8: =ROUND('Key Assumptions'!$B$37*'Key Assumptions'!$E$12,0) -> 1 | D8: =ROUND('Key Assumptions'!$B$37*'Key Assumptions'!$E$12,0) -> 1 | E8: =ROUND('Key Assumptions'!$B$37*'Key Assumptions'!$E$12,0) -> 1 | F8: =ROUND('Key Assumptions'!$B$37*'Key Assumptions'!$E$12,0) -> 1 | G8: =ROUND('Key Assumptions'!$B$37*'Key Assumptions'!$E$12,0) -> 1 | H8: =ROUND('Key Assumptions'!$B$37*'Key Assumptions'!$E$12,0) -> 1 | I8: =ROUND('Key Assumptions'!$B$37*'Key Assumptions'!$E$12,0) -> 1 | ... M8: =ROUND('Key Assumptions'!$B$37*'Key Assumptions'!$E$12,0) -> 1 | N8: =SUM(B8:M8) -> 12
A9: Reconnects | B9: ='Key Assumptions'!$B$40 -> 2 | C9: ='Key Assumptions'!$B$40 -> 2 | D9: ='Key Assumptions'!$B$40 -> 2 | E9: ='Key Assumptions'!$B$40 -> 2 | F9: ='Key Assumptions'!$B$40 -> 2 | G9: ='Key Assumptions'!$B$40 -> 2 | H9: ='Key Assumptions'!$B$40 -> 2 | I9: ='Key Assumptions'!$B$40 -> 2 | ... M9: ='Key Assumptions'!$B$40 -> 2 | N9: =SUM(B9:M9) -> 24
A10: Churn disconnects | B10: =ROUND(B6*'Key Assumptions'!$B$38*'Key Assumptions'!$F$12,0) -> 2 | C10: =ROUND(C6*'Key Assumptions'!$B$38*'Key Assumptions'!$F$12,0) -> 3 | D10: =ROUND(D6*'Key Assumptions'!$B$38*'Key Assumptions'!$F$12,0) -> 3 | E10: =ROUND(E6*'Key Assumptions'!$B$38*'Key Assumptions'!$F$12,0) -> 3 | F10: =ROUND(F6*'Key Assumptions'!$B$38*'Key Assumptions'!$F$12,0) -> 3 | G10: =ROUND(G6*'Key Assumptions'!$B$38*'Key Assumptions'!$F$12,0) -> 3 | H10: =ROUND(H6*'Key Assumptions'!$B$38*'Key Assumptions'!$F$12,0) -> 3 | I10: =ROUND(I6*'Key Assumptions'!$B$38*'Key Assumptions'!$F$12,0) -> 3 | ... M10: =ROUND(M6*'Key Assumptions'!$B$38*'Key Assumptions'!$F$12,0) -> 3 | N10: =SUM(B10:M10) -> 35
A11: Other disconnects | B11: ='Key Assumptions'!$B$39 -> 2 | C11: ='Key Assumptions'!$B$39 -> 2 | D11: ='Key Assumptions'!$B$39 -> 2 | E11: ='Key Assumptions'!$B$39 -> 2 | F11: ='Key Assumptions'!$B$39 -> 2 | G11: ='Key Assumptions'!$B$39 -> 2 | H11: ='Key Assumptions'!$B$39 -> 2 | I11: ='Key Assumptions'!$B$39 -> 2 | ... M11: ='Key Assumptions'!$B$39 -> 2 | N11: =SUM(B11:M11) -> 24
A12: Net additions | B12: =B7+B8+B9-B10-B11 -> 3 | C12: =C7+C8+C9-C10-C11 -> 2 | D12: =D7+D8+D9-D10-D11 -> 2 | E12: =E7+E8+E9-E10-E11 -> 2 | F12: =F7+F8+F9-F10-F11 -> 2 | G12: =G7+G8+G9-G10-G11 -> 2 | H12: =H7+H8+H9-H10-H11 -> 2 | I12: =I7+I8+I9-I10-I11 -> 2 | ... M12: =M7+M8+M9-M10-M11 -> 2 | N12: =SUM(B12:M12) -> 25
A13: Ending business customers | B13: =MAX(0,B6+B12) -> 252 | C13: =MAX(0,C6+C12) -> 254 | D13: =MAX(0,D6+D12) -> 256 | E13: =MAX(0,E6+E12) -> 258 | F13: =MAX(0,F6+F12) -> 260 | G13: =MAX(0,G6+G12) -> 262 | H13: =MAX(0,H6+H12) -> 264 | I13: =MAX(0,I6+I12) -> 266 | ... M13: =MAX(0,M6+M12) -> 274 | N13: =M13 -> 274
A14: Average billable business customers | B14: =IF('Key Assumptions'!$B$56="Average",(B6+B13)/2,IF('Key Assumptions'!$B$56="Beginning",B6,B13)) -> 250.5 | C14: =IF('Key Assumptions'!$B$56="Average",(C6+C13)/2,IF('Key Assumptions'!$B$56="Beginning",C6,C13)) -> 253 | D14: =IF('Key Assumptions'!$B$56="Average",(D6+D13)/2,IF('Key Assumptions'!$B$56="Beginning",D6,D13)) -> 255 | E14: =IF('Key Assumptions'!$B$56="Average",(E6+E13)/2,IF('Key Assumptions'!$B$56="Beginning",E6,E13)) -> 257 | F14: =IF('Key Assumptions'!$B$56="Average",(F6+F13)/2,IF('Key Assumptions'!$B$56="Beginning",F6,F13)) -> 259 | G14: =IF('Key Assumptions'!$B$56="Average",(G6+G13)/2,IF('Key Assumptions'!$B$56="Beginning",G6,G13)) -> 261 | H14: =IF('Key Assumptions'!$B$56="Average",(H6+H13)/2,IF('Key Assumptions'!$B$56="Beginning",H6,H13)) -> 263 | I14: =IF('Key Assumptions'!$B$56="Average",(I6+I13)/2,IF('Key Assumptions'!$B$56="Beginning",I6,I13)) -> 265 | ... M14: =IF('Key Assumptions'!$B$56="Average",(M6+M13)/2,IF('Key Assumptions'!$B$56="Beginning",M6,M13)) -> 273 | N14: =AVERAGE(B14:M14) -> 261.95833
A15: Beginning enterprise customers | B15: ='Key Assumptions'!$B$57 -> 0 | C15: =B16 -> 1 | D15: =C16 -> 2 | E15: =D16 -> 3 | F15: =E16 -> 4 | G15: =F16 -> 5 | H15: =G16 -> 6 | I15: =H16 -> 7 | J15: =I16 -> 8 | ... M15: =L16 -> 11 | N15: =B15 -> 0
A16: Ending enterprise customers | B16: =MAX(0,B15+B8-ROUND(B15*'Key Assumptions'!$B$38*'Key Assumptions'!$F$12,0)) -> 1 | C16: =MAX(0,C15+C8-ROUND(C15*'Key Assumptions'!$B$38*'Key Assumptions'!$F$12,0)) -> 2 | D16: =MAX(0,D15+D8-ROUND(D15*'Key Assumptions'!$B$38*'Key Assumptions'!$F$12,0)) -> 3 | E16: =MAX(0,E15+E8-ROUND(E15*'Key Assumptions'!$B$38*'Key Assumptions'!$F$12,0)) -> 4 | F16: =MAX(0,F15+F8-ROUND(F15*'Key Assumptions'!$B$38*'Key Assumptions'!$F$12,0)) -> 5 | G16: =MAX(0,G15+G8-ROUND(G15*'Key Assumptions'!$B$38*'Key Assumptions'!$F$12,0)) -> 6 | H16: =MAX(0,H15+H8-ROUND(H15*'Key Assumptions'!$B$38*'Key Assumptions'!$F$12,0)) -> 7 | I16: =MAX(0,I15+I8-ROUND(I15*'Key Assumptions'!$B$38*'Key Assumptions'!$F$12,0)) -> 8 | ... M16: =MAX(0,M15+M8-ROUND(M15*'Key Assumptions'!$B$38*'Key Assumptions'!$F$12,0)) -> 12 | N16: =M16 -> 12
A17: Average enterprise customers | B17: =(B15+B16)/2 -> 0.5 | C17: =(C15+C16)/2 -> 1.5 | D17: =(D15+D16)/2 -> 2.5 | E17: =(E15+E16)/2 -> 3.5 | F17: =(F15+F16)/2 -> 4.5 | G17: =(G15+G16)/2 -> 5.5 | H17: =(H15+H16)/2 -> 6.5 | I17: =(I15+I16)/2 -> 7.5 | ... M17: =(M15+M16)/2 -> 11.5 | N17: =AVERAGE(B17:M17) -> 6
A18: RECURRING REVENUE
A19: Standard business broadband | B19: =B14*('Key Assumptions'!$B$41*IF(B4>='Key Assumptions'!$B$42,1+'Key Assumptions'!$B$43,1)*'Key Assumptions'!$G$12) -> 37324.5 | C19: =C14*('Key Assumptions'!$B$41*IF(C4>='Key Assumptions'!$B$42,1+'Key Assumptions'!$B$43,1)*'Key Assumptions'!$G$12) -> 37697 | D19: =D14*('Key Assumptions'!$B$41*IF(D4>='Key Assumptions'!$B$42,1+'Key Assumptions'!$B$43,1)*'Key Assumptions'!$G$12) -> 37995 | E19: =E14*('Key Assumptions'!$B$41*IF(E4>='Key Assumptions'!$B$42,1+'Key Assumptions'!$B$43,1)*'Key Assumptions'!$G$12) -> 38293 | F19: =F14*('Key Assumptions'!$B$41*IF(F4>='Key Assumptions'!$B$42,1+'Key Assumptions'!$B$43,1)*'Key Assumptions'!$G$12) -> 38591 | G19: =G14*('Key Assumptions'!$B$41*IF(G4>='Key Assumptions'!$B$42,1+'Key Assumptions'!$B$43,1)*'Key Assumptions'!$G$12) -> 38889 | H19: =H14*('Key Assumptions'!$B$41*IF(H4>='Key Assumptions'!$B$42,1+'Key Assumptions'!$B$43,1)*'Key Assumptions'!$G$12) -> 40362.61 | I19: =I14*('Key Assumptions'!$B$41*IF(I4>='Key Assumptions'!$B$42,1+'Key Assumptions'!$B$43,1)*'Key Assumptions'!$G$12) -> 40669.55 | ... M19: =M14*('Key Assumptions'!$B$41*IF(M4>='Key Assumptions'!$B$42,1+'Key Assumptions'!$B$43,1)*'Key Assumptions'!$G$12) -> 41897.31 | N19: =SUM(B19:M19) -> 475569.26
A20: Enterprise & DIA circuits | B20: =B17*'Key Assumptions'!$B$48 -> 0 | C20: =C17*'Key Assumptions'!$B$48 -> 0 | D20: =D17*'Key Assumptions'!$B$48 -> 0 | E20: =E17*'Key Assumptions'!$B$48 -> 0 | F20: =F17*'Key Assumptions'!$B$48 -> 0 | G20: =G17*'Key Assumptions'!$B$48 -> 0 | H20: =H17*'Key Assumptions'!$B$48 -> 0 | I20: =I17*'Key Assumptions'!$B$48 -> 0 | ... M20: =M17*'Key Assumptions'!$B$48 -> 0 | N20: =SUM(B20:M20) -> 0
A21: Static IP revenue | B21: =B14*'Key Assumptions'!$B$45 -> 0 | C21: =C14*'Key Assumptions'!$B$45 -> 0 | D21: =D14*'Key Assumptions'!$B$45 -> 0 | E21: =E14*'Key Assumptions'!$B$45 -> 0 | F21: =F14*'Key Assumptions'!$B$45 -> 0 | G21: =G14*'Key Assumptions'!$B$45 -> 0 | H21: =H14*'Key Assumptions'!$B$45 -> 0 | I21: =I14*'Key Assumptions'!$B$45 -> 0 | ... M21: =M14*'Key Assumptions'!$B$45 -> 0 | N21: =SUM(B21:M21) -> 0
A22: Managed Wi-Fi / router revenue | B22: =B14*'Key Assumptions'!$B$46 -> 0 | C22: =C14*'Key Assumptions'!$B$46 -> 0 | D22: =D14*'Key Assumptions'!$B$46 -> 0 | E22: =E14*'Key Assumptions'!$B$46 -> 0 | F22: =F14*'Key Assumptions'!$B$46 -> 0 | G22: =G14*'Key Assumptions'!$B$46 -> 0 | H22: =H14*'Key Assumptions'!$B$46 -> 0 | I22: =I14*'Key Assumptions'!$B$46 -> 0 | ... M22: =M14*'Key Assumptions'!$B$46 -> 0 | N22: =SUM(B22:M22) -> 0
A23: Voice revenue | B23: =B14*'Key Assumptions'!$B$47 -> 2424.84 | C23: =C14*'Key Assumptions'!$B$47 -> 2449.04 | D23: =D14*'Key Assumptions'!$B$47 -> 2468.4 | E23: =E14*'Key Assumptions'!$B$47 -> 2487.76 | F23: =F14*'Key Assumptions'!$B$47 -> 2507.12 | G23: =G14*'Key Assumptions'!$B$47 -> 2526.48 | H23: =H14*'Key Assumptions'!$B$47 -> 2545.84 | I23: =I14*'Key Assumptions'!$B$47 -> 2565.2 | ... M23: =M14*'Key Assumptions'!$B$47 -> 2642.64 | N23: =SUM(B23:M23) -> 30429.08
A24: Other recurring business revenue | B24: =B14*'Key Assumptions'!$B$49 -> 0 | C24: =C14*'Key Assumptions'!$B$49 -> 0 | D24: =D14*'Key Assumptions'!$B$49 -> 0 | E24: =E14*'Key Assumptions'!$B$49 -> 0 | F24: =F14*'Key Assumptions'!$B$49 -> 0 | G24: =G14*'Key Assumptions'!$B$49 -> 0 | H24: =H14*'Key Assumptions'!$B$49 -> 0 | I24: =I14*'Key Assumptions'!$B$49 -> 0 | ... M24: =M14*'Key Assumptions'!$B$49 -> 0 | N24: =SUM(B24:M24) -> 0
A25: Total business recurring revenue | B25: =SUM(B19:B24) -> 39749.34 | C25: =SUM(C19:C24) -> 40146.04 | D25: =SUM(D19:D24) -> 40463.4 | E25: =SUM(E19:E24) -> 40780.76 | F25: =SUM(F19:F24) -> 41098.12 | G25: =SUM(G19:G24) -> 41415.48 | H25: =SUM(H19:H24) -> 42908.45 | I25: =SUM(I19:I24) -> 43234.75 | ... M25: =SUM(M19:M24) -> 44539.95 | N25: =SUM(B25:M25) -> 505998.34
A26: ONE-TIME REVENUE
A27: Installation charges | B27: =(B7+B8)*'Key Assumptions'!$B$44*'Key Assumptions'!$J$12 -> 2500 | C27: =(C7+C8)*'Key Assumptions'!$B$44*'Key Assumptions'!$J$12 -> 2500 | D27: =(D7+D8)*'Key Assumptions'!$B$44*'Key Assumptions'!$J$12 -> 2500 | E27: =(E7+E8)*'Key Assumptions'!$B$44*'Key Assumptions'!$J$12 -> 2500 | F27: =(F7+F8)*'Key Assumptions'!$B$44*'Key Assumptions'!$J$12 -> 2500 | G27: =(G7+G8)*'Key Assumptions'!$B$44*'Key Assumptions'!$J$12 -> 2500 | H27: =(H7+H8)*'Key Assumptions'!$B$44*'Key Assumptions'!$J$12 -> 2500 | I27: =(I7+I8)*'Key Assumptions'!$B$44*'Key Assumptions'!$J$12 -> 2500 | ... M27: =(M7+M8)*'Key Assumptions'!$B$44*'Key Assumptions'!$J$12 -> 2500 | N27: =SUM(B27:M27) -> 30000
A28: Aid-to-construction revenue | B28: =(B7+B8)*'Key Assumptions'!$B$50*'Key Assumptions'!$J$12 -> 1250 | C28: =(C7+C8)*'Key Assumptions'!$B$50*'Key Assumptions'!$J$12 -> 1250 | D28: =(D7+D8)*'Key Assumptions'!$B$50*'Key Assumptions'!$J$12 -> 1250 | E28: =(E7+E8)*'Key Assumptions'!$B$50*'Key Assumptions'!$J$12 -> 1250 | F28: =(F7+F8)*'Key Assumptions'!$B$50*'Key Assumptions'!$J$12 -> 1250 | G28: =(G7+G8)*'Key Assumptions'!$B$50*'Key Assumptions'!$J$12 -> 1250 | H28: =(H7+H8)*'Key Assumptions'!$B$50*'Key Assumptions'!$J$12 -> 1250 | I28: =(I7+I8)*'Key Assumptions'!$B$50*'Key Assumptions'!$J$12 -> 1250 | ... M28: =(M7+M8)*'Key Assumptions'!$B$50*'Key Assumptions'!$J$12 -> 1250 | N28: =SUM(B28:M28) -> 15000
A29: Activation charges | B29: =(B7+B8)*'Key Assumptions'!$B$51 -> 500 | C29: =(C7+C8)*'Key Assumptions'!$B$51 -> 500 | D29: =(D7+D8)*'Key Assumptions'!$B$51 -> 500 | E29: =(E7+E8)*'Key Assumptions'!$B$51 -> 500 | F29: =(F7+F8)*'Key Assumptions'!$B$51 -> 500 | G29: =(G7+G8)*'Key Assumptions'!$B$51 -> 500 | H29: =(H7+H8)*'Key Assumptions'!$B$51 -> 500 | I29: =(I7+I8)*'Key Assumptions'!$B$51 -> 500 | ... M29: =(M7+M8)*'Key Assumptions'!$B$51 -> 500 | N29: =SUM(B29:M29) -> 6000
A30: Professional services | B30: ='Key Assumptions'!$B$52 -> 1500 | C30: ='Key Assumptions'!$B$52 -> 1500 | D30: ='Key Assumptions'!$B$52 -> 1500 | E30: ='Key Assumptions'!$B$52 -> 1500 | F30: ='Key Assumptions'!$B$52 -> 1500 | G30: ='Key Assumptions'!$B$52 -> 1500 | H30: ='Key Assumptions'!$B$52 -> 1500 | I30: ='Key Assumptions'!$B$52 -> 1500 | ... M30: ='Key Assumptions'!$B$52 -> 1500 | N30: =SUM(B30:M30) -> 18000
A31: Other nonrecurring revenue | B31: ='Key Assumptions'!$B$53 -> 500 | C31: ='Key Assumptions'!$B$53 -> 500 | D31: ='Key Assumptions'!$B$53 -> 500 | E31: ='Key Assumptions'!$B$53 -> 500 | F31: ='Key Assumptions'!$B$53 -> 500 | G31: ='Key Assumptions'!$B$53 -> 500 | H31: ='Key Assumptions'!$B$53 -> 500 | I31: ='Key Assumptions'!$B$53 -> 500 | ... M31: ='Key Assumptions'!$B$53 -> 500 | N31: =SUM(B31:M31) -> 6000
A32: Total business one-time revenue | B32: =SUM(B27:B31) -> 6250 | C32: =SUM(C27:C31) -> 6250 | D32: =SUM(D27:D31) -> 6250 | E32: =SUM(E27:E31) -> 6250 | F32: =SUM(F27:F31) -> 6250 | G32: =SUM(G27:G31) -> 6250 | H32: =SUM(H27:H31) -> 6250 | I32: =SUM(I27:I31) -> 6250 | ... M32: =SUM(M27:M31) -> 6250 | N32: =SUM(B32:M32) -> 75000
A33: ADJUSTMENTS & TOTALS
A34: Promotional discounts | B34: =-B25*'Key Assumptions'!$B$54 -> -596.2401 | C34: =-C25*'Key Assumptions'!$B$54 -> -602.1906 | D34: =-D25*'Key Assumptions'!$B$54 -> -606.951 | E34: =-E25*'Key Assumptions'!$B$54 -> -611.7114 | F34: =-F25*'Key Assumptions'!$B$54 -> -616.4718 | G34: =-G25*'Key Assumptions'!$B$54 -> -621.2322 | H34: =-H25*'Key Assumptions'!$B$54 -> -643.62675 | I34: =-I25*'Key Assumptions'!$B$54 -> -648.52125 | ... M34: =-M25*'Key Assumptions'!$B$54 -> -668.09925 | N34: =SUM(B34:M34) -> -7589.9751
A35: Bad-debt adjustment | B35: =-(B25+B32)*'Key Assumptions'!$B$55 -> -459.9934 | C35: =-(C25+C32)*'Key Assumptions'!$B$55 -> -463.9604 | D35: =-(D25+D32)*'Key Assumptions'!$B$55 -> -467.134 | E35: =-(E25+E32)*'Key Assumptions'!$B$55 -> -470.3076 | F35: =-(F25+F32)*'Key Assumptions'!$B$55 -> -473.4812 | G35: =-(G25+G32)*'Key Assumptions'!$B$55 -> -476.6548 | H35: =-(H25+H32)*'Key Assumptions'!$B$55 -> -491.5845 | I35: =-(I25+I32)*'Key Assumptions'!$B$55 -> -494.8475 | ... M35: =-(M25+M32)*'Key Assumptions'!$B$55 -> -507.8995 | N35: =SUM(B35:M35) -> -5809.9834
A36: Net business revenue | B36: =B25+B32+B34+B35 -> 44943.106 | C36: =C25+C32+C34+C35 -> 45329.889 | D36: =D25+D32+D34+D35 -> 45639.315 | E36: =E25+E32+E34+E35 -> 45948.741 | F36: =F25+F32+F34+F35 -> 46258.167 | G36: =G25+G32+G34+G35 -> 46567.593 | H36: =H25+H32+H34+H35 -> 48023.239 | I36: =I25+I32+I34+I35 -> 48341.381 | ... M36: =M25+M32+M34+M35 -> 49613.951 | N36: =SUM(B36:M36) -> 567598.38
A37: Business MRR | B37: =B25+B34 -> 39153.1 | C37: =C25+C34 -> 39543.849 | D37: =D25+D34 -> 39856.449 | E37: =E25+E34 -> 40169.049 | F37: =F25+F34 -> 40481.648 | G37: =G25+G34 -> 40794.248 | H37: =H25+H34 -> 42264.823 | I37: =I25+I34 -> 42586.229 | ... M37: =M25+M34 -> 43871.851 | N37: =M37 -> 43871.851
A38: Business ARR run rate | B38: =B37*12 -> 469837.2 | C38: =C37*12 -> 474526.19 | D38: =D37*12 -> 478277.39 | E38: =E37*12 -> 482028.58 | F38: =F37*12 -> 485779.78 | G38: =G37*12 -> 489530.97 | H38: =H37*12 -> 507177.88 | I38: =I37*12 -> 511034.74 | ... M38: =M37*12 -> 526462.21 | N38: =M38 -> 526462.21
A39: Effective business ARPU | B39: =IFERROR(B25/B14,0) -> 158.68 | C39: =IFERROR(C25/C14,0) -> 158.68 | D39: =IFERROR(D25/D14,0) -> 158.68 | E39: =IFERROR(E25/E14,0) -> 158.68 | F39: =IFERROR(F25/F14,0) -> 158.68 | G39: =IFERROR(G25/G14,0) -> 158.68 | H39: =IFERROR(H25/H14,0) -> 163.15 | I39: =IFERROR(I25/I14,0) -> 163.15 | ... M39: =IFERROR(M25/M14,0) -> 163.15 | N39: =AVERAGE(B39:M39) -> 160.915

Sheet Dark Fiber Forecast
A1: DARK FIBER & FIBER INFRASTRUCTURE FORECAST — 2027
A2: Each contract from Key Assumptions is recognized only during its active period (start/end dates). IRU treatment per contract method — CFO/accountant review required.
A4: Month first-day → | Q4: 46388 | R4: 46419 | S4: 46447 | T4: 46478 | U4: 46508 | V4: 46539 | W4: 46569 | X4: 46600 | Y4: 46631 | Z4: 46661 | AA4: 46692 | AB4: 46722
A5: Month end (EOM) → | Q5: =EOMONTH(Q4,0) -> 46418 | R5: =EOMONTH(R4,0) -> 46446 | S5: =EOMONTH(S4,0) -> 46477 | T5: =EOMONTH(T4,0) -> 46507 | U5: =EOMONTH(U4,0) -> 46538 | V5: =EOMONTH(V4,0) -> 46568 | W5: =EOMONTH(W4,0) -> 46599 | X5: =EOMONTH(X4,0) -> 46630 | ... AB5: =EOMONTH(AB4,0) -> 46752
A7: # | B7: Contract | C7: Eff Start | D7: End | E7: MRC | F7: Esc% | G7: EscDate | H7: O&M/mo | I7: Constr | J7: Activ | K7: IRU Pay | L7: IRU Term | M7: IRU Method | N7: IRU SL/mo | Q7: Jan-27 | R7: Feb-27 | S7: Mar-27 | T7: Apr-27 | U7: May-27 | V7: Jun-27 | W7: Jul-27 | X7: Aug-27 | Y7: Sep-27 | Z7: Oct-27 | AA7: Nov-27 | AB7: Dec-27 | AC7: Annual | AD7: Remaining Value | AE7: Expiration
A8: ='Key Assumptions'!A66 -> 1 | B8: ='Key Assumptions'!B66 -> PLACEHOLDER — Current dark fiber book (H1 2026 run-rate) | C8: =IF('Key Assumptions'!H66="",0,EDATE('Key Assumptions'!H66,'Key Assumptions'!$I$12)) -> 45292 | D8: =IF('Key Assumptions'!I66="",0,'Key Assumptions'!I66) -> 47848 | E8: =N('Key Assumptions'!J66) -> 1595 | F8: =N('Key Assumptions'!K66) -> 0 | G8: =IF('Key Assumptions'!L66="",0,'Key Assumptions'!L66) -> 46388 | H8: =IF('Key Assumptions'!R66="",IF(E8>0,E8*'Key Assumptions'!$B$61,0),'Key Assumptions'!R66) -> 0 | I8: =N('Key Assumptions'!M66) -> 0 | J8: =N('Key Assumptions'!N66) -> 0 | K8: =N('Key Assumptions'!O66) -> 0 | L8: =N('Key Assumptions'!P66) -> 0 | M8: =IF('Key Assumptions'!Q66="",'Key Assumptions'!$B$60,'Key Assumptions'!Q66) | N8: =IF($M8="Straight-line",IFERROR($K8/($L8*12),0),0) -> 0 | Q8: =IF(AND($C8>0,$C8<=Q$5,$D8>=Q$4),$E8*(1+$F8*(Q$4>=$G8))*'Key Assumptions'!$H$12+$H8+IF($M8="Straight-line",$N8,0),0)+IF(AND($M8="Upfront",$C8>=Q$4,$C8<=Q$5),$K8,0)+IF(AND($C8>0,$C8>=Q$4,$C8<=Q$5),$I8+$J8,0) -> 1595 | R8: =IF(AND($C8>0,$C8<=R$5,$D8>=R$4),$E8*(1+$F8*(R$4>=$G8))*'Key Assumptions'!$H$12+$H8+IF($M8="Straight-line",$N8,0),0)+IF(AND($M8="Upfront",$C8>=R$4,$C8<=R$5),$K8,0)+IF(AND($C8>0,$C8>=R$4,$C8<=R$5),$I8+$J8,0) -> 1595 | S8: =IF(AND($C8>0,$C8<=S$5,$D8>=S$4),$E8*(1+$F8*(S$4>=$G8))*'Key Assumptions'!$H$12+$H8+IF($M8="Straight-line",$N8,0),0)+IF(AND($M8="Upfront",$C8>=S$4,$C8<=S$5),$K8,0)+IF(AND($C8>0,$C8>=S$4,$C8<=S$5),$I8+$J8,0) -> 1595 | T8: =IF(AND($C8>0,$C8<=T$5,$D8>=T$4),$E8*(1+$F8*(T$4>=$G8))*'Key Assumptions'!$H$12+$H8+IF($M8="Straight-line",$N8,0),0)+IF(AND($M8="Upfront",$C8>=T$4,$C8<=T$5),$K8,0)+IF(AND($C8>0,$C8>=T$4,$C8<=T$5),$I8+$J8,0) -> 1595 | U8: =IF(AND($C8>0,$C8<=U$5,$D8>=U$4),$E8*(1+$F8*(U$4>=$G8))*'Key Assumptions'!$H$12+$H8+IF($M8="Straight-line",$N8,0),0)+IF(AND($M8="Upfront",$C8>=U$4,$C8<=U$5),$K8,0)+IF(AND($C8>0,$C8>=U$4,$C8<=U$5),$I8+$J8,0) -> 1595 | V8: =IF(AND($C8>0,$C8<=V$5,$D8>=V$4),$E8*(1+$F8*(V$4>=$G8))*'Key Assumptions'!$H$12+$H8+IF($M8="Straight-line",$N8,0),0)+IF(AND($M8="Upfront",$C8>=V$4,$C8<=V$5),$K8,0)+IF(AND($C8>0,$C8>=V$4,$C8<=V$5),$I8+$J8,0) -> 1595 | W8: =IF(AND($C8>0,$C8<=W$5,$D8>=W$4),$E8*(1+$F8*(W$4>=$G8))*'Key Assumptions'!$H$12+$H8+IF($M8="Straight-line",$N8,0),0)+IF(AND($M8="Upfront",$C8>=W$4,$C8<=W$5),$K8,0)+IF(AND($C8>0,$C8>=W$4,$C8<=W$5),$I8+$J8,0) -> 1595 | X8: =IF(AND($C8>0,$C8<=X$5,$D8>=X$4),$E8*(1+$F8*(X$4>=$G8))*'Key Assumptions'!$H$12+$H8+IF($M8="Straight-line",$N8,0),0)+IF(AND($M8="Upfront",$C8>=X$4,$C8<=X$5),$K8,0)+IF(AND($C8>0,$C8>=X$4,$C8<=X$5),$I8+$J8,0) -> 1595 | ... AB8: =IF(AND($C8>0,$C8<=AB$5,$D8>=AB$4),$E8*(1+$F8*(AB$4>=$G8))*'Key Assumptions'!$H$12+$H8+IF($M8="Straight-line",$N8,0),0)+IF(AND($M8="Upfront",$C8>=AB$4,$C8<=AB$5),$K8,0)+IF(AND($C8>0,$C8>=AB$4,$C8<=AB$5),$I8+$J8,0) -> 1595 | AC8: =SUM(Q8:AB8) -> 19140 | AD8: =IF($D8>0,$E8*MAX(0,(YEAR($D8)-2027)*12+(MONTH($D8)-12)),0) -> 57420 | AE8: =IF('Key Assumptions'!B66="","",IF($D8<DATE(2027,12,31),"EXPIRED",IF($D8-DATE(2027,12,31)<=90,"RED <90d",IF($D8-DATE(2027,12,31)<=180,"YELLOW <180d","GREEN")))) -> GREEN
A9: ='Key Assumptions'!A67 -> 2 | B9: ='Key Assumptions'!B67 -> 0 | C9: =IF('Key Assumptions'!H67="",0,EDATE('Key Assumptions'!H67,'Key Assumptions'!$I$12)) -> 0 | D9: =IF('Key Assumptions'!I67="",0,'Key Assumptions'!I67) -> 0 | E9: =N('Key Assumptions'!J67) -> 0 | F9: =N('Key Assumptions'!K67) -> 0 | G9: =IF('Key Assumptions'!L67="",0,'Key Assumptions'!L67) -> 0 | H9: =IF('Key Assumptions'!R67="",IF(E9>0,E9*'Key Assumptions'!$B$61,0),'Key Assumptions'!R67) -> 0 | I9: =N('Key Assumptions'!M67) -> 0 | J9: =N('Key Assumptions'!N67) -> 0 | K9: =N('Key Assumptions'!O67) -> 0 | L9: =N('Key Assumptions'!P67) -> 0 | M9: =IF('Key Assumptions'!Q67="",'Key Assumptions'!$B$60,'Key Assumptions'!Q67) -> Straight-line | N9: =IF($M9="Straight-line",IFERROR($K9/($L9*12),0),0) -> 0 | Q9: =IF(AND($C9>0,$C9<=Q$5,$D9>=Q$4),$E9*(1+$F9*(Q$4>=$G9))*'Key Assumptions'!$H$12+$H9+IF($M9="Straight-line",$N9,0),0)+IF(AND($M9="Upfront",$C9>=Q$4,$C9<=Q$5),$K9,0)+IF(AND($C9>0,$C9>=Q$4,$C9<=Q$5),$I9+$J9,0) -> 0 | R9: =IF(AND($C9>0,$C9<=R$5,$D9>=R$4),$E9*(1+$F9*(R$4>=$G9))*'Key Assumptions'!$H$12+$H9+IF($M9="Straight-line",$N9,0),0)+IF(AND($M9="Upfront",$C9>=R$4,$C9<=R$5),$K9,0)+IF(AND($C9>0,$C9>=R$4,$C9<=R$5),$I9+$J9,0) -> 0 | S9: =IF(AND($C9>0,$C9<=S$5,$D9>=S$4),$E9*(1+$F9*(S$4>=$G9))*'Key Assumptions'!$H$12+$H9+IF($M9="Straight-line",$N9,0),0)+IF(AND($M9="Upfront",$C9>=S$4,$C9<=S$5),$K9,0)+IF(AND($C9>0,$C9>=S$4,$C9<=S$5),$I9+$J9,0) -> 0 | T9: =IF(AND($C9>0,$C9<=T$5,$D9>=T$4),$E9*(1+$F9*(T$4>=$G9))*'Key Assumptions'!$H$12+$H9+IF($M9="Straight-line",$N9,0),0)+IF(AND($M9="Upfront",$C9>=T$4,$C9<=T$5),$K9,0)+IF(AND($C9>0,$C9>=T$4,$C9<=T$5),$I9+$J9,0) -> 0 | U9: =IF(AND($C9>0,$C9<=U$5,$D9>=U$4),$E9*(1+$F9*(U$4>=$G9))*'Key Assumptions'!$H$12+$H9+IF($M9="Straight-line",$N9,0),0)+IF(AND($M9="Upfront",$C9>=U$4,$C9<=U$5),$K9,0)+IF(AND($C9>0,$C9>=U$4,$C9<=U$5),$I9+$J9,0) -> 0 | V9: =IF(AND($C9>0,$C9<=V$5,$D9>=V$4),$E9*(1+$F9*(V$4>=$G9))*'Key Assumptions'!$H$12+$H9+IF($M9="Straight-line",$N9,0),0)+IF(AND($M9="Upfront",$C9>=V$4,$C9<=V$5),$K9,0)+IF(AND($C9>0,$C9>=V$4,$C9<=V$5),$I9+$J9,0) -> 0 | W9: =IF(AND($C9>0,$C9<=W$5,$D9>=W$4),$E9*(1+$F9*(W$4>=$G9))*'Key Assumptions'!$H$12+$H9+IF($M9="Straight-line",$N9,0),0)+IF(AND($M9="Upfront",$C9>=W$4,$C9<=W$5),$K9,0)+IF(AND($C9>0,$C9>=W$4,$C9<=W$5),$I9+$J9,0) -> 0 | X9: =IF(AND($C9>0,$C9<=X$5,$D9>=X$4),$E9*(1+$F9*(X$4>=$G9))*'Key Assumptions'!$H$12+$H9+IF($M9="Straight-line",$N9,0),0)+IF(AND($M9="Upfront",$C9>=X$4,$C9<=X$5),$K9,0)+IF(AND($C9>0,$C9>=X$4,$C9<=X$5),$I9+$J9,0) -> 0 | ... AB9: =IF(AND($C9>0,$C9<=AB$5,$D9>=AB$4),$E9*(1+$F9*(AB$4>=$G9))*'Key Assumptions'!$H$12+$H9+IF($M9="Straight-line",$N9,0),0)+IF(AND($M9="Upfront",$C9>=AB$4,$C9<=AB$5),$K9,0)+IF(AND($C9>0,$C9>=AB$4,$C9<=AB$5),$I9+$J9,0) -> 0 | AC9: =SUM(Q9:AB9) -> 0 | AD9: =IF($D9>0,$E9*MAX(0,(YEAR($D9)-2027)*12+(MONTH($D9)-12)),0) -> 0 | AE9: =IF('Key Assumptions'!B67="","",IF($D9<DATE(2027,12,31),"EXPIRED",IF($D9-DATE(2027,12,31)<=90,"RED <90d",IF($D9-DATE(2027,12,31)<=180,"YELLOW <180d","GREEN"))))
A10: ='Key Assumptions'!A68 -> 3 | B10: ='Key Assumptions'!B68 -> 0 | C10: =IF('Key Assumptions'!H68="",0,EDATE('Key Assumptions'!H68,'Key Assumptions'!$I$12)) -> 0 | D10: =IF('Key Assumptions'!I68="",0,'Key Assumptions'!I68) -> 0 | E10: =N('Key Assumptions'!J68) -> 0 | F10: =N('Key Assumptions'!K68) -> 0 | G10: =IF('Key Assumptions'!L68="",0,'Key Assumptions'!L68) -> 0 | H10: =IF('Key Assumptions'!R68="",IF(E10>0,E10*'Key Assumptions'!$B$61,0),'Key Assumptions'!R68) -> 0 | I10: =N('Key Assumptions'!M68) -> 0 | J10: =N('Key Assumptions'!N68) -> 0 | K10: =N('Key Assumptions'!O68) -> 0 | L10: =N('Key Assumptions'!P68) -> 0 | M10: =IF('Key Assumptions'!Q68="",'Key Assumptions'!$B$60,'Key Assumptions'!Q68) -> Straight-line | N10: =IF($M10="Straight-line",IFERROR($K10/($L10*12),0),0) -> 0 | Q10: =IF(AND($C10>0,$C10<=Q$5,$D10>=Q$4),$E10*(1+$F10*(Q$4>=$G10))*'Key Assumptions'!$H$12+$H10+IF($M10="Straight-line",$N10,0),0)+IF(AND($M10="Upfront",$C10>=Q$4,$C10<=Q$5),$K10,0)+IF(AND($C10>0,$C10>=Q$4,$C10<=Q$5),$I10+$J10,0) -> 0 | R10: =IF(AND($C10>0,$C10<=R$5,$D10>=R$4),$E10*(1+$F10*(R$4>=$G10))*'Key Assumptions'!$H$12+$H10+IF($M10="Straight-line",$N10,0),0)+IF(AND($M10="Upfront",$C10>=R$4,$C10<=R$5),$K10,0)+IF(AND($C10>0,$C10>=R$4,$C10<=R$5),$I10+$J10,0) -> 0 | S10: =IF(AND($C10>0,$C10<=S$5,$D10>=S$4),$E10*(1+$F10*(S$4>=$G10))*'Key Assumptions'!$H$12+$H10+IF($M10="Straight-line",$N10,0),0)+IF(AND($M10="Upfront",$C10>=S$4,$C10<=S$5),$K10,0)+IF(AND($C10>0,$C10>=S$4,$C10<=S$5),$I10+$J10,0) -> 0 | T10: =IF(AND($C10>0,$C10<=T$5,$D10>=T$4),$E10*(1+$F10*(T$4>=$G10))*'Key Assumptions'!$H$12+$H10+IF($M10="Straight-line",$N10,0),0)+IF(AND($M10="Upfront",$C10>=T$4,$C10<=T$5),$K10,0)+IF(AND($C10>0,$C10>=T$4,$C10<=T$5),$I10+$J10,0) -> 0 | U10: =IF(AND($C10>0,$C10<=U$5,$D10>=U$4),$E10*(1+$F10*(U$4>=$G10))*'Key Assumptions'!$H$12+$H10+IF($M10="Straight-line",$N10,0),0)+IF(AND($M10="Upfront",$C10>=U$4,$C10<=U$5),$K10,0)+IF(AND($C10>0,$C10>=U$4,$C10<=U$5),$I10+$J10,0) -> 0 | V10: =IF(AND($C10>0,$C10<=V$5,$D10>=V$4),$E10*(1+$F10*(V$4>=$G10))*'Key Assumptions'!$H$12+$H10+IF($M10="Straight-line",$N10,0),0)+IF(AND($M10="Upfront",$C10>=V$4,$C10<=V$5),$K10,0)+IF(AND($C10>0,$C10>=V$4,$C10<=V$5),$I10+$J10,0) -> 0 | W10: =IF(AND($C10>0,$C10<=W$5,$D10>=W$4),$E10*(1+$F10*(W$4>=$G10))*'Key Assumptions'!$H$12+$H10+IF($M10="Straight-line",$N10,0),0)+IF(AND($M10="Upfront",$C10>=W$4,$C10<=W$5),$K10,0)+IF(AND($C10>0,$C10>=W$4,$C10<=W$5),$I10+$J10,0) -> 0 | X10: =IF(AND($C10>0,$C10<=X$5,$D10>=X$4),$E10*(1+$F10*(X$4>=$G10))*'Key Assumptions'!$H$12+$H10+IF($M10="Straight-line",$N10,0),0)+IF(AND($M10="Upfront",$C10>=X$4,$C10<=X$5),$K10,0)+IF(AND($C10>0,$C10>=X$4,$C10<=X$5),$I10+$J10,0) -> 0 | ... AB10: =IF(AND($C10>0,$C10<=AB$5,$D10>=AB$4),$E10*(1+$F10*(AB$4>=$G10))*'Key Assumptions'!$H$12+$H10+IF($M10="Straight-line",$N10,0),0)+IF(AND($M10="Upfront",$C10>=AB$4,$C10<=AB$5),$K10,0)+IF(AND($C10>0,$C10>=AB$4,$C10<=AB$5),$I10+$J10,0) -> 0 | AC10: =SUM(Q10:AB10) -> 0 | AD10: =IF($D10>0,$E10*MAX(0,(YEAR($D10)-2027)*12+(MONTH($D10)-12)),0) -> 0 | AE10: =IF('Key Assumptions'!B68="","",IF($D10<DATE(2027,12,31),"EXPIRED",IF($D10-DATE(2027,12,31)<=90,"RED <90d",IF($D10-DATE(2027,12,31)<=180,"YELLOW <180d","GREEN"))))
A11: ='Key Assumptions'!A69 -> 4 | B11: ='Key Assumptions'!B69 -> 0 | C11: =IF('Key Assumptions'!H69="",0,EDATE('Key Assumptions'!H69,'Key Assumptions'!$I$12)) -> 0 | D11: =IF('Key Assumptions'!I69="",0,'Key Assumptions'!I69) -> 0 | E11: =N('Key Assumptions'!J69) -> 0 | F11: =N('Key Assumptions'!K69) -> 0 | G11: =IF('Key Assumptions'!L69="",0,'Key Assumptions'!L69) -> 0 | H11: =IF('Key Assumptions'!R69="",IF(E11>0,E11*'Key Assumptions'!$B$61,0),'Key Assumptions'!R69) -> 0 | I11: =N('Key Assumptions'!M69) -> 0 | J11: =N('Key Assumptions'!N69) -> 0 | K11: =N('Key Assumptions'!O69) -> 0 | L11: =N('Key Assumptions'!P69) -> 0 | M11: =IF('Key Assumptions'!Q69="",'Key Assumptions'!$B$60,'Key Assumptions'!Q69) -> Straight-line | N11: =IF($M11="Straight-line",IFERROR($K11/($L11*12),0),0) -> 0 | Q11: =IF(AND($C11>0,$C11<=Q$5,$D11>=Q$4),$E11*(1+$F11*(Q$4>=$G11))*'Key Assumptions'!$H$12+$H11+IF($M11="Straight-line",$N11,0),0)+IF(AND($M11="Upfront",$C11>=Q$4,$C11<=Q$5),$K11,0)+IF(AND($C11>0,$C11>=Q$4,$C11<=Q$5),$I11+$J11,0) -> 0 | R11: =IF(AND($C11>0,$C11<=R$5,$D11>=R$4),$E11*(1+$F11*(R$4>=$G11))*'Key Assumptions'!$H$12+$H11+IF($M11="Straight-line",$N11,0),0)+IF(AND($M11="Upfront",$C11>=R$4,$C11<=R$5),$K11,0)+IF(AND($C11>0,$C11>=R$4,$C11<=R$5),$I11+$J11,0) -> 0 | S11: =IF(AND($C11>0,$C11<=S$5,$D11>=S$4),$E11*(1+$F11*(S$4>=$G11))*'Key Assumptions'!$H$12+$H11+IF($M11="Straight-line",$N11,0),0)+IF(AND($M11="Upfront",$C11>=S$4,$C11<=S$5),$K11,0)+IF(AND($C11>0,$C11>=S$4,$C11<=S$5),$I11+$J11,0) -> 0 | T11: =IF(AND($C11>0,$C11<=T$5,$D11>=T$4),$E11*(1+$F11*(T$4>=$G11))*'Key Assumptions'!$H$12+$H11+IF($M11="Straight-line",$N11,0),0)+IF(AND($M11="Upfront",$C11>=T$4,$C11<=T$5),$K11,0)+IF(AND($C11>0,$C11>=T$4,$C11<=T$5),$I11+$J11,0) -> 0 | U11: =IF(AND($C11>0,$C11<=U$5,$D11>=U$4),$E11*(1+$F11*(U$4>=$G11))*'Key Assumptions'!$H$12+$H11+IF($M11="Straight-line",$N11,0),0)+IF(AND($M11="Upfront",$C11>=U$4,$C11<=U$5),$K11,0)+IF(AND($C11>0,$C11>=U$4,$C11<=U$5),$I11+$J11,0) -> 0 | V11: =IF(AND($C11>0,$C11<=V$5,$D11>=V$4),$E11*(1+$F11*(V$4>=$G11))*'Key Assumptions'!$H$12+$H11+IF($M11="Straight-line",$N11,0),0)+IF(AND($M11="Upfront",$C11>=V$4,$C11<=V$5),$K11,0)+IF(AND($C11>0,$C11>=V$4,$C11<=V$5),$I11+$J11,0) -> 0 | W11: =IF(AND($C11>0,$C11<=W$5,$D11>=W$4),$E11*(1+$F11*(W$4>=$G11))*'Key Assumptions'!$H$12+$H11+IF($M11="Straight-line",$N11,0),0)+IF(AND($M11="Upfront",$C11>=W$4,$C11<=W$5),$K11,0)+IF(AND($C11>0,$C11>=W$4,$C11<=W$5),$I11+$J11,0) -> 0 | X11: =IF(AND($C11>0,$C11<=X$5,$D11>=X$4),$E11*(1+$F11*(X$4>=$G11))*'Key Assumptions'!$H$12+$H11+IF($M11="Straight-line",$N11,0),0)+IF(AND($M11="Upfront",$C11>=X$4,$C11<=X$5),$K11,0)+IF(AND($C11>0,$C11>=X$4,$C11<=X$5),$I11+$J11,0) -> 0 | ... AB11: =IF(AND($C11>0,$C11<=AB$5,$D11>=AB$4),$E11*(1+$F11*(AB$4>=$G11))*'Key Assumptions'!$H$12+$H11+IF($M11="Straight-line",$N11,0),0)+IF(AND($M11="Upfront",$C11>=AB$4,$C11<=AB$5),$K11,0)+IF(AND($C11>0,$C11>=AB$4,$C11<=AB$5),$I11+$J11,0) -> 0 | AC11: =SUM(Q11:AB11) -> 0 | AD11: =IF($D11>0,$E11*MAX(0,(YEAR($D11)-2027)*12+(MONTH($D11)-12)),0) -> 0 | AE11: =IF('Key Assumptions'!B69="","",IF($D11<DATE(2027,12,31),"EXPIRED",IF($D11-DATE(2027,12,31)<=90,"RED <90d",IF($D11-DATE(2027,12,31)<=180,"YELLOW <180d","GREEN"))))
A12: ='Key Assumptions'!A70 -> 5 | B12: ='Key Assumptions'!B70 -> 0 | C12: =IF('Key Assumptions'!H70="",0,EDATE('Key Assumptions'!H70,'Key Assumptions'!$I$12)) -> 0 | D12: =IF('Key Assumptions'!I70="",0,'Key Assumptions'!I70) -> 0 | E12: =N('Key Assumptions'!J70) -> 0 | F12: =N('Key Assumptions'!K70) -> 0 | G12: =IF('Key Assumptions'!L70="",0,'Key Assumptions'!L70) -> 0 | H12: =IF('Key Assumptions'!R70="",IF(E12>0,E12*'Key Assumptions'!$B$61,0),'Key Assumptions'!R70) -> 0 | I12: =N('Key Assumptions'!M70) -> 0 | J12: =N('Key Assumptions'!N70) -> 0 | K12: =N('Key Assumptions'!O70) -> 0 | L12: =N('Key Assumptions'!P70) -> 0 | M12: =IF('Key Assumptions'!Q70="",'Key Assumptions'!$B$60,'Key Assumptions'!Q70) -> Straight-line | N12: =IF($M12="Straight-line",IFERROR($K12/($L12*12),0),0) -> 0 | Q12: =IF(AND($C12>0,$C12<=Q$5,$D12>=Q$4),$E12*(1+$F12*(Q$4>=$G12))*'Key Assumptions'!$H$12+$H12+IF($M12="Straight-line",$N12,0),0)+IF(AND($M12="Upfront",$C12>=Q$4,$C12<=Q$5),$K12,0)+IF(AND($C12>0,$C12>=Q$4,$C12<=Q$5),$I12+$J12,0) -> 0 | R12: =IF(AND($C12>0,$C12<=R$5,$D12>=R$4),$E12*(1+$F12*(R$4>=$G12))*'Key Assumptions'!$H$12+$H12+IF($M12="Straight-line",$N12,0),0)+IF(AND($M12="Upfront",$C12>=R$4,$C12<=R$5),$K12,0)+IF(AND($C12>0,$C12>=R$4,$C12<=R$5),$I12+$J12,0) -> 0 | S12: =IF(AND($C12>0,$C12<=S$5,$D12>=S$4),$E12*(1+$F12*(S$4>=$G12))*'Key Assumptions'!$H$12+$H12+IF($M12="Straight-line",$N12,0),0)+IF(AND($M12="Upfront",$C12>=S$4,$C12<=S$5),$K12,0)+IF(AND($C12>0,$C12>=S$4,$C12<=S$5),$I12+$J12,0) -> 0 | T12: =IF(AND($C12>0,$C12<=T$5,$D12>=T$4),$E12*(1+$F12*(T$4>=$G12))*'Key Assumptions'!$H$12+$H12+IF($M12="Straight-line",$N12,0),0)+IF(AND($M12="Upfront",$C12>=T$4,$C12<=T$5),$K12,0)+IF(AND($C12>0,$C12>=T$4,$C12<=T$5),$I12+$J12,0) -> 0 | U12: =IF(AND($C12>0,$C12<=U$5,$D12>=U$4),$E12*(1+$F12*(U$4>=$G12))*'Key Assumptions'!$H$12+$H12+IF($M12="Straight-line",$N12,0),0)+IF(AND($M12="Upfront",$C12>=U$4,$C12<=U$5),$K12,0)+IF(AND($C12>0,$C12>=U$4,$C12<=U$5),$I12+$J12,0) -> 0 | V12: =IF(AND($C12>0,$C12<=V$5,$D12>=V$4),$E12*(1+$F12*(V$4>=$G12))*'Key Assumptions'!$H$12+$H12+IF($M12="Straight-line",$N12,0),0)+IF(AND($M12="Upfront",$C12>=V$4,$C12<=V$5),$K12,0)+IF(AND($C12>0,$C12>=V$4,$C12<=V$5),$I12+$J12,0) -> 0 | W12: =IF(AND($C12>0,$C12<=W$5,$D12>=W$4),$E12*(1+$F12*(W$4>=$G12))*'Key Assumptions'!$H$12+$H12+IF($M12="Straight-line",$N12,0),0)+IF(AND($M12="Upfront",$C12>=W$4,$C12<=W$5),$K12,0)+IF(AND($C12>0,$C12>=W$4,$C12<=W$5),$I12+$J12,0) -> 0 | X12: =IF(AND($C12>0,$C12<=X$5,$D12>=X$4),$E12*(1+$F12*(X$4>=$G12))*'Key Assumptions'!$H$12+$H12+IF($M12="Straight-line",$N12,0),0)+IF(AND($M12="Upfront",$C12>=X$4,$C12<=X$5),$K12,0)+IF(AND($C12>0,$C12>=X$4,$C12<=X$5),$I12+$J12,0) -> 0 | ... AB12: =IF(AND($C12>0,$C12<=AB$5,$D12>=AB$4),$E12*(1+$F12*(AB$4>=$G12))*'Key Assumptions'!$H$12+$H12+IF($M12="Straight-line",$N12,0),0)+IF(AND($M12="Upfront",$C12>=AB$4,$C12<=AB$5),$K12,0)+IF(AND($C12>0,$C12>=AB$4,$C12<=AB$5),$I12+$J12,0) -> 0 | AC12: =SUM(Q12:AB12) -> 0 | AD12: =IF($D12>0,$E12*MAX(0,(YEAR($D12)-2027)*12+(MONTH($D12)-12)),0) -> 0 | AE12: =IF('Key Assumptions'!B70="","",IF($D12<DATE(2027,12,31),"EXPIRED",IF($D12-DATE(2027,12,31)<=90,"RED <90d",IF($D12-DATE(2027,12,31)<=180,"YELLOW <180d","GREEN"))))
A13: ='Key Assumptions'!A71 -> 6 | B13: ='Key Assumptions'!B71 -> 0 | C13: =IF('Key Assumptions'!H71="",0,EDATE('Key Assumptions'!H71,'Key Assumptions'!$I$12)) -> 0 | D13: =IF('Key Assumptions'!I71="",0,'Key Assumptions'!I71) -> 0 | E13: =N('Key Assumptions'!J71) -> 0 | F13: =N('Key Assumptions'!K71) -> 0 | G13: =IF('Key Assumptions'!L71="",0,'Key Assumptions'!L71) -> 0 | H13: =IF('Key Assumptions'!R71="",IF(E13>0,E13*'Key Assumptions'!$B$61,0),'Key Assumptions'!R71) -> 0 | I13: =N('Key Assumptions'!M71) -> 0 | J13: =N('Key Assumptions'!N71) -> 0 | K13: =N('Key Assumptions'!O71) -> 0 | L13: =N('Key Assumptions'!P71) -> 0 | M13: =IF('Key Assumptions'!Q71="",'Key Assumptions'!$B$60,'Key Assumptions'!Q71) -> Straight-line | N13: =IF($M13="Straight-line",IFERROR($K13/($L13*12),0),0) -> 0 | Q13: =IF(AND($C13>0,$C13<=Q$5,$D13>=Q$4),$E13*(1+$F13*(Q$4>=$G13))*'Key Assumptions'!$H$12+$H13+IF($M13="Straight-line",$N13,0),0)+IF(AND($M13="Upfront",$C13>=Q$4,$C13<=Q$5),$K13,0)+IF(AND($C13>0,$C13>=Q$4,$C13<=Q$5),$I13+$J13,0) -> 0 | R13: =IF(AND($C13>0,$C13<=R$5,$D13>=R$4),$E13*(1+$F13*(R$4>=$G13))*'Key Assumptions'!$H$12+$H13+IF($M13="Straight-line",$N13,0),0)+IF(AND($M13="Upfront",$C13>=R$4,$C13<=R$5),$K13,0)+IF(AND($C13>0,$C13>=R$4,$C13<=R$5),$I13+$J13,0) -> 0 | S13: =IF(AND($C13>0,$C13<=S$5,$D13>=S$4),$E13*(1+$F13*(S$4>=$G13))*'Key Assumptions'!$H$12+$H13+IF($M13="Straight-line",$N13,0),0)+IF(AND($M13="Upfront",$C13>=S$4,$C13<=S$5),$K13,0)+IF(AND($C13>0,$C13>=S$4,$C13<=S$5),$I13+$J13,0) -> 0 | T13: =IF(AND($C13>0,$C13<=T$5,$D13>=T$4),$E13*(1+$F13*(T$4>=$G13))*'Key Assumptions'!$H$12+$H13+IF($M13="Straight-line",$N13,0),0)+IF(AND($M13="Upfront",$C13>=T$4,$C13<=T$5),$K13,0)+IF(AND($C13>0,$C13>=T$4,$C13<=T$5),$I13+$J13,0) -> 0 | U13: =IF(AND($C13>0,$C13<=U$5,$D13>=U$4),$E13*(1+$F13*(U$4>=$G13))*'Key Assumptions'!$H$12+$H13+IF($M13="Straight-line",$N13,0),0)+IF(AND($M13="Upfront",$C13>=U$4,$C13<=U$5),$K13,0)+IF(AND($C13>0,$C13>=U$4,$C13<=U$5),$I13+$J13,0) -> 0 | V13: =IF(AND($C13>0,$C13<=V$5,$D13>=V$4),$E13*(1+$F13*(V$4>=$G13))*'Key Assumptions'!$H$12+$H13+IF($M13="Straight-line",$N13,0),0)+IF(AND($M13="Upfront",$C13>=V$4,$C13<=V$5),$K13,0)+IF(AND($C13>0,$C13>=V$4,$C13<=V$5),$I13+$J13,0) -> 0 | W13: =IF(AND($C13>0,$C13<=W$5,$D13>=W$4),$E13*(1+$F13*(W$4>=$G13))*'Key Assumptions'!$H$12+$H13+IF($M13="Straight-line",$N13,0),0)+IF(AND($M13="Upfront",$C13>=W$4,$C13<=W$5),$K13,0)+IF(AND($C13>0,$C13>=W$4,$C13<=W$5),$I13+$J13,0) -> 0 | X13: =IF(AND($C13>0,$C13<=X$5,$D13>=X$4),$E13*(1+$F13*(X$4>=$G13))*'Key Assumptions'!$H$12+$H13+IF($M13="Straight-line",$N13,0),0)+IF(AND($M13="Upfront",$C13>=X$4,$C13<=X$5),$K13,0)+IF(AND($C13>0,$C13>=X$4,$C13<=X$5),$I13+$J13,0) -> 0 | ... AB13: =IF(AND($C13>0,$C13<=AB$5,$D13>=AB$4),$E13*(1+$F13*(AB$4>=$G13))*'Key Assumptions'!$H$12+$H13+IF($M13="Straight-line",$N13,0),0)+IF(AND($M13="Upfront",$C13>=AB$4,$C13<=AB$5),$K13,0)+IF(AND($C13>0,$C13>=AB$4,$C13<=AB$5),$I13+$J13,0) -> 0 | AC13: =SUM(Q13:AB13) -> 0 | AD13: =IF($D13>0,$E13*MAX(0,(YEAR($D13)-2027)*12+(MONTH($D13)-12)),0) -> 0 | AE13: =IF('Key Assumptions'!B71="","",IF($D13<DATE(2027,12,31),"EXPIRED",IF($D13-DATE(2027,12,31)<=90,"RED <90d",IF($D13-DATE(2027,12,31)<=180,"YELLOW <180d","GREEN"))))
A14: ='Key Assumptions'!A72 -> 7 | B14: ='Key Assumptions'!B72 -> 0 | C14: =IF('Key Assumptions'!H72="",0,EDATE('Key Assumptions'!H72,'Key Assumptions'!$I$12)) -> 0 | D14: =IF('Key Assumptions'!I72="",0,'Key Assumptions'!I72) -> 0 | E14: =N('Key Assumptions'!J72) -> 0 | F14: =N('Key Assumptions'!K72) -> 0 | G14: =IF('Key Assumptions'!L72="",0,'Key Assumptions'!L72) -> 0 | H14: =IF('Key Assumptions'!R72="",IF(E14>0,E14*'Key Assumptions'!$B$61,0),'Key Assumptions'!R72) -> 0 | I14: =N('Key Assumptions'!M72) -> 0 | J14: =N('Key Assumptions'!N72) -> 0 | K14: =N('Key Assumptions'!O72) -> 0 | L14: =N('Key Assumptions'!P72) -> 0 | M14: =IF('Key Assumptions'!Q72="",'Key Assumptions'!$B$60,'Key Assumptions'!Q72) -> Straight-line | N14: =IF($M14="Straight-line",IFERROR($K14/($L14*12),0),0) -> 0 | Q14: =IF(AND($C14>0,$C14<=Q$5,$D14>=Q$4),$E14*(1+$F14*(Q$4>=$G14))*'Key Assumptions'!$H$12+$H14+IF($M14="Straight-line",$N14,0),0)+IF(AND($M14="Upfront",$C14>=Q$4,$C14<=Q$5),$K14,0)+IF(AND($C14>0,$C14>=Q$4,$C14<=Q$5),$I14+$J14,0) -> 0 | R14: =IF(AND($C14>0,$C14<=R$5,$D14>=R$4),$E14*(1+$F14*(R$4>=$G14))*'Key Assumptions'!$H$12+$H14+IF($M14="Straight-line",$N14,0),0)+IF(AND($M14="Upfront",$C14>=R$4,$C14<=R$5),$K14,0)+IF(AND($C14>0,$C14>=R$4,$C14<=R$5),$I14+$J14,0) -> 0 | S14: =IF(AND($C14>0,$C14<=S$5,$D14>=S$4),$E14*(1+$F14*(S$4>=$G14))*'Key Assumptions'!$H$12+$H14+IF($M14="Straight-line",$N14,0),0)+IF(AND($M14="Upfront",$C14>=S$4,$C14<=S$5),$K14,0)+IF(AND($C14>0,$C14>=S$4,$C14<=S$5),$I14+$J14,0) -> 0 | T14: =IF(AND($C14>0,$C14<=T$5,$D14>=T$4),$E14*(1+$F14*(T$4>=$G14))*'Key Assumptions'!$H$12+$H14+IF($M14="Straight-line",$N14,0),0)+IF(AND($M14="Upfront",$C14>=T$4,$C14<=T$5),$K14,0)+IF(AND($C14>0,$C14>=T$4,$C14<=T$5),$I14+$J14,0) -> 0 | U14: =IF(AND($C14>0,$C14<=U$5,$D14>=U$4),$E14*(1+$F14*(U$4>=$G14))*'Key Assumptions'!$H$12+$H14+IF($M14="Straight-line",$N14,0),0)+IF(AND($M14="Upfront",$C14>=U$4,$C14<=U$5),$K14,0)+IF(AND($C14>0,$C14>=U$4,$C14<=U$5),$I14+$J14,0) -> 0 | V14: =IF(AND($C14>0,$C14<=V$5,$D14>=V$4),$E14*(1+$F14*(V$4>=$G14))*'Key Assumptions'!$H$12+$H14+IF($M14="Straight-line",$N14,0),0)+IF(AND($M14="Upfront",$C14>=V$4,$C14<=V$5),$K14,0)+IF(AND($C14>0,$C14>=V$4,$C14<=V$5),$I14+$J14,0) -> 0 | W14: =IF(AND($C14>0,$C14<=W$5,$D14>=W$4),$E14*(1+$F14*(W$4>=$G14))*'Key Assumptions'!$H$12+$H14+IF($M14="Straight-line",$N14,0),0)+IF(AND($M14="Upfront",$C14>=W$4,$C14<=W$5),$K14,0)+IF(AND($C14>0,$C14>=W$4,$C14<=W$5),$I14+$J14,0) -> 0 | X14: =IF(AND($C14>0,$C14<=X$5,$D14>=X$4),$E14*(1+$F14*(X$4>=$G14))*'Key Assumptions'!$H$12+$H14+IF($M14="Straight-line",$N14,0),0)+IF(AND($M14="Upfront",$C14>=X$4,$C14<=X$5),$K14,0)+IF(AND($C14>0,$C14>=X$4,$C14<=X$5),$I14+$J14,0) -> 0 | ... AB14: =IF(AND($C14>0,$C14<=AB$5,$D14>=AB$4),$E14*(1+$F14*(AB$4>=$G14))*'Key Assumptions'!$H$12+$H14+IF($M14="Straight-line",$N14,0),0)+IF(AND($M14="Upfront",$C14>=AB$4,$C14<=AB$5),$K14,0)+IF(AND($C14>0,$C14>=AB$4,$C14<=AB$5),$I14+$J14,0) -> 0 | AC14: =SUM(Q14:AB14) -> 0 | AD14: =IF($D14>0,$E14*MAX(0,(YEAR($D14)-2027)*12+(MONTH($D14)-12)),0) -> 0 | AE14: =IF('Key Assumptions'!B72="","",IF($D14<DATE(2027,12,31),"EXPIRED",IF($D14-DATE(2027,12,31)<=90,"RED <90d",IF($D14-DATE(2027,12,31)<=180,"YELLOW <180d","GREEN"))))
A15: ='Key Assumptions'!A73 -> 8 | B15: ='Key Assumptions'!B73 -> 0 | C15: =IF('Key Assumptions'!H73="",0,EDATE('Key Assumptions'!H73,'Key Assumptions'!$I$12)) -> 0 | D15: =IF('Key Assumptions'!I73="",0,'Key Assumptions'!I73) -> 0 | E15: =N('Key Assumptions'!J73) -> 0 | F15: =N('Key Assumptions'!K73) -> 0 | G15: =IF('Key Assumptions'!L73="",0,'Key Assumptions'!L73) -> 0 | H15: =IF('Key Assumptions'!R73="",IF(E15>0,E15*'Key Assumptions'!$B$61,0),'Key Assumptions'!R73) -> 0 | I15: =N('Key Assumptions'!M73) -> 0 | J15: =N('Key Assumptions'!N73) -> 0 | K15: =N('Key Assumptions'!O73) -> 0 | L15: =N('Key Assumptions'!P73) -> 0 | M15: =IF('Key Assumptions'!Q73="",'Key Assumptions'!$B$60,'Key Assumptions'!Q73) -> Straight-line | N15: =IF($M15="Straight-line",IFERROR($K15/($L15*12),0),0) -> 0 | Q15: =IF(AND($C15>0,$C15<=Q$5,$D15>=Q$4),$E15*(1+$F15*(Q$4>=$G15))*'Key Assumptions'!$H$12+$H15+IF($M15="Straight-line",$N15,0),0)+IF(AND($M15="Upfront",$C15>=Q$4,$C15<=Q$5),$K15,0)+IF(AND($C15>0,$C15>=Q$4,$C15<=Q$5),$I15+$J15,0) -> 0 | R15: =IF(AND($C15>0,$C15<=R$5,$D15>=R$4),$E15*(1+$F15*(R$4>=$G15))*'Key Assumptions'!$H$12+$H15+IF($M15="Straight-line",$N15,0),0)+IF(AND($M15="Upfront",$C15>=R$4,$C15<=R$5),$K15,0)+IF(AND($C15>0,$C15>=R$4,$C15<=R$5),$I15+$J15,0) -> 0 | S15: =IF(AND($C15>0,$C15<=S$5,$D15>=S$4),$E15*(1+$F15*(S$4>=$G15))*'Key Assumptions'!$H$12+$H15+IF($M15="Straight-line",$N15,0),0)+IF(AND($M15="Upfront",$C15>=S$4,$C15<=S$5),$K15,0)+IF(AND($C15>0,$C15>=S$4,$C15<=S$5),$I15+$J15,0) -> 0 | T15: =IF(AND($C15>0,$C15<=T$5,$D15>=T$4),$E15*(1+$F15*(T$4>=$G15))*'Key Assumptions'!$H$12+$H15+IF($M15="Straight-line",$N15,0),0)+IF(AND($M15="Upfront",$C15>=T$4,$C15<=T$5),$K15,0)+IF(AND($C15>0,$C15>=T$4,$C15<=T$5),$I15+$J15,0) -> 0 | U15: =IF(AND($C15>0,$C15<=U$5,$D15>=U$4),$E15*(1+$F15*(U$4>=$G15))*'Key Assumptions'!$H$12+$H15+IF($M15="Straight-line",$N15,0),0)+IF(AND($M15="Upfront",$C15>=U$4,$C15<=U$5),$K15,0)+IF(AND($C15>0,$C15>=U$4,$C15<=U$5),$I15+$J15,0) -> 0 | V15: =IF(AND($C15>0,$C15<=V$5,$D15>=V$4),$E15*(1+$F15*(V$4>=$G15))*'Key Assumptions'!$H$12+$H15+IF($M15="Straight-line",$N15,0),0)+IF(AND($M15="Upfront",$C15>=V$4,$C15<=V$5),$K15,0)+IF(AND($C15>0,$C15>=V$4,$C15<=V$5),$I15+$J15,0) -> 0 | W15: =IF(AND($C15>0,$C15<=W$5,$D15>=W$4),$E15*(1+$F15*(W$4>=$G15))*'Key Assumptions'!$H$12+$H15+IF($M15="Straight-line",$N15,0),0)+IF(AND($M15="Upfront",$C15>=W$4,$C15<=W$5),$K15,0)+IF(AND($C15>0,$C15>=W$4,$C15<=W$5),$I15+$J15,0) -> 0 | X15: =IF(AND($C15>0,$C15<=X$5,$D15>=X$4),$E15*(1+$F15*(X$4>=$G15))*'Key Assumptions'!$H$12+$H15+IF($M15="Straight-line",$N15,0),0)+IF(AND($M15="Upfront",$C15>=X$4,$C15<=X$5),$K15,0)+IF(AND($C15>0,$C15>=X$4,$C15<=X$5),$I15+$J15,0) -> 0 | ... AB15: =IF(AND($C15>0,$C15<=AB$5,$D15>=AB$4),$E15*(1+$F15*(AB$4>=$G15))*'Key Assumptions'!$H$12+$H15+IF($M15="Straight-line",$N15,0),0)+IF(AND($M15="Upfront",$C15>=AB$4,$C15<=AB$5),$K15,0)+IF(AND($C15>0,$C15>=AB$4,$C15<=AB$5),$I15+$J15,0) -> 0 | AC15: =SUM(Q15:AB15) -> 0 | AD15: =IF($D15>0,$E15*MAX(0,(YEAR($D15)-2027)*12+(MONTH($D15)-12)),0) -> 0 | AE15: =IF('Key Assumptions'!B73="","",IF($D15<DATE(2027,12,31),"EXPIRED",IF($D15-DATE(2027,12,31)<=90,"RED <90d",IF($D15-DATE(2027,12,31)<=180,"YELLOW <180d","GREEN"))))
A16: ='Key Assumptions'!A74 -> 9 | B16: ='Key Assumptions'!B74 -> 0 | C16: =IF('Key Assumptions'!H74="",0,EDATE('Key Assumptions'!H74,'Key Assumptions'!$I$12)) -> 0 | D16: =IF('Key Assumptions'!I74="",0,'Key Assumptions'!I74) -> 0 | E16: =N('Key Assumptions'!J74) -> 0 | F16: =N('Key Assumptions'!K74) -> 0 | G16: =IF('Key Assumptions'!L74="",0,'Key Assumptions'!L74) -> 0 | H16: =IF('Key Assumptions'!R74="",IF(E16>0,E16*'Key Assumptions'!$B$61,0),'Key Assumptions'!R74) -> 0 | I16: =N('Key Assumptions'!M74) -> 0 | J16: =N('Key Assumptions'!N74) -> 0 | K16: =N('Key Assumptions'!O74) -> 0 | L16: =N('Key Assumptions'!P74) -> 0 | M16: =IF('Key Assumptions'!Q74="",'Key Assumptions'!$B$60,'Key Assumptions'!Q74) -> Straight-line | N16: =IF($M16="Straight-line",IFERROR($K16/($L16*12),0),0) -> 0 | Q16: =IF(AND($C16>0,$C16<=Q$5,$D16>=Q$4),$E16*(1+$F16*(Q$4>=$G16))*'Key Assumptions'!$H$12+$H16+IF($M16="Straight-line",$N16,0),0)+IF(AND($M16="Upfront",$C16>=Q$4,$C16<=Q$5),$K16,0)+IF(AND($C16>0,$C16>=Q$4,$C16<=Q$5),$I16+$J16,0) -> 0 | R16: =IF(AND($C16>0,$C16<=R$5,$D16>=R$4),$E16*(1+$F16*(R$4>=$G16))*'Key Assumptions'!$H$12+$H16+IF($M16="Straight-line",$N16,0),0)+IF(AND($M16="Upfront",$C16>=R$4,$C16<=R$5),$K16,0)+IF(AND($C16>0,$C16>=R$4,$C16<=R$5),$I16+$J16,0) -> 0 | S16: =IF(AND($C16>0,$C16<=S$5,$D16>=S$4),$E16*(1+$F16*(S$4>=$G16))*'Key Assumptions'!$H$12+$H16+IF($M16="Straight-line",$N16,0),0)+IF(AND($M16="Upfront",$C16>=S$4,$C16<=S$5),$K16,0)+IF(AND($C16>0,$C16>=S$4,$C16<=S$5),$I16+$J16,0) -> 0 | T16: =IF(AND($C16>0,$C16<=T$5,$D16>=T$4),$E16*(1+$F16*(T$4>=$G16))*'Key Assumptions'!$H$12+$H16+IF($M16="Straight-line",$N16,0),0)+IF(AND($M16="Upfront",$C16>=T$4,$C16<=T$5),$K16,0)+IF(AND($C16>0,$C16>=T$4,$C16<=T$5),$I16+$J16,0) -> 0 | U16: =IF(AND($C16>0,$C16<=U$5,$D16>=U$4),$E16*(1+$F16*(U$4>=$G16))*'Key Assumptions'!$H$12+$H16+IF($M16="Straight-line",$N16,0),0)+IF(AND($M16="Upfront",$C16>=U$4,$C16<=U$5),$K16,0)+IF(AND($C16>0,$C16>=U$4,$C16<=U$5),$I16+$J16,0) -> 0 | V16: =IF(AND($C16>0,$C16<=V$5,$D16>=V$4),$E16*(1+$F16*(V$4>=$G16))*'Key Assumptions'!$H$12+$H16+IF($M16="Straight-line",$N16,0),0)+IF(AND($M16="Upfront",$C16>=V$4,$C16<=V$5),$K16,0)+IF(AND($C16>0,$C16>=V$4,$C16<=V$5),$I16+$J16,0) -> 0 | W16: =IF(AND($C16>0,$C16<=W$5,$D16>=W$4),$E16*(1+$F16*(W$4>=$G16))*'Key Assumptions'!$H$12+$H16+IF($M16="Straight-line",$N16,0),0)+IF(AND($M16="Upfront",$C16>=W$4,$C16<=W$5),$K16,0)+IF(AND($C16>0,$C16>=W$4,$C16<=W$5),$I16+$J16,0) -> 0 | X16: =IF(AND($C16>0,$C16<=X$5,$D16>=X$4),$E16*(1+$F16*(X$4>=$G16))*'Key Assumptions'!$H$12+$H16+IF($M16="Straight-line",$N16,0),0)+IF(AND($M16="Upfront",$C16>=X$4,$C16<=X$5),$K16,0)+IF(AND($C16>0,$C16>=X$4,$C16<=X$5),$I16+$J16,0) -> 0 | ... AB16: =IF(AND($C16>0,$C16<=AB$5,$D16>=AB$4),$E16*(1+$F16*(AB$4>=$G16))*'Key Assumptions'!$H$12+$H16+IF($M16="Straight-line",$N16,0),0)+IF(AND($M16="Upfront",$C16>=AB$4,$C16<=AB$5),$K16,0)+IF(AND($C16>0,$C16>=AB$4,$C16<=AB$5),$I16+$J16,0) -> 0 | AC16: =SUM(Q16:AB16) -> 0 | AD16: =IF($D16>0,$E16*MAX(0,(YEAR($D16)-2027)*12+(MONTH($D16)-12)),0) -> 0 | AE16: =IF('Key Assumptions'!B74="","",IF($D16<DATE(2027,12,31),"EXPIRED",IF($D16-DATE(2027,12,31)<=90,"RED <90d",IF($D16-DATE(2027,12,31)<=180,"YELLOW <180d","GREEN"))))
A17: ='Key Assumptions'!A75 -> 10 | B17: ='Key Assumptions'!B75 -> 0 | C17: =IF('Key Assumptions'!H75="",0,EDATE('Key Assumptions'!H75,'Key Assumptions'!$I$12)) -> 0 | D17: =IF('Key Assumptions'!I75="",0,'Key Assumptions'!I75) -> 0 | E17: =N('Key Assumptions'!J75) -> 0 | F17: =N('Key Assumptions'!K75) -> 0 | G17: =IF('Key Assumptions'!L75="",0,'Key Assumptions'!L75) -> 0 | H17: =IF('Key Assumptions'!R75="",IF(E17>0,E17*'Key Assumptions'!$B$61,0),'Key Assumptions'!R75) -> 0 | I17: =N('Key Assumptions'!M75) -> 0 | J17: =N('Key Assumptions'!N75) -> 0 | K17: =N('Key Assumptions'!O75) -> 0 | L17: =N('Key Assumptions'!P75) -> 0 | M17: =IF('Key Assumptions'!Q75="",'Key Assumptions'!$B$60,'Key Assumptions'!Q75) -> Straight-line | N17: =IF($M17="Straight-line",IFERROR($K17/($L17*12),0),0) -> 0 | Q17: =IF(AND($C17>0,$C17<=Q$5,$D17>=Q$4),$E17*(1+$F17*(Q$4>=$G17))*'Key Assumptions'!$H$12+$H17+IF($M17="Straight-line",$N17,0),0)+IF(AND($M17="Upfront",$C17>=Q$4,$C17<=Q$5),$K17,0)+IF(AND($C17>0,$C17>=Q$4,$C17<=Q$5),$I17+$J17,0) -> 0 | R17: =IF(AND($C17>0,$C17<=R$5,$D17>=R$4),$E17*(1+$F17*(R$4>=$G17))*'Key Assumptions'!$H$12+$H17+IF($M17="Straight-line",$N17,0),0)+IF(AND($M17="Upfront",$C17>=R$4,$C17<=R$5),$K17,0)+IF(AND($C17>0,$C17>=R$4,$C17<=R$5),$I17+$J17,0) -> 0 | S17: =IF(AND($C17>0,$C17<=S$5,$D17>=S$4),$E17*(1+$F17*(S$4>=$G17))*'Key Assumptions'!$H$12+$H17+IF($M17="Straight-line",$N17,0),0)+IF(AND($M17="Upfront",$C17>=S$4,$C17<=S$5),$K17,0)+IF(AND($C17>0,$C17>=S$4,$C17<=S$5),$I17+$J17,0) -> 0 | T17: =IF(AND($C17>0,$C17<=T$5,$D17>=T$4),$E17*(1+$F17*(T$4>=$G17))*'Key Assumptions'!$H$12+$H17+IF($M17="Straight-line",$N17,0),0)+IF(AND($M17="Upfront",$C17>=T$4,$C17<=T$5),$K17,0)+IF(AND($C17>0,$C17>=T$4,$C17<=T$5),$I17+$J17,0) -> 0 | U17: =IF(AND($C17>0,$C17<=U$5,$D17>=U$4),$E17*(1+$F17*(U$4>=$G17))*'Key Assumptions'!$H$12+$H17+IF($M17="Straight-line",$N17,0),0)+IF(AND($M17="Upfront",$C17>=U$4,$C17<=U$5),$K17,0)+IF(AND($C17>0,$C17>=U$4,$C17<=U$5),$I17+$J17,0) -> 0 | V17: =IF(AND($C17>0,$C17<=V$5,$D17>=V$4),$E17*(1+$F17*(V$4>=$G17))*'Key Assumptions'!$H$12+$H17+IF($M17="Straight-line",$N17,0),0)+IF(AND($M17="Upfront",$C17>=V$4,$C17<=V$5),$K17,0)+IF(AND($C17>0,$C17>=V$4,$C17<=V$5),$I17+$J17,0) -> 0 | W17: =IF(AND($C17>0,$C17<=W$5,$D17>=W$4),$E17*(1+$F17*(W$4>=$G17))*'Key Assumptions'!$H$12+$H17+IF($M17="Straight-line",$N17,0),0)+IF(AND($M17="Upfront",$C17>=W$4,$C17<=W$5),$K17,0)+IF(AND($C17>0,$C17>=W$4,$C17<=W$5),$I17+$J17,0) -> 0 | X17: =IF(AND($C17>0,$C17<=X$5,$D17>=X$4),$E17*(1+$F17*(X$4>=$G17))*'Key Assumptions'!$H$12+$H17+IF($M17="Straight-line",$N17,0),0)+IF(AND($M17="Upfront",$C17>=X$4,$C17<=X$5),$K17,0)+IF(AND($C17>0,$C17>=X$4,$C17<=X$5),$I17+$J17,0) -> 0 | ... AB17: =IF(AND($C17>0,$C17<=AB$5,$D17>=AB$4),$E17*(1+$F17*(AB$4>=$G17))*'Key Assumptions'!$H$12+$H17+IF($M17="Straight-line",$N17,0),0)+IF(AND($M17="Upfront",$C17>=AB$4,$C17<=AB$5),$K17,0)+IF(AND($C17>0,$C17>=AB$4,$C17<=AB$5),$I17+$J17,0) -> 0 | AC17: =SUM(Q17:AB17) -> 0 | AD17: =IF($D17>0,$E17*MAX(0,(YEAR($D17)-2027)*12+(MONTH($D17)-12)),0) -> 0 | AE17: =IF('Key Assumptions'!B75="","",IF($D17<DATE(2027,12,31),"EXPIRED",IF($D17-DATE(2027,12,31)<=90,"RED <90d",IF($D17-DATE(2027,12,31)<=180,"YELLOW <180d","GREEN"))))
A18: ='Key Assumptions'!A76 -> 11 | B18: ='Key Assumptions'!B76 -> 0 | C18: =IF('Key Assumptions'!H76="",0,EDATE('Key Assumptions'!H76,'Key Assumptions'!$I$12)) -> 0 | D18: =IF('Key Assumptions'!I76="",0,'Key Assumptions'!I76) -> 0 | E18: =N('Key Assumptions'!J76) -> 0 | F18: =N('Key Assumptions'!K76) -> 0 | G18: =IF('Key Assumptions'!L76="",0,'Key Assumptions'!L76) -> 0 | H18: =IF('Key Assumptions'!R76="",IF(E18>0,E18*'Key Assumptions'!$B$61,0),'Key Assumptions'!R76) -> 0 | I18: =N('Key Assumptions'!M76) -> 0 | J18: =N('Key Assumptions'!N76) -> 0 | K18: =N('Key Assumptions'!O76) -> 0 | L18: =N('Key Assumptions'!P76) -> 0 | M18: =IF('Key Assumptions'!Q76="",'Key Assumptions'!$B$60,'Key Assumptions'!Q76) -> Straight-line | N18: =IF($M18="Straight-line",IFERROR($K18/($L18*12),0),0) -> 0 | Q18: =IF(AND($C18>0,$C18<=Q$5,$D18>=Q$4),$E18*(1+$F18*(Q$4>=$G18))*'Key Assumptions'!$H$12+$H18+IF($M18="Straight-line",$N18,0),0)+IF(AND($M18="Upfront",$C18>=Q$4,$C18<=Q$5),$K18,0)+IF(AND($C18>0,$C18>=Q$4,$C18<=Q$5),$I18+$J18,0) -> 0 | R18: =IF(AND($C18>0,$C18<=R$5,$D18>=R$4),$E18*(1+$F18*(R$4>=$G18))*'Key Assumptions'!$H$12+$H18+IF($M18="Straight-line",$N18,0),0)+IF(AND($M18="Upfront",$C18>=R$4,$C18<=R$5),$K18,0)+IF(AND($C18>0,$C18>=R$4,$C18<=R$5),$I18+$J18,0) -> 0 | S18: =IF(AND($C18>0,$C18<=S$5,$D18>=S$4),$E18*(1+$F18*(S$4>=$G18))*'Key Assumptions'!$H$12+$H18+IF($M18="Straight-line",$N18,0),0)+IF(AND($M18="Upfront",$C18>=S$4,$C18<=S$5),$K18,0)+IF(AND($C18>0,$C18>=S$4,$C18<=S$5),$I18+$J18,0) -> 0 | T18: =IF(AND($C18>0,$C18<=T$5,$D18>=T$4),$E18*(1+$F18*(T$4>=$G18))*'Key Assumptions'!$H$12+$H18+IF($M18="Straight-line",$N18,0),0)+IF(AND($M18="Upfront",$C18>=T$4,$C18<=T$5),$K18,0)+IF(AND($C18>0,$C18>=T$4,$C18<=T$5),$I18+$J18,0) -> 0 | U18: =IF(AND($C18>0,$C18<=U$5,$D18>=U$4),$E18*(1+$F18*(U$4>=$G18))*'Key Assumptions'!$H$12+$H18+IF($M18="Straight-line",$N18,0),0)+IF(AND($M18="Upfront",$C18>=U$4,$C18<=U$5),$K18,0)+IF(AND($C18>0,$C18>=U$4,$C18<=U$5),$I18+$J18,0) -> 0 | V18: =IF(AND($C18>0,$C18<=V$5,$D18>=V$4),$E18*(1+$F18*(V$4>=$G18))*'Key Assumptions'!$H$12+$H18+IF($M18="Straight-line",$N18,0),0)+IF(AND($M18="Upfront",$C18>=V$4,$C18<=V$5),$K18,0)+IF(AND($C18>0,$C18>=V$4,$C18<=V$5),$I18+$J18,0) -> 0 | W18: =IF(AND($C18>0,$C18<=W$5,$D18>=W$4),$E18*(1+$F18*(W$4>=$G18))*'Key Assumptions'!$H$12+$H18+IF($M18="Straight-line",$N18,0),0)+IF(AND($M18="Upfront",$C18>=W$4,$C18<=W$5),$K18,0)+IF(AND($C18>0,$C18>=W$4,$C18<=W$5),$I18+$J18,0) -> 0 | X18: =IF(AND($C18>0,$C18<=X$5,$D18>=X$4),$E18*(1+$F18*(X$4>=$G18))*'Key Assumptions'!$H$12+$H18+IF($M18="Straight-line",$N18,0),0)+IF(AND($M18="Upfront",$C18>=X$4,$C18<=X$5),$K18,0)+IF(AND($C18>0,$C18>=X$4,$C18<=X$5),$I18+$J18,0) -> 0 | ... AB18: =IF(AND($C18>0,$C18<=AB$5,$D18>=AB$4),$E18*(1+$F18*(AB$4>=$G18))*'Key Assumptions'!$H$12+$H18+IF($M18="Straight-line",$N18,0),0)+IF(AND($M18="Upfront",$C18>=AB$4,$C18<=AB$5),$K18,0)+IF(AND($C18>0,$C18>=AB$4,$C18<=AB$5),$I18+$J18,0) -> 0 | AC18: =SUM(Q18:AB18) -> 0 | AD18: =IF($D18>0,$E18*MAX(0,(YEAR($D18)-2027)*12+(MONTH($D18)-12)),0) -> 0 | AE18: =IF('Key Assumptions'!B76="","",IF($D18<DATE(2027,12,31),"EXPIRED",IF($D18-DATE(2027,12,31)<=90,"RED <90d",IF($D18-DATE(2027,12,31)<=180,"YELLOW <180d","GREEN"))))
A19: ='Key Assumptions'!A77 -> 12 | B19: ='Key Assumptions'!B77 -> 0 | C19: =IF('Key Assumptions'!H77="",0,EDATE('Key Assumptions'!H77,'Key Assumptions'!$I$12)) -> 0 | D19: =IF('Key Assumptions'!I77="",0,'Key Assumptions'!I77) -> 0 | E19: =N('Key Assumptions'!J77) -> 0 | F19: =N('Key Assumptions'!K77) -> 0 | G19: =IF('Key Assumptions'!L77="",0,'Key Assumptions'!L77) -> 0 | H19: =IF('Key Assumptions'!R77="",IF(E19>0,E19*'Key Assumptions'!$B$61,0),'Key Assumptions'!R77) -> 0 | I19: =N('Key Assumptions'!M77) -> 0 | J19: =N('Key Assumptions'!N77) -> 0 | K19: =N('Key Assumptions'!O77) -> 0 | L19: =N('Key Assumptions'!P77) -> 0 | M19: =IF('Key Assumptions'!Q77="",'Key Assumptions'!$B$60,'Key Assumptions'!Q77) -> Straight-line | N19: =IF($M19="Straight-line",IFERROR($K19/($L19*12),0),0) -> 0 | Q19: =IF(AND($C19>0,$C19<=Q$5,$D19>=Q$4),$E19*(1+$F19*(Q$4>=$G19))*'Key Assumptions'!$H$12+$H19+IF($M19="Straight-line",$N19,0),0)+IF(AND($M19="Upfront",$C19>=Q$4,$C19<=Q$5),$K19,0)+IF(AND($C19>0,$C19>=Q$4,$C19<=Q$5),$I19+$J19,0) -> 0 | R19: =IF(AND($C19>0,$C19<=R$5,$D19>=R$4),$E19*(1+$F19*(R$4>=$G19))*'Key Assumptions'!$H$12+$H19+IF($M19="Straight-line",$N19,0),0)+IF(AND($M19="Upfront",$C19>=R$4,$C19<=R$5),$K19,0)+IF(AND($C19>0,$C19>=R$4,$C19<=R$5),$I19+$J19,0) -> 0 | S19: =IF(AND($C19>0,$C19<=S$5,$D19>=S$4),$E19*(1+$F19*(S$4>=$G19))*'Key Assumptions'!$H$12+$H19+IF($M19="Straight-line",$N19,0),0)+IF(AND($M19="Upfront",$C19>=S$4,$C19<=S$5),$K19,0)+IF(AND($C19>0,$C19>=S$4,$C19<=S$5),$I19+$J19,0) -> 0 | T19: =IF(AND($C19>0,$C19<=T$5,$D19>=T$4),$E19*(1+$F19*(T$4>=$G19))*'Key Assumptions'!$H$12+$H19+IF($M19="Straight-line",$N19,0),0)+IF(AND($M19="Upfront",$C19>=T$4,$C19<=T$5),$K19,0)+IF(AND($C19>0,$C19>=T$4,$C19<=T$5),$I19+$J19,0) -> 0 | U19: =IF(AND($C19>0,$C19<=U$5,$D19>=U$4),$E19*(1+$F19*(U$4>=$G19))*'Key Assumptions'!$H$12+$H19+IF($M19="Straight-line",$N19,0),0)+IF(AND($M19="Upfront",$C19>=U$4,$C19<=U$5),$K19,0)+IF(AND($C19>0,$C19>=U$4,$C19<=U$5),$I19+$J19,0) -> 0 | V19: =IF(AND($C19>0,$C19<=V$5,$D19>=V$4),$E19*(1+$F19*(V$4>=$G19))*'Key Assumptions'!$H$12+$H19+IF($M19="Straight-line",$N19,0),0)+IF(AND($M19="Upfront",$C19>=V$4,$C19<=V$5),$K19,0)+IF(AND($C19>0,$C19>=V$4,$C19<=V$5),$I19+$J19,0) -> 0 | W19: =IF(AND($C19>0,$C19<=W$5,$D19>=W$4),$E19*(1+$F19*(W$4>=$G19))*'Key Assumptions'!$H$12+$H19+IF($M19="Straight-line",$N19,0),0)+IF(AND($M19="Upfront",$C19>=W$4,$C19<=W$5),$K19,0)+IF(AND($C19>0,$C19>=W$4,$C19<=W$5),$I19+$J19,0) -> 0 | X19: =IF(AND($C19>0,$C19<=X$5,$D19>=X$4),$E19*(1+$F19*(X$4>=$G19))*'Key Assumptions'!$H$12+$H19+IF($M19="Straight-line",$N19,0),0)+IF(AND($M19="Upfront",$C19>=X$4,$C19<=X$5),$K19,0)+IF(AND($C19>0,$C19>=X$4,$C19<=X$5),$I19+$J19,0) -> 0 | ... AB19: =IF(AND($C19>0,$C19<=AB$5,$D19>=AB$4),$E19*(1+$F19*(AB$4>=$G19))*'Key Assumptions'!$H$12+$H19+IF($M19="Straight-line",$N19,0),0)+IF(AND($M19="Upfront",$C19>=AB$4,$C19<=AB$5),$K19,0)+IF(AND($C19>0,$C19>=AB$4,$C19<=AB$5),$I19+$J19,0) -> 0 | AC19: =SUM(Q19:AB19) -> 0 | AD19: =IF($D19>0,$E19*MAX(0,(YEAR($D19)-2027)*12+(MONTH($D19)-12)),0) -> 0 | AE19: =IF('Key Assumptions'!B77="","",IF($D19<DATE(2027,12,31),"EXPIRED",IF($D19-DATE(2027,12,31)<=90,"RED <90d",IF($D19-DATE(2027,12,31)<=180,"YELLOW <180d","GREEN"))))
... A32: ='Key Assumptions'!A90 -> 25 | B32: ='Key Assumptions'!B90 -> 0 | C32: =IF('Key Assumptions'!H90="",0,EDATE('Key Assumptions'!H90,'Key Assumptions'!$I$12)) -> 0 | D32: =IF('Key Assumptions'!I90="",0,'Key Assumptions'!I90) -> 0 | E32: =N('Key Assumptions'!J90) -> 0 | F32: =N('Key Assumptions'!K90) -> 0 | G32: =IF('Key Assumptions'!L90="",0,'Key Assumptions'!L90) -> 0 | H32: =IF('Key Assumptions'!R90="",IF(E32>0,E32*'Key Assumptions'!$B$61,0),'Key Assumptions'!R90) -> 0 | I32: =N('Key Assumptions'!M90) -> 0 | J32: =N('Key Assumptions'!N90) -> 0 | K32: =N('Key Assumptions'!O90) -> 0 | L32: =N('Key Assumptions'!P90) -> 0 | M32: =IF('Key Assumptions'!Q90="",'Key Assumptions'!$B$60,'Key Assumptions'!Q90) -> Straight-line | N32: =IF($M32="Straight-line",IFERROR($K32/($L32*12),0),0) -> 0 | Q32: =IF(AND($C32>0,$C32<=Q$5,$D32>=Q$4),$E32*(1+$F32*(Q$4>=$G32))*'Key Assumptions'!$H$12+$H32+IF($M32="Straight-line",$N32,0),0)+IF(AND($M32="Upfront",$C32>=Q$4,$C32<=Q$5),$K32,0)+IF(AND($C32>0,$C32>=Q$4,$C32<=Q$5),$I32+$J32,0) -> 0 | R32: =IF(AND($C32>0,$C32<=R$5,$D32>=R$4),$E32*(1+$F32*(R$4>=$G32))*'Key Assumptions'!$H$12+$H32+IF($M32="Straight-line",$N32,0),0)+IF(AND($M32="Upfront",$C32>=R$4,$C32<=R$5),$K32,0)+IF(AND($C32>0,$C32>=R$4,$C32<=R$5),$I32+$J32,0) -> 0 | S32: =IF(AND($C32>0,$C32<=S$5,$D32>=S$4),$E32*(1+$F32*(S$4>=$G32))*'Key Assumptions'!$H$12+$H32+IF($M32="Straight-line",$N32,0),0)+IF(AND($M32="Upfront",$C32>=S$4,$C32<=S$5),$K32,0)+IF(AND($C32>0,$C32>=S$4,$C32<=S$5),$I32+$J32,0) -> 0 | T32: =IF(AND($C32>0,$C32<=T$5,$D32>=T$4),$E32*(1+$F32*(T$4>=$G32))*'Key Assumptions'!$H$12+$H32+IF($M32="Straight-line",$N32,0),0)+IF(AND($M32="Upfront",$C32>=T$4,$C32<=T$5),$K32,0)+IF(AND($C32>0,$C32>=T$4,$C32<=T$5),$I32+$J32,0) -> 0 | U32: =IF(AND($C32>0,$C32<=U$5,$D32>=U$4),$E32*(1+$F32*(U$4>=$G32))*'Key Assumptions'!$H$12+$H32+IF($M32="Straight-line",$N32,0),0)+IF(AND($M32="Upfront",$C32>=U$4,$C32<=U$5),$K32,0)+IF(AND($C32>0,$C32>=U$4,$C32<=U$5),$I32+$J32,0) -> 0 | V32: =IF(AND($C32>0,$C32<=V$5,$D32>=V$4),$E32*(1+$F32*(V$4>=$G32))*'Key Assumptions'!$H$12+$H32+IF($M32="Straight-line",$N32,0),0)+IF(AND($M32="Upfront",$C32>=V$4,$C32<=V$5),$K32,0)+IF(AND($C32>0,$C32>=V$4,$C32<=V$5),$I32+$J32,0) -> 0 | W32: =IF(AND($C32>0,$C32<=W$5,$D32>=W$4),$E32*(1+$F32*(W$4>=$G32))*'Key Assumptions'!$H$12+$H32+IF($M32="Straight-line",$N32,0),0)+IF(AND($M32="Upfront",$C32>=W$4,$C32<=W$5),$K32,0)+IF(AND($C32>0,$C32>=W$4,$C32<=W$5),$I32+$J32,0) -> 0 | X32: =IF(AND($C32>0,$C32<=X$5,$D32>=X$4),$E32*(1+$F32*(X$4>=$G32))*'Key Assumptions'!$H$12+$H32+IF($M32="Straight-line",$N32,0),0)+IF(AND($M32="Upfront",$C32>=X$4,$C32<=X$5),$K32,0)+IF(AND($C32>0,$C32>=X$4,$C32<=X$5),$I32+$J32,0) -> 0 | ... AB32: =IF(AND($C32>0,$C32<=AB$5,$D32>=AB$4),$E32*(1+$F32*(AB$4>=$G32))*'Key Assumptions'!$H$12+$H32+IF($M32="Straight-line",$N32,0),0)+IF(AND($M32="Upfront",$C32>=AB$4,$C32<=AB$5),$K32,0)+IF(AND($C32>0,$C32>=AB$4,$C32<=AB$5),$I32+$J32,0) -> 0 | AC32: =SUM(Q32:AB32) -> 0 | AD32: =IF($D32>0,$E32*MAX(0,(YEAR($D32)-2027)*12+(MONTH($D32)-12)),0) -> 0 | AE32: =IF('Key Assumptions'!B90="","",IF($D32<DATE(2027,12,31),"EXPIRED",IF($D32-DATE(2027,12,31)<=90,"RED <90d",IF($D32-DATE(2027,12,31)<=180,"YELLOW <180d","GREEN"))))
A33: TOTAL — ALL CONTRACTS | Q33: =SUM(Q8:Q32) -> 1595 | R33: =SUM(R8:R32) -> 1595 | S33: =SUM(S8:S32) -> 1595 | T33: =SUM(T8:T32) -> 1595 | U33: =SUM(U8:U32) -> 1595 | V33: =SUM(V8:V32) -> 1595 | W33: =SUM(W8:W32) -> 1595 | X33: =SUM(X8:X32) -> 1595 | ... AB33: =SUM(AB8:AB32) -> 1595 | AC33: =SUM(Q33:AB33) -> 19140 | AD33: =SUM(AD8:AD32) -> 57420
A35: MONTHLY REVENUE BY TYPE (all contracts)
A36: Dark fiber recurring (lease) | Q36: =SUMPRODUCT(($C$8:$C$32>0)*($C$8:$C$32<=Q$5)*($D$8:$D$32>=Q$4)*$E$8:$E$32*(1+$F$8:$F$32*(Q$4>=$G$8:$G$32)))*'Key Assumptions'!$H$12 -> 1595 | R36: =SUMPRODUCT(($C$8:$C$32>0)*($C$8:$C$32<=R$5)*($D$8:$D$32>=R$4)*$E$8:$E$32*(1+$F$8:$F$32*(R$4>=$G$8:$G$32)))*'Key Assumptions'!$H$12 -> 1595 | S36: =SUMPRODUCT(($C$8:$C$32>0)*($C$8:$C$32<=S$5)*($D$8:$D$32>=S$4)*$E$8:$E$32*(1+$F$8:$F$32*(S$4>=$G$8:$G$32)))*'Key Assumptions'!$H$12 -> 1595 | T36: =SUMPRODUCT(($C$8:$C$32>0)*($C$8:$C$32<=T$5)*($D$8:$D$32>=T$4)*$E$8:$E$32*(1+$F$8:$F$32*(T$4>=$G$8:$G$32)))*'Key Assumptions'!$H$12 -> 1595 | U36: =SUMPRODUCT(($C$8:$C$32>0)*($C$8:$C$32<=U$5)*($D$8:$D$32>=U$4)*$E$8:$E$32*(1+$F$8:$F$32*(U$4>=$G$8:$G$32)))*'Key Assumptions'!$H$12 -> 1595 | V36: =SUMPRODUCT(($C$8:$C$32>0)*($C$8:$C$32<=V$5)*($D$8:$D$32>=V$4)*$E$8:$E$32*(1+$F$8:$F$32*(V$4>=$G$8:$G$32)))*'Key Assumptions'!$H$12 -> 1595 | W36: =SUMPRODUCT(($C$8:$C$32>0)*($C$8:$C$32<=W$5)*($D$8:$D$32>=W$4)*$E$8:$E$32*(1+$F$8:$F$32*(W$4>=$G$8:$G$32)))*'Key Assumptions'!$H$12 -> 1595 | X36: =SUMPRODUCT(($C$8:$C$32>0)*($C$8:$C$32<=X$5)*($D$8:$D$32>=X$4)*$E$8:$E$32*(1+$F$8:$F$32*(X$4>=$G$8:$G$32)))*'Key Assumptions'!$H$12 -> 1595 | ... AB36: =SUMPRODUCT(($C$8:$C$32>0)*($C$8:$C$32<=AB$5)*($D$8:$D$32>=AB$4)*$E$8:$E$32*(1+$F$8:$F$32*(AB$4>=$G$8:$G$32)))*'Key Assumptions'!$H$12 -> 1595 | AC36: =SUM(Q36:AB36) -> 19140
A37: O&M revenue | Q37: =SUMPRODUCT(($C$8:$C$32>0)*($C$8:$C$32<=Q$5)*($D$8:$D$32>=Q$4)*$H$8:$H$32) -> 0 | R37: =SUMPRODUCT(($C$8:$C$32>0)*($C$8:$C$32<=R$5)*($D$8:$D$32>=R$4)*$H$8:$H$32) -> 0 | S37: =SUMPRODUCT(($C$8:$C$32>0)*($C$8:$C$32<=S$5)*($D$8:$D$32>=S$4)*$H$8:$H$32) -> 0 | T37: =SUMPRODUCT(($C$8:$C$32>0)*($C$8:$C$32<=T$5)*($D$8:$D$32>=T$4)*$H$8:$H$32) -> 0 | U37: =SUMPRODUCT(($C$8:$C$32>0)*($C$8:$C$32<=U$5)*($D$8:$D$32>=U$4)*$H$8:$H$32) -> 0 | V37: =SUMPRODUCT(($C$8:$C$32>0)*($C$8:$C$32<=V$5)*($D$8:$D$32>=V$4)*$H$8:$H$32) -> 0 | W37: =SUMPRODUCT(($C$8:$C$32>0)*($C$8:$C$32<=W$5)*($D$8:$D$32>=W$4)*$H$8:$H$32) -> 0 | X37: =SUMPRODUCT(($C$8:$C$32>0)*($C$8:$C$32<=X$5)*($D$8:$D$32>=X$4)*$H$8:$H$32) -> 0 | ... AB37: =SUMPRODUCT(($C$8:$C$32>0)*($C$8:$C$32<=AB$5)*($D$8:$D$32>=AB$4)*$H$8:$H$32) -> 0 | AC37: =SUM(Q37:AB37) -> 0
A38: IRU revenue recognized | Q38: =SUMPRODUCT(($M$8:$M$32="Straight-line")*($C$8:$C$32>0)*($C$8:$C$32<=Q$5)*($D$8:$D$32>=Q$4)*$N$8:$N$32)+SUMPRODUCT(($M$8:$M$32="Upfront")*($C$8:$C$32>0)*($C$8:$C$32>=Q$4)*($C$8:$C$32<=Q$5)*$K$8:$K$32) -> 0 | R38: =SUMPRODUCT(($M$8:$M$32="Straight-line")*($C$8:$C$32>0)*($C$8:$C$32<=R$5)*($D$8:$D$32>=R$4)*$N$8:$N$32)+SUMPRODUCT(($M$8:$M$32="Upfront")*($C$8:$C$32>0)*($C$8:$C$32>=R$4)*($C$8:$C$32<=R$5)*$K$8:$K$32) -> 0 | S38: =SUMPRODUCT(($M$8:$M$32="Straight-line")*($C$8:$C$32>0)*($C$8:$C$32<=S$5)*($D$8:$D$32>=S$4)*$N$8:$N$32)+SUMPRODUCT(($M$8:$M$32="Upfront")*($C$8:$C$32>0)*($C$8:$C$32>=S$4)*($C$8:$C$32<=S$5)*$K$8:$K$32) -> 0 | T38: =SUMPRODUCT(($M$8:$M$32="Straight-line")*($C$8:$C$32>0)*($C$8:$C$32<=T$5)*($D$8:$D$32>=T$4)*$N$8:$N$32)+SUMPRODUCT(($M$8:$M$32="Upfront")*($C$8:$C$32>0)*($C$8:$C$32>=T$4)*($C$8:$C$32<=T$5)*$K$8:$K$32) -> 0 | U38: =SUMPRODUCT(($M$8:$M$32="Straight-line")*($C$8:$C$32>0)*($C$8:$C$32<=U$5)*($D$8:$D$32>=U$4)*$N$8:$N$32)+SUMPRODUCT(($M$8:$M$32="Upfront")*($C$8:$C$32>0)*($C$8:$C$32>=U$4)*($C$8:$C$32<=U$5)*$K$8:$K$32) -> 0 | V38: =SUMPRODUCT(($M$8:$M$32="Straight-line")*($C$8:$C$32>0)*($C$8:$C$32<=V$5)*($D$8:$D$32>=V$4)*$N$8:$N$32)+SUMPRODUCT(($M$8:$M$32="Upfront")*($C$8:$C$32>0)*($C$8:$C$32>=V$4)*($C$8:$C$32<=V$5)*$K$8:$K$32) -> 0 | W38: =SUMPRODUCT(($M$8:$M$32="Straight-line")*($C$8:$C$32>0)*($C$8:$C$32<=W$5)*($D$8:$D$32>=W$4)*$N$8:$N$32)+SUMPRODUCT(($M$8:$M$32="Upfront")*($C$8:$C$32>0)*($C$8:$C$32>=W$4)*($C$8:$C$32<=W$5)*$K$8:$K$32) -> 0 | X38: =SUMPRODUCT(($M$8:$M$32="Straight-line")*($C$8:$C$32>0)*($C$8:$C$32<=X$5)*($D$8:$D$32>=X$4)*$N$8:$N$32)+SUMPRODUCT(($M$8:$M$32="Upfront")*($C$8:$C$32>0)*($C$8:$C$32>=X$4)*($C$8:$C$32<=X$5)*$K$8:$K$32) -> 0 | ... AB38: =SUMPRODUCT(($M$8:$M$32="Straight-line")*($C$8:$C$32>0)*($C$8:$C$32<=AB$5)*($D$8:$D$32>=AB$4)*$N$8:$N$32)+SUMPRODUCT(($M$8:$M$32="Upfront")*($C$8:$C$32>0)*($C$8:$C$32>=AB$4)*($C$8:$C$32<=AB$5)*$K$8:$K$32) -> 0 | AC38: =SUM(Q38:AB38) -> 0
A39: One-time construction | Q39: =SUMPRODUCT(($C$8:$C$32>0)*($C$8:$C$32>=Q$4)*($C$8:$C$32<=Q$5)*$I$8:$I$32) -> 0 | R39: =SUMPRODUCT(($C$8:$C$32>0)*($C$8:$C$32>=R$4)*($C$8:$C$32<=R$5)*$I$8:$I$32) -> 0 | S39: =SUMPRODUCT(($C$8:$C$32>0)*($C$8:$C$32>=S$4)*($C$8:$C$32<=S$5)*$I$8:$I$32) -> 0 | T39: =SUMPRODUCT(($C$8:$C$32>0)*($C$8:$C$32>=T$4)*($C$8:$C$32<=T$5)*$I$8:$I$32) -> 0 | U39: =SUMPRODUCT(($C$8:$C$32>0)*($C$8:$C$32>=U$4)*($C$8:$C$32<=U$5)*$I$8:$I$32) -> 0 | V39: =SUMPRODUCT(($C$8:$C$32>0)*($C$8:$C$32>=V$4)*($C$8:$C$32<=V$5)*$I$8:$I$32) -> 0 | W39: =SUMPRODUCT(($C$8:$C$32>0)*($C$8:$C$32>=W$4)*($C$8:$C$32<=W$5)*$I$8:$I$32) -> 0 | X39: =SUMPRODUCT(($C$8:$C$32>0)*($C$8:$C$32>=X$4)*($C$8:$C$32<=X$5)*$I$8:$I$32) -> 0 | ... AB39: =SUMPRODUCT(($C$8:$C$32>0)*($C$8:$C$32>=AB$4)*($C$8:$C$32<=AB$5)*$I$8:$I$32) -> 0 | AC39: =SUM(Q39:AB39) -> 0
A40: One-time activation | Q40: =SUMPRODUCT(($C$8:$C$32>0)*($C$8:$C$32>=Q$4)*($C$8:$C$32<=Q$5)*$J$8:$J$32) -> 0 | R40: =SUMPRODUCT(($C$8:$C$32>0)*($C$8:$C$32>=R$4)*($C$8:$C$32<=R$5)*$J$8:$J$32) -> 0 | S40: =SUMPRODUCT(($C$8:$C$32>0)*($C$8:$C$32>=S$4)*($C$8:$C$32<=S$5)*$J$8:$J$32) -> 0 | T40: =SUMPRODUCT(($C$8:$C$32>0)*($C$8:$C$32>=T$4)*($C$8:$C$32<=T$5)*$J$8:$J$32) -> 0 | U40: =SUMPRODUCT(($C$8:$C$32>0)*($C$8:$C$32>=U$4)*($C$8:$C$32<=U$5)*$J$8:$J$32) -> 0 | V40: =SUMPRODUCT(($C$8:$C$32>0)*($C$8:$C$32>=V$4)*($C$8:$C$32<=V$5)*$J$8:$J$32) -> 0 | W40: =SUMPRODUCT(($C$8:$C$32>0)*($C$8:$C$32>=W$4)*($C$8:$C$32<=W$5)*$J$8:$J$32) -> 0 | X40: =SUMPRODUCT(($C$8:$C$32>0)*($C$8:$C$32>=X$4)*($C$8:$C$32<=X$5)*$J$8:$J$32) -> 0 | ... AB40: =SUMPRODUCT(($C$8:$C$32>0)*($C$8:$C$32>=AB$4)*($C$8:$C$32<=AB$5)*$J$8:$J$32) -> 0 | AC40: =SUM(Q40:AB40) -> 0
A41: Other recurring | Q41: 0 | R41: 0 | S41: 0 | T41: 0 | U41: 0 | V41: 0 | W41: 0 | X41: 0 | Y41: 0 | Z41: 0 | AA41: 0 | AB41: 0 | AC41: =SUM(Q41:AB41) -> 0
A42: Net dark fiber revenue | Q42: =SUM(Q36:Q41) -> 1595 | R42: =SUM(R36:R41) -> 1595 | S42: =SUM(S36:S41) -> 1595 | T42: =SUM(T36:T41) -> 1595 | U42: =SUM(U36:U41) -> 1595 | V42: =SUM(V36:V41) -> 1595 | W42: =SUM(W36:W41) -> 1595 | X42: =SUM(X36:X41) -> 1595 | ... AB42: =SUM(AB36:AB41) -> 1595 | AC42: =SUM(Q42:AB42) -> 19140
A43: Net dark fiber (scenario-neutral) | Q43: =SUMPRODUCT(('Key Assumptions'!$H$66:$H$90>0)*('Key Assumptions'!$H$66:$H$90<=Q$5)*('Key Assumptions'!$I$66:$I$90>=Q$4)*('Key Assumptions'!$J$66:$J$90*(1+'Key Assumptions'!$K$66:$K$90*(Q$4>='Key Assumptions'!$L$66:$L$90))+$H$8:$H$32))+SUMPRODUCT(($M$8:$M$32="Straight-line")*('Key Assumptions'!$H$66:$H$90>0)*('Key Assumptions'!$H$66:$H$90<=Q$5)*('Key Assumptions'!$I$66:$I$90>=Q$4)*$N$8:$N$32)+SUMPRODUCT(($M$8:$M$32="Upfront")*('Key Assumptions'!$H$66:$H$90>0)*('Key Assumptions'!$H$66:$H$90>=Q$4)*('Key Assumptions'!$H$66:$H$90<=Q$5)*'Key Assumptions'!$O$66:$O$90)+SUMPRODUCT(('Key Assumptions'!$H$66:$H$90>0)*('Key Assumptions'!$H$66:$H$90>=Q$4)*('Key Assumptions'!$H$66:$H$90<=Q$5)*('Key Assumptions'!$M$66:$M$90+'Key Assumptions'!$N$66:$N$90)) -> 1595 | R43: =SUMPRODUCT(('Key Assumptions'!$H$66:$H$90>0)*('Key Assumptions'!$H$66:$H$90<=R$5)*('Key Assumptions'!$I$66:$I$90>=R$4)*('Key Assumptions'!$J$66:$J$90*(1+'Key Assumptions'!$K$66:$K$90*(R$4>='Key Assumptions'!$L$66:$L$90))+$H$8:$H$32))+SUMPRODUCT(($M$8:$M$32="Straight-line")*('Key Assumptions'!$H$66:$H$90>0)*('Key Assumptions'!$H$66:$H$90<=R$5)*('Key Assumptions'!$I$66:$I$90>=R$4)*$N$8:$N$32)+SUMPRODUCT(($M$8:$M$32="Upfront")*('Key Assumptions'!$H$66:$H$90>0)*('Key Assumptions'!$H$66:$H$90>=R$4)*('Key Assumptions'!$H$66:$H$90<=R$5)*'Key Assumptions'!$O$66:$O$90)+SUMPRODUCT(('Key Assumptions'!$H$66:$H$90>0)*('Key Assumptions'!$H$66:$H$90>=R$4)*('Key Assumptions'!$H$66:$H$90<=R$5)*('Key Assumptions'!$M$66:$M$90+'Key Assumptions'!$N$66:$N$90)) -> 1595 | S43: =SUMPRODUCT(('Key Assumptions'!$H$66:$H$90>0)*('Key Assumptions'!$H$66:$H$90<=S$5)*('Key Assumptions'!$I$66:$I$90>=S$4)*('Key Assumptions'!$J$66:$J$90*(1+'Key Assumptions'!$K$66:$K$90*(S$4>='Key Assumptions'!$L$66:$L$90))+$H$8:$H$32))+SUMPRODUCT(($M$8:$M$32="Straight-line")*('Key Assumptions'!$H$66:$H$90>0)*('Key Assumptions'!$H$66:$H$90<=S$5)*('Key Assumptions'!$I$66:$I$90>=S$4)*$N$8:$N$32)+SUMPRODUCT(($M$8:$M$32="Upfront")*('Key Assumptions'!$H$66:$H$90>0)*('Key Assumptions'!$H$66:$H$90>=S$4)*('Key Assumptions'!$H$66:$H$90<=S$5)*'Key Assumptions'!$O$66:$O$90)+SUMPRODUCT(('Key Assumptions'!$H$66:$H$90>0)*('Key Assumptions'!$H$66:$H$90>=S$4)*('Key Assumptions'!$H$66:$H$90<=S$5)*('Key Assumptions'!$M$66:$M$90+'Key Assumptions'!$N$66:$N$90)) -> 1595 | T43: =SUMPRODUCT(('Key Assumptions'!$H$66:$H$90>0)*('Key Assumptions'!$H$66:$H$90<=T$5)*('Key Assumptions'!$I$66:$I$90>=T$4)*('Key Assumptions'!$J$66:$J$90*(1+'Key Assumptions'!$K$66:$K$90*(T$4>='Key Assumptions'!$L$66:$L$90))+$H$8:$H$32))+SUMPRODUCT(($M$8:$M$32="Straight-line")*('Key Assumptions'!$H$66:$H$90>0)*('Key Assumptions'!$H$66:$H$90<=T$5)*('Key Assumptions'!$I$66:$I$90>=T$4)*$N$8:$N$32)+SUMPRODUCT(($M$8:$M$32="Upfront")*('Key Assumptions'!$H$66:$H$90>0)*('Key Assumptions'!$H$66:$H$90>=T$4)*('Key Assumptions'!$H$66:$H$90<=T$5)*'Key Assumptions'!$O$66:$O$90)+SUMPRODUCT(('Key Assumptions'!$H$66:$H$90>0)*('Key Assumptions'!$H$66:$H$90>=T$4)*('Key Assumptions'!$H$66:$H$90<=T$5)*('Key Assumptions'!$M$66:$M$90+'Key Assumptions'!$N$66:$N$90)) -> 1595 | U43: =SUMPRODUCT(('Key Assumptions'!$H$66:$H$90>0)*('Key Assumptions'!$H$66:$H$90<=U$5)*('Key Assumptions'!$I$66:$I$90>=U$4)*('Key Assumptions'!$J$66:$J$90*(1+'Key Assumptions'!$K$66:$K$90*(U$4>='Key Assumptions'!$L$66:$L$90))+$H$8:$H$32))+SUMPRODUCT(($M$8:$M$32="Straight-line")*('Key Assumptions'!$H$66:$H$90>0)*('Key Assumptions'!$H$66:$H$90<=U$5)*('Key Assumptions'!$I$66:$I$90>=U$4)*$N$8:$N$32)+SUMPRODUCT(($M$8:$M$32="Upfront")*('Key Assumptions'!$H$66:$H$90>0)*('Key Assumptions'!$H$66:$H$90>=U$4)*('Key Assumptions'!$H$66:$H$90<=U$5)*'Key Assumptions'!$O$66:$O$90)+SUMPRODUCT(('Key Assumptions'!$H$66:$H$90>0)*('Key Assumptions'!$H$66:$H$90>=U$4)*('Key Assumptions'!$H$66:$H$90<=U$5)*('Key Assumptions'!$M$66:$M$90+'Key Assumptions'!$N$66:$N$90)) -> 1595 | V43: =SUMPRODUCT(('Key Assumptions'!$H$66:$H$90>0)*('Key Assumptions'!$H$66:$H$90<=V$5)*('Key Assumptions'!$I$66:$I$90>=V$4)*('Key Assumptions'!$J$66:$J$90*(1+'Key Assumptions'!$K$66:$K$90*(V$4>='Key Assumptions'!$L$66:$L$90))+$H$8:$H$32))+SUMPRODUCT(($M$8:$M$32="Straight-line")*('Key Assumptions'!$H$66:$H$90>0)*('Key Assumptions'!$H$66:$H$90<=V$5)*('Key Assumptions'!$I$66:$I$90>=V$4)*$N$8:$N$32)+SUMPRODUCT(($M$8:$M$32="Upfront")*('Key Assumptions'!$H$66:$H$90>0)*('Key Assumptions'!$H$66:$H$90>=V$4)*('Key Assumptions'!$H$66:$H$90<=V$5)*'Key Assumptions'!$O$66:$O$90)+SUMPRODUCT(('Key Assumptions'!$H$66:$H$90>0)*('Key Assumptions'!$H$66:$H$90>=V$4)*('Key Assumptions'!$H$66:$H$90<=V$5)*('Key Assumptions'!$M$66:$M$90+'Key Assumptions'!$N$66:$N$90)) -> 1595 | W43: =SUMPRODUCT(('Key Assumptions'!$H$66:$H$90>0)*('Key Assumptions'!$H$66:$H$90<=W$5)*('Key Assumptions'!$I$66:$I$90>=W$4)*('Key Assumptions'!$J$66:$J$90*(1+'Key Assumptions'!$K$66:$K$90*(W$4>='Key Assumptions'!$L$66:$L$90))+$H$8:$H$32))+SUMPRODUCT(($M$8:$M$32="Straight-line")*('Key Assumptions'!$H$66:$H$90>0)*('Key Assumptions'!$H$66:$H$90<=W$5)*('Key Assumptions'!$I$66:$I$90>=W$4)*$N$8:$N$32)+SUMPRODUCT(($M$8:$M$32="Upfront")*('Key Assumptions'!$H$66:$H$90>0)*('Key Assumptions'!$H$66:$H$90>=W$4)*('Key Assumptions'!$H$66:$H$90<=W$5)*'Key Assumptions'!$O$66:$O$90)+SUMPRODUCT(('Key Assumptions'!$H$66:$H$90>0)*('Key Assumptions'!$H$66:$H$90>=W$4)*('Key Assumptions'!$H$66:$H$90<=W$5)*('Key Assumptions'!$M$66:$M$90+'Key Assumptions'!$N$66:$N$90)) -> 1595 | X43: =SUMPRODUCT(('Key Assumptions'!$H$66:$H$90>0)*('Key Assumptions'!$H$66:$H$90<=X$5)*('Key Assumptions'!$I$66:$I$90>=X$4)*('Key Assumptions'!$J$66:$J$90*(1+'Key Assumptions'!$K$66:$K$90*(X$4>='Key Assumptions'!$L$66:$L$90))+$H$8:$H$32))+SUMPRODUCT(($M$8:$M$32="Straight-line")*('Key Assumptions'!$H$66:$H$90>0)*('Key Assumptions'!$H$66:$H$90<=X$5)*('Key Assumptions'!$I$66:$I$90>=X$4)*$N$8:$N$32)+SUMPRODUCT(($M$8:$M$32="Upfront")*('Key Assumptions'!$H$66:$H$90>0)*('Key Assumptions'!$H$66:$H$90>=X$4)*('Key Assumptions'!$H$66:$H$90<=X$5)*'Key Assumptions'!$O$66:$O$90)+SUMPRODUCT(('Key Assumptions'!$H$66:$H$90>0)*('Key Assumptions'!$H$66:$H$90>=X$4)*('Key Assumptions'!$H$66:$H$90<=X$5)*('Key Assumptions'!$M$66:$M$90+'Key Assumptions'!$N$66:$N$90)) -> 1595 | ... AB43: =SUMPRODUCT(('Key Assumptions'!$H$66:$H$90>0)*('Key Assumptions'!$H$66:$H$90<=AB$5)*('Key Assumptions'!$I$66:$I$90>=AB$4)*('Key Assumptions'!$J$66:$J$90*(1+'Key Assumptions'!$K$66:$K$90*(AB$4>='Key Assumptions'!$L$66:$L$90))+$H$8:$H$32))+SUMPRODUCT(($M$8:$M$32="Straight-line")*('Key Assumptions'!$H$66:$H$90>0)*('Key Assumptions'!$H$66:$H$90<=AB$5)*('Key Assumptions'!$I$66:$I$90>=AB$4)*$N$8:$N$32)+SUMPRODUCT(($M$8:$M$32="Upfront")*('Key Assumptions'!$H$66:$H$90>0)*('Key Assumptions'!$H$66:$H$90>=AB$4)*('Key Assumptions'!$H$66:$H$90<=AB$5)*'Key Assumptions'!$O$66:$O$90)+SUMPRODUCT(('Key Assumptions'!$H$66:$H$90>0)*('Key Assumptions'!$H$66:$H$90>=AB$4)*('Key Assumptions'!$H$66:$H$90<=AB$5)*('Key Assumptions'!$M$66:$M$90+'Key Assumptions'!$N$66:$N$90)) -> 1595 | AC43: =SUM(Q43:AB43) -> 19140
A45: Expiration alert: | B45: RED = ≤90 days | C45: YELLOW = ≤180 days | D45: GREEN = >180 days
A47: IRU NOTE: Upfront IRU recognition materially changes 2027 revenue. Confirm ASC 606 treatment with RIVR Tech CFO & external accountant before relying on these figures.

Sheet Consolidated Revenue
A1: CONSOLIDATED REVENUE STATEMENT — 2027
A2: All segments combined. Reflects the active scenario selected on Key Assumptions. Grey = formulas.
A3: Revenue ($) | B3: 46388 | C3: 46419 | D3: 46447 | E3: 46478 | F3: 46508 | G3: 46539 | H3: 46569 | I3: 46600 | J3: 46631 | K3: 46661 | L3: 46692 | M3: 46722 | N3: FY 2027 | O3: Q1 | P3: Q2 | Q3: Q3 | R3: Q4
A6: RESIDENTIAL
A7: Residential recurring revenue | B7: ='Residential Forecast'!B20 -> 320867.87 | C7: ='Residential Forecast'!C20 -> 321019.79 | D7: ='Residential Forecast'!D20 -> 321171.71 | E7: ='Residential Forecast'!E20 -> 321323.63 | F7: ='Residential Forecast'!F20 -> 321475.55 | G7: ='Residential Forecast'!G20 -> 321627.47 | H7: ='Residential Forecast'!H20 -> 330794.81 | I7: ='Residential Forecast'!I20 -> 330951.17 | ... M7: ='Residential Forecast'!M20 -> 331576.61 | N7: =SUM(B7:M7) -> 3914600.3 | O7: =SUM(B7:D7) -> 963059.38 | P7: =SUM(E7:G7) -> 964426.66 | Q7: =SUM(H7:J7) -> 992853.52 | R7: =SUM(K7:M7) -> 994260.76
A8: Residential one-time revenue | B8: ='Residential Forecast'!B21 -> 7964.5 | C8: ='Residential Forecast'!C21 -> 7965.5 | D8: ='Residential Forecast'!D21 -> 7966.5 | E8: ='Residential Forecast'!E21 -> 7967.5 | F8: ='Residential Forecast'!F21 -> 7968.5 | G8: ='Residential Forecast'!G21 -> 7969.5 | H8: ='Residential Forecast'!H21 -> 7970.5 | I8: ='Residential Forecast'!I21 -> 7971.5 | ... M8: ='Residential Forecast'!M21 -> 7975.5 | N8: =SUM(B8:M8) -> 95640 | O8: =SUM(B8:D8) -> 23896.5 | P8: =SUM(E8:G8) -> 23905.5 | Q8: =SUM(H8:J8) -> 23914.5 | R8: =SUM(K8:M8) -> 23923.5
A9: Residential adjustments | B9: ='Residential Forecast'!B23+'Residential Forecast'!B24 -> -9705.6812 | C9: ='Residential Forecast'!C23+'Residential Forecast'!C24 -> -9710.2488 | D9: ='Residential Forecast'!D23+'Residential Forecast'!D24 -> -9714.8164 | E9: ='Residential Forecast'!E23+'Residential Forecast'!E24 -> -9719.384 | F9: ='Residential Forecast'!F23+'Residential Forecast'!F24 -> -9723.9516 | G9: ='Residential Forecast'!G23+'Residential Forecast'!G24 -> -9728.5192 | H9: ='Residential Forecast'!H23+'Residential Forecast'!H24 -> -10003.549 | I9: ='Residential Forecast'!I23+'Residential Forecast'!I24 -> -10008.25 | ... M9: ='Residential Forecast'!M23+'Residential Forecast'!M24 -> -10027.053 | N9: =SUM(B9:M9) -> -118394.41 | O9: =SUM(B9:D9) -> -29130.746 | P9: =SUM(E9:G9) -> -29171.855 | Q9: =SUM(H9:J9) -> -30024.751 | R9: =SUM(K9:M9) -> -30067.058
A10: Net residential revenue | B10: ='Residential Forecast'!B25 -> 319126.69 | C10: ='Residential Forecast'!C25 -> 319275.04 | D10: ='Residential Forecast'!D25 -> 319423.4 | E10: ='Residential Forecast'!E25 -> 319571.75 | F10: ='Residential Forecast'!F25 -> 319720.1 | G10: ='Residential Forecast'!G25 -> 319868.45 | H10: ='Residential Forecast'!H25 -> 328761.76 | I10: ='Residential Forecast'!I25 -> 328914.42 | ... M10: ='Residential Forecast'!M25 -> 329525.06 | N10: =SUM(B10:M10) -> 3891845.9 | O10: =SUM(B10:D10) -> 957825.13 | P10: =SUM(E10:G10) -> 959160.31 | Q10: =SUM(H10:J10) -> 986743.27 | R10: =SUM(K10:M10) -> 988117.2
A12: BUSINESS
A13: Business recurring revenue | B13: ='Business Forecast'!B25 -> 39749.34 | C13: ='Business Forecast'!C25 -> 40146.04 | D13: ='Business Forecast'!D25 -> 40463.4 | E13: ='Business Forecast'!E25 -> 40780.76 | F13: ='Business Forecast'!F25 -> 41098.12 | G13: ='Business Forecast'!G25 -> 41415.48 | H13: ='Business Forecast'!H25 -> 42908.45 | I13: ='Business Forecast'!I25 -> 43234.75 | ... M13: ='Business Forecast'!M25 -> 44539.95 | N13: =SUM(B13:M13) -> 505998.34 | O13: =SUM(B13:D13) -> 120358.78 | P13: =SUM(E13:G13) -> 123294.36 | Q13: =SUM(H13:J13) -> 129704.25 | R13: =SUM(K13:M13) -> 132640.95
A14: Business one-time revenue | B14: ='Business Forecast'!B32 -> 6250 | C14: ='Business Forecast'!C32 -> 6250 | D14: ='Business Forecast'!D32 -> 6250 | E14: ='Business Forecast'!E32 -> 6250 | F14: ='Business Forecast'!F32 -> 6250 | G14: ='Business Forecast'!G32 -> 6250 | H14: ='Business Forecast'!H32 -> 6250 | I14: ='Business Forecast'!I32 -> 6250 | ... M14: ='Business Forecast'!M32 -> 6250 | N14: =SUM(B14:M14) -> 75000 | O14: =SUM(B14:D14) -> 18750 | P14: =SUM(E14:G14) -> 18750 | Q14: =SUM(H14:J14) -> 18750 | R14: =SUM(K14:M14) -> 18750
A15: Business adjustments | B15: ='Business Forecast'!B34+'Business Forecast'!B35 -> -1056.2335 | C15: ='Business Forecast'!C34+'Business Forecast'!C35 -> -1066.151 | D15: ='Business Forecast'!D34+'Business Forecast'!D35 -> -1074.085 | E15: ='Business Forecast'!E34+'Business Forecast'!E35 -> -1082.019 | F15: ='Business Forecast'!F34+'Business Forecast'!F35 -> -1089.953 | G15: ='Business Forecast'!G34+'Business Forecast'!G35 -> -1097.887 | H15: ='Business Forecast'!H34+'Business Forecast'!H35 -> -1135.2112 | I15: ='Business Forecast'!I34+'Business Forecast'!I35 -> -1143.3688 | ... M15: ='Business Forecast'!M34+'Business Forecast'!M35 -> -1175.9987 | N15: =SUM(B15:M15) -> -13399.959 | O15: =SUM(B15:D15) -> -3196.4695 | P15: =SUM(E15:G15) -> -3269.859 | Q15: =SUM(H15:J15) -> -3430.1062 | R15: =SUM(K15:M15) -> -3503.5237
A16: Net business revenue | B16: ='Business Forecast'!B36 -> 44943.106 | C16: ='Business Forecast'!C36 -> 45329.889 | D16: ='Business Forecast'!D36 -> 45639.315 | E16: ='Business Forecast'!E36 -> 45948.741 | F16: ='Business Forecast'!F36 -> 46258.167 | G16: ='Business Forecast'!G36 -> 46567.593 | H16: ='Business Forecast'!H36 -> 48023.239 | I16: ='Business Forecast'!I36 -> 48341.381 | ... M16: ='Business Forecast'!M36 -> 49613.951 | N16: =SUM(B16:M16) -> 567598.38 | O16: =SUM(B16:D16) -> 135912.31 | P16: =SUM(E16:G16) -> 138774.5 | Q16: =SUM(H16:J16) -> 145024.14 | R16: =SUM(K16:M16) -> 147887.43
A18: DARK FIBER
A19: Dark fiber recurring revenue | B19: ='Dark Fiber Forecast'!Q36 -> 1595 | C19: ='Dark Fiber Forecast'!R36 -> 1595 | D19: ='Dark Fiber Forecast'!S36 -> 1595 | E19: ='Dark Fiber Forecast'!T36 -> 1595 | F19: ='Dark Fiber Forecast'!U36 -> 1595 | G19: ='Dark Fiber Forecast'!V36 -> 1595 | H19: ='Dark Fiber Forecast'!W36 -> 1595 | I19: ='Dark Fiber Forecast'!X36 -> 1595 | ... M19: ='Dark Fiber Forecast'!AB36 -> 1595 | N19: =SUM(B19:M19) -> 19140 | O19: =SUM(B19:D19) -> 4785 | P19: =SUM(E19:G19) -> 4785 | Q19: =SUM(H19:J19) -> 4785 | R19: =SUM(K19:M19) -> 4785
A20: Dark fiber O&M revenue | B20: ='Dark Fiber Forecast'!Q37 -> 0 | C20: ='Dark Fiber Forecast'!R37 -> 0 | D20: ='Dark Fiber Forecast'!S37 -> 0 | E20: ='Dark Fiber Forecast'!T37 -> 0 | F20: ='Dark Fiber Forecast'!U37 -> 0 | G20: ='Dark Fiber Forecast'!V37 -> 0 | H20: ='Dark Fiber Forecast'!W37 -> 0 | I20: ='Dark Fiber Forecast'!X37 -> 0 | ... M20: ='Dark Fiber Forecast'!AB37 -> 0 | N20: =SUM(B20:M20) -> 0 | O20: =SUM(B20:D20) -> 0 | P20: =SUM(E20:G20) -> 0 | Q20: =SUM(H20:J20) -> 0 | R20: =SUM(K20:M20) -> 0
A21: IRU revenue | B21: ='Dark Fiber Forecast'!Q38 -> 0 | C21: ='Dark Fiber Forecast'!R38 -> 0 | D21: ='Dark Fiber Forecast'!S38 -> 0 | E21: ='Dark Fiber Forecast'!T38 -> 0 | F21: ='Dark Fiber Forecast'!U38 -> 0 | G21: ='Dark Fiber Forecast'!V38 -> 0 | H21: ='Dark Fiber Forecast'!W38 -> 0 | I21: ='Dark Fiber Forecast'!X38 -> 0 | ... M21: ='Dark Fiber Forecast'!AB38 -> 0 | N21: =SUM(B21:M21) -> 0 | O21: =SUM(B21:D21) -> 0 | P21: =SUM(E21:G21) -> 0 | Q21: =SUM(H21:J21) -> 0 | R21: =SUM(K21:M21) -> 0
A22: Dark fiber one-time revenue | B22: ='Dark Fiber Forecast'!Q39+'Dark Fiber Forecast'!Q40 -> 0 | C22: ='Dark Fiber Forecast'!R39+'Dark Fiber Forecast'!R40 -> 0 | D22: ='Dark Fiber Forecast'!S39+'Dark Fiber Forecast'!S40 -> 0 | E22: ='Dark Fiber Forecast'!T39+'Dark Fiber Forecast'!T40 -> 0 | F22: ='Dark Fiber Forecast'!U39+'Dark Fiber Forecast'!U40 -> 0 | G22: ='Dark Fiber Forecast'!V39+'Dark Fiber Forecast'!V40 -> 0 | H22: ='Dark Fiber Forecast'!W39+'Dark Fiber Forecast'!W40 -> 0 | I22: ='Dark Fiber Forecast'!X39+'Dark Fiber Forecast'!X40 -> 0 | ... M22: ='Dark Fiber Forecast'!AB39+'Dark Fiber Forecast'!AB40 -> 0 | N22: =SUM(B22:M22) -> 0 | O22: =SUM(B22:D22) -> 0 | P22: =SUM(E22:G22) -> 0 | Q22: =SUM(H22:J22) -> 0 | R22: =SUM(K22:M22) -> 0
A23: Net dark fiber revenue | B23: ='Dark Fiber Forecast'!Q42 -> 1595 | C23: ='Dark Fiber Forecast'!R42 -> 1595 | D23: ='Dark Fiber Forecast'!S42 -> 1595 | E23: ='Dark Fiber Forecast'!T42 -> 1595 | F23: ='Dark Fiber Forecast'!U42 -> 1595 | G23: ='Dark Fiber Forecast'!V42 -> 1595 | H23: ='Dark Fiber Forecast'!W42 -> 1595 | I23: ='Dark Fiber Forecast'!X42 -> 1595 | ... M23: ='Dark Fiber Forecast'!AB42 -> 1595 | N23: =SUM(B23:M23) -> 19140 | O23: =SUM(B23:D23) -> 4785 | P23: =SUM(E23:G23) -> 4785 | Q23: =SUM(H23:J23) -> 4785 | R23: =SUM(K23:M23) -> 4785
A25: PROJECT / OTHER
A26: Hoke County project revenue | B26: =IF(1>='Key Assumptions'!$B$94,'Key Assumptions'!$B$93,0) -> 57000 | C26: =IF(2>='Key Assumptions'!$B$94,'Key Assumptions'!$B$93,0) -> 57000 | D26: =IF(3>='Key Assumptions'!$B$94,'Key Assumptions'!$B$93,0) -> 57000 | E26: =IF(4>='Key Assumptions'!$B$94,'Key Assumptions'!$B$93,0) -> 57000 | F26: =IF(5>='Key Assumptions'!$B$94,'Key Assumptions'!$B$93,0) -> 57000 | G26: =IF(6>='Key Assumptions'!$B$94,'Key Assumptions'!$B$93,0) -> 57000 | H26: =IF(7>='Key Assumptions'!$B$94,'Key Assumptions'!$B$93,0) -> 57000 | I26: =IF(8>='Key Assumptions'!$B$94,'Key Assumptions'!$B$93,0) -> 57000 | J26: =IF(9>='Key Assumptions'!$B$94,'Key Assumptions'!$B$93,0) -> 57000 | K26: =IF(10>='Key Assumptions'!$B$94,'Key Assumptions'!$B$93,0) -> 57000 | L26: =IF(11>='Key Assumptions'!$B$94,'Key Assumptions'!$B$93,0) -> 57000 | M26: =IF(12>='Key Assumptions'!$B$94,'Key Assumptions'!$B$93,0) -> 57000 | N26: =SUM(B26:M26) -> 684000 | O26: =SUM(B26:D26) -> 171000 | P26: =SUM(E26:G26) -> 171000 | Q26: =SUM(H26:J26) -> 171000 | R26: =SUM(K26:M26) -> 171000
A28: CONSOLIDATED
A29: Total recurring revenue | B29: =B7+B13+B19+B20+'Dark Fiber Forecast'!Q41+B26 -> 419212.21 | C29: =C7+C13+C19+C20+'Dark Fiber Forecast'!R41+C26 -> 419760.83 | D29: =D7+D13+D19+D20+'Dark Fiber Forecast'!S41+D26 -> 420230.11 | E29: =E7+E13+E19+E20+'Dark Fiber Forecast'!T41+E26 -> 420699.39 | F29: =F7+F13+F19+F20+'Dark Fiber Forecast'!U41+F26 -> 421168.67 | G29: =G7+G13+G19+G20+'Dark Fiber Forecast'!V41+G26 -> 421637.95 | H29: =H7+H13+H19+H20+'Dark Fiber Forecast'!W41+H26 -> 432298.26 | I29: =I7+I13+I19+I20+'Dark Fiber Forecast'!X41+I26 -> 432780.92 | ... M29: =M7+M13+M19+M20+'Dark Fiber Forecast'!AB41+M26 -> 434711.56 | N29: =SUM(B29:M29) -> 5123738.7 | O29: =SUM(B29:D29) -> 1259203.2 | P29: =SUM(E29:G29) -> 1263506 | Q29: =SUM(H29:J29) -> 1298342.8 | R29: =SUM(K29:M29) -> 1302686.7
A30: Total one-time revenue | B30: =B8+B14+B22 -> 14214.5 | C30: =C8+C14+C22 -> 14215.5 | D30: =D8+D14+D22 -> 14216.5 | E30: =E8+E14+E22 -> 14217.5 | F30: =F8+F14+F22 -> 14218.5 | G30: =G8+G14+G22 -> 14219.5 | H30: =H8+H14+H22 -> 14220.5 | I30: =I8+I14+I22 -> 14221.5 | ... M30: =M8+M14+M22 -> 14225.5 | N30: =SUM(B30:M30) -> 170640 | O30: =SUM(B30:D30) -> 42646.5 | P30: =SUM(E30:G30) -> 42655.5 | Q30: =SUM(H30:J30) -> 42664.5 | R30: =SUM(K30:M30) -> 42673.5
A31: Gross revenue | B31: =B29+B30+B21 -> 433426.71 | C31: =C29+C30+C21 -> 433976.33 | D31: =D29+D30+D21 -> 434446.61 | E31: =E29+E30+E21 -> 434916.89 | F31: =F29+F30+F21 -> 435387.17 | G31: =G29+G30+G21 -> 435857.45 | H31: =H29+H30+H21 -> 446518.76 | I31: =I29+I30+I21 -> 447002.42 | ... M31: =M29+M30+M21 -> 448937.06 | N31: =SUM(B31:M31) -> 5294378.7 | O31: =SUM(B31:D31) -> 1301849.7 | P31: =SUM(E31:G31) -> 1306161.5 | Q31: =SUM(H31:J31) -> 1341007.3 | R31: =SUM(K31:M31) -> 1345360.2
A32: Discounts & adjustments | B32: =B9+B15 -> -10761.915 | C32: =C9+C15 -> -10776.4 | D32: =D9+D15 -> -10788.901 | E32: =E9+E15 -> -10801.403 | F32: =F9+F15 -> -10813.905 | G32: =G9+G15 -> -10826.406 | H32: =H9+H15 -> -11138.761 | I32: =I9+I15 -> -11151.619 | ... M32: =M9+M15 -> -11203.052 | N32: =SUM(B32:M32) -> -131794.37 | O32: =SUM(B32:D32) -> -32327.216 | P32: =SUM(E32:G32) -> -32441.714 | Q32: =SUM(H32:J32) -> -33454.857 | R32: =SUM(K32:M32) -> -33570.582
A33: Total net revenue | B33: =B31+B32 -> 422664.8 | C33: =C31+C32 -> 423199.93 | D33: =D31+D32 -> 423657.71 | E33: =E31+E32 -> 424115.49 | F33: =F31+F32 -> 424573.27 | G33: =G31+G32 -> 425031.05 | H33: =H31+H32 -> 435380 | I33: =I31+I32 -> 435850.8 | ... M33: =M31+M32 -> 437734.01 | N33: =SUM(B33:M33) -> 5162584.3 | O33: =SUM(B33:D33) -> 1269522.4 | P33: =SUM(E33:G33) -> 1273719.8 | Q33: =SUM(H33:J33) -> 1307552.4 | R33: =SUM(K33:M33) -> 1311789.6
A34: Month-over-month growth % | B34: ="—" -> — | C34: =IFERROR(C33/B33-1,0) -> 0.0012660976 | D34: =IFERROR(D33/C33-1,0) -> 0.0010817072 | E34: =IFERROR(E33/D33-1,0) -> 0.0010805383 | F34: =IFERROR(F33/E33-1,0) -> 0.001079372 | G34: =IFERROR(G33/F33-1,0) -> 0.0010782082 | H34: =IFERROR(H33/G33-1,0) -> 0.024348705 | I34: =IFERROR(I33/H33-1,0) -> 0.0010813581 | J34: =IFERROR(J33/I33-1,0) -> 0.00108019 | ... M34: =IFERROR(M33/L33-1,0) -> 0.0010767009
A35: Revenue per day | B35: =B33/DAY(EOMONTH(B3,0)) -> 13634.348 | C35: =C33/DAY(EOMONTH(C3,0)) -> 15114.283 | D35: =D33/DAY(EOMONTH(D3,0)) -> 13666.378 | E35: =E33/DAY(EOMONTH(E3,0)) -> 14137.183 | F35: =F33/DAY(EOMONTH(F3,0)) -> 13695.912 | G35: =G33/DAY(EOMONTH(G3,0)) -> 14167.702 | H35: =H33/DAY(EOMONTH(H3,0)) -> 14044.516 | I35: =I33/DAY(EOMONTH(I3,0)) -> 14059.703 | ... M35: =M33/DAY(EOMONTH(M3,0)) -> 14120.452 | N35: =N33/365 -> 14144.067
A36: Monthly recurring revenue (MRR) | B36: =B29 -> 419212.21 | C36: =C29 -> 419760.83 | D36: =D29 -> 420230.11 | E36: =E29 -> 420699.39 | F36: =F29 -> 421168.67 | G36: =G29 -> 421637.95 | H36: =H29 -> 432298.26 | I36: =I29 -> 432780.92 | ... M36: =M29 -> 434711.56 | N36: =M36 -> 434711.56
A37: Annualized recurring run rate (ARR) | B37: =B36*12 -> 5030546.6 | C37: =C36*12 -> 5037130 | D37: =D36*12 -> 5042761.4 | E37: =E36*12 -> 5048392.7 | F37: =F36*12 -> 5054024.1 | G37: =G36*12 -> 5059655.4 | H37: =H36*12 -> 5187579.2 | I37: =I36*12 -> 5193371.1 | ... M37: =M36*12 -> 5216538.8 | N37: =M37 -> 5216538.8
A38: % revenue — Residential | B38: =IFERROR(B10/B33,0) -> 0.75503494 | C38: =IFERROR(C10/C33,0) -> 0.75443075 | D38: =IFERROR(D10/D33,0) -> 0.75396573 | E38: =IFERROR(E10/E33,0) -> 0.75350172 | F38: =IFERROR(F10/F33,0) -> 0.7530387 | G38: =IFERROR(G10/G33,0) -> 0.75257668 | H38: =IFERROR(H10/H33,0) -> 0.75511453 | I38: =IFERROR(I10/I33,0) -> 0.75464911 | ... N38: =IFERROR(N10/N33,0) -> 0.75385615
A39: % revenue — Business | B39: =IFERROR(B16/B33,0) -> 0.10633274 | C39: =IFERROR(C16/C33,0) -> 0.10711223 | D39: =IFERROR(D16/D33,0) -> 0.10772686 | E39: =IFERROR(E16/E33,0) -> 0.10834016 | F39: =IFERROR(F16/F33,0) -> 0.10895214 | G39: =IFERROR(G16/G33,0) -> 0.1095628 | H39: =IFERROR(H16/H33,0) -> 0.11030189 | I39: =IFERROR(I16/I33,0) -> 0.11091268 | ... N39: =IFERROR(N16/N33,0) -> 0.10994462
A40: % revenue — Dark Fiber | B40: =IFERROR(B23/B33,0) -> 0.003773676 | C40: =IFERROR(C23/C33,0) -> 0.0037689042 | D40: =IFERROR(D23/D33,0) -> 0.0037648317 | E40: =IFERROR(E23/E33,0) -> 0.0037607681 | F40: =IFERROR(F23/F33,0) -> 0.0037567132 | G40: =IFERROR(G23/G33,0) -> 0.003752667 | H40: =IFERROR(H23/H33,0) -> 0.0036634664 | I40: =IFERROR(I23/I33,0) -> 0.0036595091 | ... N40: =IFERROR(N23/N33,0) -> 0.0037074455
A41: % revenue — Project | B41: =IFERROR(B26/B33,0) -> 0.13485864 | C41: =IFERROR(C26/C33,0) -> 0.13468811 | D41: =IFERROR(D26/D33,0) -> 0.13454258 | E41: =IFERROR(E26/E33,0) -> 0.13439735 | F41: =IFERROR(F26/F33,0) -> 0.13425245 | G41: =IFERROR(G26/G33,0) -> 0.13410785 | H41: =IFERROR(H26/H33,0) -> 0.13092011 | I41: =IFERROR(I26/I33,0) -> 0.1307787 | ... N41: =IFERROR(N26/N33,0) -> 0.13249178

Sheet Scenario Analysis
A1: SCENARIO ANALYSIS — 2027 (Conservative / Base / Aggressive)
A2: Three independent projections, each hard-wired to its own multiplier row on Key Assumptions (rows 8-10). Independent of the active-scenario dropdown.
A3: Scenario multipliers are edited on Key Assumptions rows 8-10. Dark fiber scaled by the DF-recurring multiplier (timing effects are modeled in the main Dark Fiber Forecast).
A5: CONSERVATIVE SCENARIO
A6: Metric | B6: 46388 | C6: 46419 | D6: 46447 | E6: 46478 | F6: 46508 | G6: 46539 | H6: 46569 | I6: 46600 | J6: 46631 | K6: 46661 | L6: 46692 | M6: 46722 | N6: FY 2027
A7: Residential beginning subs | B7: ='Key Assumptions'!$B$16 -> 4048 | C7: =B8 -> 4029 | D7: =C8 -> 4010 | E7: =D8 -> 3992 | F7: =E8 -> 3974 | G7: =F8 -> 3956 | H7: =G8 -> 3939 | I7: =H8 -> 3922 | J7: =I8 -> 3905 | ... M7: =L8 -> 3857
A8: Residential ending subs | B8: =MAX(0,B7+ROUND('Key Assumptions'!$B$17*'Key Assumptions'!$B$9,0)+'Key Assumptions'!$B$20-ROUND(B7*'Key Assumptions'!$B$18*'Key Assumptions'!$C$9,0)-'Key Assumptions'!$B$19) -> 4029 | C8: =MAX(0,C7+ROUND('Key Assumptions'!$B$17*'Key Assumptions'!$B$9,0)+'Key Assumptions'!$B$20-ROUND(C7*'Key Assumptions'!$B$18*'Key Assumptions'!$C$9,0)-'Key Assumptions'!$B$19) -> 4010 | D8: =MAX(0,D7+ROUND('Key Assumptions'!$B$17*'Key Assumptions'!$B$9,0)+'Key Assumptions'!$B$20-ROUND(D7*'Key Assumptions'!$B$18*'Key Assumptions'!$C$9,0)-'Key Assumptions'!$B$19) -> 3992 | E8: =MAX(0,E7+ROUND('Key Assumptions'!$B$17*'Key Assumptions'!$B$9,0)+'Key Assumptions'!$B$20-ROUND(E7*'Key Assumptions'!$B$18*'Key Assumptions'!$C$9,0)-'Key Assumptions'!$B$19) -> 3974 | F8: =MAX(0,F7+ROUND('Key Assumptions'!$B$17*'Key Assumptions'!$B$9,0)+'Key Assumptions'!$B$20-ROUND(F7*'Key Assumptions'!$B$18*'Key Assumptions'!$C$9,0)-'Key Assumptions'!$B$19) -> 3956 | G8: =MAX(0,G7+ROUND('Key Assumptions'!$B$17*'Key Assumptions'!$B$9,0)+'Key Assumptions'!$B$20-ROUND(G7*'Key Assumptions'!$B$18*'Key Assumptions'!$C$9,0)-'Key Assumptions'!$B$19) -> 3939 | H8: =MAX(0,H7+ROUND('Key Assumptions'!$B$17*'Key Assumptions'!$B$9,0)+'Key Assumptions'!$B$20-ROUND(H7*'Key Assumptions'!$B$18*'Key Assumptions'!$C$9,0)-'Key Assumptions'!$B$19) -> 3922 | I8: =MAX(0,I7+ROUND('Key Assumptions'!$B$17*'Key Assumptions'!$B$9,0)+'Key Assumptions'!$B$20-ROUND(I7*'Key Assumptions'!$B$18*'Key Assumptions'!$C$9,0)-'Key Assumptions'!$B$19) -> 3905 | ... M8: =MAX(0,M7+ROUND('Key Assumptions'!$B$17*'Key Assumptions'!$B$9,0)+'Key Assumptions'!$B$20-ROUND(M7*'Key Assumptions'!$B$18*'Key Assumptions'!$C$9,0)-'Key Assumptions'!$B$19) -> 3842
A9: Residential avg subs | B9: =(B7+B8)/2 -> 4038.5 | C9: =(C7+C8)/2 -> 4019.5 | D9: =(D7+D8)/2 -> 4001 | E9: =(E7+E8)/2 -> 3983 | F9: =(F7+F8)/2 -> 3965 | G9: =(G7+G8)/2 -> 3947.5 | H9: =(H7+H8)/2 -> 3930.5 | I9: =(I7+I8)/2 -> 3913.5 | ... M9: =(M7+M8)/2 -> 3849.5
A10: Residential net revenue | B10: =(B9*('Key Assumptions'!$B$21*IF(1>='Key Assumptions'!$B$22,1+'Key Assumptions'!$B$23,1)*'Key Assumptions'!$D$9)+B9*'Key Assumptions'!$B$30+'Key Assumptions'!$B$29)*(1-'Key Assumptions'!$B$27)+(ROUND('Key Assumptions'!$B$17*'Key Assumptions'!$B$9,0)*'Key Assumptions'!$B$24+B9*'Key Assumptions'!$B$26*'Key Assumptions'!$B$25)-((B9*('Key Assumptions'!$B$21*IF(1>='Key Assumptions'!$B$22,1+'Key Assumptions'!$B$23,1)*'Key Assumptions'!$D$9)+B9*'Key Assumptions'!$B$30+'Key Assumptions'!$B$29)+(ROUND('Key Assumptions'!$B$17*'Key Assumptions'!$B$9,0)*'Key Assumptions'!$B$24+B9*'Key Assumptions'!$B$26*'Key Assumptions'!$B$25))*'Key Assumptions'!$B$28 -> 308769.25 | C10: =(C9*('Key Assumptions'!$B$21*IF(2>='Key Assumptions'!$B$22,1+'Key Assumptions'!$B$23,1)*'Key Assumptions'!$D$9)+C9*'Key Assumptions'!$B$30+'Key Assumptions'!$B$29)*(1-'Key Assumptions'!$B$27)+(ROUND('Key Assumptions'!$B$17*'Key Assumptions'!$B$9,0)*'Key Assumptions'!$B$24+C9*'Key Assumptions'!$B$26*'Key Assumptions'!$B$25)-((C9*('Key Assumptions'!$B$21*IF(2>='Key Assumptions'!$B$22,1+'Key Assumptions'!$B$23,1)*'Key Assumptions'!$D$9)+C9*'Key Assumptions'!$B$30+'Key Assumptions'!$B$29)+(ROUND('Key Assumptions'!$B$17*'Key Assumptions'!$B$9,0)*'Key Assumptions'!$B$24+C9*'Key Assumptions'!$B$26*'Key Assumptions'!$B$25))*'Key Assumptions'!$B$28 -> 307400.81 | D10: =(D9*('Key Assumptions'!$B$21*IF(3>='Key Assumptions'!$B$22,1+'Key Assumptions'!$B$23,1)*'Key Assumptions'!$D$9)+D9*'Key Assumptions'!$B$30+'Key Assumptions'!$B$29)*(1-'Key Assumptions'!$B$27)+(ROUND('Key Assumptions'!$B$17*'Key Assumptions'!$B$9,0)*'Key Assumptions'!$B$24+D9*'Key Assumptions'!$B$26*'Key Assumptions'!$B$25)-((D9*('Key Assumptions'!$B$21*IF(3>='Key Assumptions'!$B$22,1+'Key Assumptions'!$B$23,1)*'Key Assumptions'!$D$9)+D9*'Key Assumptions'!$B$30+'Key Assumptions'!$B$29)+(ROUND('Key Assumptions'!$B$17*'Key Assumptions'!$B$9,0)*'Key Assumptions'!$B$24+D9*'Key Assumptions'!$B$26*'Key Assumptions'!$B$25))*'Key Assumptions'!$B$28 -> 306068.39 | E10: =(E9*('Key Assumptions'!$B$21*IF(4>='Key Assumptions'!$B$22,1+'Key Assumptions'!$B$23,1)*'Key Assumptions'!$D$9)+E9*'Key Assumptions'!$B$30+'Key Assumptions'!$B$29)*(1-'Key Assumptions'!$B$27)+(ROUND('Key Assumptions'!$B$17*'Key Assumptions'!$B$9,0)*'Key Assumptions'!$B$24+E9*'Key Assumptions'!$B$26*'Key Assumptions'!$B$25)-((E9*('Key Assumptions'!$B$21*IF(4>='Key Assumptions'!$B$22,1+'Key Assumptions'!$B$23,1)*'Key Assumptions'!$D$9)+E9*'Key Assumptions'!$B$30+'Key Assumptions'!$B$29)+(ROUND('Key Assumptions'!$B$17*'Key Assumptions'!$B$9,0)*'Key Assumptions'!$B$24+E9*'Key Assumptions'!$B$26*'Key Assumptions'!$B$25))*'Key Assumptions'!$B$28 -> 304771.98 | F10: =(F9*('Key Assumptions'!$B$21*IF(5>='Key Assumptions'!$B$22,1+'Key Assumptions'!$B$23,1)*'Key Assumptions'!$D$9)+F9*'Key Assumptions'!$B$30+'Key Assumptions'!$B$29)*(1-'Key Assumptions'!$B$27)+(ROUND('Key Assumptions'!$B$17*'Key Assumptions'!$B$9,0)*'Key Assumptions'!$B$24+F9*'Key Assumptions'!$B$26*'Key Assumptions'!$B$25)-((F9*('Key Assumptions'!$B$21*IF(5>='Key Assumptions'!$B$22,1+'Key Assumptions'!$B$23,1)*'Key Assumptions'!$D$9)+F9*'Key Assumptions'!$B$30+'Key Assumptions'!$B$29)+(ROUND('Key Assumptions'!$B$17*'Key Assumptions'!$B$9,0)*'Key Assumptions'!$B$24+F9*'Key Assumptions'!$B$26*'Key Assumptions'!$B$25))*'Key Assumptions'!$B$28 -> 303475.57 | G10: =(G9*('Key Assumptions'!$B$21*IF(6>='Key Assumptions'!$B$22,1+'Key Assumptions'!$B$23,1)*'Key Assumptions'!$D$9)+G9*'Key Assumptions'!$B$30+'Key Assumptions'!$B$29)*(1-'Key Assumptions'!$B$27)+(ROUND('Key Assumptions'!$B$17*'Key Assumptions'!$B$9,0)*'Key Assumptions'!$B$24+G9*'Key Assumptions'!$B$26*'Key Assumptions'!$B$25)-((G9*('Key Assumptions'!$B$21*IF(6>='Key Assumptions'!$B$22,1+'Key Assumptions'!$B$23,1)*'Key Assumptions'!$D$9)+G9*'Key Assumptions'!$B$30+'Key Assumptions'!$B$29)+(ROUND('Key Assumptions'!$B$17*'Key Assumptions'!$B$9,0)*'Key Assumptions'!$B$24+G9*'Key Assumptions'!$B$26*'Key Assumptions'!$B$25))*'Key Assumptions'!$B$28 -> 302215.17 | H10: =(H9*('Key Assumptions'!$B$21*IF(7>='Key Assumptions'!$B$22,1+'Key Assumptions'!$B$23,1)*'Key Assumptions'!$D$9)+H9*'Key Assumptions'!$B$30+'Key Assumptions'!$B$29)*(1-'Key Assumptions'!$B$27)+(ROUND('Key Assumptions'!$B$17*'Key Assumptions'!$B$9,0)*'Key Assumptions'!$B$24+H9*'Key Assumptions'!$B$26*'Key Assumptions'!$B$25)-((H9*('Key Assumptions'!$B$21*IF(7>='Key Assumptions'!$B$22,1+'Key Assumptions'!$B$23,1)*'Key Assumptions'!$D$9)+H9*'Key Assumptions'!$B$30+'Key Assumptions'!$B$29)+(ROUND('Key Assumptions'!$B$17*'Key Assumptions'!$B$9,0)*'Key Assumptions'!$B$24+H9*'Key Assumptions'!$B$26*'Key Assumptions'!$B$25))*'Key Assumptions'!$B$28 -> 309200.8 | I10: =(I9*('Key Assumptions'!$B$21*IF(8>='Key Assumptions'!$B$22,1+'Key Assumptions'!$B$23,1)*'Key Assumptions'!$D$9)+I9*'Key Assumptions'!$B$30+'Key Assumptions'!$B$29)*(1-'Key Assumptions'!$B$27)+(ROUND('Key Assumptions'!$B$17*'Key Assumptions'!$B$9,0)*'Key Assumptions'!$B$24+I9*'Key Assumptions'!$B$26*'Key Assumptions'!$B$25)-((I9*('Key Assumptions'!$B$21*IF(8>='Key Assumptions'!$B$22,1+'Key Assumptions'!$B$23,1)*'Key Assumptions'!$D$9)+I9*'Key Assumptions'!$B$30+'Key Assumptions'!$B$29)+(ROUND('Key Assumptions'!$B$17*'Key Assumptions'!$B$9,0)*'Key Assumptions'!$B$24+I9*'Key Assumptions'!$B$26*'Key Assumptions'!$B$25))*'Key Assumptions'!$B$28 -> 307940.91 | J10: =(J9*('Key Assumptions'!$B$21*IF(9>='Key Assumptions'!$B$22,1+'Key Assumptions'!$B$23,1)*'Key Assumptions'!$D$9)+J9*'Key Assumptions'!$B$30+'Key Assumptions'!$B$29)*(1-'Key Assumptions'!$B$27)+(ROUND('Key Assumptions'!$B$17*'Key Assumptions'!$B$9,0)*'Key Assumptions'!$B$24+J9*'Key Assumptions'!$B$26*'Key Assumptions'!$B$25)-((J9*('Key Assumptions'!$B$21*IF(9>='Key Assumptions'!$B$22,1+'Key Assumptions'!$B$23,1)*'Key Assumptions'!$D$9)+J9*'Key Assumptions'!$B$30+'Key Assumptions'!$B$29)+(ROUND('Key Assumptions'!$B$17*'Key Assumptions'!$B$9,0)*'Key Assumptions'!$B$24+J9*'Key Assumptions'!$B$26*'Key Assumptions'!$B$25))*'Key Assumptions'!$B$28 -> 306718.07 | K10: =(K9*('Key Assumptions'!$B$21*IF(10>='Key Assumptions'!$B$22,1+'Key Assumptions'!$B$23,1)*'Key Assumptions'!$D$9)+K9*'Key Assumptions'!$B$30+'Key Assumptions'!$B$29)*(1-'Key Assumptions'!$B$27)+(ROUND('Key Assumptions'!$B$17*'Key Assumptions'!$B$9,0)*'Key Assumptions'!$B$24+K9*'Key Assumptions'!$B$26*'Key Assumptions'!$B$25)-((K9*('Key Assumptions'!$B$21*IF(10>='Key Assumptions'!$B$22,1+'Key Assumptions'!$B$23,1)*'Key Assumptions'!$D$9)+K9*'Key Assumptions'!$B$30+'Key Assumptions'!$B$29)+(ROUND('Key Assumptions'!$B$17*'Key Assumptions'!$B$9,0)*'Key Assumptions'!$B$24+K9*'Key Assumptions'!$B$26*'Key Assumptions'!$B$25))*'Key Assumptions'!$B$28 -> 305532.28 | L10: =(L9*('Key Assumptions'!$B$21*IF(11>='Key Assumptions'!$B$22,1+'Key Assumptions'!$B$23,1)*'Key Assumptions'!$D$9)+L9*'Key Assumptions'!$B$30+'Key Assumptions'!$B$29)*(1-'Key Assumptions'!$B$27)+(ROUND('Key Assumptions'!$B$17*'Key Assumptions'!$B$9,0)*'Key Assumptions'!$B$24+L9*'Key Assumptions'!$B$26*'Key Assumptions'!$B$25)-((L9*('Key Assumptions'!$B$21*IF(11>='Key Assumptions'!$B$22,1+'Key Assumptions'!$B$23,1)*'Key Assumptions'!$D$9)+L9*'Key Assumptions'!$B$30+'Key Assumptions'!$B$29)+(ROUND('Key Assumptions'!$B$17*'Key Assumptions'!$B$9,0)*'Key Assumptions'!$B$24+L9*'Key Assumptions'!$B$26*'Key Assumptions'!$B$25))*'Key Assumptions'!$B$28 -> 304346.49 | M10: =(M9*('Key Assumptions'!$B$21*IF(12>='Key Assumptions'!$B$22,1+'Key Assumptions'!$B$23,1)*'Key Assumptions'!$D$9)+M9*'Key Assumptions'!$B$30+'Key Assumptions'!$B$29)*(1-'Key Assumptions'!$B$27)+(ROUND('Key Assumptions'!$B$17*'Key Assumptions'!$B$9,0)*'Key Assumptions'!$B$24+M9*'Key Assumptions'!$B$26*'Key Assumptions'!$B$25)-((M9*('Key Assumptions'!$B$21*IF(12>='Key Assumptions'!$B$22,1+'Key Assumptions'!$B$23,1)*'Key Assumptions'!$D$9)+M9*'Key Assumptions'!$B$30+'Key Assumptions'!$B$29)+(ROUND('Key Assumptions'!$B$17*'Key Assumptions'!$B$9,0)*'Key Assumptions'!$B$24+M9*'Key Assumptions'!$B$26*'Key Assumptions'!$B$25))*'Key Assumptions'!$B$28 -> 303197.76 | N10: =SUM(B10:M10) -> 3669637.5
A11: Business beginning cust | B11: ='Key Assumptions'!$B$35 -> 249 | C11: =B12 -> 250 | D11: =C12 -> 251 | E11: =D12 -> 252 | F11: =E12 -> 253 | G11: =F12 -> 254 | H11: =G12 -> 255 | I11: =H12 -> 256 | J11: =I12 -> 257 | ... M11: =L12 -> 260
A12: Business ending cust | B12: =MAX(0,B11+ROUND(('Key Assumptions'!$B$36+'Key Assumptions'!$B$37)*'Key Assumptions'!$E$9,0)+'Key Assumptions'!$B$40-ROUND(B11*'Key Assumptions'!$B$38*'Key Assumptions'!$F$9,0)-'Key Assumptions'!$B$39) -> 250 | C12: =MAX(0,C11+ROUND(('Key Assumptions'!$B$36+'Key Assumptions'!$B$37)*'Key Assumptions'!$E$9,0)+'Key Assumptions'!$B$40-ROUND(C11*'Key Assumptions'!$B$38*'Key Assumptions'!$F$9,0)-'Key Assumptions'!$B$39) -> 251 | D12: =MAX(0,D11+ROUND(('Key Assumptions'!$B$36+'Key Assumptions'!$B$37)*'Key Assumptions'!$E$9,0)+'Key Assumptions'!$B$40-ROUND(D11*'Key Assumptions'!$B$38*'Key Assumptions'!$F$9,0)-'Key Assumptions'!$B$39) -> 252 | E12: =MAX(0,E11+ROUND(('Key Assumptions'!$B$36+'Key Assumptions'!$B$37)*'Key Assumptions'!$E$9,0)+'Key Assumptions'!$B$40-ROUND(E11*'Key Assumptions'!$B$38*'Key Assumptions'!$F$9,0)-'Key Assumptions'!$B$39) -> 253 | F12: =MAX(0,F11+ROUND(('Key Assumptions'!$B$36+'Key Assumptions'!$B$37)*'Key Assumptions'!$E$9,0)+'Key Assumptions'!$B$40-ROUND(F11*'Key Assumptions'!$B$38*'Key Assumptions'!$F$9,0)-'Key Assumptions'!$B$39) -> 254 | G12: =MAX(0,G11+ROUND(('Key Assumptions'!$B$36+'Key Assumptions'!$B$37)*'Key Assumptions'!$E$9,0)+'Key Assumptions'!$B$40-ROUND(G11*'Key Assumptions'!$B$38*'Key Assumptions'!$F$9,0)-'Key Assumptions'!$B$39) -> 255 | H12: =MAX(0,H11+ROUND(('Key Assumptions'!$B$36+'Key Assumptions'!$B$37)*'Key Assumptions'!$E$9,0)+'Key Assumptions'!$B$40-ROUND(H11*'Key Assumptions'!$B$38*'Key Assumptions'!$F$9,0)-'Key Assumptions'!$B$39) -> 256 | I12: =MAX(0,I11+ROUND(('Key Assumptions'!$B$36+'Key Assumptions'!$B$37)*'Key Assumptions'!$E$9,0)+'Key Assumptions'!$B$40-ROUND(I11*'Key Assumptions'!$B$38*'Key Assumptions'!$F$9,0)-'Key Assumptions'!$B$39) -> 257 | ... M12: =MAX(0,M11+ROUND(('Key Assumptions'!$B$36+'Key Assumptions'!$B$37)*'Key Assumptions'!$E$9,0)+'Key Assumptions'!$B$40-ROUND(M11*'Key Assumptions'!$B$38*'Key Assumptions'!$F$9,0)-'Key Assumptions'!$B$39) -> 261
A13: Business avg cust | B13: =(B11+B12)/2 -> 249.5 | C13: =(C11+C12)/2 -> 250.5 | D13: =(D11+D12)/2 -> 251.5 | E13: =(E11+E12)/2 -> 252.5 | F13: =(F11+F12)/2 -> 253.5 | G13: =(G11+G12)/2 -> 254.5 | H13: =(H11+H12)/2 -> 255.5 | I13: =(I11+I12)/2 -> 256.5 | ... M13: =(M11+M12)/2 -> 260.5
A14: Enterprise beginning | B14: ='Key Assumptions'!$B$57 -> 0 | C14: =B15 -> 1 | D14: =C15 -> 2 | E14: =D15 -> 3 | F14: =E15 -> 4 | G14: =F15 -> 5 | H14: =G15 -> 6 | I14: =H15 -> 7 | J14: =I15 -> 8 | ... M14: =L15 -> 11
A15: Enterprise ending | B15: =MAX(0,B14+ROUND('Key Assumptions'!$B$37*'Key Assumptions'!$E$9,0)-ROUND(B14*'Key Assumptions'!$B$38*'Key Assumptions'!$F$9,0)) -> 1 | C15: =MAX(0,C14+ROUND('Key Assumptions'!$B$37*'Key Assumptions'!$E$9,0)-ROUND(C14*'Key Assumptions'!$B$38*'Key Assumptions'!$F$9,0)) -> 2 | D15: =MAX(0,D14+ROUND('Key Assumptions'!$B$37*'Key Assumptions'!$E$9,0)-ROUND(D14*'Key Assumptions'!$B$38*'Key Assumptions'!$F$9,0)) -> 3 | E15: =MAX(0,E14+ROUND('Key Assumptions'!$B$37*'Key Assumptions'!$E$9,0)-ROUND(E14*'Key Assumptions'!$B$38*'Key Assumptions'!$F$9,0)) -> 4 | F15: =MAX(0,F14+ROUND('Key Assumptions'!$B$37*'Key Assumptions'!$E$9,0)-ROUND(F14*'Key Assumptions'!$B$38*'Key Assumptions'!$F$9,0)) -> 5 | G15: =MAX(0,G14+ROUND('Key Assumptions'!$B$37*'Key Assumptions'!$E$9,0)-ROUND(G14*'Key Assumptions'!$B$38*'Key Assumptions'!$F$9,0)) -> 6 | H15: =MAX(0,H14+ROUND('Key Assumptions'!$B$37*'Key Assumptions'!$E$9,0)-ROUND(H14*'Key Assumptions'!$B$38*'Key Assumptions'!$F$9,0)) -> 7 | I15: =MAX(0,I14+ROUND('Key Assumptions'!$B$37*'Key Assumptions'!$E$9,0)-ROUND(I14*'Key Assumptions'!$B$38*'Key Assumptions'!$F$9,0)) -> 8 | ... M15: =MAX(0,M14+ROUND('Key Assumptions'!$B$37*'Key Assumptions'!$E$9,0)-ROUND(M14*'Key Assumptions'!$B$38*'Key Assumptions'!$F$9,0)) -> 12
A16: Enterprise avg | B16: =(B14+B15)/2 -> 0.5 | C16: =(C14+C15)/2 -> 1.5 | D16: =(D14+D15)/2 -> 2.5 | E16: =(E14+E15)/2 -> 3.5 | F16: =(F14+F15)/2 -> 4.5 | G16: =(G14+G15)/2 -> 5.5 | H16: =(H14+H15)/2 -> 6.5 | I16: =(I14+I15)/2 -> 7.5 | ... M16: =(M14+M15)/2 -> 11.5
A17: Business net revenue | B17: =(B13*('Key Assumptions'!$B$41*IF(1>='Key Assumptions'!$B$42,1+'Key Assumptions'!$B$43,1)*'Key Assumptions'!$G$9)+B13*('Key Assumptions'!$B$45+'Key Assumptions'!$B$46+'Key Assumptions'!$B$47+'Key Assumptions'!$B$49)+B16*'Key Assumptions'!$B$48)*(1-'Key Assumptions'!$B$54)+(ROUND(('Key Assumptions'!$B$36+'Key Assumptions'!$B$37)*'Key Assumptions'!$E$9,0)*('Key Assumptions'!$B$44+'Key Assumptions'!$B$50+'Key Assumptions'!$B$51)+'Key Assumptions'!$B$52+'Key Assumptions'!$B$53)-((B13*('Key Assumptions'!$B$41*IF(1>='Key Assumptions'!$B$42,1+'Key Assumptions'!$B$43,1)*'Key Assumptions'!$G$9)+B13*('Key Assumptions'!$B$45+'Key Assumptions'!$B$46+'Key Assumptions'!$B$47+'Key Assumptions'!$B$49)+B16*'Key Assumptions'!$B$48)+(ROUND(('Key Assumptions'!$B$36+'Key Assumptions'!$B$37)*'Key Assumptions'!$E$9,0)*('Key Assumptions'!$B$44+'Key Assumptions'!$B$50+'Key Assumptions'!$B$51)+'Key Assumptions'!$B$52+'Key Assumptions'!$B$53))*'Key Assumptions'!$B$55 -> 42859.51 | C17: =(C13*('Key Assumptions'!$B$41*IF(2>='Key Assumptions'!$B$42,1+'Key Assumptions'!$B$43,1)*'Key Assumptions'!$G$9)+C13*('Key Assumptions'!$B$45+'Key Assumptions'!$B$46+'Key Assumptions'!$B$47+'Key Assumptions'!$B$49)+C16*'Key Assumptions'!$B$48)*(1-'Key Assumptions'!$B$54)+(ROUND(('Key Assumptions'!$B$36+'Key Assumptions'!$B$37)*'Key Assumptions'!$E$9,0)*('Key Assumptions'!$B$44+'Key Assumptions'!$B$50+'Key Assumptions'!$B$51)+'Key Assumptions'!$B$52+'Key Assumptions'!$B$53)-((C13*('Key Assumptions'!$B$41*IF(2>='Key Assumptions'!$B$42,1+'Key Assumptions'!$B$43,1)*'Key Assumptions'!$G$9)+C13*('Key Assumptions'!$B$45+'Key Assumptions'!$B$46+'Key Assumptions'!$B$47+'Key Assumptions'!$B$49)+C16*'Key Assumptions'!$B$48)+(ROUND(('Key Assumptions'!$B$36+'Key Assumptions'!$B$37)*'Key Assumptions'!$E$9,0)*('Key Assumptions'!$B$44+'Key Assumptions'!$B$50+'Key Assumptions'!$B$51)+'Key Assumptions'!$B$52+'Key Assumptions'!$B$53))*'Key Assumptions'!$B$55 -> 43009.865 | D17: =(D13*('Key Assumptions'!$B$41*IF(3>='Key Assumptions'!$B$42,1+'Key Assumptions'!$B$43,1)*'Key Assumptions'!$G$9)+D13*('Key Assumptions'!$B$45+'Key Assumptions'!$B$46+'Key Assumptions'!$B$47+'Key Assumptions'!$B$49)+D16*'Key Assumptions'!$B$48)*(1-'Key Assumptions'!$B$54)+(ROUND(('Key Assumptions'!$B$36+'Key Assumptions'!$B$37)*'Key Assumptions'!$E$9,0)*('Key Assumptions'!$B$44+'Key Assumptions'!$B$50+'Key Assumptions'!$B$51)+'Key Assumptions'!$B$52+'Key Assumptions'!$B$53)-((D13*('Key Assumptions'!$B$41*IF(3>='Key Assumptions'!$B$42,1+'Key Assumptions'!$B$43,1)*'Key Assumptions'!$G$9)+D13*('Key Assumptions'!$B$45+'Key Assumptions'!$B$46+'Key Assumptions'!$B$47+'Key Assumptions'!$B$49)+D16*'Key Assumptions'!$B$48)+(ROUND(('Key Assumptions'!$B$36+'Key Assumptions'!$B$37)*'Key Assumptions'!$E$9,0)*('Key Assumptions'!$B$44+'Key Assumptions'!$B$50+'Key Assumptions'!$B$51)+'Key Assumptions'!$B$52+'Key Assumptions'!$B$53))*'Key Assumptions'!$B$55 -> 43160.22 | E17: =(E13*('Key Assumptions'!$B$41*IF(4>='Key Assumptions'!$B$42,1+'Key Assumptions'!$B$43,1)*'Key Assumptions'!$G$9)+E13*('Key Assumptions'!$B$45+'Key Assumptions'!$B$46+'Key Assumptions'!$B$47+'Key Assumptions'!$B$49)+E16*'Key Assumptions'!$B$48)*(1-'Key Assumptions'!$B$54)+(ROUND(('Key Assumptions'!$B$36+'Key Assumptions'!$B$37)*'Key Assumptions'!$E$9,0)*('Key Assumptions'!$B$44+'Key Assumptions'!$B$50+'Key Assumptions'!$B$51)+'Key Assumptions'!$B$52+'Key Assumptions'!$B$53)-((E13*('Key Assumptions'!$B$41*IF(4>='Key Assumptions'!$B$42,1+'Key Assumptions'!$B$43,1)*'Key Assumptions'!$G$9)+E13*('Key Assumptions'!$B$45+'Key Assumptions'!$B$46+'Key Assumptions'!$B$47+'Key Assumptions'!$B$49)+E16*'Key Assumptions'!$B$48)+(ROUND(('Key Assumptions'!$B$36+'Key Assumptions'!$B$37)*'Key Assumptions'!$E$9,0)*('Key Assumptions'!$B$44+'Key Assumptions'!$B$50+'Key Assumptions'!$B$51)+'Key Assumptions'!$B$52+'Key Assumptions'!$B$53))*'Key Assumptions'!$B$55 -> 43310.574 | F17: =(F13*('Key Assumptions'!$B$41*IF(5>='Key Assumptions'!$B$42,1+'Key Assumptions'!$B$43,1)*'Key Assumptions'!$G$9)+F13*('Key Assumptions'!$B$45+'Key Assumptions'!$B$46+'Key Assumptions'!$B$47+'Key Assumptions'!$B$49)+F16*'Key Assumptions'!$B$48)*(1-'Key Assumptions'!$B$54)+(ROUND(('Key Assumptions'!$B$36+'Key Assumptions'!$B$37)*'Key Assumptions'!$E$9,0)*('Key Assumptions'!$B$44+'Key Assumptions'!$B$50+'Key Assumptions'!$B$51)+'Key Assumptions'!$B$52+'Key Assumptions'!$B$53)-((F13*('Key Assumptions'!$B$41*IF(5>='Key Assumptions'!$B$42,1+'Key Assumptions'!$B$43,1)*'Key Assumptions'!$G$9)+F13*('Key Assumptions'!$B$45+'Key Assumptions'!$B$46+'Key Assumptions'!$B$47+'Key Assumptions'!$B$49)+F16*'Key Assumptions'!$B$48)+(ROUND(('Key Assumptions'!$B$36+'Key Assumptions'!$B$37)*'Key Assumptions'!$E$9,0)*('Key Assumptions'!$B$44+'Key Assumptions'!$B$50+'Key Assumptions'!$B$51)+'Key Assumptions'!$B$52+'Key Assumptions'!$B$53))*'Key Assumptions'!$B$55 -> 43460.929 | G17: =(G13*('Key Assumptions'!$B$41*IF(6>='Key Assumptions'!$B$42,1+'Key Assumptions'!$B$43,1)*'Key Assumptions'!$G$9)+G13*('Key Assumptions'!$B$45+'Key Assumptions'!$B$46+'Key Assumptions'!$B$47+'Key Assumptions'!$B$49)+G16*'Key Assumptions'!$B$48)*(1-'Key Assumptions'!$B$54)+(ROUND(('Key Assumptions'!$B$36+'Key Assumptions'!$B$37)*'Key Assumptions'!$E$9,0)*('Key Assumptions'!$B$44+'Key Assumptions'!$B$50+'Key Assumptions'!$B$51)+'Key Assumptions'!$B$52+'Key Assumptions'!$B$53)-((G13*('Key Assumptions'!$B$41*IF(6>='Key Assumptions'!$B$42,1+'Key Assumptions'!$B$43,1)*'Key Assumptions'!$G$9)+G13*('Key Assumptions'!$B$45+'Key Assumptions'!$B$46+'Key Assumptions'!$B$47+'Key Assumptions'!$B$49)+G16*'Key Assumptions'!$B$48)+(ROUND(('Key Assumptions'!$B$36+'Key Assumptions'!$B$37)*'Key Assumptions'!$E$9,0)*('Key Assumptions'!$B$44+'Key Assumptions'!$B$50+'Key Assumptions'!$B$51)+'Key Assumptions'!$B$52+'Key Assumptions'!$B$53))*'Key Assumptions'!$B$55 -> 43611.284 | H17: =(H13*('Key Assumptions'!$B$41*IF(7>='Key Assumptions'!$B$42,1+'Key Assumptions'!$B$43,1)*'Key Assumptions'!$G$9)+H13*('Key Assumptions'!$B$45+'Key Assumptions'!$B$46+'Key Assumptions'!$B$47+'Key Assumptions'!$B$49)+H16*'Key Assumptions'!$B$48)*(1-'Key Assumptions'!$B$54)+(ROUND(('Key Assumptions'!$B$36+'Key Assumptions'!$B$37)*'Key Assumptions'!$E$9,0)*('Key Assumptions'!$B$44+'Key Assumptions'!$B$50+'Key Assumptions'!$B$51)+'Key Assumptions'!$B$52+'Key Assumptions'!$B$53)-((H13*('Key Assumptions'!$B$41*IF(7>='Key Assumptions'!$B$42,1+'Key Assumptions'!$B$43,1)*'Key Assumptions'!$G$9)+H13*('Key Assumptions'!$B$45+'Key Assumptions'!$B$46+'Key Assumptions'!$B$47+'Key Assumptions'!$B$49)+H16*'Key Assumptions'!$B$48)+(ROUND(('Key Assumptions'!$B$36+'Key Assumptions'!$B$37)*'Key Assumptions'!$E$9,0)*('Key Assumptions'!$B$44+'Key Assumptions'!$B$50+'Key Assumptions'!$B$51)+'Key Assumptions'!$B$52+'Key Assumptions'!$B$53))*'Key Assumptions'!$B$55 -> 44841.766 | I17: =(I13*('Key Assumptions'!$B$41*IF(8>='Key Assumptions'!$B$42,1+'Key Assumptions'!$B$43,1)*'Key Assumptions'!$G$9)+I13*('Key Assumptions'!$B$45+'Key Assumptions'!$B$46+'Key Assumptions'!$B$47+'Key Assumptions'!$B$49)+I16*'Key Assumptions'!$B$48)*(1-'Key Assumptions'!$B$54)+(ROUND(('Key Assumptions'!$B$36+'Key Assumptions'!$B$37)*'Key Assumptions'!$E$9,0)*('Key Assumptions'!$B$44+'Key Assumptions'!$B$50+'Key Assumptions'!$B$51)+'Key Assumptions'!$B$52+'Key Assumptions'!$B$53)-((I13*('Key Assumptions'!$B$41*IF(8>='Key Assumptions'!$B$42,1+'Key Assumptions'!$B$43,1)*'Key Assumptions'!$G$9)+I13*('Key Assumptions'!$B$45+'Key Assumptions'!$B$46+'Key Assumptions'!$B$47+'Key Assumptions'!$B$49)+I16*'Key Assumptions'!$B$48)+(ROUND(('Key Assumptions'!$B$36+'Key Assumptions'!$B$37)*'Key Assumptions'!$E$9,0)*('Key Assumptions'!$B$44+'Key Assumptions'!$B$50+'Key Assumptions'!$B$51)+'Key Assumptions'!$B$52+'Key Assumptions'!$B$53))*'Key Assumptions'!$B$55 -> 44996.348 | J17: =(J13*('Key Assumptions'!$B$41*IF(9>='Key Assumptions'!$B$42,1+'Key Assumptions'!$B$43,1)*'Key Assumptions'!$G$9)+J13*('Key Assumptions'!$B$45+'Key Assumptions'!$B$46+'Key Assumptions'!$B$47+'Key Assumptions'!$B$49)+J16*'Key Assumptions'!$B$48)*(1-'Key Assumptions'!$B$54)+(ROUND(('Key Assumptions'!$B$36+'Key Assumptions'!$B$37)*'Key Assumptions'!$E$9,0)*('Key Assumptions'!$B$44+'Key Assumptions'!$B$50+'Key Assumptions'!$B$51)+'Key Assumptions'!$B$52+'Key Assumptions'!$B$53)-((J13*('Key Assumptions'!$B$41*IF(9>='Key Assumptions'!$B$42,1+'Key Assumptions'!$B$43,1)*'Key Assumptions'!$G$9)+J13*('Key Assumptions'!$B$45+'Key Assumptions'!$B$46+'Key Assumptions'!$B$47+'Key Assumptions'!$B$49)+J16*'Key Assumptions'!$B$48)+(ROUND(('Key Assumptions'!$B$36+'Key Assumptions'!$B$37)*'Key Assumptions'!$E$9,0)*('Key Assumptions'!$B$44+'Key Assumptions'!$B$50+'Key Assumptions'!$B$51)+'Key Assumptions'!$B$52+'Key Assumptions'!$B$53))*'Key Assumptions'!$B$55 -> 45150.93 | K17: =(K13*('Key Assumptions'!$B$41*IF(10>='Key Assumptions'!$B$42,1+'Key Assumptions'!$B$43,1)*'Key Assumptions'!$G$9)+K13*('Key Assumptions'!$B$45+'Key Assumptions'!$B$46+'Key Assumptions'!$B$47+'Key Assumptions'!$B$49)+K16*'Key Assumptions'!$B$48)*(1-'Key Assumptions'!$B$54)+(ROUND(('Key Assumptions'!$B$36+'Key Assumptions'!$B$37)*'Key Assumptions'!$E$9,0)*('Key Assumptions'!$B$44+'Key Assumptions'!$B$50+'Key Assumptions'!$B$51)+'Key Assumptions'!$B$52+'Key Assumptions'!$B$53)-((K13*('Key Assumptions'!$B$41*IF(10>='Key Assumptions'!$B$42,1+'Key Assumptions'!$B$43,1)*'Key Assumptions'!$G$9)+K13*('Key Assumptions'!$B$45+'Key Assumptions'!$B$46+'Key Assumptions'!$B$47+'Key Assumptions'!$B$49)+K16*'Key Assumptions'!$B$48)+(ROUND(('Key Assumptions'!$B$36+'Key Assumptions'!$B$37)*'Key Assumptions'!$E$9,0)*('Key Assumptions'!$B$44+'Key Assumptions'!$B$50+'Key Assumptions'!$B$51)+'Key Assumptions'!$B$52+'Key Assumptions'!$B$53))*'Key Assumptions'!$B$55 -> 45305.512 | L17: =(L13*('Key Assumptions'!$B$41*IF(11>='Key Assumptions'!$B$42,1+'Key Assumptions'!$B$43,1)*'Key Assumptions'!$G$9)+L13*('Key Assumptions'!$B$45+'Key Assumptions'!$B$46+'Key Assumptions'!$B$47+'Key Assumptions'!$B$49)+L16*'Key Assumptions'!$B$48)*(1-'Key Assumptions'!$B$54)+(ROUND(('Key Assumptions'!$B$36+'Key Assumptions'!$B$37)*'Key Assumptions'!$E$9,0)*('Key Assumptions'!$B$44+'Key Assumptions'!$B$50+'Key Assumptions'!$B$51)+'Key Assumptions'!$B$52+'Key Assumptions'!$B$53)-((L13*('Key Assumptions'!$B$41*IF(11>='Key Assumptions'!$B$42,1+'Key Assumptions'!$B$43,1)*'Key Assumptions'!$G$9)+L13*('Key Assumptions'!$B$45+'Key Assumptions'!$B$46+'Key Assumptions'!$B$47+'Key Assumptions'!$B$49)+L16*'Key Assumptions'!$B$48)+(ROUND(('Key Assumptions'!$B$36+'Key Assumptions'!$B$37)*'Key Assumptions'!$E$9,0)*('Key Assumptions'!$B$44+'Key Assumptions'!$B$50+'Key Assumptions'!$B$51)+'Key Assumptions'!$B$52+'Key Assumptions'!$B$53))*'Key Assumptions'!$B$55 -> 45460.095 | M17: =(M13*('Key Assumptions'!$B$41*IF(12>='Key Assumptions'!$B$42,1+'Key Assumptions'!$B$43,1)*'Key Assumptions'!$G$9)+M13*('Key Assumptions'!$B$45+'Key Assumptions'!$B$46+'Key Assumptions'!$B$47+'Key Assumptions'!$B$49)+M16*'Key Assumptions'!$B$48)*(1-'Key Assumptions'!$B$54)+(ROUND(('Key Assumptions'!$B$36+'Key Assumptions'!$B$37)*'Key Assumptions'!$E$9,0)*('Key Assumptions'!$B$44+'Key Assumptions'!$B$50+'Key Assumptions'!$B$51)+'Key Assumptions'!$B$52+'Key Assumptions'!$B$53)-((M13*('Key Assumptions'!$B$41*IF(12>='Key Assumptions'!$B$42,1+'Key Assumptions'!$B$43,1)*'Key Assumptions'!$G$9)+M13*('Key Assumptions'!$B$45+'Key Assumptions'!$B$46+'Key Assumptions'!$B$47+'Key Assumptions'!$B$49)+M16*'Key Assumptions'!$B$48)+(ROUND(('Key Assumptions'!$B$36+'Key Assumptions'!$B$37)*'Key Assumptions'!$E$9,0)*('Key Assumptions'!$B$44+'Key Assumptions'!$B$50+'Key Assumptions'!$B$51)+'Key Assumptions'!$B$52+'Key Assumptions'!$B$53))*'Key Assumptions'!$B$55 -> 45614.677 | N17: =SUM(B17:M17) -> 530781.71
A18: Dark fiber net revenue | B18: ='Dark Fiber Forecast'!Q43*'Key Assumptions'!$H$9 -> 1435.5 | C18: ='Dark Fiber Forecast'!R43*'Key Assumptions'!$H$9 -> 1435.5 | D18: ='Dark Fiber Forecast'!S43*'Key Assumptions'!$H$9 -> 1435.5 | E18: ='Dark Fiber Forecast'!T43*'Key Assumptions'!$H$9 -> 1435.5 | F18: ='Dark Fiber Forecast'!U43*'Key Assumptions'!$H$9 -> 1435.5 | G18: ='Dark Fiber Forecast'!V43*'Key Assumptions'!$H$9 -> 1435.5 | H18: ='Dark Fiber Forecast'!W43*'Key Assumptions'!$H$9 -> 1435.5 | I18: ='Dark Fiber Forecast'!X43*'Key Assumptions'!$H$9 -> 1435.5 | ... M18: ='Dark Fiber Forecast'!AB43*'Key Assumptions'!$H$9 -> 1435.5 | N18: =SUM(B18:M18) -> 17226
A19: TOTAL NET REVENUE | B19: =B10+B17+B18+IF(1>='Key Assumptions'!$B$94,'Key Assumptions'!$B$93,0) -> 410064.26 | C19: =C10+C17+C18+IF(2>='Key Assumptions'!$B$94,'Key Assumptions'!$B$93,0) -> 408846.18 | D19: =D10+D17+D18+IF(3>='Key Assumptions'!$B$94,'Key Assumptions'!$B$93,0) -> 407664.11 | E19: =E10+E17+E18+IF(4>='Key Assumptions'!$B$94,'Key Assumptions'!$B$93,0) -> 406518.06 | F19: =F10+F17+F18+IF(5>='Key Assumptions'!$B$94,'Key Assumptions'!$B$93,0) -> 405372 | G19: =G10+G17+G18+IF(6>='Key Assumptions'!$B$94,'Key Assumptions'!$B$93,0) -> 404261.96 | H19: =H10+H17+H18+IF(7>='Key Assumptions'!$B$94,'Key Assumptions'!$B$93,0) -> 412478.07 | I19: =I10+I17+I18+IF(8>='Key Assumptions'!$B$94,'Key Assumptions'!$B$93,0) -> 411372.75 | J19: =J10+J17+J18+IF(9>='Key Assumptions'!$B$94,'Key Assumptions'!$B$93,0) -> 410304.5 | K19: =K10+K17+K18+IF(10>='Key Assumptions'!$B$94,'Key Assumptions'!$B$93,0) -> 409273.29 | L19: =L10+L17+L18+IF(11>='Key Assumptions'!$B$94,'Key Assumptions'!$B$93,0) -> 408242.09 | M19: =M10+M17+M18+IF(12>='Key Assumptions'!$B$94,'Key Assumptions'!$B$93,0) -> 407247.94 | N19: =SUM(B19:M19) -> 4901645.2
A21: BASE SCENARIO
A22: Metric | B22: 46388 | C22: 46419 | D22: 46447 | E22: 46478 | F22: 46508 | G22: 46539 | H22: 46569 | I22: 46600 | J22: 46631 | K22: 46661 | L22: 46692 | M22: 46722 | N22: FY 2027
A23: Residential beginning subs | B23: ='Key Assumptions'!$B$16 -> 4048 | C23: =B24 -> 4050 | D23: =C24 -> 4052 | E23: =D24 -> 4054 | F23: =E24 -> 4056 | G23: =F24 -> 4058 | H23: =G24 -> 4060 | I23: =H24 -> 4062 | J23: =I24 -> 4064 | ... M23: =L24 -> 4070
A24: Residential ending subs | B24: =MAX(0,B23+ROUND('Key Assumptions'!$B$17*'Key Assumptions'!$B$8,0)+'Key Assumptions'!$B$20-ROUND(B23*'Key Assumptions'!$B$18*'Key Assumptions'!$C$8,0)-'Key Assumptions'!$B$19) -> 4050 | C24: =MAX(0,C23+ROUND('Key Assumptions'!$B$17*'Key Assumptions'!$B$8,0)+'Key Assumptions'!$B$20-ROUND(C23*'Key Assumptions'!$B$18*'Key Assumptions'!$C$8,0)-'Key Assumptions'!$B$19) -> 4052 | D24: =MAX(0,D23+ROUND('Key Assumptions'!$B$17*'Key Assumptions'!$B$8,0)+'Key Assumptions'!$B$20-ROUND(D23*'Key Assumptions'!$B$18*'Key Assumptions'!$C$8,0)-'Key Assumptions'!$B$19) -> 4054 | E24: =MAX(0,E23+ROUND('Key Assumptions'!$B$17*'Key Assumptions'!$B$8,0)+'Key Assumptions'!$B$20-ROUND(E23*'Key Assumptions'!$B$18*'Key Assumptions'!$C$8,0)-'Key Assumptions'!$B$19) -> 4056 | F24: =MAX(0,F23+ROUND('Key Assumptions'!$B$17*'Key Assumptions'!$B$8,0)+'Key Assumptions'!$B$20-ROUND(F23*'Key Assumptions'!$B$18*'Key Assumptions'!$C$8,0)-'Key Assumptions'!$B$19) -> 4058 | G24: =MAX(0,G23+ROUND('Key Assumptions'!$B$17*'Key Assumptions'!$B$8,0)+'Key Assumptions'!$B$20-ROUND(G23*'Key Assumptions'!$B$18*'Key Assumptions'!$C$8,0)-'Key Assumptions'!$B$19) -> 4060 | H24: =MAX(0,H23+ROUND('Key Assumptions'!$B$17*'Key Assumptions'!$B$8,0)+'Key Assumptions'!$B$20-ROUND(H23*'Key Assumptions'!$B$18*'Key Assumptions'!$C$8,0)-'Key Assumptions'!$B$19) -> 4062 | I24: =MAX(0,I23+ROUND('Key Assumptions'!$B$17*'Key Assumptions'!$B$8,0)+'Key Assumptions'!$B$20-ROUND(I23*'Key Assumptions'!$B$18*'Key Assumptions'!$C$8,0)-'Key Assumptions'!$B$19) -> 4064 | ... M24: =MAX(0,M23+ROUND('Key Assumptions'!$B$17*'Key Assumptions'!$B$8,0)+'Key Assumptions'!$B$20-ROUND(M23*'Key Assumptions'!$B$18*'Key Assumptions'!$C$8,0)-'Key Assumptions'!$B$19) -> 4072
A25: Residential avg subs | B25: =(B23+B24)/2 -> 4049 | C25: =(C23+C24)/2 -> 4051 | D25: =(D23+D24)/2 -> 4053 | E25: =(E23+E24)/2 -> 4055 | F25: =(F23+F24)/2 -> 4057 | G25: =(G23+G24)/2 -> 4059 | H25: =(H23+H24)/2 -> 4061 | I25: =(I23+I24)/2 -> 4063 | ... M25: =(M23+M24)/2 -> 4071
A26: Residential net revenue | B26: =(B25*('Key Assumptions'!$B$21*IF(1>='Key Assumptions'!$B$22,1+'Key Assumptions'!$B$23,1)*'Key Assumptions'!$D$8)+B25*'Key Assumptions'!$B$30+'Key Assumptions'!$B$29)*(1-'Key Assumptions'!$B$27)+(ROUND('Key Assumptions'!$B$17*'Key Assumptions'!$B$8,0)*'Key Assumptions'!$B$24+B25*'Key Assumptions'!$B$26*'Key Assumptions'!$B$25)-((B25*('Key Assumptions'!$B$21*IF(1>='Key Assumptions'!$B$22,1+'Key Assumptions'!$B$23,1)*'Key Assumptions'!$D$8)+B25*'Key Assumptions'!$B$30+'Key Assumptions'!$B$29)+(ROUND('Key Assumptions'!$B$17*'Key Assumptions'!$B$8,0)*'Key Assumptions'!$B$24+B25*'Key Assumptions'!$B$26*'Key Assumptions'!$B$25))*'Key Assumptions'!$B$28 -> 319126.69 | C26: =(C25*('Key Assumptions'!$B$21*IF(2>='Key Assumptions'!$B$22,1+'Key Assumptions'!$B$23,1)*'Key Assumptions'!$D$8)+C25*'Key Assumptions'!$B$30+'Key Assumptions'!$B$29)*(1-'Key Assumptions'!$B$27)+(ROUND('Key Assumptions'!$B$17*'Key Assumptions'!$B$8,0)*'Key Assumptions'!$B$24+C25*'Key Assumptions'!$B$26*'Key Assumptions'!$B$25)-((C25*('Key Assumptions'!$B$21*IF(2>='Key Assumptions'!$B$22,1+'Key Assumptions'!$B$23,1)*'Key Assumptions'!$D$8)+C25*'Key Assumptions'!$B$30+'Key Assumptions'!$B$29)+(ROUND('Key Assumptions'!$B$17*'Key Assumptions'!$B$8,0)*'Key Assumptions'!$B$24+C25*'Key Assumptions'!$B$26*'Key Assumptions'!$B$25))*'Key Assumptions'!$B$28 -> 319275.04 | D26: =(D25*('Key Assumptions'!$B$21*IF(3>='Key Assumptions'!$B$22,1+'Key Assumptions'!$B$23,1)*'Key Assumptions'!$D$8)+D25*'Key Assumptions'!$B$30+'Key Assumptions'!$B$29)*(1-'Key Assumptions'!$B$27)+(ROUND('Key Assumptions'!$B$17*'Key Assumptions'!$B$8,0)*'Key Assumptions'!$B$24+D25*'Key Assumptions'!$B$26*'Key Assumptions'!$B$25)-((D25*('Key Assumptions'!$B$21*IF(3>='Key Assumptions'!$B$22,1+'Key Assumptions'!$B$23,1)*'Key Assumptions'!$D$8)+D25*'Key Assumptions'!$B$30+'Key Assumptions'!$B$29)+(ROUND('Key Assumptions'!$B$17*'Key Assumptions'!$B$8,0)*'Key Assumptions'!$B$24+D25*'Key Assumptions'!$B$26*'Key Assumptions'!$B$25))*'Key Assumptions'!$B$28 -> 319423.4 | E26: =(E25*('Key Assumptions'!$B$21*IF(4>='Key Assumptions'!$B$22,1+'Key Assumptions'!$B$23,1)*'Key Assumptions'!$D$8)+E25*'Key Assumptions'!$B$30+'Key Assumptions'!$B$29)*(1-'Key Assumptions'!$B$27)+(ROUND('Key Assumptions'!$B$17*'Key Assumptions'!$B$8,0)*'Key Assumptions'!$B$24+E25*'Key Assumptions'!$B$26*'Key Assumptions'!$B$25)-((E25*('Key Assumptions'!$B$21*IF(4>='Key Assumptions'!$B$22,1+'Key Assumptions'!$B$23,1)*'Key Assumptions'!$D$8)+E25*'Key Assumptions'!$B$30+'Key Assumptions'!$B$29)+(ROUND('Key Assumptions'!$B$17*'Key Assumptions'!$B$8,0)*'Key Assumptions'!$B$24+E25*'Key Assumptions'!$B$26*'Key Assumptions'!$B$25))*'Key Assumptions'!$B$28 -> 319571.75 | F26: =(F25*('Key Assumptions'!$B$21*IF(5>='Key Assumptions'!$B$22,1+'Key Assumptions'!$B$23,1)*'Key Assumptions'!$D$8)+F25*'Key Assumptions'!$B$30+'Key Assumptions'!$B$29)*(1-'Key Assumptions'!$B$27)+(ROUND('Key Assumptions'!$B$17*'Key Assumptions'!$B$8,0)*'Key Assumptions'!$B$24+F25*'Key Assumptions'!$B$26*'Key Assumptions'!$B$25)-((F25*('Key Assumptions'!$B$21*IF(5>='Key Assumptions'!$B$22,1+'Key Assumptions'!$B$23,1)*'Key Assumptions'!$D$8)+F25*'Key Assumptions'!$B$30+'Key Assumptions'!$B$29)+(ROUND('Key Assumptions'!$B$17*'Key Assumptions'!$B$8,0)*'Key Assumptions'!$B$24+F25*'Key Assumptions'!$B$26*'Key Assumptions'!$B$25))*'Key Assumptions'!$B$28 -> 319720.1 | G26: =(G25*('Key Assumptions'!$B$21*IF(6>='Key Assumptions'!$B$22,1+'Key Assumptions'!$B$23,1)*'Key Assumptions'!$D$8)+G25*'Key Assumptions'!$B$30+'Key Assumptions'!$B$29)*(1-'Key Assumptions'!$B$27)+(ROUND('Key Assumptions'!$B$17*'Key Assumptions'!$B$8,0)*'Key Assumptions'!$B$24+G25*'Key Assumptions'!$B$26*'Key Assumptions'!$B$25)-((G25*('Key Assumptions'!$B$21*IF(6>='Key Assumptions'!$B$22,1+'Key Assumptions'!$B$23,1)*'Key Assumptions'!$D$8)+G25*'Key Assumptions'!$B$30+'Key Assumptions'!$B$29)+(ROUND('Key Assumptions'!$B$17*'Key Assumptions'!$B$8,0)*'Key Assumptions'!$B$24+G25*'Key Assumptions'!$B$26*'Key Assumptions'!$B$25))*'Key Assumptions'!$B$28 -> 319868.45 | H26: =(H25*('Key Assumptions'!$B$21*IF(7>='Key Assumptions'!$B$22,1+'Key Assumptions'!$B$23,1)*'Key Assumptions'!$D$8)+H25*'Key Assumptions'!$B$30+'Key Assumptions'!$B$29)*(1-'Key Assumptions'!$B$27)+(ROUND('Key Assumptions'!$B$17*'Key Assumptions'!$B$8,0)*'Key Assumptions'!$B$24+H25*'Key Assumptions'!$B$26*'Key Assumptions'!$B$25)-((H25*('Key Assumptions'!$B$21*IF(7>='Key Assumptions'!$B$22,1+'Key Assumptions'!$B$23,1)*'Key Assumptions'!$D$8)+H25*'Key Assumptions'!$B$30+'Key Assumptions'!$B$29)+(ROUND('Key Assumptions'!$B$17*'Key Assumptions'!$B$8,0)*'Key Assumptions'!$B$24+H25*'Key Assumptions'!$B$26*'Key Assumptions'!$B$25))*'Key Assumptions'!$B$28 -> 328761.76 | I26: =(I25*('Key Assumptions'!$B$21*IF(8>='Key Assumptions'!$B$22,1+'Key Assumptions'!$B$23,1)*'Key Assumptions'!$D$8)+I25*'Key Assumptions'!$B$30+'Key Assumptions'!$B$29)*(1-'Key Assumptions'!$B$27)+(ROUND('Key Assumptions'!$B$17*'Key Assumptions'!$B$8,0)*'Key Assumptions'!$B$24+I25*'Key Assumptions'!$B$26*'Key Assumptions'!$B$25)-((I25*('Key Assumptions'!$B$21*IF(8>='Key Assumptions'!$B$22,1+'Key Assumptions'!$B$23,1)*'Key Assumptions'!$D$8)+I25*'Key Assumptions'!$B$30+'Key Assumptions'!$B$29)+(ROUND('Key Assumptions'!$B$17*'Key Assumptions'!$B$8,0)*'Key Assumptions'!$B$24+I25*'Key Assumptions'!$B$26*'Key Assumptions'!$B$25))*'Key Assumptions'!$B$28 -> 328914.42 | J26: =(J25*('Key Assumptions'!$B$21*IF(9>='Key Assumptions'!$B$22,1+'Key Assumptions'!$B$23,1)*'Key Assumptions'!$D$8)+J25*'Key Assumptions'!$B$30+'Key Assumptions'!$B$29)*(1-'Key Assumptions'!$B$27)+(ROUND('Key Assumptions'!$B$17*'Key Assumptions'!$B$8,0)*'Key Assumptions'!$B$24+J25*'Key Assumptions'!$B$26*'Key Assumptions'!$B$25)-((J25*('Key Assumptions'!$B$21*IF(9>='Key Assumptions'!$B$22,1+'Key Assumptions'!$B$23,1)*'Key Assumptions'!$D$8)+J25*'Key Assumptions'!$B$30+'Key Assumptions'!$B$29)+(ROUND('Key Assumptions'!$B$17*'Key Assumptions'!$B$8,0)*'Key Assumptions'!$B$24+J25*'Key Assumptions'!$B$26*'Key Assumptions'!$B$25))*'Key Assumptions'!$B$28 -> 329067.08 | K26: =(K25*('Key Assumptions'!$B$21*IF(10>='Key Assumptions'!$B$22,1+'Key Assumptions'!$B$23,1)*'Key Assumptions'!$D$8)+K25*'Key Assumptions'!$B$30+'Key Assumptions'!$B$29)*(1-'Key Assumptions'!$B$27)+(ROUND('Key Assumptions'!$B$17*'Key Assumptions'!$B$8,0)*'Key Assumptions'!$B$24+K25*'Key Assumptions'!$B$26*'Key Assumptions'!$B$25)-((K25*('Key Assumptions'!$B$21*IF(10>='Key Assumptions'!$B$22,1+'Key Assumptions'!$B$23,1)*'Key Assumptions'!$D$8)+K25*'Key Assumptions'!$B$30+'Key Assumptions'!$B$29)+(ROUND('Key Assumptions'!$B$17*'Key Assumptions'!$B$8,0)*'Key Assumptions'!$B$24+K25*'Key Assumptions'!$B$26*'Key Assumptions'!$B$25))*'Key Assumptions'!$B$28 -> 329219.74 | L26: =(L25*('Key Assumptions'!$B$21*IF(11>='Key Assumptions'!$B$22,1+'Key Assumptions'!$B$23,1)*'Key Assumptions'!$D$8)+L25*'Key Assumptions'!$B$30+'Key Assumptions'!$B$29)*(1-'Key Assumptions'!$B$27)+(ROUND('Key Assumptions'!$B$17*'Key Assumptions'!$B$8,0)*'Key Assumptions'!$B$24+L25*'Key Assumptions'!$B$26*'Key Assumptions'!$B$25)-((L25*('Key Assumptions'!$B$21*IF(11>='Key Assumptions'!$B$22,1+'Key Assumptions'!$B$23,1)*'Key Assumptions'!$D$8)+L25*'Key Assumptions'!$B$30+'Key Assumptions'!$B$29)+(ROUND('Key Assumptions'!$B$17*'Key Assumptions'!$B$8,0)*'Key Assumptions'!$B$24+L25*'Key Assumptions'!$B$26*'Key Assumptions'!$B$25))*'Key Assumptions'!$B$28 -> 329372.4 | M26: =(M25*('Key Assumptions'!$B$21*IF(12>='Key Assumptions'!$B$22,1+'Key Assumptions'!$B$23,1)*'Key Assumptions'!$D$8)+M25*'Key Assumptions'!$B$30+'Key Assumptions'!$B$29)*(1-'Key Assumptions'!$B$27)+(ROUND('Key Assumptions'!$B$17*'Key Assumptions'!$B$8,0)*'Key Assumptions'!$B$24+M25*'Key Assumptions'!$B$26*'Key Assumptions'!$B$25)-((M25*('Key Assumptions'!$B$21*IF(12>='Key Assumptions'!$B$22,1+'Key Assumptions'!$B$23,1)*'Key Assumptions'!$D$8)+M25*'Key Assumptions'!$B$30+'Key Assumptions'!$B$29)+(ROUND('Key Assumptions'!$B$17*'Key Assumptions'!$B$8,0)*'Key Assumptions'!$B$24+M25*'Key Assumptions'!$B$26*'Key Assumptions'!$B$25))*'Key Assumptions'!$B$28 -> 329525.06 | N26: =SUM(B26:M26) -> 3891845.9
A27: Business beginning cust | B27: ='Key Assumptions'!$B$35 -> 249 | C27: =B28 -> 252 | D27: =C28 -> 254 | E27: =D28 -> 256 | F27: =E28 -> 258 | G27: =F28 -> 260 | H27: =G28 -> 262 | I27: =H28 -> 264 | J27: =I28 -> 266 | ... M27: =L28 -> 272
A28: Business ending cust | B28: =MAX(0,B27+ROUND(('Key Assumptions'!$B$36+'Key Assumptions'!$B$37)*'Key Assumptions'!$E$8,0)+'Key Assumptions'!$B$40-ROUND(B27*'Key Assumptions'!$B$38*'Key Assumptions'!$F$8,0)-'Key Assumptions'!$B$39) -> 252 | C28: =MAX(0,C27+ROUND(('Key Assumptions'!$B$36+'Key Assumptions'!$B$37)*'Key Assumptions'!$E$8,0)+'Key Assumptions'!$B$40-ROUND(C27*'Key Assumptions'!$B$38*'Key Assumptions'!$F$8,0)-'Key Assumptions'!$B$39) -> 254 | D28: =MAX(0,D27+ROUND(('Key Assumptions'!$B$36+'Key Assumptions'!$B$37)*'Key Assumptions'!$E$8,0)+'Key Assumptions'!$B$40-ROUND(D27*'Key Assumptions'!$B$38*'Key Assumptions'!$F$8,0)-'Key Assumptions'!$B$39) -> 256 | E28: =MAX(0,E27+ROUND(('Key Assumptions'!$B$36+'Key Assumptions'!$B$37)*'Key Assumptions'!$E$8,0)+'Key Assumptions'!$B$40-ROUND(E27*'Key Assumptions'!$B$38*'Key Assumptions'!$F$8,0)-'Key Assumptions'!$B$39) -> 258 | F28: =MAX(0,F27+ROUND(('Key Assumptions'!$B$36+'Key Assumptions'!$B$37)*'Key Assumptions'!$E$8,0)+'Key Assumptions'!$B$40-ROUND(F27*'Key Assumptions'!$B$38*'Key Assumptions'!$F$8,0)-'Key Assumptions'!$B$39) -> 260 | G28: =MAX(0,G27+ROUND(('Key Assumptions'!$B$36+'Key Assumptions'!$B$37)*'Key Assumptions'!$E$8,0)+'Key Assumptions'!$B$40-ROUND(G27*'Key Assumptions'!$B$38*'Key Assumptions'!$F$8,0)-'Key Assumptions'!$B$39) -> 262 | H28: =MAX(0,H27+ROUND(('Key Assumptions'!$B$36+'Key Assumptions'!$B$37)*'Key Assumptions'!$E$8,0)+'Key Assumptions'!$B$40-ROUND(H27*'Key Assumptions'!$B$38*'Key Assumptions'!$F$8,0)-'Key Assumptions'!$B$39) -> 264 | I28: =MAX(0,I27+ROUND(('Key Assumptions'!$B$36+'Key Assumptions'!$B$37)*'Key Assumptions'!$E$8,0)+'Key Assumptions'!$B$40-ROUND(I27*'Key Assumptions'!$B$38*'Key Assumptions'!$F$8,0)-'Key Assumptions'!$B$39) -> 266 | ... M28: =MAX(0,M27+ROUND(('Key Assumptions'!$B$36+'Key Assumptions'!$B$37)*'Key Assumptions'!$E$8,0)+'Key Assumptions'!$B$40-ROUND(M27*'Key Assumptions'!$B$38*'Key Assumptions'!$F$8,0)-'Key Assumptions'!$B$39) -> 274
A29: Business avg cust | B29: =(B27+B28)/2 -> 250.5 | C29: =(C27+C28)/2 -> 253 | D29: =(D27+D28)/2 -> 255 | E29: =(E27+E28)/2 -> 257 | F29: =(F27+F28)/2 -> 259 | G29: =(G27+G28)/2 -> 261 | H29: =(H27+H28)/2 -> 263 | I29: =(I27+I28)/2 -> 265 | ... M29: =(M27+M28)/2 -> 273
A30: Enterprise beginning | B30: ='Key Assumptions'!$B$57 -> 0 | C30: =B31 -> 1 | D30: =C31 -> 2 | E30: =D31 -> 3 | F30: =E31 -> 4 | G30: =F31 -> 5 | H30: =G31 -> 6 | I30: =H31 -> 7 | J30: =I31 -> 8 | ... M30: =L31 -> 11
A31: Enterprise ending | B31: =MAX(0,B30+ROUND('Key Assumptions'!$B$37*'Key Assumptions'!$E$8,0)-ROUND(B30*'Key Assumptions'!$B$38*'Key Assumptions'!$F$8,0)) -> 1 | C31: =MAX(0,C30+ROUND('Key Assumptions'!$B$37*'Key Assumptions'!$E$8,0)-ROUND(C30*'Key Assumptions'!$B$38*'Key Assumptions'!$F$8,0)) -> 2 | D31: =MAX(0,D30+ROUND('Key Assumptions'!$B$37*'Key Assumptions'!$E$8,0)-ROUND(D30*'Key Assumptions'!$B$38*'Key Assumptions'!$F$8,0)) -> 3 | E31: =MAX(0,E30+ROUND('Key Assumptions'!$B$37*'Key Assumptions'!$E$8,0)-ROUND(E30*'Key Assumptions'!$B$38*'Key Assumptions'!$F$8,0)) -> 4 | F31: =MAX(0,F30+ROUND('Key Assumptions'!$B$37*'Key Assumptions'!$E$8,0)-ROUND(F30*'Key Assumptions'!$B$38*'Key Assumptions'!$F$8,0)) -> 5 | G31: =MAX(0,G30+ROUND('Key Assumptions'!$B$37*'Key Assumptions'!$E$8,0)-ROUND(G30*'Key Assumptions'!$B$38*'Key Assumptions'!$F$8,0)) -> 6 | H31: =MAX(0,H30+ROUND('Key Assumptions'!$B$37*'Key Assumptions'!$E$8,0)-ROUND(H30*'Key Assumptions'!$B$38*'Key Assumptions'!$F$8,0)) -> 7 | I31: =MAX(0,I30+ROUND('Key Assumptions'!$B$37*'Key Assumptions'!$E$8,0)-ROUND(I30*'Key Assumptions'!$B$38*'Key Assumptions'!$F$8,0)) -> 8 | ... M31: =MAX(0,M30+ROUND('Key Assumptions'!$B$37*'Key Assumptions'!$E$8,0)-ROUND(M30*'Key Assumptions'!$B$38*'Key Assumptions'!$F$8,0)) -> 12
A32: Enterprise avg | B32: =(B30+B31)/2 -> 0.5 | C32: =(C30+C31)/2 -> 1.5 | D32: =(D30+D31)/2 -> 2.5 | E32: =(E30+E31)/2 -> 3.5 | F32: =(F30+F31)/2 -> 4.5 | G32: =(G30+G31)/2 -> 5.5 | H32: =(H30+H31)/2 -> 6.5 | I32: =(I30+I31)/2 -> 7.5 | ... M32: =(M30+M31)/2 -> 11.5
A33: Business net revenue | B33: =(B29*('Key Assumptions'!$B$41*IF(1>='Key Assumptions'!$B$42,1+'Key Assumptions'!$B$43,1)*'Key Assumptions'!$G$8)+B29*('Key Assumptions'!$B$45+'Key Assumptions'!$B$46+'Key Assumptions'!$B$47+'Key Assumptions'!$B$49)+B32*'Key Assumptions'!$B$48)*(1-'Key Assumptions'!$B$54)+(ROUND(('Key Assumptions'!$B$36+'Key Assumptions'!$B$37)*'Key Assumptions'!$E$8,0)*('Key Assumptions'!$B$44+'Key Assumptions'!$B$50+'Key Assumptions'!$B$51)+'Key Assumptions'!$B$52+'Key Assumptions'!$B$53)-((B29*('Key Assumptions'!$B$41*IF(1>='Key Assumptions'!$B$42,1+'Key Assumptions'!$B$43,1)*'Key Assumptions'!$G$8)+B29*('Key Assumptions'!$B$45+'Key Assumptions'!$B$46+'Key Assumptions'!$B$47+'Key Assumptions'!$B$49)+B32*'Key Assumptions'!$B$48)+(ROUND(('Key Assumptions'!$B$36+'Key Assumptions'!$B$37)*'Key Assumptions'!$E$8,0)*('Key Assumptions'!$B$44+'Key Assumptions'!$B$50+'Key Assumptions'!$B$51)+'Key Assumptions'!$B$52+'Key Assumptions'!$B$53))*'Key Assumptions'!$B$55 -> 44943.106 | C33: =(C29*('Key Assumptions'!$B$41*IF(2>='Key Assumptions'!$B$42,1+'Key Assumptions'!$B$43,1)*'Key Assumptions'!$G$8)+C29*('Key Assumptions'!$B$45+'Key Assumptions'!$B$46+'Key Assumptions'!$B$47+'Key Assumptions'!$B$49)+C32*'Key Assumptions'!$B$48)*(1-'Key Assumptions'!$B$54)+(ROUND(('Key Assumptions'!$B$36+'Key Assumptions'!$B$37)*'Key Assumptions'!$E$8,0)*('Key Assumptions'!$B$44+'Key Assumptions'!$B$50+'Key Assumptions'!$B$51)+'Key Assumptions'!$B$52+'Key Assumptions'!$B$53)-((C29*('Key Assumptions'!$B$41*IF(2>='Key Assumptions'!$B$42,1+'Key Assumptions'!$B$43,1)*'Key Assumptions'!$G$8)+C29*('Key Assumptions'!$B$45+'Key Assumptions'!$B$46+'Key Assumptions'!$B$47+'Key Assumptions'!$B$49)+C32*'Key Assumptions'!$B$48)+(ROUND(('Key Assumptions'!$B$36+'Key Assumptions'!$B$37)*'Key Assumptions'!$E$8,0)*('Key Assumptions'!$B$44+'Key Assumptions'!$B$50+'Key Assumptions'!$B$51)+'Key Assumptions'!$B$52+'Key Assumptions'!$B$53))*'Key Assumptions'!$B$55 -> 45329.889 | D33: =(D29*('Key Assumptions'!$B$41*IF(3>='Key Assumptions'!$B$42,1+'Key Assumptions'!$B$43,1)*'Key Assumptions'!$G$8)+D29*('Key Assumptions'!$B$45+'Key Assumptions'!$B$46+'Key Assumptions'!$B$47+'Key Assumptions'!$B$49)+D32*'Key Assumptions'!$B$48)*(1-'Key Assumptions'!$B$54)+(ROUND(('Key Assumptions'!$B$36+'Key Assumptions'!$B$37)*'Key Assumptions'!$E$8,0)*('Key Assumptions'!$B$44+'Key Assumptions'!$B$50+'Key Assumptions'!$B$51)+'Key Assumptions'!$B$52+'Key Assumptions'!$B$53)-((D29*('Key Assumptions'!$B$41*IF(3>='Key Assumptions'!$B$42,1+'Key Assumptions'!$B$43,1)*'Key Assumptions'!$G$8)+D29*('Key Assumptions'!$B$45+'Key Assumptions'!$B$46+'Key Assumptions'!$B$47+'Key Assumptions'!$B$49)+D32*'Key Assumptions'!$B$48)+(ROUND(('Key Assumptions'!$B$36+'Key Assumptions'!$B$37)*'Key Assumptions'!$E$8,0)*('Key Assumptions'!$B$44+'Key Assumptions'!$B$50+'Key Assumptions'!$B$51)+'Key Assumptions'!$B$52+'Key Assumptions'!$B$53))*'Key Assumptions'!$B$55 -> 45639.315 | E33: =(E29*('Key Assumptions'!$B$41*IF(4>='Key Assumptions'!$B$42,1+'Key Assumptions'!$B$43,1)*'Key Assumptions'!$G$8)+E29*('Key Assumptions'!$B$45+'Key Assumptions'!$B$46+'Key Assumptions'!$B$47+'Key Assumptions'!$B$49)+E32*'Key Assumptions'!$B$48)*(1-'Key Assumptions'!$B$54)+(ROUND(('Key Assumptions'!$B$36+'Key Assumptions'!$B$37)*'Key Assumptions'!$E$8,0)*('Key Assumptions'!$B$44+'Key Assumptions'!$B$50+'Key Assumptions'!$B$51)+'Key Assumptions'!$B$52+'Key Assumptions'!$B$53)-((E29*('Key Assumptions'!$B$41*IF(4>='Key Assumptions'!$B$42,1+'Key Assumptions'!$B$43,1)*'Key Assumptions'!$G$8)+E29*('Key Assumptions'!$B$45+'Key Assumptions'!$B$46+'Key Assumptions'!$B$47+'Key Assumptions'!$B$49)+E32*'Key Assumptions'!$B$48)+(ROUND(('Key Assumptions'!$B$36+'Key Assumptions'!$B$37)*'Key Assumptions'!$E$8,0)*('Key Assumptions'!$B$44+'Key Assumptions'!$B$50+'Key Assumptions'!$B$51)+'Key Assumptions'!$B$52+'Key Assumptions'!$B$53))*'Key Assumptions'!$B$55 -> 45948.741 | F33: =(F29*('Key Assumptions'!$B$41*IF(5>='Key Assumptions'!$B$42,1+'Key Assumptions'!$B$43,1)*'Key Assumptions'!$G$8)+F29*('Key Assumptions'!$B$45+'Key Assumptions'!$B$46+'Key Assumptions'!$B$47+'Key Assumptions'!$B$49)+F32*'Key Assumptions'!$B$48)*(1-'Key Assumptions'!$B$54)+(ROUND(('Key Assumptions'!$B$36+'Key Assumptions'!$B$37)*'Key Assumptions'!$E$8,0)*('Key Assumptions'!$B$44+'Key Assumptions'!$B$50+'Key Assumptions'!$B$51)+'Key Assumptions'!$B$52+'Key Assumptions'!$B$53)-((F29*('Key Assumptions'!$B$41*IF(5>='Key Assumptions'!$B$42,1+'Key Assumptions'!$B$43,1)*'Key Assumptions'!$G$8)+F29*('Key Assumptions'!$B$45+'Key Assumptions'!$B$46+'Key Assumptions'!$B$47+'Key Assumptions'!$B$49)+F32*'Key Assumptions'!$B$48)+(ROUND(('Key Assumptions'!$B$36+'Key Assumptions'!$B$37)*'Key Assumptions'!$E$8,0)*('Key Assumptions'!$B$44+'Key Assumptions'!$B$50+'Key Assumptions'!$B$51)+'Key Assumptions'!$B$52+'Key Assumptions'!$B$53))*'Key Assumptions'!$B$55 -> 46258.167 | G33: =(G29*('Key Assumptions'!$B$41*IF(6>='Key Assumptions'!$B$42,1+'Key Assumptions'!$B$43,1)*'Key Assumptions'!$G$8)+G29*('Key Assumptions'!$B$45+'Key Assumptions'!$B$46+'Key Assumptions'!$B$47+'Key Assumptions'!$B$49)+G32*'Key Assumptions'!$B$48)*(1-'Key Assumptions'!$B$54)+(ROUND(('Key Assumptions'!$B$36+'Key Assumptions'!$B$37)*'Key Assumptions'!$E$8,0)*('Key Assumptions'!$B$44+'Key Assumptions'!$B$50+'Key Assumptions'!$B$51)+'Key Assumptions'!$B$52+'Key Assumptions'!$B$53)-((G29*('Key Assumptions'!$B$41*IF(6>='Key Assumptions'!$B$42,1+'Key Assumptions'!$B$43,1)*'Key Assumptions'!$G$8)+G29*('Key Assumptions'!$B$45+'Key Assumptions'!$B$46+'Key Assumptions'!$B$47+'Key Assumptions'!$B$49)+G32*'Key Assumptions'!$B$48)+(ROUND(('Key Assumptions'!$B$36+'Key Assumptions'!$B$37)*'Key Assumptions'!$E$8,0)*('Key Assumptions'!$B$44+'Key Assumptions'!$B$50+'Key Assumptions'!$B$51)+'Key Assumptions'!$B$52+'Key Assumptions'!$B$53))*'Key Assumptions'!$B$55 -> 46567.593 | H33: =(H29*('Key Assumptions'!$B$41*IF(7>='Key Assumptions'!$B$42,1+'Key Assumptions'!$B$43,1)*'Key Assumptions'!$G$8)+H29*('Key Assumptions'!$B$45+'Key Assumptions'!$B$46+'Key Assumptions'!$B$47+'Key Assumptions'!$B$49)+H32*'Key Assumptions'!$B$48)*(1-'Key Assumptions'!$B$54)+(ROUND(('Key Assumptions'!$B$36+'Key Assumptions'!$B$37)*'Key Assumptions'!$E$8,0)*('Key Assumptions'!$B$44+'Key Assumptions'!$B$50+'Key Assumptions'!$B$51)+'Key Assumptions'!$B$52+'Key Assumptions'!$B$53)-((H29*('Key Assumptions'!$B$41*IF(7>='Key Assumptions'!$B$42,1+'Key Assumptions'!$B$43,1)*'Key Assumptions'!$G$8)+H29*('Key Assumptions'!$B$45+'Key Assumptions'!$B$46+'Key Assumptions'!$B$47+'Key Assumptions'!$B$49)+H32*'Key Assumptions'!$B$48)+(ROUND(('Key Assumptions'!$B$36+'Key Assumptions'!$B$37)*'Key Assumptions'!$E$8,0)*('Key Assumptions'!$B$44+'Key Assumptions'!$B$50+'Key Assumptions'!$B$51)+'Key Assumptions'!$B$52+'Key Assumptions'!$B$53))*'Key Assumptions'!$B$55 -> 48023.239 | I33: =(I29*('Key Assumptions'!$B$41*IF(8>='Key Assumptions'!$B$42,1+'Key Assumptions'!$B$43,1)*'Key Assumptions'!$G$8)+I29*('Key Assumptions'!$B$45+'Key Assumptions'!$B$46+'Key Assumptions'!$B$47+'Key Assumptions'!$B$49)+I32*'Key Assumptions'!$B$48)*(1-'Key Assumptions'!$B$54)+(ROUND(('Key Assumptions'!$B$36+'Key Assumptions'!$B$37)*'Key Assumptions'!$E$8,0)*('Key Assumptions'!$B$44+'Key Assumptions'!$B$50+'Key Assumptions'!$B$51)+'Key Assumptions'!$B$52+'Key Assumptions'!$B$53)-((I29*('Key Assumptions'!$B$41*IF(8>='Key Assumptions'!$B$42,1+'Key Assumptions'!$B$43,1)*'Key Assumptions'!$G$8)+I29*('Key Assumptions'!$B$45+'Key Assumptions'!$B$46+'Key Assumptions'!$B$47+'Key Assumptions'!$B$49)+I32*'Key Assumptions'!$B$48)+(ROUND(('Key Assumptions'!$B$36+'Key Assumptions'!$B$37)*'Key Assumptions'!$E$8,0)*('Key Assumptions'!$B$44+'Key Assumptions'!$B$50+'Key Assumptions'!$B$51)+'Key Assumptions'!$B$52+'Key Assumptions'!$B$53))*'Key Assumptions'!$B$55 -> 48341.381 | J33: =(J29*('Key Assumptions'!$B$41*IF(9>='Key Assumptions'!$B$42,1+'Key Assumptions'!$B$43,1)*'Key Assumptions'!$G$8)+J29*('Key Assumptions'!$B$45+'Key Assumptions'!$B$46+'Key Assumptions'!$B$47+'Key Assumptions'!$B$49)+J32*'Key Assumptions'!$B$48)*(1-'Key Assumptions'!$B$54)+(ROUND(('Key Assumptions'!$B$36+'Key Assumptions'!$B$37)*'Key Assumptions'!$E$8,0)*('Key Assumptions'!$B$44+'Key Assumptions'!$B$50+'Key Assumptions'!$B$51)+'Key Assumptions'!$B$52+'Key Assumptions'!$B$53)-((J29*('Key Assumptions'!$B$41*IF(9>='Key Assumptions'!$B$42,1+'Key Assumptions'!$B$43,1)*'Key Assumptions'!$G$8)+J29*('Key Assumptions'!$B$45+'Key Assumptions'!$B$46+'Key Assumptions'!$B$47+'Key Assumptions'!$B$49)+J32*'Key Assumptions'!$B$48)+(ROUND(('Key Assumptions'!$B$36+'Key Assumptions'!$B$37)*'Key Assumptions'!$E$8,0)*('Key Assumptions'!$B$44+'Key Assumptions'!$B$50+'Key Assumptions'!$B$51)+'Key Assumptions'!$B$52+'Key Assumptions'!$B$53))*'Key Assumptions'!$B$55 -> 48659.524 | K33: =(K29*('Key Assumptions'!$B$41*IF(10>='Key Assumptions'!$B$42,1+'Key Assumptions'!$B$43,1)*'Key Assumptions'!$G$8)+K29*('Key Assumptions'!$B$45+'Key Assumptions'!$B$46+'Key Assumptions'!$B$47+'Key Assumptions'!$B$49)+K32*'Key Assumptions'!$B$48)*(1-'Key Assumptions'!$B$54)+(ROUND(('Key Assumptions'!$B$36+'Key Assumptions'!$B$37)*'Key Assumptions'!$E$8,0)*('Key Assumptions'!$B$44+'Key Assumptions'!$B$50+'Key Assumptions'!$B$51)+'Key Assumptions'!$B$52+'Key Assumptions'!$B$53)-((K29*('Key Assumptions'!$B$41*IF(10>='Key Assumptions'!$B$42,1+'Key Assumptions'!$B$43,1)*'Key Assumptions'!$G$8)+K29*('Key Assumptions'!$B$45+'Key Assumptions'!$B$46+'Key Assumptions'!$B$47+'Key Assumptions'!$B$49)+K32*'Key Assumptions'!$B$48)+(ROUND(('Key Assumptions'!$B$36+'Key Assumptions'!$B$37)*'Key Assumptions'!$E$8,0)*('Key Assumptions'!$B$44+'Key Assumptions'!$B$50+'Key Assumptions'!$B$51)+'Key Assumptions'!$B$52+'Key Assumptions'!$B$53))*'Key Assumptions'!$B$55 -> 48977.666 | L33: =(L29*('Key Assumptions'!$B$41*IF(11>='Key Assumptions'!$B$42,1+'Key Assumptions'!$B$43,1)*'Key Assumptions'!$G$8)+L29*('Key Assumptions'!$B$45+'Key Assumptions'!$B$46+'Key Assumptions'!$B$47+'Key Assumptions'!$B$49)+L32*'Key Assumptions'!$B$48)*(1-'Key Assumptions'!$B$54)+(ROUND(('Key Assumptions'!$B$36+'Key Assumptions'!$B$37)*'Key Assumptions'!$E$8,0)*('Key Assumptions'!$B$44+'Key Assumptions'!$B$50+'Key Assumptions'!$B$51)+'Key Assumptions'!$B$52+'Key Assumptions'!$B$53)-((L29*('Key Assumptions'!$B$41*IF(11>='Key Assumptions'!$B$42,1+'Key Assumptions'!$B$43,1)*'Key Assumptions'!$G$8)+L29*('Key Assumptions'!$B$45+'Key Assumptions'!$B$46+'Key Assumptions'!$B$47+'Key Assumptions'!$B$49)+L32*'Key Assumptions'!$B$48)+(ROUND(('Key Assumptions'!$B$36+'Key Assumptions'!$B$37)*'Key Assumptions'!$E$8,0)*('Key Assumptions'!$B$44+'Key Assumptions'!$B$50+'Key Assumptions'!$B$51)+'Key Assumptions'!$B$52+'Key Assumptions'!$B$53))*'Key Assumptions'!$B$55 -> 49295.809 | M33: =(M29*('Key Assumptions'!$B$41*IF(12>='Key Assumptions'!$B$42,1+'Key Assumptions'!$B$43,1)*'Key Assumptions'!$G$8)+M29*('Key Assumptions'!$B$45+'Key Assumptions'!$B$46+'Key Assumptions'!$B$47+'Key Assumptions'!$B$49)+M32*'Key Assumptions'!$B$48)*(1-'Key Assumptions'!$B$54)+(ROUND(('Key Assumptions'!$B$36+'Key Assumptions'!$B$37)*'Key Assumptions'!$E$8,0)*('Key Assumptions'!$B$44+'Key Assumptions'!$B$50+'Key Assumptions'!$B$51)+'Key Assumptions'!$B$52+'Key Assumptions'!$B$53)-((M29*('Key Assumptions'!$B$41*IF(12>='Key Assumptions'!$B$42,1+'Key Assumptions'!$B$43,1)*'Key Assumptions'!$G$8)+M29*('Key Assumptions'!$B$45+'Key Assumptions'!$B$46+'Key Assumptions'!$B$47+'Key Assumptions'!$B$49)+M32*'Key Assumptions'!$B$48)+(ROUND(('Key Assumptions'!$B$36+'Key Assumptions'!$B$37)*'Key Assumptions'!$E$8,0)*('Key Assumptions'!$B$44+'Key Assumptions'!$B$50+'Key Assumptions'!$B$51)+'Key Assumptions'!$B$52+'Key Assumptions'!$B$53))*'Key Assumptions'!$B$55 -> 49613.951 | N33: =SUM(B33:M33) -> 567598.38
A34: Dark fiber net revenue | B34: ='Dark Fiber Forecast'!Q43*'Key Assumptions'!$H$8 -> 1595 | C34: ='Dark Fiber Forecast'!R43*'Key Assumptions'!$H$8 -> 1595 | D34: ='Dark Fiber Forecast'!S43*'Key Assumptions'!$H$8 -> 1595 | E34: ='Dark Fiber Forecast'!T43*'Key Assumptions'!$H$8 -> 1595 | F34: ='Dark Fiber Forecast'!U43*'Key Assumptions'!$H$8 -> 1595 | G34: ='Dark Fiber Forecast'!V43*'Key Assumptions'!$H$8 -> 1595 | H34: ='Dark Fiber Forecast'!W43*'Key Assumptions'!$H$8 -> 1595 | I34: ='Dark Fiber Forecast'!X43*'Key Assumptions'!$H$8 -> 1595 | ... M34: ='Dark Fiber Forecast'!AB43*'Key Assumptions'!$H$8 -> 1595 | N34: =SUM(B34:M34) -> 19140
A35: TOTAL NET REVENUE | B35: =B26+B33+B34+IF(1>='Key Assumptions'!$B$94,'Key Assumptions'!$B$93,0) -> 422664.8 | C35: =C26+C33+C34+IF(2>='Key Assumptions'!$B$94,'Key Assumptions'!$B$93,0) -> 423199.93 | D35: =D26+D33+D34+IF(3>='Key Assumptions'!$B$94,'Key Assumptions'!$B$93,0) -> 423657.71 | E35: =E26+E33+E34+IF(4>='Key Assumptions'!$B$94,'Key Assumptions'!$B$93,0) -> 424115.49 | F35: =F26+F33+F34+IF(5>='Key Assumptions'!$B$94,'Key Assumptions'!$B$93,0) -> 424573.27 | G35: =G26+G33+G34+IF(6>='Key Assumptions'!$B$94,'Key Assumptions'!$B$93,0) -> 425031.05 | H35: =H26+H33+H34+IF(7>='Key Assumptions'!$B$94,'Key Assumptions'!$B$93,0) -> 435380 | I35: =I26+I33+I34+IF(8>='Key Assumptions'!$B$94,'Key Assumptions'!$B$93,0) -> 435850.8 | J35: =J26+J33+J34+IF(9>='Key Assumptions'!$B$94,'Key Assumptions'!$B$93,0) -> 436321.61 | K35: =K26+K33+K34+IF(10>='Key Assumptions'!$B$94,'Key Assumptions'!$B$93,0) -> 436792.41 | L35: =L26+L33+L34+IF(11>='Key Assumptions'!$B$94,'Key Assumptions'!$B$93,0) -> 437263.21 | M35: =M26+M33+M34+IF(12>='Key Assumptions'!$B$94,'Key Assumptions'!$B$93,0) -> 437734.01 | N35: =SUM(B35:M35) -> 5162584.3
A37: AGGRESSIVE SCENARIO
A38: Metric | B38: 46388 | C38: 46419 | D38: 46447 | E38: 46478 | F38: 46508 | G38: 46539 | H38: 46569 | I38: 46600 | J38: 46631 | K38: 46661 | L38: 46692 | M38: 46722 | N38: FY 2027
A39: Residential beginning subs | B39: ='Key Assumptions'!$B$16 -> 4048 | C39: =B40 -> 4068 | D39: =C40 -> 4088 | E39: =D40 -> 4108 | F39: =E40 -> 4128 | G39: =F40 -> 4147 | H39: =G40 -> 4166 | I39: =H40 -> 4185 | J39: =I40 -> 4204 | ... M39: =L40 -> 4258
A40: Residential ending subs | B40: =MAX(0,B39+ROUND('Key Assumptions'!$B$17*'Key Assumptions'!$B$10,0)+'Key Assumptions'!$B$20-ROUND(B39*'Key Assumptions'!$B$18*'Key Assumptions'!$C$10,0)-'Key Assumptions'!$B$19) -> 4068 | C40: =MAX(0,C39+ROUND('Key Assumptions'!$B$17*'Key Assumptions'!$B$10,0)+'Key Assumptions'!$B$20-ROUND(C39*'Key Assumptions'!$B$18*'Key Assumptions'!$C$10,0)-'Key Assumptions'!$B$19) -> 4088 | D40: =MAX(0,D39+ROUND('Key Assumptions'!$B$17*'Key Assumptions'!$B$10,0)+'Key Assumptions'!$B$20-ROUND(D39*'Key Assumptions'!$B$18*'Key Assumptions'!$C$10,0)-'Key Assumptions'!$B$19) -> 4108 | E40: =MAX(0,E39+ROUND('Key Assumptions'!$B$17*'Key Assumptions'!$B$10,0)+'Key Assumptions'!$B$20-ROUND(E39*'Key Assumptions'!$B$18*'Key Assumptions'!$C$10,0)-'Key Assumptions'!$B$19) -> 4128 | F40: =MAX(0,F39+ROUND('Key Assumptions'!$B$17*'Key Assumptions'!$B$10,0)+'Key Assumptions'!$B$20-ROUND(F39*'Key Assumptions'!$B$18*'Key Assumptions'!$C$10,0)-'Key Assumptions'!$B$19) -> 4147 | G40: =MAX(0,G39+ROUND('Key Assumptions'!$B$17*'Key Assumptions'!$B$10,0)+'Key Assumptions'!$B$20-ROUND(G39*'Key Assumptions'!$B$18*'Key Assumptions'!$C$10,0)-'Key Assumptions'!$B$19) -> 4166 | H40: =MAX(0,H39+ROUND('Key Assumptions'!$B$17*'Key Assumptions'!$B$10,0)+'Key Assumptions'!$B$20-ROUND(H39*'Key Assumptions'!$B$18*'Key Assumptions'!$C$10,0)-'Key Assumptions'!$B$19) -> 4185 | I40: =MAX(0,I39+ROUND('Key Assumptions'!$B$17*'Key Assumptions'!$B$10,0)+'Key Assumptions'!$B$20-ROUND(I39*'Key Assumptions'!$B$18*'Key Assumptions'!$C$10,0)-'Key Assumptions'!$B$19) -> 4204 | ... M40: =MAX(0,M39+ROUND('Key Assumptions'!$B$17*'Key Assumptions'!$B$10,0)+'Key Assumptions'!$B$20-ROUND(M39*'Key Assumptions'!$B$18*'Key Assumptions'!$C$10,0)-'Key Assumptions'!$B$19) -> 4276
A41: Residential avg subs | B41: =(B39+B40)/2 -> 4058 | C41: =(C39+C40)/2 -> 4078 | D41: =(D39+D40)/2 -> 4098 | E41: =(E39+E40)/2 -> 4118 | F41: =(F39+F40)/2 -> 4137.5 | G41: =(G39+G40)/2 -> 4156.5 | H41: =(H39+H40)/2 -> 4175.5 | I41: =(I39+I40)/2 -> 4194.5 | ... M41: =(M39+M40)/2 -> 4267
A42: Residential net revenue | B42: =(B41*('Key Assumptions'!$B$21*IF(1>='Key Assumptions'!$B$22,1+'Key Assumptions'!$B$23,1)*'Key Assumptions'!$D$10)+B41*'Key Assumptions'!$B$30+'Key Assumptions'!$B$29)*(1-'Key Assumptions'!$B$27)+(ROUND('Key Assumptions'!$B$17*'Key Assumptions'!$B$10,0)*'Key Assumptions'!$B$24+B41*'Key Assumptions'!$B$26*'Key Assumptions'!$B$25)-((B41*('Key Assumptions'!$B$21*IF(1>='Key Assumptions'!$B$22,1+'Key Assumptions'!$B$23,1)*'Key Assumptions'!$D$10)+B41*'Key Assumptions'!$B$30+'Key Assumptions'!$B$29)+(ROUND('Key Assumptions'!$B$17*'Key Assumptions'!$B$10,0)*'Key Assumptions'!$B$24+B41*'Key Assumptions'!$B$26*'Key Assumptions'!$B$25))*'Key Assumptions'!$B$28 -> 329414.87 | C42: =(C41*('Key Assumptions'!$B$21*IF(2>='Key Assumptions'!$B$22,1+'Key Assumptions'!$B$23,1)*'Key Assumptions'!$D$10)+C41*'Key Assumptions'!$B$30+'Key Assumptions'!$B$29)*(1-'Key Assumptions'!$B$27)+(ROUND('Key Assumptions'!$B$17*'Key Assumptions'!$B$10,0)*'Key Assumptions'!$B$24+C41*'Key Assumptions'!$B$26*'Key Assumptions'!$B$25)-((C41*('Key Assumptions'!$B$21*IF(2>='Key Assumptions'!$B$22,1+'Key Assumptions'!$B$23,1)*'Key Assumptions'!$D$10)+C41*'Key Assumptions'!$B$30+'Key Assumptions'!$B$29)+(ROUND('Key Assumptions'!$B$17*'Key Assumptions'!$B$10,0)*'Key Assumptions'!$B$24+C41*'Key Assumptions'!$B$26*'Key Assumptions'!$B$25))*'Key Assumptions'!$B$28 -> 330941.46 | D42: =(D41*('Key Assumptions'!$B$21*IF(3>='Key Assumptions'!$B$22,1+'Key Assumptions'!$B$23,1)*'Key Assumptions'!$D$10)+D41*'Key Assumptions'!$B$30+'Key Assumptions'!$B$29)*(1-'Key Assumptions'!$B$27)+(ROUND('Key Assumptions'!$B$17*'Key Assumptions'!$B$10,0)*'Key Assumptions'!$B$24+D41*'Key Assumptions'!$B$26*'Key Assumptions'!$B$25)-((D41*('Key Assumptions'!$B$21*IF(3>='Key Assumptions'!$B$22,1+'Key Assumptions'!$B$23,1)*'Key Assumptions'!$D$10)+D41*'Key Assumptions'!$B$30+'Key Assumptions'!$B$29)+(ROUND('Key Assumptions'!$B$17*'Key Assumptions'!$B$10,0)*'Key Assumptions'!$B$24+D41*'Key Assumptions'!$B$26*'Key Assumptions'!$B$25))*'Key Assumptions'!$B$28 -> 332468.05 | E42: =(E41*('Key Assumptions'!$B$21*IF(4>='Key Assumptions'!$B$22,1+'Key Assumptions'!$B$23,1)*'Key Assumptions'!$D$10)+E41*'Key Assumptions'!$B$30+'Key Assumptions'!$B$29)*(1-'Key Assumptions'!$B$27)+(ROUND('Key Assumptions'!$B$17*'Key Assumptions'!$B$10,0)*'Key Assumptions'!$B$24+E41*'Key Assumptions'!$B$26*'Key Assumptions'!$B$25)-((E41*('Key Assumptions'!$B$21*IF(4>='Key Assumptions'!$B$22,1+'Key Assumptions'!$B$23,1)*'Key Assumptions'!$D$10)+E41*'Key Assumptions'!$B$30+'Key Assumptions'!$B$29)+(ROUND('Key Assumptions'!$B$17*'Key Assumptions'!$B$10,0)*'Key Assumptions'!$B$24+E41*'Key Assumptions'!$B$26*'Key Assumptions'!$B$25))*'Key Assumptions'!$B$28 -> 333994.64 | F42: =(F41*('Key Assumptions'!$B$21*IF(5>='Key Assumptions'!$B$22,1+'Key Assumptions'!$B$23,1)*'Key Assumptions'!$D$10)+F41*'Key Assumptions'!$B$30+'Key Assumptions'!$B$29)*(1-'Key Assumptions'!$B$27)+(ROUND('Key Assumptions'!$B$17*'Key Assumptions'!$B$10,0)*'Key Assumptions'!$B$24+F41*'Key Assumptions'!$B$26*'Key Assumptions'!$B$25)-((F41*('Key Assumptions'!$B$21*IF(5>='Key Assumptions'!$B$22,1+'Key Assumptions'!$B$23,1)*'Key Assumptions'!$D$10)+F41*'Key Assumptions'!$B$30+'Key Assumptions'!$B$29)+(ROUND('Key Assumptions'!$B$17*'Key Assumptions'!$B$10,0)*'Key Assumptions'!$B$24+F41*'Key Assumptions'!$B$26*'Key Assumptions'!$B$25))*'Key Assumptions'!$B$28 -> 335483.07 | G42: =(G41*('Key Assumptions'!$B$21*IF(6>='Key Assumptions'!$B$22,1+'Key Assumptions'!$B$23,1)*'Key Assumptions'!$D$10)+G41*'Key Assumptions'!$B$30+'Key Assumptions'!$B$29)*(1-'Key Assumptions'!$B$27)+(ROUND('Key Assumptions'!$B$17*'Key Assumptions'!$B$10,0)*'Key Assumptions'!$B$24+G41*'Key Assumptions'!$B$26*'Key Assumptions'!$B$25)-((G41*('Key Assumptions'!$B$21*IF(6>='Key Assumptions'!$B$22,1+'Key Assumptions'!$B$23,1)*'Key Assumptions'!$D$10)+G41*'Key Assumptions'!$B$30+'Key Assumptions'!$B$29)+(ROUND('Key Assumptions'!$B$17*'Key Assumptions'!$B$10,0)*'Key Assumptions'!$B$24+G41*'Key Assumptions'!$B$26*'Key Assumptions'!$B$25))*'Key Assumptions'!$B$28 -> 336933.33 | H42: =(H41*('Key Assumptions'!$B$21*IF(7>='Key Assumptions'!$B$22,1+'Key Assumptions'!$B$23,1)*'Key Assumptions'!$D$10)+H41*'Key Assumptions'!$B$30+'Key Assumptions'!$B$29)*(1-'Key Assumptions'!$B$27)+(ROUND('Key Assumptions'!$B$17*'Key Assumptions'!$B$10,0)*'Key Assumptions'!$B$24+H41*'Key Assumptions'!$B$26*'Key Assumptions'!$B$25)-((H41*('Key Assumptions'!$B$21*IF(7>='Key Assumptions'!$B$22,1+'Key Assumptions'!$B$23,1)*'Key Assumptions'!$D$10)+H41*'Key Assumptions'!$B$30+'Key Assumptions'!$B$29)+(ROUND('Key Assumptions'!$B$17*'Key Assumptions'!$B$10,0)*'Key Assumptions'!$B$24+H41*'Key Assumptions'!$B$26*'Key Assumptions'!$B$25))*'Key Assumptions'!$B$28 -> 347644.86 | I42: =(I41*('Key Assumptions'!$B$21*IF(8>='Key Assumptions'!$B$22,1+'Key Assumptions'!$B$23,1)*'Key Assumptions'!$D$10)+I41*'Key Assumptions'!$B$30+'Key Assumptions'!$B$29)*(1-'Key Assumptions'!$B$27)+(ROUND('Key Assumptions'!$B$17*'Key Assumptions'!$B$10,0)*'Key Assumptions'!$B$24+I41*'Key Assumptions'!$B$26*'Key Assumptions'!$B$25)-((I41*('Key Assumptions'!$B$21*IF(8>='Key Assumptions'!$B$22,1+'Key Assumptions'!$B$23,1)*'Key Assumptions'!$D$10)+I41*'Key Assumptions'!$B$30+'Key Assumptions'!$B$29)+(ROUND('Key Assumptions'!$B$17*'Key Assumptions'!$B$10,0)*'Key Assumptions'!$B$24+I41*'Key Assumptions'!$B$26*'Key Assumptions'!$B$25))*'Key Assumptions'!$B$28 -> 349137.26 | J42: =(J41*('Key Assumptions'!$B$21*IF(9>='Key Assumptions'!$B$22,1+'Key Assumptions'!$B$23,1)*'Key Assumptions'!$D$10)+J41*'Key Assumptions'!$B$30+'Key Assumptions'!$B$29)*(1-'Key Assumptions'!$B$27)+(ROUND('Key Assumptions'!$B$17*'Key Assumptions'!$B$10,0)*'Key Assumptions'!$B$24+J41*'Key Assumptions'!$B$26*'Key Assumptions'!$B$25)-((J41*('Key Assumptions'!$B$21*IF(9>='Key Assumptions'!$B$22,1+'Key Assumptions'!$B$23,1)*'Key Assumptions'!$D$10)+J41*'Key Assumptions'!$B$30+'Key Assumptions'!$B$29)+(ROUND('Key Assumptions'!$B$17*'Key Assumptions'!$B$10,0)*'Key Assumptions'!$B$24+J41*'Key Assumptions'!$B$26*'Key Assumptions'!$B$25))*'Key Assumptions'!$B$28 -> 350590.4 | K42: =(K41*('Key Assumptions'!$B$21*IF(10>='Key Assumptions'!$B$22,1+'Key Assumptions'!$B$23,1)*'Key Assumptions'!$D$10)+K41*'Key Assumptions'!$B$30+'Key Assumptions'!$B$29)*(1-'Key Assumptions'!$B$27)+(ROUND('Key Assumptions'!$B$17*'Key Assumptions'!$B$10,0)*'Key Assumptions'!$B$24+K41*'Key Assumptions'!$B$26*'Key Assumptions'!$B$25)-((K41*('Key Assumptions'!$B$21*IF(10>='Key Assumptions'!$B$22,1+'Key Assumptions'!$B$23,1)*'Key Assumptions'!$D$10)+K41*'Key Assumptions'!$B$30+'Key Assumptions'!$B$29)+(ROUND('Key Assumptions'!$B$17*'Key Assumptions'!$B$10,0)*'Key Assumptions'!$B$24+K41*'Key Assumptions'!$B$26*'Key Assumptions'!$B$25))*'Key Assumptions'!$B$28 -> 352004.25 | L42: =(L41*('Key Assumptions'!$B$21*IF(11>='Key Assumptions'!$B$22,1+'Key Assumptions'!$B$23,1)*'Key Assumptions'!$D$10)+L41*'Key Assumptions'!$B$30+'Key Assumptions'!$B$29)*(1-'Key Assumptions'!$B$27)+(ROUND('Key Assumptions'!$B$17*'Key Assumptions'!$B$10,0)*'Key Assumptions'!$B$24+L41*'Key Assumptions'!$B$26*'Key Assumptions'!$B$25)-((L41*('Key Assumptions'!$B$21*IF(11>='Key Assumptions'!$B$22,1+'Key Assumptions'!$B$23,1)*'Key Assumptions'!$D$10)+L41*'Key Assumptions'!$B$30+'Key Assumptions'!$B$29)+(ROUND('Key Assumptions'!$B$17*'Key Assumptions'!$B$10,0)*'Key Assumptions'!$B$24+L41*'Key Assumptions'!$B$26*'Key Assumptions'!$B$25))*'Key Assumptions'!$B$28 -> 353418.11 | M42: =(M41*('Key Assumptions'!$B$21*IF(12>='Key Assumptions'!$B$22,1+'Key Assumptions'!$B$23,1)*'Key Assumptions'!$D$10)+M41*'Key Assumptions'!$B$30+'Key Assumptions'!$B$29)*(1-'Key Assumptions'!$B$27)+(ROUND('Key Assumptions'!$B$17*'Key Assumptions'!$B$10,0)*'Key Assumptions'!$B$24+M41*'Key Assumptions'!$B$26*'Key Assumptions'!$B$25)-((M41*('Key Assumptions'!$B$21*IF(12>='Key Assumptions'!$B$22,1+'Key Assumptions'!$B$23,1)*'Key Assumptions'!$D$10)+M41*'Key Assumptions'!$B$30+'Key Assumptions'!$B$29)+(ROUND('Key Assumptions'!$B$17*'Key Assumptions'!$B$10,0)*'Key Assumptions'!$B$24+M41*'Key Assumptions'!$B$26*'Key Assumptions'!$B$25))*'Key Assumptions'!$B$28 -> 354831.97 | N42: =SUM(B42:M42) -> 4106862.3
A43: Business beginning cust | B43: ='Key Assumptions'!$B$35 -> 249 | C43: =B44 -> 253 | D43: =C44 -> 257 | E43: =D44 -> 261 | F43: =E44 -> 265 | G43: =F44 -> 269 | H43: =G44 -> 273 | I43: =H44 -> 277 | J43: =I44 -> 281 | ... M43: =L44 -> 293
A44: Business ending cust | B44: =MAX(0,B43+ROUND(('Key Assumptions'!$B$36+'Key Assumptions'!$B$37)*'Key Assumptions'!$E$10,0)+'Key Assumptions'!$B$40-ROUND(B43*'Key Assumptions'!$B$38*'Key Assumptions'!$F$10,0)-'Key Assumptions'!$B$39) -> 253 | C44: =MAX(0,C43+ROUND(('Key Assumptions'!$B$36+'Key Assumptions'!$B$37)*'Key Assumptions'!$E$10,0)+'Key Assumptions'!$B$40-ROUND(C43*'Key Assumptions'!$B$38*'Key Assumptions'!$F$10,0)-'Key Assumptions'!$B$39) -> 257 | D44: =MAX(0,D43+ROUND(('Key Assumptions'!$B$36+'Key Assumptions'!$B$37)*'Key Assumptions'!$E$10,0)+'Key Assumptions'!$B$40-ROUND(D43*'Key Assumptions'!$B$38*'Key Assumptions'!$F$10,0)-'Key Assumptions'!$B$39) -> 261 | E44: =MAX(0,E43+ROUND(('Key Assumptions'!$B$36+'Key Assumptions'!$B$37)*'Key Assumptions'!$E$10,0)+'Key Assumptions'!$B$40-ROUND(E43*'Key Assumptions'!$B$38*'Key Assumptions'!$F$10,0)-'Key Assumptions'!$B$39) -> 265 | F44: =MAX(0,F43+ROUND(('Key Assumptions'!$B$36+'Key Assumptions'!$B$37)*'Key Assumptions'!$E$10,0)+'Key Assumptions'!$B$40-ROUND(F43*'Key Assumptions'!$B$38*'Key Assumptions'!$F$10,0)-'Key Assumptions'!$B$39) -> 269 | G44: =MAX(0,G43+ROUND(('Key Assumptions'!$B$36+'Key Assumptions'!$B$37)*'Key Assumptions'!$E$10,0)+'Key Assumptions'!$B$40-ROUND(G43*'Key Assumptions'!$B$38*'Key Assumptions'!$F$10,0)-'Key Assumptions'!$B$39) -> 273 | H44: =MAX(0,H43+ROUND(('Key Assumptions'!$B$36+'Key Assumptions'!$B$37)*'Key Assumptions'!$E$10,0)+'Key Assumptions'!$B$40-ROUND(H43*'Key Assumptions'!$B$38*'Key Assumptions'!$F$10,0)-'Key Assumptions'!$B$39) -> 277 | I44: =MAX(0,I43+ROUND(('Key Assumptions'!$B$36+'Key Assumptions'!$B$37)*'Key Assumptions'!$E$10,0)+'Key Assumptions'!$B$40-ROUND(I43*'Key Assumptions'!$B$38*'Key Assumptions'!$F$10,0)-'Key Assumptions'!$B$39) -> 281 | ... M44: =MAX(0,M43+ROUND(('Key Assumptions'!$B$36+'Key Assumptions'!$B$37)*'Key Assumptions'!$E$10,0)+'Key Assumptions'!$B$40-ROUND(M43*'Key Assumptions'!$B$38*'Key Assumptions'!$F$10,0)-'Key Assumptions'!$B$39) -> 297
A45: Business avg cust | B45: =(B43+B44)/2 -> 251 | C45: =(C43+C44)/2 -> 255 | D45: =(D43+D44)/2 -> 259 | E45: =(E43+E44)/2 -> 263 | F45: =(F43+F44)/2 -> 267 | G45: =(G43+G44)/2 -> 271 | H45: =(H43+H44)/2 -> 275 | I45: =(I43+I44)/2 -> 279 | ... M45: =(M43+M44)/2 -> 295
A46: Enterprise beginning | B46: ='Key Assumptions'!$B$57 -> 0 | C46: =B47 -> 1 | D46: =C47 -> 2 | E46: =D47 -> 3 | F46: =E47 -> 4 | G46: =F47 -> 5 | H46: =G47 -> 6 | I46: =H47 -> 7 | J46: =I47 -> 8 | ... M46: =L47 -> 11
A47: Enterprise ending | B47: =MAX(0,B46+ROUND('Key Assumptions'!$B$37*'Key Assumptions'!$E$10,0)-ROUND(B46*'Key Assumptions'!$B$38*'Key Assumptions'!$F$10,0)) -> 1 | C47: =MAX(0,C46+ROUND('Key Assumptions'!$B$37*'Key Assumptions'!$E$10,0)-ROUND(C46*'Key Assumptions'!$B$38*'Key Assumptions'!$F$10,0)) -> 2 | D47: =MAX(0,D46+ROUND('Key Assumptions'!$B$37*'Key Assumptions'!$E$10,0)-ROUND(D46*'Key Assumptions'!$B$38*'Key Assumptions'!$F$10,0)) -> 3 | E47: =MAX(0,E46+ROUND('Key Assumptions'!$B$37*'Key Assumptions'!$E$10,0)-ROUND(E46*'Key Assumptions'!$B$38*'Key Assumptions'!$F$10,0)) -> 4 | F47: =MAX(0,F46+ROUND('Key Assumptions'!$B$37*'Key Assumptions'!$E$10,0)-ROUND(F46*'Key Assumptions'!$B$38*'Key Assumptions'!$F$10,0)) -> 5 | G47: =MAX(0,G46+ROUND('Key Assumptions'!$B$37*'Key Assumptions'!$E$10,0)-ROUND(G46*'Key Assumptions'!$B$38*'Key Assumptions'!$F$10,0)) -> 6 | H47: =MAX(0,H46+ROUND('Key Assumptions'!$B$37*'Key Assumptions'!$E$10,0)-ROUND(H46*'Key Assumptions'!$B$38*'Key Assumptions'!$F$10,0)) -> 7 | I47: =MAX(0,I46+ROUND('Key Assumptions'!$B$37*'Key Assumptions'!$E$10,0)-ROUND(I46*'Key Assumptions'!$B$38*'Key Assumptions'!$F$10,0)) -> 8 | ... M47: =MAX(0,M46+ROUND('Key Assumptions'!$B$37*'Key Assumptions'!$E$10,0)-ROUND(M46*'Key Assumptions'!$B$38*'Key Assumptions'!$F$10,0)) -> 12
A48: Enterprise avg | B48: =(B46+B47)/2 -> 0.5 | C48: =(C46+C47)/2 -> 1.5 | D48: =(D46+D47)/2 -> 2.5 | E48: =(E46+E47)/2 -> 3.5 | F48: =(F46+F47)/2 -> 4.5 | G48: =(G46+G47)/2 -> 5.5 | H48: =(H46+H47)/2 -> 6.5 | I48: =(I46+I47)/2 -> 7.5 | ... M48: =(M46+M47)/2 -> 11.5
A49: Business net revenue | B49: =(B45*('Key Assumptions'!$B$41*IF(1>='Key Assumptions'!$B$42,1+'Key Assumptions'!$B$43,1)*'Key Assumptions'!$G$10)+B45*('Key Assumptions'!$B$45+'Key Assumptions'!$B$46+'Key Assumptions'!$B$47+'Key Assumptions'!$B$49)+B48*'Key Assumptions'!$B$48)*(1-'Key Assumptions'!$B$54)+(ROUND(('Key Assumptions'!$B$36+'Key Assumptions'!$B$37)*'Key Assumptions'!$E$10,0)*('Key Assumptions'!$B$44+'Key Assumptions'!$B$50+'Key Assumptions'!$B$51)+'Key Assumptions'!$B$52+'Key Assumptions'!$B$53)-((B45*('Key Assumptions'!$B$41*IF(1>='Key Assumptions'!$B$42,1+'Key Assumptions'!$B$43,1)*'Key Assumptions'!$G$10)+B45*('Key Assumptions'!$B$45+'Key Assumptions'!$B$46+'Key Assumptions'!$B$47+'Key Assumptions'!$B$49)+B48*'Key Assumptions'!$B$48)+(ROUND(('Key Assumptions'!$B$36+'Key Assumptions'!$B$37)*'Key Assumptions'!$E$10,0)*('Key Assumptions'!$B$44+'Key Assumptions'!$B$50+'Key Assumptions'!$B$51)+'Key Assumptions'!$B$52+'Key Assumptions'!$B$53))*'Key Assumptions'!$B$55 -> 46955.884 | C49: =(C45*('Key Assumptions'!$B$41*IF(2>='Key Assumptions'!$B$42,1+'Key Assumptions'!$B$43,1)*'Key Assumptions'!$G$10)+C45*('Key Assumptions'!$B$45+'Key Assumptions'!$B$46+'Key Assumptions'!$B$47+'Key Assumptions'!$B$49)+C48*'Key Assumptions'!$B$48)*(1-'Key Assumptions'!$B$54)+(ROUND(('Key Assumptions'!$B$36+'Key Assumptions'!$B$37)*'Key Assumptions'!$E$10,0)*('Key Assumptions'!$B$44+'Key Assumptions'!$B$50+'Key Assumptions'!$B$51)+'Key Assumptions'!$B$52+'Key Assumptions'!$B$53)-((C45*('Key Assumptions'!$B$41*IF(2>='Key Assumptions'!$B$42,1+'Key Assumptions'!$B$43,1)*'Key Assumptions'!$G$10)+C45*('Key Assumptions'!$B$45+'Key Assumptions'!$B$46+'Key Assumptions'!$B$47+'Key Assumptions'!$B$49)+C48*'Key Assumptions'!$B$48)+(ROUND(('Key Assumptions'!$B$36+'Key Assumptions'!$B$37)*'Key Assumptions'!$E$10,0)*('Key Assumptions'!$B$44+'Key Assumptions'!$B$50+'Key Assumptions'!$B$51)+'Key Assumptions'!$B$52+'Key Assumptions'!$B$53))*'Key Assumptions'!$B$55 -> 47592.169 | D49: =(D45*('Key Assumptions'!$B$41*IF(3>='Key Assumptions'!$B$42,1+'Key Assumptions'!$B$43,1)*'Key Assumptions'!$G$10)+D45*('Key Assumptions'!$B$45+'Key Assumptions'!$B$46+'Key Assumptions'!$B$47+'Key Assumptions'!$B$49)+D48*'Key Assumptions'!$B$48)*(1-'Key Assumptions'!$B$54)+(ROUND(('Key Assumptions'!$B$36+'Key Assumptions'!$B$37)*'Key Assumptions'!$E$10,0)*('Key Assumptions'!$B$44+'Key Assumptions'!$B$50+'Key Assumptions'!$B$51)+'Key Assumptions'!$B$52+'Key Assumptions'!$B$53)-((D45*('Key Assumptions'!$B$41*IF(3>='Key Assumptions'!$B$42,1+'Key Assumptions'!$B$43,1)*'Key Assumptions'!$G$10)+D45*('Key Assumptions'!$B$45+'Key Assumptions'!$B$46+'Key Assumptions'!$B$47+'Key Assumptions'!$B$49)+D48*'Key Assumptions'!$B$48)+(ROUND(('Key Assumptions'!$B$36+'Key Assumptions'!$B$37)*'Key Assumptions'!$E$10,0)*('Key Assumptions'!$B$44+'Key Assumptions'!$B$50+'Key Assumptions'!$B$51)+'Key Assumptions'!$B$52+'Key Assumptions'!$B$53))*'Key Assumptions'!$B$55 -> 48228.454 | E49: =(E45*('Key Assumptions'!$B$41*IF(4>='Key Assumptions'!$B$42,1+'Key Assumptions'!$B$43,1)*'Key Assumptions'!$G$10)+E45*('Key Assumptions'!$B$45+'Key Assumptions'!$B$46+'Key Assumptions'!$B$47+'Key Assumptions'!$B$49)+E48*'Key Assumptions'!$B$48)*(1-'Key Assumptions'!$B$54)+(ROUND(('Key Assumptions'!$B$36+'Key Assumptions'!$B$37)*'Key Assumptions'!$E$10,0)*('Key Assumptions'!$B$44+'Key Assumptions'!$B$50+'Key Assumptions'!$B$51)+'Key Assumptions'!$B$52+'Key Assumptions'!$B$53)-((E45*('Key Assumptions'!$B$41*IF(4>='Key Assumptions'!$B$42,1+'Key Assumptions'!$B$43,1)*'Key Assumptions'!$G$10)+E45*('Key Assumptions'!$B$45+'Key Assumptions'!$B$46+'Key Assumptions'!$B$47+'Key Assumptions'!$B$49)+E48*'Key Assumptions'!$B$48)+(ROUND(('Key Assumptions'!$B$36+'Key Assumptions'!$B$37)*'Key Assumptions'!$E$10,0)*('Key Assumptions'!$B$44+'Key Assumptions'!$B$50+'Key Assumptions'!$B$51)+'Key Assumptions'!$B$52+'Key Assumptions'!$B$53))*'Key Assumptions'!$B$55 -> 48864.739 | F49: =(F45*('Key Assumptions'!$B$41*IF(5>='Key Assumptions'!$B$42,1+'Key Assumptions'!$B$43,1)*'Key Assumptions'!$G$10)+F45*('Key Assumptions'!$B$45+'Key Assumptions'!$B$46+'Key Assumptions'!$B$47+'Key Assumptions'!$B$49)+F48*'Key Assumptions'!$B$48)*(1-'Key Assumptions'!$B$54)+(ROUND(('Key Assumptions'!$B$36+'Key Assumptions'!$B$37)*'Key Assumptions'!$E$10,0)*('Key Assumptions'!$B$44+'Key Assumptions'!$B$50+'Key Assumptions'!$B$51)+'Key Assumptions'!$B$52+'Key Assumptions'!$B$53)-((F45*('Key Assumptions'!$B$41*IF(5>='Key Assumptions'!$B$42,1+'Key Assumptions'!$B$43,1)*'Key Assumptions'!$G$10)+F45*('Key Assumptions'!$B$45+'Key Assumptions'!$B$46+'Key Assumptions'!$B$47+'Key Assumptions'!$B$49)+F48*'Key Assumptions'!$B$48)+(ROUND(('Key Assumptions'!$B$36+'Key Assumptions'!$B$37)*'Key Assumptions'!$E$10,0)*('Key Assumptions'!$B$44+'Key Assumptions'!$B$50+'Key Assumptions'!$B$51)+'Key Assumptions'!$B$52+'Key Assumptions'!$B$53))*'Key Assumptions'!$B$55 -> 49501.024 | G49: =(G45*('Key Assumptions'!$B$41*IF(6>='Key Assumptions'!$B$42,1+'Key Assumptions'!$B$43,1)*'Key Assumptions'!$G$10)+G45*('Key Assumptions'!$B$45+'Key Assumptions'!$B$46+'Key Assumptions'!$B$47+'Key Assumptions'!$B$49)+G48*'Key Assumptions'!$B$48)*(1-'Key Assumptions'!$B$54)+(ROUND(('Key Assumptions'!$B$36+'Key Assumptions'!$B$37)*'Key Assumptions'!$E$10,0)*('Key Assumptions'!$B$44+'Key Assumptions'!$B$50+'Key Assumptions'!$B$51)+'Key Assumptions'!$B$52+'Key Assumptions'!$B$53)-((G45*('Key Assumptions'!$B$41*IF(6>='Key Assumptions'!$B$42,1+'Key Assumptions'!$B$43,1)*'Key Assumptions'!$G$10)+G45*('Key Assumptions'!$B$45+'Key Assumptions'!$B$46+'Key Assumptions'!$B$47+'Key Assumptions'!$B$49)+G48*'Key Assumptions'!$B$48)+(ROUND(('Key Assumptions'!$B$36+'Key Assumptions'!$B$37)*'Key Assumptions'!$E$10,0)*('Key Assumptions'!$B$44+'Key Assumptions'!$B$50+'Key Assumptions'!$B$51)+'Key Assumptions'!$B$52+'Key Assumptions'!$B$53))*'Key Assumptions'!$B$55 -> 50137.309 | H49: =(H45*('Key Assumptions'!$B$41*IF(7>='Key Assumptions'!$B$42,1+'Key Assumptions'!$B$43,1)*'Key Assumptions'!$G$10)+H45*('Key Assumptions'!$B$45+'Key Assumptions'!$B$46+'Key Assumptions'!$B$47+'Key Assumptions'!$B$49)+H48*'Key Assumptions'!$B$48)*(1-'Key Assumptions'!$B$54)+(ROUND(('Key Assumptions'!$B$36+'Key Assumptions'!$B$37)*'Key Assumptions'!$E$10,0)*('Key Assumptions'!$B$44+'Key Assumptions'!$B$50+'Key Assumptions'!$B$51)+'Key Assumptions'!$B$52+'Key Assumptions'!$B$53)-((H45*('Key Assumptions'!$B$41*IF(7>='Key Assumptions'!$B$42,1+'Key Assumptions'!$B$43,1)*'Key Assumptions'!$G$10)+H45*('Key Assumptions'!$B$45+'Key Assumptions'!$B$46+'Key Assumptions'!$B$47+'Key Assumptions'!$B$49)+H48*'Key Assumptions'!$B$48)+(ROUND(('Key Assumptions'!$B$36+'Key Assumptions'!$B$37)*'Key Assumptions'!$E$10,0)*('Key Assumptions'!$B$44+'Key Assumptions'!$B$50+'Key Assumptions'!$B$51)+'Key Assumptions'!$B$52+'Key Assumptions'!$B$53))*'Key Assumptions'!$B$55 -> 52008.068 | I49: =(I45*('Key Assumptions'!$B$41*IF(8>='Key Assumptions'!$B$42,1+'Key Assumptions'!$B$43,1)*'Key Assumptions'!$G$10)+I45*('Key Assumptions'!$B$45+'Key Assumptions'!$B$46+'Key Assumptions'!$B$47+'Key Assumptions'!$B$49)+I48*'Key Assumptions'!$B$48)*(1-'Key Assumptions'!$B$54)+(ROUND(('Key Assumptions'!$B$36+'Key Assumptions'!$B$37)*'Key Assumptions'!$E$10,0)*('Key Assumptions'!$B$44+'Key Assumptions'!$B$50+'Key Assumptions'!$B$51)+'Key Assumptions'!$B$52+'Key Assumptions'!$B$53)-((I45*('Key Assumptions'!$B$41*IF(8>='Key Assumptions'!$B$42,1+'Key Assumptions'!$B$43,1)*'Key Assumptions'!$G$10)+I45*('Key Assumptions'!$B$45+'Key Assumptions'!$B$46+'Key Assumptions'!$B$47+'Key Assumptions'!$B$49)+I48*'Key Assumptions'!$B$48)+(ROUND(('Key Assumptions'!$B$36+'Key Assumptions'!$B$37)*'Key Assumptions'!$E$10,0)*('Key Assumptions'!$B$44+'Key Assumptions'!$B$50+'Key Assumptions'!$B$51)+'Key Assumptions'!$B$52+'Key Assumptions'!$B$53))*'Key Assumptions'!$B$55 -> 52662.309 | J49: =(J45*('Key Assumptions'!$B$41*IF(9>='Key Assumptions'!$B$42,1+'Key Assumptions'!$B$43,1)*'Key Assumptions'!$G$10)+J45*('Key Assumptions'!$B$45+'Key Assumptions'!$B$46+'Key Assumptions'!$B$47+'Key Assumptions'!$B$49)+J48*'Key Assumptions'!$B$48)*(1-'Key Assumptions'!$B$54)+(ROUND(('Key Assumptions'!$B$36+'Key Assumptions'!$B$37)*'Key Assumptions'!$E$10,0)*('Key Assumptions'!$B$44+'Key Assumptions'!$B$50+'Key Assumptions'!$B$51)+'Key Assumptions'!$B$52+'Key Assumptions'!$B$53)-((J45*('Key Assumptions'!$B$41*IF(9>='Key Assumptions'!$B$42,1+'Key Assumptions'!$B$43,1)*'Key Assumptions'!$G$10)+J45*('Key Assumptions'!$B$45+'Key Assumptions'!$B$46+'Key Assumptions'!$B$47+'Key Assumptions'!$B$49)+J48*'Key Assumptions'!$B$48)+(ROUND(('Key Assumptions'!$B$36+'Key Assumptions'!$B$37)*'Key Assumptions'!$E$10,0)*('Key Assumptions'!$B$44+'Key Assumptions'!$B$50+'Key Assumptions'!$B$51)+'Key Assumptions'!$B$52+'Key Assumptions'!$B$53))*'Key Assumptions'!$B$55 -> 53316.55 | K49: =(K45*('Key Assumptions'!$B$41*IF(10>='Key Assumptions'!$B$42,1+'Key Assumptions'!$B$43,1)*'Key Assumptions'!$G$10)+K45*('Key Assumptions'!$B$45+'Key Assumptions'!$B$46+'Key Assumptions'!$B$47+'Key Assumptions'!$B$49)+K48*'Key Assumptions'!$B$48)*(1-'Key Assumptions'!$B$54)+(ROUND(('Key Assumptions'!$B$36+'Key Assumptions'!$B$37)*'Key Assumptions'!$E$10,0)*('Key Assumptions'!$B$44+'Key Assumptions'!$B$50+'Key Assumptions'!$B$51)+'Key Assumptions'!$B$52+'Key Assumptions'!$B$53)-((K45*('Key Assumptions'!$B$41*IF(10>='Key Assumptions'!$B$42,1+'Key Assumptions'!$B$43,1)*'Key Assumptions'!$G$10)+K45*('Key Assumptions'!$B$45+'Key Assumptions'!$B$46+'Key Assumptions'!$B$47+'Key Assumptions'!$B$49)+K48*'Key Assumptions'!$B$48)+(ROUND(('Key Assumptions'!$B$36+'Key Assumptions'!$B$37)*'Key Assumptions'!$E$10,0)*('Key Assumptions'!$B$44+'Key Assumptions'!$B$50+'Key Assumptions'!$B$51)+'Key Assumptions'!$B$52+'Key Assumptions'!$B$53))*'Key Assumptions'!$B$55 -> 53970.791 | L49: =(L45*('Key Assumptions'!$B$41*IF(11>='Key Assumptions'!$B$42,1+'Key Assumptions'!$B$43,1)*'Key Assumptions'!$G$10)+L45*('Key Assumptions'!$B$45+'Key Assumptions'!$B$46+'Key Assumptions'!$B$47+'Key Assumptions'!$B$49)+L48*'Key Assumptions'!$B$48)*(1-'Key Assumptions'!$B$54)+(ROUND(('Key Assumptions'!$B$36+'Key Assumptions'!$B$37)*'Key Assumptions'!$E$10,0)*('Key Assumptions'!$B$44+'Key Assumptions'!$B$50+'Key Assumptions'!$B$51)+'Key Assumptions'!$B$52+'Key Assumptions'!$B$53)-((L45*('Key Assumptions'!$B$41*IF(11>='Key Assumptions'!$B$42,1+'Key Assumptions'!$B$43,1)*'Key Assumptions'!$G$10)+L45*('Key Assumptions'!$B$45+'Key Assumptions'!$B$46+'Key Assumptions'!$B$47+'Key Assumptions'!$B$49)+L48*'Key Assumptions'!$B$48)+(ROUND(('Key Assumptions'!$B$36+'Key Assumptions'!$B$37)*'Key Assumptions'!$E$10,0)*('Key Assumptions'!$B$44+'Key Assumptions'!$B$50+'Key Assumptions'!$B$51)+'Key Assumptions'!$B$52+'Key Assumptions'!$B$53))*'Key Assumptions'!$B$55 -> 54625.032 | M49: =(M45*('Key Assumptions'!$B$41*IF(12>='Key Assumptions'!$B$42,1+'Key Assumptions'!$B$43,1)*'Key Assumptions'!$G$10)+M45*('Key Assumptions'!$B$45+'Key Assumptions'!$B$46+'Key Assumptions'!$B$47+'Key Assumptions'!$B$49)+M48*'Key Assumptions'!$B$48)*(1-'Key Assumptions'!$B$54)+(ROUND(('Key Assumptions'!$B$36+'Key Assumptions'!$B$37)*'Key Assumptions'!$E$10,0)*('Key Assumptions'!$B$44+'Key Assumptions'!$B$50+'Key Assumptions'!$B$51)+'Key Assumptions'!$B$52+'Key Assumptions'!$B$53)-((M45*('Key Assumptions'!$B$41*IF(12>='Key Assumptions'!$B$42,1+'Key Assumptions'!$B$43,1)*'Key Assumptions'!$G$10)+M45*('Key Assumptions'!$B$45+'Key Assumptions'!$B$46+'Key Assumptions'!$B$47+'Key Assumptions'!$B$49)+M48*'Key Assumptions'!$B$48)+(ROUND(('Key Assumptions'!$B$36+'Key Assumptions'!$B$37)*'Key Assumptions'!$E$10,0)*('Key Assumptions'!$B$44+'Key Assumptions'!$B$50+'Key Assumptions'!$B$51)+'Key Assumptions'!$B$52+'Key Assumptions'!$B$53))*'Key Assumptions'!$B$55 -> 55279.273 | N49: =SUM(B49:M49) -> 613141.6
A50: Dark fiber net revenue | B50: ='Dark Fiber Forecast'!Q43*'Key Assumptions'!$H$10 -> 1754.5 | C50: ='Dark Fiber Forecast'!R43*'Key Assumptions'!$H$10 -> 1754.5 | D50: ='Dark Fiber Forecast'!S43*'Key Assumptions'!$H$10 -> 1754.5 | E50: ='Dark Fiber Forecast'!T43*'Key Assumptions'!$H$10 -> 1754.5 | F50: ='Dark Fiber Forecast'!U43*'Key Assumptions'!$H$10 -> 1754.5 | G50: ='Dark Fiber Forecast'!V43*'Key Assumptions'!$H$10 -> 1754.5 | H50: ='Dark Fiber Forecast'!W43*'Key Assumptions'!$H$10 -> 1754.5 | I50: ='Dark Fiber Forecast'!X43*'Key Assumptions'!$H$10 -> 1754.5 | ... M50: ='Dark Fiber Forecast'!AB43*'Key Assumptions'!$H$10 -> 1754.5 | N50: =SUM(B50:M50) -> 21054
A51: TOTAL NET REVENUE | B51: =B42+B49+B50+IF(1>='Key Assumptions'!$B$94,'Key Assumptions'!$B$93,0) -> 435125.25 | C51: =C42+C49+C50+IF(2>='Key Assumptions'!$B$94,'Key Assumptions'!$B$93,0) -> 437288.13 | D51: =D42+D49+D50+IF(3>='Key Assumptions'!$B$94,'Key Assumptions'!$B$93,0) -> 439451 | E51: =E42+E49+E50+IF(4>='Key Assumptions'!$B$94,'Key Assumptions'!$B$93,0) -> 441613.88 | F51: =F42+F49+F50+IF(5>='Key Assumptions'!$B$94,'Key Assumptions'!$B$93,0) -> 443738.59 | G51: =G42+G49+G50+IF(6>='Key Assumptions'!$B$94,'Key Assumptions'!$B$93,0) -> 445825.14 | H51: =H42+H49+H50+IF(7>='Key Assumptions'!$B$94,'Key Assumptions'!$B$93,0) -> 458407.43 | I51: =I42+I49+I50+IF(8>='Key Assumptions'!$B$94,'Key Assumptions'!$B$93,0) -> 460554.07 | J51: =J42+J49+J50+IF(9>='Key Assumptions'!$B$94,'Key Assumptions'!$B$93,0) -> 462661.45 | K51: =K42+K49+K50+IF(10>='Key Assumptions'!$B$94,'Key Assumptions'!$B$93,0) -> 464729.54 | L51: =L42+L49+L50+IF(11>='Key Assumptions'!$B$94,'Key Assumptions'!$B$93,0) -> 466797.64 | M51: =M42+M49+M50+IF(12>='Key Assumptions'!$B$94,'Key Assumptions'!$B$93,0) -> 468865.74 | N51: =SUM(B51:M51) -> 5425057.9
A54: SCENARIO COMPARISON — ANNUAL NET REVENUE
A55: Scenario | B55: Annual Net Revenue | C55: vs Base
A56: Conservative | B56: =N19 -> 4901645.2 | C56: =IFERROR(N19/N35-1,0) -> -0.050544278
A57: Base | B57: =N35 -> 5162584.3 | C57: =IFERROR(N35/N35-1,0) -> 0
A58: Aggressive | B58: =N51 -> 5425057.9 | C58: =IFERROR(N51/N35-1,0) -> 0.050841508

Sheet Annual Summary
A1: ANNUAL SUMMARY — RIVR Tech 2027
A2: Management summary. All values link to the forecast tabs (active scenario).
A4: Total 2027 revenue | B4: ='Consolidated Revenue'!N33 -> 5162584.3 | D4: Ending residential subscribers | E4: ='Residential Forecast'!M12 -> 4072
A5: Residential revenue | B5: ='Consolidated Revenue'!N10 -> 3891845.9 | D5: Ending business customers | E5: ='Business Forecast'!M13 -> 274
A6: Business revenue | B6: ='Consolidated Revenue'!N16 -> 567598.38 | D6: Residential net additions | E6: ='Residential Forecast'!M12-'Residential Forecast'!B6 -> 24
A7: Dark fiber revenue | B7: ='Consolidated Revenue'!N23 -> 19140 | D7: Business net additions | E7: ='Business Forecast'!M13-'Business Forecast'!B6 -> 25
A8: Total recurring revenue | B8: ='Consolidated Revenue'!N29 -> 5123738.7 | D8: Average residential ARPU | E8: ='Residential Forecast'!N28 -> 75.11
A9: Total one-time revenue | B9: ='Consolidated Revenue'!N30 -> 170640 | D9: Average business ARPU | E9: ='Business Forecast'!N39 -> 160.915
A10: IRU revenue recognized | B10: ='Consolidated Revenue'!N21 -> 0 | D10: Total dark fiber contract revenue | E10: ='Dark Fiber Forecast'!AC33 -> 19140
