Workbook

Sheet Budget Dashboard
A1: RIVR TECH — 2027 MASTER BUDGET DASHBOARD
A2: Revenue (forecast model) vs Expenses (CFO budget). Operating income, EBITDA, and net income after grants.
B4: TOTAL REVENUE | E4: TOTAL EXPENSES | H4: OPERATING INCOME (EBIT) | K4: EBITDA | N4: NET INCOME (after grants)
B5: ='Master Pro Forma'!N10 -> 7196939.9 | E5: ='Master Pro Forma'!N18 -> 7696812.4 | H5: ='Master Pro Forma'!N20 -> -499872.5 | K5: ='Master Pro Forma'!N23 -> -358997.5 | N5: ='Master Pro Forma'!N32 -> 658211.5
B7: EBIT MARGIN % | E7: NET MARGIN % | H7: GRANT + OTHER INCOME | K7: NEW POSITIONS COST | N7: NEW FTE (planned)
B8: =IFERROR('Master Pro Forma'!N20/'Master Pro Forma'!N10,0) -> -0.069456256 | E8: =IFERROR('Master Pro Forma'!N32/'Master Pro Forma'!N10,0) -> 0.091457135 | H8: ='Master Pro Forma'!N28 -> 1158084 | K8: ='Expense Budget'!S15 -> 714483.23 | N8: =COUNTA('New Positions'!A4:A11) -> 8
B38: Operating income is before grants; net income includes grant & nonoperating income. Toggle new positions on the Assumptions tab.
A40: chart data
A41: Residential | B41: ='Master Pro Forma'!N6 -> 5287699.9
A42: Business | B42: ='Master Pro Forma'!N7 -> 445239.97
A43: Dark Fiber | B43: ='Master Pro Forma'!N8 -> 780000
A44: Hoke County Project | B44: ='Master Pro Forma'!N9 -> 684000
A47: ='Master Pro Forma'!A13 -> Cost of Power / COGS | B47: ='Master Pro Forma'!N13 -> 637300
A48: ='Master Pro Forma'!A14 -> Fiber Network Operations | B48: ='Master Pro Forma'!N14 -> 4222706
A49: ='Master Pro Forma'!A15 -> New Positions (2027 staffing plan) | B49: ='Master Pro Forma'!N15 -> 714483.23
A50: ='Master Pro Forma'!A16 -> Sales, Marketing & Member Svc | B50: ='Master Pro Forma'!N16 -> 319054.13
A51: ='Master Pro Forma'!A17 -> General & Administrative | B51: ='Master Pro Forma'!N17 -> 1803269

Sheet Master Pro Forma
A1: MASTER PRO FORMA — Revenue & Expense Budget, 2027
A2: LREMC Technologies, LLC d/b/a RIVR Tech · Revenue from the forecast model · Expenses from the CFO budget · monthly, quarterly, full-year.
A3: $ (positive = income / cost as labeled) | B3: 46388 | C3: 46419 | D3: 46447 | E3: 46478 | F3: 46508 | G3: 46539 | H3: 46569 | I3: 46600 | J3: 46631 | K3: 46661 | L3: 46692 | M3: 46722 | N3: FY 2027 | O3: Q1 | P3: Q2 | Q3: Q3 | R3: Q4
A5: OPERATING REVENUE
A6: Residential | B6: ='Revenue Detail'!B4 -> 391456.45 | C6: ='Revenue Detail'!C4 -> 399431.69 | D6: ='Revenue Detail'!D4 -> 407342.36 | E6: ='Revenue Detail'!E4 -> 415188.46 | F6: ='Revenue Detail'!F4 -> 422969.97 | G6: ='Revenue Detail'!G4 -> 430686.91 | H6: ='Revenue Detail'!H4 -> 450800.48 | I6: ='Revenue Detail'!I4 -> 458610.51 | ... M6: ='Revenue Detail'!M4 -> 489185.98 | N6: =SUM(B6:M6) -> 5287699.9 | O6: =SUM(B6:D6) -> 1198230.5 | P6: =SUM(E6:G6) -> 1268845.3 | Q6: =SUM(H6:J6) -> 1375765.1 | R6: =SUM(K6:M6) -> 1444859
A7: Business | B7: ='Revenue Detail'!B5 -> 31836.57 | C7: ='Revenue Detail'!C5 -> 32700.2 | D7: ='Revenue Detail'!D5 -> 33563.83 | E7: ='Revenue Detail'!E5 -> 34427.46 | F7: ='Revenue Detail'!F5 -> 35291.09 | G7: ='Revenue Detail'!G5 -> 36154.72 | H7: ='Revenue Detail'!H5 -> 38045.81 | I7: ='Revenue Detail'!I5 -> 38933.41 | ... M7: ='Revenue Detail'!M5 -> 42241.74 | N7: =SUM(B7:M7) -> 445239.97 | O7: =SUM(B7:D7) -> 98100.6 | P7: =SUM(E7:G7) -> 105873.27 | Q7: =SUM(H7:J7) -> 116800.23 | R7: =SUM(K7:M7) -> 124465.87
A8: Dark Fiber | B8: ='Revenue Detail'!B6 -> 65000 | C8: ='Revenue Detail'!C6 -> 65000 | D8: ='Revenue Detail'!D6 -> 65000 | E8: ='Revenue Detail'!E6 -> 65000 | F8: ='Revenue Detail'!F6 -> 65000 | G8: ='Revenue Detail'!G6 -> 65000 | H8: ='Revenue Detail'!H6 -> 65000 | I8: ='Revenue Detail'!I6 -> 65000 | ... M8: ='Revenue Detail'!M6 -> 65000 | N8: =SUM(B8:M8) -> 780000 | O8: =SUM(B8:D8) -> 195000 | P8: =SUM(E8:G8) -> 195000 | Q8: =SUM(H8:J8) -> 195000 | R8: =SUM(K8:M8) -> 195000
A9: Hoke County Project | B9: ='Revenue Detail'!B7 -> 57000 | C9: ='Revenue Detail'!C7 -> 57000 | D9: ='Revenue Detail'!D7 -> 57000 | E9: ='Revenue Detail'!E7 -> 57000 | F9: ='Revenue Detail'!F7 -> 57000 | G9: ='Revenue Detail'!G7 -> 57000 | H9: ='Revenue Detail'!H7 -> 57000 | I9: ='Revenue Detail'!I7 -> 57000 | ... M9: ='Revenue Detail'!M7 -> 57000 | N9: =SUM(B9:M9) -> 684000 | O9: =SUM(B9:D9) -> 171000 | P9: =SUM(E9:G9) -> 171000 | Q9: =SUM(H9:J9) -> 171000 | R9: =SUM(K9:M9) -> 171000
A10: Total Operating Revenue | B10: ='Revenue Detail'!B8 -> 545293.02 | C10: ='Revenue Detail'!C8 -> 554131.89 | D10: ='Revenue Detail'!D8 -> 562906.19 | E10: ='Revenue Detail'!E8 -> 571615.92 | F10: ='Revenue Detail'!F8 -> 580261.06 | G10: ='Revenue Detail'!G8 -> 588841.63 | H10: ='Revenue Detail'!H8 -> 610846.29 | I10: ='Revenue Detail'!I8 -> 619543.92 | ... M10: ='Revenue Detail'!M8 -> 653427.72 | N10: =SUM(B10:M10) -> 7196939.9 | O10: =SUM(B10:D10) -> 1662331.1 | P10: =SUM(E10:G10) -> 1740718.6 | Q10: =SUM(H10:J10) -> 1858565.3 | R10: =SUM(K10:M10) -> 1935324.9
A12: OPERATING EXPENSES
A13: Cost of Power / COGS | B13: ='Expense Budget'!G4 -> 53108.333 | C13: ='Expense Budget'!H4 -> 53108.333 | D13: ='Expense Budget'!I4 -> 53108.333 | E13: ='Expense Budget'!J4 -> 53108.333 | F13: ='Expense Budget'!K4 -> 53108.333 | G13: ='Expense Budget'!L4 -> 53108.333 | H13: ='Expense Budget'!M4 -> 53108.333 | I13: ='Expense Budget'!N4 -> 53108.333 | ... M13: ='Expense Budget'!R4 -> 53108.333 | N13: =SUM(B13:M13) -> 637300 | O13: =SUM(B13:D13) -> 159325 | P13: =SUM(E13:G13) -> 159325 | Q13: =SUM(H13:J13) -> 159325 | R13: =SUM(K13:M13) -> 159325
A14: Fiber Network Operations | B14: ='Expense Budget'!G5 -> 351892.17 | C14: ='Expense Budget'!H5 -> 351892.17 | D14: ='Expense Budget'!I5 -> 351892.17 | E14: ='Expense Budget'!J5 -> 351892.17 | F14: ='Expense Budget'!K5 -> 351892.17 | G14: ='Expense Budget'!L5 -> 351892.17 | H14: ='Expense Budget'!M5 -> 351892.17 | I14: ='Expense Budget'!N5 -> 351892.17 | ... M14: ='Expense Budget'!R5 -> 351892.17 | N14: =SUM(B14:M14) -> 4222706 | O14: =SUM(B14:D14) -> 1055676.5 | P14: =SUM(E14:G14) -> 1055676.5 | Q14: =SUM(H14:J14) -> 1055676.5 | R14: =SUM(K14:M14) -> 1055676.5
A15: New Positions (2027 staffing plan) | B15: ='Expense Budget'!G15 -> 29883.33 | C15: ='Expense Budget'!H15 -> 35995.83 | D15: ='Expense Budget'!I15 -> 58136.66 | E15: ='Expense Budget'!J15 -> 65607.49 | F15: ='Expense Budget'!K15 -> 65607.49 | G15: ='Expense Budget'!L15 -> 65607.49 | H15: ='Expense Budget'!M15 -> 65607.49 | I15: ='Expense Budget'!N15 -> 65607.49 | ... M15: ='Expense Budget'!R15 -> 65607.49 | N15: =SUM(B15:M15) -> 714483.23 | O15: =SUM(B15:D15) -> 124015.82 | P15: =SUM(E15:G15) -> 196822.47 | Q15: =SUM(H15:J15) -> 196822.47 | R15: =SUM(K15:M15) -> 196822.47
A16: Sales, Marketing & Member Svc | B16: ='Expense Budget'!G7+'Expense Budget'!G8 -> 26587.844 | C16: ='Expense Budget'!H7+'Expense Budget'!H8 -> 26587.844 | D16: ='Expense Budget'!I7+'Expense Budget'!I8 -> 26587.844 | E16: ='Expense Budget'!J7+'Expense Budget'!J8 -> 26587.844 | F16: ='Expense Budget'!K7+'Expense Budget'!K8 -> 26587.844 | G16: ='Expense Budget'!L7+'Expense Budget'!L8 -> 26587.844 | H16: ='Expense Budget'!M7+'Expense Budget'!M8 -> 26587.844 | I16: ='Expense Budget'!N7+'Expense Budget'!N8 -> 26587.844 | ... M16: ='Expense Budget'!R7+'Expense Budget'!R8 -> 26587.844 | N16: =SUM(B16:M16) -> 319054.13 | O16: =SUM(B16:D16) -> 79763.533 | P16: =SUM(E16:G16) -> 79763.533 | Q16: =SUM(H16:J16) -> 79763.533 | R16: =SUM(K16:M16) -> 79763.533
A17: General & Administrative | B17: ='Expense Budget'!G6+'Expense Budget'!G9+'Expense Budget'!G10+'Expense Budget'!G11+'Expense Budget'!G12+'Expense Budget'!G13+'Expense Budget'!G14 -> 150272.42 | C17: ='Expense Budget'!H6+'Expense Budget'!H9+'Expense Budget'!H10+'Expense Budget'!H11+'Expense Budget'!H12+'Expense Budget'!H13+'Expense Budget'!H14 -> 150272.42 | D17: ='Expense Budget'!I6+'Expense Budget'!I9+'Expense Budget'!I10+'Expense Budget'!I11+'Expense Budget'!I12+'Expense Budget'!I13+'Expense Budget'!I14 -> 150272.42 | E17: ='Expense Budget'!J6+'Expense Budget'!J9+'Expense Budget'!J10+'Expense Budget'!J11+'Expense Budget'!J12+'Expense Budget'!J13+'Expense Budget'!J14 -> 150272.42 | F17: ='Expense Budget'!K6+'Expense Budget'!K9+'Expense Budget'!K10+'Expense Budget'!K11+'Expense Budget'!K12+'Expense Budget'!K13+'Expense Budget'!K14 -> 150272.42 | G17: ='Expense Budget'!L6+'Expense Budget'!L9+'Expense Budget'!L10+'Expense Budget'!L11+'Expense Budget'!L12+'Expense Budget'!L13+'Expense Budget'!L14 -> 150272.42 | H17: ='Expense Budget'!M6+'Expense Budget'!M9+'Expense Budget'!M10+'Expense Budget'!M11+'Expense Budget'!M12+'Expense Budget'!M13+'Expense Budget'!M14 -> 150272.42 | I17: ='Expense Budget'!N6+'Expense Budget'!N9+'Expense Budget'!N10+'Expense Budget'!N11+'Expense Budget'!N12+'Expense Budget'!N13+'Expense Budget'!N14 -> 150272.42 | ... M17: ='Expense Budget'!R6+'Expense Budget'!R9+'Expense Budget'!R10+'Expense Budget'!R11+'Expense Budget'!R12+'Expense Budget'!R13+'Expense Budget'!R14 -> 150272.42 | N17: =SUM(B17:M17) -> 1803269 | O17: =SUM(B17:D17) -> 450817.25 | P17: =SUM(E17:G17) -> 450817.25 | Q17: =SUM(H17:J17) -> 450817.25 | R17: =SUM(K17:M17) -> 450817.25
A18: Total Operating Expenses | B18: ='Expense Budget'!G16 -> 611744.09 | C18: ='Expense Budget'!H16 -> 617856.59 | D18: ='Expense Budget'!I16 -> 639997.42 | E18: ='Expense Budget'!J16 -> 647468.25 | F18: ='Expense Budget'!K16 -> 647468.25 | G18: ='Expense Budget'!L16 -> 647468.25 | H18: ='Expense Budget'!M16 -> 647468.25 | I18: ='Expense Budget'!N16 -> 647468.25 | ... M18: ='Expense Budget'!R16 -> 647468.25 | N18: =SUM(B18:M18) -> 7696812.4 | O18: =SUM(B18:D18) -> 1869598.1 | P18: =SUM(E18:G18) -> 1942404.8 | Q18: =SUM(H18:J18) -> 1942404.8 | R18: =SUM(K18:M18) -> 1942404.8
A20: OPERATING INCOME (EBIT) | B20: =B10-B18 -> -66451.071 | C20: =C10-C18 -> -63724.701 | D20: =D10-D18 -> -77091.231 | E20: =E10-E18 -> -75852.331 | F20: =F10-F18 -> -67207.191 | G20: =G10-G18 -> -58626.621 | H20: =H10-H18 -> -36621.961 | I20: =I10-I18 -> -27924.331 | ... M20: =M10-M18 -> 5959.4692 | N20: =SUM(B20:M20) -> -499872.5 | O20: =SUM(B20:D20) -> -207267 | P20: =SUM(E20:G20) -> -201686.14 | Q20: =SUM(H20:J20) -> -83839.452 | R20: =SUM(K20:M20) -> -7079.9025
A21: EBIT margin % | B21: =IFERROR(B20/B10,0) -> -0.12186305 | C21: =IFERROR(C20/C10,0) -> -0.11499916 | D21: =IFERROR(D20/D10,0) -> -0.13695218 | E21: =IFERROR(E20/E10,0) -> -0.13269807 | F21: =IFERROR(F20/F10,0) -> -0.11582233 | G21: =IFERROR(G20/G10,0) -> -0.099562629 | H21: =IFERROR(H20/H10,0) -> -0.059952825 | I21: =IFERROR(I20/I10,0) -> -0.045072399 | ... R21: =IFERROR(R20/R10,0) -> -0.0036582502
A22: Add back: depreciation & amortization | B22: ='Assumptions & Notes'!$B$8/12 -> 11739.583 | C22: ='Assumptions & Notes'!$B$8/12 -> 11739.583 | D22: ='Assumptions & Notes'!$B$8/12 -> 11739.583 | E22: ='Assumptions & Notes'!$B$8/12 -> 11739.583 | F22: ='Assumptions & Notes'!$B$8/12 -> 11739.583 | G22: ='Assumptions & Notes'!$B$8/12 -> 11739.583 | H22: ='Assumptions & Notes'!$B$8/12 -> 11739.583 | I22: ='Assumptions & Notes'!$B$8/12 -> 11739.583 | ... M22: ='Assumptions & Notes'!$B$8/12 -> 11739.583 | N22: =SUM(B22:M22) -> 140875 | O22: =SUM(B22:D22) -> 35218.75 | P22: =SUM(E22:G22) -> 35218.75 | Q22: =SUM(H22:J22) -> 35218.75 | R22: =SUM(K22:M22) -> 35218.75
A23: EBITDA | B23: =B20+B22 -> -54711.487 | C23: =C20+C22 -> -51985.117 | D23: =D20+D22 -> -65351.648 | E23: =E20+E22 -> -64112.747 | F23: =F20+F22 -> -55467.608 | G23: =G20+G22 -> -46887.038 | H23: =H20+H22 -> -24882.377 | I23: =I20+I22 -> -16184.747 | ... M23: =M20+M22 -> 17699.052 | N23: =SUM(B23:M23) -> -358997.5 | O23: =SUM(B23:D23) -> -172048.25 | P23: =SUM(E23:G23) -> -166467.39 | Q23: =SUM(H23:J23) -> -48620.702 | R23: =SUM(K23:M23) -> 28138.848
A25: OTHER INCOME (nonoperating)
A26: Grant income | B26: ='Assumptions & Notes'!$B$10/12 -> 65340 | C26: ='Assumptions & Notes'!$B$10/12 -> 65340 | D26: ='Assumptions & Notes'!$B$10/12 -> 65340 | E26: ='Assumptions & Notes'!$B$10/12 -> 65340 | F26: ='Assumptions & Notes'!$B$10/12 -> 65340 | G26: ='Assumptions & Notes'!$B$10/12 -> 65340 | H26: ='Assumptions & Notes'!$B$10/12 -> 65340 | I26: ='Assumptions & Notes'!$B$10/12 -> 65340 | ... M26: ='Assumptions & Notes'!$B$10/12 -> 65340 | N26: =SUM(B26:M26) -> 784080 | O26: =SUM(B26:D26) -> 196020 | P26: =SUM(E26:G26) -> 196020 | Q26: =SUM(H26:J26) -> 196020 | R26: =SUM(K26:M26) -> 196020
A27: Nonoperating income | B27: ='Assumptions & Notes'!$B$11/12 -> 31167 | C27: ='Assumptions & Notes'!$B$11/12 -> 31167 | D27: ='Assumptions & Notes'!$B$11/12 -> 31167 | E27: ='Assumptions & Notes'!$B$11/12 -> 31167 | F27: ='Assumptions & Notes'!$B$11/12 -> 31167 | G27: ='Assumptions & Notes'!$B$11/12 -> 31167 | H27: ='Assumptions & Notes'!$B$11/12 -> 31167 | I27: ='Assumptions & Notes'!$B$11/12 -> 31167 | ... M27: ='Assumptions & Notes'!$B$11/12 -> 31167 | N27: =SUM(B27:M27) -> 374004 | O27: =SUM(B27:D27) -> 93501 | P27: =SUM(E27:G27) -> 93501 | Q27: =SUM(H27:J27) -> 93501 | R27: =SUM(K27:M27) -> 93501
A28: Total other income | B28: =B26+B27 -> 96507 | C28: =C26+C27 -> 96507 | D28: =D26+D27 -> 96507 | E28: =E26+E27 -> 96507 | F28: =F26+F27 -> 96507 | G28: =G26+G27 -> 96507 | H28: =H26+H27 -> 96507 | I28: =I26+I27 -> 96507 | ... M28: =M26+M27 -> 96507 | N28: =SUM(B28:M28) -> 1158084 | O28: =SUM(B28:D28) -> 289521 | P28: =SUM(E28:G28) -> 289521 | Q28: =SUM(H28:J28) -> 289521 | R28: =SUM(K28:M28) -> 289521
A30: PRE-TAX INCOME | B30: =B20+B28 -> 30055.929 | C30: =C20+C28 -> 32782.299 | D30: =D20+D28 -> 19415.769 | E30: =E20+E28 -> 20654.669 | F30: =F20+F28 -> 29299.809 | G30: =G20+G28 -> 37880.379 | H30: =H20+H28 -> 59885.039 | I30: =I20+I28 -> 68582.669 | ... M30: =M20+M28 -> 102466.47 | N30: =SUM(B30:M30) -> 658211.5 | O30: =SUM(B30:D30) -> 82253.997 | P30: =SUM(E30:G30) -> 87834.857 | Q30: =SUM(H30:J30) -> 205681.55 | R30: =SUM(K30:M30) -> 282441.1
A31: Income tax | B31: =-'Assumptions & Notes'!$B$9*MAX(0,B30) -> 0 | C31: =-'Assumptions & Notes'!$B$9*MAX(0,C30) -> 0 | D31: =-'Assumptions & Notes'!$B$9*MAX(0,D30) -> 0 | E31: =-'Assumptions & Notes'!$B$9*MAX(0,E30) -> 0 | F31: =-'Assumptions & Notes'!$B$9*MAX(0,F30) -> 0 | G31: =-'Assumptions & Notes'!$B$9*MAX(0,G30) -> 0 | H31: =-'Assumptions & Notes'!$B$9*MAX(0,H30) -> 0 | I31: =-'Assumptions & Notes'!$B$9*MAX(0,I30) -> 0 | ... M31: =-'Assumptions & Notes'!$B$9*MAX(0,M30) -> 0 | N31: =SUM(B31:M31) -> 0 | O31: =SUM(B31:D31) -> 0 | P31: =SUM(E31:G31) -> 0 | Q31: =SUM(H31:J31) -> 0 | R31: =SUM(K31:M31) -> 0
A32: NET INCOME | B32: =B30+B31 -> 30055.929 | C32: =C30+C31 -> 32782.299 | D32: =D30+D31 -> 19415.769 | E32: =E30+E31 -> 20654.669 | F32: =F30+F31 -> 29299.809 | G32: =G30+G31 -> 37880.379 | H32: =H30+H31 -> 59885.039 | I32: =I30+I31 -> 68582.669 | ... M32: =M30+M31 -> 102466.47 | N32: =SUM(B32:M32) -> 658211.5 | O32: =SUM(B32:D32) -> 82253.997 | P32: =SUM(E32:G32) -> 87834.857 | Q32: =SUM(H32:J32) -> 205681.55 | R32: =SUM(K32:M32) -> 282441.1
A33: Net margin % | B33: =IFERROR(B32/B10,0) -> 0.055118859 | C33: =IFERROR(C32/C10,0) -> 0.059159741 | D33: =IFERROR(D32/D10,0) -> 0.034492016 | E33: =IFERROR(E32/E10,0) -> 0.036133824 | F33: =IFERROR(F32/F10,0) -> 0.050494185 | G33: =IFERROR(G32/G10,0) -> 0.064330335 | H33: =IFERROR(H32/H10,0) -> 0.098036184 | I33: =IFERROR(I32/I10,0) -> 0.11069864 | ... R33: =IFERROR(R32/R10,0) -> 0.14593989

Sheet Revenue Detail
A1: REVENUE DETAIL — 2027 (from RIVR revenue model, Base scenario)
A2: Green = imported from the revenue forecast model. Update by re-importing. Monthly, quarterly and full-year.
A3: Revenue segment ($) | B3: 46388 | C3: 46419 | D3: 46447 | E3: 46478 | F3: 46508 | G3: 46539 | H3: 46569 | I3: 46600 | J3: 46631 | K3: 46661 | L3: 46692 | M3: 46722 | N3: FY 2027 | O3: Q1 | P3: Q2 | Q3: Q3 | R3: Q4
A4: Residential | B4: 391456.45 | C4: 399431.69 | D4: 407342.36 | E4: 415188.46 | F4: 422969.97 | G4: 430686.91 | H4: 450800.48 | I4: 458610.51 | J4: 466354.08 | K4: 474031.18 | L4: 481641.82 | M4: 489185.98 | N4: =SUM(B4:M4) -> 5287699.9 | O4: =SUM(B4:D4) -> 1198230.5 | P4: =SUM(E4:G4) -> 1268845.3 | Q4: =SUM(H4:J4) -> 1375765.1 | R4: =SUM(K4:M4) -> 1444859
A5: Business | B5: 31836.57 | C5: 32700.2 | D5: 33563.83 | E5: 34427.46 | F5: 35291.09 | G5: 36154.72 | H5: 38045.81 | I5: 38933.41 | J5: 39821.01 | K5: 40708.61 | L5: 41515.52 | M5: 42241.74 | N5: =SUM(B5:M5) -> 445239.97 | O5: =SUM(B5:D5) -> 98100.6 | P5: =SUM(E5:G5) -> 105873.27 | Q5: =SUM(H5:J5) -> 116800.23 | R5: =SUM(K5:M5) -> 124465.87
A6: Dark Fiber | B6: 65000 | C6: 65000 | D6: 65000 | E6: 65000 | F6: 65000 | G6: 65000 | H6: 65000 | I6: 65000 | J6: 65000 | K6: 65000 | L6: 65000 | M6: 65000 | N6: =SUM(B6:M6) -> 780000 | O6: =SUM(B6:D6) -> 195000 | P6: =SUM(E6:G6) -> 195000 | Q6: =SUM(H6:J6) -> 195000 | R6: =SUM(K6:M6) -> 195000
A7: Hoke County Project | B7: 57000 | C7: 57000 | D7: 57000 | E7: 57000 | F7: 57000 | G7: 57000 | H7: 57000 | I7: 57000 | J7: 57000 | K7: 57000 | L7: 57000 | M7: 57000 | N7: =SUM(B7:M7) -> 684000 | O7: =SUM(B7:D7) -> 171000 | P7: =SUM(E7:G7) -> 171000 | Q7: =SUM(H7:J7) -> 171000 | R7: =SUM(K7:M7) -> 171000
A8: Total Operating Revenue | B8: =SUM(B4:B7) -> 545293.02 | C8: =SUM(C4:C7) -> 554131.89 | D8: =SUM(D4:D7) -> 562906.19 | E8: =SUM(E4:E7) -> 571615.92 | F8: =SUM(F4:F7) -> 580261.06 | G8: =SUM(G4:G7) -> 588841.63 | H8: =SUM(H4:H7) -> 610846.29 | I8: =SUM(I4:I7) -> 619543.92 | ... M8: =SUM(M4:M7) -> 653427.72 | N8: =SUM(B8:M8) -> 7196939.9 | O8: =SUM(B8:D8) -> 1662331.1 | P8: =SUM(E8:G8) -> 1740718.6 | Q8: =SUM(H8:J8) -> 1858565.3 | R8: =SUM(K8:M8) -> 1935324.9
A10: Memo: recurring revenue | B10: 557019.66 | C10: 566102.13 | D10: 575118.23 | E10: 584067.96 | F10: 592951.32 | G10: 601768.31 | H10: 624419.33 | I10: 633357.29 | J10: 642226.93 | K10: 651028.25 | L10: 659678.49 | M10: 668177.65 | N10: =SUM(B10:M10) -> 7355915.6 | O10: =SUM(B10:D10) -> 1698240 | P10: =SUM(E10:G10) -> 1778787.6 | Q10: =SUM(H10:J10) -> 1900003.6 | R10: =SUM(K10:M10) -> 1978884.4
A11: Memo: one-time revenue | B11: 1172.4 | C11: 1197.1 | D11: 1221.6 | E11: 1245.9 | F11: 1270 | G11: 1293.9 | H11: 1317.6 | I11: 1341.1 | J11: 1364.4 | K11: 1387.5 | L11: 1410.4 | M11: 1433.1 | N11: =SUM(B11:M11) -> 15655 | O11: =SUM(B11:D11) -> 3591.1 | P11: =SUM(E11:G11) -> 3809.8 | Q11: =SUM(H11:J11) -> 4023.1 | R11: =SUM(K11:M11) -> 4231
A13: Source: RIVR_Tech_2027_Revenue_Forecast.xlsx — Consolidated Revenue (Base scenario). Segment nets tie to that model's Total net revenue.

Sheet Expense Budget
A1: EXPENSE BUDGET — 2027 (from CFO budget, by department)
A2: 2027 base = CFO department budget. Apply a global % (Assumptions) or a per-line override. Base lines spread evenly; new positions ramp.
A3: Department / line | B3: 2026 ($) | C3: 2027 base ($) | D3: Ovr % | E3: Fixed $ | F3: 2027 Budget ($) | G3: 46388 | H3: 46419 | I3: 46447 | J3: 46478 | K3: 46508 | L3: 46539 | M3: 46569 | N3: 46600 | O3: 46631 | P3: 46661 | Q3: 46692 | R3: 46722 | S3: FY 2027 | T3: Q1 | U3: Q2 | V3: Q3 | W3: Q4
A4: Cost of Power / COGS | B4: 843355.62 | C4: 637300 | F4: =C4*(1+IF(D4="",'Assumptions & Notes'!$B$6,D4))+IF(E4="",0,E4) -> 637300 | G4: =$F4/12 -> 53108.333 | H4: =$F4/12 -> 53108.333 | I4: =$F4/12 -> 53108.333 | J4: =$F4/12 -> 53108.333 | K4: =$F4/12 -> 53108.333 | L4: =$F4/12 -> 53108.333 | M4: =$F4/12 -> 53108.333 | N4: =$F4/12 -> 53108.333 | ... R4: =$F4/12 -> 53108.333 | S4: =SUM(G4:R4) -> 637300 | T4: =SUM(G4:I4) -> 159325 | U4: =SUM(J4:L4) -> 159325 | V4: =SUM(M4:O4) -> 159325 | W4: =SUM(P4:R4) -> 159325
A5: Fiber Network Ops (ex new positions) | B5: 4479541 | C5: 4222706 | F5: =C5*(1+IF(D5="",'Assumptions & Notes'!$B$6,D5))+IF(E5="",0,E5) -> 4222706 | G5: =$F5/12 -> 351892.17 | H5: =$F5/12 -> 351892.17 | I5: =$F5/12 -> 351892.17 | J5: =$F5/12 -> 351892.17 | K5: =$F5/12 -> 351892.17 | L5: =$F5/12 -> 351892.17 | M5: =$F5/12 -> 351892.17 | N5: =$F5/12 -> 351892.17 | ... R5: =$F5/12 -> 351892.17 | S5: =SUM(G5:R5) -> 4222706 | T5: =SUM(G5:I5) -> 1055676.5 | U5: =SUM(J5:L5) -> 1055676.5 | V5: =SUM(M5:O5) -> 1055676.5 | W5: =SUM(P5:R5) -> 1055676.5
A6: Accounting & Finance | B6: 1056711 | C6: 1326510 | F6: =C6*(1+IF(D6="",'Assumptions & Notes'!$B$6,D6))+IF(E6="",0,E6) -> 1326510 | G6: =$F6/12 -> 110542.5 | H6: =$F6/12 -> 110542.5 | I6: =$F6/12 -> 110542.5 | J6: =$F6/12 -> 110542.5 | K6: =$F6/12 -> 110542.5 | L6: =$F6/12 -> 110542.5 | M6: =$F6/12 -> 110542.5 | N6: =$F6/12 -> 110542.5 | ... R6: =$F6/12 -> 110542.5 | S6: =SUM(G6:R6) -> 1326510 | T6: =SUM(G6:I6) -> 331627.5 | U6: =SUM(J6:L6) -> 331627.5 | V6: =SUM(M6:O6) -> 331627.5 | W6: =SUM(P6:R6) -> 331627.5
A7: Marketing | B7: 199999 | C7: 203998.98 | F7: =C7*(1+IF(D7="",'Assumptions & Notes'!$B$6,D7))+IF(E7="",0,E7) -> 203998.98 | G7: =$F7/12 -> 16999.915 | H7: =$F7/12 -> 16999.915 | I7: =$F7/12 -> 16999.915 | J7: =$F7/12 -> 16999.915 | K7: =$F7/12 -> 16999.915 | L7: =$F7/12 -> 16999.915 | M7: =$F7/12 -> 16999.915 | N7: =$F7/12 -> 16999.915 | ... R7: =$F7/12 -> 16999.915 | S7: =SUM(G7:R7) -> 203998.98 | T7: =SUM(G7:I7) -> 50999.745 | U7: =SUM(J7:L7) -> 50999.745 | V7: =SUM(M7:O7) -> 50999.745 | W7: =SUM(P7:R7) -> 50999.745
A8: Member / Customer Services | B8: 135359 | C8: 115055.15 | F8: =C8*(1+IF(D8="",'Assumptions & Notes'!$B$6,D8))+IF(E8="",0,E8) -> 115055.15 | G8: =$F8/12 -> 9587.9292 | H8: =$F8/12 -> 9587.9292 | I8: =$F8/12 -> 9587.9292 | J8: =$F8/12 -> 9587.9292 | K8: =$F8/12 -> 9587.9292 | L8: =$F8/12 -> 9587.9292 | M8: =$F8/12 -> 9587.9292 | N8: =$F8/12 -> 9587.9292 | ... R8: =$F8/12 -> 9587.9292 | S8: =SUM(G8:R8) -> 115055.15 | T8: =SUM(G8:I8) -> 28763.787 | U8: =SUM(J8:L8) -> 28763.787 | V8: =SUM(M8:O8) -> 28763.787 | W8: =SUM(P8:R8) -> 28763.787
A9: Administrative & General | B9: 169529 | C9: 169529 | F9: =C9*(1+IF(D9="",'Assumptions & Notes'!$B$6,D9))+IF(E9="",0,E9) -> 169529 | G9: =$F9/12 -> 14127.417 | H9: =$F9/12 -> 14127.417 | I9: =$F9/12 -> 14127.417 | J9: =$F9/12 -> 14127.417 | K9: =$F9/12 -> 14127.417 | L9: =$F9/12 -> 14127.417 | M9: =$F9/12 -> 14127.417 | N9: =$F9/12 -> 14127.417 | ... R9: =$F9/12 -> 14127.417 | S9: =SUM(G9:R9) -> 169529 | T9: =SUM(G9:I9) -> 42382.25 | U9: =SUM(J9:L9) -> 42382.25 | V9: =SUM(M9:O9) -> 42382.25 | W9: =SUM(P9:R9) -> 42382.25
A10: Human Resources | B10: 66460 | C10: 66460 | F10: =C10*(1+IF(D10="",'Assumptions & Notes'!$B$6,D10))+IF(E10="",0,E10) -> 66460 | G10: =$F10/12 -> 5538.3333 | H10: =$F10/12 -> 5538.3333 | I10: =$F10/12 -> 5538.3333 | J10: =$F10/12 -> 5538.3333 | K10: =$F10/12 -> 5538.3333 | L10: =$F10/12 -> 5538.3333 | M10: =$F10/12 -> 5538.3333 | N10: =$F10/12 -> 5538.3333 | ... R10: =$F10/12 -> 5538.3333 | S10: =SUM(G10:R10) -> 66460 | T10: =SUM(G10:I10) -> 16615 | U10: =SUM(J10:L10) -> 16615 | V10: =SUM(M10:O10) -> 16615 | W10: =SUM(P10:R10) -> 16615
A11: Data Processing / Billing | B11: 83029 | C11: 83029 | F11: =C11*(1+IF(D11="",'Assumptions & Notes'!$B$6,D11))+IF(E11="",0,E11) -> 83029 | G11: =$F11/12 -> 6919.0833 | H11: =$F11/12 -> 6919.0833 | I11: =$F11/12 -> 6919.0833 | J11: =$F11/12 -> 6919.0833 | K11: =$F11/12 -> 6919.0833 | L11: =$F11/12 -> 6919.0833 | M11: =$F11/12 -> 6919.0833 | N11: =$F11/12 -> 6919.0833 | ... R11: =$F11/12 -> 6919.0833 | S11: =SUM(G11:R11) -> 83029 | T11: =SUM(G11:I11) -> 20757.25 | U11: =SUM(J11:L11) -> 20757.25 | V11: =SUM(M11:O11) -> 20757.25 | W11: =SUM(P11:R11) -> 20757.25
A12: Logistics / Inventory | B12: 76613 | C12: 76613 | F12: =C12*(1+IF(D12="",'Assumptions & Notes'!$B$6,D12))+IF(E12="",0,E12) -> 76613 | G12: =$F12/12 -> 6384.4167 | H12: =$F12/12 -> 6384.4167 | I12: =$F12/12 -> 6384.4167 | J12: =$F12/12 -> 6384.4167 | K12: =$F12/12 -> 6384.4167 | L12: =$F12/12 -> 6384.4167 | M12: =$F12/12 -> 6384.4167 | N12: =$F12/12 -> 6384.4167 | ... R12: =$F12/12 -> 6384.4167 | S12: =SUM(G12:R12) -> 76613 | T12: =SUM(G12:I12) -> 19153.25 | U12: =SUM(J12:L12) -> 19153.25 | V12: =SUM(M12:O12) -> 19153.25 | W12: =SUM(P12:R12) -> 19153.25
A13: Safety & Training | B13: 44842 | C13: 44842 | F13: =C13*(1+IF(D13="",'Assumptions & Notes'!$B$6,D13))+IF(E13="",0,E13) -> 44842 | G13: =$F13/12 -> 3736.8333 | H13: =$F13/12 -> 3736.8333 | I13: =$F13/12 -> 3736.8333 | J13: =$F13/12 -> 3736.8333 | K13: =$F13/12 -> 3736.8333 | L13: =$F13/12 -> 3736.8333 | M13: =$F13/12 -> 3736.8333 | N13: =$F13/12 -> 3736.8333 | ... R13: =$F13/12 -> 3736.8333 | S13: =SUM(G13:R13) -> 44842 | T13: =SUM(G13:I13) -> 11210.5 | U13: =SUM(J13:L13) -> 11210.5 | V13: =SUM(M13:O13) -> 11210.5 | W13: =SUM(P13:R13) -> 11210.5
A14: IT Support | B14: 36286 | C14: 36286 | F14: =C14*(1+IF(D14="",'Assumptions & Notes'!$B$6,D14))+IF(E14="",0,E14) -> 36286 | G14: =$F14/12 -> 3023.8333 | H14: =$F14/12 -> 3023.8333 | I14: =$F14/12 -> 3023.8333 | J14: =$F14/12 -> 3023.8333 | K14: =$F14/12 -> 3023.8333 | L14: =$F14/12 -> 3023.8333 | M14: =$F14/12 -> 3023.8333 | N14: =$F14/12 -> 3023.8333 | ... R14: =$F14/12 -> 3023.8333 | S14: =SUM(G14:R14) -> 36286 | T14: =SUM(G14:I14) -> 9071.5 | U14: =SUM(J14:L14) -> 9071.5 | V14: =SUM(M14:O14) -> 9071.5 | W14: =SUM(P14:R14) -> 9071.5
A15: New Positions (2027 staffing plan) | B15: 0 | C15: =IF('Assumptions & Notes'!$B$7="Yes",'New Positions'!S12,0) -> 714483.23 | F15: =C15 -> 714483.23 | G15: =IF('Assumptions & Notes'!$B$7="Yes",'New Positions'!G12,0) -> 29883.33 | H15: =IF('Assumptions & Notes'!$B$7="Yes",'New Positions'!H12,0) -> 35995.83 | I15: =IF('Assumptions & Notes'!$B$7="Yes",'New Positions'!I12,0) -> 58136.66 | J15: =IF('Assumptions & Notes'!$B$7="Yes",'New Positions'!J12,0) -> 65607.49 | K15: =IF('Assumptions & Notes'!$B$7="Yes",'New Positions'!K12,0) -> 65607.49 | L15: =IF('Assumptions & Notes'!$B$7="Yes",'New Positions'!L12,0) -> 65607.49 | M15: =IF('Assumptions & Notes'!$B$7="Yes",'New Positions'!M12,0) -> 65607.49 | N15: =IF('Assumptions & Notes'!$B$7="Yes",'New Positions'!N12,0) -> 65607.49 | ... R15: =IF('Assumptions & Notes'!$B$7="Yes",'New Positions'!R12,0) -> 65607.49 | S15: =SUM(G15:R15) -> 714483.23 | T15: =SUM(G15:I15) -> 124015.82 | U15: =SUM(J15:L15) -> 196822.47 | V15: =SUM(M15:O15) -> 196822.47 | W15: =SUM(P15:R15) -> 196822.47
A16: TOTAL OPERATING EXPENSES | B16: =SUM(B4:B15) -> 7191724.6 | C16: =SUM(C4:C15) -> 7696812.4 | F16: =SUM(F4:F15) -> 7696812.4 | G16: =SUM(G4:G15) -> 611744.09 | H16: =SUM(H4:H15) -> 617856.59 | I16: =SUM(I4:I15) -> 639997.42 | J16: =SUM(J4:J15) -> 647468.25 | K16: =SUM(K4:K15) -> 647468.25 | L16: =SUM(L4:L15) -> 647468.25 | M16: =SUM(M4:M15) -> 647468.25 | ... R16: =SUM(R4:R15) -> 647468.25 | S16: =SUM(G16:R16) -> 7696812.4 | T16: =SUM(G16:I16) -> 1869598.1 | U16: =SUM(J16:L16) -> 1942404.8 | V16: =SUM(M16:O16) -> 1942404.8 | W16: =SUM(P16:R16) -> 1942404.8

Sheet New Positions
A1: 2027 NEW POSITIONS — Staffing Plan (from CFO budget)
A2: 8 FTE. Payroll + burden, ramped by start month. Feeds the Expense Budget when 'Include new positions' = Yes.
A3: Role | B3: Dept | C3: Start mo | D3: Base comp | E3: Burden % | F3: Annual impact | G3: Jan | H3: Feb | I3: Mar | J3: Apr | K3: May | L3: Jun | M3: Jul | N3: Aug | O3: Sep | P3: Oct | Q3: Nov | R3: Dec | S3: Total
A4: Field Tech Staker (replace Daniel/Travis) | B4: 90 - Fiber | C4: 2 | D4: 45000 | E4: 0.63 | F4: 67237.5 | G4: 0 | H4: 6112.5 | I4: 6112.5 | J4: 6112.5 | K4: 6112.5 | L4: 6112.5 | M4: 6112.5 | N4: 6112.5 | O4: 6112.5 | P4: 6112.5 | Q4: 6112.5 | R4: 6112.5 | S4: =SUM(G4:R4) -> 67237.5
A5: 2nd Field Tech / Installer - Drop splice capable | B5: 90 - Fiber | C5: 4 | D5: 55000 | E5: 0.63 | F5: 67237.5 | G5: 0 | H5: 0 | I5: 0 | J5: 7470.83 | K5: 7470.83 | L5: 7470.83 | M5: 7470.83 | N5: 7470.83 | O5: 7470.83 | P5: 7470.83 | Q5: 7470.83 | R5: 7470.83 | S5: =SUM(G5:R5) -> 67237.47
A6: Installations Supervisor (Travis) | B6: 90 - Fiber | C6: 1 | D6: 80000 | E6: 0.63 | F6: 130400 | G6: 10866.67 | H6: 10866.67 | I6: 10866.67 | J6: 10866.67 | K6: 10866.67 | L6: 10866.67 | M6: 10866.67 | N6: 10866.67 | O6: 10866.67 | P6: 10866.67 | Q6: 10866.67 | R6: 10866.67 | S6: =SUM(G6:R6) -> 130400.04
A7: OSP Field Tech - Aerial Lineman / Underground | B7: 90 - Fiber | C7: 3 | D7: 63000 | E7: 0.63 | F7: 85575 | G7: 0 | H7: 0 | I7: 8557.5 | J7: 8557.5 | K7: 8557.5 | L7: 8557.5 | M7: 8557.5 | N7: 8557.5 | O7: 8557.5 | P7: 8557.5 | Q7: 8557.5 | R7: 8557.5 | S7: =SUM(G7:R7) -> 85575
A8: OSP Field Tech Groundman | B8: 90 - Fiber | C8: 3 | D8: 40000 | E8: 0.63 | F8: 54333.33 | G8: 0 | H8: 0 | I8: 5433.33 | J8: 5433.33 | K8: 5433.33 | L8: 5433.33 | M8: 5433.33 | N8: 5433.33 | O8: 5433.33 | P8: 5433.33 | Q8: 5433.33 | R8: 5433.33 | S8: =SUM(G8:R8) -> 54333.3
A9: OSP Splicer - Drop & Mainline Repair / OTDR | B9: 90 - Fiber | C9: 3 | D9: 60000 | E9: 0.63 | F9: 81500 | G9: 0 | H9: 0 | I9: 8150 | J9: 8150 | K9: 8150 | L9: 8150 | M9: 8150 | N9: 8150 | O9: 8150 | P9: 8150 | Q9: 8150 | R9: 8150 | S9: =SUM(G9:R9) -> 81500
A10: Data Entry / Redlines & Closing Docs | B10: 90 - Fiber | C10: 1 | D10: 40000 | E10: 0.63 | F10: 65200 | G10: 5433.33 | H10: 5433.33 | I10: 5433.33 | J10: 5433.33 | K10: 5433.33 | L10: 5433.33 | M10: 5433.33 | N10: 5433.33 | O10: 5433.33 | P10: 5433.33 | Q10: 5433.33 | R10: 5433.33 | S10: =SUM(G10:R10) -> 65199.96
A11: Construction Design Engineer (Rocky) | B11: 90 - Fiber | C11: 1 | D11: 100000 | E11: 0.63 | F11: 163000 | G11: 13583.33 | H11: 13583.33 | I11: 13583.33 | J11: 13583.33 | K11: 13583.33 | L11: 13583.33 | M11: 13583.33 | N11: 13583.33 | O11: 13583.33 | P11: 13583.33 | Q11: 13583.33 | R11: 13583.33 | S11: =SUM(G11:R11) -> 162999.96
A12: TOTAL — new positions | F12: =SUM(F4:F11) -> 714483.33 | G12: =SUM(G4:G11) -> 29883.33 | H12: =SUM(H4:H11) -> 35995.83 | I12: =SUM(I4:I11) -> 58136.66 | J12: =SUM(J4:J11) -> 65607.49 | K12: =SUM(K4:K11) -> 65607.49 | L12: =SUM(L4:L11) -> 65607.49 | M12: =SUM(M4:M11) -> 65607.49 | ... R12: =SUM(R4:R11) -> 65607.49 | S12: =SUM(G12:R12) -> 714483.23
A14: Monthly amounts ramp by each role's start month (per the CFO staffing plan). Annual impact = prorated base payroll x (1 + burden %).

Sheet Assumptions & Notes
A1: MASTER PRO FORMA — ASSUMPTIONS & CONTROL PANEL
A2: Blue/yellow = editable inputs. Green = links. Grey = calculated. Change these to flex the pro forma.
E3: LEGEND
A4: CONTROL INPUTS | E4: Editable input
A5: Planning year | B5: 2027 | C5: Budget year modeled. | E5: Sourced from a linked workbook
A6: Global expense adjustment % | B6: 0 | C6: Applied on top of the CFO 2027 department budgets. 0 = use the budget as-is. | E6: Calculated
A7: Include new positions (Yes/No) | B7: Yes | C7: Include the 2027 staffing plan (8 FTE, $714K) in expenses.
A8: Depreciation & amortization (annual) | B8: 140875 | C8: Used only to add back to EBIT for the EBITDA line. From CFO budget.
A9: Effective income tax rate | B9: 0 | C9: Applied to positive pre-tax income. 0 by default (LLC / pass-through — confirm with CFO).
A10: Grant income (annual) | B10: 784080 | C10: Nonoperating grant income, from CFO budget (spread evenly).
A11: Nonoperating income (annual) | B11: 374004 | C11: Other nonoperating income, from CFO budget (spread evenly).
A14: SOURCES & METHOD
A15: • REVENUE is sourced from RIVR_Tech_2027_Revenue_Forecast (Consolidated Revenue, Base scenario): Residential, Business, Dark Fiber and the Hoke County project, by month. Update by re-importing that model.
A16: • EXPENSES are sourced from the RIVR CFO-Style 2027 Budget Workbook, by department (2027 budget column). The 8-FTE 2027 staffing plan ($714,483) is shown as its own line and stripped out of the Fiber department to avoid double counting.
A17: • GRANT and NONOPERATING income are sourced from the CFO budget and shown below operating income (the revenue model excludes them).
A18: • NOTE on the source budget: its Budget Builder total row double-counts expenses (its total = 2 x expenses + revenue). This master uses the clean per-department / GL rollup ($7.70M of 2027 expense), which ties to the CFO Dashboard and Department Summary.
A19: • Base lines are spread evenly across the year (the CFO budget's default). New-position costs ramp by each role's start month.
A20: • Operating income excludes grants; net income includes them. Confirm final GAAP treatment (esp. grants and IRU) with the CFO/accountant.
