Workbook

Sheet Executive Dashboard
A1: RIVR Tech — Executive Dashboard
A2: Blanket Maintenance Protection Plan — headline analysis
A3: v1.0 (Draft for Executive Review) | 2026-07-29 | LREMC Technologies, LLC d/b/a RIVR Tech | NOT LEGAL ADVICE
A4: LEGEND: | B4: User input | C4: Calculated | D4: Recommended | E4: Warning
A6: Loaded cost / call | C6: Break-even util $3.99 | E6: Break-even util $4.99 | G6: Contribution/member $3.99
A7: =Assumptions!$B$35 | C7: ='Scenario A'!$B$14 | E7: ='Scenario B'!$B$14 | G7: ='Scenario A'!$B$12
A10: Contribution/member $4.99 | C10: Mandatory net $3.99 (curr) | E10: Mandatory net $4.99 (curr) | G10: 5-yr cum net (opt-in $3.99)
A11: ='Scenario B'!$B$12 | C11: ='Scenario A'!$J$19 | E11: ='Scenario B'!$J$19 | G11: ='Five-Year Forecast'!$H$12
A19: Enrollment-Model Net Annual (chart data, computed snapshot)
A20: Model | B20: Net $3.99 | C20: Net $4.99
A21: Mandatory | B21: 32980 | C21: 87525
A22: Opt-out 85% | B22: 18191 | C22: 64554
A23: Opt-out 60% | B23: -6457 | C23: 26270
A24: Opt-in 40% | B24: -1208 | C24: 20610
A25: Opt-in 30% | B25: -6906 | C25: 9457
A26: Opt-in 20% | B26: -12604 | C26: -1695
A45: Churn Sensitivity — Net $3.99 Mandatory (snapshot)
A46: Incr. Churn | B46: Net $3.99 | C46: Net $4.99
A47: 0.00% | B47: 74592 | C47: 129137
A48: 0.25% | B48: 64189 | C48: 118734
A49: 0.50% | B49: 53786 | C49: 108331
A50: 1.00% | B50: 32980 | C50: 87525
A51: 2.00% | B51: -8632 | C51: 45913
A52: 3.00% | B52: -50243 | C52: 4302
A53: 5.00% | B53: -133467 | C53: -78922

Sheet Assumptions
A1: RIVR Tech — Assumptions
A2: Edit yellow cells — all scenarios recalculate from here.
A3: v1.0 (Draft for Executive Review) | 2026-07-29 | LREMC Technologies, LLC d/b/a RIVR Tech | NOT LEGAL ADVICE
A4: LEGEND: | B4: User input | C4: Calculated | D4: Recommended | E4: Warning
A6: Assumption | B6: Value | C6: Unit | D6: Type | E6: Note
A7: Current residential subscribers | B7: 4686 | C7: count | D7: Assumption | E7: Editable — starting residential internet accounts.
A8: Monthly subscriber growth | B8: 0.01 | C8: pct | D8: Assumption | E8: Assumption — ~12.7%/yr compounded.
A9: Average residential ARPU (monthly) | B9: 74 | C9: usd | D9: Given/Scenario | E9: Provided.
A10: Plan price — Scenario A (monthly) | B10: 3.99 | C10: usd | D10: Given/Scenario | E10: Scenario A.
A11: Plan price — Scenario B (monthly) | B11: 4.99 | C11: usd | D11: Given/Scenario | E11: Scenario B.
A12: Enrollment % (driver) | B12: 0.4 | C12: pct | D12: Assumption | E12: Default driver — overridden per enrollment model.
A13: Baseline monthly disconnect/churn | B13: 0.015 | C13: pct | D13: Assumption | E13: Assumption — ~16.6%/yr baseline.
A14: Incremental annual churn from the fee | B14: 0.01 | C14: pct | D14: Assumption | E14: Driver — tested 0%-5%.
A15: % of customers generating a trouble call/yr | B15: 0.3 | C15: pct | D15: Assumption | E15: Assumption.
A16: % of calls that are customer-caused | B16: 0.45 | C16: pct | D16: Assumption | E16: Assumption — remainder are RIVR-network/equipment (free).
A17: Expected annual covered-visit utilization | B17: 0.15 | C17: pct | D17: Assumption | E17: Share of ENROLLED members using a covered visit/yr.
A18: Technician labor time per call (hr) | B18: 1 | C18: hours | D18: Assumption | E18: On-site time.
... A34: Pay-per-visit collection rate | B34: 0.8 | C34: pct | D34: Assumption | E34: Share of billed visit fees collected.
A35: Cost per covered call (loaded, computed) | B35: =((Assumptions!$B$18+Assumptions!$B$20)*Assumptions!$B$19+Assumptions!$B$21+Assumptions!$B$22+Assumptions!$B$23)*(1+Assumptions!$B$24)

Sheet Subscriber Forecast
A1: RIVR Tech — Subscriber Forecast
A2: Modeled subscriber levels + 5-year organic growth
A3: v1.0 (Draft for Executive Review) | 2026-07-29 | LREMC Technologies, LLC d/b/a RIVR Tech | NOT LEGAL ADVICE
A5: Modeled subscriber levels
A6: Subscriber Level | B6: Monthly Plan Rev @ $3.99 (100%) | C6: Monthly Plan Rev @ $4.99 (100%)
A7: 4686 | B7: =A7*Assumptions!$B$10 | C7: =A7*Assumptions!$B$11
A8: 5000 | B8: =A8*Assumptions!$B$10 | C8: =A8*Assumptions!$B$11
A9: 5500 | B9: =A9*Assumptions!$B$10 | C9: =A9*Assumptions!$B$11
A10: 6000 | B10: =A10*Assumptions!$B$10 | C10: =A10*Assumptions!$B$11
A11: 7500 | B11: =A11*Assumptions!$B$10 | C11: =A11*Assumptions!$B$11
A12: 10000 | B12: =A12*Assumptions!$B$10 | C12: =A12*Assumptions!$B$11
A14: 5-Year organic growth (from current subscribers)
A15: Year | B15: Subscribers | C15: @ $3.99 100% Annual | D15: @ $4.99 100% Annual
A16: 1 | B16: =Assumptions!$B$7 | C16: =B16*Assumptions!$B$10*12 | D16: =B16*Assumptions!$B$11*12
A17: 2 | B17: =B16*(1+Assumptions!$B$8)^12 | C17: =B17*Assumptions!$B$10*12 | D17: =B17*Assumptions!$B$11*12
A18: 3 | B18: =B17*(1+Assumptions!$B$8)^12 | C18: =B18*Assumptions!$B$10*12 | D18: =B18*Assumptions!$B$11*12
A19: 4 | B19: =B18*(1+Assumptions!$B$8)^12 | C19: =B19*Assumptions!$B$10*12 | D19: =B19*Assumptions!$B$11*12
A20: 5 | B20: =B19*(1+Assumptions!$B$8)^12 | C20: =B20*Assumptions!$B$10*12 | D20: =B20*Assumptions!$B$11*12

Sheet Scenario A
A1: RIVR Tech — Scenario A — $3.99/month
A2: Per-member economics + mandatory totals across subscriber levels
A3: v1.0 (Draft for Executive Review) | 2026-07-29 | LREMC Technologies, LLC d/b/a RIVR Tech | NOT LEGAL ADVICE
A5: Per-enrolled-member annual economics (at expected utilization)
A7: Plan revenue / member | B7: =Assumptions!$B$10*12
A8: Covered service-call expense / member | B8: =Assumptions!$B$17*Assumptions!$B$35
A9: Call-center expense / member | B9: =Assumptions!$B$17*Assumptions!$B$25
A10: Billing & admin / member | B10: =Assumptions!$B$26
A11: Bad debt / member | B11: =Assumptions!$B$10*12*Assumptions!$B$28
A12: Contribution / member | B12: =B7-B8-B9-B10-B11
A13: Contribution margin % | B13: =B12/B7
A14: Break-even utilization | B14: =(B7-B10-B11)/(Assumptions!$B$35+Assumptions!$B$25)
A17: Mandatory (100% enrolled) annual totals by subscriber level
A18: Subs | B18: Enrolled | C18: Gross Annual | D18: Covered Exp | E18: CC Exp | F18: Admin | G18: Bad Debt | H18: Fixed | I18: Churn Loss | J18: Net Annual (Y2+) | K18: Net Margin %
A19: 4686 | B19: =A19*1 | C19: =B19*Assumptions!$B$10*12 | D19: =B19*Assumptions!$B$17*Assumptions!$B$35 | E19: =B19*Assumptions!$B$17*Assumptions!$B$25 | F19: =B19*Assumptions!$B$26 | G19: =C19*Assumptions!$B$28 | H19: =Assumptions!$B$32+Assumptions!$B$33 | I19: =A19*Assumptions!$B$14*Assumptions!$B$9*12 | J19: =C19-D19-E19-F19-G19-H19-I19 | K19: =J19/C19
A20: 5000 | B20: =A20*1 | C20: =B20*Assumptions!$B$10*12 | D20: =B20*Assumptions!$B$17*Assumptions!$B$35 | E20: =B20*Assumptions!$B$17*Assumptions!$B$25 | F20: =B20*Assumptions!$B$26 | G20: =C20*Assumptions!$B$28 | H20: =Assumptions!$B$32+Assumptions!$B$33 | I20: =A20*Assumptions!$B$14*Assumptions!$B$9*12 | J20: =C20-D20-E20-F20-G20-H20-I20 | K20: =J20/C20
A21: 5500 | B21: =A21*1 | C21: =B21*Assumptions!$B$10*12 | D21: =B21*Assumptions!$B$17*Assumptions!$B$35 | E21: =B21*Assumptions!$B$17*Assumptions!$B$25 | F21: =B21*Assumptions!$B$26 | G21: =C21*Assumptions!$B$28 | H21: =Assumptions!$B$32+Assumptions!$B$33 | I21: =A21*Assumptions!$B$14*Assumptions!$B$9*12 | J21: =C21-D21-E21-F21-G21-H21-I21 | K21: =J21/C21
A22: 6000 | B22: =A22*1 | C22: =B22*Assumptions!$B$10*12 | D22: =B22*Assumptions!$B$17*Assumptions!$B$35 | E22: =B22*Assumptions!$B$17*Assumptions!$B$25 | F22: =B22*Assumptions!$B$26 | G22: =C22*Assumptions!$B$28 | H22: =Assumptions!$B$32+Assumptions!$B$33 | I22: =A22*Assumptions!$B$14*Assumptions!$B$9*12 | J22: =C22-D22-E22-F22-G22-H22-I22 | K22: =J22/C22
A23: 7500 | B23: =A23*1 | C23: =B23*Assumptions!$B$10*12 | D23: =B23*Assumptions!$B$17*Assumptions!$B$35 | E23: =B23*Assumptions!$B$17*Assumptions!$B$25 | F23: =B23*Assumptions!$B$26 | G23: =C23*Assumptions!$B$28 | H23: =Assumptions!$B$32+Assumptions!$B$33 | I23: =A23*Assumptions!$B$14*Assumptions!$B$9*12 | J23: =C23-D23-E23-F23-G23-H23-I23 | K23: =J23/C23
A24: 10000 | B24: =A24*1 | C24: =B24*Assumptions!$B$10*12 | D24: =B24*Assumptions!$B$17*Assumptions!$B$35 | E24: =B24*Assumptions!$B$17*Assumptions!$B$25 | F24: =B24*Assumptions!$B$26 | G24: =C24*Assumptions!$B$28 | H24: =Assumptions!$B$32+Assumptions!$B$33 | I24: =A24*Assumptions!$B$14*Assumptions!$B$9*12 | J24: =C24-D24-E24-F24-G24-H24-I24 | K24: =J24/C24
A26: Net Annual excludes one-time launch/billing costs (see Five-Year & Dashboard). Churn Loss uses incremental-churn assumption on full base.

Sheet Scenario B
A1: RIVR Tech — Scenario B — $4.99/month
A2: Per-member economics + mandatory totals across subscriber levels
A3: v1.0 (Draft for Executive Review) | 2026-07-29 | LREMC Technologies, LLC d/b/a RIVR Tech | NOT LEGAL ADVICE
A5: Per-enrolled-member annual economics (at expected utilization)
A7: Plan revenue / member | B7: =Assumptions!$B$11*12
A8: Covered service-call expense / member | B8: =Assumptions!$B$17*Assumptions!$B$35
A9: Call-center expense / member | B9: =Assumptions!$B$17*Assumptions!$B$25
A10: Billing & admin / member | B10: =Assumptions!$B$26
A11: Bad debt / member | B11: =Assumptions!$B$11*12*Assumptions!$B$28
A12: Contribution / member | B12: =B7-B8-B9-B10-B11
A13: Contribution margin % | B13: =B12/B7
A14: Break-even utilization | B14: =(B7-B10-B11)/(Assumptions!$B$35+Assumptions!$B$25)
A17: Mandatory (100% enrolled) annual totals by subscriber level
A18: Subs | B18: Enrolled | C18: Gross Annual | D18: Covered Exp | E18: CC Exp | F18: Admin | G18: Bad Debt | H18: Fixed | I18: Churn Loss | J18: Net Annual (Y2+) | K18: Net Margin %
A19: 4686 | B19: =A19*1 | C19: =B19*Assumptions!$B$11*12 | D19: =B19*Assumptions!$B$17*Assumptions!$B$35 | E19: =B19*Assumptions!$B$17*Assumptions!$B$25 | F19: =B19*Assumptions!$B$26 | G19: =C19*Assumptions!$B$28 | H19: =Assumptions!$B$32+Assumptions!$B$33 | I19: =A19*Assumptions!$B$14*Assumptions!$B$9*12 | J19: =C19-D19-E19-F19-G19-H19-I19 | K19: =J19/C19
A20: 5000 | B20: =A20*1 | C20: =B20*Assumptions!$B$11*12 | D20: =B20*Assumptions!$B$17*Assumptions!$B$35 | E20: =B20*Assumptions!$B$17*Assumptions!$B$25 | F20: =B20*Assumptions!$B$26 | G20: =C20*Assumptions!$B$28 | H20: =Assumptions!$B$32+Assumptions!$B$33 | I20: =A20*Assumptions!$B$14*Assumptions!$B$9*12 | J20: =C20-D20-E20-F20-G20-H20-I20 | K20: =J20/C20
A21: 5500 | B21: =A21*1 | C21: =B21*Assumptions!$B$11*12 | D21: =B21*Assumptions!$B$17*Assumptions!$B$35 | E21: =B21*Assumptions!$B$17*Assumptions!$B$25 | F21: =B21*Assumptions!$B$26 | G21: =C21*Assumptions!$B$28 | H21: =Assumptions!$B$32+Assumptions!$B$33 | I21: =A21*Assumptions!$B$14*Assumptions!$B$9*12 | J21: =C21-D21-E21-F21-G21-H21-I21 | K21: =J21/C21
A22: 6000 | B22: =A22*1 | C22: =B22*Assumptions!$B$11*12 | D22: =B22*Assumptions!$B$17*Assumptions!$B$35 | E22: =B22*Assumptions!$B$17*Assumptions!$B$25 | F22: =B22*Assumptions!$B$26 | G22: =C22*Assumptions!$B$28 | H22: =Assumptions!$B$32+Assumptions!$B$33 | I22: =A22*Assumptions!$B$14*Assumptions!$B$9*12 | J22: =C22-D22-E22-F22-G22-H22-I22 | K22: =J22/C22
A23: 7500 | B23: =A23*1 | C23: =B23*Assumptions!$B$11*12 | D23: =B23*Assumptions!$B$17*Assumptions!$B$35 | E23: =B23*Assumptions!$B$17*Assumptions!$B$25 | F23: =B23*Assumptions!$B$26 | G23: =C23*Assumptions!$B$28 | H23: =Assumptions!$B$32+Assumptions!$B$33 | I23: =A23*Assumptions!$B$14*Assumptions!$B$9*12 | J23: =C23-D23-E23-F23-G23-H23-I23 | K23: =J23/C23
A24: 10000 | B24: =A24*1 | C24: =B24*Assumptions!$B$11*12 | D24: =B24*Assumptions!$B$17*Assumptions!$B$35 | E24: =B24*Assumptions!$B$17*Assumptions!$B$25 | F24: =B24*Assumptions!$B$26 | G24: =C24*Assumptions!$B$28 | H24: =Assumptions!$B$32+Assumptions!$B$33 | I24: =A24*Assumptions!$B$14*Assumptions!$B$9*12 | J24: =C24-D24-E24-F24-G24-H24-I24 | K24: =J24/C24
A26: Net Annual excludes one-time launch/billing costs (see Five-Year & Dashboard). Churn Loss uses incremental-churn assumption on full base.

Sheet Enrollment Models
A1: RIVR Tech — Enrollment-Model Comparison
A2: Mandatory / Opt-out / Opt-in at current subscribers
A3: v1.0 (Draft for Executive Review) | 2026-07-29 | LREMC Technologies, LLC d/b/a RIVR Tech | NOT LEGAL ADVICE
A5: At current subscribers (Assumptions) — Gross & Net annual by model and price
A6: Model | B6: Participation | C6: Enrolled | D6: Gross Annual $3.99 | E6: Net Annual $3.99 | F6: Gross Annual $4.99 | G6: Net Annual $4.99
A7: Mandatory | B7: 1 | C7: =Assumptions!$B$7*B7 | D7: =C7*Assumptions!$B$10*12 | E7: =C7*Assumptions!$B$10*12-(C7*Assumptions!$B$17*Assumptions!$B$35)-(C7*Assumptions!$B$17*Assumptions!$B$25)-(C7*Assumptions!$B$26)-(C7*Assumptions!$B$10*12*Assumptions!$B$28)-(Assumptions!$B$32+Assumptions!$B$33)-(Assumptions!$B$7*Assumptions!$B$14*Assumptions!$B$9*12) | F7: =C7*Assumptions!$B$11*12 | G7: =C7*Assumptions!$B$11*12-(C7*Assumptions!$B$17*Assumptions!$B$35)-(C7*Assumptions!$B$17*Assumptions!$B$25)-(C7*Assumptions!$B$26)-(C7*Assumptions!$B$11*12*Assumptions!$B$28)-(Assumptions!$B$32+Assumptions!$B$33)-(Assumptions!$B$7*Assumptions!$B$14*Assumptions!$B$9*12)
A8: Opt-out | B8: 0.95 | C8: =Assumptions!$B$7*B8 | D8: =C8*Assumptions!$B$10*12 | E8: =C8*Assumptions!$B$10*12-(C8*Assumptions!$B$17*Assumptions!$B$35)-(C8*Assumptions!$B$17*Assumptions!$B$25)-(C8*Assumptions!$B$26)-(C8*Assumptions!$B$10*12*Assumptions!$B$28)-(Assumptions!$B$32+Assumptions!$B$33)-(Assumptions!$B$7*Assumptions!$B$14*Assumptions!$B$9*12) | F8: =C8*Assumptions!$B$11*12 | G8: =C8*Assumptions!$B$11*12-(C8*Assumptions!$B$17*Assumptions!$B$35)-(C8*Assumptions!$B$17*Assumptions!$B$25)-(C8*Assumptions!$B$26)-(C8*Assumptions!$B$11*12*Assumptions!$B$28)-(Assumptions!$B$32+Assumptions!$B$33)-(Assumptions!$B$7*Assumptions!$B$14*Assumptions!$B$9*12)
A9: Opt-out | B9: 0.85 | C9: =Assumptions!$B$7*B9 | D9: =C9*Assumptions!$B$10*12 | E9: =C9*Assumptions!$B$10*12-(C9*Assumptions!$B$17*Assumptions!$B$35)-(C9*Assumptions!$B$17*Assumptions!$B$25)-(C9*Assumptions!$B$26)-(C9*Assumptions!$B$10*12*Assumptions!$B$28)-(Assumptions!$B$32+Assumptions!$B$33)-(Assumptions!$B$7*Assumptions!$B$14*Assumptions!$B$9*12) | F9: =C9*Assumptions!$B$11*12 | G9: =C9*Assumptions!$B$11*12-(C9*Assumptions!$B$17*Assumptions!$B$35)-(C9*Assumptions!$B$17*Assumptions!$B$25)-(C9*Assumptions!$B$26)-(C9*Assumptions!$B$11*12*Assumptions!$B$28)-(Assumptions!$B$32+Assumptions!$B$33)-(Assumptions!$B$7*Assumptions!$B$14*Assumptions!$B$9*12)
A10: Opt-out | B10: 0.75 | C10: =Assumptions!$B$7*B10 | D10: =C10*Assumptions!$B$10*12 | E10: =C10*Assumptions!$B$10*12-(C10*Assumptions!$B$17*Assumptions!$B$35)-(C10*Assumptions!$B$17*Assumptions!$B$25)-(C10*Assumptions!$B$26)-(C10*Assumptions!$B$10*12*Assumptions!$B$28)-(Assumptions!$B$32+Assumptions!$B$33)-(Assumptions!$B$7*Assumptions!$B$14*Assumptions!$B$9*12) | F10: =C10*Assumptions!$B$11*12 | G10: =C10*Assumptions!$B$11*12-(C10*Assumptions!$B$17*Assumptions!$B$35)-(C10*Assumptions!$B$17*Assumptions!$B$25)-(C10*Assumptions!$B$26)-(C10*Assumptions!$B$11*12*Assumptions!$B$28)-(Assumptions!$B$32+Assumptions!$B$33)-(Assumptions!$B$7*Assumptions!$B$14*Assumptions!$B$9*12)
A11: Opt-out | B11: 0.6 | C11: =Assumptions!$B$7*B11 | D11: =C11*Assumptions!$B$10*12 | E11: =C11*Assumptions!$B$10*12-(C11*Assumptions!$B$17*Assumptions!$B$35)-(C11*Assumptions!$B$17*Assumptions!$B$25)-(C11*Assumptions!$B$26)-(C11*Assumptions!$B$10*12*Assumptions!$B$28)-(Assumptions!$B$32+Assumptions!$B$33)-(Assumptions!$B$7*Assumptions!$B$14*Assumptions!$B$9*12) | F11: =C11*Assumptions!$B$11*12 | G11: =C11*Assumptions!$B$11*12-(C11*Assumptions!$B$17*Assumptions!$B$35)-(C11*Assumptions!$B$17*Assumptions!$B$25)-(C11*Assumptions!$B$26)-(C11*Assumptions!$B$11*12*Assumptions!$B$28)-(Assumptions!$B$32+Assumptions!$B$33)-(Assumptions!$B$7*Assumptions!$B$14*Assumptions!$B$9*12)
A12: Opt-out | B12: 0.5 | C12: =Assumptions!$B$7*B12 | D12: =C12*Assumptions!$B$10*12 | E12: =C12*Assumptions!$B$10*12-(C12*Assumptions!$B$17*Assumptions!$B$35)-(C12*Assumptions!$B$17*Assumptions!$B$25)-(C12*Assumptions!$B$26)-(C12*Assumptions!$B$10*12*Assumptions!$B$28)-(Assumptions!$B$32+Assumptions!$B$33)-(Assumptions!$B$7*Assumptions!$B$14*Assumptions!$B$9*12) | F12: =C12*Assumptions!$B$11*12 | G12: =C12*Assumptions!$B$11*12-(C12*Assumptions!$B$17*Assumptions!$B$35)-(C12*Assumptions!$B$17*Assumptions!$B$25)-(C12*Assumptions!$B$26)-(C12*Assumptions!$B$11*12*Assumptions!$B$28)-(Assumptions!$B$32+Assumptions!$B$33)-(Assumptions!$B$7*Assumptions!$B$14*Assumptions!$B$9*12)
A13: Opt-in | B13: 0.2 | C13: =Assumptions!$B$7*B13 | D13: =C13*Assumptions!$B$10*12 | E13: =C13*Assumptions!$B$10*12-(C13*Assumptions!$B$17*Assumptions!$B$35)-(C13*Assumptions!$B$17*Assumptions!$B$25)-(C13*Assumptions!$B$26)-(C13*Assumptions!$B$10*12*Assumptions!$B$28)-(Assumptions!$B$32+Assumptions!$B$33)-(C13*Assumptions!$B$14*Assumptions!$B$9*12) | F13: =C13*Assumptions!$B$11*12 | G13: =C13*Assumptions!$B$11*12-(C13*Assumptions!$B$17*Assumptions!$B$35)-(C13*Assumptions!$B$17*Assumptions!$B$25)-(C13*Assumptions!$B$26)-(C13*Assumptions!$B$11*12*Assumptions!$B$28)-(Assumptions!$B$32+Assumptions!$B$33)-(C13*Assumptions!$B$14*Assumptions!$B$9*12)
A14: Opt-in | B14: 0.3 | C14: =Assumptions!$B$7*B14 | D14: =C14*Assumptions!$B$10*12 | E14: =C14*Assumptions!$B$10*12-(C14*Assumptions!$B$17*Assumptions!$B$35)-(C14*Assumptions!$B$17*Assumptions!$B$25)-(C14*Assumptions!$B$26)-(C14*Assumptions!$B$10*12*Assumptions!$B$28)-(Assumptions!$B$32+Assumptions!$B$33)-(C14*Assumptions!$B$14*Assumptions!$B$9*12) | F14: =C14*Assumptions!$B$11*12 | G14: =C14*Assumptions!$B$11*12-(C14*Assumptions!$B$17*Assumptions!$B$35)-(C14*Assumptions!$B$17*Assumptions!$B$25)-(C14*Assumptions!$B$26)-(C14*Assumptions!$B$11*12*Assumptions!$B$28)-(Assumptions!$B$32+Assumptions!$B$33)-(C14*Assumptions!$B$14*Assumptions!$B$9*12)
A15: Opt-in | B15: 0.4 | C15: =Assumptions!$B$7*B15 | D15: =C15*Assumptions!$B$10*12 | E15: =C15*Assumptions!$B$10*12-(C15*Assumptions!$B$17*Assumptions!$B$35)-(C15*Assumptions!$B$17*Assumptions!$B$25)-(C15*Assumptions!$B$26)-(C15*Assumptions!$B$10*12*Assumptions!$B$28)-(Assumptions!$B$32+Assumptions!$B$33)-(C15*Assumptions!$B$14*Assumptions!$B$9*12) | F15: =C15*Assumptions!$B$11*12 | G15: =C15*Assumptions!$B$11*12-(C15*Assumptions!$B$17*Assumptions!$B$35)-(C15*Assumptions!$B$17*Assumptions!$B$25)-(C15*Assumptions!$B$26)-(C15*Assumptions!$B$11*12*Assumptions!$B$28)-(Assumptions!$B$32+Assumptions!$B$33)-(C15*Assumptions!$B$14*Assumptions!$B$9*12)
A16: Opt-in | B16: 0.5 | C16: =Assumptions!$B$7*B16 | D16: =C16*Assumptions!$B$10*12 | E16: =C16*Assumptions!$B$10*12-(C16*Assumptions!$B$17*Assumptions!$B$35)-(C16*Assumptions!$B$17*Assumptions!$B$25)-(C16*Assumptions!$B$26)-(C16*Assumptions!$B$10*12*Assumptions!$B$28)-(Assumptions!$B$32+Assumptions!$B$33)-(C16*Assumptions!$B$14*Assumptions!$B$9*12) | F16: =C16*Assumptions!$B$11*12 | G16: =C16*Assumptions!$B$11*12-(C16*Assumptions!$B$17*Assumptions!$B$35)-(C16*Assumptions!$B$17*Assumptions!$B$25)-(C16*Assumptions!$B$26)-(C16*Assumptions!$B$11*12*Assumptions!$B$28)-(Assumptions!$B$32+Assumptions!$B$33)-(C16*Assumptions!$B$14*Assumptions!$B$9*12)
A17: Opt-in | B17: 0.6 | C17: =Assumptions!$B$7*B17 | D17: =C17*Assumptions!$B$10*12 | E17: =C17*Assumptions!$B$10*12-(C17*Assumptions!$B$17*Assumptions!$B$35)-(C17*Assumptions!$B$17*Assumptions!$B$25)-(C17*Assumptions!$B$26)-(C17*Assumptions!$B$10*12*Assumptions!$B$28)-(Assumptions!$B$32+Assumptions!$B$33)-(C17*Assumptions!$B$14*Assumptions!$B$9*12) | F17: =C17*Assumptions!$B$11*12 | G17: =C17*Assumptions!$B$11*12-(C17*Assumptions!$B$17*Assumptions!$B$35)-(C17*Assumptions!$B$17*Assumptions!$B$25)-(C17*Assumptions!$B$26)-(C17*Assumptions!$B$11*12*Assumptions!$B$28)-(Assumptions!$B$32+Assumptions!$B$33)-(C17*Assumptions!$B$14*Assumptions!$B$9*12)
A19: Net excludes one-time costs; churn applied to full base for mandatory/opt-out, enrolled base for opt-in.

Sheet Utilization Analysis
A1: RIVR Tech — Service-Call Utilization Sensitivity
A2: Per-member contribution by utilization × loaded call cost (negative = unprofitable)
A3: v1.0 (Draft for Executive Review) | 2026-07-29 | LREMC Technologies, LLC d/b/a RIVR Tech | NOT LEGAL ADVICE
A5: $3.99 — per-member annual contribution (rows=utilization, cols=loaded cost/call)
A6: Util \ Cost | B6: 75 | C6: 100 | D6: 125 | E6: 150 | F6: 200 | G6: 250
A7: 0.05 | B7: =Assumptions!$B$10*12 - $A7*B$6 - $A7*Assumptions!$B$25 - Assumptions!$B$26 - Assumptions!$B$10*12*Assumptions!$B$28 | C7: =Assumptions!$B$10*12 - $A7*C$6 - $A7*Assumptions!$B$25 - Assumptions!$B$26 - Assumptions!$B$10*12*Assumptions!$B$28 | D7: =Assumptions!$B$10*12 - $A7*D$6 - $A7*Assumptions!$B$25 - Assumptions!$B$26 - Assumptions!$B$10*12*Assumptions!$B$28 | E7: =Assumptions!$B$10*12 - $A7*E$6 - $A7*Assumptions!$B$25 - Assumptions!$B$26 - Assumptions!$B$10*12*Assumptions!$B$28 | F7: =Assumptions!$B$10*12 - $A7*F$6 - $A7*Assumptions!$B$25 - Assumptions!$B$26 - Assumptions!$B$10*12*Assumptions!$B$28 | G7: =Assumptions!$B$10*12 - $A7*G$6 - $A7*Assumptions!$B$25 - Assumptions!$B$26 - Assumptions!$B$10*12*Assumptions!$B$28
A8: 0.1 | B8: =Assumptions!$B$10*12 - $A8*B$6 - $A8*Assumptions!$B$25 - Assumptions!$B$26 - Assumptions!$B$10*12*Assumptions!$B$28 | C8: =Assumptions!$B$10*12 - $A8*C$6 - $A8*Assumptions!$B$25 - Assumptions!$B$26 - Assumptions!$B$10*12*Assumptions!$B$28 | D8: =Assumptions!$B$10*12 - $A8*D$6 - $A8*Assumptions!$B$25 - Assumptions!$B$26 - Assumptions!$B$10*12*Assumptions!$B$28 | E8: =Assumptions!$B$10*12 - $A8*E$6 - $A8*Assumptions!$B$25 - Assumptions!$B$26 - Assumptions!$B$10*12*Assumptions!$B$28 | F8: =Assumptions!$B$10*12 - $A8*F$6 - $A8*Assumptions!$B$25 - Assumptions!$B$26 - Assumptions!$B$10*12*Assumptions!$B$28 | G8: =Assumptions!$B$10*12 - $A8*G$6 - $A8*Assumptions!$B$25 - Assumptions!$B$26 - Assumptions!$B$10*12*Assumptions!$B$28
A9: 0.15 | B9: =Assumptions!$B$10*12 - $A9*B$6 - $A9*Assumptions!$B$25 - Assumptions!$B$26 - Assumptions!$B$10*12*Assumptions!$B$28 | C9: =Assumptions!$B$10*12 - $A9*C$6 - $A9*Assumptions!$B$25 - Assumptions!$B$26 - Assumptions!$B$10*12*Assumptions!$B$28 | D9: =Assumptions!$B$10*12 - $A9*D$6 - $A9*Assumptions!$B$25 - Assumptions!$B$26 - Assumptions!$B$10*12*Assumptions!$B$28 | E9: =Assumptions!$B$10*12 - $A9*E$6 - $A9*Assumptions!$B$25 - Assumptions!$B$26 - Assumptions!$B$10*12*Assumptions!$B$28 | F9: =Assumptions!$B$10*12 - $A9*F$6 - $A9*Assumptions!$B$25 - Assumptions!$B$26 - Assumptions!$B$10*12*Assumptions!$B$28 | G9: =Assumptions!$B$10*12 - $A9*G$6 - $A9*Assumptions!$B$25 - Assumptions!$B$26 - Assumptions!$B$10*12*Assumptions!$B$28
A10: 0.2 | B10: =Assumptions!$B$10*12 - $A10*B$6 - $A10*Assumptions!$B$25 - Assumptions!$B$26 - Assumptions!$B$10*12*Assumptions!$B$28 | C10: =Assumptions!$B$10*12 - $A10*C$6 - $A10*Assumptions!$B$25 - Assumptions!$B$26 - Assumptions!$B$10*12*Assumptions!$B$28 | D10: =Assumptions!$B$10*12 - $A10*D$6 - $A10*Assumptions!$B$25 - Assumptions!$B$26 - Assumptions!$B$10*12*Assumptions!$B$28 | E10: =Assumptions!$B$10*12 - $A10*E$6 - $A10*Assumptions!$B$25 - Assumptions!$B$26 - Assumptions!$B$10*12*Assumptions!$B$28 | F10: =Assumptions!$B$10*12 - $A10*F$6 - $A10*Assumptions!$B$25 - Assumptions!$B$26 - Assumptions!$B$10*12*Assumptions!$B$28 | G10: =Assumptions!$B$10*12 - $A10*G$6 - $A10*Assumptions!$B$25 - Assumptions!$B$26 - Assumptions!$B$10*12*Assumptions!$B$28
A11: 0.25 | B11: =Assumptions!$B$10*12 - $A11*B$6 - $A11*Assumptions!$B$25 - Assumptions!$B$26 - Assumptions!$B$10*12*Assumptions!$B$28 | C11: =Assumptions!$B$10*12 - $A11*C$6 - $A11*Assumptions!$B$25 - Assumptions!$B$26 - Assumptions!$B$10*12*Assumptions!$B$28 | D11: =Assumptions!$B$10*12 - $A11*D$6 - $A11*Assumptions!$B$25 - Assumptions!$B$26 - Assumptions!$B$10*12*Assumptions!$B$28 | E11: =Assumptions!$B$10*12 - $A11*E$6 - $A11*Assumptions!$B$25 - Assumptions!$B$26 - Assumptions!$B$10*12*Assumptions!$B$28 | F11: =Assumptions!$B$10*12 - $A11*F$6 - $A11*Assumptions!$B$25 - Assumptions!$B$26 - Assumptions!$B$10*12*Assumptions!$B$28 | G11: =Assumptions!$B$10*12 - $A11*G$6 - $A11*Assumptions!$B$25 - Assumptions!$B$26 - Assumptions!$B$10*12*Assumptions!$B$28
A12: 0.3 | B12: =Assumptions!$B$10*12 - $A12*B$6 - $A12*Assumptions!$B$25 - Assumptions!$B$26 - Assumptions!$B$10*12*Assumptions!$B$28 | C12: =Assumptions!$B$10*12 - $A12*C$6 - $A12*Assumptions!$B$25 - Assumptions!$B$26 - Assumptions!$B$10*12*Assumptions!$B$28 | D12: =Assumptions!$B$10*12 - $A12*D$6 - $A12*Assumptions!$B$25 - Assumptions!$B$26 - Assumptions!$B$10*12*Assumptions!$B$28 | E12: =Assumptions!$B$10*12 - $A12*E$6 - $A12*Assumptions!$B$25 - Assumptions!$B$26 - Assumptions!$B$10*12*Assumptions!$B$28 | F12: =Assumptions!$B$10*12 - $A12*F$6 - $A12*Assumptions!$B$25 - Assumptions!$B$26 - Assumptions!$B$10*12*Assumptions!$B$28 | G12: =Assumptions!$B$10*12 - $A12*G$6 - $A12*Assumptions!$B$25 - Assumptions!$B$26 - Assumptions!$B$10*12*Assumptions!$B$28
A13: 0.4 | B13: =Assumptions!$B$10*12 - $A13*B$6 - $A13*Assumptions!$B$25 - Assumptions!$B$26 - Assumptions!$B$10*12*Assumptions!$B$28 | C13: =Assumptions!$B$10*12 - $A13*C$6 - $A13*Assumptions!$B$25 - Assumptions!$B$26 - Assumptions!$B$10*12*Assumptions!$B$28 | D13: =Assumptions!$B$10*12 - $A13*D$6 - $A13*Assumptions!$B$25 - Assumptions!$B$26 - Assumptions!$B$10*12*Assumptions!$B$28 | E13: =Assumptions!$B$10*12 - $A13*E$6 - $A13*Assumptions!$B$25 - Assumptions!$B$26 - Assumptions!$B$10*12*Assumptions!$B$28 | F13: =Assumptions!$B$10*12 - $A13*F$6 - $A13*Assumptions!$B$25 - Assumptions!$B$26 - Assumptions!$B$10*12*Assumptions!$B$28 | G13: =Assumptions!$B$10*12 - $A13*G$6 - $A13*Assumptions!$B$25 - Assumptions!$B$26 - Assumptions!$B$10*12*Assumptions!$B$28
A16: $4.99 — per-member annual contribution (rows=utilization, cols=loaded cost/call)
A17: Util \ Cost | B17: 75 | C17: 100 | D17: 125 | E17: 150 | F17: 200 | G17: 250
A18: 0.05 | B18: =Assumptions!$B$11*12 - $A18*B$17 - $A18*Assumptions!$B$25 - Assumptions!$B$26 - Assumptions!$B$11*12*Assumptions!$B$28 | C18: =Assumptions!$B$11*12 - $A18*C$17 - $A18*Assumptions!$B$25 - Assumptions!$B$26 - Assumptions!$B$11*12*Assumptions!$B$28 | D18: =Assumptions!$B$11*12 - $A18*D$17 - $A18*Assumptions!$B$25 - Assumptions!$B$26 - Assumptions!$B$11*12*Assumptions!$B$28 | E18: =Assumptions!$B$11*12 - $A18*E$17 - $A18*Assumptions!$B$25 - Assumptions!$B$26 - Assumptions!$B$11*12*Assumptions!$B$28 | F18: =Assumptions!$B$11*12 - $A18*F$17 - $A18*Assumptions!$B$25 - Assumptions!$B$26 - Assumptions!$B$11*12*Assumptions!$B$28 | G18: =Assumptions!$B$11*12 - $A18*G$17 - $A18*Assumptions!$B$25 - Assumptions!$B$26 - Assumptions!$B$11*12*Assumptions!$B$28
A19: 0.1 | B19: =Assumptions!$B$11*12 - $A19*B$17 - $A19*Assumptions!$B$25 - Assumptions!$B$26 - Assumptions!$B$11*12*Assumptions!$B$28 | C19: =Assumptions!$B$11*12 - $A19*C$17 - $A19*Assumptions!$B$25 - Assumptions!$B$26 - Assumptions!$B$11*12*Assumptions!$B$28 | D19: =Assumptions!$B$11*12 - $A19*D$17 - $A19*Assumptions!$B$25 - Assumptions!$B$26 - Assumptions!$B$11*12*Assumptions!$B$28 | E19: =Assumptions!$B$11*12 - $A19*E$17 - $A19*Assumptions!$B$25 - Assumptions!$B$26 - Assumptions!$B$11*12*Assumptions!$B$28 | F19: =Assumptions!$B$11*12 - $A19*F$17 - $A19*Assumptions!$B$25 - Assumptions!$B$26 - Assumptions!$B$11*12*Assumptions!$B$28 | G19: =Assumptions!$B$11*12 - $A19*G$17 - $A19*Assumptions!$B$25 - Assumptions!$B$26 - Assumptions!$B$11*12*Assumptions!$B$28
A20: 0.15 | B20: =Assumptions!$B$11*12 - $A20*B$17 - $A20*Assumptions!$B$25 - Assumptions!$B$26 - Assumptions!$B$11*12*Assumptions!$B$28 | C20: =Assumptions!$B$11*12 - $A20*C$17 - $A20*Assumptions!$B$25 - Assumptions!$B$26 - Assumptions!$B$11*12*Assumptions!$B$28 | D20: =Assumptions!$B$11*12 - $A20*D$17 - $A20*Assumptions!$B$25 - Assumptions!$B$26 - Assumptions!$B$11*12*Assumptions!$B$28 | E20: =Assumptions!$B$11*12 - $A20*E$17 - $A20*Assumptions!$B$25 - Assumptions!$B$26 - Assumptions!$B$11*12*Assumptions!$B$28 | F20: =Assumptions!$B$11*12 - $A20*F$17 - $A20*Assumptions!$B$25 - Assumptions!$B$26 - Assumptions!$B$11*12*Assumptions!$B$28 | G20: =Assumptions!$B$11*12 - $A20*G$17 - $A20*Assumptions!$B$25 - Assumptions!$B$26 - Assumptions!$B$11*12*Assumptions!$B$28
A21: 0.2 | B21: =Assumptions!$B$11*12 - $A21*B$17 - $A21*Assumptions!$B$25 - Assumptions!$B$26 - Assumptions!$B$11*12*Assumptions!$B$28 | C21: =Assumptions!$B$11*12 - $A21*C$17 - $A21*Assumptions!$B$25 - Assumptions!$B$26 - Assumptions!$B$11*12*Assumptions!$B$28 | D21: =Assumptions!$B$11*12 - $A21*D$17 - $A21*Assumptions!$B$25 - Assumptions!$B$26 - Assumptions!$B$11*12*Assumptions!$B$28 | E21: =Assumptions!$B$11*12 - $A21*E$17 - $A21*Assumptions!$B$25 - Assumptions!$B$26 - Assumptions!$B$11*12*Assumptions!$B$28 | F21: =Assumptions!$B$11*12 - $A21*F$17 - $A21*Assumptions!$B$25 - Assumptions!$B$26 - Assumptions!$B$11*12*Assumptions!$B$28 | G21: =Assumptions!$B$11*12 - $A21*G$17 - $A21*Assumptions!$B$25 - Assumptions!$B$26 - Assumptions!$B$11*12*Assumptions!$B$28
A22: 0.25 | B22: =Assumptions!$B$11*12 - $A22*B$17 - $A22*Assumptions!$B$25 - Assumptions!$B$26 - Assumptions!$B$11*12*Assumptions!$B$28 | C22: =Assumptions!$B$11*12 - $A22*C$17 - $A22*Assumptions!$B$25 - Assumptions!$B$26 - Assumptions!$B$11*12*Assumptions!$B$28 | D22: =Assumptions!$B$11*12 - $A22*D$17 - $A22*Assumptions!$B$25 - Assumptions!$B$26 - Assumptions!$B$11*12*Assumptions!$B$28 | E22: =Assumptions!$B$11*12 - $A22*E$17 - $A22*Assumptions!$B$25 - Assumptions!$B$26 - Assumptions!$B$11*12*Assumptions!$B$28 | F22: =Assumptions!$B$11*12 - $A22*F$17 - $A22*Assumptions!$B$25 - Assumptions!$B$26 - Assumptions!$B$11*12*Assumptions!$B$28 | G22: =Assumptions!$B$11*12 - $A22*G$17 - $A22*Assumptions!$B$25 - Assumptions!$B$26 - Assumptions!$B$11*12*Assumptions!$B$28
A23: 0.3 | B23: =Assumptions!$B$11*12 - $A23*B$17 - $A23*Assumptions!$B$25 - Assumptions!$B$26 - Assumptions!$B$11*12*Assumptions!$B$28 | C23: =Assumptions!$B$11*12 - $A23*C$17 - $A23*Assumptions!$B$25 - Assumptions!$B$26 - Assumptions!$B$11*12*Assumptions!$B$28 | D23: =Assumptions!$B$11*12 - $A23*D$17 - $A23*Assumptions!$B$25 - Assumptions!$B$26 - Assumptions!$B$11*12*Assumptions!$B$28 | E23: =Assumptions!$B$11*12 - $A23*E$17 - $A23*Assumptions!$B$25 - Assumptions!$B$26 - Assumptions!$B$11*12*Assumptions!$B$28 | F23: =Assumptions!$B$11*12 - $A23*F$17 - $A23*Assumptions!$B$25 - Assumptions!$B$26 - Assumptions!$B$11*12*Assumptions!$B$28 | G23: =Assumptions!$B$11*12 - $A23*G$17 - $A23*Assumptions!$B$25 - Assumptions!$B$26 - Assumptions!$B$11*12*Assumptions!$B$28
A24: 0.4 | B24: =Assumptions!$B$11*12 - $A24*B$17 - $A24*Assumptions!$B$25 - Assumptions!$B$26 - Assumptions!$B$11*12*Assumptions!$B$28 | C24: =Assumptions!$B$11*12 - $A24*C$17 - $A24*Assumptions!$B$25 - Assumptions!$B$26 - Assumptions!$B$11*12*Assumptions!$B$28 | D24: =Assumptions!$B$11*12 - $A24*D$17 - $A24*Assumptions!$B$25 - Assumptions!$B$26 - Assumptions!$B$11*12*Assumptions!$B$28 | E24: =Assumptions!$B$11*12 - $A24*E$17 - $A24*Assumptions!$B$25 - Assumptions!$B$26 - Assumptions!$B$11*12*Assumptions!$B$28 | F24: =Assumptions!$B$11*12 - $A24*F$17 - $A24*Assumptions!$B$25 - Assumptions!$B$26 - Assumptions!$B$11*12*Assumptions!$B$28 | G24: =Assumptions!$B$11*12 - $A24*G$17 - $A24*Assumptions!$B$25 - Assumptions!$B$26 - Assumptions!$B$11*12*Assumptions!$B$28
A27: Green = profitable per member; Clay = unprofitable. Loaded cost/call default is computed on Assumptions.

Sheet Churn Sensitivity
A1: RIVR Tech — Churn Sensitivity
A2: Net annual effect vs. incremental annual churn (mandatory, current subs)
A3: v1.0 (Draft for Executive Review) | 2026-07-29 | LREMC Technologies, LLC d/b/a RIVR Tech | NOT LEGAL ADVICE
A5: Incremental churn wipes out plan value once net turns negative.
A6: Incremental Annual Churn | B6: Churned Customers | C6: Lost Internet Rev | D6: Net $3.99 (Mandatory) | E6: Net $4.99 (Mandatory)
A7: 0 | B7: =Assumptions!$B$7*A7 | C7: =B7*Assumptions!$B$9*12 | D7: =Assumptions!$B$7*Assumptions!$B$10*12-(Assumptions!$B$7*Assumptions!$B$17*Assumptions!$B$35)-(Assumptions!$B$7*Assumptions!$B$17*Assumptions!$B$25)-(Assumptions!$B$7*Assumptions!$B$26)-(Assumptions!$B$7*Assumptions!$B$10*12*Assumptions!$B$28)-(Assumptions!$B$32+Assumptions!$B$33)-C7 | E7: =Assumptions!$B$7*Assumptions!$B$11*12-(Assumptions!$B$7*Assumptions!$B$17*Assumptions!$B$35)-(Assumptions!$B$7*Assumptions!$B$17*Assumptions!$B$25)-(Assumptions!$B$7*Assumptions!$B$26)-(Assumptions!$B$7*Assumptions!$B$11*12*Assumptions!$B$28)-(Assumptions!$B$32+Assumptions!$B$33)-C7
A8: 0.0025 | B8: =Assumptions!$B$7*A8 | C8: =B8*Assumptions!$B$9*12 | D8: =Assumptions!$B$7*Assumptions!$B$10*12-(Assumptions!$B$7*Assumptions!$B$17*Assumptions!$B$35)-(Assumptions!$B$7*Assumptions!$B$17*Assumptions!$B$25)-(Assumptions!$B$7*Assumptions!$B$26)-(Assumptions!$B$7*Assumptions!$B$10*12*Assumptions!$B$28)-(Assumptions!$B$32+Assumptions!$B$33)-C8 | E8: =Assumptions!$B$7*Assumptions!$B$11*12-(Assumptions!$B$7*Assumptions!$B$17*Assumptions!$B$35)-(Assumptions!$B$7*Assumptions!$B$17*Assumptions!$B$25)-(Assumptions!$B$7*Assumptions!$B$26)-(Assumptions!$B$7*Assumptions!$B$11*12*Assumptions!$B$28)-(Assumptions!$B$32+Assumptions!$B$33)-C8
A9: 0.005 | B9: =Assumptions!$B$7*A9 | C9: =B9*Assumptions!$B$9*12 | D9: =Assumptions!$B$7*Assumptions!$B$10*12-(Assumptions!$B$7*Assumptions!$B$17*Assumptions!$B$35)-(Assumptions!$B$7*Assumptions!$B$17*Assumptions!$B$25)-(Assumptions!$B$7*Assumptions!$B$26)-(Assumptions!$B$7*Assumptions!$B$10*12*Assumptions!$B$28)-(Assumptions!$B$32+Assumptions!$B$33)-C9 | E9: =Assumptions!$B$7*Assumptions!$B$11*12-(Assumptions!$B$7*Assumptions!$B$17*Assumptions!$B$35)-(Assumptions!$B$7*Assumptions!$B$17*Assumptions!$B$25)-(Assumptions!$B$7*Assumptions!$B$26)-(Assumptions!$B$7*Assumptions!$B$11*12*Assumptions!$B$28)-(Assumptions!$B$32+Assumptions!$B$33)-C9
A10: 0.01 | B10: =Assumptions!$B$7*A10 | C10: =B10*Assumptions!$B$9*12 | D10: =Assumptions!$B$7*Assumptions!$B$10*12-(Assumptions!$B$7*Assumptions!$B$17*Assumptions!$B$35)-(Assumptions!$B$7*Assumptions!$B$17*Assumptions!$B$25)-(Assumptions!$B$7*Assumptions!$B$26)-(Assumptions!$B$7*Assumptions!$B$10*12*Assumptions!$B$28)-(Assumptions!$B$32+Assumptions!$B$33)-C10 | E10: =Assumptions!$B$7*Assumptions!$B$11*12-(Assumptions!$B$7*Assumptions!$B$17*Assumptions!$B$35)-(Assumptions!$B$7*Assumptions!$B$17*Assumptions!$B$25)-(Assumptions!$B$7*Assumptions!$B$26)-(Assumptions!$B$7*Assumptions!$B$11*12*Assumptions!$B$28)-(Assumptions!$B$32+Assumptions!$B$33)-C10
A11: 0.02 | B11: =Assumptions!$B$7*A11 | C11: =B11*Assumptions!$B$9*12 | D11: =Assumptions!$B$7*Assumptions!$B$10*12-(Assumptions!$B$7*Assumptions!$B$17*Assumptions!$B$35)-(Assumptions!$B$7*Assumptions!$B$17*Assumptions!$B$25)-(Assumptions!$B$7*Assumptions!$B$26)-(Assumptions!$B$7*Assumptions!$B$10*12*Assumptions!$B$28)-(Assumptions!$B$32+Assumptions!$B$33)-C11 | E11: =Assumptions!$B$7*Assumptions!$B$11*12-(Assumptions!$B$7*Assumptions!$B$17*Assumptions!$B$35)-(Assumptions!$B$7*Assumptions!$B$17*Assumptions!$B$25)-(Assumptions!$B$7*Assumptions!$B$26)-(Assumptions!$B$7*Assumptions!$B$11*12*Assumptions!$B$28)-(Assumptions!$B$32+Assumptions!$B$33)-C11
A12: 0.03 | B12: =Assumptions!$B$7*A12 | C12: =B12*Assumptions!$B$9*12 | D12: =Assumptions!$B$7*Assumptions!$B$10*12-(Assumptions!$B$7*Assumptions!$B$17*Assumptions!$B$35)-(Assumptions!$B$7*Assumptions!$B$17*Assumptions!$B$25)-(Assumptions!$B$7*Assumptions!$B$26)-(Assumptions!$B$7*Assumptions!$B$10*12*Assumptions!$B$28)-(Assumptions!$B$32+Assumptions!$B$33)-C12 | E12: =Assumptions!$B$7*Assumptions!$B$11*12-(Assumptions!$B$7*Assumptions!$B$17*Assumptions!$B$35)-(Assumptions!$B$7*Assumptions!$B$17*Assumptions!$B$25)-(Assumptions!$B$7*Assumptions!$B$26)-(Assumptions!$B$7*Assumptions!$B$11*12*Assumptions!$B$28)-(Assumptions!$B$32+Assumptions!$B$33)-C12
A13: 0.05 | B13: =Assumptions!$B$7*A13 | C13: =B13*Assumptions!$B$9*12 | D13: =Assumptions!$B$7*Assumptions!$B$10*12-(Assumptions!$B$7*Assumptions!$B$17*Assumptions!$B$35)-(Assumptions!$B$7*Assumptions!$B$17*Assumptions!$B$25)-(Assumptions!$B$7*Assumptions!$B$26)-(Assumptions!$B$7*Assumptions!$B$10*12*Assumptions!$B$28)-(Assumptions!$B$32+Assumptions!$B$33)-C13 | E13: =Assumptions!$B$7*Assumptions!$B$11*12-(Assumptions!$B$7*Assumptions!$B$17*Assumptions!$B$35)-(Assumptions!$B$7*Assumptions!$B$17*Assumptions!$B$25)-(Assumptions!$B$7*Assumptions!$B$26)-(Assumptions!$B$7*Assumptions!$B$11*12*Assumptions!$B$28)-(Assumptions!$B$32+Assumptions!$B$33)-C13
A15: Break-even incremental churn (mandatory): $3.99 ≈ 1.79% · $4.99 ≈ 3.10% (computed).

Sheet Pay-Per-Visit
A1: RIVR Tech — Pay-Per-Visit Comparison
A2: Charge non-enrolled customers per customer-caused visit
A3: v1.0 (Draft for Executive Review) | 2026-07-29 | LREMC Technologies, LLC d/b/a RIVR Tech | NOT LEGAL ADVICE
A6: Charge / Visit | B6: Customer-Caused Calls/yr | C6: Gross Billed | D6: Collected (recovered) | E6: Loaded Cost (incurred anyway) | F6: Cost Recovery %
A7: 75 | B7: =Assumptions!$B$7*Assumptions!$B$15*Assumptions!$B$16 | C7: =B7*A7 | D7: =C7*Assumptions!$B$34 | E7: =B7*(Assumptions!$B$35+Assumptions!$B$25) | F7: =D7/E7
A8: 99 | B8: =Assumptions!$B$7*Assumptions!$B$15*Assumptions!$B$16 | C8: =B8*A8 | D8: =C8*Assumptions!$B$34 | E8: =B8*(Assumptions!$B$35+Assumptions!$B$25) | F8: =D8/E8
A9: 125 | B9: =Assumptions!$B$7*Assumptions!$B$15*Assumptions!$B$16 | C9: =B9*A9 | D9: =C9*Assumptions!$B$34 | E9: =B9*(Assumptions!$B$35+Assumptions!$B$25) | F9: =D9/E9
A10: 150 | B10: =Assumptions!$B$7*Assumptions!$B$15*Assumptions!$B$16 | C10: =B10*A10 | D10: =C10*Assumptions!$B$34 | E10: =B10*(Assumptions!$B$35+Assumptions!$B$25) | F10: =D10/E10
A11: Cost is incurred whether or not RIVR bills; 'Collected' is revenue recovered against an otherwise-absorbed cost. No single charge in this range fully covers the loaded call cost — an argument for the subscription risk-pool.
A12: Qualitative comparison
A13: Dimension | B13: Monthly Plan | C13: Pay-Per-Visit
A14: Revenue predictability | B14: High (recurring) | C14: Low (event-driven)
A15: Customer acceptance | B15: Mixed (if mandatory) | C15: Higher (only users pay)
A16: Administrative complexity | B16: Higher (enrollment/billing) | C16: Lower per event, disputes per visit
A17: Technician documentation | B17: Lighter (covered) | C17: Heavy (must justify each charge)
A18: Billing disputes | B18: Fewer per-visit disputes | C18: More per-visit disputes
A19: Collection risk | B19: Spread across base | C19: Concentrated at billing
A20: Utilization risk | B20: Provider bears it | C20: Customer bears it
A21: Fairness to non-users | B21: Low (all pay) | C21: High (only users pay)

Sheet Five-Year Forecast
A1: RIVR Tech — Five-Year Forecast
A2: Recommended structure: voluntary opt-in $3.99 at expected enrollment
A3: v1.0 (Draft for Executive Review) | 2026-07-29 | LREMC Technologies, LLC d/b/a RIVR Tech | NOT LEGAL ADVICE
A5: Recommended enrollment (opt-in, editable): | C5: 0.35
A7: Year | B7: Subscribers | C7: Enrolled | D7: Price | E7: Gross Annual | F7: Net Annual | G7: Cum. Gross | H7: Cum. Net
A8: 1 | B8: =Assumptions!$B$7 | C8: =B8*'Five-Year Forecast'!$C$5 | D8: =Assumptions!$B$10 | E8: =C8*D8*12 | F8: =E8-(C8*Assumptions!$B$17*Assumptions!$B$35)-(C8*Assumptions!$B$17*Assumptions!$B$25)-(C8*Assumptions!$B$26)-(E8*Assumptions!$B$28)-(Assumptions!$B$32+Assumptions!$B$33)-(Assumptions!$B$30+Assumptions!$B$31) | G8: =E8 | H8: =F8
A9: 2 | B9: =B8*(1+Assumptions!$B$8)^12 | C9: =B9*'Five-Year Forecast'!$C$5 | D9: =D8*(1+Assumptions!$B$27) | E9: =C9*D9*12 | F9: =E9-(C9*Assumptions!$B$17*Assumptions!$B$35)-(C9*Assumptions!$B$17*Assumptions!$B$25)-(C9*Assumptions!$B$26)-(E9*Assumptions!$B$28)-(Assumptions!$B$32+Assumptions!$B$33)-0 | G9: =G8+E9 | H9: =H8+F9
A10: 3 | B10: =B9*(1+Assumptions!$B$8)^12 | C10: =B10*'Five-Year Forecast'!$C$5 | D10: =D9*(1+Assumptions!$B$27) | E10: =C10*D10*12 | F10: =E10-(C10*Assumptions!$B$17*Assumptions!$B$35)-(C10*Assumptions!$B$17*Assumptions!$B$25)-(C10*Assumptions!$B$26)-(E10*Assumptions!$B$28)-(Assumptions!$B$32+Assumptions!$B$33)-0 | G10: =G9+E10 | H10: =H9+F10
A11: 4 | B11: =B10*(1+Assumptions!$B$8)^12 | C11: =B11*'Five-Year Forecast'!$C$5 | D11: =D10*(1+Assumptions!$B$27) | E11: =C11*D11*12 | F11: =E11-(C11*Assumptions!$B$17*Assumptions!$B$35)-(C11*Assumptions!$B$17*Assumptions!$B$25)-(C11*Assumptions!$B$26)-(E11*Assumptions!$B$28)-(Assumptions!$B$32+Assumptions!$B$33)-0 | G11: =G10+E11 | H11: =H10+F11
A12: 5 | B12: =B11*(1+Assumptions!$B$8)^12 | C12: =B12*'Five-Year Forecast'!$C$5 | D12: =D11*(1+Assumptions!$B$27) | E12: =C12*D12*12 | F12: =E12-(C12*Assumptions!$B$17*Assumptions!$B$35)-(C12*Assumptions!$B$17*Assumptions!$B$25)-(C12*Assumptions!$B$26)-(E12*Assumptions!$B$28)-(Assumptions!$B$32+Assumptions!$B$33)-0 | G12: =G11+E12 | H12: =H11+F12
A14: Voluntary opt-in assumes ~0 fee-driven churn (enrollees chose the plan). Excludes pay-per-visit revenue from decliners — the hybrid adds that upside. Year 1 net absorbs one-time launch/billing costs.

Sheet Recommendation Summary
A1: RIVR Tech — Recommendation Summary
A2: Weighted decision matrix (scores 1-5; higher = better)
A3: v1.0 (Draft for Executive Review) | 2026-07-29 | LREMC Technologies, LLC d/b/a RIVR Tech | NOT LEGAL ADVICE
A5: Criteria & Weights
A6: Criterion | B6: Weight %
A7: Net financial benefit | B7: 15
A8: Customer fairness | B8: 12
A9: Customer acceptance | B9: 12
A10: Regulatory risk (5=low risk) | B10: 15
A11: Operational simplicity | B11: 8
A12: Revenue predictability | B12: 8
A13: Churn risk (5=low risk) | B13: 12
A14: Brand impact | B14: 10
A15: Scalability | B15: 4
A16: Ease of implementation | B16: 4
A18: Weighted Scores by Option
A19: Option | B19: Net financial benefit | C19: Customer fairness | D19: Customer acceptance | E19: Regulatory risk (5=low risk) | F19: Operational simplicity | G19: Revenue predictability | H19: Churn risk (5=low risk) | I19: Brand impact | J19: Scalability | K19: Ease of implementation | L19: Weighted Score | M19: Rank
A20: Mandatory $3.99 | B20: 5 | C20: 1 | D20: 1 | E20: 1 | F20: 4 | G20: 5 | H20: 1 | I20: 1 | J20: 5 | K20: 3 | L20: =SUMPRODUCT(B20:K20,TRANSPOSE($B$7:$B$16))/SUM($B$7:$B$16) | M20: =RANK(L20,L20:L28)
A21: Mandatory $4.99 | B21: 5 | C21: 1 | D21: 1 | E21: 1 | F21: 4 | G21: 5 | H21: 1 | I21: 1 | J21: 5 | K21: 3 | L21: =SUMPRODUCT(B21:K21,TRANSPOSE($B$7:$B$16))/SUM($B$7:$B$16) | M21: =RANK(L21,L20:L28)
A22: Opt-out $3.99 | B22: 4 | C22: 2 | D22: 2 | E22: 2 | F22: 3 | G22: 4 | H22: 2 | I22: 2 | J22: 4 | K22: 3 | L22: =SUMPRODUCT(B22:K22,TRANSPOSE($B$7:$B$16))/SUM($B$7:$B$16) | M22: =RANK(L22,L20:L28)
A23: Opt-out $4.99 | B23: 4 | C23: 2 | D23: 2 | E23: 2 | F23: 3 | G23: 4 | H23: 2 | I23: 2 | J23: 4 | K23: 3 | L23: =SUMPRODUCT(B23:K23,TRANSPOSE($B$7:$B$16))/SUM($B$7:$B$16) | M23: =RANK(L23,L20:L28)
A24: Opt-in $3.99 | B24: 3 | C24: 5 | D24: 5 | E24: 5 | F24: 3 | G24: 3 | H24: 5 | I24: 5 | J24: 4 | K24: 4 | L24: =SUMPRODUCT(B24:K24,TRANSPOSE($B$7:$B$16))/SUM($B$7:$B$16) | M24: =RANK(L24,L20:L28)
A25: Opt-in $4.99 | B25: 3 | C25: 5 | D25: 4 | E25: 5 | F25: 3 | G25: 3 | H25: 5 | I25: 5 | J25: 4 | K25: 4 | L25: =SUMPRODUCT(B25:K25,TRANSPOSE($B$7:$B$16))/SUM($B$7:$B$16) | M25: =RANK(L25,L20:L28)
A26: Pay-per-visit only | B26: 2 | C26: 4 | D26: 3 | E26: 4 | F26: 2 | G26: 1 | H26: 4 | I26: 3 | J26: 3 | K26: 3 | L26: =SUMPRODUCT(B26:K26,TRANSPOSE($B$7:$B$16))/SUM($B$7:$B$16) | M26: =RANK(L26,L20:L28)
A27: Hybrid (opt-in + PPV) | B27: 4 | C27: 5 | D27: 4 | E27: 4 | F27: 2 | G27: 3 | H27: 5 | I27: 5 | J27: 4 | K27: 3 | L27: =SUMPRODUCT(B27:K27,TRANSPOSE($B$7:$B$16))/SUM($B$7:$B$16) | M27: =RANK(L27,L20:L28)
A28: Do not implement | B28: 1 | C28: 4 | D28: 5 | E28: 5 | F28: 5 | G28: 1 | H28: 5 | I28: 4 | J28: 2 | K28: 5 | L28: =SUMPRODUCT(B28:K28,TRANSPOSE($B$7:$B$16))/SUM($B$7:$B$16) | M28: =RANK(L28,L20:L28)
A31: RECOMMENDATION
A32: Voluntary opt-in at $3.99 (Basic/Standard coverage) delivered as a HYBRID: enrollees get the plan; customers who decline pay a per-visit dispatch charge. Do NOT implement a mandatory blanket fee. Exempt Lifeline/Tribal/low-income (opt-in only); exclude bulk/managed properties. Requires legal review of negative-option/consumer-protection rules.
