Workbook

Sheet Instructions
A1: INSTRUCTIONS
A2: PRELIMINARY DRAFT – NO CONTROLLING TBCP AWARD OR SOURCE DOCUMENTS SUPPLIED – PROVISIONAL BASELINE: MARCH 2024 AMENDED ROUND 2 NOFO – SUBJECT TO LEGAL, GRANT AND FINANCIAL REVIEW
B3: Parties: Lumbee Tribe of North Carolina (the “Lumbee Tribe”); LREMC Technologies, LLC d/b/a RIVR Tech (“RIVR Tech”); Lumbee River Electric Membership Corporation d/b/a Lumbee River EMC (“LREMC”), separate asset owner.
B5: Annual Budget, Capital-Refresh, Replacement-Reserve & Sustainability
B6: Purpose: plan the annual operating budget, capital-refresh, and replacement-reserve funding, and test long-run sustainability of the Tribal Network.
B7: • Amber INPUT cells are yours; blue FORMULA and green OUTPUT cells compute.
B8: • Checks flag if the replacement reserve is underfunded or if revenue does not cover operating expense.
B9: • Cross-reference: Network Operations, Maintenance, and Lifecycle Agreement and Schedule S6 (Operations, Service Levels, Lifecycle, Spares, Refresh, and Reserves).
B10: • PRELIMINARY DRAFT – SUBJECT TO LEGAL, GRANT AND FINANCIAL REVIEW
A12: Legend: | B12: INPUT (edit these) | C12: FORMULA (do not edit) | D12: OUTPUT / RESULT

Sheet Operating Budget
A1: Annual Operating Budget
A2: PRELIMINARY DRAFT – NO CONTROLLING TBCP AWARD OR SOURCE DOCUMENTS SUPPLIED – PROVISIONAL BASELINE: MARCH 2024 AMENDED ROUND 2 NOFO – SUBJECT TO LEGAL, GRANT AND FINANCIAL REVIEW
A3: Budget year: [■ year]
A5: Line Item | B5: Amount | C5: % of Revenue | D5: Notes
A6: REVENUE
A7: Per-Active-Subscriber operating revenue | B7: [■ $ amount] | C7: =IFERROR(B7/$B$11,0) | D7: [■ notes]
A8: Other retail revenue | B8: [■ $ amount] | C8: =IFERROR(B8/$B$11,0) | D8: [■ notes]
A9: Approved commercial / non-project use revenue | B9: [■ $ amount] | C9: =IFERROR(B9/$B$11,0) | D9: [■ notes]
A10: Other income | B10: [■ $ amount] | C10: =IFERROR(B10/$B$11,0) | D10: [■ notes]
A11: Total Revenue | B11: =SUM(B7:B10) | C11: =IFERROR(B11/B11,0)
A13: OPERATING EXPENSE
A14: Network operations & maintenance (O&M) | B14: [■ $ amount] | C14: =IFERROR(B14/$B$11,0) | D14: [■ notes]
A15: NOC / monitoring (24x7x365) | B15: [■ $ amount] | C15: =IFERROR(B15/$B$11,0) | D15: [■ notes]
A16: Field labor & vehicles | B16: [■ $ amount] | C16: =IFERROR(B16/$B$11,0) | D16: [■ notes]
A17: Power & site costs | B17: [■ $ amount] | C17: =IFERROR(B17/$B$11,0) | D17: [■ notes]
A18: Pole / easement / ROW / LREMC facility fees | B18: [■ $ amount] | C18: =IFERROR(B18/$B$11,0) | D18: [■ notes]
A19: Transport & IP transit | B19: [■ $ amount] | C19: =IFERROR(B19/$B$11,0) | D19: [■ notes]
A20: Billing, customer care & collections | B20: [■ $ amount] | C20: =IFERROR(B20/$B$11,0) | D20: [■ notes]
A21: Insurance | B21: [■ $ amount] | C21: =IFERROR(B21/$B$11,0) | D21: [■ notes]
A22: Software & licenses | B22: [■ $ amount] | C22: =IFERROR(B22/$B$11,0) | D22: [■ notes]
A23: Administrative & compliance | B23: [■ $ amount] | C23: =IFERROR(B23/$B$11,0) | D23: [■ notes]
A24: Taxes & regulatory fees | B24: [■ $ amount] | C24: =IFERROR(B24/$B$11,0) | D24: [■ notes]
A25: Total Operating Expense | B25: =SUM(B14:B24) | C25: =IFERROR(B25/$B$11,0)
A27: Net Operating Income (Revenue − Opex) | B27: =B11-B25
A28: Reserve contribution (from Reserve Schedule): | B28: ='Reserve Schedule'!B6
A29: Net after reserve contribution | B29: =B27-B28
A31: FORMULA CHECKS
A32: Revenue ≥ Operating Expense: | B32: =IF(B11>=B25,"PASS — revenue covers opex","FLAG — revenue below opex; sustainability risk")
A34: Legend: | B34: INPUT (edit these) | C34: FORMULA (do not edit) | D34: OUTPUT / RESULT

Sheet Capital Refresh
A1: Capital-Refresh Plan
A2: PRELIMINARY DRAFT – NO CONTROLLING TBCP AWARD OR SOURCE DOCUMENTS SUPPLIED – PROVISIONAL BASELINE: MARCH 2024 AMENDED ROUND 2 NOFO – SUBJECT TO LEGAL, GRANT AND FINANCIAL REVIEW
A5: Asset Class | B5: In-Service Year | C5: Expected Useful Life (yrs) | D5: Next Refresh Year | E5: Estimated Refresh Cost | F5: Notes
A6: Outside-plant fiber / cable | B6: [■ year] | C6: [■ life] | D6: =IFERROR(B6+C6,"") | E6: [■ $ cost] | F6: [■ notes]
A7: Splice enclosures / hardware | B7: [■ year] | C7: [■ life] | D7: =IFERROR(B7+C7,"") | E7: [■ $ cost] | F7: [■ notes]
A8: OLT / access electronics | B8: [■ year] | C8: [■ life] | D8: =IFERROR(B8+C8,"") | E8: [■ $ cost] | F8: [■ notes]
A9: Core / aggregation electronics | B9: [■ year] | C9: [■ life] | D9: =IFERROR(B9+C9,"") | E9: [■ $ cost] | F9: [■ notes]
A10: Optical network terminals (ONTs / CPE) | B10: [■ year] | C10: [■ life] | D10: =IFERROR(B10+C10,"") | E10: [■ $ cost] | F10: [■ notes]
A11: Power / backup / batteries | B11: [■ year] | C11: [■ life] | D11: =IFERROR(B11+C11,"") | E11: [■ $ cost] | F11: [■ notes]
A12: Huts / cabinets / enclosures | B12: [■ year] | C12: [■ life] | D12: =IFERROR(B12+C12,"") | E12: [■ $ cost] | F12: [■ notes]
A13: Network monitoring / software | B13: [■ year] | C13: [■ life] | D13: =IFERROR(B13+C13,"") | E13: [■ $ cost] | F13: [■ notes]
A14: Total planned refresh cost | E14: =SUM(E6:E13)
A16: Legend: | B16: INPUT (edit these) | C16: FORMULA (do not edit) | D16: OUTPUT / RESULT

Sheet Reserve Schedule
A1: Replacement-Reserve Schedule
A2: PRELIMINARY DRAFT – NO CONTROLLING TBCP AWARD OR SOURCE DOCUMENTS SUPPLIED – PROVISIONAL BASELINE: MARCH 2024 AMENDED ROUND 2 NOFO – SUBJECT TO LEGAL, GRANT AND FINANCIAL REVIEW
A4: Reserve Line | B4: Amount | C4: Notes
A5: Opening reserve balance | B5: [■ $ balance] | C5: [■ notes]
A6: Annual reserve contribution | B6: [■ $ contribution] | C6: Feeds the Operating Budget
A7: Reserve draws (refresh / replacement) | B7: [■ $ draws] | C7: [■ notes]
A8: Closing reserve balance (opening + contribution − draws) | B8: =IFERROR(B5+B6-B7,0)
A9: Required reserve (target funding level) | B9: [■ $ required reserve target]
A11: FORMULA CHECKS
A12: Closing reserve ≥ required target: | B12: =IF(B8>=B9,"PASS — reserve funded","FLAG — reserve underfunded")
A14: Legend: | B14: INPUT (edit these) | C14: FORMULA (do not edit) | D14: OUTPUT / RESULT

Sheet Capacity Forecast
A1: Capacity & Subscriber Forecast
A2: PRELIMINARY DRAFT – NO CONTROLLING TBCP AWARD OR SOURCE DOCUMENTS SUPPLIED – PROVISIONAL BASELINE: MARCH 2024 AMENDED ROUND 2 NOFO – SUBJECT TO LEGAL, GRANT AND FINANCIAL REVIEW
A5: Metric | B5: Year 1 | C5: Year 2 | D5: Year 3 | E5: Year 5
A6: Locations passed | B6: [■ value] | C6: [■ value] | D6: [■ value] | E6: [■ value]
A7: Active Subscribers | B7: [■ value] | C7: [■ value] | D7: [■ value] | E7: [■ value]
A8: Take rate | B8: [■ value] | C8: [■ value] | D8: [■ value] | E8: [■ value]
A9: Peak utilization (%) | B9: [■ value] | C9: [■ value] | D9: [■ value] | E9: [■ value]
A10: Headroom to capacity (%) | B10: [■ value] | C10: [■ value] | D10: [■ value] | E10: [■ value]
A12: Legend: | B12: INPUT (edit these) | C12: FORMULA (do not edit) | D12: OUTPUT / RESULT

Sheet Sustainability
A1: Annual Sustainability Review
A2: PRELIMINARY DRAFT – NO CONTROLLING TBCP AWARD OR SOURCE DOCUMENTS SUPPLIED – PROVISIONAL BASELINE: MARCH 2024 AMENDED ROUND 2 NOFO – SUBJECT TO LEGAL, GRANT AND FINANCIAL REVIEW
A5: Indicator | B5: Value | C5: Assessment
A6: Total revenue | B6: ='Operating Budget'!B11 | C6: [■ assessment]
A7: Total operating expense | B7: ='Operating Budget'!B25 | C7: [■ assessment]
A8: Net operating income | B8: ='Operating Budget'!B27 | C8: [■ assessment]
A9: Operating margin | B9: =IFERROR('Operating Budget'!B27/'Operating Budget'!B11,0) | C9: [■ assessment]
A10: Reserve funding status | B10: =IF('Reserve Schedule'!B8>='Reserve Schedule'!B9,"Funded","Underfunded") | C10: [■ assessment]
A12: FORMULA CHECKS
A13: Revenue ≥ Opex (self-sustaining): | B13: =IF('Operating Budget'!B11>='Operating Budget'!B25,"PASS — self-sustaining on opex","FLAG — subsidy required")
A14: Replacement reserve funded: | B14: =IF('Reserve Schedule'!B8>='Reserve Schedule'!B9,"PASS — reserve funded","FLAG — reserve underfunded")
A16: Legend: | B16: INPUT (edit these) | C16: FORMULA (do not edit) | D16: OUTPUT / RESULT
