Workbook
Name LL_STD: Assumptions!$C$7
Name LL_TRIBAL_ADD: Assumptions!$C$8
Name LL_TRIBAL_TOTAL: Assumptions!$C$9
Name RETAIL_SENIOR: Assumptions!$C$12
Name RETAIL_STD: Assumptions!$C$13
Name TARGET_PAY: Assumptions!$C$14
Name EQUIP_MO: Assumptions!$C$15
Name INSTALL: Assumptions!$C$16
Name VOICE_MO: Assumptions!$C$17
Name VAR_COST: Assumptions!$C$18
Name ADMIN_COST: Assumptions!$C$19
Name CAC: Assumptions!$C$20
Name BADDEBT: Assumptions!$C$21
Name USAC_LAG: Assumptions!$C$22
Name RIVR_DISC: Assumptions!$C$24
Name TRIBE_DISC: Assumptions!$C$25
Name N_STD: Assumptions!$C$27
Name N_TRIBAL: Assumptions!$C$28
Name N_NOLL: Assumptions!$C$29
Name ENROLL_MO: Assumptions!$C$30
Name CHURN: Assumptions!$C$31
Name ALT_C_RATE_MINUS: 'Senior Alternatives'!$H$20
Name SCEN_MULT: Subscriber Model!$C$6
Name N_NOLL_ZERO: Assumptions!$C$6

Sheet Cover
B2: RIVR Tech — Lifeline & Lumbee Broadband Affordability
B3: Financial Model (Deliverable 06)
B5: LREMC Technologies, LLC d/b/a RIVR Tech
B7: Document owner: Finance / FP&A (with Program Owner)
B8: Version: v0.1 — DRAFT for internal review
B9: Prepared: Program build phase (Phase 0 — ETC application pending)
B10: Status: PRE-DECISION. All retail prices, costs and volumes are ILLUSTRATIVE PLACEHOLDERS.
B12: HOW TO USE: Edit only the yellow (INPUT) and orange (PLACEHOLDER) cells. Orange cells contain illustrative numbers that MUST be replaced with figures confirmed by RIVR Tech (retail rates, costs) or USAC (benefit amounts) before any decision relies on this model. Blue cells are federal program constants — re-verify each program year against the cited source. White cells are formulas; do not hand-edit.
B14: CRITICAL COMPLIANCE NOTE: The enhanced Tribal Lifeline benefit ($34.25) is modeled ONLY for subscribers whose PRINCIPAL RESIDENCE is confirmed on qualifying Tribal lands per 47 C.F.R. 54.400(e). Lumbee tribal membership does NOT by itself qualify a customer for enhanced support. Until a written USAC/legal determination confirms qualifying Tribal lands exist in the service area, set the enhanced-Tribal subscriber count to ZERO in the Assumptions tab.
B17: Legend:
B18: INPUT — edit me
B19: PLACEHOLDER — replace w/ confirmed figure
... B21: CALCULATED — do not edit

Sheet Assumptions
B2: Editable Assumptions
B3: Named ranges drive every other tab. Confirm every orange cell before use.
B5: Assumption | C5: Value | D5: Unit | E5: Source / note
B6: — FEDERAL PROGRAM CONSTANTS (re-verify each program year) —
B7: Standard Lifeline benefit (broadband) | C7: 9.25 | D7: $/mo | E7: 47 C.F.R. 54.403(a). Confirm current amount at USAC.
B8: Enhanced Tribal ADDITIONAL support | C8: 25 | D8: $/mo | E8: 47 C.F.R. 54.403(a)(3). Added ON TOP of standard; total up to $34.25.
B9: Enhanced Tribal TOTAL benefit | C9: =LL_STD+LL_TRIBAL_ADD | D9: $/mo | E9: Standard + Tribal enhancement.
B10: Lifeline income threshold | C10: 1.35 | D10: x FPG | E10: 135% of Federal Poverty Guidelines — 47 C.F.R. 54.409(a). Verify annual $ figures.
B11: — RIVR TECH RETAIL & COST INPUTS (PLACEHOLDER — replace with confirmed figures) —
B12: Senior 100/100 plan — retail (list) rate | C12: 55 | D12: $/mo | E12: ILLUSTRATIVE. NEW tier below current 250/250 entry. Confirm rate w/ RIVR.
B13: Current ENTRY tier (250/250 sym.) retail rate | C13: 69.95 | D13: $/mo | E13: ILLUSTRATIVE. RIVR's lowest current tier is 250/250. Confirm price w/ RIVR.
B14: Senior plan target CUSTOMER payment | C14: 10 | D14: $/mo | E14: Program design target (before tax). Executive decision.
B15: Equipment / managed Wi-Fi charge (monthly) | C15: 5 | D15: $/mo | E15: RIVR site: $5/mo indoor Wi-Fi 6 router (/$10 outdoor mesh). Confirm & decide if waived for program. Sep. tax.
B16: Installation charge (one-time) | C16: 0 | D16: $ one-time | E16: RIVR site: install advertised free ($99 value, promotional). Confirm program policy.
B17: Optional voice add-on charge | C17: 0 | D17: $/mo | E17: ILLUSTRATIVE. Voice is optional; Lifeline min-standard is broadband.
B18: Variable network + support cost / sub | C18: 22 | D18: $/mo | E18: ILLUSTRATIVE avoided/served cost per subscriber. Confirm w/ Finance.
B19: Billing + compliance labor / sub / mo | C19: 3.5 | D19: $/mo | E19: ILLUSTRATIVE fully-loaded ongoing admin per active Lifeline sub.
B20: Customer acquisition cost (one-time) | C20: 45 | D20: $/enroll | E20: ILLUSTRATIVE. Outreach, enrollment labor, QC per new enrollee.
B21: Bad-debt rate (on customer-paid portion) | C21: 0.04 | D21: % | E21: ILLUSTRATIVE. Lifeline reduces customer bill so exposure is low.
B22: USAC reimbursement lag | C22: 1 | D22: months | E22: Claim filed after service month; cash received after. Confirm cycle.
B23: — OPTIONAL PROGRAM DISCOUNTS (executive decisions) —
B24: RIVR-funded discount / sub (non-Lifeline senior) | C24: 0 | D24: $/mo | E24: Company subsidy to reach target for seniors w/o Lifeline (Alt A).
B25: Lumbee Tribe-funded discount / sub | C25: 0 | D25: $/mo | E25: ONLY if Tribe funds it under a signed MOU. Separate accounting.
B26: — SUBSCRIBER VOLUMES (Expected scenario — see Subscriber Model for all 3) —
B27: Std-Lifeline senior subs (steady-state) | C27: 300 | D27: subs | E27: Seniors approved for STANDARD Lifeline via National Verifier.
B28: Enhanced-Tribal subs (steady-state) | C28: 0 | D28: subs | E28: SET TO 0 until qualifying Tribal lands confirmed by USAC/legal.
B29: Senior subs, NO Lifeline (company-funded) | C29: 150 | D29: subs | E29: Seniors on the $10 plan who do not qualify for Lifeline.
B30: Avg. monthly gross enrollments (ramp) | C30: 40 | D30: subs/mo | E30: New approved enrollments per month during ramp.
B31: Monthly de-enrollment / churn rate | C31: 0.02 | D31: %/mo | E31: Failure to recertify, moves, loss of eligibility, non-pay.
B32: Break-even / sustainability check ↓
B34: Legend:
B35: INPUT — edit me
B36: PLACEHOLDER — replace w/ confirmed figure
B37: PROGRAM CONSTANT — re-verify each year
B38: CALCULATED — do not edit

Sheet Pricing Matrix
B2: Pricing & Subsidy Matrix — per-subscriber monthly economics
B3: All figures pre-tax. 'Plus tax' disclosure pending RIVR tax-advisor confirmation. Formulas reference Assumptions.
B5: Line item | C5: (1) Regular retail | D5: (2) + Standard Lifeline | E5: (3) + Enhanced Tribal | F5: (4) + RIVR discount | G5: (5) + Tribe discount | H5: (6) Senior 100/100 target
B6: Retail (list) price | C6: =RETAIL_STD | D6: =RETAIL_STD | E6: =RETAIL_STD | F6: =RETAIL_SENIOR | G6: =RETAIL_SENIOR | H6: =RETAIL_SENIOR
B7: Less: Standard Lifeline credit | C7: 0 | D7: =-LL_STD | E7: =-LL_STD | F7: =-LL_STD | G7: =-LL_STD | H7: =-LL_STD
B8: Less: Tribal enhancement credit | C8: 0 | D8: 0 | E8: =-LL_TRIBAL_ADD | F8: 0 | G8: 0 | H8: 0
B9: Less: RIVR-funded discount | C9: 0 | D9: 0 | E9: 0 | F9: =-RIVR_DISC | G9: =-RIVR_DISC | H9: =-(MAX(0,RETAIL_SENIOR-LL_STD-TARGET_PAY))
B10: Less: Tribe-funded discount | C10: 0 | D10: 0 | E10: 0 | F10: 0 | G10: =-TRIBE_DISC | H10: =-TRIBE_DISC
B11: Plus: Equipment / mgd Wi-Fi | C11: =EQUIP_MO | D11: =EQUIP_MO | E11: =EQUIP_MO | F11: =EQUIP_MO | G11: =EQUIP_MO | H11: =EQUIP_MO
B12: Plus: Optional voice | C12: =VOICE_MO | D12: =VOICE_MO | E12: =VOICE_MO | F12: =VOICE_MO | G12: =VOICE_MO | H12: =VOICE_MO
B13: =FINAL CUSTOMER PAYMENT (pre-tax) | C13: =C6+C7+C8+C9+C10+C11+C12 | D13: =D6+D7+D8+D9+D10+D11+D12 | E13: =E6+E7+E8+E9+E10+E11+E12 | F13: =F6+F7+F8+F9+F10+F11+F12 | G13: =G6+G7+G8+G9+G10+G11+G12 | H13: =H6+H7+H8+H9+H10+H11+H12
B14: Applicable taxes & fees | C14: TBD | D14: TBD | E14: TBD | F14: TBD | G14: TBD | H14: TBD
B15: USAC reimbursement to RIVR | C15: 0 | D15: =LL_STD | E15: =LL_TRIBAL_TOTAL | F15: =LL_STD | G15: =LL_STD | H15: =LL_STD
B16: RIVR gross revenue (cust pay + USAC) | C16: =C13+C15+(-1)*C10 | D16: =D13+D15+(-1)*D10 | E16: =E13+E15+(-1)*E10 | F16: =F13+F15+(-1)*F10 | G16: =G13+G15+(-1)*G10 | H16: =H13+H15+(-1)*H10
B17: Less: variable + admin cost | C17: =-(VAR_COST+ADMIN_COST) | D17: =-(VAR_COST+ADMIN_COST) | E17: =-(VAR_COST+ADMIN_COST) | F17: =-(VAR_COST+ADMIN_COST) | G17: =-(VAR_COST+ADMIN_COST) | H17: =-(VAR_COST+ADMIN_COST)
B18: =CONTRIBUTION MARGIN / sub / mo | C18: =C16+C17 | D18: =D16+D17 | E18: =E16+E17 | F18: =F16+F17 | G18: =G16+G17 | H18: =H16+H17
B20: Notes: (3) applies ONLY where the principal residence is confirmed on qualifying Tribal lands. (6) shows the Senior 100/100 target under Alternative D (Lifeline first, then RIVR/Tribe top-up to reach the $10 target). Tribe-funded discount is treated as revenue to RIVR under a settlement, kept in a separate GL category. Taxes shown as TBD pending tax-advisor review.

Sheet Senior Alternatives
B2: Senior 100/100 Plan — Alternatives A/B/C/D
B3: Per-subscriber monthly economics under each design. Recommend Alternative D (see Exec Plan).
B5: Metric | C5: Alt A: Universal $10 | D5: Alt B: $10 net after Std LL | E5: Alt C: $10 net after Tribal | F5: Alt D: Blended | G5: Comment
B6: Retail (list) rate set | C6: =RETAIL_SENIOR | D6: =TARGET_PAY+LL_STD | E6: =TARGET_PAY+LL_TRIBAL_TOTAL | F6: =RETAIL_SENIOR | G6: List stays at retail; subsidies layer to reach target
B7: Customer pays — has Std Lifeline | C7: =TARGET_PAY | D7: =TARGET_PAY | E7: =MAX(0,ALT_C_RATE_MINUS) | F7: =TARGET_PAY | G7: Alt C leaves std-LL seniors ABOVE $10 unless topped up
B8: Customer pays — has Enhanced Tribal | C8: =TARGET_PAY | D8: =MAX(0,TARGET_PAY+LL_STD-LL_TRIBAL_TOTAL) | E8: =TARGET_PAY | F8: =TARGET_PAY | G8: Alt B risks OVER-recovery for tribal (pays < $10 / negative)
B9: Customer pays — NO Lifeline | C9: =TARGET_PAY | D9: =TARGET_PAY+LL_STD | E9: =TARGET_PAY+LL_TRIBAL_TOTAL | F9: =TARGET_PAY | G9: Alt A & D shield non-LL seniors; B & C do not
B10: RIVR-funded subsidy — has Std LL | C10: =RETAIL_SENIOR-LL_STD-TARGET_PAY | D10: 0 | E10: 0 | F10: =MAX(0,RETAIL_SENIOR-LL_STD-TARGET_PAY-TRIBE_DISC) | G10: Company exposure per subsidized sub
B11: RIVR-funded subsidy — NO Lifeline | C11: =RETAIL_SENIOR-TARGET_PAY | D11: 0 | E11: 0 | F11: =RETAIL_SENIOR-TARGET_PAY-TRIBE_DISC | G11: Largest company exposure (no USAC offset)
B12: Compliance risk | C12: Low-Med | D12: Med (over-recovery on tribal) | E12: High (misapplies tribal) | F12: Low | G12: Alt C mis-signals tribal eligibility
B14: Alt A = universal $10 retail; RIVR absorbs the gap for non-Lifeline seniors and applies Lifeline only where permissible. Alt B sets retail so the bill nets to $10 after the $9.25 standard credit — but a tribal-qualified sub would net BELOW $10 (over-recovery risk). Alt C sets retail so the bill nets to $10 after the $34.25 tribal credit — but this only works for the (currently zero) tribal-lands population and leaves standard-LL seniors above $10. Alt D applies Lifeline first, then a defined RIVR/Tribe top-up so EVERY approved participant reaches the $10 target — recommended for compliance simplicity and NISC administrability.
H19: helper:
H20: =(TARGET_PAY+LL_TRIBAL_TOTAL)-LL_STD

Sheet Subscriber Model
B2: Subscriber Build — 12 months (Expected scenario)
B3: Scenario multipliers: Conservative 0.6x / Expected 1.0x / Aggressive 1.5x applied to enrollments.
B5: Metric | C5: M1 | D5: M2 | E5: M3 | F5: M4 | G5: M5 | H5: M6 | I5: M7 | J5: M8 | K5: M9 | L5: M10 | M5: M11 | N5: M12
B6: Scenario multiplier (0.6/1.0/1.5) | C6: 1
B8: Beginning active subs | C8: 0 | D8: =C11 | E8: =D11 | F8: =E11 | G8: =F11 | H8: =G11 | I8: =H11 | J8: =I11 | K8: =J11 | ... N8: =M11
B9: Gross new enrollments | C9: =ROUND(ENROLL_MO*SCEN_MULT,0) | D9: =ROUND(ENROLL_MO*SCEN_MULT,0) | E9: =ROUND(ENROLL_MO*SCEN_MULT,0) | F9: =ROUND(ENROLL_MO*SCEN_MULT,0) | G9: =ROUND(ENROLL_MO*SCEN_MULT,0) | H9: =ROUND(ENROLL_MO*SCEN_MULT,0) | I9: =ROUND(ENROLL_MO*SCEN_MULT,0) | J9: =ROUND(ENROLL_MO*SCEN_MULT,0) | ... N9: =ROUND(ENROLL_MO*SCEN_MULT,0)
B10: De-enrollments (churn) | C10: =-ROUND(C8*CHURN,0) | D10: =-ROUND(D8*CHURN,0) | E10: =-ROUND(E8*CHURN,0) | F10: =-ROUND(F8*CHURN,0) | G10: =-ROUND(G8*CHURN,0) | H10: =-ROUND(H8*CHURN,0) | I10: =-ROUND(I8*CHURN,0) | J10: =-ROUND(J8*CHURN,0) | ... N10: =-ROUND(N8*CHURN,0)
B11: Ending active subs | C11: =C8+C9+C10 | D11: =D8+D9+D10 | E11: =E8+E9+E10 | F11: =F8+F9+F10 | G11: =G8+G9+G10 | H11: =H8+H9+H10 | I11: =I8+I9+I10 | J11: =J8+J9+J10 | ... N11: =N8+N9+N10
B13: Cohort split (of ending subs) — apply steady-state mix from Assumptions once ramped. Enhanced-Tribal cohort held at 0 until qualifying Tribal lands confirmed.

Sheet P&L 12mo
B2: Contribution P&L — 12 months (Expected)
B3: Uses ending subs from Subscriber Model x per-sub economics. USAC cash lagged by USAC_LAG.
B5: Line ($/month) | C5: M1 | D5: M2 | E5: M3 | F5: M4 | G5: M5 | H5: M6 | I5: M7 | J5: M8 | K5: M9 | L5: M10 | M5: M11 | N5: M12
B6: Active subs (end) | C6: ='Subscriber Model'!C11 | D6: ='Subscriber Model'!D11 | E6: ='Subscriber Model'!E11 | F6: ='Subscriber Model'!F11 | G6: ='Subscriber Model'!G11 | H6: ='Subscriber Model'!H11 | I6: ='Subscriber Model'!I11 | J6: ='Subscriber Model'!J11 | ... N6: ='Subscriber Model'!N11
B7: Customer payments ($) | C7: =C7*TARGET_PAY | D7: =D7*TARGET_PAY | E7: =E7*TARGET_PAY | F7: =F7*TARGET_PAY | G7: =G7*TARGET_PAY | H7: =H7*TARGET_PAY | I7: =I7*TARGET_PAY | J7: =J7*TARGET_PAY | ... N7: =N7*TARGET_PAY
B8: USAC reimb — accrued ($) | C8: =(C7)*LL_STD | D8: =(D7)*LL_STD | E8: =(E7)*LL_STD | F8: =(F7)*LL_STD | G8: =(G7)*LL_STD | H8: =(H7)*LL_STD | I8: =(I7)*LL_STD | J8: =(J7)*LL_STD | ... N8: =(N7)*LL_STD
B9: USAC reimb — CASH (lagged) ($) | C9: =0 | D9: =C9 | E9: =D9 | F9: =E9 | G9: =F9 | H9: =G9 | I9: =H9 | J9: =I9 | K9: =J9 | ... N9: =M9
B10: RIVR-funded subsidy ($) | C10: =-C7*RIVR_DISC | D10: =-D7*RIVR_DISC | E10: =-E7*RIVR_DISC | F10: =-F7*RIVR_DISC | G10: =-G7*RIVR_DISC | H10: =-H7*RIVR_DISC | I10: =-I7*RIVR_DISC | J10: =-J7*RIVR_DISC | ... N10: =-N7*RIVR_DISC
B11: Tribe settlement ($) | C11: =C7*TRIBE_DISC | D11: =D7*TRIBE_DISC | E11: =E7*TRIBE_DISC | F11: =F7*TRIBE_DISC | G11: =G7*TRIBE_DISC | H11: =H7*TRIBE_DISC | I11: =I7*TRIBE_DISC | J11: =J7*TRIBE_DISC | ... N11: =N7*TRIBE_DISC
B12: Variable+admin cost ($) | C12: =-C7*(VAR_COST+ADMIN_COST) | D12: =-D7*(VAR_COST+ADMIN_COST) | E12: =-E7*(VAR_COST+ADMIN_COST) | F12: =-F7*(VAR_COST+ADMIN_COST) | G12: =-G7*(VAR_COST+ADMIN_COST) | H12: =-H7*(VAR_COST+ADMIN_COST) | I12: =-I7*(VAR_COST+ADMIN_COST) | J12: =-J7*(VAR_COST+ADMIN_COST) | ... N12: =-N7*(VAR_COST+ADMIN_COST)
B13: Acquisition cost ($) | C13: =-'Subscriber Model'!C9*CAC | D13: =-'Subscriber Model'!D9*CAC | E13: =-'Subscriber Model'!E9*CAC | F13: =-'Subscriber Model'!F9*CAC | G13: =-'Subscriber Model'!G9*CAC | H13: =-'Subscriber Model'!H9*CAC | I13: =-'Subscriber Model'!I9*CAC | J13: =-'Subscriber Model'!J9*CAC | ... N13: =-'Subscriber Model'!N9*CAC
B14: Bad debt ($) | C14: =-C7*TARGET_PAY*BADDEBT | D14: =-D7*TARGET_PAY*BADDEBT | E14: =-E7*TARGET_PAY*BADDEBT | F14: =-F7*TARGET_PAY*BADDEBT | G14: =-G7*TARGET_PAY*BADDEBT | H14: =-H7*TARGET_PAY*BADDEBT | I14: =-I7*TARGET_PAY*BADDEBT | J14: =-J7*TARGET_PAY*BADDEBT | ... N14: =-N7*TARGET_PAY*BADDEBT
B15: =CONTRIBUTION MARGIN (accrual $) | C15: =C7+C8+C10+C11+C12+C13+C14 | D15: =D7+D8+D10+D11+D12+D13+D14 | E15: =E7+E8+E10+E11+E12+E13+E14 | F15: =F7+F8+F10+F11+F12+F13+F14 | G15: =G7+G8+G10+G11+G12+G13+G14 | H15: =H7+H8+H10+H11+H12+H13+H14 | I15: =I7+I8+I10+I11+I12+I13+I14 | J15: =J7+J8+J10+J11+J12+J13+J14 | ... N15: =N7+N8+N10+N11+N12+N13+N14
B17: Note: 'active subs' here uses the blended ending count. For mixed cohorts, extend the model per cohort (std-LL, tribal, no-LL). USAC cash column lags accrual by 1 month (USAC_LAG).

Sheet Break-even
B2: Break-even & Sustainability
B5: Metric | C5: Value | D5: Note
B6: Contribution margin / std-LL senior / mo | C6: ='Pricing Matrix'!H18 | D6: From Pricing Matrix, scenario (6)
B7: Contribution margin / no-LL senior / mo | C7: =TARGET_PAY-VAR_COST-ADMIN_COST-(RETAIL_SENIOR-LL_STD-TARGET_PAY) | D7: Company funds full gap; often negative
B8: Monthly RIVR subsidy — no-LL cohort | C8: =N_NOLL*(RETAIL_SENIOR-TARGET_PAY-TRIBE_DISC) | D8: Alt D company exposure, no-LL seniors
B9: Monthly RIVR subsidy — std-LL cohort | C9: =N_STD*MAX(0,RETAIL_SENIOR-LL_STD-TARGET_PAY-TRIBE_DISC) | D9: Alt D company exposure, std-LL seniors
B10: Total monthly company subsidy | C10: =B10+B11 | D10: Sum of company-funded exposure
B11: Annual company subsidy | C11: =C12*12 | D11: For budgeting
B12: USAC monthly reimbursement (all LL subs) | C12: =N_STD*LL_STD+N_TRIBAL*LL_TRIBAL_TOTAL | D12: Federal support inflow
B14: Sustainability test: the program is self-sustaining when contribution margin across the Lifeline-supported cohorts covers the company-funded subsidy to the non-Lifeline cohort plus fixed program overhead. Maximizing National Verifier approval rate (moving seniors from the no-LL cohort to the std-LL cohort) is the single biggest lever.

Sheet 36mo Scenarios
B2: 36-Month Scenario Summary
B3: Steady-state annualized view. Adjust volumes in Assumptions; multiplier column shows sensitivity.
B5: Metric (annual, steady-state) | C5: Conservative 0.6x | D5: Expected 1.0x | E5: Aggressive 1.5x
B6: Total Lifeline subs | C6: =ROUND((N_STD+N_TRIBAL)*0.6,0) | D6: =ROUND((N_STD+N_TRIBAL)*1.0,0) | E6: =ROUND((N_STD+N_TRIBAL)*1.5,0)
B7: USAC reimbursement / yr | C7: =(N_STD*LL_STD+N_TRIBAL*LL_TRIBAL_TOTAL)*12*0.6 | D7: =(N_STD*LL_STD+N_TRIBAL*LL_TRIBAL_TOTAL)*12*1.0 | E7: =(N_STD*LL_STD+N_TRIBAL*LL_TRIBAL_TOTAL)*12*1.5
B8: Customer payments / yr | C8: =(N_STD+N_TRIBAL+N_NOLL)*TARGET_PAY*12*0.6 | D8: =(N_STD+N_TRIBAL+N_NOLL)*TARGET_PAY*12*1.0 | E8: =(N_STD+N_TRIBAL+N_NOLL)*TARGET_PAY*12*1.5
B9: Company subsidy / yr | C9: =(N_NOLL*(RETAIL_SENIOR-TARGET_PAY)+N_STD*MAX(0,RETAIL_SENIOR-LL_STD-TARGET_PAY))*12*0.6 | D9: =(N_NOLL*(RETAIL_SENIOR-TARGET_PAY)+N_STD*MAX(0,RETAIL_SENIOR-LL_STD-TARGET_PAY))*12*1.0 | E9: =(N_NOLL*(RETAIL_SENIOR-TARGET_PAY)+N_STD*MAX(0,RETAIL_SENIOR-LL_STD-TARGET_PAY))*12*1.5
B10: Variable+admin cost / yr | C10: =(N_STD+N_TRIBAL+N_NOLL)*(VAR_COST+ADMIN_COST)*12*0.6 | D10: =(N_STD+N_TRIBAL+N_NOLL)*(VAR_COST+ADMIN_COST)*12*1.0 | E10: =(N_STD+N_TRIBAL+N_NOLL)*(VAR_COST+ADMIN_COST)*12*1.5
B11: Contribution margin / yr | C11: =C7+C8-C9-C10 | D11: =D7+D8-D9-D10 | E11: =E7+E8-E9-E10
B13: Contribution margin here = customer payments + USAC − company subsidy − variable/admin. Sign depends heavily on the (placeholder) retail rate and cost inputs; replace before relying on it.
