Workbook

Sheet Instructions
A1: INSTRUCTIONS — READ FIRST
A2: DRAFT FOR DISCUSSION – SUBJECT TO LEGAL, GRANT AND FINANCIAL REVIEW
B5: Deliverable 10 — 30-Year Editable Financial Model
B6: Lumbee Tribe of North Carolina & LREMC Technologies, LLC d/b/a RIVR Tech
B7: TBCP grant-funded hybrid broadband network — southeastern North Carolina.
B9: DRAFT / PLACEHOLDER WARNING
B10: Every dollar figure, rate, and count in this workbook is a PLACEHOLDER for negotiation. The model is a working draft — subject to legal, grant, and financial review. Do NOT rely on any output as a final term. Replace the amber input cells with negotiated values.
B12: COLOR LEGEND
B13: • AMBER = INPUT — edit these. All assumptions live on the Assumptions sheet.
B14: • BLUE = FORMULA — do not edit; these compute from inputs.
B15: • GREEN = OUTPUT / RESULT — headline numbers and NPV/IRR.
B16: The model is designed to be used WITHOUT editing any formula — change inputs only.
B18: THE THREE SWITCHES (all on the Assumptions sheet, top block)
B19: • Scenario switch — type 1 (Low), 2 (Base), or 3 (High). Drives every scenario-dependent driver (take rate, ARPU, churn, bad debt, inflation, construction cost) via CHOOSE.
... B40: This file is generated by a script and stores formulas (not cached results). Open it in Excel / LibreOffice and allow calculation (F9) so every blue/green cell evaluates.
A42: Legend: | B42: INPUT (edit these) | C42: FORMULA (do not edit) | D42: OUTPUT / RESULT

Sheet Dashboard
A1: EXECUTIVE DASHBOARD
A2: DRAFT FOR DISCUSSION – SUBJECT TO LEGAL, GRANT AND FINANCIAL REVIEW
A3: Active scenario / term / option, headline outputs, and formula-check roll-up. All values are live formulas.
A4: Legend: | B4: INPUT (edit these) | C4: FORMULA (do not edit) | D4: OUTPUT / RESULT
B6: ACTIVE SETTINGS | E6: INDIVIDUAL CHECKS
B7: Scenario | C7: =Assumptions!$D$7 | E7: Construction_Budget | F7: =Construction_Budget!F21
B8: IRU term (years) | C8: =Assumptions!$C$8 | E8: Grant_Funding | F8: =Grant_Funding!F16
B9: Revenue-share option | C9: =Assumptions!$C$10 | E9: Grant_Funding | F9: =Grant_Funding!F17
B10: TBCP grant amount | C10: =Assumptions!$C$29 | E10: Homes_Passed | F10: =Homes_Passed!F38
B11: Homes passed (total) | C11: =Assumptions!$C$30 | E11: Take_Rate_Customers | F11: =Take_Rate_Customers!F38
B12: Discount rate (NPV) | C12: =Assumptions!$C$44 | E12: Revenue | F12: =Revenue!F38
E13: Operating_Expenses | F13: =Operating_Expenses!F38
B14: HEADLINE OUTPUTS (active case) | E14: Capital_Replacement | F14: =Capital_Replacement!F38
B15: Year-30 gross revenue | C15: =Revenue!$I$36 | E15: Revenue_Share_Options | F15: =Revenue_Share_Options!F38
B16: Total Tribal receipts (undiscounted) | C16: =Tribal_Economics!$B$39 | E16: Annual_Cash_Flow | F16: =Annual_Cash_Flow!F38
B17: Tribal NPV | C17: =Tribal_Economics!$B$38 | E17: Consolidated_Project | F17: =Consolidated_Project!F41
B18: RIVR Tech NPV | C18: =RIVR_Tech_Economics!$B$39 | E18: Case_Engine | F18: =Case_Engine!F112
B19: RIVR Tech IRR | C19: =RIVR_Tech_Economics!$B$40
B20: RIVR payback (year) | C20: =RIVR_Tech_Economics!$B$41
B21: Project NPV | C21: =Consolidated_Project!$B$38
B22: Project IRR | C22: =Consolidated_Project!$B$39
B24: FORMULA-CHECK ROLL-UP
B25: Checks passing | C25: =--(Construction_Budget!F21="PASS")+--(Grant_Funding!F16="PASS")+--(Grant_Funding!F17="PASS")+--(Homes_Passed!F38="PASS")+--(Take_Rate_Customers!F38="PASS")+--(Revenue!F38="PASS")+--(Operating_Expenses!F38="PASS")+--(Capital_Replacement!F38="PASS")+--(Revenue_Share_Options!F38="PASS")+--(Annual_Cash_Flow!F38="PASS")+--(Consolidated_Project!F41="PASS")+--(Case_Engine!F112="PASS")
B26: Total checks | C26: 12
B27: OVERALL STATUS | C27: =IF((--(Construction_Budget!F21="PASS")+--(Grant_Funding!F16="PASS")+--(Grant_Funding!F17="PASS")+--(Homes_Passed!F38="PASS")+--(Take_Rate_Customers!F38="PASS")+--(Revenue!F38="PASS")+--(Operating_Expenses!F38="PASS")+--(Capital_Replacement!F38="PASS")+--(Revenue_Share_Options!F38="PASS")+--(Annual_Cash_Flow!F38="PASS")+--(Consolidated_Project!F41="PASS")+--(Case_Engine!F112="PASS"))=12,"ALL CHECKS PASS","REVIEW — SEE FAILED CHECKS")

Sheet Assumptions
A1: ASSUMPTIONS — All Editable Input Drivers
A2: DRAFT FOR DISCUSSION – SUBJECT TO LEGAL, GRANT AND FINANCIAL REVIEW
A3: Amber cells are INPUTS you may edit. Blue cells are FORMULAS (do not edit).
A4: Legend: | B4: INPUT (edit these) | C4: FORMULA (do not edit) | D4: OUTPUT / RESULT
B6: MODEL SWITCHES
B7: Scenario switch (1 = Low, 2 = Base, 3 = High) | C7: 2 | D7: =CHOOSE($C$7,"LOW","BASE","HIGH") | G7: Drives every scenario-dependent driver via CHOOSE.
B8: IRU term switch (20 / 25 / 30 years — recommend 30) | C8: 30 | G8: Analysis horizon for NPV/IRR. Revenue & payments beyond term = 0.
B9: Revenue-share option switch (1=A 2=B 3=C 4=D 5=E) | C9: 4 | D9: =CHOOSE($C$9,"A","B","C","D","E") | G9: Recommended: D (Hybrid). All five computed side-by-side.
B10: Active option name | C10: =CHOOSE($C$9,"A — Fixed Annual","B — % Gross Revenue","C — % Operating Cash Flow","D — Hybrid (Base + Share)","E — Holiday then Stepped")
B12: SCENARIO-DEPENDENT DRIVERS
B13: Driver | C13: Low | D13: Base | E13: High | F13: Active | G13: Units / Notes
B14: Terminal take rate (net penetration) | C14: 0.35 | D14: 0.45 | E14: 0.55 | F14: =CHOOSE($C$7,$C$14,$D$14,$E$14) | G14: % of homes passed
B15: Take-rate ramp (years to terminal) | C15: 6 | D15: 5 | E15: 4 | F15: =CHOOSE($C$7,$C$15,$D$15,$E$15) | G15: years
B16: Residential ARPU (monthly) | C16: 65 | D16: 75 | E16: 85 | F16: =CHOOSE($C$7,$C$16,$D$16,$E$16) | G16: $/sub/month
B17: Business ARPU (monthly) | C17: 200 | D17: 250 | E17: 300 | F17: =CHOOSE($C$7,$C$17,$D$17,$E$17) | G17: $/sub/month
B18: Enterprise ARPU (monthly) | C18: 800 | D18: 1000 | E18: 1200 | F18: =CHOOSE($C$7,$C$18,$D$18,$E$18) | G18: $/sub/month
B19: Voice ARPU (monthly) | C19: 30 | D19: 35 | E19: 40 | F19: =CHOOSE($C$7,$C$19,$D$19,$E$19) | G19: $/sub/month
B20: Enterprise subscribers at maturity | C20: 15 | D20: 25 | E20: 40 | F20: =CHOOSE($C$7,$C$20,$D$20,$E$20) | G20: count
B21: Wholesale revenue at maturity (annual) | C21: 300000 | D21: 500000 | E21: 750000 | F21: =CHOOSE($C$7,$C$21,$D$21,$E$21) | G21: $/year
B22: Annual customer churn | C22: 0.18 | D22: 0.14 | E22: 0.1 | F22: =CHOOSE($C$7,$C$22,$D$22,$E$22) | G22: % per year
B23: Bad debt | C23: 0.025 | D23: 0.015 | E23: 0.01 | F23: =CHOOSE($C$7,$C$23,$D$23,$E$23) | G23: % of recurring rev
B24: Operating-cost inflation | C24: 0.035 | D24: 0.03 | E24: 0.025 | F24: =CHOOSE($C$7,$C$24,$D$24,$E$24) | G24: % per year
B25: Construction cost factor | C25: 1.15 | D25: 1 | E25: 0.9 | F25: =CHOOSE($C$7,$C$25,$D$25,$E$25) | G25: x on budget (High=cheaper)
B27: SINGLE INPUTS (not case-varying)
B28: Input | C28: Value | G28: Units / Notes
B29: TBCP grant amount (funds Tribal Assets) | C29: 25000000 | G29: $ (placeholder $25M)
B30: Homes passed (total) | C30: 8500 | G30: premises (placeholder 8,500)
B31: Build-out period | C31: 3 | G31: years to complete homes passed
B32: Business penetration | C32: 0.04 | G32: % of homes passed
B33: Voice attach rate | C33: 0.4 | G33: % of residential subs
B34: Installation fee (one-time) | C34: 100 | G34: $/new connect
B35: ARPU / price escalation | C35: 0.02 | G35: % per year (set 0 to disable)
B36: Network operations cost | C36: 120 | G36: $/subscriber/year
B37: Network maintenance | C37: 0.03 | G37: % of construction cost/yr
B38: Staffing headcount | C38: 12 | G38: FTEs
B39: Loaded cost per FTE | C39: 85000 | G39: $/FTE/year
B40: Marketing | C40: 0.06 | G40: % of gross revenue
... B46: Reserved-capacity value to Lumbee Tribe | C46: 150000 | G46: $/yr in-kind (memo)
B48: REVENUE-SHARE OPTION INPUTS
B49: Option A — fixed annual payment | C49: 500000 | G49: $/yr (escalated)
B50: Option A — annual escalator | C50: 0.02 | G50: % per year
B51: Option B — share of gross revenue | C51: 0.05 | G51: % (placeholder 5%)
B52: Option C — share of operating cash flow | C52: 0.2 | G52: % (placeholder 20%)
B53: Option D — hybrid fixed base | C53: 250000 | G53: $/yr
B54: Option D — hybrid revenue share | C54: 0.025 | G54: % of gross revenue
B55: Option E — payment-holiday period | C55: 2 | G55: years at $0
B56: Option E — first payment after holiday | C56: 300000 | G56: $/yr
B57: Option E — annual step-up | C57: 0.05 | G57: % per year

Sheet Construction_Budget
A1: CONSTRUCTION BUDGET — Capital Line Items (Year 0)
A2: DRAFT FOR DISCUSSION – SUBJECT TO LEGAL, GRANT AND FINANCIAL REVIEW
A3: Qty x Unit Cost = Extended. Construction cost factor (scenario) applied to the total.
B5: Capital Line Item | C5: Quantity | D5: Unit Cost | E5: Extended | F5: Notes
B6: Outside-plant (OSP) fiber | C6: 250 | D6: 45000 | E6: =$C6*$D6 | F6: route miles x $/mi
B7: Conduit / directional bore | C7: 80 | D7: 30000 | E7: =$C7*$D7 | F7: miles x $/mi
B8: Electronics (OLT / aggregation / core) | C8: 1 | D8: 4000000 | E8: =$C8*$D8 | F8: lump — basis for replacement cycle
B9: Fiber huts / cabinets / power | C9: 25 | D9: 60000 | E9: =$C9*$D9 | F9: sites x $/site
B10: Service drops | C10: 3825 | D10: 650 | E10: =$C10*$D10 | F10: connects x $/drop
B11: Engineering & design | C11: 1 | D11: 1500000 | E11: =$C11*$D11 | F11: lump
B12: Permitting, make-ready & pole attach | C12: 1 | D12: 1200000 | E12: =$C12*$D12 | F12: lump
B13: Subtotal (direct construction) | E13: =SUM($E6:$E12)
B14: Contingency | C14: 0.1 | E14: =$C14*$E13
B15: Subtotal + contingency | E15: =$E13+$E14
B16: Construction cost factor (active scenario) | E16: =Assumptions!$F$25
B17: TOTAL CONSTRUCTION COST | E17: =$E15*$E16
B19: Electronics replacement basis (factored) | E19: =Construction_Budget!$E$8*Construction_Budget!$E$16
B21: CHECK: no #REF / all line items numeric | F21: =IF(ISNUMBER($E17),"PASS","FAIL")

Sheet Grant_Funding
A1: GRANT FUNDING — Sources & Uses
A2: DRAFT FOR DISCUSSION – SUBJECT TO LEGAL, GRANT AND FINANCIAL REVIEW
A3: TBCP funds the Tribal Assets. TBCP does not require non-federal match. Sources must equal Uses.
B5: Sources & Uses | C5: Amount | D5: Notes
B6: SOURCES
B7: TBCP federal grant | C7: =Assumptions!$C$29 | D7: Placeholder $25,000,000 — funds Tribal Assets
B8: Non-federal match (not required by TBCP) | C8: 0 | D8: Editable — TBCP Round 3 requires no match
B9: TOTAL SOURCES | C9: =SUM($C7:$C8)
B11: USES
B12: Total construction cost | C12: =Construction_Budget!$E$17 | D12: From Construction_Budget
B13: Surplus / (funding gap) plug | C13: =$C9-$C12 | D13: Positive = surplus for contingency; negative = gap (flag)
B14: TOTAL USES | C14: =SUM($C12:$C13)
B16: CHECK: Sources = Uses (reconciles) | F16: =IF(ABS($C9-$C14)<1,"PASS","FAIL")
B17: CHECK: Uses do not exceed grant sources (no funding gap) | F17: =IF($C9>=$C12,"PASS","FAIL — FUNDING GAP")

Sheet Homes_Passed
A1: HOMES PASSED — Build-out Schedule
A2: DRAFT FOR DISCUSSION – SUBJECT TO LEGAL, GRANT AND FINANCIAL REVIEW
A3: Year 0 = construction. Serviceable homes ramp over the build-out period.
A5: Year | B5: Homes Passed (cum.) | C5: New Homes Passed | D5: % Complete
A6: 0 | B6: 0 | C6: =$B6-0 | D6: =$B6/Assumptions!$C$30
A7: 1 | B7: =Assumptions!$C$30*MIN(1,$A7/Assumptions!$C$31) | C7: =$B7-$B6 | D7: =$B7/Assumptions!$C$30
A8: 2 | B8: =Assumptions!$C$30*MIN(1,$A8/Assumptions!$C$31) | C8: =$B8-$B7 | D8: =$B8/Assumptions!$C$30
A9: 3 | B9: =Assumptions!$C$30*MIN(1,$A9/Assumptions!$C$31) | C9: =$B9-$B8 | D9: =$B9/Assumptions!$C$30
A10: 4 | B10: =Assumptions!$C$30*MIN(1,$A10/Assumptions!$C$31) | C10: =$B10-$B9 | D10: =$B10/Assumptions!$C$30
A11: 5 | B11: =Assumptions!$C$30*MIN(1,$A11/Assumptions!$C$31) | C11: =$B11-$B10 | D11: =$B11/Assumptions!$C$30
A12: 6 | B12: =Assumptions!$C$30*MIN(1,$A12/Assumptions!$C$31) | C12: =$B12-$B11 | D12: =$B12/Assumptions!$C$30
A13: 7 | B13: =Assumptions!$C$30*MIN(1,$A13/Assumptions!$C$31) | C13: =$B13-$B12 | D13: =$B13/Assumptions!$C$30
A14: 8 | B14: =Assumptions!$C$30*MIN(1,$A14/Assumptions!$C$31) | C14: =$B14-$B13 | D14: =$B14/Assumptions!$C$30
A15: 9 | B15: =Assumptions!$C$30*MIN(1,$A15/Assumptions!$C$31) | C15: =$B15-$B14 | D15: =$B15/Assumptions!$C$30
A16: 10 | B16: =Assumptions!$C$30*MIN(1,$A16/Assumptions!$C$31) | C16: =$B16-$B15 | D16: =$B16/Assumptions!$C$30
A17: 11 | B17: =Assumptions!$C$30*MIN(1,$A17/Assumptions!$C$31) | C17: =$B17-$B16 | D17: =$B17/Assumptions!$C$30
A18: 12 | B18: =Assumptions!$C$30*MIN(1,$A18/Assumptions!$C$31) | C18: =$B18-$B17 | D18: =$B18/Assumptions!$C$30
... A36: 30 | B36: =Assumptions!$C$30*MIN(1,$A36/Assumptions!$C$31) | C36: =$B36-$B35 | D36: =$B36/Assumptions!$C$30
B38: CHECK: homes passed never exceed total (Assumptions) | F38: =IF(MAX($B6:$B36)<=Assumptions!$C$30+0.5,"PASS","FAIL")

Sheet Take_Rate_Customers
A1: TAKE RATE & CUSTOMERS
A2: DRAFT FOR DISCUSSION – SUBJECT TO LEGAL, GRANT AND FINANCIAL REVIEW
A3: Net penetration ramps to terminal. Gross adds (incl. churn replacement) drive install revenue.
A5: Year | B5: Take Rate | C5: Residential Subs | D5: Business Subs | E5: Enterprise Subs | F5: Voice Subs | G5: Total Premise Subs | H5: Gross Adds
A6: 0 | B6: 0 | C6: 0 | D6: 0 | E6: 0 | F6: 0 | G6: 0 | H6: 0
A7: 1 | B7: =Assumptions!$F$14*MIN(1,$A7/Assumptions!$F$15) | C7: =Homes_Passed!$B$7*$B7 | D7: =Homes_Passed!$B$7*Assumptions!$C$32 | E7: =Assumptions!$F$20*MIN(1,$A7/Assumptions!$F$15) | F7: =$C7*Assumptions!$C$33 | G7: =$C7+$D7+$E7 | H7: =MAX(0,$G7-0)+0*Assumptions!$F$22
A8: 2 | B8: =Assumptions!$F$14*MIN(1,$A8/Assumptions!$F$15) | C8: =Homes_Passed!$B$8*$B8 | D8: =Homes_Passed!$B$8*Assumptions!$C$32 | E8: =Assumptions!$F$20*MIN(1,$A8/Assumptions!$F$15) | F8: =$C8*Assumptions!$C$33 | G8: =$C8+$D8+$E8 | H8: =MAX(0,$G8-$G7)+$G7*Assumptions!$F$22
A9: 3 | B9: =Assumptions!$F$14*MIN(1,$A9/Assumptions!$F$15) | C9: =Homes_Passed!$B$9*$B9 | D9: =Homes_Passed!$B$9*Assumptions!$C$32 | E9: =Assumptions!$F$20*MIN(1,$A9/Assumptions!$F$15) | F9: =$C9*Assumptions!$C$33 | G9: =$C9+$D9+$E9 | H9: =MAX(0,$G9-$G8)+$G8*Assumptions!$F$22
A10: 4 | B10: =Assumptions!$F$14*MIN(1,$A10/Assumptions!$F$15) | C10: =Homes_Passed!$B$10*$B10 | D10: =Homes_Passed!$B$10*Assumptions!$C$32 | E10: =Assumptions!$F$20*MIN(1,$A10/Assumptions!$F$15) | F10: =$C10*Assumptions!$C$33 | G10: =$C10+$D10+$E10 | H10: =MAX(0,$G10-$G9)+$G9*Assumptions!$F$22
A11: 5 | B11: =Assumptions!$F$14*MIN(1,$A11/Assumptions!$F$15) | C11: =Homes_Passed!$B$11*$B11 | D11: =Homes_Passed!$B$11*Assumptions!$C$32 | E11: =Assumptions!$F$20*MIN(1,$A11/Assumptions!$F$15) | F11: =$C11*Assumptions!$C$33 | G11: =$C11+$D11+$E11 | H11: =MAX(0,$G11-$G10)+$G10*Assumptions!$F$22
A12: 6 | B12: =Assumptions!$F$14*MIN(1,$A12/Assumptions!$F$15) | C12: =Homes_Passed!$B$12*$B12 | D12: =Homes_Passed!$B$12*Assumptions!$C$32 | E12: =Assumptions!$F$20*MIN(1,$A12/Assumptions!$F$15) | F12: =$C12*Assumptions!$C$33 | G12: =$C12+$D12+$E12 | H12: =MAX(0,$G12-$G11)+$G11*Assumptions!$F$22
A13: 7 | B13: =Assumptions!$F$14*MIN(1,$A13/Assumptions!$F$15) | C13: =Homes_Passed!$B$13*$B13 | D13: =Homes_Passed!$B$13*Assumptions!$C$32 | E13: =Assumptions!$F$20*MIN(1,$A13/Assumptions!$F$15) | F13: =$C13*Assumptions!$C$33 | G13: =$C13+$D13+$E13 | H13: =MAX(0,$G13-$G12)+$G12*Assumptions!$F$22
A14: 8 | B14: =Assumptions!$F$14*MIN(1,$A14/Assumptions!$F$15) | C14: =Homes_Passed!$B$14*$B14 | D14: =Homes_Passed!$B$14*Assumptions!$C$32 | E14: =Assumptions!$F$20*MIN(1,$A14/Assumptions!$F$15) | F14: =$C14*Assumptions!$C$33 | G14: =$C14+$D14+$E14 | H14: =MAX(0,$G14-$G13)+$G13*Assumptions!$F$22
A15: 9 | B15: =Assumptions!$F$14*MIN(1,$A15/Assumptions!$F$15) | C15: =Homes_Passed!$B$15*$B15 | D15: =Homes_Passed!$B$15*Assumptions!$C$32 | E15: =Assumptions!$F$20*MIN(1,$A15/Assumptions!$F$15) | F15: =$C15*Assumptions!$C$33 | G15: =$C15+$D15+$E15 | H15: =MAX(0,$G15-$G14)+$G14*Assumptions!$F$22
A16: 10 | B16: =Assumptions!$F$14*MIN(1,$A16/Assumptions!$F$15) | C16: =Homes_Passed!$B$16*$B16 | D16: =Homes_Passed!$B$16*Assumptions!$C$32 | E16: =Assumptions!$F$20*MIN(1,$A16/Assumptions!$F$15) | F16: =$C16*Assumptions!$C$33 | G16: =$C16+$D16+$E16 | H16: =MAX(0,$G16-$G15)+$G15*Assumptions!$F$22
A17: 11 | B17: =Assumptions!$F$14*MIN(1,$A17/Assumptions!$F$15) | C17: =Homes_Passed!$B$17*$B17 | D17: =Homes_Passed!$B$17*Assumptions!$C$32 | E17: =Assumptions!$F$20*MIN(1,$A17/Assumptions!$F$15) | F17: =$C17*Assumptions!$C$33 | G17: =$C17+$D17+$E17 | H17: =MAX(0,$G17-$G16)+$G16*Assumptions!$F$22
A18: 12 | B18: =Assumptions!$F$14*MIN(1,$A18/Assumptions!$F$15) | C18: =Homes_Passed!$B$18*$B18 | D18: =Homes_Passed!$B$18*Assumptions!$C$32 | E18: =Assumptions!$F$20*MIN(1,$A18/Assumptions!$F$15) | F18: =$C18*Assumptions!$C$33 | G18: =$C18+$D18+$E18 | H18: =MAX(0,$G18-$G17)+$G17*Assumptions!$F$22
A19: 13 | B19: =Assumptions!$F$14*MIN(1,$A19/Assumptions!$F$15) | C19: =Homes_Passed!$B$19*$B19 | D19: =Homes_Passed!$B$19*Assumptions!$C$32 | E19: =Assumptions!$F$20*MIN(1,$A19/Assumptions!$F$15) | F19: =$C19*Assumptions!$C$33 | G19: =$C19+$D19+$E19 | H19: =MAX(0,$G19-$G18)+$G18*Assumptions!$F$22
A20: 14 | B20: =Assumptions!$F$14*MIN(1,$A20/Assumptions!$F$15) | C20: =Homes_Passed!$B$20*$B20 | D20: =Homes_Passed!$B$20*Assumptions!$C$32 | E20: =Assumptions!$F$20*MIN(1,$A20/Assumptions!$F$15) | F20: =$C20*Assumptions!$C$33 | G20: =$C20+$D20+$E20 | H20: =MAX(0,$G20-$G19)+$G19*Assumptions!$F$22
A21: 15 | B21: =Assumptions!$F$14*MIN(1,$A21/Assumptions!$F$15) | C21: =Homes_Passed!$B$21*$B21 | D21: =Homes_Passed!$B$21*Assumptions!$C$32 | E21: =Assumptions!$F$20*MIN(1,$A21/Assumptions!$F$15) | F21: =$C21*Assumptions!$C$33 | G21: =$C21+$D21+$E21 | H21: =MAX(0,$G21-$G20)+$G20*Assumptions!$F$22
A22: 16 | B22: =Assumptions!$F$14*MIN(1,$A22/Assumptions!$F$15) | C22: =Homes_Passed!$B$22*$B22 | D22: =Homes_Passed!$B$22*Assumptions!$C$32 | E22: =Assumptions!$F$20*MIN(1,$A22/Assumptions!$F$15) | F22: =$C22*Assumptions!$C$33 | G22: =$C22+$D22+$E22 | H22: =MAX(0,$G22-$G21)+$G21*Assumptions!$F$22
A23: 17 | B23: =Assumptions!$F$14*MIN(1,$A23/Assumptions!$F$15) | C23: =Homes_Passed!$B$23*$B23 | D23: =Homes_Passed!$B$23*Assumptions!$C$32 | E23: =Assumptions!$F$20*MIN(1,$A23/Assumptions!$F$15) | F23: =$C23*Assumptions!$C$33 | G23: =$C23+$D23+$E23 | H23: =MAX(0,$G23-$G22)+$G22*Assumptions!$F$22
A24: 18 | B24: =Assumptions!$F$14*MIN(1,$A24/Assumptions!$F$15) | C24: =Homes_Passed!$B$24*$B24 | D24: =Homes_Passed!$B$24*Assumptions!$C$32 | E24: =Assumptions!$F$20*MIN(1,$A24/Assumptions!$F$15) | F24: =$C24*Assumptions!$C$33 | G24: =$C24+$D24+$E24 | H24: =MAX(0,$G24-$G23)+$G23*Assumptions!$F$22
A25: 19 | B25: =Assumptions!$F$14*MIN(1,$A25/Assumptions!$F$15) | C25: =Homes_Passed!$B$25*$B25 | D25: =Homes_Passed!$B$25*Assumptions!$C$32 | E25: =Assumptions!$F$20*MIN(1,$A25/Assumptions!$F$15) | F25: =$C25*Assumptions!$C$33 | G25: =$C25+$D25+$E25 | H25: =MAX(0,$G25-$G24)+$G24*Assumptions!$F$22
A26: 20 | B26: =Assumptions!$F$14*MIN(1,$A26/Assumptions!$F$15) | C26: =Homes_Passed!$B$26*$B26 | D26: =Homes_Passed!$B$26*Assumptions!$C$32 | E26: =Assumptions!$F$20*MIN(1,$A26/Assumptions!$F$15) | F26: =$C26*Assumptions!$C$33 | G26: =$C26+$D26+$E26 | H26: =MAX(0,$G26-$G25)+$G25*Assumptions!$F$22
A27: 21 | B27: =Assumptions!$F$14*MIN(1,$A27/Assumptions!$F$15) | C27: =Homes_Passed!$B$27*$B27 | D27: =Homes_Passed!$B$27*Assumptions!$C$32 | E27: =Assumptions!$F$20*MIN(1,$A27/Assumptions!$F$15) | F27: =$C27*Assumptions!$C$33 | G27: =$C27+$D27+$E27 | H27: =MAX(0,$G27-$G26)+$G26*Assumptions!$F$22
A28: 22 | B28: =Assumptions!$F$14*MIN(1,$A28/Assumptions!$F$15) | C28: =Homes_Passed!$B$28*$B28 | D28: =Homes_Passed!$B$28*Assumptions!$C$32 | E28: =Assumptions!$F$20*MIN(1,$A28/Assumptions!$F$15) | F28: =$C28*Assumptions!$C$33 | G28: =$C28+$D28+$E28 | H28: =MAX(0,$G28-$G27)+$G27*Assumptions!$F$22
A29: 23 | B29: =Assumptions!$F$14*MIN(1,$A29/Assumptions!$F$15) | C29: =Homes_Passed!$B$29*$B29 | D29: =Homes_Passed!$B$29*Assumptions!$C$32 | E29: =Assumptions!$F$20*MIN(1,$A29/Assumptions!$F$15) | F29: =$C29*Assumptions!$C$33 | G29: =$C29+$D29+$E29 | H29: =MAX(0,$G29-$G28)+$G28*Assumptions!$F$22
A30: 24 | B30: =Assumptions!$F$14*MIN(1,$A30/Assumptions!$F$15) | C30: =Homes_Passed!$B$30*$B30 | D30: =Homes_Passed!$B$30*Assumptions!$C$32 | E30: =Assumptions!$F$20*MIN(1,$A30/Assumptions!$F$15) | F30: =$C30*Assumptions!$C$33 | G30: =$C30+$D30+$E30 | H30: =MAX(0,$G30-$G29)+$G29*Assumptions!$F$22
A31: 25 | B31: =Assumptions!$F$14*MIN(1,$A31/Assumptions!$F$15) | C31: =Homes_Passed!$B$31*$B31 | D31: =Homes_Passed!$B$31*Assumptions!$C$32 | E31: =Assumptions!$F$20*MIN(1,$A31/Assumptions!$F$15) | F31: =$C31*Assumptions!$C$33 | G31: =$C31+$D31+$E31 | H31: =MAX(0,$G31-$G30)+$G30*Assumptions!$F$22
A32: 26 | B32: =Assumptions!$F$14*MIN(1,$A32/Assumptions!$F$15) | C32: =Homes_Passed!$B$32*$B32 | D32: =Homes_Passed!$B$32*Assumptions!$C$32 | E32: =Assumptions!$F$20*MIN(1,$A32/Assumptions!$F$15) | F32: =$C32*Assumptions!$C$33 | G32: =$C32+$D32+$E32 | H32: =MAX(0,$G32-$G31)+$G31*Assumptions!$F$22
A33: 27 | B33: =Assumptions!$F$14*MIN(1,$A33/Assumptions!$F$15) | C33: =Homes_Passed!$B$33*$B33 | D33: =Homes_Passed!$B$33*Assumptions!$C$32 | E33: =Assumptions!$F$20*MIN(1,$A33/Assumptions!$F$15) | F33: =$C33*Assumptions!$C$33 | G33: =$C33+$D33+$E33 | H33: =MAX(0,$G33-$G32)+$G32*Assumptions!$F$22
A34: 28 | B34: =Assumptions!$F$14*MIN(1,$A34/Assumptions!$F$15) | C34: =Homes_Passed!$B$34*$B34 | D34: =Homes_Passed!$B$34*Assumptions!$C$32 | E34: =Assumptions!$F$20*MIN(1,$A34/Assumptions!$F$15) | F34: =$C34*Assumptions!$C$33 | G34: =$C34+$D34+$E34 | H34: =MAX(0,$G34-$G33)+$G33*Assumptions!$F$22
A35: 29 | B35: =Assumptions!$F$14*MIN(1,$A35/Assumptions!$F$15) | C35: =Homes_Passed!$B$35*$B35 | D35: =Homes_Passed!$B$35*Assumptions!$C$32 | E35: =Assumptions!$F$20*MIN(1,$A35/Assumptions!$F$15) | F35: =$C35*Assumptions!$C$33 | G35: =$C35+$D35+$E35 | H35: =MAX(0,$G35-$G34)+$G34*Assumptions!$F$22
A36: 30 | B36: =Assumptions!$F$14*MIN(1,$A36/Assumptions!$F$15) | C36: =Homes_Passed!$B$36*$B36 | D36: =Homes_Passed!$B$36*Assumptions!$C$32 | E36: =Assumptions!$F$20*MIN(1,$A36/Assumptions!$F$15) | F36: =$C36*Assumptions!$C$33 | G36: =$C36+$D36+$E36 | H36: =MAX(0,$G36-$G35)+$G35*Assumptions!$F$22
B38: CHECK: residential subs never exceed homes passed | F38: =IF(SUMPRODUCT(--($C6:$C36>Homes_Passed!$B6:$B36))=0,"PASS","FAIL")

Sheet Revenue
A1: REVENUE — ARPU x Customers
A2: DRAFT FOR DISCUSSION – SUBJECT TO LEGAL, GRANT AND FINANCIAL REVIEW
A3: Monthly ARPU x 12. Revenue beyond the selected IRU term is zero (term gate).
A5: Year | B5: Residential | C5: Business | D5: Enterprise | E5: Voice | F5: Wholesale | G5: Installation | H5: Recurring Subtotal | I5: TOTAL GROSS REVENUE
A6: 0 | B6: 0 | C6: 0 | D6: 0 | E6: 0 | F6: 0 | G6: 0 | H6: 0 | I6: 0
A7: 1 | B7: =Take_Rate_Customers!$C$7*Assumptions!$F$16*(1+Assumptions!$C$35)^($A7-1)*12*IF($A7>Assumptions!$C$8,0,1) | C7: =Take_Rate_Customers!$D$7*Assumptions!$F$17*(1+Assumptions!$C$35)^($A7-1)*12*IF($A7>Assumptions!$C$8,0,1) | D7: =Take_Rate_Customers!$E$7*Assumptions!$F$18*(1+Assumptions!$C$35)^($A7-1)*12*IF($A7>Assumptions!$C$8,0,1) | E7: =Take_Rate_Customers!$F$7*Assumptions!$F$19*(1+Assumptions!$C$35)^($A7-1)*12*IF($A7>Assumptions!$C$8,0,1) | F7: =Assumptions!$F$21*MIN(1,$A7/Assumptions!$C$31)*IF($A7>Assumptions!$C$8,0,1) | G7: =Take_Rate_Customers!$H$7*Assumptions!$C$34*IF($A7>Assumptions!$C$8,0,1) | H7: =SUM($B7:$F7) | I7: =$H7+$G7
A8: 2 | B8: =Take_Rate_Customers!$C$8*Assumptions!$F$16*(1+Assumptions!$C$35)^($A8-1)*12*IF($A8>Assumptions!$C$8,0,1) | C8: =Take_Rate_Customers!$D$8*Assumptions!$F$17*(1+Assumptions!$C$35)^($A8-1)*12*IF($A8>Assumptions!$C$8,0,1) | D8: =Take_Rate_Customers!$E$8*Assumptions!$F$18*(1+Assumptions!$C$35)^($A8-1)*12*IF($A8>Assumptions!$C$8,0,1) | E8: =Take_Rate_Customers!$F$8*Assumptions!$F$19*(1+Assumptions!$C$35)^($A8-1)*12*IF($A8>Assumptions!$C$8,0,1) | F8: =Assumptions!$F$21*MIN(1,$A8/Assumptions!$C$31)*IF($A8>Assumptions!$C$8,0,1) | G8: =Take_Rate_Customers!$H$8*Assumptions!$C$34*IF($A8>Assumptions!$C$8,0,1) | H8: =SUM($B8:$F8) | I8: =$H8+$G8
A9: 3 | B9: =Take_Rate_Customers!$C$9*Assumptions!$F$16*(1+Assumptions!$C$35)^($A9-1)*12*IF($A9>Assumptions!$C$8,0,1) | C9: =Take_Rate_Customers!$D$9*Assumptions!$F$17*(1+Assumptions!$C$35)^($A9-1)*12*IF($A9>Assumptions!$C$8,0,1) | D9: =Take_Rate_Customers!$E$9*Assumptions!$F$18*(1+Assumptions!$C$35)^($A9-1)*12*IF($A9>Assumptions!$C$8,0,1) | E9: =Take_Rate_Customers!$F$9*Assumptions!$F$19*(1+Assumptions!$C$35)^($A9-1)*12*IF($A9>Assumptions!$C$8,0,1) | F9: =Assumptions!$F$21*MIN(1,$A9/Assumptions!$C$31)*IF($A9>Assumptions!$C$8,0,1) | G9: =Take_Rate_Customers!$H$9*Assumptions!$C$34*IF($A9>Assumptions!$C$8,0,1) | H9: =SUM($B9:$F9) | I9: =$H9+$G9
A10: 4 | B10: =Take_Rate_Customers!$C$10*Assumptions!$F$16*(1+Assumptions!$C$35)^($A10-1)*12*IF($A10>Assumptions!$C$8,0,1) | C10: =Take_Rate_Customers!$D$10*Assumptions!$F$17*(1+Assumptions!$C$35)^($A10-1)*12*IF($A10>Assumptions!$C$8,0,1) | D10: =Take_Rate_Customers!$E$10*Assumptions!$F$18*(1+Assumptions!$C$35)^($A10-1)*12*IF($A10>Assumptions!$C$8,0,1) | E10: =Take_Rate_Customers!$F$10*Assumptions!$F$19*(1+Assumptions!$C$35)^($A10-1)*12*IF($A10>Assumptions!$C$8,0,1) | F10: =Assumptions!$F$21*MIN(1,$A10/Assumptions!$C$31)*IF($A10>Assumptions!$C$8,0,1) | G10: =Take_Rate_Customers!$H$10*Assumptions!$C$34*IF($A10>Assumptions!$C$8,0,1) | H10: =SUM($B10:$F10) | I10: =$H10+$G10
A11: 5 | B11: =Take_Rate_Customers!$C$11*Assumptions!$F$16*(1+Assumptions!$C$35)^($A11-1)*12*IF($A11>Assumptions!$C$8,0,1) | C11: =Take_Rate_Customers!$D$11*Assumptions!$F$17*(1+Assumptions!$C$35)^($A11-1)*12*IF($A11>Assumptions!$C$8,0,1) | D11: =Take_Rate_Customers!$E$11*Assumptions!$F$18*(1+Assumptions!$C$35)^($A11-1)*12*IF($A11>Assumptions!$C$8,0,1) | E11: =Take_Rate_Customers!$F$11*Assumptions!$F$19*(1+Assumptions!$C$35)^($A11-1)*12*IF($A11>Assumptions!$C$8,0,1) | F11: =Assumptions!$F$21*MIN(1,$A11/Assumptions!$C$31)*IF($A11>Assumptions!$C$8,0,1) | G11: =Take_Rate_Customers!$H$11*Assumptions!$C$34*IF($A11>Assumptions!$C$8,0,1) | H11: =SUM($B11:$F11) | I11: =$H11+$G11
A12: 6 | B12: =Take_Rate_Customers!$C$12*Assumptions!$F$16*(1+Assumptions!$C$35)^($A12-1)*12*IF($A12>Assumptions!$C$8,0,1) | C12: =Take_Rate_Customers!$D$12*Assumptions!$F$17*(1+Assumptions!$C$35)^($A12-1)*12*IF($A12>Assumptions!$C$8,0,1) | D12: =Take_Rate_Customers!$E$12*Assumptions!$F$18*(1+Assumptions!$C$35)^($A12-1)*12*IF($A12>Assumptions!$C$8,0,1) | E12: =Take_Rate_Customers!$F$12*Assumptions!$F$19*(1+Assumptions!$C$35)^($A12-1)*12*IF($A12>Assumptions!$C$8,0,1) | F12: =Assumptions!$F$21*MIN(1,$A12/Assumptions!$C$31)*IF($A12>Assumptions!$C$8,0,1) | G12: =Take_Rate_Customers!$H$12*Assumptions!$C$34*IF($A12>Assumptions!$C$8,0,1) | H12: =SUM($B12:$F12) | I12: =$H12+$G12
A13: 7 | B13: =Take_Rate_Customers!$C$13*Assumptions!$F$16*(1+Assumptions!$C$35)^($A13-1)*12*IF($A13>Assumptions!$C$8,0,1) | C13: =Take_Rate_Customers!$D$13*Assumptions!$F$17*(1+Assumptions!$C$35)^($A13-1)*12*IF($A13>Assumptions!$C$8,0,1) | D13: =Take_Rate_Customers!$E$13*Assumptions!$F$18*(1+Assumptions!$C$35)^($A13-1)*12*IF($A13>Assumptions!$C$8,0,1) | E13: =Take_Rate_Customers!$F$13*Assumptions!$F$19*(1+Assumptions!$C$35)^($A13-1)*12*IF($A13>Assumptions!$C$8,0,1) | F13: =Assumptions!$F$21*MIN(1,$A13/Assumptions!$C$31)*IF($A13>Assumptions!$C$8,0,1) | G13: =Take_Rate_Customers!$H$13*Assumptions!$C$34*IF($A13>Assumptions!$C$8,0,1) | H13: =SUM($B13:$F13) | I13: =$H13+$G13
A14: 8 | B14: =Take_Rate_Customers!$C$14*Assumptions!$F$16*(1+Assumptions!$C$35)^($A14-1)*12*IF($A14>Assumptions!$C$8,0,1) | C14: =Take_Rate_Customers!$D$14*Assumptions!$F$17*(1+Assumptions!$C$35)^($A14-1)*12*IF($A14>Assumptions!$C$8,0,1) | D14: =Take_Rate_Customers!$E$14*Assumptions!$F$18*(1+Assumptions!$C$35)^($A14-1)*12*IF($A14>Assumptions!$C$8,0,1) | E14: =Take_Rate_Customers!$F$14*Assumptions!$F$19*(1+Assumptions!$C$35)^($A14-1)*12*IF($A14>Assumptions!$C$8,0,1) | F14: =Assumptions!$F$21*MIN(1,$A14/Assumptions!$C$31)*IF($A14>Assumptions!$C$8,0,1) | G14: =Take_Rate_Customers!$H$14*Assumptions!$C$34*IF($A14>Assumptions!$C$8,0,1) | H14: =SUM($B14:$F14) | I14: =$H14+$G14
A15: 9 | B15: =Take_Rate_Customers!$C$15*Assumptions!$F$16*(1+Assumptions!$C$35)^($A15-1)*12*IF($A15>Assumptions!$C$8,0,1) | C15: =Take_Rate_Customers!$D$15*Assumptions!$F$17*(1+Assumptions!$C$35)^($A15-1)*12*IF($A15>Assumptions!$C$8,0,1) | D15: =Take_Rate_Customers!$E$15*Assumptions!$F$18*(1+Assumptions!$C$35)^($A15-1)*12*IF($A15>Assumptions!$C$8,0,1) | E15: =Take_Rate_Customers!$F$15*Assumptions!$F$19*(1+Assumptions!$C$35)^($A15-1)*12*IF($A15>Assumptions!$C$8,0,1) | F15: =Assumptions!$F$21*MIN(1,$A15/Assumptions!$C$31)*IF($A15>Assumptions!$C$8,0,1) | G15: =Take_Rate_Customers!$H$15*Assumptions!$C$34*IF($A15>Assumptions!$C$8,0,1) | H15: =SUM($B15:$F15) | I15: =$H15+$G15
A16: 10 | B16: =Take_Rate_Customers!$C$16*Assumptions!$F$16*(1+Assumptions!$C$35)^($A16-1)*12*IF($A16>Assumptions!$C$8,0,1) | C16: =Take_Rate_Customers!$D$16*Assumptions!$F$17*(1+Assumptions!$C$35)^($A16-1)*12*IF($A16>Assumptions!$C$8,0,1) | D16: =Take_Rate_Customers!$E$16*Assumptions!$F$18*(1+Assumptions!$C$35)^($A16-1)*12*IF($A16>Assumptions!$C$8,0,1) | E16: =Take_Rate_Customers!$F$16*Assumptions!$F$19*(1+Assumptions!$C$35)^($A16-1)*12*IF($A16>Assumptions!$C$8,0,1) | F16: =Assumptions!$F$21*MIN(1,$A16/Assumptions!$C$31)*IF($A16>Assumptions!$C$8,0,1) | G16: =Take_Rate_Customers!$H$16*Assumptions!$C$34*IF($A16>Assumptions!$C$8,0,1) | H16: =SUM($B16:$F16) | I16: =$H16+$G16
A17: 11 | B17: =Take_Rate_Customers!$C$17*Assumptions!$F$16*(1+Assumptions!$C$35)^($A17-1)*12*IF($A17>Assumptions!$C$8,0,1) | C17: =Take_Rate_Customers!$D$17*Assumptions!$F$17*(1+Assumptions!$C$35)^($A17-1)*12*IF($A17>Assumptions!$C$8,0,1) | D17: =Take_Rate_Customers!$E$17*Assumptions!$F$18*(1+Assumptions!$C$35)^($A17-1)*12*IF($A17>Assumptions!$C$8,0,1) | E17: =Take_Rate_Customers!$F$17*Assumptions!$F$19*(1+Assumptions!$C$35)^($A17-1)*12*IF($A17>Assumptions!$C$8,0,1) | F17: =Assumptions!$F$21*MIN(1,$A17/Assumptions!$C$31)*IF($A17>Assumptions!$C$8,0,1) | G17: =Take_Rate_Customers!$H$17*Assumptions!$C$34*IF($A17>Assumptions!$C$8,0,1) | H17: =SUM($B17:$F17) | I17: =$H17+$G17
A18: 12 | B18: =Take_Rate_Customers!$C$18*Assumptions!$F$16*(1+Assumptions!$C$35)^($A18-1)*12*IF($A18>Assumptions!$C$8,0,1) | C18: =Take_Rate_Customers!$D$18*Assumptions!$F$17*(1+Assumptions!$C$35)^($A18-1)*12*IF($A18>Assumptions!$C$8,0,1) | D18: =Take_Rate_Customers!$E$18*Assumptions!$F$18*(1+Assumptions!$C$35)^($A18-1)*12*IF($A18>Assumptions!$C$8,0,1) | E18: =Take_Rate_Customers!$F$18*Assumptions!$F$19*(1+Assumptions!$C$35)^($A18-1)*12*IF($A18>Assumptions!$C$8,0,1) | F18: =Assumptions!$F$21*MIN(1,$A18/Assumptions!$C$31)*IF($A18>Assumptions!$C$8,0,1) | G18: =Take_Rate_Customers!$H$18*Assumptions!$C$34*IF($A18>Assumptions!$C$8,0,1) | H18: =SUM($B18:$F18) | I18: =$H18+$G18
A19: 13 | B19: =Take_Rate_Customers!$C$19*Assumptions!$F$16*(1+Assumptions!$C$35)^($A19-1)*12*IF($A19>Assumptions!$C$8,0,1) | C19: =Take_Rate_Customers!$D$19*Assumptions!$F$17*(1+Assumptions!$C$35)^($A19-1)*12*IF($A19>Assumptions!$C$8,0,1) | D19: =Take_Rate_Customers!$E$19*Assumptions!$F$18*(1+Assumptions!$C$35)^($A19-1)*12*IF($A19>Assumptions!$C$8,0,1) | E19: =Take_Rate_Customers!$F$19*Assumptions!$F$19*(1+Assumptions!$C$35)^($A19-1)*12*IF($A19>Assumptions!$C$8,0,1) | F19: =Assumptions!$F$21*MIN(1,$A19/Assumptions!$C$31)*IF($A19>Assumptions!$C$8,0,1) | G19: =Take_Rate_Customers!$H$19*Assumptions!$C$34*IF($A19>Assumptions!$C$8,0,1) | H19: =SUM($B19:$F19) | I19: =$H19+$G19
A20: 14 | B20: =Take_Rate_Customers!$C$20*Assumptions!$F$16*(1+Assumptions!$C$35)^($A20-1)*12*IF($A20>Assumptions!$C$8,0,1) | C20: =Take_Rate_Customers!$D$20*Assumptions!$F$17*(1+Assumptions!$C$35)^($A20-1)*12*IF($A20>Assumptions!$C$8,0,1) | D20: =Take_Rate_Customers!$E$20*Assumptions!$F$18*(1+Assumptions!$C$35)^($A20-1)*12*IF($A20>Assumptions!$C$8,0,1) | E20: =Take_Rate_Customers!$F$20*Assumptions!$F$19*(1+Assumptions!$C$35)^($A20-1)*12*IF($A20>Assumptions!$C$8,0,1) | F20: =Assumptions!$F$21*MIN(1,$A20/Assumptions!$C$31)*IF($A20>Assumptions!$C$8,0,1) | G20: =Take_Rate_Customers!$H$20*Assumptions!$C$34*IF($A20>Assumptions!$C$8,0,1) | H20: =SUM($B20:$F20) | I20: =$H20+$G20
A21: 15 | B21: =Take_Rate_Customers!$C$21*Assumptions!$F$16*(1+Assumptions!$C$35)^($A21-1)*12*IF($A21>Assumptions!$C$8,0,1) | C21: =Take_Rate_Customers!$D$21*Assumptions!$F$17*(1+Assumptions!$C$35)^($A21-1)*12*IF($A21>Assumptions!$C$8,0,1) | D21: =Take_Rate_Customers!$E$21*Assumptions!$F$18*(1+Assumptions!$C$35)^($A21-1)*12*IF($A21>Assumptions!$C$8,0,1) | E21: =Take_Rate_Customers!$F$21*Assumptions!$F$19*(1+Assumptions!$C$35)^($A21-1)*12*IF($A21>Assumptions!$C$8,0,1) | F21: =Assumptions!$F$21*MIN(1,$A21/Assumptions!$C$31)*IF($A21>Assumptions!$C$8,0,1) | G21: =Take_Rate_Customers!$H$21*Assumptions!$C$34*IF($A21>Assumptions!$C$8,0,1) | H21: =SUM($B21:$F21) | I21: =$H21+$G21
A22: 16 | B22: =Take_Rate_Customers!$C$22*Assumptions!$F$16*(1+Assumptions!$C$35)^($A22-1)*12*IF($A22>Assumptions!$C$8,0,1) | C22: =Take_Rate_Customers!$D$22*Assumptions!$F$17*(1+Assumptions!$C$35)^($A22-1)*12*IF($A22>Assumptions!$C$8,0,1) | D22: =Take_Rate_Customers!$E$22*Assumptions!$F$18*(1+Assumptions!$C$35)^($A22-1)*12*IF($A22>Assumptions!$C$8,0,1) | E22: =Take_Rate_Customers!$F$22*Assumptions!$F$19*(1+Assumptions!$C$35)^($A22-1)*12*IF($A22>Assumptions!$C$8,0,1) | F22: =Assumptions!$F$21*MIN(1,$A22/Assumptions!$C$31)*IF($A22>Assumptions!$C$8,0,1) | G22: =Take_Rate_Customers!$H$22*Assumptions!$C$34*IF($A22>Assumptions!$C$8,0,1) | H22: =SUM($B22:$F22) | I22: =$H22+$G22
A23: 17 | B23: =Take_Rate_Customers!$C$23*Assumptions!$F$16*(1+Assumptions!$C$35)^($A23-1)*12*IF($A23>Assumptions!$C$8,0,1) | C23: =Take_Rate_Customers!$D$23*Assumptions!$F$17*(1+Assumptions!$C$35)^($A23-1)*12*IF($A23>Assumptions!$C$8,0,1) | D23: =Take_Rate_Customers!$E$23*Assumptions!$F$18*(1+Assumptions!$C$35)^($A23-1)*12*IF($A23>Assumptions!$C$8,0,1) | E23: =Take_Rate_Customers!$F$23*Assumptions!$F$19*(1+Assumptions!$C$35)^($A23-1)*12*IF($A23>Assumptions!$C$8,0,1) | F23: =Assumptions!$F$21*MIN(1,$A23/Assumptions!$C$31)*IF($A23>Assumptions!$C$8,0,1) | G23: =Take_Rate_Customers!$H$23*Assumptions!$C$34*IF($A23>Assumptions!$C$8,0,1) | H23: =SUM($B23:$F23) | I23: =$H23+$G23
A24: 18 | B24: =Take_Rate_Customers!$C$24*Assumptions!$F$16*(1+Assumptions!$C$35)^($A24-1)*12*IF($A24>Assumptions!$C$8,0,1) | C24: =Take_Rate_Customers!$D$24*Assumptions!$F$17*(1+Assumptions!$C$35)^($A24-1)*12*IF($A24>Assumptions!$C$8,0,1) | D24: =Take_Rate_Customers!$E$24*Assumptions!$F$18*(1+Assumptions!$C$35)^($A24-1)*12*IF($A24>Assumptions!$C$8,0,1) | E24: =Take_Rate_Customers!$F$24*Assumptions!$F$19*(1+Assumptions!$C$35)^($A24-1)*12*IF($A24>Assumptions!$C$8,0,1) | F24: =Assumptions!$F$21*MIN(1,$A24/Assumptions!$C$31)*IF($A24>Assumptions!$C$8,0,1) | G24: =Take_Rate_Customers!$H$24*Assumptions!$C$34*IF($A24>Assumptions!$C$8,0,1) | H24: =SUM($B24:$F24) | I24: =$H24+$G24
A25: 19 | B25: =Take_Rate_Customers!$C$25*Assumptions!$F$16*(1+Assumptions!$C$35)^($A25-1)*12*IF($A25>Assumptions!$C$8,0,1) | C25: =Take_Rate_Customers!$D$25*Assumptions!$F$17*(1+Assumptions!$C$35)^($A25-1)*12*IF($A25>Assumptions!$C$8,0,1) | D25: =Take_Rate_Customers!$E$25*Assumptions!$F$18*(1+Assumptions!$C$35)^($A25-1)*12*IF($A25>Assumptions!$C$8,0,1) | E25: =Take_Rate_Customers!$F$25*Assumptions!$F$19*(1+Assumptions!$C$35)^($A25-1)*12*IF($A25>Assumptions!$C$8,0,1) | F25: =Assumptions!$F$21*MIN(1,$A25/Assumptions!$C$31)*IF($A25>Assumptions!$C$8,0,1) | G25: =Take_Rate_Customers!$H$25*Assumptions!$C$34*IF($A25>Assumptions!$C$8,0,1) | H25: =SUM($B25:$F25) | I25: =$H25+$G25
A26: 20 | B26: =Take_Rate_Customers!$C$26*Assumptions!$F$16*(1+Assumptions!$C$35)^($A26-1)*12*IF($A26>Assumptions!$C$8,0,1) | C26: =Take_Rate_Customers!$D$26*Assumptions!$F$17*(1+Assumptions!$C$35)^($A26-1)*12*IF($A26>Assumptions!$C$8,0,1) | D26: =Take_Rate_Customers!$E$26*Assumptions!$F$18*(1+Assumptions!$C$35)^($A26-1)*12*IF($A26>Assumptions!$C$8,0,1) | E26: =Take_Rate_Customers!$F$26*Assumptions!$F$19*(1+Assumptions!$C$35)^($A26-1)*12*IF($A26>Assumptions!$C$8,0,1) | F26: =Assumptions!$F$21*MIN(1,$A26/Assumptions!$C$31)*IF($A26>Assumptions!$C$8,0,1) | G26: =Take_Rate_Customers!$H$26*Assumptions!$C$34*IF($A26>Assumptions!$C$8,0,1) | H26: =SUM($B26:$F26) | I26: =$H26+$G26
A27: 21 | B27: =Take_Rate_Customers!$C$27*Assumptions!$F$16*(1+Assumptions!$C$35)^($A27-1)*12*IF($A27>Assumptions!$C$8,0,1) | C27: =Take_Rate_Customers!$D$27*Assumptions!$F$17*(1+Assumptions!$C$35)^($A27-1)*12*IF($A27>Assumptions!$C$8,0,1) | D27: =Take_Rate_Customers!$E$27*Assumptions!$F$18*(1+Assumptions!$C$35)^($A27-1)*12*IF($A27>Assumptions!$C$8,0,1) | E27: =Take_Rate_Customers!$F$27*Assumptions!$F$19*(1+Assumptions!$C$35)^($A27-1)*12*IF($A27>Assumptions!$C$8,0,1) | F27: =Assumptions!$F$21*MIN(1,$A27/Assumptions!$C$31)*IF($A27>Assumptions!$C$8,0,1) | G27: =Take_Rate_Customers!$H$27*Assumptions!$C$34*IF($A27>Assumptions!$C$8,0,1) | H27: =SUM($B27:$F27) | I27: =$H27+$G27
A28: 22 | B28: =Take_Rate_Customers!$C$28*Assumptions!$F$16*(1+Assumptions!$C$35)^($A28-1)*12*IF($A28>Assumptions!$C$8,0,1) | C28: =Take_Rate_Customers!$D$28*Assumptions!$F$17*(1+Assumptions!$C$35)^($A28-1)*12*IF($A28>Assumptions!$C$8,0,1) | D28: =Take_Rate_Customers!$E$28*Assumptions!$F$18*(1+Assumptions!$C$35)^($A28-1)*12*IF($A28>Assumptions!$C$8,0,1) | E28: =Take_Rate_Customers!$F$28*Assumptions!$F$19*(1+Assumptions!$C$35)^($A28-1)*12*IF($A28>Assumptions!$C$8,0,1) | F28: =Assumptions!$F$21*MIN(1,$A28/Assumptions!$C$31)*IF($A28>Assumptions!$C$8,0,1) | G28: =Take_Rate_Customers!$H$28*Assumptions!$C$34*IF($A28>Assumptions!$C$8,0,1) | H28: =SUM($B28:$F28) | I28: =$H28+$G28
A29: 23 | B29: =Take_Rate_Customers!$C$29*Assumptions!$F$16*(1+Assumptions!$C$35)^($A29-1)*12*IF($A29>Assumptions!$C$8,0,1) | C29: =Take_Rate_Customers!$D$29*Assumptions!$F$17*(1+Assumptions!$C$35)^($A29-1)*12*IF($A29>Assumptions!$C$8,0,1) | D29: =Take_Rate_Customers!$E$29*Assumptions!$F$18*(1+Assumptions!$C$35)^($A29-1)*12*IF($A29>Assumptions!$C$8,0,1) | E29: =Take_Rate_Customers!$F$29*Assumptions!$F$19*(1+Assumptions!$C$35)^($A29-1)*12*IF($A29>Assumptions!$C$8,0,1) | F29: =Assumptions!$F$21*MIN(1,$A29/Assumptions!$C$31)*IF($A29>Assumptions!$C$8,0,1) | G29: =Take_Rate_Customers!$H$29*Assumptions!$C$34*IF($A29>Assumptions!$C$8,0,1) | H29: =SUM($B29:$F29) | I29: =$H29+$G29
A30: 24 | B30: =Take_Rate_Customers!$C$30*Assumptions!$F$16*(1+Assumptions!$C$35)^($A30-1)*12*IF($A30>Assumptions!$C$8,0,1) | C30: =Take_Rate_Customers!$D$30*Assumptions!$F$17*(1+Assumptions!$C$35)^($A30-1)*12*IF($A30>Assumptions!$C$8,0,1) | D30: =Take_Rate_Customers!$E$30*Assumptions!$F$18*(1+Assumptions!$C$35)^($A30-1)*12*IF($A30>Assumptions!$C$8,0,1) | E30: =Take_Rate_Customers!$F$30*Assumptions!$F$19*(1+Assumptions!$C$35)^($A30-1)*12*IF($A30>Assumptions!$C$8,0,1) | F30: =Assumptions!$F$21*MIN(1,$A30/Assumptions!$C$31)*IF($A30>Assumptions!$C$8,0,1) | G30: =Take_Rate_Customers!$H$30*Assumptions!$C$34*IF($A30>Assumptions!$C$8,0,1) | H30: =SUM($B30:$F30) | I30: =$H30+$G30
A31: 25 | B31: =Take_Rate_Customers!$C$31*Assumptions!$F$16*(1+Assumptions!$C$35)^($A31-1)*12*IF($A31>Assumptions!$C$8,0,1) | C31: =Take_Rate_Customers!$D$31*Assumptions!$F$17*(1+Assumptions!$C$35)^($A31-1)*12*IF($A31>Assumptions!$C$8,0,1) | D31: =Take_Rate_Customers!$E$31*Assumptions!$F$18*(1+Assumptions!$C$35)^($A31-1)*12*IF($A31>Assumptions!$C$8,0,1) | E31: =Take_Rate_Customers!$F$31*Assumptions!$F$19*(1+Assumptions!$C$35)^($A31-1)*12*IF($A31>Assumptions!$C$8,0,1) | F31: =Assumptions!$F$21*MIN(1,$A31/Assumptions!$C$31)*IF($A31>Assumptions!$C$8,0,1) | G31: =Take_Rate_Customers!$H$31*Assumptions!$C$34*IF($A31>Assumptions!$C$8,0,1) | H31: =SUM($B31:$F31) | I31: =$H31+$G31
A32: 26 | B32: =Take_Rate_Customers!$C$32*Assumptions!$F$16*(1+Assumptions!$C$35)^($A32-1)*12*IF($A32>Assumptions!$C$8,0,1) | C32: =Take_Rate_Customers!$D$32*Assumptions!$F$17*(1+Assumptions!$C$35)^($A32-1)*12*IF($A32>Assumptions!$C$8,0,1) | D32: =Take_Rate_Customers!$E$32*Assumptions!$F$18*(1+Assumptions!$C$35)^($A32-1)*12*IF($A32>Assumptions!$C$8,0,1) | E32: =Take_Rate_Customers!$F$32*Assumptions!$F$19*(1+Assumptions!$C$35)^($A32-1)*12*IF($A32>Assumptions!$C$8,0,1) | F32: =Assumptions!$F$21*MIN(1,$A32/Assumptions!$C$31)*IF($A32>Assumptions!$C$8,0,1) | G32: =Take_Rate_Customers!$H$32*Assumptions!$C$34*IF($A32>Assumptions!$C$8,0,1) | H32: =SUM($B32:$F32) | I32: =$H32+$G32
A33: 27 | B33: =Take_Rate_Customers!$C$33*Assumptions!$F$16*(1+Assumptions!$C$35)^($A33-1)*12*IF($A33>Assumptions!$C$8,0,1) | C33: =Take_Rate_Customers!$D$33*Assumptions!$F$17*(1+Assumptions!$C$35)^($A33-1)*12*IF($A33>Assumptions!$C$8,0,1) | D33: =Take_Rate_Customers!$E$33*Assumptions!$F$18*(1+Assumptions!$C$35)^($A33-1)*12*IF($A33>Assumptions!$C$8,0,1) | E33: =Take_Rate_Customers!$F$33*Assumptions!$F$19*(1+Assumptions!$C$35)^($A33-1)*12*IF($A33>Assumptions!$C$8,0,1) | F33: =Assumptions!$F$21*MIN(1,$A33/Assumptions!$C$31)*IF($A33>Assumptions!$C$8,0,1) | G33: =Take_Rate_Customers!$H$33*Assumptions!$C$34*IF($A33>Assumptions!$C$8,0,1) | H33: =SUM($B33:$F33) | I33: =$H33+$G33
A34: 28 | B34: =Take_Rate_Customers!$C$34*Assumptions!$F$16*(1+Assumptions!$C$35)^($A34-1)*12*IF($A34>Assumptions!$C$8,0,1) | C34: =Take_Rate_Customers!$D$34*Assumptions!$F$17*(1+Assumptions!$C$35)^($A34-1)*12*IF($A34>Assumptions!$C$8,0,1) | D34: =Take_Rate_Customers!$E$34*Assumptions!$F$18*(1+Assumptions!$C$35)^($A34-1)*12*IF($A34>Assumptions!$C$8,0,1) | E34: =Take_Rate_Customers!$F$34*Assumptions!$F$19*(1+Assumptions!$C$35)^($A34-1)*12*IF($A34>Assumptions!$C$8,0,1) | F34: =Assumptions!$F$21*MIN(1,$A34/Assumptions!$C$31)*IF($A34>Assumptions!$C$8,0,1) | G34: =Take_Rate_Customers!$H$34*Assumptions!$C$34*IF($A34>Assumptions!$C$8,0,1) | H34: =SUM($B34:$F34) | I34: =$H34+$G34
A35: 29 | B35: =Take_Rate_Customers!$C$35*Assumptions!$F$16*(1+Assumptions!$C$35)^($A35-1)*12*IF($A35>Assumptions!$C$8,0,1) | C35: =Take_Rate_Customers!$D$35*Assumptions!$F$17*(1+Assumptions!$C$35)^($A35-1)*12*IF($A35>Assumptions!$C$8,0,1) | D35: =Take_Rate_Customers!$E$35*Assumptions!$F$18*(1+Assumptions!$C$35)^($A35-1)*12*IF($A35>Assumptions!$C$8,0,1) | E35: =Take_Rate_Customers!$F$35*Assumptions!$F$19*(1+Assumptions!$C$35)^($A35-1)*12*IF($A35>Assumptions!$C$8,0,1) | F35: =Assumptions!$F$21*MIN(1,$A35/Assumptions!$C$31)*IF($A35>Assumptions!$C$8,0,1) | G35: =Take_Rate_Customers!$H$35*Assumptions!$C$34*IF($A35>Assumptions!$C$8,0,1) | H35: =SUM($B35:$F35) | I35: =$H35+$G35
A36: 30 | B36: =Take_Rate_Customers!$C$36*Assumptions!$F$16*(1+Assumptions!$C$35)^($A36-1)*12*IF($A36>Assumptions!$C$8,0,1) | C36: =Take_Rate_Customers!$D$36*Assumptions!$F$17*(1+Assumptions!$C$35)^($A36-1)*12*IF($A36>Assumptions!$C$8,0,1) | D36: =Take_Rate_Customers!$E$36*Assumptions!$F$18*(1+Assumptions!$C$35)^($A36-1)*12*IF($A36>Assumptions!$C$8,0,1) | E36: =Take_Rate_Customers!$F$36*Assumptions!$F$19*(1+Assumptions!$C$35)^($A36-1)*12*IF($A36>Assumptions!$C$8,0,1) | F36: =Assumptions!$F$21*MIN(1,$A36/Assumptions!$C$31)*IF($A36>Assumptions!$C$8,0,1) | G36: =Take_Rate_Customers!$H$36*Assumptions!$C$34*IF($A36>Assumptions!$C$8,0,1) | H36: =SUM($B36:$F36) | I36: =$H36+$G36
B38: CHECK: no #REF errors in total gross revenue column | F38: =IF(SUMPRODUCT(--ISERROR($I6:$I36))=0,"PASS","FAIL")

Sheet Operating_Expenses
A1: OPERATING EXPENSES
A2: DRAFT FOR DISCUSSION – SUBJECT TO LEGAL, GRANT AND FINANCIAL REVIEW
A3: Fixed components inflate; %-of-revenue components scale with revenue. Electronics replacement is a MEMO here — the capital charge lives in Capital_Replacement to avoid double counting.
A5: Year | B5: Infl. Factor | C5: Network Ops | D5: Maintenance | E5: Staffing | F5: Marketing | G5: G&A | H5: Bad Debt | I5: TOTAL OPEX | J5: Electronics (memo)
A6: 0 | B6: 1 | C6: 0 | D6: 0 | E6: 0 | F6: 0 | G6: 0 | H6: 0 | I6: 0 | J6: 0
A7: 1 | B7: =(1+Assumptions!$F$24)^($A7-1) | C7: =Take_Rate_Customers!$G$7*Assumptions!$C$36*$B7 | D7: =Assumptions!$C$37*Construction_Budget!$E$17*$B7 | E7: =Assumptions!$C$38*Assumptions!$C$39*$B7 | F7: =Assumptions!$C$40*Revenue!$I$7 | G7: =Assumptions!$C$41*Revenue!$I$7 | H7: =Assumptions!$F$23*Revenue!$H$7 | I7: =SUM($C7:$H7) | J7: =Construction_Budget!$E$19/Assumptions!$C$42*$B7
A8: 2 | B8: =(1+Assumptions!$F$24)^($A8-1) | C8: =Take_Rate_Customers!$G$8*Assumptions!$C$36*$B8 | D8: =Assumptions!$C$37*Construction_Budget!$E$17*$B8 | E8: =Assumptions!$C$38*Assumptions!$C$39*$B8 | F8: =Assumptions!$C$40*Revenue!$I$8 | G8: =Assumptions!$C$41*Revenue!$I$8 | H8: =Assumptions!$F$23*Revenue!$H$8 | I8: =SUM($C8:$H8) | J8: =Construction_Budget!$E$19/Assumptions!$C$42*$B8
A9: 3 | B9: =(1+Assumptions!$F$24)^($A9-1) | C9: =Take_Rate_Customers!$G$9*Assumptions!$C$36*$B9 | D9: =Assumptions!$C$37*Construction_Budget!$E$17*$B9 | E9: =Assumptions!$C$38*Assumptions!$C$39*$B9 | F9: =Assumptions!$C$40*Revenue!$I$9 | G9: =Assumptions!$C$41*Revenue!$I$9 | H9: =Assumptions!$F$23*Revenue!$H$9 | I9: =SUM($C9:$H9) | J9: =Construction_Budget!$E$19/Assumptions!$C$42*$B9
A10: 4 | B10: =(1+Assumptions!$F$24)^($A10-1) | C10: =Take_Rate_Customers!$G$10*Assumptions!$C$36*$B10 | D10: =Assumptions!$C$37*Construction_Budget!$E$17*$B10 | E10: =Assumptions!$C$38*Assumptions!$C$39*$B10 | F10: =Assumptions!$C$40*Revenue!$I$10 | G10: =Assumptions!$C$41*Revenue!$I$10 | H10: =Assumptions!$F$23*Revenue!$H$10 | I10: =SUM($C10:$H10) | J10: =Construction_Budget!$E$19/Assumptions!$C$42*$B10
A11: 5 | B11: =(1+Assumptions!$F$24)^($A11-1) | C11: =Take_Rate_Customers!$G$11*Assumptions!$C$36*$B11 | D11: =Assumptions!$C$37*Construction_Budget!$E$17*$B11 | E11: =Assumptions!$C$38*Assumptions!$C$39*$B11 | F11: =Assumptions!$C$40*Revenue!$I$11 | G11: =Assumptions!$C$41*Revenue!$I$11 | H11: =Assumptions!$F$23*Revenue!$H$11 | I11: =SUM($C11:$H11) | J11: =Construction_Budget!$E$19/Assumptions!$C$42*$B11
A12: 6 | B12: =(1+Assumptions!$F$24)^($A12-1) | C12: =Take_Rate_Customers!$G$12*Assumptions!$C$36*$B12 | D12: =Assumptions!$C$37*Construction_Budget!$E$17*$B12 | E12: =Assumptions!$C$38*Assumptions!$C$39*$B12 | F12: =Assumptions!$C$40*Revenue!$I$12 | G12: =Assumptions!$C$41*Revenue!$I$12 | H12: =Assumptions!$F$23*Revenue!$H$12 | I12: =SUM($C12:$H12) | J12: =Construction_Budget!$E$19/Assumptions!$C$42*$B12
A13: 7 | B13: =(1+Assumptions!$F$24)^($A13-1) | C13: =Take_Rate_Customers!$G$13*Assumptions!$C$36*$B13 | D13: =Assumptions!$C$37*Construction_Budget!$E$17*$B13 | E13: =Assumptions!$C$38*Assumptions!$C$39*$B13 | F13: =Assumptions!$C$40*Revenue!$I$13 | G13: =Assumptions!$C$41*Revenue!$I$13 | H13: =Assumptions!$F$23*Revenue!$H$13 | I13: =SUM($C13:$H13) | J13: =Construction_Budget!$E$19/Assumptions!$C$42*$B13
A14: 8 | B14: =(1+Assumptions!$F$24)^($A14-1) | C14: =Take_Rate_Customers!$G$14*Assumptions!$C$36*$B14 | D14: =Assumptions!$C$37*Construction_Budget!$E$17*$B14 | E14: =Assumptions!$C$38*Assumptions!$C$39*$B14 | F14: =Assumptions!$C$40*Revenue!$I$14 | G14: =Assumptions!$C$41*Revenue!$I$14 | H14: =Assumptions!$F$23*Revenue!$H$14 | I14: =SUM($C14:$H14) | J14: =Construction_Budget!$E$19/Assumptions!$C$42*$B14
A15: 9 | B15: =(1+Assumptions!$F$24)^($A15-1) | C15: =Take_Rate_Customers!$G$15*Assumptions!$C$36*$B15 | D15: =Assumptions!$C$37*Construction_Budget!$E$17*$B15 | E15: =Assumptions!$C$38*Assumptions!$C$39*$B15 | F15: =Assumptions!$C$40*Revenue!$I$15 | G15: =Assumptions!$C$41*Revenue!$I$15 | H15: =Assumptions!$F$23*Revenue!$H$15 | I15: =SUM($C15:$H15) | J15: =Construction_Budget!$E$19/Assumptions!$C$42*$B15
A16: 10 | B16: =(1+Assumptions!$F$24)^($A16-1) | C16: =Take_Rate_Customers!$G$16*Assumptions!$C$36*$B16 | D16: =Assumptions!$C$37*Construction_Budget!$E$17*$B16 | E16: =Assumptions!$C$38*Assumptions!$C$39*$B16 | F16: =Assumptions!$C$40*Revenue!$I$16 | G16: =Assumptions!$C$41*Revenue!$I$16 | H16: =Assumptions!$F$23*Revenue!$H$16 | I16: =SUM($C16:$H16) | J16: =Construction_Budget!$E$19/Assumptions!$C$42*$B16
A17: 11 | B17: =(1+Assumptions!$F$24)^($A17-1) | C17: =Take_Rate_Customers!$G$17*Assumptions!$C$36*$B17 | D17: =Assumptions!$C$37*Construction_Budget!$E$17*$B17 | E17: =Assumptions!$C$38*Assumptions!$C$39*$B17 | F17: =Assumptions!$C$40*Revenue!$I$17 | G17: =Assumptions!$C$41*Revenue!$I$17 | H17: =Assumptions!$F$23*Revenue!$H$17 | I17: =SUM($C17:$H17) | J17: =Construction_Budget!$E$19/Assumptions!$C$42*$B17
A18: 12 | B18: =(1+Assumptions!$F$24)^($A18-1) | C18: =Take_Rate_Customers!$G$18*Assumptions!$C$36*$B18 | D18: =Assumptions!$C$37*Construction_Budget!$E$17*$B18 | E18: =Assumptions!$C$38*Assumptions!$C$39*$B18 | F18: =Assumptions!$C$40*Revenue!$I$18 | G18: =Assumptions!$C$41*Revenue!$I$18 | H18: =Assumptions!$F$23*Revenue!$H$18 | I18: =SUM($C18:$H18) | J18: =Construction_Budget!$E$19/Assumptions!$C$42*$B18
A19: 13 | B19: =(1+Assumptions!$F$24)^($A19-1) | C19: =Take_Rate_Customers!$G$19*Assumptions!$C$36*$B19 | D19: =Assumptions!$C$37*Construction_Budget!$E$17*$B19 | E19: =Assumptions!$C$38*Assumptions!$C$39*$B19 | F19: =Assumptions!$C$40*Revenue!$I$19 | G19: =Assumptions!$C$41*Revenue!$I$19 | H19: =Assumptions!$F$23*Revenue!$H$19 | I19: =SUM($C19:$H19) | J19: =Construction_Budget!$E$19/Assumptions!$C$42*$B19
A20: 14 | B20: =(1+Assumptions!$F$24)^($A20-1) | C20: =Take_Rate_Customers!$G$20*Assumptions!$C$36*$B20 | D20: =Assumptions!$C$37*Construction_Budget!$E$17*$B20 | E20: =Assumptions!$C$38*Assumptions!$C$39*$B20 | F20: =Assumptions!$C$40*Revenue!$I$20 | G20: =Assumptions!$C$41*Revenue!$I$20 | H20: =Assumptions!$F$23*Revenue!$H$20 | I20: =SUM($C20:$H20) | J20: =Construction_Budget!$E$19/Assumptions!$C$42*$B20
A21: 15 | B21: =(1+Assumptions!$F$24)^($A21-1) | C21: =Take_Rate_Customers!$G$21*Assumptions!$C$36*$B21 | D21: =Assumptions!$C$37*Construction_Budget!$E$17*$B21 | E21: =Assumptions!$C$38*Assumptions!$C$39*$B21 | F21: =Assumptions!$C$40*Revenue!$I$21 | G21: =Assumptions!$C$41*Revenue!$I$21 | H21: =Assumptions!$F$23*Revenue!$H$21 | I21: =SUM($C21:$H21) | J21: =Construction_Budget!$E$19/Assumptions!$C$42*$B21
A22: 16 | B22: =(1+Assumptions!$F$24)^($A22-1) | C22: =Take_Rate_Customers!$G$22*Assumptions!$C$36*$B22 | D22: =Assumptions!$C$37*Construction_Budget!$E$17*$B22 | E22: =Assumptions!$C$38*Assumptions!$C$39*$B22 | F22: =Assumptions!$C$40*Revenue!$I$22 | G22: =Assumptions!$C$41*Revenue!$I$22 | H22: =Assumptions!$F$23*Revenue!$H$22 | I22: =SUM($C22:$H22) | J22: =Construction_Budget!$E$19/Assumptions!$C$42*$B22
A23: 17 | B23: =(1+Assumptions!$F$24)^($A23-1) | C23: =Take_Rate_Customers!$G$23*Assumptions!$C$36*$B23 | D23: =Assumptions!$C$37*Construction_Budget!$E$17*$B23 | E23: =Assumptions!$C$38*Assumptions!$C$39*$B23 | F23: =Assumptions!$C$40*Revenue!$I$23 | G23: =Assumptions!$C$41*Revenue!$I$23 | H23: =Assumptions!$F$23*Revenue!$H$23 | I23: =SUM($C23:$H23) | J23: =Construction_Budget!$E$19/Assumptions!$C$42*$B23
A24: 18 | B24: =(1+Assumptions!$F$24)^($A24-1) | C24: =Take_Rate_Customers!$G$24*Assumptions!$C$36*$B24 | D24: =Assumptions!$C$37*Construction_Budget!$E$17*$B24 | E24: =Assumptions!$C$38*Assumptions!$C$39*$B24 | F24: =Assumptions!$C$40*Revenue!$I$24 | G24: =Assumptions!$C$41*Revenue!$I$24 | H24: =Assumptions!$F$23*Revenue!$H$24 | I24: =SUM($C24:$H24) | J24: =Construction_Budget!$E$19/Assumptions!$C$42*$B24
A25: 19 | B25: =(1+Assumptions!$F$24)^($A25-1) | C25: =Take_Rate_Customers!$G$25*Assumptions!$C$36*$B25 | D25: =Assumptions!$C$37*Construction_Budget!$E$17*$B25 | E25: =Assumptions!$C$38*Assumptions!$C$39*$B25 | F25: =Assumptions!$C$40*Revenue!$I$25 | G25: =Assumptions!$C$41*Revenue!$I$25 | H25: =Assumptions!$F$23*Revenue!$H$25 | I25: =SUM($C25:$H25) | J25: =Construction_Budget!$E$19/Assumptions!$C$42*$B25
A26: 20 | B26: =(1+Assumptions!$F$24)^($A26-1) | C26: =Take_Rate_Customers!$G$26*Assumptions!$C$36*$B26 | D26: =Assumptions!$C$37*Construction_Budget!$E$17*$B26 | E26: =Assumptions!$C$38*Assumptions!$C$39*$B26 | F26: =Assumptions!$C$40*Revenue!$I$26 | G26: =Assumptions!$C$41*Revenue!$I$26 | H26: =Assumptions!$F$23*Revenue!$H$26 | I26: =SUM($C26:$H26) | J26: =Construction_Budget!$E$19/Assumptions!$C$42*$B26
A27: 21 | B27: =(1+Assumptions!$F$24)^($A27-1) | C27: =Take_Rate_Customers!$G$27*Assumptions!$C$36*$B27 | D27: =Assumptions!$C$37*Construction_Budget!$E$17*$B27 | E27: =Assumptions!$C$38*Assumptions!$C$39*$B27 | F27: =Assumptions!$C$40*Revenue!$I$27 | G27: =Assumptions!$C$41*Revenue!$I$27 | H27: =Assumptions!$F$23*Revenue!$H$27 | I27: =SUM($C27:$H27) | J27: =Construction_Budget!$E$19/Assumptions!$C$42*$B27
A28: 22 | B28: =(1+Assumptions!$F$24)^($A28-1) | C28: =Take_Rate_Customers!$G$28*Assumptions!$C$36*$B28 | D28: =Assumptions!$C$37*Construction_Budget!$E$17*$B28 | E28: =Assumptions!$C$38*Assumptions!$C$39*$B28 | F28: =Assumptions!$C$40*Revenue!$I$28 | G28: =Assumptions!$C$41*Revenue!$I$28 | H28: =Assumptions!$F$23*Revenue!$H$28 | I28: =SUM($C28:$H28) | J28: =Construction_Budget!$E$19/Assumptions!$C$42*$B28
A29: 23 | B29: =(1+Assumptions!$F$24)^($A29-1) | C29: =Take_Rate_Customers!$G$29*Assumptions!$C$36*$B29 | D29: =Assumptions!$C$37*Construction_Budget!$E$17*$B29 | E29: =Assumptions!$C$38*Assumptions!$C$39*$B29 | F29: =Assumptions!$C$40*Revenue!$I$29 | G29: =Assumptions!$C$41*Revenue!$I$29 | H29: =Assumptions!$F$23*Revenue!$H$29 | I29: =SUM($C29:$H29) | J29: =Construction_Budget!$E$19/Assumptions!$C$42*$B29
A30: 24 | B30: =(1+Assumptions!$F$24)^($A30-1) | C30: =Take_Rate_Customers!$G$30*Assumptions!$C$36*$B30 | D30: =Assumptions!$C$37*Construction_Budget!$E$17*$B30 | E30: =Assumptions!$C$38*Assumptions!$C$39*$B30 | F30: =Assumptions!$C$40*Revenue!$I$30 | G30: =Assumptions!$C$41*Revenue!$I$30 | H30: =Assumptions!$F$23*Revenue!$H$30 | I30: =SUM($C30:$H30) | J30: =Construction_Budget!$E$19/Assumptions!$C$42*$B30
A31: 25 | B31: =(1+Assumptions!$F$24)^($A31-1) | C31: =Take_Rate_Customers!$G$31*Assumptions!$C$36*$B31 | D31: =Assumptions!$C$37*Construction_Budget!$E$17*$B31 | E31: =Assumptions!$C$38*Assumptions!$C$39*$B31 | F31: =Assumptions!$C$40*Revenue!$I$31 | G31: =Assumptions!$C$41*Revenue!$I$31 | H31: =Assumptions!$F$23*Revenue!$H$31 | I31: =SUM($C31:$H31) | J31: =Construction_Budget!$E$19/Assumptions!$C$42*$B31
A32: 26 | B32: =(1+Assumptions!$F$24)^($A32-1) | C32: =Take_Rate_Customers!$G$32*Assumptions!$C$36*$B32 | D32: =Assumptions!$C$37*Construction_Budget!$E$17*$B32 | E32: =Assumptions!$C$38*Assumptions!$C$39*$B32 | F32: =Assumptions!$C$40*Revenue!$I$32 | G32: =Assumptions!$C$41*Revenue!$I$32 | H32: =Assumptions!$F$23*Revenue!$H$32 | I32: =SUM($C32:$H32) | J32: =Construction_Budget!$E$19/Assumptions!$C$42*$B32
A33: 27 | B33: =(1+Assumptions!$F$24)^($A33-1) | C33: =Take_Rate_Customers!$G$33*Assumptions!$C$36*$B33 | D33: =Assumptions!$C$37*Construction_Budget!$E$17*$B33 | E33: =Assumptions!$C$38*Assumptions!$C$39*$B33 | F33: =Assumptions!$C$40*Revenue!$I$33 | G33: =Assumptions!$C$41*Revenue!$I$33 | H33: =Assumptions!$F$23*Revenue!$H$33 | I33: =SUM($C33:$H33) | J33: =Construction_Budget!$E$19/Assumptions!$C$42*$B33
A34: 28 | B34: =(1+Assumptions!$F$24)^($A34-1) | C34: =Take_Rate_Customers!$G$34*Assumptions!$C$36*$B34 | D34: =Assumptions!$C$37*Construction_Budget!$E$17*$B34 | E34: =Assumptions!$C$38*Assumptions!$C$39*$B34 | F34: =Assumptions!$C$40*Revenue!$I$34 | G34: =Assumptions!$C$41*Revenue!$I$34 | H34: =Assumptions!$F$23*Revenue!$H$34 | I34: =SUM($C34:$H34) | J34: =Construction_Budget!$E$19/Assumptions!$C$42*$B34
A35: 29 | B35: =(1+Assumptions!$F$24)^($A35-1) | C35: =Take_Rate_Customers!$G$35*Assumptions!$C$36*$B35 | D35: =Assumptions!$C$37*Construction_Budget!$E$17*$B35 | E35: =Assumptions!$C$38*Assumptions!$C$39*$B35 | F35: =Assumptions!$C$40*Revenue!$I$35 | G35: =Assumptions!$C$41*Revenue!$I$35 | H35: =Assumptions!$F$23*Revenue!$H$35 | I35: =SUM($C35:$H35) | J35: =Construction_Budget!$E$19/Assumptions!$C$42*$B35
A36: 30 | B36: =(1+Assumptions!$F$24)^($A36-1) | C36: =Take_Rate_Customers!$G$36*Assumptions!$C$36*$B36 | D36: =Assumptions!$C$37*Construction_Budget!$E$17*$B36 | E36: =Assumptions!$C$38*Assumptions!$C$39*$B36 | F36: =Assumptions!$C$40*Revenue!$I$36 | G36: =Assumptions!$C$41*Revenue!$I$36 | H36: =Assumptions!$F$23*Revenue!$H$36 | I36: =SUM($C36:$H36) | J36: =Construction_Budget!$E$19/Assumptions!$C$42*$B36
B38: CHECK: total opex is non-negative and error-free | F38: =IF(AND(MIN($I6:$I36)>=0,SUMPRODUCT(--ISERROR($I6:$I36))=0),"PASS","FAIL")

Sheet Capital_Replacement
A1: CAPITAL REPLACEMENT — Electronics Refresh & Reserve
A2: DRAFT FOR DISCUSSION – SUBJECT TO LEGAL, GRANT AND FINANCIAL REVIEW
A3: Annualized charge flows to cash flow. Lumpy refresh + reserve funding test reserve adequacy.
A5: Year | B5: Annualized Elec. Charge | C5: Lumpy Refresh (memo) | D5: Reserve Funding | E5: Cum. Reserve | F5: Cum. Refresh Spend
A6: 0 | B6: 0 | C6: 0 | D6: 0 | E6: 0 | F6: 0
A7: 1 | B7: =Construction_Budget!$E$19/Assumptions!$C$42*(1+Assumptions!$F$24)^($A7-1) | C7: =IF(AND($A7>0,MOD($A7,Assumptions!$C$42)=0),Construction_Budget!$E$19*(1+Assumptions!$F$24)^$A7,0) | D7: =Assumptions!$C$43*Revenue!$I$7 | E7: =0+$D7 | F7: =0+$C7
A8: 2 | B8: =Construction_Budget!$E$19/Assumptions!$C$42*(1+Assumptions!$F$24)^($A8-1) | C8: =IF(AND($A8>0,MOD($A8,Assumptions!$C$42)=0),Construction_Budget!$E$19*(1+Assumptions!$F$24)^$A8,0) | D8: =Assumptions!$C$43*Revenue!$I$8 | E8: =$E7+$D8 | F8: =$F7+$C8
A9: 3 | B9: =Construction_Budget!$E$19/Assumptions!$C$42*(1+Assumptions!$F$24)^($A9-1) | C9: =IF(AND($A9>0,MOD($A9,Assumptions!$C$42)=0),Construction_Budget!$E$19*(1+Assumptions!$F$24)^$A9,0) | D9: =Assumptions!$C$43*Revenue!$I$9 | E9: =$E8+$D9 | F9: =$F8+$C9
A10: 4 | B10: =Construction_Budget!$E$19/Assumptions!$C$42*(1+Assumptions!$F$24)^($A10-1) | C10: =IF(AND($A10>0,MOD($A10,Assumptions!$C$42)=0),Construction_Budget!$E$19*(1+Assumptions!$F$24)^$A10,0) | D10: =Assumptions!$C$43*Revenue!$I$10 | E10: =$E9+$D10 | F10: =$F9+$C10
A11: 5 | B11: =Construction_Budget!$E$19/Assumptions!$C$42*(1+Assumptions!$F$24)^($A11-1) | C11: =IF(AND($A11>0,MOD($A11,Assumptions!$C$42)=0),Construction_Budget!$E$19*(1+Assumptions!$F$24)^$A11,0) | D11: =Assumptions!$C$43*Revenue!$I$11 | E11: =$E10+$D11 | F11: =$F10+$C11
A12: 6 | B12: =Construction_Budget!$E$19/Assumptions!$C$42*(1+Assumptions!$F$24)^($A12-1) | C12: =IF(AND($A12>0,MOD($A12,Assumptions!$C$42)=0),Construction_Budget!$E$19*(1+Assumptions!$F$24)^$A12,0) | D12: =Assumptions!$C$43*Revenue!$I$12 | E12: =$E11+$D12 | F12: =$F11+$C12
A13: 7 | B13: =Construction_Budget!$E$19/Assumptions!$C$42*(1+Assumptions!$F$24)^($A13-1) | C13: =IF(AND($A13>0,MOD($A13,Assumptions!$C$42)=0),Construction_Budget!$E$19*(1+Assumptions!$F$24)^$A13,0) | D13: =Assumptions!$C$43*Revenue!$I$13 | E13: =$E12+$D13 | F13: =$F12+$C13
A14: 8 | B14: =Construction_Budget!$E$19/Assumptions!$C$42*(1+Assumptions!$F$24)^($A14-1) | C14: =IF(AND($A14>0,MOD($A14,Assumptions!$C$42)=0),Construction_Budget!$E$19*(1+Assumptions!$F$24)^$A14,0) | D14: =Assumptions!$C$43*Revenue!$I$14 | E14: =$E13+$D14 | F14: =$F13+$C14
A15: 9 | B15: =Construction_Budget!$E$19/Assumptions!$C$42*(1+Assumptions!$F$24)^($A15-1) | C15: =IF(AND($A15>0,MOD($A15,Assumptions!$C$42)=0),Construction_Budget!$E$19*(1+Assumptions!$F$24)^$A15,0) | D15: =Assumptions!$C$43*Revenue!$I$15 | E15: =$E14+$D15 | F15: =$F14+$C15
A16: 10 | B16: =Construction_Budget!$E$19/Assumptions!$C$42*(1+Assumptions!$F$24)^($A16-1) | C16: =IF(AND($A16>0,MOD($A16,Assumptions!$C$42)=0),Construction_Budget!$E$19*(1+Assumptions!$F$24)^$A16,0) | D16: =Assumptions!$C$43*Revenue!$I$16 | E16: =$E15+$D16 | F16: =$F15+$C16
A17: 11 | B17: =Construction_Budget!$E$19/Assumptions!$C$42*(1+Assumptions!$F$24)^($A17-1) | C17: =IF(AND($A17>0,MOD($A17,Assumptions!$C$42)=0),Construction_Budget!$E$19*(1+Assumptions!$F$24)^$A17,0) | D17: =Assumptions!$C$43*Revenue!$I$17 | E17: =$E16+$D17 | F17: =$F16+$C17
A18: 12 | B18: =Construction_Budget!$E$19/Assumptions!$C$42*(1+Assumptions!$F$24)^($A18-1) | C18: =IF(AND($A18>0,MOD($A18,Assumptions!$C$42)=0),Construction_Budget!$E$19*(1+Assumptions!$F$24)^$A18,0) | D18: =Assumptions!$C$43*Revenue!$I$18 | E18: =$E17+$D18 | F18: =$F17+$C18
A19: 13 | B19: =Construction_Budget!$E$19/Assumptions!$C$42*(1+Assumptions!$F$24)^($A19-1) | C19: =IF(AND($A19>0,MOD($A19,Assumptions!$C$42)=0),Construction_Budget!$E$19*(1+Assumptions!$F$24)^$A19,0) | D19: =Assumptions!$C$43*Revenue!$I$19 | E19: =$E18+$D19 | F19: =$F18+$C19
A20: 14 | B20: =Construction_Budget!$E$19/Assumptions!$C$42*(1+Assumptions!$F$24)^($A20-1) | C20: =IF(AND($A20>0,MOD($A20,Assumptions!$C$42)=0),Construction_Budget!$E$19*(1+Assumptions!$F$24)^$A20,0) | D20: =Assumptions!$C$43*Revenue!$I$20 | E20: =$E19+$D20 | F20: =$F19+$C20
A21: 15 | B21: =Construction_Budget!$E$19/Assumptions!$C$42*(1+Assumptions!$F$24)^($A21-1) | C21: =IF(AND($A21>0,MOD($A21,Assumptions!$C$42)=0),Construction_Budget!$E$19*(1+Assumptions!$F$24)^$A21,0) | D21: =Assumptions!$C$43*Revenue!$I$21 | E21: =$E20+$D21 | F21: =$F20+$C21
A22: 16 | B22: =Construction_Budget!$E$19/Assumptions!$C$42*(1+Assumptions!$F$24)^($A22-1) | C22: =IF(AND($A22>0,MOD($A22,Assumptions!$C$42)=0),Construction_Budget!$E$19*(1+Assumptions!$F$24)^$A22,0) | D22: =Assumptions!$C$43*Revenue!$I$22 | E22: =$E21+$D22 | F22: =$F21+$C22
A23: 17 | B23: =Construction_Budget!$E$19/Assumptions!$C$42*(1+Assumptions!$F$24)^($A23-1) | C23: =IF(AND($A23>0,MOD($A23,Assumptions!$C$42)=0),Construction_Budget!$E$19*(1+Assumptions!$F$24)^$A23,0) | D23: =Assumptions!$C$43*Revenue!$I$23 | E23: =$E22+$D23 | F23: =$F22+$C23
A24: 18 | B24: =Construction_Budget!$E$19/Assumptions!$C$42*(1+Assumptions!$F$24)^($A24-1) | C24: =IF(AND($A24>0,MOD($A24,Assumptions!$C$42)=0),Construction_Budget!$E$19*(1+Assumptions!$F$24)^$A24,0) | D24: =Assumptions!$C$43*Revenue!$I$24 | E24: =$E23+$D24 | F24: =$F23+$C24
A25: 19 | B25: =Construction_Budget!$E$19/Assumptions!$C$42*(1+Assumptions!$F$24)^($A25-1) | C25: =IF(AND($A25>0,MOD($A25,Assumptions!$C$42)=0),Construction_Budget!$E$19*(1+Assumptions!$F$24)^$A25,0) | D25: =Assumptions!$C$43*Revenue!$I$25 | E25: =$E24+$D25 | F25: =$F24+$C25
A26: 20 | B26: =Construction_Budget!$E$19/Assumptions!$C$42*(1+Assumptions!$F$24)^($A26-1) | C26: =IF(AND($A26>0,MOD($A26,Assumptions!$C$42)=0),Construction_Budget!$E$19*(1+Assumptions!$F$24)^$A26,0) | D26: =Assumptions!$C$43*Revenue!$I$26 | E26: =$E25+$D26 | F26: =$F25+$C26
A27: 21 | B27: =Construction_Budget!$E$19/Assumptions!$C$42*(1+Assumptions!$F$24)^($A27-1) | C27: =IF(AND($A27>0,MOD($A27,Assumptions!$C$42)=0),Construction_Budget!$E$19*(1+Assumptions!$F$24)^$A27,0) | D27: =Assumptions!$C$43*Revenue!$I$27 | E27: =$E26+$D27 | F27: =$F26+$C27
A28: 22 | B28: =Construction_Budget!$E$19/Assumptions!$C$42*(1+Assumptions!$F$24)^($A28-1) | C28: =IF(AND($A28>0,MOD($A28,Assumptions!$C$42)=0),Construction_Budget!$E$19*(1+Assumptions!$F$24)^$A28,0) | D28: =Assumptions!$C$43*Revenue!$I$28 | E28: =$E27+$D28 | F28: =$F27+$C28
A29: 23 | B29: =Construction_Budget!$E$19/Assumptions!$C$42*(1+Assumptions!$F$24)^($A29-1) | C29: =IF(AND($A29>0,MOD($A29,Assumptions!$C$42)=0),Construction_Budget!$E$19*(1+Assumptions!$F$24)^$A29,0) | D29: =Assumptions!$C$43*Revenue!$I$29 | E29: =$E28+$D29 | F29: =$F28+$C29
A30: 24 | B30: =Construction_Budget!$E$19/Assumptions!$C$42*(1+Assumptions!$F$24)^($A30-1) | C30: =IF(AND($A30>0,MOD($A30,Assumptions!$C$42)=0),Construction_Budget!$E$19*(1+Assumptions!$F$24)^$A30,0) | D30: =Assumptions!$C$43*Revenue!$I$30 | E30: =$E29+$D30 | F30: =$F29+$C30
A31: 25 | B31: =Construction_Budget!$E$19/Assumptions!$C$42*(1+Assumptions!$F$24)^($A31-1) | C31: =IF(AND($A31>0,MOD($A31,Assumptions!$C$42)=0),Construction_Budget!$E$19*(1+Assumptions!$F$24)^$A31,0) | D31: =Assumptions!$C$43*Revenue!$I$31 | E31: =$E30+$D31 | F31: =$F30+$C31
A32: 26 | B32: =Construction_Budget!$E$19/Assumptions!$C$42*(1+Assumptions!$F$24)^($A32-1) | C32: =IF(AND($A32>0,MOD($A32,Assumptions!$C$42)=0),Construction_Budget!$E$19*(1+Assumptions!$F$24)^$A32,0) | D32: =Assumptions!$C$43*Revenue!$I$32 | E32: =$E31+$D32 | F32: =$F31+$C32
A33: 27 | B33: =Construction_Budget!$E$19/Assumptions!$C$42*(1+Assumptions!$F$24)^($A33-1) | C33: =IF(AND($A33>0,MOD($A33,Assumptions!$C$42)=0),Construction_Budget!$E$19*(1+Assumptions!$F$24)^$A33,0) | D33: =Assumptions!$C$43*Revenue!$I$33 | E33: =$E32+$D33 | F33: =$F32+$C33
A34: 28 | B34: =Construction_Budget!$E$19/Assumptions!$C$42*(1+Assumptions!$F$24)^($A34-1) | C34: =IF(AND($A34>0,MOD($A34,Assumptions!$C$42)=0),Construction_Budget!$E$19*(1+Assumptions!$F$24)^$A34,0) | D34: =Assumptions!$C$43*Revenue!$I$34 | E34: =$E33+$D34 | F34: =$F33+$C34
A35: 29 | B35: =Construction_Budget!$E$19/Assumptions!$C$42*(1+Assumptions!$F$24)^($A35-1) | C35: =IF(AND($A35>0,MOD($A35,Assumptions!$C$42)=0),Construction_Budget!$E$19*(1+Assumptions!$F$24)^$A35,0) | D35: =Assumptions!$C$43*Revenue!$I$35 | E35: =$E34+$D35 | F35: =$F34+$C35
A36: 30 | B36: =Construction_Budget!$E$19/Assumptions!$C$42*(1+Assumptions!$F$24)^($A36-1) | C36: =IF(AND($A36>0,MOD($A36,Assumptions!$C$42)=0),Construction_Budget!$E$19*(1+Assumptions!$F$24)^$A36,0) | D36: =Assumptions!$C$43*Revenue!$I$36 | E36: =$E35+$D36 | F36: =$F35+$C36
B38: CHECK: reserve funding covers cumulative refresh spend at horizon | F38: =IF($E36>=$F36,"PASS","FAIL — under-reserved")

Sheet Revenue_Share_Options
A1: REVENUE-SHARE OPTIONS — Tribal Payment by Option
A2: DRAFT FOR DISCUSSION – SUBJECT TO LEGAL, GRANT AND FINANCIAL REVIEW
A3: All five computed every year; SELECTED follows the option switch. Payments beyond term = 0.
A5: Year | B5: Gross Revenue | C5: Adj. Op. Cash Flow | D5: A: Fixed | E5: B: % Gross | F5: C: % Op CF | G5: D: Hybrid | H5: E: Holiday/Step | I5: SELECTED (active option)
A6: 0 | B6: 0 | C6: 0 | D6: 0 | E6: 0 | F6: 0 | G6: 0 | H6: 0 | I6: 0
A7: 1 | B7: =Revenue!$I$7 | C7: =Revenue!$I$7-Operating_Expenses!$I$7-Capital_Replacement!$B$7 | D7: =Assumptions!$C$49*(1+Assumptions!$C$50)^($A7-1)*IF($A7>Assumptions!$C$8,0,1) | E7: =Assumptions!$C$51*$B7*IF($A7>Assumptions!$C$8,0,1) | F7: =Assumptions!$C$52*MAX(0,$C7)*IF($A7>Assumptions!$C$8,0,1) | G7: =(Assumptions!$C$53+Assumptions!$C$54*$B7)*IF($A7>Assumptions!$C$8,0,1) | H7: =IF($A7<=Assumptions!$C$55,0,Assumptions!$C$56*(1+Assumptions!$C$57)^($A7-Assumptions!$C$55-1))*IF($A7>Assumptions!$C$8,0,1) | I7: =CHOOSE(Assumptions!$C$9,$D7,$E7,$F7,$G7,$H7)
A8: 2 | B8: =Revenue!$I$8 | C8: =Revenue!$I$8-Operating_Expenses!$I$8-Capital_Replacement!$B$8 | D8: =Assumptions!$C$49*(1+Assumptions!$C$50)^($A8-1)*IF($A8>Assumptions!$C$8,0,1) | E8: =Assumptions!$C$51*$B8*IF($A8>Assumptions!$C$8,0,1) | F8: =Assumptions!$C$52*MAX(0,$C8)*IF($A8>Assumptions!$C$8,0,1) | G8: =(Assumptions!$C$53+Assumptions!$C$54*$B8)*IF($A8>Assumptions!$C$8,0,1) | H8: =IF($A8<=Assumptions!$C$55,0,Assumptions!$C$56*(1+Assumptions!$C$57)^($A8-Assumptions!$C$55-1))*IF($A8>Assumptions!$C$8,0,1) | I8: =CHOOSE(Assumptions!$C$9,$D8,$E8,$F8,$G8,$H8)
A9: 3 | B9: =Revenue!$I$9 | C9: =Revenue!$I$9-Operating_Expenses!$I$9-Capital_Replacement!$B$9 | D9: =Assumptions!$C$49*(1+Assumptions!$C$50)^($A9-1)*IF($A9>Assumptions!$C$8,0,1) | E9: =Assumptions!$C$51*$B9*IF($A9>Assumptions!$C$8,0,1) | F9: =Assumptions!$C$52*MAX(0,$C9)*IF($A9>Assumptions!$C$8,0,1) | G9: =(Assumptions!$C$53+Assumptions!$C$54*$B9)*IF($A9>Assumptions!$C$8,0,1) | H9: =IF($A9<=Assumptions!$C$55,0,Assumptions!$C$56*(1+Assumptions!$C$57)^($A9-Assumptions!$C$55-1))*IF($A9>Assumptions!$C$8,0,1) | I9: =CHOOSE(Assumptions!$C$9,$D9,$E9,$F9,$G9,$H9)
A10: 4 | B10: =Revenue!$I$10 | C10: =Revenue!$I$10-Operating_Expenses!$I$10-Capital_Replacement!$B$10 | D10: =Assumptions!$C$49*(1+Assumptions!$C$50)^($A10-1)*IF($A10>Assumptions!$C$8,0,1) | E10: =Assumptions!$C$51*$B10*IF($A10>Assumptions!$C$8,0,1) | F10: =Assumptions!$C$52*MAX(0,$C10)*IF($A10>Assumptions!$C$8,0,1) | G10: =(Assumptions!$C$53+Assumptions!$C$54*$B10)*IF($A10>Assumptions!$C$8,0,1) | H10: =IF($A10<=Assumptions!$C$55,0,Assumptions!$C$56*(1+Assumptions!$C$57)^($A10-Assumptions!$C$55-1))*IF($A10>Assumptions!$C$8,0,1) | I10: =CHOOSE(Assumptions!$C$9,$D10,$E10,$F10,$G10,$H10)
A11: 5 | B11: =Revenue!$I$11 | C11: =Revenue!$I$11-Operating_Expenses!$I$11-Capital_Replacement!$B$11 | D11: =Assumptions!$C$49*(1+Assumptions!$C$50)^($A11-1)*IF($A11>Assumptions!$C$8,0,1) | E11: =Assumptions!$C$51*$B11*IF($A11>Assumptions!$C$8,0,1) | F11: =Assumptions!$C$52*MAX(0,$C11)*IF($A11>Assumptions!$C$8,0,1) | G11: =(Assumptions!$C$53+Assumptions!$C$54*$B11)*IF($A11>Assumptions!$C$8,0,1) | H11: =IF($A11<=Assumptions!$C$55,0,Assumptions!$C$56*(1+Assumptions!$C$57)^($A11-Assumptions!$C$55-1))*IF($A11>Assumptions!$C$8,0,1) | I11: =CHOOSE(Assumptions!$C$9,$D11,$E11,$F11,$G11,$H11)
A12: 6 | B12: =Revenue!$I$12 | C12: =Revenue!$I$12-Operating_Expenses!$I$12-Capital_Replacement!$B$12 | D12: =Assumptions!$C$49*(1+Assumptions!$C$50)^($A12-1)*IF($A12>Assumptions!$C$8,0,1) | E12: =Assumptions!$C$51*$B12*IF($A12>Assumptions!$C$8,0,1) | F12: =Assumptions!$C$52*MAX(0,$C12)*IF($A12>Assumptions!$C$8,0,1) | G12: =(Assumptions!$C$53+Assumptions!$C$54*$B12)*IF($A12>Assumptions!$C$8,0,1) | H12: =IF($A12<=Assumptions!$C$55,0,Assumptions!$C$56*(1+Assumptions!$C$57)^($A12-Assumptions!$C$55-1))*IF($A12>Assumptions!$C$8,0,1) | I12: =CHOOSE(Assumptions!$C$9,$D12,$E12,$F12,$G12,$H12)
A13: 7 | B13: =Revenue!$I$13 | C13: =Revenue!$I$13-Operating_Expenses!$I$13-Capital_Replacement!$B$13 | D13: =Assumptions!$C$49*(1+Assumptions!$C$50)^($A13-1)*IF($A13>Assumptions!$C$8,0,1) | E13: =Assumptions!$C$51*$B13*IF($A13>Assumptions!$C$8,0,1) | F13: =Assumptions!$C$52*MAX(0,$C13)*IF($A13>Assumptions!$C$8,0,1) | G13: =(Assumptions!$C$53+Assumptions!$C$54*$B13)*IF($A13>Assumptions!$C$8,0,1) | H13: =IF($A13<=Assumptions!$C$55,0,Assumptions!$C$56*(1+Assumptions!$C$57)^($A13-Assumptions!$C$55-1))*IF($A13>Assumptions!$C$8,0,1) | I13: =CHOOSE(Assumptions!$C$9,$D13,$E13,$F13,$G13,$H13)
A14: 8 | B14: =Revenue!$I$14 | C14: =Revenue!$I$14-Operating_Expenses!$I$14-Capital_Replacement!$B$14 | D14: =Assumptions!$C$49*(1+Assumptions!$C$50)^($A14-1)*IF($A14>Assumptions!$C$8,0,1) | E14: =Assumptions!$C$51*$B14*IF($A14>Assumptions!$C$8,0,1) | F14: =Assumptions!$C$52*MAX(0,$C14)*IF($A14>Assumptions!$C$8,0,1) | G14: =(Assumptions!$C$53+Assumptions!$C$54*$B14)*IF($A14>Assumptions!$C$8,0,1) | H14: =IF($A14<=Assumptions!$C$55,0,Assumptions!$C$56*(1+Assumptions!$C$57)^($A14-Assumptions!$C$55-1))*IF($A14>Assumptions!$C$8,0,1) | I14: =CHOOSE(Assumptions!$C$9,$D14,$E14,$F14,$G14,$H14)
A15: 9 | B15: =Revenue!$I$15 | C15: =Revenue!$I$15-Operating_Expenses!$I$15-Capital_Replacement!$B$15 | D15: =Assumptions!$C$49*(1+Assumptions!$C$50)^($A15-1)*IF($A15>Assumptions!$C$8,0,1) | E15: =Assumptions!$C$51*$B15*IF($A15>Assumptions!$C$8,0,1) | F15: =Assumptions!$C$52*MAX(0,$C15)*IF($A15>Assumptions!$C$8,0,1) | G15: =(Assumptions!$C$53+Assumptions!$C$54*$B15)*IF($A15>Assumptions!$C$8,0,1) | H15: =IF($A15<=Assumptions!$C$55,0,Assumptions!$C$56*(1+Assumptions!$C$57)^($A15-Assumptions!$C$55-1))*IF($A15>Assumptions!$C$8,0,1) | I15: =CHOOSE(Assumptions!$C$9,$D15,$E15,$F15,$G15,$H15)
A16: 10 | B16: =Revenue!$I$16 | C16: =Revenue!$I$16-Operating_Expenses!$I$16-Capital_Replacement!$B$16 | D16: =Assumptions!$C$49*(1+Assumptions!$C$50)^($A16-1)*IF($A16>Assumptions!$C$8,0,1) | E16: =Assumptions!$C$51*$B16*IF($A16>Assumptions!$C$8,0,1) | F16: =Assumptions!$C$52*MAX(0,$C16)*IF($A16>Assumptions!$C$8,0,1) | G16: =(Assumptions!$C$53+Assumptions!$C$54*$B16)*IF($A16>Assumptions!$C$8,0,1) | H16: =IF($A16<=Assumptions!$C$55,0,Assumptions!$C$56*(1+Assumptions!$C$57)^($A16-Assumptions!$C$55-1))*IF($A16>Assumptions!$C$8,0,1) | I16: =CHOOSE(Assumptions!$C$9,$D16,$E16,$F16,$G16,$H16)
A17: 11 | B17: =Revenue!$I$17 | C17: =Revenue!$I$17-Operating_Expenses!$I$17-Capital_Replacement!$B$17 | D17: =Assumptions!$C$49*(1+Assumptions!$C$50)^($A17-1)*IF($A17>Assumptions!$C$8,0,1) | E17: =Assumptions!$C$51*$B17*IF($A17>Assumptions!$C$8,0,1) | F17: =Assumptions!$C$52*MAX(0,$C17)*IF($A17>Assumptions!$C$8,0,1) | G17: =(Assumptions!$C$53+Assumptions!$C$54*$B17)*IF($A17>Assumptions!$C$8,0,1) | H17: =IF($A17<=Assumptions!$C$55,0,Assumptions!$C$56*(1+Assumptions!$C$57)^($A17-Assumptions!$C$55-1))*IF($A17>Assumptions!$C$8,0,1) | I17: =CHOOSE(Assumptions!$C$9,$D17,$E17,$F17,$G17,$H17)
A18: 12 | B18: =Revenue!$I$18 | C18: =Revenue!$I$18-Operating_Expenses!$I$18-Capital_Replacement!$B$18 | D18: =Assumptions!$C$49*(1+Assumptions!$C$50)^($A18-1)*IF($A18>Assumptions!$C$8,0,1) | E18: =Assumptions!$C$51*$B18*IF($A18>Assumptions!$C$8,0,1) | F18: =Assumptions!$C$52*MAX(0,$C18)*IF($A18>Assumptions!$C$8,0,1) | G18: =(Assumptions!$C$53+Assumptions!$C$54*$B18)*IF($A18>Assumptions!$C$8,0,1) | H18: =IF($A18<=Assumptions!$C$55,0,Assumptions!$C$56*(1+Assumptions!$C$57)^($A18-Assumptions!$C$55-1))*IF($A18>Assumptions!$C$8,0,1) | I18: =CHOOSE(Assumptions!$C$9,$D18,$E18,$F18,$G18,$H18)
A19: 13 | B19: =Revenue!$I$19 | C19: =Revenue!$I$19-Operating_Expenses!$I$19-Capital_Replacement!$B$19 | D19: =Assumptions!$C$49*(1+Assumptions!$C$50)^($A19-1)*IF($A19>Assumptions!$C$8,0,1) | E19: =Assumptions!$C$51*$B19*IF($A19>Assumptions!$C$8,0,1) | F19: =Assumptions!$C$52*MAX(0,$C19)*IF($A19>Assumptions!$C$8,0,1) | G19: =(Assumptions!$C$53+Assumptions!$C$54*$B19)*IF($A19>Assumptions!$C$8,0,1) | H19: =IF($A19<=Assumptions!$C$55,0,Assumptions!$C$56*(1+Assumptions!$C$57)^($A19-Assumptions!$C$55-1))*IF($A19>Assumptions!$C$8,0,1) | I19: =CHOOSE(Assumptions!$C$9,$D19,$E19,$F19,$G19,$H19)
A20: 14 | B20: =Revenue!$I$20 | C20: =Revenue!$I$20-Operating_Expenses!$I$20-Capital_Replacement!$B$20 | D20: =Assumptions!$C$49*(1+Assumptions!$C$50)^($A20-1)*IF($A20>Assumptions!$C$8,0,1) | E20: =Assumptions!$C$51*$B20*IF($A20>Assumptions!$C$8,0,1) | F20: =Assumptions!$C$52*MAX(0,$C20)*IF($A20>Assumptions!$C$8,0,1) | G20: =(Assumptions!$C$53+Assumptions!$C$54*$B20)*IF($A20>Assumptions!$C$8,0,1) | H20: =IF($A20<=Assumptions!$C$55,0,Assumptions!$C$56*(1+Assumptions!$C$57)^($A20-Assumptions!$C$55-1))*IF($A20>Assumptions!$C$8,0,1) | I20: =CHOOSE(Assumptions!$C$9,$D20,$E20,$F20,$G20,$H20)
A21: 15 | B21: =Revenue!$I$21 | C21: =Revenue!$I$21-Operating_Expenses!$I$21-Capital_Replacement!$B$21 | D21: =Assumptions!$C$49*(1+Assumptions!$C$50)^($A21-1)*IF($A21>Assumptions!$C$8,0,1) | E21: =Assumptions!$C$51*$B21*IF($A21>Assumptions!$C$8,0,1) | F21: =Assumptions!$C$52*MAX(0,$C21)*IF($A21>Assumptions!$C$8,0,1) | G21: =(Assumptions!$C$53+Assumptions!$C$54*$B21)*IF($A21>Assumptions!$C$8,0,1) | H21: =IF($A21<=Assumptions!$C$55,0,Assumptions!$C$56*(1+Assumptions!$C$57)^($A21-Assumptions!$C$55-1))*IF($A21>Assumptions!$C$8,0,1) | I21: =CHOOSE(Assumptions!$C$9,$D21,$E21,$F21,$G21,$H21)
A22: 16 | B22: =Revenue!$I$22 | C22: =Revenue!$I$22-Operating_Expenses!$I$22-Capital_Replacement!$B$22 | D22: =Assumptions!$C$49*(1+Assumptions!$C$50)^($A22-1)*IF($A22>Assumptions!$C$8,0,1) | E22: =Assumptions!$C$51*$B22*IF($A22>Assumptions!$C$8,0,1) | F22: =Assumptions!$C$52*MAX(0,$C22)*IF($A22>Assumptions!$C$8,0,1) | G22: =(Assumptions!$C$53+Assumptions!$C$54*$B22)*IF($A22>Assumptions!$C$8,0,1) | H22: =IF($A22<=Assumptions!$C$55,0,Assumptions!$C$56*(1+Assumptions!$C$57)^($A22-Assumptions!$C$55-1))*IF($A22>Assumptions!$C$8,0,1) | I22: =CHOOSE(Assumptions!$C$9,$D22,$E22,$F22,$G22,$H22)
A23: 17 | B23: =Revenue!$I$23 | C23: =Revenue!$I$23-Operating_Expenses!$I$23-Capital_Replacement!$B$23 | D23: =Assumptions!$C$49*(1+Assumptions!$C$50)^($A23-1)*IF($A23>Assumptions!$C$8,0,1) | E23: =Assumptions!$C$51*$B23*IF($A23>Assumptions!$C$8,0,1) | F23: =Assumptions!$C$52*MAX(0,$C23)*IF($A23>Assumptions!$C$8,0,1) | G23: =(Assumptions!$C$53+Assumptions!$C$54*$B23)*IF($A23>Assumptions!$C$8,0,1) | H23: =IF($A23<=Assumptions!$C$55,0,Assumptions!$C$56*(1+Assumptions!$C$57)^($A23-Assumptions!$C$55-1))*IF($A23>Assumptions!$C$8,0,1) | I23: =CHOOSE(Assumptions!$C$9,$D23,$E23,$F23,$G23,$H23)
A24: 18 | B24: =Revenue!$I$24 | C24: =Revenue!$I$24-Operating_Expenses!$I$24-Capital_Replacement!$B$24 | D24: =Assumptions!$C$49*(1+Assumptions!$C$50)^($A24-1)*IF($A24>Assumptions!$C$8,0,1) | E24: =Assumptions!$C$51*$B24*IF($A24>Assumptions!$C$8,0,1) | F24: =Assumptions!$C$52*MAX(0,$C24)*IF($A24>Assumptions!$C$8,0,1) | G24: =(Assumptions!$C$53+Assumptions!$C$54*$B24)*IF($A24>Assumptions!$C$8,0,1) | H24: =IF($A24<=Assumptions!$C$55,0,Assumptions!$C$56*(1+Assumptions!$C$57)^($A24-Assumptions!$C$55-1))*IF($A24>Assumptions!$C$8,0,1) | I24: =CHOOSE(Assumptions!$C$9,$D24,$E24,$F24,$G24,$H24)
A25: 19 | B25: =Revenue!$I$25 | C25: =Revenue!$I$25-Operating_Expenses!$I$25-Capital_Replacement!$B$25 | D25: =Assumptions!$C$49*(1+Assumptions!$C$50)^($A25-1)*IF($A25>Assumptions!$C$8,0,1) | E25: =Assumptions!$C$51*$B25*IF($A25>Assumptions!$C$8,0,1) | F25: =Assumptions!$C$52*MAX(0,$C25)*IF($A25>Assumptions!$C$8,0,1) | G25: =(Assumptions!$C$53+Assumptions!$C$54*$B25)*IF($A25>Assumptions!$C$8,0,1) | H25: =IF($A25<=Assumptions!$C$55,0,Assumptions!$C$56*(1+Assumptions!$C$57)^($A25-Assumptions!$C$55-1))*IF($A25>Assumptions!$C$8,0,1) | I25: =CHOOSE(Assumptions!$C$9,$D25,$E25,$F25,$G25,$H25)
A26: 20 | B26: =Revenue!$I$26 | C26: =Revenue!$I$26-Operating_Expenses!$I$26-Capital_Replacement!$B$26 | D26: =Assumptions!$C$49*(1+Assumptions!$C$50)^($A26-1)*IF($A26>Assumptions!$C$8,0,1) | E26: =Assumptions!$C$51*$B26*IF($A26>Assumptions!$C$8,0,1) | F26: =Assumptions!$C$52*MAX(0,$C26)*IF($A26>Assumptions!$C$8,0,1) | G26: =(Assumptions!$C$53+Assumptions!$C$54*$B26)*IF($A26>Assumptions!$C$8,0,1) | H26: =IF($A26<=Assumptions!$C$55,0,Assumptions!$C$56*(1+Assumptions!$C$57)^($A26-Assumptions!$C$55-1))*IF($A26>Assumptions!$C$8,0,1) | I26: =CHOOSE(Assumptions!$C$9,$D26,$E26,$F26,$G26,$H26)
A27: 21 | B27: =Revenue!$I$27 | C27: =Revenue!$I$27-Operating_Expenses!$I$27-Capital_Replacement!$B$27 | D27: =Assumptions!$C$49*(1+Assumptions!$C$50)^($A27-1)*IF($A27>Assumptions!$C$8,0,1) | E27: =Assumptions!$C$51*$B27*IF($A27>Assumptions!$C$8,0,1) | F27: =Assumptions!$C$52*MAX(0,$C27)*IF($A27>Assumptions!$C$8,0,1) | G27: =(Assumptions!$C$53+Assumptions!$C$54*$B27)*IF($A27>Assumptions!$C$8,0,1) | H27: =IF($A27<=Assumptions!$C$55,0,Assumptions!$C$56*(1+Assumptions!$C$57)^($A27-Assumptions!$C$55-1))*IF($A27>Assumptions!$C$8,0,1) | I27: =CHOOSE(Assumptions!$C$9,$D27,$E27,$F27,$G27,$H27)
A28: 22 | B28: =Revenue!$I$28 | C28: =Revenue!$I$28-Operating_Expenses!$I$28-Capital_Replacement!$B$28 | D28: =Assumptions!$C$49*(1+Assumptions!$C$50)^($A28-1)*IF($A28>Assumptions!$C$8,0,1) | E28: =Assumptions!$C$51*$B28*IF($A28>Assumptions!$C$8,0,1) | F28: =Assumptions!$C$52*MAX(0,$C28)*IF($A28>Assumptions!$C$8,0,1) | G28: =(Assumptions!$C$53+Assumptions!$C$54*$B28)*IF($A28>Assumptions!$C$8,0,1) | H28: =IF($A28<=Assumptions!$C$55,0,Assumptions!$C$56*(1+Assumptions!$C$57)^($A28-Assumptions!$C$55-1))*IF($A28>Assumptions!$C$8,0,1) | I28: =CHOOSE(Assumptions!$C$9,$D28,$E28,$F28,$G28,$H28)
A29: 23 | B29: =Revenue!$I$29 | C29: =Revenue!$I$29-Operating_Expenses!$I$29-Capital_Replacement!$B$29 | D29: =Assumptions!$C$49*(1+Assumptions!$C$50)^($A29-1)*IF($A29>Assumptions!$C$8,0,1) | E29: =Assumptions!$C$51*$B29*IF($A29>Assumptions!$C$8,0,1) | F29: =Assumptions!$C$52*MAX(0,$C29)*IF($A29>Assumptions!$C$8,0,1) | G29: =(Assumptions!$C$53+Assumptions!$C$54*$B29)*IF($A29>Assumptions!$C$8,0,1) | H29: =IF($A29<=Assumptions!$C$55,0,Assumptions!$C$56*(1+Assumptions!$C$57)^($A29-Assumptions!$C$55-1))*IF($A29>Assumptions!$C$8,0,1) | I29: =CHOOSE(Assumptions!$C$9,$D29,$E29,$F29,$G29,$H29)
A30: 24 | B30: =Revenue!$I$30 | C30: =Revenue!$I$30-Operating_Expenses!$I$30-Capital_Replacement!$B$30 | D30: =Assumptions!$C$49*(1+Assumptions!$C$50)^($A30-1)*IF($A30>Assumptions!$C$8,0,1) | E30: =Assumptions!$C$51*$B30*IF($A30>Assumptions!$C$8,0,1) | F30: =Assumptions!$C$52*MAX(0,$C30)*IF($A30>Assumptions!$C$8,0,1) | G30: =(Assumptions!$C$53+Assumptions!$C$54*$B30)*IF($A30>Assumptions!$C$8,0,1) | H30: =IF($A30<=Assumptions!$C$55,0,Assumptions!$C$56*(1+Assumptions!$C$57)^($A30-Assumptions!$C$55-1))*IF($A30>Assumptions!$C$8,0,1) | I30: =CHOOSE(Assumptions!$C$9,$D30,$E30,$F30,$G30,$H30)
A31: 25 | B31: =Revenue!$I$31 | C31: =Revenue!$I$31-Operating_Expenses!$I$31-Capital_Replacement!$B$31 | D31: =Assumptions!$C$49*(1+Assumptions!$C$50)^($A31-1)*IF($A31>Assumptions!$C$8,0,1) | E31: =Assumptions!$C$51*$B31*IF($A31>Assumptions!$C$8,0,1) | F31: =Assumptions!$C$52*MAX(0,$C31)*IF($A31>Assumptions!$C$8,0,1) | G31: =(Assumptions!$C$53+Assumptions!$C$54*$B31)*IF($A31>Assumptions!$C$8,0,1) | H31: =IF($A31<=Assumptions!$C$55,0,Assumptions!$C$56*(1+Assumptions!$C$57)^($A31-Assumptions!$C$55-1))*IF($A31>Assumptions!$C$8,0,1) | I31: =CHOOSE(Assumptions!$C$9,$D31,$E31,$F31,$G31,$H31)
A32: 26 | B32: =Revenue!$I$32 | C32: =Revenue!$I$32-Operating_Expenses!$I$32-Capital_Replacement!$B$32 | D32: =Assumptions!$C$49*(1+Assumptions!$C$50)^($A32-1)*IF($A32>Assumptions!$C$8,0,1) | E32: =Assumptions!$C$51*$B32*IF($A32>Assumptions!$C$8,0,1) | F32: =Assumptions!$C$52*MAX(0,$C32)*IF($A32>Assumptions!$C$8,0,1) | G32: =(Assumptions!$C$53+Assumptions!$C$54*$B32)*IF($A32>Assumptions!$C$8,0,1) | H32: =IF($A32<=Assumptions!$C$55,0,Assumptions!$C$56*(1+Assumptions!$C$57)^($A32-Assumptions!$C$55-1))*IF($A32>Assumptions!$C$8,0,1) | I32: =CHOOSE(Assumptions!$C$9,$D32,$E32,$F32,$G32,$H32)
A33: 27 | B33: =Revenue!$I$33 | C33: =Revenue!$I$33-Operating_Expenses!$I$33-Capital_Replacement!$B$33 | D33: =Assumptions!$C$49*(1+Assumptions!$C$50)^($A33-1)*IF($A33>Assumptions!$C$8,0,1) | E33: =Assumptions!$C$51*$B33*IF($A33>Assumptions!$C$8,0,1) | F33: =Assumptions!$C$52*MAX(0,$C33)*IF($A33>Assumptions!$C$8,0,1) | G33: =(Assumptions!$C$53+Assumptions!$C$54*$B33)*IF($A33>Assumptions!$C$8,0,1) | H33: =IF($A33<=Assumptions!$C$55,0,Assumptions!$C$56*(1+Assumptions!$C$57)^($A33-Assumptions!$C$55-1))*IF($A33>Assumptions!$C$8,0,1) | I33: =CHOOSE(Assumptions!$C$9,$D33,$E33,$F33,$G33,$H33)
A34: 28 | B34: =Revenue!$I$34 | C34: =Revenue!$I$34-Operating_Expenses!$I$34-Capital_Replacement!$B$34 | D34: =Assumptions!$C$49*(1+Assumptions!$C$50)^($A34-1)*IF($A34>Assumptions!$C$8,0,1) | E34: =Assumptions!$C$51*$B34*IF($A34>Assumptions!$C$8,0,1) | F34: =Assumptions!$C$52*MAX(0,$C34)*IF($A34>Assumptions!$C$8,0,1) | G34: =(Assumptions!$C$53+Assumptions!$C$54*$B34)*IF($A34>Assumptions!$C$8,0,1) | H34: =IF($A34<=Assumptions!$C$55,0,Assumptions!$C$56*(1+Assumptions!$C$57)^($A34-Assumptions!$C$55-1))*IF($A34>Assumptions!$C$8,0,1) | I34: =CHOOSE(Assumptions!$C$9,$D34,$E34,$F34,$G34,$H34)
A35: 29 | B35: =Revenue!$I$35 | C35: =Revenue!$I$35-Operating_Expenses!$I$35-Capital_Replacement!$B$35 | D35: =Assumptions!$C$49*(1+Assumptions!$C$50)^($A35-1)*IF($A35>Assumptions!$C$8,0,1) | E35: =Assumptions!$C$51*$B35*IF($A35>Assumptions!$C$8,0,1) | F35: =Assumptions!$C$52*MAX(0,$C35)*IF($A35>Assumptions!$C$8,0,1) | G35: =(Assumptions!$C$53+Assumptions!$C$54*$B35)*IF($A35>Assumptions!$C$8,0,1) | H35: =IF($A35<=Assumptions!$C$55,0,Assumptions!$C$56*(1+Assumptions!$C$57)^($A35-Assumptions!$C$55-1))*IF($A35>Assumptions!$C$8,0,1) | I35: =CHOOSE(Assumptions!$C$9,$D35,$E35,$F35,$G35,$H35)
A36: 30 | B36: =Revenue!$I$36 | C36: =Revenue!$I$36-Operating_Expenses!$I$36-Capital_Replacement!$B$36 | D36: =Assumptions!$C$49*(1+Assumptions!$C$50)^($A36-1)*IF($A36>Assumptions!$C$8,0,1) | E36: =Assumptions!$C$51*$B36*IF($A36>Assumptions!$C$8,0,1) | F36: =Assumptions!$C$52*MAX(0,$C36)*IF($A36>Assumptions!$C$8,0,1) | G36: =(Assumptions!$C$53+Assumptions!$C$54*$B36)*IF($A36>Assumptions!$C$8,0,1) | H36: =IF($A36<=Assumptions!$C$55,0,Assumptions!$C$56*(1+Assumptions!$C$57)^($A36-Assumptions!$C$55-1))*IF($A36>Assumptions!$C$8,0,1) | I36: =CHOOSE(Assumptions!$C$9,$D36,$E36,$F36,$G36,$H36)
B38: CHECK: SELECTED equals the option chosen by the switch | F38: =IF(SUMPRODUCT(--(ABS($I6:$I36-CHOOSE(Assumptions!$C$9,$D6:$D36,$E6:$E36,$F6:$F36,$G6:$G36,$H6:$H36))>0.5))=0,"PASS","FAIL")

Sheet Annual_Cash_Flow
A1: ANNUAL CASH FLOW — Consolidated
A2: DRAFT FOR DISCUSSION – SUBJECT TO LEGAL, GRANT AND FINANCIAL REVIEW
A3: Gross revenue - opex - capital replacement - Tribal payment = RIVR net. Year 0 = RIVR upfront investment.
A5: Year | B5: Gross Revenue | C5: Operating Expenses | D5: Capital Replacement | E5: Adj. Operating CF | F5: Tribal Payment | G5: RIVR Net Cash Flow | H5: RIVR Cumulative
A6: 0 | B6: 0 | C6: 0 | D6: 0 | E6: 0 | F6: 0 | G6: =-Assumptions!$C$45 | H6: =$G6
A7: 1 | B7: =Revenue!$I$7 | C7: =Operating_Expenses!$I$7 | D7: =Capital_Replacement!$B$7 | E7: =$B7-$C7-$D7 | F7: =Revenue_Share_Options!$I$7 | G7: =$E7-$F7 | H7: =$H6+$G7
A8: 2 | B8: =Revenue!$I$8 | C8: =Operating_Expenses!$I$8 | D8: =Capital_Replacement!$B$8 | E8: =$B8-$C8-$D8 | F8: =Revenue_Share_Options!$I$8 | G8: =$E8-$F8 | H8: =$H7+$G8
A9: 3 | B9: =Revenue!$I$9 | C9: =Operating_Expenses!$I$9 | D9: =Capital_Replacement!$B$9 | E9: =$B9-$C9-$D9 | F9: =Revenue_Share_Options!$I$9 | G9: =$E9-$F9 | H9: =$H8+$G9
A10: 4 | B10: =Revenue!$I$10 | C10: =Operating_Expenses!$I$10 | D10: =Capital_Replacement!$B$10 | E10: =$B10-$C10-$D10 | F10: =Revenue_Share_Options!$I$10 | G10: =$E10-$F10 | H10: =$H9+$G10
A11: 5 | B11: =Revenue!$I$11 | C11: =Operating_Expenses!$I$11 | D11: =Capital_Replacement!$B$11 | E11: =$B11-$C11-$D11 | F11: =Revenue_Share_Options!$I$11 | G11: =$E11-$F11 | H11: =$H10+$G11
A12: 6 | B12: =Revenue!$I$12 | C12: =Operating_Expenses!$I$12 | D12: =Capital_Replacement!$B$12 | E12: =$B12-$C12-$D12 | F12: =Revenue_Share_Options!$I$12 | G12: =$E12-$F12 | H12: =$H11+$G12
A13: 7 | B13: =Revenue!$I$13 | C13: =Operating_Expenses!$I$13 | D13: =Capital_Replacement!$B$13 | E13: =$B13-$C13-$D13 | F13: =Revenue_Share_Options!$I$13 | G13: =$E13-$F13 | H13: =$H12+$G13
A14: 8 | B14: =Revenue!$I$14 | C14: =Operating_Expenses!$I$14 | D14: =Capital_Replacement!$B$14 | E14: =$B14-$C14-$D14 | F14: =Revenue_Share_Options!$I$14 | G14: =$E14-$F14 | H14: =$H13+$G14
A15: 9 | B15: =Revenue!$I$15 | C15: =Operating_Expenses!$I$15 | D15: =Capital_Replacement!$B$15 | E15: =$B15-$C15-$D15 | F15: =Revenue_Share_Options!$I$15 | G15: =$E15-$F15 | H15: =$H14+$G15
A16: 10 | B16: =Revenue!$I$16 | C16: =Operating_Expenses!$I$16 | D16: =Capital_Replacement!$B$16 | E16: =$B16-$C16-$D16 | F16: =Revenue_Share_Options!$I$16 | G16: =$E16-$F16 | H16: =$H15+$G16
A17: 11 | B17: =Revenue!$I$17 | C17: =Operating_Expenses!$I$17 | D17: =Capital_Replacement!$B$17 | E17: =$B17-$C17-$D17 | F17: =Revenue_Share_Options!$I$17 | G17: =$E17-$F17 | H17: =$H16+$G17
A18: 12 | B18: =Revenue!$I$18 | C18: =Operating_Expenses!$I$18 | D18: =Capital_Replacement!$B$18 | E18: =$B18-$C18-$D18 | F18: =Revenue_Share_Options!$I$18 | G18: =$E18-$F18 | H18: =$H17+$G18
A19: 13 | B19: =Revenue!$I$19 | C19: =Operating_Expenses!$I$19 | D19: =Capital_Replacement!$B$19 | E19: =$B19-$C19-$D19 | F19: =Revenue_Share_Options!$I$19 | G19: =$E19-$F19 | H19: =$H18+$G19
A20: 14 | B20: =Revenue!$I$20 | C20: =Operating_Expenses!$I$20 | D20: =Capital_Replacement!$B$20 | E20: =$B20-$C20-$D20 | F20: =Revenue_Share_Options!$I$20 | G20: =$E20-$F20 | H20: =$H19+$G20
A21: 15 | B21: =Revenue!$I$21 | C21: =Operating_Expenses!$I$21 | D21: =Capital_Replacement!$B$21 | E21: =$B21-$C21-$D21 | F21: =Revenue_Share_Options!$I$21 | G21: =$E21-$F21 | H21: =$H20+$G21
A22: 16 | B22: =Revenue!$I$22 | C22: =Operating_Expenses!$I$22 | D22: =Capital_Replacement!$B$22 | E22: =$B22-$C22-$D22 | F22: =Revenue_Share_Options!$I$22 | G22: =$E22-$F22 | H22: =$H21+$G22
A23: 17 | B23: =Revenue!$I$23 | C23: =Operating_Expenses!$I$23 | D23: =Capital_Replacement!$B$23 | E23: =$B23-$C23-$D23 | F23: =Revenue_Share_Options!$I$23 | G23: =$E23-$F23 | H23: =$H22+$G23
A24: 18 | B24: =Revenue!$I$24 | C24: =Operating_Expenses!$I$24 | D24: =Capital_Replacement!$B$24 | E24: =$B24-$C24-$D24 | F24: =Revenue_Share_Options!$I$24 | G24: =$E24-$F24 | H24: =$H23+$G24
A25: 19 | B25: =Revenue!$I$25 | C25: =Operating_Expenses!$I$25 | D25: =Capital_Replacement!$B$25 | E25: =$B25-$C25-$D25 | F25: =Revenue_Share_Options!$I$25 | G25: =$E25-$F25 | H25: =$H24+$G25
A26: 20 | B26: =Revenue!$I$26 | C26: =Operating_Expenses!$I$26 | D26: =Capital_Replacement!$B$26 | E26: =$B26-$C26-$D26 | F26: =Revenue_Share_Options!$I$26 | G26: =$E26-$F26 | H26: =$H25+$G26
A27: 21 | B27: =Revenue!$I$27 | C27: =Operating_Expenses!$I$27 | D27: =Capital_Replacement!$B$27 | E27: =$B27-$C27-$D27 | F27: =Revenue_Share_Options!$I$27 | G27: =$E27-$F27 | H27: =$H26+$G27
A28: 22 | B28: =Revenue!$I$28 | C28: =Operating_Expenses!$I$28 | D28: =Capital_Replacement!$B$28 | E28: =$B28-$C28-$D28 | F28: =Revenue_Share_Options!$I$28 | G28: =$E28-$F28 | H28: =$H27+$G28
A29: 23 | B29: =Revenue!$I$29 | C29: =Operating_Expenses!$I$29 | D29: =Capital_Replacement!$B$29 | E29: =$B29-$C29-$D29 | F29: =Revenue_Share_Options!$I$29 | G29: =$E29-$F29 | H29: =$H28+$G29
A30: 24 | B30: =Revenue!$I$30 | C30: =Operating_Expenses!$I$30 | D30: =Capital_Replacement!$B$30 | E30: =$B30-$C30-$D30 | F30: =Revenue_Share_Options!$I$30 | G30: =$E30-$F30 | H30: =$H29+$G30
A31: 25 | B31: =Revenue!$I$31 | C31: =Operating_Expenses!$I$31 | D31: =Capital_Replacement!$B$31 | E31: =$B31-$C31-$D31 | F31: =Revenue_Share_Options!$I$31 | G31: =$E31-$F31 | H31: =$H30+$G31
A32: 26 | B32: =Revenue!$I$32 | C32: =Operating_Expenses!$I$32 | D32: =Capital_Replacement!$B$32 | E32: =$B32-$C32-$D32 | F32: =Revenue_Share_Options!$I$32 | G32: =$E32-$F32 | H32: =$H31+$G32
A33: 27 | B33: =Revenue!$I$33 | C33: =Operating_Expenses!$I$33 | D33: =Capital_Replacement!$B$33 | E33: =$B33-$C33-$D33 | F33: =Revenue_Share_Options!$I$33 | G33: =$E33-$F33 | H33: =$H32+$G33
A34: 28 | B34: =Revenue!$I$34 | C34: =Operating_Expenses!$I$34 | D34: =Capital_Replacement!$B$34 | E34: =$B34-$C34-$D34 | F34: =Revenue_Share_Options!$I$34 | G34: =$E34-$F34 | H34: =$H33+$G34
A35: 29 | B35: =Revenue!$I$35 | C35: =Operating_Expenses!$I$35 | D35: =Capital_Replacement!$B$35 | E35: =$B35-$C35-$D35 | F35: =Revenue_Share_Options!$I$35 | G35: =$E35-$F35 | H35: =$H34+$G35
A36: 30 | B36: =Revenue!$I$36 | C36: =Operating_Expenses!$I$36 | D36: =Capital_Replacement!$B$36 | E36: =$B36-$C36-$D36 | F36: =Revenue_Share_Options!$I$36 | G36: =$E36-$F36 | H36: =$H35+$G36
B38: CHECK: RIVR net = adj op CF - Tribal payment (identity holds) | F38: =IF(SUMPRODUCT(--(ABS($G7:$G36-($E7:$E36-$F7:$F36))>0.5))=0,"PASS","FAIL")

Sheet RIVR_Tech_Economics
A1: RIVR TECH ECONOMICS — Cash Flow, NPV, IRR
A2: DRAFT FOR DISCUSSION – SUBJECT TO LEGAL, GRANT AND FINANCIAL REVIEW
A3: From the active scenario / term / option. NPV discounts Years 1-30; Year 0 at time zero.
A5: Year | B5: RIVR Net Cash Flow | C5: Cumulative | D5: Payback Helper
A6: 0 | B6: =Annual_Cash_Flow!$G$6 | C6: =0+$B6 | D6: =IF($C6>=0,$A6,9999)
A7: 1 | B7: =Annual_Cash_Flow!$G$7 | C7: =$C6+$B7 | D7: =IF($C7>=0,$A7,9999)
A8: 2 | B8: =Annual_Cash_Flow!$G$8 | C8: =$C7+$B8 | D8: =IF($C8>=0,$A8,9999)
A9: 3 | B9: =Annual_Cash_Flow!$G$9 | C9: =$C8+$B9 | D9: =IF($C9>=0,$A9,9999)
A10: 4 | B10: =Annual_Cash_Flow!$G$10 | C10: =$C9+$B10 | D10: =IF($C10>=0,$A10,9999)
A11: 5 | B11: =Annual_Cash_Flow!$G$11 | C11: =$C10+$B11 | D11: =IF($C11>=0,$A11,9999)
A12: 6 | B12: =Annual_Cash_Flow!$G$12 | C12: =$C11+$B12 | D12: =IF($C12>=0,$A12,9999)
A13: 7 | B13: =Annual_Cash_Flow!$G$13 | C13: =$C12+$B13 | D13: =IF($C13>=0,$A13,9999)
A14: 8 | B14: =Annual_Cash_Flow!$G$14 | C14: =$C13+$B14 | D14: =IF($C14>=0,$A14,9999)
A15: 9 | B15: =Annual_Cash_Flow!$G$15 | C15: =$C14+$B15 | D15: =IF($C15>=0,$A15,9999)
A16: 10 | B16: =Annual_Cash_Flow!$G$16 | C16: =$C15+$B16 | D16: =IF($C16>=0,$A16,9999)
A17: 11 | B17: =Annual_Cash_Flow!$G$17 | C17: =$C16+$B17 | D17: =IF($C17>=0,$A17,9999)
A18: 12 | B18: =Annual_Cash_Flow!$G$18 | C18: =$C17+$B18 | D18: =IF($C18>=0,$A18,9999)
A19: 13 | B19: =Annual_Cash_Flow!$G$19 | C19: =$C18+$B19 | D19: =IF($C19>=0,$A19,9999)
A20: 14 | B20: =Annual_Cash_Flow!$G$20 | C20: =$C19+$B20 | D20: =IF($C20>=0,$A20,9999)
A21: 15 | B21: =Annual_Cash_Flow!$G$21 | C21: =$C20+$B21 | D21: =IF($C21>=0,$A21,9999)
A22: 16 | B22: =Annual_Cash_Flow!$G$22 | C22: =$C21+$B22 | D22: =IF($C22>=0,$A22,9999)
A23: 17 | B23: =Annual_Cash_Flow!$G$23 | C23: =$C22+$B23 | D23: =IF($C23>=0,$A23,9999)
A24: 18 | B24: =Annual_Cash_Flow!$G$24 | C24: =$C23+$B24 | D24: =IF($C24>=0,$A24,9999)
A25: 19 | B25: =Annual_Cash_Flow!$G$25 | C25: =$C24+$B25 | D25: =IF($C25>=0,$A25,9999)
A26: 20 | B26: =Annual_Cash_Flow!$G$26 | C26: =$C25+$B26 | D26: =IF($C26>=0,$A26,9999)
A27: 21 | B27: =Annual_Cash_Flow!$G$27 | C27: =$C26+$B27 | D27: =IF($C27>=0,$A27,9999)
A28: 22 | B28: =Annual_Cash_Flow!$G$28 | C28: =$C27+$B28 | D28: =IF($C28>=0,$A28,9999)
A29: 23 | B29: =Annual_Cash_Flow!$G$29 | C29: =$C28+$B29 | D29: =IF($C29>=0,$A29,9999)
A30: 24 | B30: =Annual_Cash_Flow!$G$30 | C30: =$C29+$B30 | D30: =IF($C30>=0,$A30,9999)
A31: 25 | B31: =Annual_Cash_Flow!$G$31 | C31: =$C30+$B31 | D31: =IF($C31>=0,$A31,9999)
A32: 26 | B32: =Annual_Cash_Flow!$G$32 | C32: =$C31+$B32 | D32: =IF($C32>=0,$A32,9999)
A33: 27 | B33: =Annual_Cash_Flow!$G$33 | C33: =$C32+$B33 | D33: =IF($C33>=0,$A33,9999)
A34: 28 | B34: =Annual_Cash_Flow!$G$34 | C34: =$C33+$B34 | D34: =IF($C34>=0,$A34,9999)
A35: 29 | B35: =Annual_Cash_Flow!$G$35 | C35: =$C34+$B35 | D35: =IF($C35>=0,$A35,9999)
A36: 30 | B36: =Annual_Cash_Flow!$G$36 | C36: =$C35+$B36 | D36: =IF($C36>=0,$A36,9999)
A38: SUMMARY
A39: RIVR NPV (active) | B39: =$B6+NPV(Assumptions!$C$44,$B7:$B36)
A40: RIVR IRR (active) | B40: =IFERROR(IRR($B6:$B36),"n/m")
A41: Payback (year cum. >= 0) | B41: =IF(MIN($D6:$D36)=9999,"beyond horizon",MIN($D6:$D36))

Sheet Tribal_Economics
A1: TRIBAL ECONOMICS — Receipts, NPV
A2: DRAFT FOR DISCUSSION – SUBJECT TO LEGAL, GRANT AND FINANCIAL REVIEW
A3: IRU/revenue-share payment plus reserved-capacity in-kind value. Grant funds the asset (no Tribal cash outlay).
A5: Year | B5: Tribal Payment | C5: Reserved-Capacity Value | D5: Total Tribal Receipts | E5: Cumulative
A6: 0 | B6: =Revenue_Share_Options!$I$6 | C6: 0 | D6: =$B6+$C6 | E6: =0+$D6
A7: 1 | B7: =Revenue_Share_Options!$I$7 | C7: =Assumptions!$C$46*IF($A7>Assumptions!$C$8,0,1)*MIN(1,$A7/Assumptions!$C$31) | D7: =$B7+$C7 | E7: =$E6+$D7
A8: 2 | B8: =Revenue_Share_Options!$I$8 | C8: =Assumptions!$C$46*IF($A8>Assumptions!$C$8,0,1)*MIN(1,$A8/Assumptions!$C$31) | D8: =$B8+$C8 | E8: =$E7+$D8
A9: 3 | B9: =Revenue_Share_Options!$I$9 | C9: =Assumptions!$C$46*IF($A9>Assumptions!$C$8,0,1)*MIN(1,$A9/Assumptions!$C$31) | D9: =$B9+$C9 | E9: =$E8+$D9
A10: 4 | B10: =Revenue_Share_Options!$I$10 | C10: =Assumptions!$C$46*IF($A10>Assumptions!$C$8,0,1)*MIN(1,$A10/Assumptions!$C$31) | D10: =$B10+$C10 | E10: =$E9+$D10
A11: 5 | B11: =Revenue_Share_Options!$I$11 | C11: =Assumptions!$C$46*IF($A11>Assumptions!$C$8,0,1)*MIN(1,$A11/Assumptions!$C$31) | D11: =$B11+$C11 | E11: =$E10+$D11
A12: 6 | B12: =Revenue_Share_Options!$I$12 | C12: =Assumptions!$C$46*IF($A12>Assumptions!$C$8,0,1)*MIN(1,$A12/Assumptions!$C$31) | D12: =$B12+$C12 | E12: =$E11+$D12
A13: 7 | B13: =Revenue_Share_Options!$I$13 | C13: =Assumptions!$C$46*IF($A13>Assumptions!$C$8,0,1)*MIN(1,$A13/Assumptions!$C$31) | D13: =$B13+$C13 | E13: =$E12+$D13
A14: 8 | B14: =Revenue_Share_Options!$I$14 | C14: =Assumptions!$C$46*IF($A14>Assumptions!$C$8,0,1)*MIN(1,$A14/Assumptions!$C$31) | D14: =$B14+$C14 | E14: =$E13+$D14
A15: 9 | B15: =Revenue_Share_Options!$I$15 | C15: =Assumptions!$C$46*IF($A15>Assumptions!$C$8,0,1)*MIN(1,$A15/Assumptions!$C$31) | D15: =$B15+$C15 | E15: =$E14+$D15
A16: 10 | B16: =Revenue_Share_Options!$I$16 | C16: =Assumptions!$C$46*IF($A16>Assumptions!$C$8,0,1)*MIN(1,$A16/Assumptions!$C$31) | D16: =$B16+$C16 | E16: =$E15+$D16
A17: 11 | B17: =Revenue_Share_Options!$I$17 | C17: =Assumptions!$C$46*IF($A17>Assumptions!$C$8,0,1)*MIN(1,$A17/Assumptions!$C$31) | D17: =$B17+$C17 | E17: =$E16+$D17
A18: 12 | B18: =Revenue_Share_Options!$I$18 | C18: =Assumptions!$C$46*IF($A18>Assumptions!$C$8,0,1)*MIN(1,$A18/Assumptions!$C$31) | D18: =$B18+$C18 | E18: =$E17+$D18
A19: 13 | B19: =Revenue_Share_Options!$I$19 | C19: =Assumptions!$C$46*IF($A19>Assumptions!$C$8,0,1)*MIN(1,$A19/Assumptions!$C$31) | D19: =$B19+$C19 | E19: =$E18+$D19
A20: 14 | B20: =Revenue_Share_Options!$I$20 | C20: =Assumptions!$C$46*IF($A20>Assumptions!$C$8,0,1)*MIN(1,$A20/Assumptions!$C$31) | D20: =$B20+$C20 | E20: =$E19+$D20
A21: 15 | B21: =Revenue_Share_Options!$I$21 | C21: =Assumptions!$C$46*IF($A21>Assumptions!$C$8,0,1)*MIN(1,$A21/Assumptions!$C$31) | D21: =$B21+$C21 | E21: =$E20+$D21
A22: 16 | B22: =Revenue_Share_Options!$I$22 | C22: =Assumptions!$C$46*IF($A22>Assumptions!$C$8,0,1)*MIN(1,$A22/Assumptions!$C$31) | D22: =$B22+$C22 | E22: =$E21+$D22
A23: 17 | B23: =Revenue_Share_Options!$I$23 | C23: =Assumptions!$C$46*IF($A23>Assumptions!$C$8,0,1)*MIN(1,$A23/Assumptions!$C$31) | D23: =$B23+$C23 | E23: =$E22+$D23
A24: 18 | B24: =Revenue_Share_Options!$I$24 | C24: =Assumptions!$C$46*IF($A24>Assumptions!$C$8,0,1)*MIN(1,$A24/Assumptions!$C$31) | D24: =$B24+$C24 | E24: =$E23+$D24
A25: 19 | B25: =Revenue_Share_Options!$I$25 | C25: =Assumptions!$C$46*IF($A25>Assumptions!$C$8,0,1)*MIN(1,$A25/Assumptions!$C$31) | D25: =$B25+$C25 | E25: =$E24+$D25
A26: 20 | B26: =Revenue_Share_Options!$I$26 | C26: =Assumptions!$C$46*IF($A26>Assumptions!$C$8,0,1)*MIN(1,$A26/Assumptions!$C$31) | D26: =$B26+$C26 | E26: =$E25+$D26
A27: 21 | B27: =Revenue_Share_Options!$I$27 | C27: =Assumptions!$C$46*IF($A27>Assumptions!$C$8,0,1)*MIN(1,$A27/Assumptions!$C$31) | D27: =$B27+$C27 | E27: =$E26+$D27
A28: 22 | B28: =Revenue_Share_Options!$I$28 | C28: =Assumptions!$C$46*IF($A28>Assumptions!$C$8,0,1)*MIN(1,$A28/Assumptions!$C$31) | D28: =$B28+$C28 | E28: =$E27+$D28
A29: 23 | B29: =Revenue_Share_Options!$I$29 | C29: =Assumptions!$C$46*IF($A29>Assumptions!$C$8,0,1)*MIN(1,$A29/Assumptions!$C$31) | D29: =$B29+$C29 | E29: =$E28+$D29
A30: 24 | B30: =Revenue_Share_Options!$I$30 | C30: =Assumptions!$C$46*IF($A30>Assumptions!$C$8,0,1)*MIN(1,$A30/Assumptions!$C$31) | D30: =$B30+$C30 | E30: =$E29+$D30
A31: 25 | B31: =Revenue_Share_Options!$I$31 | C31: =Assumptions!$C$46*IF($A31>Assumptions!$C$8,0,1)*MIN(1,$A31/Assumptions!$C$31) | D31: =$B31+$C31 | E31: =$E30+$D31
A32: 26 | B32: =Revenue_Share_Options!$I$32 | C32: =Assumptions!$C$46*IF($A32>Assumptions!$C$8,0,1)*MIN(1,$A32/Assumptions!$C$31) | D32: =$B32+$C32 | E32: =$E31+$D32
A33: 27 | B33: =Revenue_Share_Options!$I$33 | C33: =Assumptions!$C$46*IF($A33>Assumptions!$C$8,0,1)*MIN(1,$A33/Assumptions!$C$31) | D33: =$B33+$C33 | E33: =$E32+$D33
A34: 28 | B34: =Revenue_Share_Options!$I$34 | C34: =Assumptions!$C$46*IF($A34>Assumptions!$C$8,0,1)*MIN(1,$A34/Assumptions!$C$31) | D34: =$B34+$C34 | E34: =$E33+$D34
A35: 29 | B35: =Revenue_Share_Options!$I$35 | C35: =Assumptions!$C$46*IF($A35>Assumptions!$C$8,0,1)*MIN(1,$A35/Assumptions!$C$31) | D35: =$B35+$C35 | E35: =$E34+$D35
A36: 30 | B36: =Revenue_Share_Options!$I$36 | C36: =Assumptions!$C$46*IF($A36>Assumptions!$C$8,0,1)*MIN(1,$A36/Assumptions!$C$31) | D36: =$B36+$C36 | E36: =$E35+$D36
A38: Tribal NPV (active) | B38: =NPV(Assumptions!$C$44,$D7:$D36)
A39: Total Tribal receipts (undiscounted) | B39: =$E36

Sheet Consolidated_Project
A1: CONSOLIDATED PROJECT ECONOMICS — Blended
A2: DRAFT FOR DISCUSSION – SUBJECT TO LEGAL, GRANT AND FINANCIAL REVIEW
A3: Total project view. Tribal payment is an internal transfer and nets out. Year 0 = construction + RIVR upfront.
A5: Year | B5: Gross Revenue | C5: Operating Expenses | D5: Capital (constr./replace.) | E5: Project Net Cash Flow | F5: Cumulative
A6: 0 | B6: 0 | C6: 0 | D6: =Construction_Budget!$E$17+Assumptions!$C$45 | E6: =-$D6 | F6: =$E6
A7: 1 | B7: =Revenue!$I$7 | C7: =Operating_Expenses!$I$7 | D7: =Capital_Replacement!$B$7 | E7: =$B7-$C7-$D7 | F7: =$F6+$E7
A8: 2 | B8: =Revenue!$I$8 | C8: =Operating_Expenses!$I$8 | D8: =Capital_Replacement!$B$8 | E8: =$B8-$C8-$D8 | F8: =$F7+$E8
A9: 3 | B9: =Revenue!$I$9 | C9: =Operating_Expenses!$I$9 | D9: =Capital_Replacement!$B$9 | E9: =$B9-$C9-$D9 | F9: =$F8+$E9
A10: 4 | B10: =Revenue!$I$10 | C10: =Operating_Expenses!$I$10 | D10: =Capital_Replacement!$B$10 | E10: =$B10-$C10-$D10 | F10: =$F9+$E10
A11: 5 | B11: =Revenue!$I$11 | C11: =Operating_Expenses!$I$11 | D11: =Capital_Replacement!$B$11 | E11: =$B11-$C11-$D11 | F11: =$F10+$E11
A12: 6 | B12: =Revenue!$I$12 | C12: =Operating_Expenses!$I$12 | D12: =Capital_Replacement!$B$12 | E12: =$B12-$C12-$D12 | F12: =$F11+$E12
A13: 7 | B13: =Revenue!$I$13 | C13: =Operating_Expenses!$I$13 | D13: =Capital_Replacement!$B$13 | E13: =$B13-$C13-$D13 | F13: =$F12+$E13
A14: 8 | B14: =Revenue!$I$14 | C14: =Operating_Expenses!$I$14 | D14: =Capital_Replacement!$B$14 | E14: =$B14-$C14-$D14 | F14: =$F13+$E14
A15: 9 | B15: =Revenue!$I$15 | C15: =Operating_Expenses!$I$15 | D15: =Capital_Replacement!$B$15 | E15: =$B15-$C15-$D15 | F15: =$F14+$E15
A16: 10 | B16: =Revenue!$I$16 | C16: =Operating_Expenses!$I$16 | D16: =Capital_Replacement!$B$16 | E16: =$B16-$C16-$D16 | F16: =$F15+$E16
A17: 11 | B17: =Revenue!$I$17 | C17: =Operating_Expenses!$I$17 | D17: =Capital_Replacement!$B$17 | E17: =$B17-$C17-$D17 | F17: =$F16+$E17
A18: 12 | B18: =Revenue!$I$18 | C18: =Operating_Expenses!$I$18 | D18: =Capital_Replacement!$B$18 | E18: =$B18-$C18-$D18 | F18: =$F17+$E18
A19: 13 | B19: =Revenue!$I$19 | C19: =Operating_Expenses!$I$19 | D19: =Capital_Replacement!$B$19 | E19: =$B19-$C19-$D19 | F19: =$F18+$E19
A20: 14 | B20: =Revenue!$I$20 | C20: =Operating_Expenses!$I$20 | D20: =Capital_Replacement!$B$20 | E20: =$B20-$C20-$D20 | F20: =$F19+$E20
A21: 15 | B21: =Revenue!$I$21 | C21: =Operating_Expenses!$I$21 | D21: =Capital_Replacement!$B$21 | E21: =$B21-$C21-$D21 | F21: =$F20+$E21
A22: 16 | B22: =Revenue!$I$22 | C22: =Operating_Expenses!$I$22 | D22: =Capital_Replacement!$B$22 | E22: =$B22-$C22-$D22 | F22: =$F21+$E22
A23: 17 | B23: =Revenue!$I$23 | C23: =Operating_Expenses!$I$23 | D23: =Capital_Replacement!$B$23 | E23: =$B23-$C23-$D23 | F23: =$F22+$E23
A24: 18 | B24: =Revenue!$I$24 | C24: =Operating_Expenses!$I$24 | D24: =Capital_Replacement!$B$24 | E24: =$B24-$C24-$D24 | F24: =$F23+$E24
A25: 19 | B25: =Revenue!$I$25 | C25: =Operating_Expenses!$I$25 | D25: =Capital_Replacement!$B$25 | E25: =$B25-$C25-$D25 | F25: =$F24+$E25
A26: 20 | B26: =Revenue!$I$26 | C26: =Operating_Expenses!$I$26 | D26: =Capital_Replacement!$B$26 | E26: =$B26-$C26-$D26 | F26: =$F25+$E26
A27: 21 | B27: =Revenue!$I$27 | C27: =Operating_Expenses!$I$27 | D27: =Capital_Replacement!$B$27 | E27: =$B27-$C27-$D27 | F27: =$F26+$E27
A28: 22 | B28: =Revenue!$I$28 | C28: =Operating_Expenses!$I$28 | D28: =Capital_Replacement!$B$28 | E28: =$B28-$C28-$D28 | F28: =$F27+$E28
A29: 23 | B29: =Revenue!$I$29 | C29: =Operating_Expenses!$I$29 | D29: =Capital_Replacement!$B$29 | E29: =$B29-$C29-$D29 | F29: =$F28+$E29
A30: 24 | B30: =Revenue!$I$30 | C30: =Operating_Expenses!$I$30 | D30: =Capital_Replacement!$B$30 | E30: =$B30-$C30-$D30 | F30: =$F29+$E30
A31: 25 | B31: =Revenue!$I$31 | C31: =Operating_Expenses!$I$31 | D31: =Capital_Replacement!$B$31 | E31: =$B31-$C31-$D31 | F31: =$F30+$E31
A32: 26 | B32: =Revenue!$I$32 | C32: =Operating_Expenses!$I$32 | D32: =Capital_Replacement!$B$32 | E32: =$B32-$C32-$D32 | F32: =$F31+$E32
A33: 27 | B33: =Revenue!$I$33 | C33: =Operating_Expenses!$I$33 | D33: =Capital_Replacement!$B$33 | E33: =$B33-$C33-$D33 | F33: =$F32+$E33
A34: 28 | B34: =Revenue!$I$34 | C34: =Operating_Expenses!$I$34 | D34: =Capital_Replacement!$B$34 | E34: =$B34-$C34-$D34 | F34: =$F33+$E34
A35: 29 | B35: =Revenue!$I$35 | C35: =Operating_Expenses!$I$35 | D35: =Capital_Replacement!$B$35 | E35: =$B35-$C35-$D35 | F35: =$F34+$E35
A36: 30 | B36: =Revenue!$I$36 | C36: =Operating_Expenses!$I$36 | D36: =Capital_Replacement!$B$36 | E36: =$B36-$C36-$D36 | F36: =$F35+$E36
A38: Project NPV (active) | B38: =$E6+NPV(Assumptions!$C$44,$E7:$E36)
A39: Project IRR (active) | B39: =IFERROR(IRR($E6:$E36),"n/m")
B41: CHECK: project net = revenue - opex - capital (identity) | F41: =IF(SUMPRODUCT(--(ABS($E7:$E36-($B7:$B36-$C7:$C36-$D7:$D36))>0.5))=0,"PASS","FAIL")

Sheet Case_Engine
A1: CASE ENGINE — Low / Base / High Parallel Cash Flows
A2: DRAFT FOR DISCUSSION – SUBJECT TO LEGAL, GRANT AND FINANCIAL REVIEW
A3: Formula computation blocks used by NPV_IRR and Scenario_Comparison. Each block reads its own Low/Base/High driver column and holds the OPTION switch constant.
B6: LOW CASE
B7: Year | C7: Homes | D7: TakeRate | E7: Res Subs | F7: Bus Subs | G7: Ent Subs | H7: Gross Rev | I7: Opex | J7: Capital | K7: Adj Op CF | L7: Tribal Pmt | M7: RIVR Net | N7: Proj Net
B8: 0 | D8: 0 | E8: 0 | F8: 0 | G8: 0 | H8: 0 | I8: 0 | J8: 0 | K8: 0 | L8: 0 | M8: =-Assumptions!$C$45 | N8: =-((Construction_Budget!$E$15*Assumptions!$C$25)+Assumptions!$C$45)
B9: 1 | C9: =Assumptions!$C$30*MIN(1,$B9/Assumptions!$C$31) | D9: =Assumptions!$C$14*MIN(1,$B9/Assumptions!$C$15) | E9: =$C9*$D9 | F9: =$C9*Assumptions!$C$32 | G9: =Assumptions!$C$20*MIN(1,$B9/Assumptions!$C$15) | H9: =(($E9*Assumptions!$C$16+$F9*Assumptions!$C$17+$G9*Assumptions!$C$18+($E9*Assumptions!$C$33)*Assumptions!$C$19)*12*(1+Assumptions!$C$35)^($B9-1))+(Assumptions!$C$21*MIN(1,$B9/Assumptions!$C$31))+((MAX(0,($E9+$F9+$G9)-(0))+(0)*Assumptions!$C$22)*Assumptions!$C$34) | I9: =($E9+$F9+$G9)*Assumptions!$C$36*(1+Assumptions!$C$24)^($B9-1)+Assumptions!$C$37*(Construction_Budget!$E$15*Assumptions!$C$25)*(1+Assumptions!$C$24)^($B9-1)+Assumptions!$C$38*Assumptions!$C$39*(1+Assumptions!$C$24)^($B9-1)+Assumptions!$C$40*$H9+Assumptions!$C$41*$H9+Assumptions!$C$23*((($E9*Assumptions!$C$16+$F9*Assumptions!$C$17+$G9*Assumptions!$C$18+($E9*Assumptions!$C$33)*Assumptions!$C$19)*12*(1+Assumptions!$C$35)^($B9-1))+(Assumptions!$C$21*MIN(1,$B9/Assumptions!$C$31))) | J9: =(Construction_Budget!$E$8*Assumptions!$C$25)/Assumptions!$C$42*(1+Assumptions!$C$24)^($B9-1) | K9: =$H9-$I9-$J9 | L9: =CHOOSE(Assumptions!$C$9,Assumptions!$C$49*(1+Assumptions!$C$50)^($B9-1),Assumptions!$C$51*$H9,Assumptions!$C$52*MAX(0,$K9),Assumptions!$C$53+Assumptions!$C$54*$H9,IF($B9<=Assumptions!$C$55,0,Assumptions!$C$56*(1+Assumptions!$C$57)^($B9-Assumptions!$C$55-1))) | M9: =$K9-$L9 | N9: =$H9-$I9-$J9
B10: 2 | C10: =Assumptions!$C$30*MIN(1,$B10/Assumptions!$C$31) | D10: =Assumptions!$C$14*MIN(1,$B10/Assumptions!$C$15) | E10: =$C10*$D10 | F10: =$C10*Assumptions!$C$32 | G10: =Assumptions!$C$20*MIN(1,$B10/Assumptions!$C$15) | H10: =(($E10*Assumptions!$C$16+$F10*Assumptions!$C$17+$G10*Assumptions!$C$18+($E10*Assumptions!$C$33)*Assumptions!$C$19)*12*(1+Assumptions!$C$35)^($B10-1))+(Assumptions!$C$21*MIN(1,$B10/Assumptions!$C$31))+((MAX(0,($E10+$F10+$G10)-(($E9+$F9+$G9)))+(($E9+$F9+$G9))*Assumptions!$C$22)*Assumptions!$C$34) | I10: =($E10+$F10+$G10)*Assumptions!$C$36*(1+Assumptions!$C$24)^($B10-1)+Assumptions!$C$37*(Construction_Budget!$E$15*Assumptions!$C$25)*(1+Assumptions!$C$24)^($B10-1)+Assumptions!$C$38*Assumptions!$C$39*(1+Assumptions!$C$24)^($B10-1)+Assumptions!$C$40*$H10+Assumptions!$C$41*$H10+Assumptions!$C$23*((($E10*Assumptions!$C$16+$F10*Assumptions!$C$17+$G10*Assumptions!$C$18+($E10*Assumptions!$C$33)*Assumptions!$C$19)*12*(1+Assumptions!$C$35)^($B10-1))+(Assumptions!$C$21*MIN(1,$B10/Assumptions!$C$31))) | J10: =(Construction_Budget!$E$8*Assumptions!$C$25)/Assumptions!$C$42*(1+Assumptions!$C$24)^($B10-1) | K10: =$H10-$I10-$J10 | L10: =CHOOSE(Assumptions!$C$9,Assumptions!$C$49*(1+Assumptions!$C$50)^($B10-1),Assumptions!$C$51*$H10,Assumptions!$C$52*MAX(0,$K10),Assumptions!$C$53+Assumptions!$C$54*$H10,IF($B10<=Assumptions!$C$55,0,Assumptions!$C$56*(1+Assumptions!$C$57)^($B10-Assumptions!$C$55-1))) | M10: =$K10-$L10 | N10: =$H10-$I10-$J10
B11: 3 | C11: =Assumptions!$C$30*MIN(1,$B11/Assumptions!$C$31) | D11: =Assumptions!$C$14*MIN(1,$B11/Assumptions!$C$15) | E11: =$C11*$D11 | F11: =$C11*Assumptions!$C$32 | G11: =Assumptions!$C$20*MIN(1,$B11/Assumptions!$C$15) | H11: =(($E11*Assumptions!$C$16+$F11*Assumptions!$C$17+$G11*Assumptions!$C$18+($E11*Assumptions!$C$33)*Assumptions!$C$19)*12*(1+Assumptions!$C$35)^($B11-1))+(Assumptions!$C$21*MIN(1,$B11/Assumptions!$C$31))+((MAX(0,($E11+$F11+$G11)-(($E10+$F10+$G10)))+(($E10+$F10+$G10))*Assumptions!$C$22)*Assumptions!$C$34) | I11: =($E11+$F11+$G11)*Assumptions!$C$36*(1+Assumptions!$C$24)^($B11-1)+Assumptions!$C$37*(Construction_Budget!$E$15*Assumptions!$C$25)*(1+Assumptions!$C$24)^($B11-1)+Assumptions!$C$38*Assumptions!$C$39*(1+Assumptions!$C$24)^($B11-1)+Assumptions!$C$40*$H11+Assumptions!$C$41*$H11+Assumptions!$C$23*((($E11*Assumptions!$C$16+$F11*Assumptions!$C$17+$G11*Assumptions!$C$18+($E11*Assumptions!$C$33)*Assumptions!$C$19)*12*(1+Assumptions!$C$35)^($B11-1))+(Assumptions!$C$21*MIN(1,$B11/Assumptions!$C$31))) | J11: =(Construction_Budget!$E$8*Assumptions!$C$25)/Assumptions!$C$42*(1+Assumptions!$C$24)^($B11-1) | K11: =$H11-$I11-$J11 | L11: =CHOOSE(Assumptions!$C$9,Assumptions!$C$49*(1+Assumptions!$C$50)^($B11-1),Assumptions!$C$51*$H11,Assumptions!$C$52*MAX(0,$K11),Assumptions!$C$53+Assumptions!$C$54*$H11,IF($B11<=Assumptions!$C$55,0,Assumptions!$C$56*(1+Assumptions!$C$57)^($B11-Assumptions!$C$55-1))) | M11: =$K11-$L11 | N11: =$H11-$I11-$J11
B12: 4 | C12: =Assumptions!$C$30*MIN(1,$B12/Assumptions!$C$31) | D12: =Assumptions!$C$14*MIN(1,$B12/Assumptions!$C$15) | E12: =$C12*$D12 | F12: =$C12*Assumptions!$C$32 | G12: =Assumptions!$C$20*MIN(1,$B12/Assumptions!$C$15) | H12: =(($E12*Assumptions!$C$16+$F12*Assumptions!$C$17+$G12*Assumptions!$C$18+($E12*Assumptions!$C$33)*Assumptions!$C$19)*12*(1+Assumptions!$C$35)^($B12-1))+(Assumptions!$C$21*MIN(1,$B12/Assumptions!$C$31))+((MAX(0,($E12+$F12+$G12)-(($E11+$F11+$G11)))+(($E11+$F11+$G11))*Assumptions!$C$22)*Assumptions!$C$34) | I12: =($E12+$F12+$G12)*Assumptions!$C$36*(1+Assumptions!$C$24)^($B12-1)+Assumptions!$C$37*(Construction_Budget!$E$15*Assumptions!$C$25)*(1+Assumptions!$C$24)^($B12-1)+Assumptions!$C$38*Assumptions!$C$39*(1+Assumptions!$C$24)^($B12-1)+Assumptions!$C$40*$H12+Assumptions!$C$41*$H12+Assumptions!$C$23*((($E12*Assumptions!$C$16+$F12*Assumptions!$C$17+$G12*Assumptions!$C$18+($E12*Assumptions!$C$33)*Assumptions!$C$19)*12*(1+Assumptions!$C$35)^($B12-1))+(Assumptions!$C$21*MIN(1,$B12/Assumptions!$C$31))) | J12: =(Construction_Budget!$E$8*Assumptions!$C$25)/Assumptions!$C$42*(1+Assumptions!$C$24)^($B12-1) | K12: =$H12-$I12-$J12 | L12: =CHOOSE(Assumptions!$C$9,Assumptions!$C$49*(1+Assumptions!$C$50)^($B12-1),Assumptions!$C$51*$H12,Assumptions!$C$52*MAX(0,$K12),Assumptions!$C$53+Assumptions!$C$54*$H12,IF($B12<=Assumptions!$C$55,0,Assumptions!$C$56*(1+Assumptions!$C$57)^($B12-Assumptions!$C$55-1))) | M12: =$K12-$L12 | N12: =$H12-$I12-$J12
B13: 5 | C13: =Assumptions!$C$30*MIN(1,$B13/Assumptions!$C$31) | D13: =Assumptions!$C$14*MIN(1,$B13/Assumptions!$C$15) | E13: =$C13*$D13 | F13: =$C13*Assumptions!$C$32 | G13: =Assumptions!$C$20*MIN(1,$B13/Assumptions!$C$15) | H13: =(($E13*Assumptions!$C$16+$F13*Assumptions!$C$17+$G13*Assumptions!$C$18+($E13*Assumptions!$C$33)*Assumptions!$C$19)*12*(1+Assumptions!$C$35)^($B13-1))+(Assumptions!$C$21*MIN(1,$B13/Assumptions!$C$31))+((MAX(0,($E13+$F13+$G13)-(($E12+$F12+$G12)))+(($E12+$F12+$G12))*Assumptions!$C$22)*Assumptions!$C$34) | I13: =($E13+$F13+$G13)*Assumptions!$C$36*(1+Assumptions!$C$24)^($B13-1)+Assumptions!$C$37*(Construction_Budget!$E$15*Assumptions!$C$25)*(1+Assumptions!$C$24)^($B13-1)+Assumptions!$C$38*Assumptions!$C$39*(1+Assumptions!$C$24)^($B13-1)+Assumptions!$C$40*$H13+Assumptions!$C$41*$H13+Assumptions!$C$23*((($E13*Assumptions!$C$16+$F13*Assumptions!$C$17+$G13*Assumptions!$C$18+($E13*Assumptions!$C$33)*Assumptions!$C$19)*12*(1+Assumptions!$C$35)^($B13-1))+(Assumptions!$C$21*MIN(1,$B13/Assumptions!$C$31))) | J13: =(Construction_Budget!$E$8*Assumptions!$C$25)/Assumptions!$C$42*(1+Assumptions!$C$24)^($B13-1) | K13: =$H13-$I13-$J13 | L13: =CHOOSE(Assumptions!$C$9,Assumptions!$C$49*(1+Assumptions!$C$50)^($B13-1),Assumptions!$C$51*$H13,Assumptions!$C$52*MAX(0,$K13),Assumptions!$C$53+Assumptions!$C$54*$H13,IF($B13<=Assumptions!$C$55,0,Assumptions!$C$56*(1+Assumptions!$C$57)^($B13-Assumptions!$C$55-1))) | M13: =$K13-$L13 | N13: =$H13-$I13-$J13
B14: 6 | C14: =Assumptions!$C$30*MIN(1,$B14/Assumptions!$C$31) | D14: =Assumptions!$C$14*MIN(1,$B14/Assumptions!$C$15) | E14: =$C14*$D14 | F14: =$C14*Assumptions!$C$32 | G14: =Assumptions!$C$20*MIN(1,$B14/Assumptions!$C$15) | H14: =(($E14*Assumptions!$C$16+$F14*Assumptions!$C$17+$G14*Assumptions!$C$18+($E14*Assumptions!$C$33)*Assumptions!$C$19)*12*(1+Assumptions!$C$35)^($B14-1))+(Assumptions!$C$21*MIN(1,$B14/Assumptions!$C$31))+((MAX(0,($E14+$F14+$G14)-(($E13+$F13+$G13)))+(($E13+$F13+$G13))*Assumptions!$C$22)*Assumptions!$C$34) | I14: =($E14+$F14+$G14)*Assumptions!$C$36*(1+Assumptions!$C$24)^($B14-1)+Assumptions!$C$37*(Construction_Budget!$E$15*Assumptions!$C$25)*(1+Assumptions!$C$24)^($B14-1)+Assumptions!$C$38*Assumptions!$C$39*(1+Assumptions!$C$24)^($B14-1)+Assumptions!$C$40*$H14+Assumptions!$C$41*$H14+Assumptions!$C$23*((($E14*Assumptions!$C$16+$F14*Assumptions!$C$17+$G14*Assumptions!$C$18+($E14*Assumptions!$C$33)*Assumptions!$C$19)*12*(1+Assumptions!$C$35)^($B14-1))+(Assumptions!$C$21*MIN(1,$B14/Assumptions!$C$31))) | J14: =(Construction_Budget!$E$8*Assumptions!$C$25)/Assumptions!$C$42*(1+Assumptions!$C$24)^($B14-1) | K14: =$H14-$I14-$J14 | L14: =CHOOSE(Assumptions!$C$9,Assumptions!$C$49*(1+Assumptions!$C$50)^($B14-1),Assumptions!$C$51*$H14,Assumptions!$C$52*MAX(0,$K14),Assumptions!$C$53+Assumptions!$C$54*$H14,IF($B14<=Assumptions!$C$55,0,Assumptions!$C$56*(1+Assumptions!$C$57)^($B14-Assumptions!$C$55-1))) | M14: =$K14-$L14 | N14: =$H14-$I14-$J14
B15: 7 | C15: =Assumptions!$C$30*MIN(1,$B15/Assumptions!$C$31) | D15: =Assumptions!$C$14*MIN(1,$B15/Assumptions!$C$15) | E15: =$C15*$D15 | F15: =$C15*Assumptions!$C$32 | G15: =Assumptions!$C$20*MIN(1,$B15/Assumptions!$C$15) | H15: =(($E15*Assumptions!$C$16+$F15*Assumptions!$C$17+$G15*Assumptions!$C$18+($E15*Assumptions!$C$33)*Assumptions!$C$19)*12*(1+Assumptions!$C$35)^($B15-1))+(Assumptions!$C$21*MIN(1,$B15/Assumptions!$C$31))+((MAX(0,($E15+$F15+$G15)-(($E14+$F14+$G14)))+(($E14+$F14+$G14))*Assumptions!$C$22)*Assumptions!$C$34) | I15: =($E15+$F15+$G15)*Assumptions!$C$36*(1+Assumptions!$C$24)^($B15-1)+Assumptions!$C$37*(Construction_Budget!$E$15*Assumptions!$C$25)*(1+Assumptions!$C$24)^($B15-1)+Assumptions!$C$38*Assumptions!$C$39*(1+Assumptions!$C$24)^($B15-1)+Assumptions!$C$40*$H15+Assumptions!$C$41*$H15+Assumptions!$C$23*((($E15*Assumptions!$C$16+$F15*Assumptions!$C$17+$G15*Assumptions!$C$18+($E15*Assumptions!$C$33)*Assumptions!$C$19)*12*(1+Assumptions!$C$35)^($B15-1))+(Assumptions!$C$21*MIN(1,$B15/Assumptions!$C$31))) | J15: =(Construction_Budget!$E$8*Assumptions!$C$25)/Assumptions!$C$42*(1+Assumptions!$C$24)^($B15-1) | K15: =$H15-$I15-$J15 | L15: =CHOOSE(Assumptions!$C$9,Assumptions!$C$49*(1+Assumptions!$C$50)^($B15-1),Assumptions!$C$51*$H15,Assumptions!$C$52*MAX(0,$K15),Assumptions!$C$53+Assumptions!$C$54*$H15,IF($B15<=Assumptions!$C$55,0,Assumptions!$C$56*(1+Assumptions!$C$57)^($B15-Assumptions!$C$55-1))) | M15: =$K15-$L15 | N15: =$H15-$I15-$J15
B16: 8 | C16: =Assumptions!$C$30*MIN(1,$B16/Assumptions!$C$31) | D16: =Assumptions!$C$14*MIN(1,$B16/Assumptions!$C$15) | E16: =$C16*$D16 | F16: =$C16*Assumptions!$C$32 | G16: =Assumptions!$C$20*MIN(1,$B16/Assumptions!$C$15) | H16: =(($E16*Assumptions!$C$16+$F16*Assumptions!$C$17+$G16*Assumptions!$C$18+($E16*Assumptions!$C$33)*Assumptions!$C$19)*12*(1+Assumptions!$C$35)^($B16-1))+(Assumptions!$C$21*MIN(1,$B16/Assumptions!$C$31))+((MAX(0,($E16+$F16+$G16)-(($E15+$F15+$G15)))+(($E15+$F15+$G15))*Assumptions!$C$22)*Assumptions!$C$34) | I16: =($E16+$F16+$G16)*Assumptions!$C$36*(1+Assumptions!$C$24)^($B16-1)+Assumptions!$C$37*(Construction_Budget!$E$15*Assumptions!$C$25)*(1+Assumptions!$C$24)^($B16-1)+Assumptions!$C$38*Assumptions!$C$39*(1+Assumptions!$C$24)^($B16-1)+Assumptions!$C$40*$H16+Assumptions!$C$41*$H16+Assumptions!$C$23*((($E16*Assumptions!$C$16+$F16*Assumptions!$C$17+$G16*Assumptions!$C$18+($E16*Assumptions!$C$33)*Assumptions!$C$19)*12*(1+Assumptions!$C$35)^($B16-1))+(Assumptions!$C$21*MIN(1,$B16/Assumptions!$C$31))) | J16: =(Construction_Budget!$E$8*Assumptions!$C$25)/Assumptions!$C$42*(1+Assumptions!$C$24)^($B16-1) | K16: =$H16-$I16-$J16 | L16: =CHOOSE(Assumptions!$C$9,Assumptions!$C$49*(1+Assumptions!$C$50)^($B16-1),Assumptions!$C$51*$H16,Assumptions!$C$52*MAX(0,$K16),Assumptions!$C$53+Assumptions!$C$54*$H16,IF($B16<=Assumptions!$C$55,0,Assumptions!$C$56*(1+Assumptions!$C$57)^($B16-Assumptions!$C$55-1))) | M16: =$K16-$L16 | N16: =$H16-$I16-$J16
B17: 9 | C17: =Assumptions!$C$30*MIN(1,$B17/Assumptions!$C$31) | D17: =Assumptions!$C$14*MIN(1,$B17/Assumptions!$C$15) | E17: =$C17*$D17 | F17: =$C17*Assumptions!$C$32 | G17: =Assumptions!$C$20*MIN(1,$B17/Assumptions!$C$15) | H17: =(($E17*Assumptions!$C$16+$F17*Assumptions!$C$17+$G17*Assumptions!$C$18+($E17*Assumptions!$C$33)*Assumptions!$C$19)*12*(1+Assumptions!$C$35)^($B17-1))+(Assumptions!$C$21*MIN(1,$B17/Assumptions!$C$31))+((MAX(0,($E17+$F17+$G17)-(($E16+$F16+$G16)))+(($E16+$F16+$G16))*Assumptions!$C$22)*Assumptions!$C$34) | I17: =($E17+$F17+$G17)*Assumptions!$C$36*(1+Assumptions!$C$24)^($B17-1)+Assumptions!$C$37*(Construction_Budget!$E$15*Assumptions!$C$25)*(1+Assumptions!$C$24)^($B17-1)+Assumptions!$C$38*Assumptions!$C$39*(1+Assumptions!$C$24)^($B17-1)+Assumptions!$C$40*$H17+Assumptions!$C$41*$H17+Assumptions!$C$23*((($E17*Assumptions!$C$16+$F17*Assumptions!$C$17+$G17*Assumptions!$C$18+($E17*Assumptions!$C$33)*Assumptions!$C$19)*12*(1+Assumptions!$C$35)^($B17-1))+(Assumptions!$C$21*MIN(1,$B17/Assumptions!$C$31))) | J17: =(Construction_Budget!$E$8*Assumptions!$C$25)/Assumptions!$C$42*(1+Assumptions!$C$24)^($B17-1) | K17: =$H17-$I17-$J17 | L17: =CHOOSE(Assumptions!$C$9,Assumptions!$C$49*(1+Assumptions!$C$50)^($B17-1),Assumptions!$C$51*$H17,Assumptions!$C$52*MAX(0,$K17),Assumptions!$C$53+Assumptions!$C$54*$H17,IF($B17<=Assumptions!$C$55,0,Assumptions!$C$56*(1+Assumptions!$C$57)^($B17-Assumptions!$C$55-1))) | M17: =$K17-$L17 | N17: =$H17-$I17-$J17
B18: 10 | C18: =Assumptions!$C$30*MIN(1,$B18/Assumptions!$C$31) | D18: =Assumptions!$C$14*MIN(1,$B18/Assumptions!$C$15) | E18: =$C18*$D18 | F18: =$C18*Assumptions!$C$32 | G18: =Assumptions!$C$20*MIN(1,$B18/Assumptions!$C$15) | H18: =(($E18*Assumptions!$C$16+$F18*Assumptions!$C$17+$G18*Assumptions!$C$18+($E18*Assumptions!$C$33)*Assumptions!$C$19)*12*(1+Assumptions!$C$35)^($B18-1))+(Assumptions!$C$21*MIN(1,$B18/Assumptions!$C$31))+((MAX(0,($E18+$F18+$G18)-(($E17+$F17+$G17)))+(($E17+$F17+$G17))*Assumptions!$C$22)*Assumptions!$C$34) | I18: =($E18+$F18+$G18)*Assumptions!$C$36*(1+Assumptions!$C$24)^($B18-1)+Assumptions!$C$37*(Construction_Budget!$E$15*Assumptions!$C$25)*(1+Assumptions!$C$24)^($B18-1)+Assumptions!$C$38*Assumptions!$C$39*(1+Assumptions!$C$24)^($B18-1)+Assumptions!$C$40*$H18+Assumptions!$C$41*$H18+Assumptions!$C$23*((($E18*Assumptions!$C$16+$F18*Assumptions!$C$17+$G18*Assumptions!$C$18+($E18*Assumptions!$C$33)*Assumptions!$C$19)*12*(1+Assumptions!$C$35)^($B18-1))+(Assumptions!$C$21*MIN(1,$B18/Assumptions!$C$31))) | J18: =(Construction_Budget!$E$8*Assumptions!$C$25)/Assumptions!$C$42*(1+Assumptions!$C$24)^($B18-1) | K18: =$H18-$I18-$J18 | L18: =CHOOSE(Assumptions!$C$9,Assumptions!$C$49*(1+Assumptions!$C$50)^($B18-1),Assumptions!$C$51*$H18,Assumptions!$C$52*MAX(0,$K18),Assumptions!$C$53+Assumptions!$C$54*$H18,IF($B18<=Assumptions!$C$55,0,Assumptions!$C$56*(1+Assumptions!$C$57)^($B18-Assumptions!$C$55-1))) | M18: =$K18-$L18 | N18: =$H18-$I18-$J18
B19: 11 | C19: =Assumptions!$C$30*MIN(1,$B19/Assumptions!$C$31) | D19: =Assumptions!$C$14*MIN(1,$B19/Assumptions!$C$15) | E19: =$C19*$D19 | F19: =$C19*Assumptions!$C$32 | G19: =Assumptions!$C$20*MIN(1,$B19/Assumptions!$C$15) | H19: =(($E19*Assumptions!$C$16+$F19*Assumptions!$C$17+$G19*Assumptions!$C$18+($E19*Assumptions!$C$33)*Assumptions!$C$19)*12*(1+Assumptions!$C$35)^($B19-1))+(Assumptions!$C$21*MIN(1,$B19/Assumptions!$C$31))+((MAX(0,($E19+$F19+$G19)-(($E18+$F18+$G18)))+(($E18+$F18+$G18))*Assumptions!$C$22)*Assumptions!$C$34) | I19: =($E19+$F19+$G19)*Assumptions!$C$36*(1+Assumptions!$C$24)^($B19-1)+Assumptions!$C$37*(Construction_Budget!$E$15*Assumptions!$C$25)*(1+Assumptions!$C$24)^($B19-1)+Assumptions!$C$38*Assumptions!$C$39*(1+Assumptions!$C$24)^($B19-1)+Assumptions!$C$40*$H19+Assumptions!$C$41*$H19+Assumptions!$C$23*((($E19*Assumptions!$C$16+$F19*Assumptions!$C$17+$G19*Assumptions!$C$18+($E19*Assumptions!$C$33)*Assumptions!$C$19)*12*(1+Assumptions!$C$35)^($B19-1))+(Assumptions!$C$21*MIN(1,$B19/Assumptions!$C$31))) | J19: =(Construction_Budget!$E$8*Assumptions!$C$25)/Assumptions!$C$42*(1+Assumptions!$C$24)^($B19-1) | K19: =$H19-$I19-$J19 | L19: =CHOOSE(Assumptions!$C$9,Assumptions!$C$49*(1+Assumptions!$C$50)^($B19-1),Assumptions!$C$51*$H19,Assumptions!$C$52*MAX(0,$K19),Assumptions!$C$53+Assumptions!$C$54*$H19,IF($B19<=Assumptions!$C$55,0,Assumptions!$C$56*(1+Assumptions!$C$57)^($B19-Assumptions!$C$55-1))) | M19: =$K19-$L19 | N19: =$H19-$I19-$J19
B20: 12 | C20: =Assumptions!$C$30*MIN(1,$B20/Assumptions!$C$31) | D20: =Assumptions!$C$14*MIN(1,$B20/Assumptions!$C$15) | E20: =$C20*$D20 | F20: =$C20*Assumptions!$C$32 | G20: =Assumptions!$C$20*MIN(1,$B20/Assumptions!$C$15) | H20: =(($E20*Assumptions!$C$16+$F20*Assumptions!$C$17+$G20*Assumptions!$C$18+($E20*Assumptions!$C$33)*Assumptions!$C$19)*12*(1+Assumptions!$C$35)^($B20-1))+(Assumptions!$C$21*MIN(1,$B20/Assumptions!$C$31))+((MAX(0,($E20+$F20+$G20)-(($E19+$F19+$G19)))+(($E19+$F19+$G19))*Assumptions!$C$22)*Assumptions!$C$34) | I20: =($E20+$F20+$G20)*Assumptions!$C$36*(1+Assumptions!$C$24)^($B20-1)+Assumptions!$C$37*(Construction_Budget!$E$15*Assumptions!$C$25)*(1+Assumptions!$C$24)^($B20-1)+Assumptions!$C$38*Assumptions!$C$39*(1+Assumptions!$C$24)^($B20-1)+Assumptions!$C$40*$H20+Assumptions!$C$41*$H20+Assumptions!$C$23*((($E20*Assumptions!$C$16+$F20*Assumptions!$C$17+$G20*Assumptions!$C$18+($E20*Assumptions!$C$33)*Assumptions!$C$19)*12*(1+Assumptions!$C$35)^($B20-1))+(Assumptions!$C$21*MIN(1,$B20/Assumptions!$C$31))) | J20: =(Construction_Budget!$E$8*Assumptions!$C$25)/Assumptions!$C$42*(1+Assumptions!$C$24)^($B20-1) | K20: =$H20-$I20-$J20 | L20: =CHOOSE(Assumptions!$C$9,Assumptions!$C$49*(1+Assumptions!$C$50)^($B20-1),Assumptions!$C$51*$H20,Assumptions!$C$52*MAX(0,$K20),Assumptions!$C$53+Assumptions!$C$54*$H20,IF($B20<=Assumptions!$C$55,0,Assumptions!$C$56*(1+Assumptions!$C$57)^($B20-Assumptions!$C$55-1))) | M20: =$K20-$L20 | N20: =$H20-$I20-$J20
B21: 13 | C21: =Assumptions!$C$30*MIN(1,$B21/Assumptions!$C$31) | D21: =Assumptions!$C$14*MIN(1,$B21/Assumptions!$C$15) | E21: =$C21*$D21 | F21: =$C21*Assumptions!$C$32 | G21: =Assumptions!$C$20*MIN(1,$B21/Assumptions!$C$15) | H21: =(($E21*Assumptions!$C$16+$F21*Assumptions!$C$17+$G21*Assumptions!$C$18+($E21*Assumptions!$C$33)*Assumptions!$C$19)*12*(1+Assumptions!$C$35)^($B21-1))+(Assumptions!$C$21*MIN(1,$B21/Assumptions!$C$31))+((MAX(0,($E21+$F21+$G21)-(($E20+$F20+$G20)))+(($E20+$F20+$G20))*Assumptions!$C$22)*Assumptions!$C$34) | I21: =($E21+$F21+$G21)*Assumptions!$C$36*(1+Assumptions!$C$24)^($B21-1)+Assumptions!$C$37*(Construction_Budget!$E$15*Assumptions!$C$25)*(1+Assumptions!$C$24)^($B21-1)+Assumptions!$C$38*Assumptions!$C$39*(1+Assumptions!$C$24)^($B21-1)+Assumptions!$C$40*$H21+Assumptions!$C$41*$H21+Assumptions!$C$23*((($E21*Assumptions!$C$16+$F21*Assumptions!$C$17+$G21*Assumptions!$C$18+($E21*Assumptions!$C$33)*Assumptions!$C$19)*12*(1+Assumptions!$C$35)^($B21-1))+(Assumptions!$C$21*MIN(1,$B21/Assumptions!$C$31))) | J21: =(Construction_Budget!$E$8*Assumptions!$C$25)/Assumptions!$C$42*(1+Assumptions!$C$24)^($B21-1) | K21: =$H21-$I21-$J21 | L21: =CHOOSE(Assumptions!$C$9,Assumptions!$C$49*(1+Assumptions!$C$50)^($B21-1),Assumptions!$C$51*$H21,Assumptions!$C$52*MAX(0,$K21),Assumptions!$C$53+Assumptions!$C$54*$H21,IF($B21<=Assumptions!$C$55,0,Assumptions!$C$56*(1+Assumptions!$C$57)^($B21-Assumptions!$C$55-1))) | M21: =$K21-$L21 | N21: =$H21-$I21-$J21
... B38: 30 | C38: =Assumptions!$C$30*MIN(1,$B38/Assumptions!$C$31) | D38: =Assumptions!$C$14*MIN(1,$B38/Assumptions!$C$15) | E38: =$C38*$D38 | F38: =$C38*Assumptions!$C$32 | G38: =Assumptions!$C$20*MIN(1,$B38/Assumptions!$C$15) | H38: =(($E38*Assumptions!$C$16+$F38*Assumptions!$C$17+$G38*Assumptions!$C$18+($E38*Assumptions!$C$33)*Assumptions!$C$19)*12*(1+Assumptions!$C$35)^($B38-1))+(Assumptions!$C$21*MIN(1,$B38/Assumptions!$C$31))+((MAX(0,($E38+$F38+$G38)-(($E37+$F37+$G37)))+(($E37+$F37+$G37))*Assumptions!$C$22)*Assumptions!$C$34) | I38: =($E38+$F38+$G38)*Assumptions!$C$36*(1+Assumptions!$C$24)^($B38-1)+Assumptions!$C$37*(Construction_Budget!$E$15*Assumptions!$C$25)*(1+Assumptions!$C$24)^($B38-1)+Assumptions!$C$38*Assumptions!$C$39*(1+Assumptions!$C$24)^($B38-1)+Assumptions!$C$40*$H38+Assumptions!$C$41*$H38+Assumptions!$C$23*((($E38*Assumptions!$C$16+$F38*Assumptions!$C$17+$G38*Assumptions!$C$18+($E38*Assumptions!$C$33)*Assumptions!$C$19)*12*(1+Assumptions!$C$35)^($B38-1))+(Assumptions!$C$21*MIN(1,$B38/Assumptions!$C$31))) | J38: =(Construction_Budget!$E$8*Assumptions!$C$25)/Assumptions!$C$42*(1+Assumptions!$C$24)^($B38-1) | K38: =$H38-$I38-$J38 | L38: =CHOOSE(Assumptions!$C$9,Assumptions!$C$49*(1+Assumptions!$C$50)^($B38-1),Assumptions!$C$51*$H38,Assumptions!$C$52*MAX(0,$K38),Assumptions!$C$53+Assumptions!$C$54*$H38,IF($B38<=Assumptions!$C$55,0,Assumptions!$C$56*(1+Assumptions!$C$57)^($B38-Assumptions!$C$55-1))) | M38: =$K38-$L38 | N38: =$H38-$I38-$J38
B41: BASE CASE
B42: Year | C42: Homes | D42: TakeRate | E42: Res Subs | F42: Bus Subs | G42: Ent Subs | H42: Gross Rev | I42: Opex | J42: Capital | K42: Adj Op CF | L42: Tribal Pmt | M42: RIVR Net | N42: Proj Net
B43: 0 | D43: 0 | E43: 0 | F43: 0 | G43: 0 | H43: 0 | I43: 0 | J43: 0 | K43: 0 | L43: 0 | M43: =-Assumptions!$C$45 | N43: =-((Construction_Budget!$E$15*Assumptions!$D$25)+Assumptions!$C$45)
B44: 1 | C44: =Assumptions!$C$30*MIN(1,$B44/Assumptions!$C$31) | D44: =Assumptions!$D$14*MIN(1,$B44/Assumptions!$D$15) | E44: =$C44*$D44 | F44: =$C44*Assumptions!$C$32 | G44: =Assumptions!$D$20*MIN(1,$B44/Assumptions!$D$15) | H44: =(($E44*Assumptions!$D$16+$F44*Assumptions!$D$17+$G44*Assumptions!$D$18+($E44*Assumptions!$C$33)*Assumptions!$D$19)*12*(1+Assumptions!$C$35)^($B44-1))+(Assumptions!$D$21*MIN(1,$B44/Assumptions!$C$31))+((MAX(0,($E44+$F44+$G44)-(0))+(0)*Assumptions!$D$22)*Assumptions!$C$34) | I44: =($E44+$F44+$G44)*Assumptions!$C$36*(1+Assumptions!$D$24)^($B44-1)+Assumptions!$C$37*(Construction_Budget!$E$15*Assumptions!$D$25)*(1+Assumptions!$D$24)^($B44-1)+Assumptions!$C$38*Assumptions!$C$39*(1+Assumptions!$D$24)^($B44-1)+Assumptions!$C$40*$H44+Assumptions!$C$41*$H44+Assumptions!$D$23*((($E44*Assumptions!$D$16+$F44*Assumptions!$D$17+$G44*Assumptions!$D$18+($E44*Assumptions!$C$33)*Assumptions!$D$19)*12*(1+Assumptions!$C$35)^($B44-1))+(Assumptions!$D$21*MIN(1,$B44/Assumptions!$C$31))) | J44: =(Construction_Budget!$E$8*Assumptions!$D$25)/Assumptions!$C$42*(1+Assumptions!$D$24)^($B44-1) | K44: =$H44-$I44-$J44 | L44: =CHOOSE(Assumptions!$C$9,Assumptions!$C$49*(1+Assumptions!$C$50)^($B44-1),Assumptions!$C$51*$H44,Assumptions!$C$52*MAX(0,$K44),Assumptions!$C$53+Assumptions!$C$54*$H44,IF($B44<=Assumptions!$C$55,0,Assumptions!$C$56*(1+Assumptions!$C$57)^($B44-Assumptions!$C$55-1))) | M44: =$K44-$L44 | N44: =$H44-$I44-$J44
B45: 2 | C45: =Assumptions!$C$30*MIN(1,$B45/Assumptions!$C$31) | D45: =Assumptions!$D$14*MIN(1,$B45/Assumptions!$D$15) | E45: =$C45*$D45 | F45: =$C45*Assumptions!$C$32 | G45: =Assumptions!$D$20*MIN(1,$B45/Assumptions!$D$15) | H45: =(($E45*Assumptions!$D$16+$F45*Assumptions!$D$17+$G45*Assumptions!$D$18+($E45*Assumptions!$C$33)*Assumptions!$D$19)*12*(1+Assumptions!$C$35)^($B45-1))+(Assumptions!$D$21*MIN(1,$B45/Assumptions!$C$31))+((MAX(0,($E45+$F45+$G45)-(($E44+$F44+$G44)))+(($E44+$F44+$G44))*Assumptions!$D$22)*Assumptions!$C$34) | I45: =($E45+$F45+$G45)*Assumptions!$C$36*(1+Assumptions!$D$24)^($B45-1)+Assumptions!$C$37*(Construction_Budget!$E$15*Assumptions!$D$25)*(1+Assumptions!$D$24)^($B45-1)+Assumptions!$C$38*Assumptions!$C$39*(1+Assumptions!$D$24)^($B45-1)+Assumptions!$C$40*$H45+Assumptions!$C$41*$H45+Assumptions!$D$23*((($E45*Assumptions!$D$16+$F45*Assumptions!$D$17+$G45*Assumptions!$D$18+($E45*Assumptions!$C$33)*Assumptions!$D$19)*12*(1+Assumptions!$C$35)^($B45-1))+(Assumptions!$D$21*MIN(1,$B45/Assumptions!$C$31))) | J45: =(Construction_Budget!$E$8*Assumptions!$D$25)/Assumptions!$C$42*(1+Assumptions!$D$24)^($B45-1) | K45: =$H45-$I45-$J45 | L45: =CHOOSE(Assumptions!$C$9,Assumptions!$C$49*(1+Assumptions!$C$50)^($B45-1),Assumptions!$C$51*$H45,Assumptions!$C$52*MAX(0,$K45),Assumptions!$C$53+Assumptions!$C$54*$H45,IF($B45<=Assumptions!$C$55,0,Assumptions!$C$56*(1+Assumptions!$C$57)^($B45-Assumptions!$C$55-1))) | M45: =$K45-$L45 | N45: =$H45-$I45-$J45
B46: 3 | C46: =Assumptions!$C$30*MIN(1,$B46/Assumptions!$C$31) | D46: =Assumptions!$D$14*MIN(1,$B46/Assumptions!$D$15) | E46: =$C46*$D46 | F46: =$C46*Assumptions!$C$32 | G46: =Assumptions!$D$20*MIN(1,$B46/Assumptions!$D$15) | H46: =(($E46*Assumptions!$D$16+$F46*Assumptions!$D$17+$G46*Assumptions!$D$18+($E46*Assumptions!$C$33)*Assumptions!$D$19)*12*(1+Assumptions!$C$35)^($B46-1))+(Assumptions!$D$21*MIN(1,$B46/Assumptions!$C$31))+((MAX(0,($E46+$F46+$G46)-(($E45+$F45+$G45)))+(($E45+$F45+$G45))*Assumptions!$D$22)*Assumptions!$C$34) | I46: =($E46+$F46+$G46)*Assumptions!$C$36*(1+Assumptions!$D$24)^($B46-1)+Assumptions!$C$37*(Construction_Budget!$E$15*Assumptions!$D$25)*(1+Assumptions!$D$24)^($B46-1)+Assumptions!$C$38*Assumptions!$C$39*(1+Assumptions!$D$24)^($B46-1)+Assumptions!$C$40*$H46+Assumptions!$C$41*$H46+Assumptions!$D$23*((($E46*Assumptions!$D$16+$F46*Assumptions!$D$17+$G46*Assumptions!$D$18+($E46*Assumptions!$C$33)*Assumptions!$D$19)*12*(1+Assumptions!$C$35)^($B46-1))+(Assumptions!$D$21*MIN(1,$B46/Assumptions!$C$31))) | J46: =(Construction_Budget!$E$8*Assumptions!$D$25)/Assumptions!$C$42*(1+Assumptions!$D$24)^($B46-1) | K46: =$H46-$I46-$J46 | L46: =CHOOSE(Assumptions!$C$9,Assumptions!$C$49*(1+Assumptions!$C$50)^($B46-1),Assumptions!$C$51*$H46,Assumptions!$C$52*MAX(0,$K46),Assumptions!$C$53+Assumptions!$C$54*$H46,IF($B46<=Assumptions!$C$55,0,Assumptions!$C$56*(1+Assumptions!$C$57)^($B46-Assumptions!$C$55-1))) | M46: =$K46-$L46 | N46: =$H46-$I46-$J46
B47: 4 | C47: =Assumptions!$C$30*MIN(1,$B47/Assumptions!$C$31) | D47: =Assumptions!$D$14*MIN(1,$B47/Assumptions!$D$15) | E47: =$C47*$D47 | F47: =$C47*Assumptions!$C$32 | G47: =Assumptions!$D$20*MIN(1,$B47/Assumptions!$D$15) | H47: =(($E47*Assumptions!$D$16+$F47*Assumptions!$D$17+$G47*Assumptions!$D$18+($E47*Assumptions!$C$33)*Assumptions!$D$19)*12*(1+Assumptions!$C$35)^($B47-1))+(Assumptions!$D$21*MIN(1,$B47/Assumptions!$C$31))+((MAX(0,($E47+$F47+$G47)-(($E46+$F46+$G46)))+(($E46+$F46+$G46))*Assumptions!$D$22)*Assumptions!$C$34) | I47: =($E47+$F47+$G47)*Assumptions!$C$36*(1+Assumptions!$D$24)^($B47-1)+Assumptions!$C$37*(Construction_Budget!$E$15*Assumptions!$D$25)*(1+Assumptions!$D$24)^($B47-1)+Assumptions!$C$38*Assumptions!$C$39*(1+Assumptions!$D$24)^($B47-1)+Assumptions!$C$40*$H47+Assumptions!$C$41*$H47+Assumptions!$D$23*((($E47*Assumptions!$D$16+$F47*Assumptions!$D$17+$G47*Assumptions!$D$18+($E47*Assumptions!$C$33)*Assumptions!$D$19)*12*(1+Assumptions!$C$35)^($B47-1))+(Assumptions!$D$21*MIN(1,$B47/Assumptions!$C$31))) | J47: =(Construction_Budget!$E$8*Assumptions!$D$25)/Assumptions!$C$42*(1+Assumptions!$D$24)^($B47-1) | K47: =$H47-$I47-$J47 | L47: =CHOOSE(Assumptions!$C$9,Assumptions!$C$49*(1+Assumptions!$C$50)^($B47-1),Assumptions!$C$51*$H47,Assumptions!$C$52*MAX(0,$K47),Assumptions!$C$53+Assumptions!$C$54*$H47,IF($B47<=Assumptions!$C$55,0,Assumptions!$C$56*(1+Assumptions!$C$57)^($B47-Assumptions!$C$55-1))) | M47: =$K47-$L47 | N47: =$H47-$I47-$J47
B48: 5 | C48: =Assumptions!$C$30*MIN(1,$B48/Assumptions!$C$31) | D48: =Assumptions!$D$14*MIN(1,$B48/Assumptions!$D$15) | E48: =$C48*$D48 | F48: =$C48*Assumptions!$C$32 | G48: =Assumptions!$D$20*MIN(1,$B48/Assumptions!$D$15) | H48: =(($E48*Assumptions!$D$16+$F48*Assumptions!$D$17+$G48*Assumptions!$D$18+($E48*Assumptions!$C$33)*Assumptions!$D$19)*12*(1+Assumptions!$C$35)^($B48-1))+(Assumptions!$D$21*MIN(1,$B48/Assumptions!$C$31))+((MAX(0,($E48+$F48+$G48)-(($E47+$F47+$G47)))+(($E47+$F47+$G47))*Assumptions!$D$22)*Assumptions!$C$34) | I48: =($E48+$F48+$G48)*Assumptions!$C$36*(1+Assumptions!$D$24)^($B48-1)+Assumptions!$C$37*(Construction_Budget!$E$15*Assumptions!$D$25)*(1+Assumptions!$D$24)^($B48-1)+Assumptions!$C$38*Assumptions!$C$39*(1+Assumptions!$D$24)^($B48-1)+Assumptions!$C$40*$H48+Assumptions!$C$41*$H48+Assumptions!$D$23*((($E48*Assumptions!$D$16+$F48*Assumptions!$D$17+$G48*Assumptions!$D$18+($E48*Assumptions!$C$33)*Assumptions!$D$19)*12*(1+Assumptions!$C$35)^($B48-1))+(Assumptions!$D$21*MIN(1,$B48/Assumptions!$C$31))) | J48: =(Construction_Budget!$E$8*Assumptions!$D$25)/Assumptions!$C$42*(1+Assumptions!$D$24)^($B48-1) | K48: =$H48-$I48-$J48 | L48: =CHOOSE(Assumptions!$C$9,Assumptions!$C$49*(1+Assumptions!$C$50)^($B48-1),Assumptions!$C$51*$H48,Assumptions!$C$52*MAX(0,$K48),Assumptions!$C$53+Assumptions!$C$54*$H48,IF($B48<=Assumptions!$C$55,0,Assumptions!$C$56*(1+Assumptions!$C$57)^($B48-Assumptions!$C$55-1))) | M48: =$K48-$L48 | N48: =$H48-$I48-$J48
B49: 6 | C49: =Assumptions!$C$30*MIN(1,$B49/Assumptions!$C$31) | D49: =Assumptions!$D$14*MIN(1,$B49/Assumptions!$D$15) | E49: =$C49*$D49 | F49: =$C49*Assumptions!$C$32 | G49: =Assumptions!$D$20*MIN(1,$B49/Assumptions!$D$15) | H49: =(($E49*Assumptions!$D$16+$F49*Assumptions!$D$17+$G49*Assumptions!$D$18+($E49*Assumptions!$C$33)*Assumptions!$D$19)*12*(1+Assumptions!$C$35)^($B49-1))+(Assumptions!$D$21*MIN(1,$B49/Assumptions!$C$31))+((MAX(0,($E49+$F49+$G49)-(($E48+$F48+$G48)))+(($E48+$F48+$G48))*Assumptions!$D$22)*Assumptions!$C$34) | I49: =($E49+$F49+$G49)*Assumptions!$C$36*(1+Assumptions!$D$24)^($B49-1)+Assumptions!$C$37*(Construction_Budget!$E$15*Assumptions!$D$25)*(1+Assumptions!$D$24)^($B49-1)+Assumptions!$C$38*Assumptions!$C$39*(1+Assumptions!$D$24)^($B49-1)+Assumptions!$C$40*$H49+Assumptions!$C$41*$H49+Assumptions!$D$23*((($E49*Assumptions!$D$16+$F49*Assumptions!$D$17+$G49*Assumptions!$D$18+($E49*Assumptions!$C$33)*Assumptions!$D$19)*12*(1+Assumptions!$C$35)^($B49-1))+(Assumptions!$D$21*MIN(1,$B49/Assumptions!$C$31))) | J49: =(Construction_Budget!$E$8*Assumptions!$D$25)/Assumptions!$C$42*(1+Assumptions!$D$24)^($B49-1) | K49: =$H49-$I49-$J49 | L49: =CHOOSE(Assumptions!$C$9,Assumptions!$C$49*(1+Assumptions!$C$50)^($B49-1),Assumptions!$C$51*$H49,Assumptions!$C$52*MAX(0,$K49),Assumptions!$C$53+Assumptions!$C$54*$H49,IF($B49<=Assumptions!$C$55,0,Assumptions!$C$56*(1+Assumptions!$C$57)^($B49-Assumptions!$C$55-1))) | M49: =$K49-$L49 | N49: =$H49-$I49-$J49
B50: 7 | C50: =Assumptions!$C$30*MIN(1,$B50/Assumptions!$C$31) | D50: =Assumptions!$D$14*MIN(1,$B50/Assumptions!$D$15) | E50: =$C50*$D50 | F50: =$C50*Assumptions!$C$32 | G50: =Assumptions!$D$20*MIN(1,$B50/Assumptions!$D$15) | H50: =(($E50*Assumptions!$D$16+$F50*Assumptions!$D$17+$G50*Assumptions!$D$18+($E50*Assumptions!$C$33)*Assumptions!$D$19)*12*(1+Assumptions!$C$35)^($B50-1))+(Assumptions!$D$21*MIN(1,$B50/Assumptions!$C$31))+((MAX(0,($E50+$F50+$G50)-(($E49+$F49+$G49)))+(($E49+$F49+$G49))*Assumptions!$D$22)*Assumptions!$C$34) | I50: =($E50+$F50+$G50)*Assumptions!$C$36*(1+Assumptions!$D$24)^($B50-1)+Assumptions!$C$37*(Construction_Budget!$E$15*Assumptions!$D$25)*(1+Assumptions!$D$24)^($B50-1)+Assumptions!$C$38*Assumptions!$C$39*(1+Assumptions!$D$24)^($B50-1)+Assumptions!$C$40*$H50+Assumptions!$C$41*$H50+Assumptions!$D$23*((($E50*Assumptions!$D$16+$F50*Assumptions!$D$17+$G50*Assumptions!$D$18+($E50*Assumptions!$C$33)*Assumptions!$D$19)*12*(1+Assumptions!$C$35)^($B50-1))+(Assumptions!$D$21*MIN(1,$B50/Assumptions!$C$31))) | J50: =(Construction_Budget!$E$8*Assumptions!$D$25)/Assumptions!$C$42*(1+Assumptions!$D$24)^($B50-1) | K50: =$H50-$I50-$J50 | L50: =CHOOSE(Assumptions!$C$9,Assumptions!$C$49*(1+Assumptions!$C$50)^($B50-1),Assumptions!$C$51*$H50,Assumptions!$C$52*MAX(0,$K50),Assumptions!$C$53+Assumptions!$C$54*$H50,IF($B50<=Assumptions!$C$55,0,Assumptions!$C$56*(1+Assumptions!$C$57)^($B50-Assumptions!$C$55-1))) | M50: =$K50-$L50 | N50: =$H50-$I50-$J50
B51: 8 | C51: =Assumptions!$C$30*MIN(1,$B51/Assumptions!$C$31) | D51: =Assumptions!$D$14*MIN(1,$B51/Assumptions!$D$15) | E51: =$C51*$D51 | F51: =$C51*Assumptions!$C$32 | G51: =Assumptions!$D$20*MIN(1,$B51/Assumptions!$D$15) | H51: =(($E51*Assumptions!$D$16+$F51*Assumptions!$D$17+$G51*Assumptions!$D$18+($E51*Assumptions!$C$33)*Assumptions!$D$19)*12*(1+Assumptions!$C$35)^($B51-1))+(Assumptions!$D$21*MIN(1,$B51/Assumptions!$C$31))+((MAX(0,($E51+$F51+$G51)-(($E50+$F50+$G50)))+(($E50+$F50+$G50))*Assumptions!$D$22)*Assumptions!$C$34) | I51: =($E51+$F51+$G51)*Assumptions!$C$36*(1+Assumptions!$D$24)^($B51-1)+Assumptions!$C$37*(Construction_Budget!$E$15*Assumptions!$D$25)*(1+Assumptions!$D$24)^($B51-1)+Assumptions!$C$38*Assumptions!$C$39*(1+Assumptions!$D$24)^($B51-1)+Assumptions!$C$40*$H51+Assumptions!$C$41*$H51+Assumptions!$D$23*((($E51*Assumptions!$D$16+$F51*Assumptions!$D$17+$G51*Assumptions!$D$18+($E51*Assumptions!$C$33)*Assumptions!$D$19)*12*(1+Assumptions!$C$35)^($B51-1))+(Assumptions!$D$21*MIN(1,$B51/Assumptions!$C$31))) | J51: =(Construction_Budget!$E$8*Assumptions!$D$25)/Assumptions!$C$42*(1+Assumptions!$D$24)^($B51-1) | K51: =$H51-$I51-$J51 | L51: =CHOOSE(Assumptions!$C$9,Assumptions!$C$49*(1+Assumptions!$C$50)^($B51-1),Assumptions!$C$51*$H51,Assumptions!$C$52*MAX(0,$K51),Assumptions!$C$53+Assumptions!$C$54*$H51,IF($B51<=Assumptions!$C$55,0,Assumptions!$C$56*(1+Assumptions!$C$57)^($B51-Assumptions!$C$55-1))) | M51: =$K51-$L51 | N51: =$H51-$I51-$J51
B52: 9 | C52: =Assumptions!$C$30*MIN(1,$B52/Assumptions!$C$31) | D52: =Assumptions!$D$14*MIN(1,$B52/Assumptions!$D$15) | E52: =$C52*$D52 | F52: =$C52*Assumptions!$C$32 | G52: =Assumptions!$D$20*MIN(1,$B52/Assumptions!$D$15) | H52: =(($E52*Assumptions!$D$16+$F52*Assumptions!$D$17+$G52*Assumptions!$D$18+($E52*Assumptions!$C$33)*Assumptions!$D$19)*12*(1+Assumptions!$C$35)^($B52-1))+(Assumptions!$D$21*MIN(1,$B52/Assumptions!$C$31))+((MAX(0,($E52+$F52+$G52)-(($E51+$F51+$G51)))+(($E51+$F51+$G51))*Assumptions!$D$22)*Assumptions!$C$34) | I52: =($E52+$F52+$G52)*Assumptions!$C$36*(1+Assumptions!$D$24)^($B52-1)+Assumptions!$C$37*(Construction_Budget!$E$15*Assumptions!$D$25)*(1+Assumptions!$D$24)^($B52-1)+Assumptions!$C$38*Assumptions!$C$39*(1+Assumptions!$D$24)^($B52-1)+Assumptions!$C$40*$H52+Assumptions!$C$41*$H52+Assumptions!$D$23*((($E52*Assumptions!$D$16+$F52*Assumptions!$D$17+$G52*Assumptions!$D$18+($E52*Assumptions!$C$33)*Assumptions!$D$19)*12*(1+Assumptions!$C$35)^($B52-1))+(Assumptions!$D$21*MIN(1,$B52/Assumptions!$C$31))) | J52: =(Construction_Budget!$E$8*Assumptions!$D$25)/Assumptions!$C$42*(1+Assumptions!$D$24)^($B52-1) | K52: =$H52-$I52-$J52 | L52: =CHOOSE(Assumptions!$C$9,Assumptions!$C$49*(1+Assumptions!$C$50)^($B52-1),Assumptions!$C$51*$H52,Assumptions!$C$52*MAX(0,$K52),Assumptions!$C$53+Assumptions!$C$54*$H52,IF($B52<=Assumptions!$C$55,0,Assumptions!$C$56*(1+Assumptions!$C$57)^($B52-Assumptions!$C$55-1))) | M52: =$K52-$L52 | N52: =$H52-$I52-$J52
B53: 10 | C53: =Assumptions!$C$30*MIN(1,$B53/Assumptions!$C$31) | D53: =Assumptions!$D$14*MIN(1,$B53/Assumptions!$D$15) | E53: =$C53*$D53 | F53: =$C53*Assumptions!$C$32 | G53: =Assumptions!$D$20*MIN(1,$B53/Assumptions!$D$15) | H53: =(($E53*Assumptions!$D$16+$F53*Assumptions!$D$17+$G53*Assumptions!$D$18+($E53*Assumptions!$C$33)*Assumptions!$D$19)*12*(1+Assumptions!$C$35)^($B53-1))+(Assumptions!$D$21*MIN(1,$B53/Assumptions!$C$31))+((MAX(0,($E53+$F53+$G53)-(($E52+$F52+$G52)))+(($E52+$F52+$G52))*Assumptions!$D$22)*Assumptions!$C$34) | I53: =($E53+$F53+$G53)*Assumptions!$C$36*(1+Assumptions!$D$24)^($B53-1)+Assumptions!$C$37*(Construction_Budget!$E$15*Assumptions!$D$25)*(1+Assumptions!$D$24)^($B53-1)+Assumptions!$C$38*Assumptions!$C$39*(1+Assumptions!$D$24)^($B53-1)+Assumptions!$C$40*$H53+Assumptions!$C$41*$H53+Assumptions!$D$23*((($E53*Assumptions!$D$16+$F53*Assumptions!$D$17+$G53*Assumptions!$D$18+($E53*Assumptions!$C$33)*Assumptions!$D$19)*12*(1+Assumptions!$C$35)^($B53-1))+(Assumptions!$D$21*MIN(1,$B53/Assumptions!$C$31))) | J53: =(Construction_Budget!$E$8*Assumptions!$D$25)/Assumptions!$C$42*(1+Assumptions!$D$24)^($B53-1) | K53: =$H53-$I53-$J53 | L53: =CHOOSE(Assumptions!$C$9,Assumptions!$C$49*(1+Assumptions!$C$50)^($B53-1),Assumptions!$C$51*$H53,Assumptions!$C$52*MAX(0,$K53),Assumptions!$C$53+Assumptions!$C$54*$H53,IF($B53<=Assumptions!$C$55,0,Assumptions!$C$56*(1+Assumptions!$C$57)^($B53-Assumptions!$C$55-1))) | M53: =$K53-$L53 | N53: =$H53-$I53-$J53
B54: 11 | C54: =Assumptions!$C$30*MIN(1,$B54/Assumptions!$C$31) | D54: =Assumptions!$D$14*MIN(1,$B54/Assumptions!$D$15) | E54: =$C54*$D54 | F54: =$C54*Assumptions!$C$32 | G54: =Assumptions!$D$20*MIN(1,$B54/Assumptions!$D$15) | H54: =(($E54*Assumptions!$D$16+$F54*Assumptions!$D$17+$G54*Assumptions!$D$18+($E54*Assumptions!$C$33)*Assumptions!$D$19)*12*(1+Assumptions!$C$35)^($B54-1))+(Assumptions!$D$21*MIN(1,$B54/Assumptions!$C$31))+((MAX(0,($E54+$F54+$G54)-(($E53+$F53+$G53)))+(($E53+$F53+$G53))*Assumptions!$D$22)*Assumptions!$C$34) | I54: =($E54+$F54+$G54)*Assumptions!$C$36*(1+Assumptions!$D$24)^($B54-1)+Assumptions!$C$37*(Construction_Budget!$E$15*Assumptions!$D$25)*(1+Assumptions!$D$24)^($B54-1)+Assumptions!$C$38*Assumptions!$C$39*(1+Assumptions!$D$24)^($B54-1)+Assumptions!$C$40*$H54+Assumptions!$C$41*$H54+Assumptions!$D$23*((($E54*Assumptions!$D$16+$F54*Assumptions!$D$17+$G54*Assumptions!$D$18+($E54*Assumptions!$C$33)*Assumptions!$D$19)*12*(1+Assumptions!$C$35)^($B54-1))+(Assumptions!$D$21*MIN(1,$B54/Assumptions!$C$31))) | J54: =(Construction_Budget!$E$8*Assumptions!$D$25)/Assumptions!$C$42*(1+Assumptions!$D$24)^($B54-1) | K54: =$H54-$I54-$J54 | L54: =CHOOSE(Assumptions!$C$9,Assumptions!$C$49*(1+Assumptions!$C$50)^($B54-1),Assumptions!$C$51*$H54,Assumptions!$C$52*MAX(0,$K54),Assumptions!$C$53+Assumptions!$C$54*$H54,IF($B54<=Assumptions!$C$55,0,Assumptions!$C$56*(1+Assumptions!$C$57)^($B54-Assumptions!$C$55-1))) | M54: =$K54-$L54 | N54: =$H54-$I54-$J54
B55: 12 | C55: =Assumptions!$C$30*MIN(1,$B55/Assumptions!$C$31) | D55: =Assumptions!$D$14*MIN(1,$B55/Assumptions!$D$15) | E55: =$C55*$D55 | F55: =$C55*Assumptions!$C$32 | G55: =Assumptions!$D$20*MIN(1,$B55/Assumptions!$D$15) | H55: =(($E55*Assumptions!$D$16+$F55*Assumptions!$D$17+$G55*Assumptions!$D$18+($E55*Assumptions!$C$33)*Assumptions!$D$19)*12*(1+Assumptions!$C$35)^($B55-1))+(Assumptions!$D$21*MIN(1,$B55/Assumptions!$C$31))+((MAX(0,($E55+$F55+$G55)-(($E54+$F54+$G54)))+(($E54+$F54+$G54))*Assumptions!$D$22)*Assumptions!$C$34) | I55: =($E55+$F55+$G55)*Assumptions!$C$36*(1+Assumptions!$D$24)^($B55-1)+Assumptions!$C$37*(Construction_Budget!$E$15*Assumptions!$D$25)*(1+Assumptions!$D$24)^($B55-1)+Assumptions!$C$38*Assumptions!$C$39*(1+Assumptions!$D$24)^($B55-1)+Assumptions!$C$40*$H55+Assumptions!$C$41*$H55+Assumptions!$D$23*((($E55*Assumptions!$D$16+$F55*Assumptions!$D$17+$G55*Assumptions!$D$18+($E55*Assumptions!$C$33)*Assumptions!$D$19)*12*(1+Assumptions!$C$35)^($B55-1))+(Assumptions!$D$21*MIN(1,$B55/Assumptions!$C$31))) | J55: =(Construction_Budget!$E$8*Assumptions!$D$25)/Assumptions!$C$42*(1+Assumptions!$D$24)^($B55-1) | K55: =$H55-$I55-$J55 | L55: =CHOOSE(Assumptions!$C$9,Assumptions!$C$49*(1+Assumptions!$C$50)^($B55-1),Assumptions!$C$51*$H55,Assumptions!$C$52*MAX(0,$K55),Assumptions!$C$53+Assumptions!$C$54*$H55,IF($B55<=Assumptions!$C$55,0,Assumptions!$C$56*(1+Assumptions!$C$57)^($B55-Assumptions!$C$55-1))) | M55: =$K55-$L55 | N55: =$H55-$I55-$J55
B56: 13 | C56: =Assumptions!$C$30*MIN(1,$B56/Assumptions!$C$31) | D56: =Assumptions!$D$14*MIN(1,$B56/Assumptions!$D$15) | E56: =$C56*$D56 | F56: =$C56*Assumptions!$C$32 | G56: =Assumptions!$D$20*MIN(1,$B56/Assumptions!$D$15) | H56: =(($E56*Assumptions!$D$16+$F56*Assumptions!$D$17+$G56*Assumptions!$D$18+($E56*Assumptions!$C$33)*Assumptions!$D$19)*12*(1+Assumptions!$C$35)^($B56-1))+(Assumptions!$D$21*MIN(1,$B56/Assumptions!$C$31))+((MAX(0,($E56+$F56+$G56)-(($E55+$F55+$G55)))+(($E55+$F55+$G55))*Assumptions!$D$22)*Assumptions!$C$34) | I56: =($E56+$F56+$G56)*Assumptions!$C$36*(1+Assumptions!$D$24)^($B56-1)+Assumptions!$C$37*(Construction_Budget!$E$15*Assumptions!$D$25)*(1+Assumptions!$D$24)^($B56-1)+Assumptions!$C$38*Assumptions!$C$39*(1+Assumptions!$D$24)^($B56-1)+Assumptions!$C$40*$H56+Assumptions!$C$41*$H56+Assumptions!$D$23*((($E56*Assumptions!$D$16+$F56*Assumptions!$D$17+$G56*Assumptions!$D$18+($E56*Assumptions!$C$33)*Assumptions!$D$19)*12*(1+Assumptions!$C$35)^($B56-1))+(Assumptions!$D$21*MIN(1,$B56/Assumptions!$C$31))) | J56: =(Construction_Budget!$E$8*Assumptions!$D$25)/Assumptions!$C$42*(1+Assumptions!$D$24)^($B56-1) | K56: =$H56-$I56-$J56 | L56: =CHOOSE(Assumptions!$C$9,Assumptions!$C$49*(1+Assumptions!$C$50)^($B56-1),Assumptions!$C$51*$H56,Assumptions!$C$52*MAX(0,$K56),Assumptions!$C$53+Assumptions!$C$54*$H56,IF($B56<=Assumptions!$C$55,0,Assumptions!$C$56*(1+Assumptions!$C$57)^($B56-Assumptions!$C$55-1))) | M56: =$K56-$L56 | N56: =$H56-$I56-$J56
... B73: 30 | C73: =Assumptions!$C$30*MIN(1,$B73/Assumptions!$C$31) | D73: =Assumptions!$D$14*MIN(1,$B73/Assumptions!$D$15) | E73: =$C73*$D73 | F73: =$C73*Assumptions!$C$32 | G73: =Assumptions!$D$20*MIN(1,$B73/Assumptions!$D$15) | H73: =(($E73*Assumptions!$D$16+$F73*Assumptions!$D$17+$G73*Assumptions!$D$18+($E73*Assumptions!$C$33)*Assumptions!$D$19)*12*(1+Assumptions!$C$35)^($B73-1))+(Assumptions!$D$21*MIN(1,$B73/Assumptions!$C$31))+((MAX(0,($E73+$F73+$G73)-(($E72+$F72+$G72)))+(($E72+$F72+$G72))*Assumptions!$D$22)*Assumptions!$C$34) | I73: =($E73+$F73+$G73)*Assumptions!$C$36*(1+Assumptions!$D$24)^($B73-1)+Assumptions!$C$37*(Construction_Budget!$E$15*Assumptions!$D$25)*(1+Assumptions!$D$24)^($B73-1)+Assumptions!$C$38*Assumptions!$C$39*(1+Assumptions!$D$24)^($B73-1)+Assumptions!$C$40*$H73+Assumptions!$C$41*$H73+Assumptions!$D$23*((($E73*Assumptions!$D$16+$F73*Assumptions!$D$17+$G73*Assumptions!$D$18+($E73*Assumptions!$C$33)*Assumptions!$D$19)*12*(1+Assumptions!$C$35)^($B73-1))+(Assumptions!$D$21*MIN(1,$B73/Assumptions!$C$31))) | J73: =(Construction_Budget!$E$8*Assumptions!$D$25)/Assumptions!$C$42*(1+Assumptions!$D$24)^($B73-1) | K73: =$H73-$I73-$J73 | L73: =CHOOSE(Assumptions!$C$9,Assumptions!$C$49*(1+Assumptions!$C$50)^($B73-1),Assumptions!$C$51*$H73,Assumptions!$C$52*MAX(0,$K73),Assumptions!$C$53+Assumptions!$C$54*$H73,IF($B73<=Assumptions!$C$55,0,Assumptions!$C$56*(1+Assumptions!$C$57)^($B73-Assumptions!$C$55-1))) | M73: =$K73-$L73 | N73: =$H73-$I73-$J73
B76: HIGH CASE
B77: Year | C77: Homes | D77: TakeRate | E77: Res Subs | F77: Bus Subs | G77: Ent Subs | H77: Gross Rev | I77: Opex | J77: Capital | K77: Adj Op CF | L77: Tribal Pmt | M77: RIVR Net | N77: Proj Net
B78: 0 | D78: 0 | E78: 0 | F78: 0 | G78: 0 | H78: 0 | I78: 0 | J78: 0 | K78: 0 | L78: 0 | M78: =-Assumptions!$C$45 | N78: =-((Construction_Budget!$E$15*Assumptions!$E$25)+Assumptions!$C$45)
B79: 1 | C79: =Assumptions!$C$30*MIN(1,$B79/Assumptions!$C$31) | D79: =Assumptions!$E$14*MIN(1,$B79/Assumptions!$E$15) | E79: =$C79*$D79 | F79: =$C79*Assumptions!$C$32 | G79: =Assumptions!$E$20*MIN(1,$B79/Assumptions!$E$15) | H79: =(($E79*Assumptions!$E$16+$F79*Assumptions!$E$17+$G79*Assumptions!$E$18+($E79*Assumptions!$C$33)*Assumptions!$E$19)*12*(1+Assumptions!$C$35)^($B79-1))+(Assumptions!$E$21*MIN(1,$B79/Assumptions!$C$31))+((MAX(0,($E79+$F79+$G79)-(0))+(0)*Assumptions!$E$22)*Assumptions!$C$34) | I79: =($E79+$F79+$G79)*Assumptions!$C$36*(1+Assumptions!$E$24)^($B79-1)+Assumptions!$C$37*(Construction_Budget!$E$15*Assumptions!$E$25)*(1+Assumptions!$E$24)^($B79-1)+Assumptions!$C$38*Assumptions!$C$39*(1+Assumptions!$E$24)^($B79-1)+Assumptions!$C$40*$H79+Assumptions!$C$41*$H79+Assumptions!$E$23*((($E79*Assumptions!$E$16+$F79*Assumptions!$E$17+$G79*Assumptions!$E$18+($E79*Assumptions!$C$33)*Assumptions!$E$19)*12*(1+Assumptions!$C$35)^($B79-1))+(Assumptions!$E$21*MIN(1,$B79/Assumptions!$C$31))) | J79: =(Construction_Budget!$E$8*Assumptions!$E$25)/Assumptions!$C$42*(1+Assumptions!$E$24)^($B79-1) | K79: =$H79-$I79-$J79 | L79: =CHOOSE(Assumptions!$C$9,Assumptions!$C$49*(1+Assumptions!$C$50)^($B79-1),Assumptions!$C$51*$H79,Assumptions!$C$52*MAX(0,$K79),Assumptions!$C$53+Assumptions!$C$54*$H79,IF($B79<=Assumptions!$C$55,0,Assumptions!$C$56*(1+Assumptions!$C$57)^($B79-Assumptions!$C$55-1))) | M79: =$K79-$L79 | N79: =$H79-$I79-$J79
B80: 2 | C80: =Assumptions!$C$30*MIN(1,$B80/Assumptions!$C$31) | D80: =Assumptions!$E$14*MIN(1,$B80/Assumptions!$E$15) | E80: =$C80*$D80 | F80: =$C80*Assumptions!$C$32 | G80: =Assumptions!$E$20*MIN(1,$B80/Assumptions!$E$15) | H80: =(($E80*Assumptions!$E$16+$F80*Assumptions!$E$17+$G80*Assumptions!$E$18+($E80*Assumptions!$C$33)*Assumptions!$E$19)*12*(1+Assumptions!$C$35)^($B80-1))+(Assumptions!$E$21*MIN(1,$B80/Assumptions!$C$31))+((MAX(0,($E80+$F80+$G80)-(($E79+$F79+$G79)))+(($E79+$F79+$G79))*Assumptions!$E$22)*Assumptions!$C$34) | I80: =($E80+$F80+$G80)*Assumptions!$C$36*(1+Assumptions!$E$24)^($B80-1)+Assumptions!$C$37*(Construction_Budget!$E$15*Assumptions!$E$25)*(1+Assumptions!$E$24)^($B80-1)+Assumptions!$C$38*Assumptions!$C$39*(1+Assumptions!$E$24)^($B80-1)+Assumptions!$C$40*$H80+Assumptions!$C$41*$H80+Assumptions!$E$23*((($E80*Assumptions!$E$16+$F80*Assumptions!$E$17+$G80*Assumptions!$E$18+($E80*Assumptions!$C$33)*Assumptions!$E$19)*12*(1+Assumptions!$C$35)^($B80-1))+(Assumptions!$E$21*MIN(1,$B80/Assumptions!$C$31))) | J80: =(Construction_Budget!$E$8*Assumptions!$E$25)/Assumptions!$C$42*(1+Assumptions!$E$24)^($B80-1) | K80: =$H80-$I80-$J80 | L80: =CHOOSE(Assumptions!$C$9,Assumptions!$C$49*(1+Assumptions!$C$50)^($B80-1),Assumptions!$C$51*$H80,Assumptions!$C$52*MAX(0,$K80),Assumptions!$C$53+Assumptions!$C$54*$H80,IF($B80<=Assumptions!$C$55,0,Assumptions!$C$56*(1+Assumptions!$C$57)^($B80-Assumptions!$C$55-1))) | M80: =$K80-$L80 | N80: =$H80-$I80-$J80
B81: 3 | C81: =Assumptions!$C$30*MIN(1,$B81/Assumptions!$C$31) | D81: =Assumptions!$E$14*MIN(1,$B81/Assumptions!$E$15) | E81: =$C81*$D81 | F81: =$C81*Assumptions!$C$32 | G81: =Assumptions!$E$20*MIN(1,$B81/Assumptions!$E$15) | H81: =(($E81*Assumptions!$E$16+$F81*Assumptions!$E$17+$G81*Assumptions!$E$18+($E81*Assumptions!$C$33)*Assumptions!$E$19)*12*(1+Assumptions!$C$35)^($B81-1))+(Assumptions!$E$21*MIN(1,$B81/Assumptions!$C$31))+((MAX(0,($E81+$F81+$G81)-(($E80+$F80+$G80)))+(($E80+$F80+$G80))*Assumptions!$E$22)*Assumptions!$C$34) | I81: =($E81+$F81+$G81)*Assumptions!$C$36*(1+Assumptions!$E$24)^($B81-1)+Assumptions!$C$37*(Construction_Budget!$E$15*Assumptions!$E$25)*(1+Assumptions!$E$24)^($B81-1)+Assumptions!$C$38*Assumptions!$C$39*(1+Assumptions!$E$24)^($B81-1)+Assumptions!$C$40*$H81+Assumptions!$C$41*$H81+Assumptions!$E$23*((($E81*Assumptions!$E$16+$F81*Assumptions!$E$17+$G81*Assumptions!$E$18+($E81*Assumptions!$C$33)*Assumptions!$E$19)*12*(1+Assumptions!$C$35)^($B81-1))+(Assumptions!$E$21*MIN(1,$B81/Assumptions!$C$31))) | J81: =(Construction_Budget!$E$8*Assumptions!$E$25)/Assumptions!$C$42*(1+Assumptions!$E$24)^($B81-1) | K81: =$H81-$I81-$J81 | L81: =CHOOSE(Assumptions!$C$9,Assumptions!$C$49*(1+Assumptions!$C$50)^($B81-1),Assumptions!$C$51*$H81,Assumptions!$C$52*MAX(0,$K81),Assumptions!$C$53+Assumptions!$C$54*$H81,IF($B81<=Assumptions!$C$55,0,Assumptions!$C$56*(1+Assumptions!$C$57)^($B81-Assumptions!$C$55-1))) | M81: =$K81-$L81 | N81: =$H81-$I81-$J81
B82: 4 | C82: =Assumptions!$C$30*MIN(1,$B82/Assumptions!$C$31) | D82: =Assumptions!$E$14*MIN(1,$B82/Assumptions!$E$15) | E82: =$C82*$D82 | F82: =$C82*Assumptions!$C$32 | G82: =Assumptions!$E$20*MIN(1,$B82/Assumptions!$E$15) | H82: =(($E82*Assumptions!$E$16+$F82*Assumptions!$E$17+$G82*Assumptions!$E$18+($E82*Assumptions!$C$33)*Assumptions!$E$19)*12*(1+Assumptions!$C$35)^($B82-1))+(Assumptions!$E$21*MIN(1,$B82/Assumptions!$C$31))+((MAX(0,($E82+$F82+$G82)-(($E81+$F81+$G81)))+(($E81+$F81+$G81))*Assumptions!$E$22)*Assumptions!$C$34) | I82: =($E82+$F82+$G82)*Assumptions!$C$36*(1+Assumptions!$E$24)^($B82-1)+Assumptions!$C$37*(Construction_Budget!$E$15*Assumptions!$E$25)*(1+Assumptions!$E$24)^($B82-1)+Assumptions!$C$38*Assumptions!$C$39*(1+Assumptions!$E$24)^($B82-1)+Assumptions!$C$40*$H82+Assumptions!$C$41*$H82+Assumptions!$E$23*((($E82*Assumptions!$E$16+$F82*Assumptions!$E$17+$G82*Assumptions!$E$18+($E82*Assumptions!$C$33)*Assumptions!$E$19)*12*(1+Assumptions!$C$35)^($B82-1))+(Assumptions!$E$21*MIN(1,$B82/Assumptions!$C$31))) | J82: =(Construction_Budget!$E$8*Assumptions!$E$25)/Assumptions!$C$42*(1+Assumptions!$E$24)^($B82-1) | K82: =$H82-$I82-$J82 | L82: =CHOOSE(Assumptions!$C$9,Assumptions!$C$49*(1+Assumptions!$C$50)^($B82-1),Assumptions!$C$51*$H82,Assumptions!$C$52*MAX(0,$K82),Assumptions!$C$53+Assumptions!$C$54*$H82,IF($B82<=Assumptions!$C$55,0,Assumptions!$C$56*(1+Assumptions!$C$57)^($B82-Assumptions!$C$55-1))) | M82: =$K82-$L82 | N82: =$H82-$I82-$J82
B83: 5 | C83: =Assumptions!$C$30*MIN(1,$B83/Assumptions!$C$31) | D83: =Assumptions!$E$14*MIN(1,$B83/Assumptions!$E$15) | E83: =$C83*$D83 | F83: =$C83*Assumptions!$C$32 | G83: =Assumptions!$E$20*MIN(1,$B83/Assumptions!$E$15) | H83: =(($E83*Assumptions!$E$16+$F83*Assumptions!$E$17+$G83*Assumptions!$E$18+($E83*Assumptions!$C$33)*Assumptions!$E$19)*12*(1+Assumptions!$C$35)^($B83-1))+(Assumptions!$E$21*MIN(1,$B83/Assumptions!$C$31))+((MAX(0,($E83+$F83+$G83)-(($E82+$F82+$G82)))+(($E82+$F82+$G82))*Assumptions!$E$22)*Assumptions!$C$34) | I83: =($E83+$F83+$G83)*Assumptions!$C$36*(1+Assumptions!$E$24)^($B83-1)+Assumptions!$C$37*(Construction_Budget!$E$15*Assumptions!$E$25)*(1+Assumptions!$E$24)^($B83-1)+Assumptions!$C$38*Assumptions!$C$39*(1+Assumptions!$E$24)^($B83-1)+Assumptions!$C$40*$H83+Assumptions!$C$41*$H83+Assumptions!$E$23*((($E83*Assumptions!$E$16+$F83*Assumptions!$E$17+$G83*Assumptions!$E$18+($E83*Assumptions!$C$33)*Assumptions!$E$19)*12*(1+Assumptions!$C$35)^($B83-1))+(Assumptions!$E$21*MIN(1,$B83/Assumptions!$C$31))) | J83: =(Construction_Budget!$E$8*Assumptions!$E$25)/Assumptions!$C$42*(1+Assumptions!$E$24)^($B83-1) | K83: =$H83-$I83-$J83 | L83: =CHOOSE(Assumptions!$C$9,Assumptions!$C$49*(1+Assumptions!$C$50)^($B83-1),Assumptions!$C$51*$H83,Assumptions!$C$52*MAX(0,$K83),Assumptions!$C$53+Assumptions!$C$54*$H83,IF($B83<=Assumptions!$C$55,0,Assumptions!$C$56*(1+Assumptions!$C$57)^($B83-Assumptions!$C$55-1))) | M83: =$K83-$L83 | N83: =$H83-$I83-$J83
B84: 6 | C84: =Assumptions!$C$30*MIN(1,$B84/Assumptions!$C$31) | D84: =Assumptions!$E$14*MIN(1,$B84/Assumptions!$E$15) | E84: =$C84*$D84 | F84: =$C84*Assumptions!$C$32 | G84: =Assumptions!$E$20*MIN(1,$B84/Assumptions!$E$15) | H84: =(($E84*Assumptions!$E$16+$F84*Assumptions!$E$17+$G84*Assumptions!$E$18+($E84*Assumptions!$C$33)*Assumptions!$E$19)*12*(1+Assumptions!$C$35)^($B84-1))+(Assumptions!$E$21*MIN(1,$B84/Assumptions!$C$31))+((MAX(0,($E84+$F84+$G84)-(($E83+$F83+$G83)))+(($E83+$F83+$G83))*Assumptions!$E$22)*Assumptions!$C$34) | I84: =($E84+$F84+$G84)*Assumptions!$C$36*(1+Assumptions!$E$24)^($B84-1)+Assumptions!$C$37*(Construction_Budget!$E$15*Assumptions!$E$25)*(1+Assumptions!$E$24)^($B84-1)+Assumptions!$C$38*Assumptions!$C$39*(1+Assumptions!$E$24)^($B84-1)+Assumptions!$C$40*$H84+Assumptions!$C$41*$H84+Assumptions!$E$23*((($E84*Assumptions!$E$16+$F84*Assumptions!$E$17+$G84*Assumptions!$E$18+($E84*Assumptions!$C$33)*Assumptions!$E$19)*12*(1+Assumptions!$C$35)^($B84-1))+(Assumptions!$E$21*MIN(1,$B84/Assumptions!$C$31))) | J84: =(Construction_Budget!$E$8*Assumptions!$E$25)/Assumptions!$C$42*(1+Assumptions!$E$24)^($B84-1) | K84: =$H84-$I84-$J84 | L84: =CHOOSE(Assumptions!$C$9,Assumptions!$C$49*(1+Assumptions!$C$50)^($B84-1),Assumptions!$C$51*$H84,Assumptions!$C$52*MAX(0,$K84),Assumptions!$C$53+Assumptions!$C$54*$H84,IF($B84<=Assumptions!$C$55,0,Assumptions!$C$56*(1+Assumptions!$C$57)^($B84-Assumptions!$C$55-1))) | M84: =$K84-$L84 | N84: =$H84-$I84-$J84
B85: 7 | C85: =Assumptions!$C$30*MIN(1,$B85/Assumptions!$C$31) | D85: =Assumptions!$E$14*MIN(1,$B85/Assumptions!$E$15) | E85: =$C85*$D85 | F85: =$C85*Assumptions!$C$32 | G85: =Assumptions!$E$20*MIN(1,$B85/Assumptions!$E$15) | H85: =(($E85*Assumptions!$E$16+$F85*Assumptions!$E$17+$G85*Assumptions!$E$18+($E85*Assumptions!$C$33)*Assumptions!$E$19)*12*(1+Assumptions!$C$35)^($B85-1))+(Assumptions!$E$21*MIN(1,$B85/Assumptions!$C$31))+((MAX(0,($E85+$F85+$G85)-(($E84+$F84+$G84)))+(($E84+$F84+$G84))*Assumptions!$E$22)*Assumptions!$C$34) | I85: =($E85+$F85+$G85)*Assumptions!$C$36*(1+Assumptions!$E$24)^($B85-1)+Assumptions!$C$37*(Construction_Budget!$E$15*Assumptions!$E$25)*(1+Assumptions!$E$24)^($B85-1)+Assumptions!$C$38*Assumptions!$C$39*(1+Assumptions!$E$24)^($B85-1)+Assumptions!$C$40*$H85+Assumptions!$C$41*$H85+Assumptions!$E$23*((($E85*Assumptions!$E$16+$F85*Assumptions!$E$17+$G85*Assumptions!$E$18+($E85*Assumptions!$C$33)*Assumptions!$E$19)*12*(1+Assumptions!$C$35)^($B85-1))+(Assumptions!$E$21*MIN(1,$B85/Assumptions!$C$31))) | J85: =(Construction_Budget!$E$8*Assumptions!$E$25)/Assumptions!$C$42*(1+Assumptions!$E$24)^($B85-1) | K85: =$H85-$I85-$J85 | L85: =CHOOSE(Assumptions!$C$9,Assumptions!$C$49*(1+Assumptions!$C$50)^($B85-1),Assumptions!$C$51*$H85,Assumptions!$C$52*MAX(0,$K85),Assumptions!$C$53+Assumptions!$C$54*$H85,IF($B85<=Assumptions!$C$55,0,Assumptions!$C$56*(1+Assumptions!$C$57)^($B85-Assumptions!$C$55-1))) | M85: =$K85-$L85 | N85: =$H85-$I85-$J85
B86: 8 | C86: =Assumptions!$C$30*MIN(1,$B86/Assumptions!$C$31) | D86: =Assumptions!$E$14*MIN(1,$B86/Assumptions!$E$15) | E86: =$C86*$D86 | F86: =$C86*Assumptions!$C$32 | G86: =Assumptions!$E$20*MIN(1,$B86/Assumptions!$E$15) | H86: =(($E86*Assumptions!$E$16+$F86*Assumptions!$E$17+$G86*Assumptions!$E$18+($E86*Assumptions!$C$33)*Assumptions!$E$19)*12*(1+Assumptions!$C$35)^($B86-1))+(Assumptions!$E$21*MIN(1,$B86/Assumptions!$C$31))+((MAX(0,($E86+$F86+$G86)-(($E85+$F85+$G85)))+(($E85+$F85+$G85))*Assumptions!$E$22)*Assumptions!$C$34) | I86: =($E86+$F86+$G86)*Assumptions!$C$36*(1+Assumptions!$E$24)^($B86-1)+Assumptions!$C$37*(Construction_Budget!$E$15*Assumptions!$E$25)*(1+Assumptions!$E$24)^($B86-1)+Assumptions!$C$38*Assumptions!$C$39*(1+Assumptions!$E$24)^($B86-1)+Assumptions!$C$40*$H86+Assumptions!$C$41*$H86+Assumptions!$E$23*((($E86*Assumptions!$E$16+$F86*Assumptions!$E$17+$G86*Assumptions!$E$18+($E86*Assumptions!$C$33)*Assumptions!$E$19)*12*(1+Assumptions!$C$35)^($B86-1))+(Assumptions!$E$21*MIN(1,$B86/Assumptions!$C$31))) | J86: =(Construction_Budget!$E$8*Assumptions!$E$25)/Assumptions!$C$42*(1+Assumptions!$E$24)^($B86-1) | K86: =$H86-$I86-$J86 | L86: =CHOOSE(Assumptions!$C$9,Assumptions!$C$49*(1+Assumptions!$C$50)^($B86-1),Assumptions!$C$51*$H86,Assumptions!$C$52*MAX(0,$K86),Assumptions!$C$53+Assumptions!$C$54*$H86,IF($B86<=Assumptions!$C$55,0,Assumptions!$C$56*(1+Assumptions!$C$57)^($B86-Assumptions!$C$55-1))) | M86: =$K86-$L86 | N86: =$H86-$I86-$J86
B87: 9 | C87: =Assumptions!$C$30*MIN(1,$B87/Assumptions!$C$31) | D87: =Assumptions!$E$14*MIN(1,$B87/Assumptions!$E$15) | E87: =$C87*$D87 | F87: =$C87*Assumptions!$C$32 | G87: =Assumptions!$E$20*MIN(1,$B87/Assumptions!$E$15) | H87: =(($E87*Assumptions!$E$16+$F87*Assumptions!$E$17+$G87*Assumptions!$E$18+($E87*Assumptions!$C$33)*Assumptions!$E$19)*12*(1+Assumptions!$C$35)^($B87-1))+(Assumptions!$E$21*MIN(1,$B87/Assumptions!$C$31))+((MAX(0,($E87+$F87+$G87)-(($E86+$F86+$G86)))+(($E86+$F86+$G86))*Assumptions!$E$22)*Assumptions!$C$34) | I87: =($E87+$F87+$G87)*Assumptions!$C$36*(1+Assumptions!$E$24)^($B87-1)+Assumptions!$C$37*(Construction_Budget!$E$15*Assumptions!$E$25)*(1+Assumptions!$E$24)^($B87-1)+Assumptions!$C$38*Assumptions!$C$39*(1+Assumptions!$E$24)^($B87-1)+Assumptions!$C$40*$H87+Assumptions!$C$41*$H87+Assumptions!$E$23*((($E87*Assumptions!$E$16+$F87*Assumptions!$E$17+$G87*Assumptions!$E$18+($E87*Assumptions!$C$33)*Assumptions!$E$19)*12*(1+Assumptions!$C$35)^($B87-1))+(Assumptions!$E$21*MIN(1,$B87/Assumptions!$C$31))) | J87: =(Construction_Budget!$E$8*Assumptions!$E$25)/Assumptions!$C$42*(1+Assumptions!$E$24)^($B87-1) | K87: =$H87-$I87-$J87 | L87: =CHOOSE(Assumptions!$C$9,Assumptions!$C$49*(1+Assumptions!$C$50)^($B87-1),Assumptions!$C$51*$H87,Assumptions!$C$52*MAX(0,$K87),Assumptions!$C$53+Assumptions!$C$54*$H87,IF($B87<=Assumptions!$C$55,0,Assumptions!$C$56*(1+Assumptions!$C$57)^($B87-Assumptions!$C$55-1))) | M87: =$K87-$L87 | N87: =$H87-$I87-$J87
B88: 10 | C88: =Assumptions!$C$30*MIN(1,$B88/Assumptions!$C$31) | D88: =Assumptions!$E$14*MIN(1,$B88/Assumptions!$E$15) | E88: =$C88*$D88 | F88: =$C88*Assumptions!$C$32 | G88: =Assumptions!$E$20*MIN(1,$B88/Assumptions!$E$15) | H88: =(($E88*Assumptions!$E$16+$F88*Assumptions!$E$17+$G88*Assumptions!$E$18+($E88*Assumptions!$C$33)*Assumptions!$E$19)*12*(1+Assumptions!$C$35)^($B88-1))+(Assumptions!$E$21*MIN(1,$B88/Assumptions!$C$31))+((MAX(0,($E88+$F88+$G88)-(($E87+$F87+$G87)))+(($E87+$F87+$G87))*Assumptions!$E$22)*Assumptions!$C$34) | I88: =($E88+$F88+$G88)*Assumptions!$C$36*(1+Assumptions!$E$24)^($B88-1)+Assumptions!$C$37*(Construction_Budget!$E$15*Assumptions!$E$25)*(1+Assumptions!$E$24)^($B88-1)+Assumptions!$C$38*Assumptions!$C$39*(1+Assumptions!$E$24)^($B88-1)+Assumptions!$C$40*$H88+Assumptions!$C$41*$H88+Assumptions!$E$23*((($E88*Assumptions!$E$16+$F88*Assumptions!$E$17+$G88*Assumptions!$E$18+($E88*Assumptions!$C$33)*Assumptions!$E$19)*12*(1+Assumptions!$C$35)^($B88-1))+(Assumptions!$E$21*MIN(1,$B88/Assumptions!$C$31))) | J88: =(Construction_Budget!$E$8*Assumptions!$E$25)/Assumptions!$C$42*(1+Assumptions!$E$24)^($B88-1) | K88: =$H88-$I88-$J88 | L88: =CHOOSE(Assumptions!$C$9,Assumptions!$C$49*(1+Assumptions!$C$50)^($B88-1),Assumptions!$C$51*$H88,Assumptions!$C$52*MAX(0,$K88),Assumptions!$C$53+Assumptions!$C$54*$H88,IF($B88<=Assumptions!$C$55,0,Assumptions!$C$56*(1+Assumptions!$C$57)^($B88-Assumptions!$C$55-1))) | M88: =$K88-$L88 | N88: =$H88-$I88-$J88
B89: 11 | C89: =Assumptions!$C$30*MIN(1,$B89/Assumptions!$C$31) | D89: =Assumptions!$E$14*MIN(1,$B89/Assumptions!$E$15) | E89: =$C89*$D89 | F89: =$C89*Assumptions!$C$32 | G89: =Assumptions!$E$20*MIN(1,$B89/Assumptions!$E$15) | H89: =(($E89*Assumptions!$E$16+$F89*Assumptions!$E$17+$G89*Assumptions!$E$18+($E89*Assumptions!$C$33)*Assumptions!$E$19)*12*(1+Assumptions!$C$35)^($B89-1))+(Assumptions!$E$21*MIN(1,$B89/Assumptions!$C$31))+((MAX(0,($E89+$F89+$G89)-(($E88+$F88+$G88)))+(($E88+$F88+$G88))*Assumptions!$E$22)*Assumptions!$C$34) | I89: =($E89+$F89+$G89)*Assumptions!$C$36*(1+Assumptions!$E$24)^($B89-1)+Assumptions!$C$37*(Construction_Budget!$E$15*Assumptions!$E$25)*(1+Assumptions!$E$24)^($B89-1)+Assumptions!$C$38*Assumptions!$C$39*(1+Assumptions!$E$24)^($B89-1)+Assumptions!$C$40*$H89+Assumptions!$C$41*$H89+Assumptions!$E$23*((($E89*Assumptions!$E$16+$F89*Assumptions!$E$17+$G89*Assumptions!$E$18+($E89*Assumptions!$C$33)*Assumptions!$E$19)*12*(1+Assumptions!$C$35)^($B89-1))+(Assumptions!$E$21*MIN(1,$B89/Assumptions!$C$31))) | J89: =(Construction_Budget!$E$8*Assumptions!$E$25)/Assumptions!$C$42*(1+Assumptions!$E$24)^($B89-1) | K89: =$H89-$I89-$J89 | L89: =CHOOSE(Assumptions!$C$9,Assumptions!$C$49*(1+Assumptions!$C$50)^($B89-1),Assumptions!$C$51*$H89,Assumptions!$C$52*MAX(0,$K89),Assumptions!$C$53+Assumptions!$C$54*$H89,IF($B89<=Assumptions!$C$55,0,Assumptions!$C$56*(1+Assumptions!$C$57)^($B89-Assumptions!$C$55-1))) | M89: =$K89-$L89 | N89: =$H89-$I89-$J89
B90: 12 | C90: =Assumptions!$C$30*MIN(1,$B90/Assumptions!$C$31) | D90: =Assumptions!$E$14*MIN(1,$B90/Assumptions!$E$15) | E90: =$C90*$D90 | F90: =$C90*Assumptions!$C$32 | G90: =Assumptions!$E$20*MIN(1,$B90/Assumptions!$E$15) | H90: =(($E90*Assumptions!$E$16+$F90*Assumptions!$E$17+$G90*Assumptions!$E$18+($E90*Assumptions!$C$33)*Assumptions!$E$19)*12*(1+Assumptions!$C$35)^($B90-1))+(Assumptions!$E$21*MIN(1,$B90/Assumptions!$C$31))+((MAX(0,($E90+$F90+$G90)-(($E89+$F89+$G89)))+(($E89+$F89+$G89))*Assumptions!$E$22)*Assumptions!$C$34) | I90: =($E90+$F90+$G90)*Assumptions!$C$36*(1+Assumptions!$E$24)^($B90-1)+Assumptions!$C$37*(Construction_Budget!$E$15*Assumptions!$E$25)*(1+Assumptions!$E$24)^($B90-1)+Assumptions!$C$38*Assumptions!$C$39*(1+Assumptions!$E$24)^($B90-1)+Assumptions!$C$40*$H90+Assumptions!$C$41*$H90+Assumptions!$E$23*((($E90*Assumptions!$E$16+$F90*Assumptions!$E$17+$G90*Assumptions!$E$18+($E90*Assumptions!$C$33)*Assumptions!$E$19)*12*(1+Assumptions!$C$35)^($B90-1))+(Assumptions!$E$21*MIN(1,$B90/Assumptions!$C$31))) | J90: =(Construction_Budget!$E$8*Assumptions!$E$25)/Assumptions!$C$42*(1+Assumptions!$E$24)^($B90-1) | K90: =$H90-$I90-$J90 | L90: =CHOOSE(Assumptions!$C$9,Assumptions!$C$49*(1+Assumptions!$C$50)^($B90-1),Assumptions!$C$51*$H90,Assumptions!$C$52*MAX(0,$K90),Assumptions!$C$53+Assumptions!$C$54*$H90,IF($B90<=Assumptions!$C$55,0,Assumptions!$C$56*(1+Assumptions!$C$57)^($B90-Assumptions!$C$55-1))) | M90: =$K90-$L90 | N90: =$H90-$I90-$J90
B91: 13 | C91: =Assumptions!$C$30*MIN(1,$B91/Assumptions!$C$31) | D91: =Assumptions!$E$14*MIN(1,$B91/Assumptions!$E$15) | E91: =$C91*$D91 | F91: =$C91*Assumptions!$C$32 | G91: =Assumptions!$E$20*MIN(1,$B91/Assumptions!$E$15) | H91: =(($E91*Assumptions!$E$16+$F91*Assumptions!$E$17+$G91*Assumptions!$E$18+($E91*Assumptions!$C$33)*Assumptions!$E$19)*12*(1+Assumptions!$C$35)^($B91-1))+(Assumptions!$E$21*MIN(1,$B91/Assumptions!$C$31))+((MAX(0,($E91+$F91+$G91)-(($E90+$F90+$G90)))+(($E90+$F90+$G90))*Assumptions!$E$22)*Assumptions!$C$34) | I91: =($E91+$F91+$G91)*Assumptions!$C$36*(1+Assumptions!$E$24)^($B91-1)+Assumptions!$C$37*(Construction_Budget!$E$15*Assumptions!$E$25)*(1+Assumptions!$E$24)^($B91-1)+Assumptions!$C$38*Assumptions!$C$39*(1+Assumptions!$E$24)^($B91-1)+Assumptions!$C$40*$H91+Assumptions!$C$41*$H91+Assumptions!$E$23*((($E91*Assumptions!$E$16+$F91*Assumptions!$E$17+$G91*Assumptions!$E$18+($E91*Assumptions!$C$33)*Assumptions!$E$19)*12*(1+Assumptions!$C$35)^($B91-1))+(Assumptions!$E$21*MIN(1,$B91/Assumptions!$C$31))) | J91: =(Construction_Budget!$E$8*Assumptions!$E$25)/Assumptions!$C$42*(1+Assumptions!$E$24)^($B91-1) | K91: =$H91-$I91-$J91 | L91: =CHOOSE(Assumptions!$C$9,Assumptions!$C$49*(1+Assumptions!$C$50)^($B91-1),Assumptions!$C$51*$H91,Assumptions!$C$52*MAX(0,$K91),Assumptions!$C$53+Assumptions!$C$54*$H91,IF($B91<=Assumptions!$C$55,0,Assumptions!$C$56*(1+Assumptions!$C$57)^($B91-Assumptions!$C$55-1))) | M91: =$K91-$L91 | N91: =$H91-$I91-$J91
... B108: 30 | C108: =Assumptions!$C$30*MIN(1,$B108/Assumptions!$C$31) | D108: =Assumptions!$E$14*MIN(1,$B108/Assumptions!$E$15) | E108: =$C108*$D108 | F108: =$C108*Assumptions!$C$32 | G108: =Assumptions!$E$20*MIN(1,$B108/Assumptions!$E$15) | H108: =(($E108*Assumptions!$E$16+$F108*Assumptions!$E$17+$G108*Assumptions!$E$18+($E108*Assumptions!$C$33)*Assumptions!$E$19)*12*(1+Assumptions!$C$35)^($B108-1))+(Assumptions!$E$21*MIN(1,$B108/Assumptions!$C$31))+((MAX(0,($E108+$F108+$G108)-(($E107+$F107+$G107)))+(($E107+$F107+$G107))*Assumptions!$E$22)*Assumptions!$C$34) | I108: =($E108+$F108+$G108)*Assumptions!$C$36*(1+Assumptions!$E$24)^($B108-1)+Assumptions!$C$37*(Construction_Budget!$E$15*Assumptions!$E$25)*(1+Assumptions!$E$24)^($B108-1)+Assumptions!$C$38*Assumptions!$C$39*(1+Assumptions!$E$24)^($B108-1)+Assumptions!$C$40*$H108+Assumptions!$C$41*$H108+Assumptions!$E$23*((($E108*Assumptions!$E$16+$F108*Assumptions!$E$17+$G108*Assumptions!$E$18+($E108*Assumptions!$C$33)*Assumptions!$E$19)*12*(1+Assumptions!$C$35)^($B108-1))+(Assumptions!$E$21*MIN(1,$B108/Assumptions!$C$31))) | J108: =(Construction_Budget!$E$8*Assumptions!$E$25)/Assumptions!$C$42*(1+Assumptions!$E$24)^($B108-1) | K108: =$H108-$I108-$J108 | L108: =CHOOSE(Assumptions!$C$9,Assumptions!$C$49*(1+Assumptions!$C$50)^($B108-1),Assumptions!$C$51*$H108,Assumptions!$C$52*MAX(0,$K108),Assumptions!$C$53+Assumptions!$C$54*$H108,IF($B108<=Assumptions!$C$55,0,Assumptions!$C$56*(1+Assumptions!$C$57)^($B108-Assumptions!$C$55-1))) | M108: =$K108-$L108 | N108: =$H108-$I108-$J108
B111: Reconciliation (valid when Scenario switch = 2 / Base):
B112: CHECK: Base-case Y30 gross revenue reconciles to live Revenue sheet (set Scenario=2) | F112: =IF(OR(Assumptions!$C$7<>2,ABS($H73-Revenue!$I$36)<50),"PASS","FAIL")

Sheet NPV_IRR
A1: NPV & IRR — 3 Cases x 3 IRU Terms
A2: DRAFT FOR DISCUSSION – SUBJECT TO LEGAL, GRANT AND FINANCIAL REVIEW
A3: Computed from Case_Engine parallel cash flows. NPV discounts Years 1..T; IRR over Years 0..T. Discount rate & option follow Assumptions.
B6: LOW CASE
B7: Metric \ IRU Term | C7: 20-yr | D7: 25-yr | E7: 30-yr
B8: RIVR NPV (Low case) | C8: =Case_Engine!$M$8+NPV(Assumptions!$C$44,Case_Engine!$M$9:$M$28) | D8: =Case_Engine!$M$8+NPV(Assumptions!$C$44,Case_Engine!$M$9:$M$33) | E8: =Case_Engine!$M$8+NPV(Assumptions!$C$44,Case_Engine!$M$9:$M$38)
B9: RIVR IRR (Low case) | C9: =IFERROR(IRR(Case_Engine!$M$8:$M$28),"n/m") | D9: =IFERROR(IRR(Case_Engine!$M$8:$M$33),"n/m") | E9: =IFERROR(IRR(Case_Engine!$M$8:$M$38),"n/m")
B10: Project NPV (Low case) | C10: =Case_Engine!$N$8+NPV(Assumptions!$C$44,Case_Engine!$N$9:$N$28) | D10: =Case_Engine!$N$8+NPV(Assumptions!$C$44,Case_Engine!$N$9:$N$33) | E10: =Case_Engine!$N$8+NPV(Assumptions!$C$44,Case_Engine!$N$9:$N$38)
B11: Project IRR (Low case) | C11: =IFERROR(IRR(Case_Engine!$N$8:$N$28),"n/m") | D11: =IFERROR(IRR(Case_Engine!$N$8:$N$33),"n/m") | E11: =IFERROR(IRR(Case_Engine!$N$8:$N$38),"n/m")
B13: BASE CASE
B14: Metric \ IRU Term | C14: 20-yr | D14: 25-yr | E14: 30-yr
B15: RIVR NPV (Base case) | C15: =Case_Engine!$M$43+NPV(Assumptions!$C$44,Case_Engine!$M$44:$M$63) | D15: =Case_Engine!$M$43+NPV(Assumptions!$C$44,Case_Engine!$M$44:$M$68) | E15: =Case_Engine!$M$43+NPV(Assumptions!$C$44,Case_Engine!$M$44:$M$73)
B16: RIVR IRR (Base case) | C16: =IFERROR(IRR(Case_Engine!$M$43:$M$63),"n/m") | D16: =IFERROR(IRR(Case_Engine!$M$43:$M$68),"n/m") | E16: =IFERROR(IRR(Case_Engine!$M$43:$M$73),"n/m")
B17: Project NPV (Base case) | C17: =Case_Engine!$N$43+NPV(Assumptions!$C$44,Case_Engine!$N$44:$N$63) | D17: =Case_Engine!$N$43+NPV(Assumptions!$C$44,Case_Engine!$N$44:$N$68) | E17: =Case_Engine!$N$43+NPV(Assumptions!$C$44,Case_Engine!$N$44:$N$73)
B18: Project IRR (Base case) | C18: =IFERROR(IRR(Case_Engine!$N$43:$N$63),"n/m") | D18: =IFERROR(IRR(Case_Engine!$N$43:$N$68),"n/m") | E18: =IFERROR(IRR(Case_Engine!$N$43:$N$73),"n/m")
B20: HIGH CASE
B21: Metric \ IRU Term | C21: 20-yr | D21: 25-yr | E21: 30-yr
B22: RIVR NPV (High case) | C22: =Case_Engine!$M$78+NPV(Assumptions!$C$44,Case_Engine!$M$79:$M$98) | D22: =Case_Engine!$M$78+NPV(Assumptions!$C$44,Case_Engine!$M$79:$M$103) | E22: =Case_Engine!$M$78+NPV(Assumptions!$C$44,Case_Engine!$M$79:$M$108)
B23: RIVR IRR (High case) | C23: =IFERROR(IRR(Case_Engine!$M$78:$M$98),"n/m") | D23: =IFERROR(IRR(Case_Engine!$M$78:$M$103),"n/m") | E23: =IFERROR(IRR(Case_Engine!$M$78:$M$108),"n/m")
B24: Project NPV (High case) | C24: =Case_Engine!$N$78+NPV(Assumptions!$C$44,Case_Engine!$N$79:$N$98) | D24: =Case_Engine!$N$78+NPV(Assumptions!$C$44,Case_Engine!$N$79:$N$103) | E24: =Case_Engine!$N$78+NPV(Assumptions!$C$44,Case_Engine!$N$79:$N$108)
B25: Project IRR (High case) | C25: =IFERROR(IRR(Case_Engine!$N$78:$N$98),"n/m") | D25: =IFERROR(IRR(Case_Engine!$N$78:$N$103),"n/m") | E25: =IFERROR(IRR(Case_Engine!$N$78:$N$108),"n/m")

Sheet Sensitivity
A1: SENSITIVITY — Take Rate & ARPU vs RIVR NPV
A2: DRAFT FOR DISCUSSION – SUBJECT TO LEGAL, GRANT AND FINANCIAL REVIEW
A3: Formula-driven. Recomputes a simplified 30-yr RIVR NPV as take rate and residential ARPU flex around the active case.
B5: Two-way sensitivity: Residential ARPU (rows) x Terminal Take Rate (cols)
B6: Simplified steady-state RIVR NPV proxy ($). Holds other active drivers fixed; for directional read only.
B8: ARPU \ Take | C8: 0.3 | D8: 0.375 | E8: 0.45 | F8: 0.525 | G8: 0.6
B9: 55 | C9: =((Assumptions!$C$30*C8*$B9*12)-((Assumptions!$C$40+Assumptions!$C$41)*(Assumptions!$C$30*C8*$B9*12)+Assumptions!$C$30*C8*Assumptions!$C$36)-(Assumptions!$C$51*(Assumptions!$C$30*C8*$B9*12)))*((1-(1+Assumptions!$C$44)^-30)/Assumptions!$C$44) | D9: =((Assumptions!$C$30*D8*$B9*12)-((Assumptions!$C$40+Assumptions!$C$41)*(Assumptions!$C$30*D8*$B9*12)+Assumptions!$C$30*D8*Assumptions!$C$36)-(Assumptions!$C$51*(Assumptions!$C$30*D8*$B9*12)))*((1-(1+Assumptions!$C$44)^-30)/Assumptions!$C$44) | E9: =((Assumptions!$C$30*E8*$B9*12)-((Assumptions!$C$40+Assumptions!$C$41)*(Assumptions!$C$30*E8*$B9*12)+Assumptions!$C$30*E8*Assumptions!$C$36)-(Assumptions!$C$51*(Assumptions!$C$30*E8*$B9*12)))*((1-(1+Assumptions!$C$44)^-30)/Assumptions!$C$44) | F9: =((Assumptions!$C$30*F8*$B9*12)-((Assumptions!$C$40+Assumptions!$C$41)*(Assumptions!$C$30*F8*$B9*12)+Assumptions!$C$30*F8*Assumptions!$C$36)-(Assumptions!$C$51*(Assumptions!$C$30*F8*$B9*12)))*((1-(1+Assumptions!$C$44)^-30)/Assumptions!$C$44) | G9: =((Assumptions!$C$30*G8*$B9*12)-((Assumptions!$C$40+Assumptions!$C$41)*(Assumptions!$C$30*G8*$B9*12)+Assumptions!$C$30*G8*Assumptions!$C$36)-(Assumptions!$C$51*(Assumptions!$C$30*G8*$B9*12)))*((1-(1+Assumptions!$C$44)^-30)/Assumptions!$C$44)
B10: 65 | C10: =((Assumptions!$C$30*C8*$B10*12)-((Assumptions!$C$40+Assumptions!$C$41)*(Assumptions!$C$30*C8*$B10*12)+Assumptions!$C$30*C8*Assumptions!$C$36)-(Assumptions!$C$51*(Assumptions!$C$30*C8*$B10*12)))*((1-(1+Assumptions!$C$44)^-30)/Assumptions!$C$44) | D10: =((Assumptions!$C$30*D8*$B10*12)-((Assumptions!$C$40+Assumptions!$C$41)*(Assumptions!$C$30*D8*$B10*12)+Assumptions!$C$30*D8*Assumptions!$C$36)-(Assumptions!$C$51*(Assumptions!$C$30*D8*$B10*12)))*((1-(1+Assumptions!$C$44)^-30)/Assumptions!$C$44) | E10: =((Assumptions!$C$30*E8*$B10*12)-((Assumptions!$C$40+Assumptions!$C$41)*(Assumptions!$C$30*E8*$B10*12)+Assumptions!$C$30*E8*Assumptions!$C$36)-(Assumptions!$C$51*(Assumptions!$C$30*E8*$B10*12)))*((1-(1+Assumptions!$C$44)^-30)/Assumptions!$C$44) | F10: =((Assumptions!$C$30*F8*$B10*12)-((Assumptions!$C$40+Assumptions!$C$41)*(Assumptions!$C$30*F8*$B10*12)+Assumptions!$C$30*F8*Assumptions!$C$36)-(Assumptions!$C$51*(Assumptions!$C$30*F8*$B10*12)))*((1-(1+Assumptions!$C$44)^-30)/Assumptions!$C$44) | G10: =((Assumptions!$C$30*G8*$B10*12)-((Assumptions!$C$40+Assumptions!$C$41)*(Assumptions!$C$30*G8*$B10*12)+Assumptions!$C$30*G8*Assumptions!$C$36)-(Assumptions!$C$51*(Assumptions!$C$30*G8*$B10*12)))*((1-(1+Assumptions!$C$44)^-30)/Assumptions!$C$44)
B11: 75 | C11: =((Assumptions!$C$30*C8*$B11*12)-((Assumptions!$C$40+Assumptions!$C$41)*(Assumptions!$C$30*C8*$B11*12)+Assumptions!$C$30*C8*Assumptions!$C$36)-(Assumptions!$C$51*(Assumptions!$C$30*C8*$B11*12)))*((1-(1+Assumptions!$C$44)^-30)/Assumptions!$C$44) | D11: =((Assumptions!$C$30*D8*$B11*12)-((Assumptions!$C$40+Assumptions!$C$41)*(Assumptions!$C$30*D8*$B11*12)+Assumptions!$C$30*D8*Assumptions!$C$36)-(Assumptions!$C$51*(Assumptions!$C$30*D8*$B11*12)))*((1-(1+Assumptions!$C$44)^-30)/Assumptions!$C$44) | E11: =((Assumptions!$C$30*E8*$B11*12)-((Assumptions!$C$40+Assumptions!$C$41)*(Assumptions!$C$30*E8*$B11*12)+Assumptions!$C$30*E8*Assumptions!$C$36)-(Assumptions!$C$51*(Assumptions!$C$30*E8*$B11*12)))*((1-(1+Assumptions!$C$44)^-30)/Assumptions!$C$44) | F11: =((Assumptions!$C$30*F8*$B11*12)-((Assumptions!$C$40+Assumptions!$C$41)*(Assumptions!$C$30*F8*$B11*12)+Assumptions!$C$30*F8*Assumptions!$C$36)-(Assumptions!$C$51*(Assumptions!$C$30*F8*$B11*12)))*((1-(1+Assumptions!$C$44)^-30)/Assumptions!$C$44) | G11: =((Assumptions!$C$30*G8*$B11*12)-((Assumptions!$C$40+Assumptions!$C$41)*(Assumptions!$C$30*G8*$B11*12)+Assumptions!$C$30*G8*Assumptions!$C$36)-(Assumptions!$C$51*(Assumptions!$C$30*G8*$B11*12)))*((1-(1+Assumptions!$C$44)^-30)/Assumptions!$C$44)
B12: 85 | C12: =((Assumptions!$C$30*C8*$B12*12)-((Assumptions!$C$40+Assumptions!$C$41)*(Assumptions!$C$30*C8*$B12*12)+Assumptions!$C$30*C8*Assumptions!$C$36)-(Assumptions!$C$51*(Assumptions!$C$30*C8*$B12*12)))*((1-(1+Assumptions!$C$44)^-30)/Assumptions!$C$44) | D12: =((Assumptions!$C$30*D8*$B12*12)-((Assumptions!$C$40+Assumptions!$C$41)*(Assumptions!$C$30*D8*$B12*12)+Assumptions!$C$30*D8*Assumptions!$C$36)-(Assumptions!$C$51*(Assumptions!$C$30*D8*$B12*12)))*((1-(1+Assumptions!$C$44)^-30)/Assumptions!$C$44) | E12: =((Assumptions!$C$30*E8*$B12*12)-((Assumptions!$C$40+Assumptions!$C$41)*(Assumptions!$C$30*E8*$B12*12)+Assumptions!$C$30*E8*Assumptions!$C$36)-(Assumptions!$C$51*(Assumptions!$C$30*E8*$B12*12)))*((1-(1+Assumptions!$C$44)^-30)/Assumptions!$C$44) | F12: =((Assumptions!$C$30*F8*$B12*12)-((Assumptions!$C$40+Assumptions!$C$41)*(Assumptions!$C$30*F8*$B12*12)+Assumptions!$C$30*F8*Assumptions!$C$36)-(Assumptions!$C$51*(Assumptions!$C$30*F8*$B12*12)))*((1-(1+Assumptions!$C$44)^-30)/Assumptions!$C$44) | G12: =((Assumptions!$C$30*G8*$B12*12)-((Assumptions!$C$40+Assumptions!$C$41)*(Assumptions!$C$30*G8*$B12*12)+Assumptions!$C$30*G8*Assumptions!$C$36)-(Assumptions!$C$51*(Assumptions!$C$30*G8*$B12*12)))*((1-(1+Assumptions!$C$44)^-30)/Assumptions!$C$44)
B13: 95 | C13: =((Assumptions!$C$30*C8*$B13*12)-((Assumptions!$C$40+Assumptions!$C$41)*(Assumptions!$C$30*C8*$B13*12)+Assumptions!$C$30*C8*Assumptions!$C$36)-(Assumptions!$C$51*(Assumptions!$C$30*C8*$B13*12)))*((1-(1+Assumptions!$C$44)^-30)/Assumptions!$C$44) | D13: =((Assumptions!$C$30*D8*$B13*12)-((Assumptions!$C$40+Assumptions!$C$41)*(Assumptions!$C$30*D8*$B13*12)+Assumptions!$C$30*D8*Assumptions!$C$36)-(Assumptions!$C$51*(Assumptions!$C$30*D8*$B13*12)))*((1-(1+Assumptions!$C$44)^-30)/Assumptions!$C$44) | E13: =((Assumptions!$C$30*E8*$B13*12)-((Assumptions!$C$40+Assumptions!$C$41)*(Assumptions!$C$30*E8*$B13*12)+Assumptions!$C$30*E8*Assumptions!$C$36)-(Assumptions!$C$51*(Assumptions!$C$30*E8*$B13*12)))*((1-(1+Assumptions!$C$44)^-30)/Assumptions!$C$44) | F13: =((Assumptions!$C$30*F8*$B13*12)-((Assumptions!$C$40+Assumptions!$C$41)*(Assumptions!$C$30*F8*$B13*12)+Assumptions!$C$30*F8*Assumptions!$C$36)-(Assumptions!$C$51*(Assumptions!$C$30*F8*$B13*12)))*((1-(1+Assumptions!$C$44)^-30)/Assumptions!$C$44) | G13: =((Assumptions!$C$30*G8*$B13*12)-((Assumptions!$C$40+Assumptions!$C$41)*(Assumptions!$C$30*G8*$B13*12)+Assumptions!$C$30*G8*Assumptions!$C$36)-(Assumptions!$C$51*(Assumptions!$C$30*G8*$B13*12)))*((1-(1+Assumptions!$C$44)^-30)/Assumptions!$C$44)
B15: One-way sensitivity: Terminal Take Rate vs RIVR NPV proxy (residential ARPU = active case)
B16: Terminal Take Rate | C16: RIVR NPV proxy ($)
B17: 0.3 | C17: =((Assumptions!$C$30*$B17*Assumptions!$F$16*12)-((Assumptions!$C$40+Assumptions!$C$41)*(Assumptions!$C$30*$B17*Assumptions!$F$16*12)+Assumptions!$C$30*$B17*Assumptions!$C$36)-(Assumptions!$C$51*(Assumptions!$C$30*$B17*Assumptions!$F$16*12)))*((1-(1+Assumptions!$C$44)^-30)/Assumptions!$C$44)
B18: 0.375 | C18: =((Assumptions!$C$30*$B18*Assumptions!$F$16*12)-((Assumptions!$C$40+Assumptions!$C$41)*(Assumptions!$C$30*$B18*Assumptions!$F$16*12)+Assumptions!$C$30*$B18*Assumptions!$C$36)-(Assumptions!$C$51*(Assumptions!$C$30*$B18*Assumptions!$F$16*12)))*((1-(1+Assumptions!$C$44)^-30)/Assumptions!$C$44)
B19: 0.45 | C19: =((Assumptions!$C$30*$B19*Assumptions!$F$16*12)-((Assumptions!$C$40+Assumptions!$C$41)*(Assumptions!$C$30*$B19*Assumptions!$F$16*12)+Assumptions!$C$30*$B19*Assumptions!$C$36)-(Assumptions!$C$51*(Assumptions!$C$30*$B19*Assumptions!$F$16*12)))*((1-(1+Assumptions!$C$44)^-30)/Assumptions!$C$44)
B20: 0.525 | C20: =((Assumptions!$C$30*$B20*Assumptions!$F$16*12)-((Assumptions!$C$40+Assumptions!$C$41)*(Assumptions!$C$30*$B20*Assumptions!$F$16*12)+Assumptions!$C$30*$B20*Assumptions!$C$36)-(Assumptions!$C$51*(Assumptions!$C$30*$B20*Assumptions!$F$16*12)))*((1-(1+Assumptions!$C$44)^-30)/Assumptions!$C$44)
B21: 0.6 | C21: =((Assumptions!$C$30*$B21*Assumptions!$F$16*12)-((Assumptions!$C$40+Assumptions!$C$41)*(Assumptions!$C$30*$B21*Assumptions!$F$16*12)+Assumptions!$C$30*$B21*Assumptions!$C$36)-(Assumptions!$C$51*(Assumptions!$C$30*$B21*Assumptions!$F$16*12)))*((1-(1+Assumptions!$C$44)^-30)/Assumptions!$C$44)

Sheet Scenario_Comparison
A1: SCENARIO COMPARISON — Low / Base / High
A2: DRAFT FOR DISCUSSION – SUBJECT TO LEGAL, GRANT AND FINANCIAL REVIEW
A3: Key outputs from Case_Engine (30-yr horizon, active option). Independent of the Scenario switch.
B5: Output Metric | C5: Low | D5: Base | E5: High
B6: Year-30 gross revenue | C6: =Case_Engine!$H$38 | D6: =Case_Engine!$H$73 | E6: =Case_Engine!$H$108
B7: Cumulative Tribal payments (30 yr) | C7: =SUM(Case_Engine!$L$8:$L$38) | D7: =SUM(Case_Engine!$L$43:$L$73) | E7: =SUM(Case_Engine!$L$78:$L$108)
B8: RIVR NPV (30-yr term) | C8: =Case_Engine!$M$8+NPV(Assumptions!$C$44,Case_Engine!$M$9:$M$38) | D8: =Case_Engine!$M$43+NPV(Assumptions!$C$44,Case_Engine!$M$44:$M$73) | E8: =Case_Engine!$M$78+NPV(Assumptions!$C$44,Case_Engine!$M$79:$M$108)
B9: RIVR IRR (30-yr term) | C9: =IFERROR(IRR(Case_Engine!$M$8:$M$38),"n/m") | D9: =IFERROR(IRR(Case_Engine!$M$43:$M$73),"n/m") | E9: =IFERROR(IRR(Case_Engine!$M$78:$M$108),"n/m")
B10: Project NPV (30-yr term) | C10: =Case_Engine!$N$8+NPV(Assumptions!$C$44,Case_Engine!$N$9:$N$38) | D10: =Case_Engine!$N$43+NPV(Assumptions!$C$44,Case_Engine!$N$44:$N$73) | E10: =Case_Engine!$N$78+NPV(Assumptions!$C$44,Case_Engine!$N$79:$N$108)
